Workbook
Name PRV_ALL: [1]List!$H$4:$H$929
Name table: #REF!
Name TableML: #REF!
Name กระบี่: province!$B$2:$B$51
Name กรุงเทพมหานคร: province!$A$2:$A$51
Name กาญจนบุรี: province!$C$2:$C$51
Name กาฬสินธุ์: province!$D$2:$D$51
Name กำแพงเพชร: province!$E$2:$E$51
Name ขอนแก่น: province!$F$2:$F$51
Name จังหวัด: #REF!
Name จังหวัด2: #REF!
Name จันทบุรี: province!$G$2:$G$51
Name ฉะเชิงเทรา: province!$H$2:$H$51
Name ชลบุรี: province!$I$2:$I$51
Name ชัยนาท: province!$J$2:$J$51
Name ชัยภูมิ: province!$K$2:$K$51
Name ชุมพร: province!$L$2:$L$51
Name เชียงราย: province!$M$2:$M$51
Name เชียงใหม่: province!$N$2:$N$51
Name ตรัง: province!$O$2:$O$51
Name ตราด: province!$P$2:$P$51
Name ตาก: province!$Q$2:$Q$51
Name นครนายก: province!$R$2:$R$51
Name นครปฐม: province!$S$2:$S$51
Name นครพนม: province!$T$2:$T$51
Name นครราชสีมา: province!$U$2:$U$51
Name นครศรีธรรมราช: province!$V$2:$V$51
Name นครสวรรค์: province!$W$2:$W$51
Name นนทบุรี: province!$X$2:$X$51
Name นราธิวาส: province!$Y$2:$Y$51
Name น่าน: province!$Z$2:$Z$51
Name บุรีรัมย์: province!$AA$2:$AA$51
Name ปทุมธานี: province!$AB$2:$AB$51
Name ประจวบคีรีขันธ์: province!$AC$2:$AC$51
Name ปราจีนบุรี: province!$AD$2:$AD$51
Name ปัตตานี: province!$AE$2:$AE$51
Name พระนครศรีอยุธยา: province!$AF$2:$AF$51
Name พะเยา: province!$AN$2:$AN$51
Name พังงา: province!$AG$2:$AG$51
Name พัทลุง: province!$AH$2:$AH$51
Name พิจิตร: province!$AI$2:$AI$51
Name พิษณุโลก: province!$AJ$2:$AJ$51
Name เพชรบุรี: province!$AK$2:$AK$51
Name เพชรบูรณ์: province!$AL$2:$AL$51
Name แพร่: province!$AM$2:$AM$51
Name ภูเก็ต: province!$AO$2:$AO$51
Name มหาสารคาม: province!$AP$2:$AP$51
Name มุกดาหาร: province!$AQ$2:$AQ$51
Name เมืองสุรินทร์: #REF!
Name เมืองหนองคาย: #REF!
Name แม่ฮ่องสอน: province!$AR$2:$AR$51
Name ยโสธร: province!$AT$2:$AT$51
Name ยะลา: province!$AS$2:$AS$51
Name ร้อยเอ็ด: province!$AU$2:$AU$51
Name ระนอง: province!$AV$2:$AV$51
Name ระยอง: province!$AW$2:$AW$51
Name ราชบุรี: province!$AX$2:$AX$51
Name ลพบุรี: province!$AY$2:$AY$51
Name ลำปาง: province!$AZ$2:$AZ$51
Name ลำพูน: province!$BA$2:$BA$51

Sheet 1.ลดดอกเบี้ย
B1: ตารางพิจารณาขอลดดอกเบี้ย | F1: v.202608.01 | H1: To be hide
B3: ชื่อลูกค้า | J3: 3Y | K3: 5Y | AV3: * กรอกเฉพาะช่องสีเหลือง
B4: เลข App. | I4: =IFERROR(AD10,0) -> 0 | J4: =SUM(U20:W20) -> 0 | K4: =SUM(U20:Y20) -> 0
B5: อัตราดอกเบี้ย MRR
C7: HL | E7: MP/PP | I7: HL Facility | O7: MP/PP Facility | U7: All Facility | AV7: หมายเหตุ
B8: วงเงิน | I8: =I11/$C$8 -> #DIV/0! | J8: =J11/$C$8 -> #DIV/0! | K8: =K11/$C$8 -> #DIV/0! | L8: =L11/$C$8 -> #DIV/0! | M8: =M11/$C$8 -> #DIV/0! | O8: =O11/$F$8 -> #DIV/0! | P8: =P11/$F$8 -> #DIV/0! | Q8: =Q11/$F$8 -> #DIV/0! | R8: =R11/$F$8 -> #DIV/0! | S8: =S11/$F$8 -> #DIV/0! | AA8: Cumulative | AD8: Check Value | AV8: - ปีที่ 1 ไม่สามารถขอต่ำกว่า 1.44%
B9: ผ่อนชำระ (ปี) | I9: Y1 | J9: Y2 | K9: Y3 | L9: Y4 | M9: Y5 | O9: Y1 | P9: Y2 | Q9: Y3 | R9: Y4 | S9: Y5 | U9: Y1 | V9: Y2 | W9: Y3 | X9: Y4 | Y9: Y5 | AA9: For 3Y | AB9: For 5Y | AD9: =IF(C17="Lock 5Y",AB20,AA20) -> 0 | AV9: - ดอกเบี้ยที่ขออนุมัติ ต้องไม่มีปีไหน
B10: ดอกเบี้ย (เฉลี่ย 3 ปี) | C10: =IFERROR(AVERAGE(D11:D13),"") | E10: =IFERROR(AVERAGE(F11:F13),"") | H10: ENR | I10: =C8*95% -> 0 | J10: =C8*90% -> 0 | K10: =C8*85% -> 0 | L10: =C8*80% -> 0 | M10: =C8*75% -> 0 | O10: =E8*95% -> 0 | P10: =E8*90% -> 0 | Q10: =E8*85% -> 0 | R10: =E8*80% -> 0 | S10: =E8*75% -> 0 | U10: =I10+O10 -> 0 | V10: =J10+P10 -> 0 | W10: =K10+Q10 -> 0 | X10: =L10+R10 -> 0 | Y10: =M10+S10 -> 0 | AD10: =IF(C17="Lock 5Y",1+AB22,1+AA22) -> #DIV/0! | AV10: มากกว่าดอกเบี้ยตามแคมเปญ
B11: ปีที่ 1 | H11: ANR | I11: =AVERAGE(C8,I10) -> 0 | J11: =AVERAGE(I10:J10) -> 0 | K11: =AVERAGE(J10:K10) -> 0 | L11: =AVERAGE(K10:L10) -> 0 | M11: =AVERAGE(L10:M10) -> 0 | O11: =AVERAGE(F8,O10) -> 0 | P11: =AVERAGE(O10:P10) -> 0 | Q11: =AVERAGE(P10:Q10) -> 0 | R11: =AVERAGE(Q10:R10) -> 0 | S11: =AVERAGE(R10:S10) -> 0 | U11: =I11+O11 -> 0 | V11: =J11+P11 -> 0 | W11: =K11+Q11 -> 0 | X11: =L11+R11 -> 0 | Y11: =M11+S11 -> 0 | AV11: อาจจะส่งผลให้ ค่างวดไม่พอตัด
B12: ปีที่ 2 | AE12: ="<"&TEXT(AD18,"0.00%")&" of trigger point" -> #N/A | AH12: >> cannot submit Pricing Deviation | AV12: ชำระยอดดอกเบี้ย
B13: ปีที่ 3 | H13: Revenue | I13: =IFERROR(I11*$D$11,0) -> 0 | J13: =IFERROR(J11*$D$12,0) -> 0 | K13: =IFERROR(K11*$D$13,0) -> 0 | L13: =IFERROR(L11*$D$32,0) -> 0 | M13: =IFERROR(M11*$D$33,0) -> 0 | O13: =O11*$F$11 -> 0 | P13: =P11*$F$12 -> 0 | Q13: =Q11*$F$13 -> 0 | R13: =R11*$F$32 -> 0 | S13: =S11*$F$33 -> 0 | U13: =I13+O13 -> 0 | V13: =J13+P13 -> 0 | W13: =K13+Q13 -> 0 | X13: =L13+R13 -> 0 | Y13: =M13+S13 -> 0 | AA13: =SUM(U13:W13) -> 0 | AB13: =SUM(U13:Y13) -> 0 | AE13: =">="&TEXT(AD18,"0.00%")&" of trigger point" -> #N/A | AH13: >> can submit Pricing Deviation | AV13: - ตารางคำนวณนี้เพื่อเป็นแนวทาง
B14: ปีที่ 4 | H14: COF | I14: =I11*$D$34 -> 0 | J14: =J11*$D$34 -> 0 | K14: =K11*$D$34 -> 0 | L14: =L11*$D$34 -> 0 | M14: =M11*$D$34 -> 0 | O14: =O11*$F$34 -> 0 | P14: =P11*$F$34 -> 0 | Q14: =Q11*$F$34 -> 0 | R14: =R11*$F$34 -> 0 | S14: =S11*$F$34 -> 0 | U14: =I14+O14 -> 0 | V14: =J14+P14 -> 0 | W14: =K14+Q14 -> 0 | X14: =L14+R14 -> 0 | Y14: =M14+S14 -> 0 | AA14: =SUM(U14:W14) -> 0 | AB14: =SUM(U14:Y14) -> 0 | AV14: การนำเสนอดอกเบี้ยเท่านั้น
B15: เบี้ยประกัน MRTA/MLTA | H15: NII | I15: =I13-I14 -> 0 | J15: =J13-J14 -> 0 | K15: =K13-K14 -> 0 | L15: =L13-L14 -> 0 | M15: =M13-M14 -> 0 | O15: =O13-O14 -> 0 | P15: =P13-P14 -> 0 | Q15: =Q13-Q14 -> 0 | R15: =R13-R14 -> 0 | S15: =S13-S14 -> 0 | U15: =I15+O15 -> 0 | V15: =J15+P15 -> 0 | W15: =K15+Q15 -> 0 | X15: =L15+R15 -> 0 | Y15: =M15+S15 -> 0 | AA15: =SUM(U15:W15) -> 0 | AB15: =SUM(U15:Y15) -> 0 | AV15: Product ขอสงวนสิทธิ์ในการ
B16: ยกเว้นค่าจดจำนอง | H16: NOII | I16: =$C$15*34% -> 0 | O16: =$E$15*34% -> 0 | U16: =I16+O16 -> 0 | V16: =J16+P16 -> 0 | W16: =K16+Q16 -> 0 | X16: =L16+R16 -> 0 | Y16: =M16+S16 -> 0 | AA16: =SUM(U16:W16) -> 0 | AB16: =SUM(U16:Y16) -> 0 | AV16: พิจารณาอนุมัติดอกเบี้ยที่เสนอขอ
B17: ผูกสัญญา | H17: CC | I17: =IFERROR(VLOOKUP($C$20,pam!$U$5:$AE$9,pam!$V$12,FALSE)*I11*-1,0) -> 0 | J17: =IFERROR(VLOOKUP($C$20,pam!$U$5:$AE$9,pam!$V$12,FALSE)*J11*-1,0) -> 0 | K17: =IFERROR(VLOOKUP($C$20,pam!$U$5:$AE$9,pam!$V$12,FALSE)*K11*-1,0) -> 0 | L17: =IFERROR(VLOOKUP($C$20,pam!$U$5:$AE$9,pam!$V$12,FALSE)*L11*-1,0) -> 0 | M17: =IFERROR(VLOOKUP($C$20,pam!$U$5:$AE$9,pam!$V$12,FALSE)*M11*-1,0) -> 0 | O17: =O11*$P$28 -> 0 | P17: =P11*$P$28 -> 0 | Q17: =Q11*$P$28 -> 0 | R17: =R11*$P$28 -> 0 | S17: =S11*$P$28 -> 0 | U17: =I17+O17 -> 0 | V17: =J17+P17 -> 0 | W17: =K17+Q17 -> 0 | X17: =L17+R17 -> 0 | Y17: =M17+S17 -> 0 | AA17: =SUM(U17:W17) -> 0 | AB17: =SUM(U17:Y17) -> 0 | AD17: 0 | AE17: =AD18-0.01% -> #N/A | AF17: ไม่สามารถนำเสนอลดดอกเบี้ยได้
B18: แคมเปญ | H18: Commission | I18: =I28*C8 -> 0 | O18: =P29*E8 -> 0 | U18: =I18+O18 -> 0 | V18: =J18+P18 -> 0 | W18: =K18+Q18 -> 0 | X18: =L18+R18 -> 0 | Y18: =M18+S18 -> 0 | AA18: =SUM(U18:W18) -> 0 | AB18: =SUM(U18:Y18) -> 0 | AD18: =AD34 -> #N/A | AF18: สามารถนำเสนอลดดอกเบี้ยได้
B19: รายได้ | H19: OPEX | I19: =IF(IF($C$16="Yes",C8*1%,0)>=100000,100000,IF($C$16="Yes",C8*1%,0)) -> 0 | O19: =IF(IF($E$16="Yes",E8*1%,0)>=100000,100000,IF($E$16="Yes",E8*1%,0)) -> 0 | U19: =I19+O19 -> 0 | V19: =J19+P19 -> 0 | W19: =K19+Q19 -> 0 | X19: =L19+R19 -> 0 | Y19: =M19+S19 -> 0 | AA19: =SUM(U19:W19) -> 0 | AB19: =SUM(U19:Y19) -> 0
B20: Score Grade | H20: PBT | I20: =IFERROR(I15+I16-I17-I18-I19,0) -> 0 | J20: =IFERROR(J15+J16-J17-J18-J19,0) -> 0 | K20: =IFERROR(K15+K16-K17-K18-K19,0) -> 0 | L20: =IFERROR(L15+L16-L17-L18-L19,0) -> 0 | M20: =IFERROR(M15+M16-M17-M18-M19,0) -> 0 | O20: =IFERROR(O15+O16-O17-O18-O19,0) -> 0 | P20: =IFERROR(P15+P16-P17-P18-P19,0) -> 0 | Q20: =IFERROR(Q15+Q16-Q17-Q18-Q19,0) -> 0 | R20: =IFERROR(R15+R16-R17-R18-R19,0) -> 0 | S20: =IFERROR(S15+S16-S17-S18-S19,0) -> 0 | U20: =I20+O20 -> 0 | V20: =J20+P20 -> 0 | W20: =K20+Q20 -> 0 | X20: =L20+R20 -> 0 | Y20: =M20+S20 -> 0 | AA20: =SUM(U20:W20) -> 0 | AB20: =SUM(U20:Y20) -> 0 | AG20: BaseLine | AH20: Lock 3Y | AI20: Lock 5Y
B21: %LTV (รวม MRTA/MLTA) | AD21: Cap Min Rate | AE21: 0.02 | AG21: 1 | AH21: 2 | AI21: 3
B22: หลักประกัน | AA22: =ROUNDDOWN((AA20/3)/AVERAGE($U$11:W$11),4) -> #DIV/0! | AB22: =ROUNDDOWN((AB20/3)/AVERAGE($U$11:Y$11),4) -> #DIV/0! | AD22: Cap Max Loss | AE22: -30000 | AG22: No Ins | AH22: 0.026 | AI22: 0.024
B23: ที่ตั้งหลักประกัน | AG23: Ins | AH23: 0.025 | AI23: 0.023
B24: ช่องทางขาย | AB24: Base line | AD24: 1 | AG24: Index | AH24: =HLOOKUP(C17,AG20:AI21,2,FALSE) -> #N/A
B25: Consent 1.1
B26: ประเภทการผ่อน | E26: เท่ากันทุกเดือน | AB26: Loan Size | AD26: =VLOOKUP(SUM(C8:F8),AF27:AH31,3,TRUE) -> 0.0005 | AF26: LoanSize | AI26: Income | AL26: Campaign | AN26: Collateral | AP26: Location | AR26: LTV
B27: ค่างวดผ่อนชำระ | AB27: Income | AD27: =VLOOKUP(SUM(C19:F19),AI27:AK33,3,TRUE) -> 0.002 | AF27: 0 | AG27: 3000000 | AH27: 0.0005 | AI27: 0 | AJ27: 30000 | AK27: 0.002 | AL27: BT | AM27: 0.0002 | AN27: SingleHouse | AO27: 0.0001 | AP27: BKK&VIC | AQ27: 0.0001 | AR27: 0 | AS27: 0.4999 | AT27: 0.0001
B28: ปีที่ 1 | C28: =IF(C26="เท่ากันทุกเดือน",'Straight-HL'!C10,'Step-HL'!L10) -> 0 | E28: =IF(E26="เท่ากันทุกเดือน",'Straight-MP'!C10,'Step-MP'!L10) -> 0 | H28: %Comm (after var) | I28: =IFERROR(I29*I30,0) -> 0 | O28: MP %CC | P28: 0.011 | AB28: Campaign | AD28: =VLOOKUP(IF(C18<>"",C18,E18),AL27:AM34,2,FALSE) -> #N/A | AF28: =AG27+1 -> 3000001 | AG28: 5000000 | AH28: 0.0003 | AI28: =AJ27+1 -> 30001 | AJ28: 50000 | AK28: 0.0015 | AL28: Focus | AM28: 0.0005 | AN28: TwinHouse | AO28: 0.0001 | AP28: North | AQ28: 0.0005 | AR28: =AS27+0.01% -> 0.5 | AS28: 0.5999 | AT28: 0.0001
B29: ปีที่ 2 | C29: =IF(C26="เท่ากันทุกเดือน",'Straight-HL'!C10,'Step-HL'!L11) -> 0 | E29: =IF(E26="เท่ากันทุกเดือน",'Straight-MP'!C10,'Step-MP'!L11) -> 0 | H29: %Comm | I29: 0.005 | O29: MP %Comm | P29: =IF(E24="DSA",0.5%,0.3%) -> 0.003 | AB29: Collateral | AD29: =VLOOKUP(IF(C22<>"",C22,E22),AN27:AO32,2,FALSE) -> #N/A | AF29: =AG28+1 -> 5000001 | AG29: 7500000 | AH29: 0.0001 | AI29: =AJ28+1 -> 50001 | AJ29: 75000 | AK29: 0.001 | AL29: 2ndHand | AM29: 0.0005 | AN29: TownHouse | AO29: 0.0001 | AP29: NorthEast | AQ29: 0.0005 | AR29: =AS28+0.01% -> 0.6 | AS29: 0.7999 | AT29: 0.0001
B30: ปีที่ 3 | C30: =IF(C26="เท่ากันทุกเดือน",'Straight-HL'!C10,'Step-HL'!L12) -> 0 | E30: =IF(E26="เท่ากันทุกเดือน",'Straight-MP'!C10,'Step-MP'!L12) -> 0 | H30: com variance | I30: =IFERROR(IF((C15/C8)<2%,VLOOKUP(C18,pam!C:E,2,FALSE),VLOOKUP(C18,pam!C:E,3,FALSE)),0) -> 0 | AB30: Location | AD30: =VLOOKUP(IF(C23<>"",C23,E23),AP27:AQ32,2,FALSE) -> #N/A | AF30: =AG29+1 -> 7500001 | AG30: 10000000 | AH30: 0 | AI30: =AJ29+1 -> 75001 | AJ30: 100000 | AK30: 0.0005 | AL30: RBP | AM30: 0.001 | AN30: Condo | AO30: 0.0005 | AP30: East | AQ30: 0.0005 | AR30: =AS29+0.01% -> 0.8 | AS30: 0.8999 | AT30: 0.0001
B31: ปีที่ 4 เป็นต้นไป | C31: =IF(C26="เท่ากันทุกเดือน",'Straight-HL'!C10,'Step-HL'!L13) -> 0 | E31: =IF(E26="เท่ากันทุกเดือน",'Straight-MP'!C10,'Step-MP'!L13) -> 0 | AB31: LTV | AD31: =VLOOKUP(C21,AR27:AT33,3,TRUE) -> 0.0001 | AF31: =AG30+1 -> 10000001 | AH31: 0 | AI31: =AJ30+1 -> 100001 | AJ31: 200000 | AK31: 0.0001 | AL31: PVL | AM31: 0.001 | AN31: ShopHouse | AO31: 0.001 | AP31: South | AQ31: 0.0005 | AR31: =AS30+0.01% -> 0.9 | AS31: 1 | AT31: 0.0001
B32: Retention ปีที่ 4 | D32: =IF(C16="Yes",C10+0.2%,C10) | F32: =IFERROR(E10+0.2%,0) -> 0 | AB32: Total add-on | AD32: =SUM(AD26:AD31) -> #N/A | AI32: =AJ31+1 -> 200001 | AJ32: 500000 | AK32: 0 | AL32: Project | AM32: 0.0015 | AN32: Commercial | AO32: 0.01 | AP32: West | AQ32: 0.0005 | AR32: =AS31+0.01% -> 1.0001 | AS32: 1.4999 | AT32: 0.0001
B33: Retention ปีที่ 5 | D33: =IF(C16="Yes",C10+0.2%,C10) | F33: =IFERROR(E10+0.2%,0) -> 0 | AI33: =AJ32+1 -> 500001 | AK33: 0 | AL33: Other | AM33: 0.002 | AR33: =AS32+0.01% -> 1.5 | AT33: 0.9
B34: COF | D34: =IFERROR(pam!Q21,0) -> 0 | F34: =IFERROR(pam!Q22,0) -> 0 | AB34: Final threshold | AD34: =AD24+AD32 -> #N/A | AL34: MP/PP | AM34: 0.005
B35: NII | D35: =IFERROR(C10-D34,0) -> 0 | F35: =IFERROR(E10-F34,0) -> 0
B41: ผลการพิจารณา | E41: =IFERROR(VLOOKUP($AD$10,$AD$17:$AF$19,3,TRUE),"")

Sheet 2.นำเสนอดอกเบี้ย
A1: ตารางนำเสนอดอกเบี้ย HL | N1: ='1.ลดดอกเบี้ย'!F1 -> v.202608.01
A2: อัตราดอกเบี้ย | C2: Month | F2: ตามมติ | I2: ขออนุมัติในครั้งนี้ | L2: ส่วนต่าง | M2: ดอกเบี้ยคู่แข่ง
A3: MRR = | C3: 1 | D3: - | E3: 12 | I3: ='1.ลดดอกเบี้ย'!C11 -> 0 | K3: ='1.ลดดอกเบี้ย'!D11 -> 0 | N3: โปรดระบุอัตราดอกเบี้ยและโปรโมชั่นคู่แข่ง... | P3: * กรอกเฉพาะช่องสีเหลือง
A4: ='1.ลดดอกเบี้ย'!C5 -> 0 | C4: =E3+1 -> 13 | D4: - | E4: 24 | I4: ='1.ลดดอกเบี้ย'!C12 -> 0 | K4: ='1.ลดดอกเบี้ย'!D12 -> 0
C5: =E4+1 -> 25 | D5: - | E5: 36 | I5: ='1.ลดดอกเบี้ย'!C13 -> 0 | K5: ='1.ลดดอกเบี้ย'!D13 -> 0
C6: 37 | D6: - | E6: For the rest | I6: ='1.ลดดอกเบี้ย'!C14 -> 0 | K6: ='1.ลดดอกเบี้ย'!D14 -> 0
F7: เฉลี่ย 3 ปี | H7: =AVERAGE(H3:H5) -> #DIV/0! | K7: =AVERAGE(K3:K5) -> 0 | L7: =K7-H7 -> #DIV/0!
A9: ชื่อลูกค้า | E9: ='1.ลดดอกเบี้ย'!C3 -> 0 | L9: App No. | N9: ='1.ลดดอกเบี้ย'!C4 -> 0
A10: ช่องทางการขาย | E10: ='1.ลดดอกเบี้ย'!C24 -> 0 | L10: Application Status
A11: ชื่อโครงการ / ชื่อ Developer | K11: ประเภทหลักประกัน
A12: จังหวัดที่ตั้งหลักประกัน | K12: อำเภอของหลักประกัน
A13: แคมเปญสินเชื่อ | E13: ='1.ลดดอกเบี้ย'!C18 -> 0 | K13: ผ่อนชำระ | M13: ='1.ลดดอกเบี้ย'!C9 -> 0 | N13: ปี
A14: วงเงินสินเชื่อ | E14: วงเงิน HL | G14: ='1.ลดดอกเบี้ย'!C8 -> 0 | N14: บาท
A15: วงเงินสินเชื่อ | E15: วงเงิน Insurance | H15: ='1.ลดดอกเบี้ย'!C15 -> 0 | N15: บาท
A16: ประวัติลูกค้า | E16: ผู้กู้หลัก ทำงานที่... ตำแหน่ง... รายได้รวม… อายุงาน... ผู้กู้ร่วม ทำงานที่... ตำแหน่ง... รายได้รวม… อายุงาน...
A17: LTV | H17: DSR | L17: Grade | N17: ='1.ลดดอกเบี้ย'!C20 -> 0
A19: --------------------------------------------------------------------------------------------------------------------------------------------------------------------------------------------------------
A21: ตารางนำเสนอดอกเบี้ย MP | N21: ='1.ลดดอกเบี้ย'!F1 -> v.202608.01
A22: อัตราดอกเบี้ย | C22: Month | F22: ตามมติ | I22: ขออนุมัติในครั้งนี้ | L22: ส่วนต่าง | M22: ดอกเบี้ยคู่แข่ง
A23: MRR = | C23: 1 | D23: - | E23: 12 | I23: ='1.ลดดอกเบี้ย'!E11 -> 0 | K23: ='1.ลดดอกเบี้ย'!F11 -> 0 | N23: โปรดระบุอัตราดอกเบี้ยและโปรโมชั่นคู่แข่ง... | P23: * กรอกเฉพาะช่องสีเหลือง
A24: ='1.ลดดอกเบี้ย'!C5 -> 0 | C24: =E23+1 -> 13 | D24: - | E24: 24 | I24: ='1.ลดดอกเบี้ย'!E12 -> 0 | K24: ='1.ลดดอกเบี้ย'!F12 -> 0
C25: =E24+1 -> 25 | D25: - | E25: 36 | I25: ='1.ลดดอกเบี้ย'!E13 -> 0 | K25: ='1.ลดดอกเบี้ย'!F13 -> 0
C26: 37 | D26: - | E26: For the rest | I26: ='1.ลดดอกเบี้ย'!E14 -> 0 | K26: ='1.ลดดอกเบี้ย'!F14 -> 0
F27: เฉลี่ย 3 ปี | H27: =AVERAGE(H23:H25) -> #DIV/0! | K27: =AVERAGE(K23:K25) -> 0 | L27: =K27-H27 -> #DIV/0!
A29: ชื่อลูกค้า | E29: ='1.ลดดอกเบี้ย'!C3 -> 0 | L29: App No. | N29: ='1.ลดดอกเบี้ย'!C4 -> 0
A30: ช่องทางการขาย | E30: ='1.ลดดอกเบี้ย'!E24 -> 0 | L30: Application Status
A31: ชื่อโครงการ / ชื่อ Developer | K31: ประเภทหลักประกัน
A32: จังหวัดที่ตั้งหลักประกัน | K32: อำเภอของหลักประกัน
A33: แคมเปญสินเชื่อ | E33: Mortgage Power / Property Power | K33: ผ่อนชำระ | M33: ='1.ลดดอกเบี้ย'!E9 -> 0 | N33: ปี
A34: วงเงินสินเชื่อ | E34: วงเงิน MP/PP | H34: ='1.ลดดอกเบี้ย'!E8 -> 0 | N34: บาท
A35: วงเงินสินเชื่อ | E35: วงเงิน Insurance | H35: ='1.ลดดอกเบี้ย'!E15 -> 0 | N35: บาท
A36: ประวัติลูกค้า | E36: ผู้กู้หลัก ทำงานที่... ตำแหน่ง... รายได้รวม… อายุงาน... ผู้กู้ร่วม ทำงานที่... ตำแหน่ง... รายได้รวม… อายุงาน...
A37: LTV | H37: DSR | L37: Grade | N37: ='1.ลดดอกเบี้ย'!E20 -> 0

Sheet ตาราง-HL-เสนอลด
B1: ตารางผ่อนชำระเบื้องต้น HL (อัตราดอกเบี้ยนำเสนอลด)
B2: ชื่อ | C2: ='1.ลดดอกเบี้ย'!C3 -> 0 | G2: ผ่อนชำระ
B3: App No | C3: ='1.ลดดอกเบี้ย'!C4 -> 0 | F3: อัตราดอกเบี้ย | G3: {='1.ลดดอกเบี้ย'!C26:D26} -> 0 | H3: 0
B4: วงเงิน | C4: ='2.นำเสนอดอกเบี้ย'!G14 -> 0 | D4: บาท | E4: ปีที่ 1 | F4: ='2.นำเสนอดอกเบี้ย'!K3 -> 0 | G4: ='1.ลดดอกเบี้ย'!C28 -> 0
B5: ระยะเวลา | C5: ='1.ลดดอกเบี้ย'!C9 -> 0 | D5: ปี | E5: ปีที่ 2 | F5: ='2.นำเสนอดอกเบี้ย'!K4 -> 0 | G5: ='1.ลดดอกเบี้ย'!C29 -> 0 | H5: =SUM(I6:I10)/#REF! -> #REF!
E6: ปีที่ 3 | F6: ='2.นำเสนอดอกเบี้ย'!K5 -> 0 | G6: ='1.ลดดอกเบี้ย'!C30 -> 0 | H6: =F4*12 -> 0
C7: Buffer | D7: 0.01 | E7: ปีที่ 4+ | F7: ='2.นำเสนอดอกเบี้ย'!K6 -> 0 | G7: ='1.ลดดอกเบี้ย'!C31 -> 0 | H7: =F5*12 -> 0
H8: =F6*12 -> 0
H9: =F7*12 -> 0
F10: Int. Yr. 5+ | G10: =F7 -> 0 | H10: =IF(G3="เท่ากันทุกเดือน",'1.ลดดอกเบี้ย'!#REF!,'1.ลดดอกเบี้ย'!C31) -> 0 | I10: =G10*(#REF!-48) -> #REF!
D11: =12*3 -> 36 | E11: =12*5 -> 60 | F11: =12*7 -> 84 | G11: =12*10 -> 120 | H11: =12*30 -> 360 | I11: =12*15 -> 180
D12: 3 Yrs. | E12: 5 Yrs. | F12: 7 Yrs. | G12: 10 Yrs. | H12: 30 Yrs. | I12: 15 Yrs
B13: Total Int. | D13: =SUM($G$20:$G$55) -> 0 | E13: =SUM($G$20:$G$79) -> 0 | F13: =SUM($G$20:$G$103) -> 0 | G13: =SUM($G$20:$G$139) -> 0 | H13: =SUM($G$20:$G$379) -> 0 | I13: =SUM($G$20:$G$199) -> 0
B14: Average O/S | D14: =AVERAGE($D$20:$D$55) -> 0 | E14: =AVERAGE($D$20:$D$79) -> 0 | F14: =AVERAGE($D$20:$D$103) -> 0 | G14: =AVERAGE($D$20:$D$139) -> 0 | H14: =AVERAGE($D$20:$D$379) -> 0 | I14: =AVERAGE($D$20:$D$199) -> 0
B15: EIR | D15: =D13/D14/(D11/12) -> #DIV/0! | E15: =E13/E14/(E11/12) -> #DIV/0! | F15: =F13/F14/(F11/12) -> #DIV/0! | G15: =G13/G14/(G11/12) -> #DIV/0! | H15: =H13/H14/(H11/12) -> #DIV/0! | I15: =I13/I14/(I11/12) -> #DIV/0!
B17: Average | D17: =AVERAGE($C$20:$C$55) -> 0 | E17: =AVERAGE($C$20:$C$79) -> 0 | F17: =AVERAGE($C$20:$C$103) -> 0 | G17: =AVERAGE($C$20:$C$139) -> 0 | H17: =AVERAGE($C$20:$C$379) -> 0 | I17: =AVERAGE(C20:C199) -> 0
B19: เดือน | C19: อัตราดอกเบี้ย | D19: ยอดคงค้าง | E19: ยอดผ่อนชำระ | F19: ยอดเงินต้น | G19: ยอดดอกเบี้ย | H19: ยอดคงค้าง | I19: LTV | O19: Tenor
B20: 1 | C20: =IF(D20>0,$F$4,0) -> 0 | D20: =C4 -> 0 | E20: =G4 -> 0 | F20: =E20-G20 -> 0 | G20: =C20*(D20/365)*30 -> 0 | H20: =IF((D20+G20-E20)<0,0,D20+G20-E20) -> 0 | O20: =IF(H20=0,B20,"n.a.") -> 1
B21: =B20+1 -> 2 | C21: =IF(D21>0,$F$4,0) -> 0 | D21: =H20 -> 0 | E21: =IF(H20<=E20,H20+G21,$G$4) -> 0 | F21: =E21-G21 -> 0 | G21: =C21*(D21/365)*30 -> 0 | H21: =IF((D21+G21-E21)<0,0,D21+G21-E21) -> 0 | O21: =IF(H21=0,B21,"n.a.") -> 2
B22: =B21+1 -> 3 | C22: =IF(D22>0,$F$4,0) -> 0 | D22: =H21 -> 0 | E22: =IF(H21<=E21,H21+G22,$G$4) -> 0 | F22: =E22-G22 -> 0 | G22: =C22*(D22/365)*30 -> 0 | H22: =IF((D22+G22-E22)<0,0,D22+G22-E22) -> 0 | O22: =IF(H22=0,B22,"n.a.") -> 3
B23: =B22+1 -> 4 | C23: =IF(D23>0,$F$4,0) -> 0 | D23: =H22 -> 0 | E23: =IF(H22<=E22,H22+G23,$G$4) -> 0 | F23: =E23-G23 -> 0 | G23: =C23*(D23/365)*30 -> 0 | H23: =IF((D23+G23-E23)<0,0,D23+G23-E23) -> 0 | O23: =IF(H23=0,B23,"n.a.") -> 4
B24: =B23+1 -> 5 | C24: =IF(D24>0,$F$4,0) -> 0 | D24: =H23 -> 0 | E24: =IF(H23<=E23,H23+G24,$G$4) -> 0 | F24: =E24-G24 -> 0 | G24: =C24*(D24/365)*30 -> 0 | H24: =IF((D24+G24-E24)<0,0,D24+G24-E24) -> 0 | O24: =IF(H24=0,B24,"n.a.") -> 5
B25: =B24+1 -> 6 | C25: =IF(D25>0,$F$4,0) -> 0 | D25: =H24 -> 0 | E25: =IF(H24<=E24,H24+G25,$G$4) -> 0 | F25: =E25-G25 -> 0 | G25: =C25*(D25/365)*30 -> 0 | H25: =IF((D25+G25-E25)<0,0,D25+G25-E25) -> 0 | O25: =IF(H25=0,B25,"n.a.") -> 6
B26: =B25+1 -> 7 | C26: =IF(D26>0,$F$4,0) -> 0 | D26: =H25 -> 0 | E26: =IF(H25<=E25,H25+G26,$G$4) -> 0 | F26: =E26-G26 -> 0 | G26: =C26*(D26/365)*30 -> 0 | H26: =IF((D26+G26-E26)<0,0,D26+G26-E26) -> 0 | O26: =IF(H26=0,B26,"n.a.") -> 7
B27: =B26+1 -> 8 | C27: =IF(D27>0,$F$4,0) -> 0 | D27: =H26 -> 0 | E27: =IF(H26<=E26,H26+G27,$G$4) -> 0 | F27: =E27-G27 -> 0 | G27: =C27*(D27/365)*30 -> 0 | H27: =IF((D27+G27-E27)<0,0,D27+G27-E27) -> 0 | O27: =IF(H27=0,B27,"n.a.") -> 8
B28: =B27+1 -> 9 | C28: =IF(D28>0,$F$4,0) -> 0 | D28: =H27 -> 0 | E28: =IF(H27<=E27,H27+G28,$G$4) -> 0 | F28: =E28-G28 -> 0 | G28: =C28*(D28/365)*30 -> 0 | H28: =IF((D28+G28-E28)<0,0,D28+G28-E28) -> 0 | O28: =IF(H28=0,B28,"n.a.") -> 9
B29: =B28+1 -> 10 | C29: =IF(D29>0,$F$4,0) -> 0 | D29: =H28 -> 0 | E29: =IF(H28<=E28,H28+G29,$G$4) -> 0 | F29: =E29-G29 -> 0 | G29: =C29*(D29/365)*30 -> 0 | H29: =IF((D29+G29-E29)<0,0,D29+G29-E29) -> 0 | O29: =IF(H29=0,B29,"n.a.") -> 10
B30: =B29+1 -> 11 | C30: =IF(D30>0,$F$4,0) -> 0 | D30: =H29 -> 0 | E30: =IF(H29<=E29,H29+G30,$G$4) -> 0 | F30: =E30-G30 -> 0 | G30: =C30*(D30/365)*30 -> 0 | H30: =IF((D30+G30-E30)<0,0,D30+G30-E30) -> 0 | O30: =IF(H30=0,B30,"n.a.") -> 11
B31: =B30+1 -> 12 | C31: =IF(D31>0,$F$4,0) -> 0 | D31: =H30 -> 0 | E31: =IF(H30<=E30,H30+G31,$G$4) -> 0 | F31: =E31-G31 -> 0 | G31: =C31*(D31/365)*30 -> 0 | H31: =IF((D31+G31-E31)<0,0,D31+G31-E31) -> 0 | I31: =H31/$D$5 -> #VALUE! | O31: =IF(H31=0,B31,"n.a.") -> 12
B32: =B31+1 -> 13 | C32: =IF(D32>0,$F$5,0) -> 0 | D32: =H31 -> 0 | E32: =IF(H31<=E31,H31+G32,$G$5) -> 0 | F32: =E32-G32 -> 0 | G32: =C32*(D32/365)*30 -> 0 | H32: =IF((D32+G32-E32)<0,0,D32+G32-E32) -> 0 | O32: =IF(H32=0,B32,"n.a.") -> 13
B33: =B32+1 -> 14 | C33: =IF(D33>0,$F$5,0) -> 0 | D33: =H32 -> 0 | E33: =IF(H32<=E32,H32+G33,$G$5) -> 0 | F33: =E33-G33 -> 0 | G33: =C33*(D33/365)*30 -> 0 | H33: =IF((D33+G33-E33)<0,0,D33+G33-E33) -> 0 | O33: =IF(H33=0,B33,"n.a.") -> 14
B34: =B33+1 -> 15 | C34: =IF(D34>0,$F$5,0) -> 0 | D34: =H33 -> 0 | E34: =IF(H33<=E33,H33+G34,$G$5) -> 0 | F34: =E34-G34 -> 0 | G34: =C34*(D34/365)*30 -> 0 | H34: =IF((D34+G34-E34)<0,0,D34+G34-E34) -> 0 | O34: =IF(H34=0,B34,"n.a.") -> 15
B35: =B34+1 -> 16 | C35: =IF(D35>0,$F$5,0) -> 0 | D35: =H34 -> 0 | E35: =IF(H34<=E34,H34+G35,$G$5) -> 0 | F35: =E35-G35 -> 0 | G35: =C35*(D35/365)*30 -> 0 | H35: =IF((D35+G35-E35)<0,0,D35+G35-E35) -> 0 | O35: =IF(H35=0,B35,"n.a.") -> 16
B36: =B35+1 -> 17 | C36: =IF(D36>0,$F$5,0) -> 0 | D36: =H35 -> 0 | E36: =IF(H35<=E35,H35+G36,$G$5) -> 0 | F36: =E36-G36 -> 0 | G36: =C36*(D36/365)*30 -> 0 | H36: =IF((D36+G36-E36)<0,0,D36+G36-E36) -> 0 | O36: =IF(H36=0,B36,"n.a.") -> 17
B37: =B36+1 -> 18 | C37: =IF(D37>0,$F$5,0) -> 0 | D37: =H36 -> 0 | E37: =IF(H36<=E36,H36+G37,$G$5) -> 0 | F37: =E37-G37 -> 0 | G37: =C37*(D37/365)*30 -> 0 | H37: =IF((D37+G37-E37)<0,0,D37+G37-E37) -> 0 | O37: =IF(H37=0,B37,"n.a.") -> 18
B38: =B37+1 -> 19 | C38: =IF(D38>0,$F$5,0) -> 0 | D38: =H37 -> 0 | E38: =IF(H37<=E37,H37+G38,$G$5) -> 0 | F38: =E38-G38 -> 0 | G38: =C38*(D38/365)*30 -> 0 | H38: =IF((D38+G38-E38)<0,0,D38+G38-E38) -> 0 | O38: =IF(H38=0,B38,"n.a.") -> 19
B39: =B38+1 -> 20 | C39: =IF(D39>0,$F$5,0) -> 0 | D39: =H38 -> 0 | E39: =IF(H38<=E38,H38+G39,$G$5) -> 0 | F39: =E39-G39 -> 0 | G39: =C39*(D39/365)*30 -> 0 | H39: =IF((D39+G39-E39)<0,0,D39+G39-E39) -> 0 | O39: =IF(H39=0,B39,"n.a.") -> 20
B40: =B39+1 -> 21 | C40: =IF(D40>0,$F$5,0) -> 0 | D40: =H39 -> 0 | E40: =IF(H39<=E39,H39+G40,$G$5) -> 0 | F40: =E40-G40 -> 0 | G40: =C40*(D40/365)*30 -> 0 | H40: =IF((D40+G40-E40)<0,0,D40+G40-E40) -> 0 | O40: =IF(H40=0,B40,"n.a.") -> 21
B41: =B40+1 -> 22 | C41: =IF(D41>0,$F$5,0) -> 0 | D41: =H40 -> 0 | E41: =IF(H40<=E40,H40+G41,$G$5) -> 0 | F41: =E41-G41 -> 0 | G41: =C41*(D41/365)*30 -> 0 | H41: =IF((D41+G41-E41)<0,0,D41+G41-E41) -> 0 | O41: =IF(H41=0,B41,"n.a.") -> 22
B42: =B41+1 -> 23 | C42: =IF(D42>0,$F$5,0) -> 0 | D42: =H41 -> 0 | E42: =IF(H41<=E41,H41+G42,$G$5) -> 0 | F42: =E42-G42 -> 0 | G42: =C42*(D42/365)*30 -> 0 | H42: =IF((D42+G42-E42)<0,0,D42+G42-E42) -> 0 | O42: =IF(H42=0,B42,"n.a.") -> 23
B43: =B42+1 -> 24 | C43: =IF(D43>0,$F$5,0) -> 0 | D43: =H42 -> 0 | E43: =IF(H42<=E42,H42+G43,$G$5) -> 0 | F43: =E43-G43 -> 0 | G43: =C43*(D43/365)*30 -> 0 | H43: =IF((D43+G43-E43)<0,0,D43+G43-E43) -> 0 | I43: =H43/$D$5 -> #VALUE! | O43: =IF(H43=0,B43,"n.a.") -> 24
B44: =B43+1 -> 25 | C44: =IF(D44>0,$F$6,0) -> 0 | D44: =H43 -> 0 | E44: =IF(H43<=E43,H43+G44,$G$6) -> 0 | F44: =E44-G44 -> 0 | G44: =C44*(D44/365)*30 -> 0 | H44: =IF((D44+G44-E44)<0,0,D44+G44-E44) -> 0 | O44: =IF(H44=0,B44,"n.a.") -> 25
B45: =B44+1 -> 26 | C45: =IF(D45>0,$F$6,0) -> 0 | D45: =H44 -> 0 | E45: =IF(H44<=E44,H44+G45,$G$6) -> 0 | F45: =E45-G45 -> 0 | G45: =C45*(D45/365)*30 -> 0 | H45: =IF((D45+G45-E45)<0,0,D45+G45-E45) -> 0 | O45: =IF(H45=0,B45,"n.a.") -> 26
B46: =B45+1 -> 27 | C46: =IF(D46>0,$F$6,0) -> 0 | D46: =H45 -> 0 | E46: =IF(H45<=E45,H45+G46,$G$6) -> 0 | F46: =E46-G46 -> 0 | G46: =C46*(D46/365)*30 -> 0 | H46: =IF((D46+G46-E46)<0,0,D46+G46-E46) -> 0 | O46: =IF(H46=0,B46,"n.a.") -> 27
B47: =B46+1 -> 28 | C47: =IF(D47>0,$F$6,0) -> 0 | D47: =H46 -> 0 | E47: =IF(H46<=E46,H46+G47,$G$6) -> 0 | F47: =E47-G47 -> 0 | G47: =C47*(D47/365)*30 -> 0 | H47: =IF((D47+G47-E47)<0,0,D47+G47-E47) -> 0 | O47: =IF(H47=0,B47,"n.a.") -> 28
B48: =B47+1 -> 29 | C48: =IF(D48>0,$F$6,0) -> 0 | D48: =H47 -> 0 | E48: =IF(H47<=E47,H47+G48,$G$6) -> 0 | F48: =E48-G48 -> 0 | G48: =C48*(D48/365)*30 -> 0 | H48: =IF((D48+G48-E48)<0,0,D48+G48-E48) -> 0 | O48: =IF(H48=0,B48,"n.a.") -> 29
B49: =B48+1 -> 30 | C49: =IF(D49>0,$F$6,0) -> 0 | D49: =H48 -> 0 | E49: =IF(H48<=E48,H48+G49,$G$6) -> 0 | F49: =E49-G49 -> 0 | G49: =C49*(D49/365)*30 -> 0 | H49: =IF((D49+G49-E49)<0,0,D49+G49-E49) -> 0 | O49: =IF(H49=0,B49,"n.a.") -> 30
B50: =B49+1 -> 31 | C50: =IF(D50>0,$F$6,0) -> 0 | D50: =H49 -> 0 | E50: =IF(H49<=E49,H49+G50,$G$6) -> 0 | F50: =E50-G50 -> 0 | G50: =C50*(D50/365)*30 -> 0 | H50: =IF((D50+G50-E50)<0,0,D50+G50-E50) -> 0 | O50: =IF(H50=0,B50,"n.a.") -> 31
B51: =B50+1 -> 32 | C51: =IF(D51>0,$F$6,0) -> 0 | D51: =H50 -> 0 | E51: =IF(H50<=E50,H50+G51,$G$6) -> 0 | F51: =E51-G51 -> 0 | G51: =C51*(D51/365)*30 -> 0 | H51: =IF((D51+G51-E51)<0,0,D51+G51-E51) -> 0 | O51: =IF(H51=0,B51,"n.a.") -> 32
B52: =B51+1 -> 33 | C52: =IF(D52>0,$F$6,0) -> 0 | D52: =H51 -> 0 | E52: =IF(H51<=E51,H51+G52,$G$6) -> 0 | F52: =E52-G52 -> 0 | G52: =C52*(D52/365)*30 -> 0 | H52: =IF((D52+G52-E52)<0,0,D52+G52-E52) -> 0 | O52: =IF(H52=0,B52,"n.a.") -> 33
B53: =B52+1 -> 34 | C53: =IF(D53>0,$F$6,0) -> 0 | D53: =H52 -> 0 | E53: =IF(H52<=E52,H52+G53,$G$6) -> 0 | F53: =E53-G53 -> 0 | G53: =C53*(D53/365)*30 -> 0 | H53: =IF((D53+G53-E53)<0,0,D53+G53-E53) -> 0 | O53: =IF(H53=0,B53,"n.a.") -> 34
B54: =B53+1 -> 35 | C54: =IF(D54>0,$F$6,0) -> 0 | D54: =H53 -> 0 | E54: =IF(H53<=E53,H53+G54,$G$6) -> 0 | F54: =E54-G54 -> 0 | G54: =C54*(D54/365)*30 -> 0 | H54: =IF((D54+G54-E54)<0,0,D54+G54-E54) -> 0 | O54: =IF(H54=0,B54,"n.a.") -> 35
B55: =B54+1 -> 36 | C55: =IF(D55>0,$F$6,0) -> 0 | D55: =H54 -> 0 | E55: =IF(H54<=E54,H54+G55,$G$6) -> 0 | F55: =E55-G55 -> 0 | G55: =C55*(D55/365)*30 -> 0 | H55: =IF((D55+G55-E55)<0,0,D55+G55-E55) -> 0 | I55: =H55/$D$5 -> #VALUE! | O55: =IF(H55=0,B55,"n.a.") -> 36
B56: =B55+1 -> 37 | C56: =IF(D56>0,$F$7,0) -> 0 | D56: =H55 -> 0 | E56: =IF(H55<=E55,H55+G56,$G$7) -> 0 | F56: =E56-G56 -> 0 | G56: =C56*(D56/365)*30 -> 0 | H56: =IF((D56+G56-E56)<0,0,D56+G56-E56) -> 0 | O56: =IF(H56=0,B56,"n.a.") -> 37
B57: =B56+1 -> 38 | C57: =IF(D57>0,$F$7,0) -> 0 | D57: =H56 -> 0 | E57: =IF(H56<=E56,H56+G57,$G$7) -> 0 | F57: =E57-G57 -> 0 | G57: =C57*(D57/365)*30 -> 0 | H57: =IF((D57+G57-E57)<0,0,D57+G57-E57) -> 0 | O57: =IF(H57=0,B57,"n.a.") -> 38
B58: =B57+1 -> 39 | C58: =IF(D58>0,$F$7,0) -> 0 | D58: =H57 -> 0 | E58: =IF(H57<=E57,H57+G58,$G$7) -> 0 | F58: =E58-G58 -> 0 | G58: =C58*(D58/365)*30 -> 0 | H58: =IF((D58+G58-E58)<0,0,D58+G58-E58) -> 0 | O58: =IF(H58=0,B58,"n.a.") -> 39
B59: =B58+1 -> 40 | C59: =IF(D59>0,$F$7,0) -> 0 | D59: =H58 -> 0 | E59: =IF(H58<=E58,H58+G59,$G$7) -> 0 | F59: =E59-G59 -> 0 | G59: =C59*(D59/365)*30 -> 0 | H59: =IF((D59+G59-E59)<0,0,D59+G59-E59) -> 0 | O59: =IF(H59=0,B59,"n.a.") -> 40
B60: =B59+1 -> 41 | C60: =IF(D60>0,$F$7,0) -> 0 | D60: =H59 -> 0 | E60: =IF(H59<=E59,H59+G60,$G$7) -> 0 | F60: =E60-G60 -> 0 | G60: =C60*(D60/365)*30 -> 0 | H60: =IF((D60+G60-E60)<0,0,D60+G60-E60) -> 0 | O60: =IF(H60=0,B60,"n.a.") -> 41
B61: =B60+1 -> 42 | C61: =IF(D61>0,$F$7,0) -> 0 | D61: =H60 -> 0 | E61: =IF(H60<=E60,H60+G61,$G$7) -> 0 | F61: =E61-G61 -> 0 | G61: =C61*(D61/365)*30 -> 0 | H61: =IF((D61+G61-E61)<0,0,D61+G61-E61) -> 0 | O61: =IF(H61=0,B61,"n.a.") -> 42
B62: =B61+1 -> 43 | C62: =IF(D62>0,$F$7,0) -> 0 | D62: =H61 -> 0 | E62: =IF(H61<=E61,H61+G62,$G$7) -> 0 | F62: =E62-G62 -> 0 | G62: =C62*(D62/365)*30 -> 0 | H62: =IF((D62+G62-E62)<0,0,D62+G62-E62) -> 0 | O62: =IF(H62=0,B62,"n.a.") -> 43
B63: =B62+1 -> 44 | C63: =IF(D63>0,$F$7,0) -> 0 | D63: =H62 -> 0 | E63: =IF(H62<=E62,H62+G63,$G$7) -> 0 | F63: =E63-G63 -> 0 | G63: =C63*(D63/365)*30 -> 0 | H63: =IF((D63+G63-E63)<0,0,D63+G63-E63) -> 0 | O63: =IF(H63=0,B63,"n.a.") -> 44
B64: =B63+1 -> 45 | C64: =IF(D64>0,$F$7,0) -> 0 | D64: =H63 -> 0 | E64: =IF(H63<=E63,H63+G64,$G$7) -> 0 | F64: =E64-G64 -> 0 | G64: =C64*(D64/365)*30 -> 0 | H64: =IF((D64+G64-E64)<0,0,D64+G64-E64) -> 0 | O64: =IF(H64=0,B64,"n.a.") -> 45
B65: =B64+1 -> 46 | C65: =IF(D65>0,$F$7,0) -> 0 | D65: =H64 -> 0 | E65: =IF(H64<=E64,H64+G65,$G$7) -> 0 | F65: =E65-G65 -> 0 | G65: =C65*(D65/365)*30 -> 0 | H65: =IF((D65+G65-E65)<0,0,D65+G65-E65) -> 0 | O65: =IF(H65=0,B65,"n.a.") -> 46
B66: =B65+1 -> 47 | C66: =IF(D66>0,$F$7,0) -> 0 | D66: =H65 -> 0 | E66: =IF(H65<=E65,H65+G66,$G$7) -> 0 | F66: =E66-G66 -> 0 | G66: =C66*(D66/365)*30 -> 0 | H66: =IF((D66+G66-E66)<0,0,D66+G66-E66) -> 0 | O66: =IF(H66=0,B66,"n.a.") -> 47
B67: =B66+1 -> 48 | C67: =IF(D67>0,$F$7,0) -> 0 | D67: =H66 -> 0 | E67: =IF(H66<=E66,H66+G67,$G$7) -> 0 | F67: =E67-G67 -> 0 | G67: =C67*(D67/365)*30 -> 0 | H67: =IF((D67+G67-E67)<0,0,D67+G67-E67) -> 0 | I67: =H67/$D$5 -> #VALUE! | O67: =IF(H67=0,B67,"n.a.") -> 48
B68: =B67+1 -> 49 | C68: =IF(D68>0,$F$7,0) -> 0 | D68: =H67 -> 0 | E68: =IF(H67<=E67,H67+G68,$H$10) -> 0 | F68: =E68-G68 -> 0 | G68: =C68*(D68/365)*30 -> 0 | H68: =IF((D68+G68-E68)<0,0,D68+G68-E68) -> 0 | O68: =IF(H68=0,B68,"n.a.") -> 49
B69: =B68+1 -> 50 | C69: =IF(D69>0,$F$7,0) -> 0 | D69: =H68 -> 0 | E69: =IF(H68<=E68,H68+G69,$H$10) -> 0 | F69: =E69-G69 -> 0 | G69: =C69*(D69/365)*30 -> 0 | H69: =IF((D69+G69-E69)<0,0,D69+G69-E69) -> 0 | O69: =IF(H69=0,B69,"n.a.") -> 50
B70: =B69+1 -> 51 | C70: =IF(D70>0,$F$7,0) -> 0 | D70: =H69 -> 0 | E70: =IF(H69<=E69,H69+G70,$H$10) -> 0 | F70: =E70-G70 -> 0 | G70: =C70*(D70/365)*30 -> 0 | H70: =IF((D70+G70-E70)<0,0,D70+G70-E70) -> 0 | O70: =IF(H70=0,B70,"n.a.") -> 51
B71: =B70+1 -> 52 | C71: =IF(D71>0,$F$7,0) -> 0 | D71: =H70 -> 0 | E71: =IF(H70<=E70,H70+G71,$H$10) -> 0 | F71: =E71-G71 -> 0 | G71: =C71*(D71/365)*30 -> 0 | H71: =IF((D71+G71-E71)<0,0,D71+G71-E71) -> 0 | O71: =IF(H71=0,B71,"n.a.") -> 52
B72: =B71+1 -> 53 | C72: =IF(D72>0,$F$7,0) -> 0 | D72: =H71 -> 0 | E72: =IF(H71<=E71,H71+G72,$H$10) -> 0 | F72: =E72-G72 -> 0 | G72: =C72*(D72/365)*30 -> 0 | H72: =IF((D72+G72-E72)<0,0,D72+G72-E72) -> 0 | O72: =IF(H72=0,B72,"n.a.") -> 53
B73: =B72+1 -> 54 | C73: =IF(D73>0,$F$7,0) -> 0 | D73: =H72 -> 0 | E73: =IF(H72<=E72,H72+G73,$H$10) -> 0 | F73: =E73-G73 -> 0 | G73: =C73*(D73/365)*30 -> 0 | H73: =IF((D73+G73-E73)<0,0,D73+G73-E73) -> 0 | O73: =IF(H73=0,B73,"n.a.") -> 54
B74: =B73+1 -> 55 | C74: =IF(D74>0,$F$7,0) -> 0 | D74: =H73 -> 0 | E74: =IF(H73<=E73,H73+G74,$H$10) -> 0 | F74: =E74-G74 -> 0 | G74: =C74*(D74/365)*30 -> 0 | H74: =IF((D74+G74-E74)<0,0,D74+G74-E74) -> 0 | O74: =IF(H74=0,B74,"n.a.") -> 55
B75: =B74+1 -> 56 | C75: =IF(D75>0,$F$7,0) -> 0 | D75: =H74 -> 0 | E75: =IF(H74<=E74,H74+G75,$H$10) -> 0 | F75: =E75-G75 -> 0 | G75: =C75*(D75/365)*30 -> 0 | H75: =IF((D75+G75-E75)<0,0,D75+G75-E75) -> 0 | O75: =IF(H75=0,B75,"n.a.") -> 56
B76: =B75+1 -> 57 | C76: =IF(D76>0,$F$7,0) -> 0 | D76: =H75 -> 0 | E76: =IF(H75<=E75,H75+G76,$H$10) -> 0 | F76: =E76-G76 -> 0 | G76: =C76*(D76/365)*30 -> 0 | H76: =IF((D76+G76-E76)<0,0,D76+G76-E76) -> 0 | O76: =IF(H76=0,B76,"n.a.") -> 57
B77: =B76+1 -> 58 | C77: =IF(D77>0,$F$7,0) -> 0 | D77: =H76 -> 0 | E77: =IF(H76<=E76,H76+G77,$H$10) -> 0 | F77: =E77-G77 -> 0 | G77: =C77*(D77/365)*30 -> 0 | H77: =IF((D77+G77-E77)<0,0,D77+G77-E77) -> 0 | O77: =IF(H77=0,B77,"n.a.") -> 58
B78: =B77+1 -> 59 | C78: =IF(D78>0,$F$7,0) -> 0 | D78: =H77 -> 0 | E78: =IF(H77<=E77,H77+G78,$H$10) -> 0 | F78: =E78-G78 -> 0 | G78: =C78*(D78/365)*30 -> 0 | H78: =IF((D78+G78-E78)<0,0,D78+G78-E78) -> 0 | O78: =IF(H78=0,B78,"n.a.") -> 59
B79: =B78+1 -> 60 | C79: =IF(D79>0,$F$7,0) -> 0 | D79: =H78 -> 0 | E79: =IF(H78<=E78,H78+G79,$H$10) -> 0 | F79: =E79-G79 -> 0 | G79: =C79*(D79/365)*30 -> 0 | H79: =IF((D79+G79-E79)<0,0,D79+G79-E79) -> 0 | I79: =H79/$D$5 -> #VALUE! | O79: =IF(H79=0,B79,"n.a.") -> 60
B80: =B79+1 -> 61 | C80: =IF(D80>0,$F$7,0) -> 0 | D80: =H79 -> 0 | E80: =IF(H79<=E79,H79+G80,$H$10) -> 0 | F80: =E80-G80 -> 0 | G80: =C80*(D80/365)*30 -> 0 | H80: =IF((D80+G80-E80)<0,0,D80+G80-E80) -> 0 | O80: =IF(H80=0,B80,"n.a.") -> 61
B81: =B80+1 -> 62 | C81: =IF(D81>0,$F$7,0) -> 0 | D81: =H80 -> 0 | E81: =IF(H80<=E80,H80+G81,$H$10) -> 0 | F81: =E81-G81 -> 0 | G81: =C81*(D81/365)*30 -> 0 | H81: =IF((D81+G81-E81)<0,0,D81+G81-E81) -> 0 | O81: =IF(H81=0,B81,"n.a.") -> 62
B82: =B81+1 -> 63 | C82: =IF(D82>0,$F$7,0) -> 0 | D82: =H81 -> 0 | E82: =IF(H81<=E81,H81+G82,$H$10) -> 0 | F82: =E82-G82 -> 0 | G82: =C82*(D82/365)*30 -> 0 | H82: =IF((D82+G82-E82)<0,0,D82+G82-E82) -> 0 | O82: =IF(H82=0,B82,"n.a.") -> 63
B83: =B82+1 -> 64 | C83: =IF(D83>0,$F$7,0) -> 0 | D83: =H82 -> 0 | E83: =IF(H82<=E82,H82+G83,$H$10) -> 0 | F83: =E83-G83 -> 0 | G83: =C83*(D83/365)*30 -> 0 | H83: =IF((D83+G83-E83)<0,0,D83+G83-E83) -> 0 | O83: =IF(H83=0,B83,"n.a.") -> 64
B84: =B83+1 -> 65 | C84: =IF(D84>0,$F$7,0) -> 0 | D84: =H83 -> 0 | E84: =IF(H83<=E83,H83+G84,$H$10) -> 0 | F84: =E84-G84 -> 0 | G84: =C84*(D84/365)*30 -> 0 | H84: =IF((D84+G84-E84)<0,0,D84+G84-E84) -> 0 | O84: =IF(H84=0,B84,"n.a.") -> 65
B85: =B84+1 -> 66 | C85: =IF(D85>0,$F$7,0) -> 0 | D85: =H84 -> 0 | E85: =IF(H84<=E84,H84+G85,$H$10) -> 0 | F85: =E85-G85 -> 0 | G85: =C85*(D85/365)*30 -> 0 | H85: =IF((D85+G85-E85)<0,0,D85+G85-E85) -> 0 | O85: =IF(H85=0,B85,"n.a.") -> 66
B86: =B85+1 -> 67 | C86: =IF(D86>0,$F$7,0) -> 0 | D86: =H85 -> 0 | E86: =IF(H85<=E85,H85+G86,$H$10) -> 0 | F86: =E86-G86 -> 0 | G86: =C86*(D86/365)*30 -> 0 | H86: =IF((D86+G86-E86)<0,0,D86+G86-E86) -> 0 | O86: =IF(H86=0,B86,"n.a.") -> 67
B87: =B86+1 -> 68 | C87: =IF(D87>0,$F$7,0) -> 0 | D87: =H86 -> 0 | E87: =IF(H86<=E86,H86+G87,$H$10) -> 0 | F87: =E87-G87 -> 0 | G87: =C87*(D87/365)*30 -> 0 | H87: =IF((D87+G87-E87)<0,0,D87+G87-E87) -> 0 | O87: =IF(H87=0,B87,"n.a.") -> 68
B88: =B87+1 -> 69 | C88: =IF(D88>0,$F$7,0) -> 0 | D88: =H87 -> 0 | E88: =IF(H87<=E87,H87+G88,$H$10) -> 0 | F88: =E88-G88 -> 0 | G88: =C88*(D88/365)*30 -> 0 | H88: =IF((D88+G88-E88)<0,0,D88+G88-E88) -> 0 | O88: =IF(H88=0,B88,"n.a.") -> 69
B89: =B88+1 -> 70 | C89: =IF(D89>0,$F$7,0) -> 0 | D89: =H88 -> 0 | E89: =IF(H88<=E88,H88+G89,$H$10) -> 0 | F89: =E89-G89 -> 0 | G89: =C89*(D89/365)*30 -> 0 | H89: =IF((D89+G89-E89)<0,0,D89+G89-E89) -> 0 | O89: =IF(H89=0,B89,"n.a.") -> 70
B90: =B89+1 -> 71 | C90: =IF(D90>0,$F$7,0) -> 0 | D90: =H89 -> 0 | E90: =IF(H89<=E89,H89+G90,$H$10) -> 0 | F90: =E90-G90 -> 0 | G90: =C90*(D90/365)*30 -> 0 | H90: =IF((D90+G90-E90)<0,0,D90+G90-E90) -> 0 | O90: =IF(H90=0,B90,"n.a.") -> 71
B91: =B90+1 -> 72 | C91: =IF(D91>0,$F$7,0) -> 0 | D91: =H90 -> 0 | E91: =IF(H90<=E90,H90+G91,$H$10) -> 0 | F91: =E91-G91 -> 0 | G91: =C91*(D91/365)*30 -> 0 | H91: =IF((D91+G91-E91)<0,0,D91+G91-E91) -> 0 | I91: =H91/$D$5 -> #VALUE! | O91: =IF(H91=0,B91,"n.a.") -> 72
B92: =B91+1 -> 73 | C92: =IF(D92>0,$F$7,0) -> 0 | D92: =H91 -> 0 | E92: =IF(H91<=E91,H91+G92,$H$10) -> 0 | F92: =E92-G92 -> 0 | G92: =C92*(D92/365)*30 -> 0 | H92: =IF((D92+G92-E92)<0,0,D92+G92-E92) -> 0 | O92: =IF(H92=0,B92,"n.a.") -> 73
B93: =B92+1 -> 74 | C93: =IF(D93>0,$F$7,0) -> 0 | D93: =H92 -> 0 | E93: =IF(H92<=E92,H92+G93,$H$10) -> 0 | F93: =E93-G93 -> 0 | G93: =C93*(D93/365)*30 -> 0 | H93: =IF((D93+G93-E93)<0,0,D93+G93-E93) -> 0 | O93: =IF(H93=0,B93,"n.a.") -> 74
B94: =B93+1 -> 75 | C94: =IF(D94>0,$F$7,0) -> 0 | D94: =H93 -> 0 | E94: =IF(H93<=E93,H93+G94,$H$10) -> 0 | F94: =E94-G94 -> 0 | G94: =C94*(D94/365)*30 -> 0 | H94: =IF((D94+G94-E94)<0,0,D94+G94-E94) -> 0 | O94: =IF(H94=0,B94,"n.a.") -> 75
B95: =B94+1 -> 76 | C95: =IF(D95>0,$F$7,0) -> 0 | D95: =H94 -> 0 | E95: =IF(H94<=E94,H94+G95,$H$10) -> 0 | F95: =E95-G95 -> 0 | G95: =C95*(D95/365)*30 -> 0 | H95: =IF((D95+G95-E95)<0,0,D95+G95-E95) -> 0 | O95: =IF(H95=0,B95,"n.a.") -> 76
B96: =B95+1 -> 77 | C96: =IF(D96>0,$F$7,0) -> 0 | D96: =H95 -> 0 | E96: =IF(H95<=E95,H95+G96,$H$10) -> 0 | F96: =E96-G96 -> 0 | G96: =C96*(D96/365)*30 -> 0 | H96: =IF((D96+G96-E96)<0,0,D96+G96-E96) -> 0 | O96: =IF(H96=0,B96,"n.a.") -> 77
B97: =B96+1 -> 78 | C97: =IF(D97>0,$F$7,0) -> 0 | D97: =H96 -> 0 | E97: =IF(H96<=E96,H96+G97,$H$10) -> 0 | F97: =E97-G97 -> 0 | G97: =C97*(D97/365)*30 -> 0 | H97: =IF((D97+G97-E97)<0,0,D97+G97-E97) -> 0 | O97: =IF(H97=0,B97,"n.a.") -> 78
B98: =B97+1 -> 79 | C98: =IF(D98>0,$F$7,0) -> 0 | D98: =H97 -> 0 | E98: =IF(H97<=E97,H97+G98,$H$10) -> 0 | F98: =E98-G98 -> 0 | G98: =C98*(D98/365)*30 -> 0 | H98: =IF((D98+G98-E98)<0,0,D98+G98-E98) -> 0 | O98: =IF(H98=0,B98,"n.a.") -> 79
B99: =B98+1 -> 80 | C99: =IF(D99>0,$F$7,0) -> 0 | D99: =H98 -> 0 | E99: =IF(H98<=E98,H98+G99,$H$10) -> 0 | F99: =E99-G99 -> 0 | G99: =C99*(D99/365)*30 -> 0 | H99: =IF((D99+G99-E99)<0,0,D99+G99-E99) -> 0 | O99: =IF(H99=0,B99,"n.a.") -> 80
B100: =B99+1 -> 81 | C100: =IF(D100>0,$F$7,0) -> 0 | D100: =H99 -> 0 | E100: =IF(H99<=E99,H99+G100,$H$10) -> 0 | F100: =E100-G100 -> 0 | G100: =C100*(D100/365)*30 -> 0 | H100: =IF((D100+G100-E100)<0,0,D100+G100-E100) -> 0 | O100: =IF(H100=0,B100,"n.a.") -> 81
B101: =B100+1 -> 82 | C101: =IF(D101>0,$F$7,0) -> 0 | D101: =H100 -> 0 | E101: =IF(H100<=E100,H100+G101,$H$10) -> 0 | F101: =E101-G101 -> 0 | G101: =C101*(D101/365)*30 -> 0 | H101: =IF((D101+G101-E101)<0,0,D101+G101-E101) -> 0 | O101: =IF(H101=0,B101,"n.a.") -> 82
B102: =B101+1 -> 83 | C102: =IF(D102>0,$F$7,0) -> 0 | D102: =H101 -> 0 | E102: =IF(H101<=E101,H101+G102,$H$10) -> 0 | F102: =E102-G102 -> 0 | G102: =C102*(D102/365)*30 -> 0 | H102: =IF((D102+G102-E102)<0,0,D102+G102-E102) -> 0 | O102: =IF(H102=0,B102,"n.a.") -> 83
...

Sheet ตาราง-HL-ตามมติ
B1: ตารางผ่อนชำระเบื้องต้น HL (อัตราดอกเบี้ยตามมติ)
B2: ชื่อ | C2: ='1.ลดดอกเบี้ย'!C3 -> 0 | G2: ผ่อนชำระ
B3: App No | C3: ='1.ลดดอกเบี้ย'!C4 -> 0 | F3: อัตราดอกเบี้ย | G3: {='1.ลดดอกเบี้ย'!C26:D26} -> 0 | H3: 0
B4: วงเงิน | C4: ='2.นำเสนอดอกเบี้ย'!G14 -> 0 | D4: บาท | E4: ปีที่ 1 | F4: ='2.นำเสนอดอกเบี้ย'!H3 -> 0 | G4: ='1.ลดดอกเบี้ย'!C28 -> 0
B5: ระยะเวลา | C5: ='1.ลดดอกเบี้ย'!C9 -> 0 | D5: ปี | E5: ปีที่ 2 | F5: ='2.นำเสนอดอกเบี้ย'!H4 -> 0 | G5: ='1.ลดดอกเบี้ย'!C29 -> 0 | H5: =SUM(I6:I10)/#REF! -> #REF!
E6: ปีที่ 3 | F6: ='2.นำเสนอดอกเบี้ย'!H5 -> 0 | G6: ='1.ลดดอกเบี้ย'!C30 -> 0 | H6: =F4*12 -> 0
C7: Buffer | D7: 0.01 | E7: ปีที่ 4+ | F7: ='2.นำเสนอดอกเบี้ย'!H6 -> 0 | G7: ='1.ลดดอกเบี้ย'!C31 -> 0 | H7: =F5*12 -> 0
H8: =F6*12 -> 0
H9: =F7*12 -> 0
F10: Int. Yr. 5+ | G10: =F7 -> 0 | H10: =IF(G3="เท่ากันทุกเดือน",'1.ลดดอกเบี้ย'!#REF!,'1.ลดดอกเบี้ย'!C31) -> 0 | I10: =G10*(#REF!-48) -> #REF!
D11: =12*3 -> 36 | E11: =12*5 -> 60 | F11: =12*7 -> 84 | G11: =12*10 -> 120 | H11: =12*30 -> 360 | I11: =12*15 -> 180
D12: 3 Yrs. | E12: 5 Yrs. | F12: 7 Yrs. | G12: 10 Yrs. | H12: 30 Yrs. | I12: 15 Yrs
B13: Total Int. | D13: =SUM($G$20:$G$55) -> 0 | E13: =SUM($G$20:$G$79) -> 0 | F13: =SUM($G$20:$G$103) -> 0 | G13: =SUM($G$20:$G$139) -> 0 | H13: =SUM($G$20:$G$379) -> 0 | I13: =SUM($G$20:$G$199) -> 0
B14: Average O/S | D14: =AVERAGE($D$20:$D$55) -> 0 | E14: =AVERAGE($D$20:$D$79) -> 0 | F14: =AVERAGE($D$20:$D$103) -> 0 | G14: =AVERAGE($D$20:$D$139) -> 0 | H14: =AVERAGE($D$20:$D$379) -> 0 | I14: =AVERAGE($D$20:$D$199) -> 0
B15: EIR | D15: =D13/D14/(D11/12) -> #DIV/0! | E15: =E13/E14/(E11/12) -> #DIV/0! | F15: =F13/F14/(F11/12) -> #DIV/0! | G15: =G13/G14/(G11/12) -> #DIV/0! | H15: =H13/H14/(H11/12) -> #DIV/0! | I15: =I13/I14/(I11/12) -> #DIV/0!
B17: Average | D17: =AVERAGE($C$20:$C$55) -> 0 | E17: =AVERAGE($C$20:$C$79) -> 0 | F17: =AVERAGE($C$20:$C$103) -> 0 | G17: =AVERAGE($C$20:$C$139) -> 0 | H17: =AVERAGE($C$20:$C$379) -> 0 | I17: =AVERAGE(C20:C199) -> 0
B19: เดือน | C19: อัตราดอกเบี้ย | D19: ยอดคงค้าง | E19: ยอดผ่อนชำระ | F19: ยอดเงินต้น | G19: ยอดดอกเบี้ย | H19: ยอดคงค้าง | I19: LTV | O19: Tenor
B20: 1 | C20: =IF(D20>0,$F$4,0) -> 0 | D20: =C4 -> 0 | E20: =G4 -> 0 | F20: =E20-G20 -> 0 | G20: =C20*(D20/365)*30 -> 0 | H20: =IF((D20+G20-E20)<0,0,D20+G20-E20) -> 0 | O20: =IF(H20=0,B20,"n.a.") -> 1
B21: =B20+1 -> 2 | C21: =IF(D21>0,$F$4,0) -> 0 | D21: =H20 -> 0 | E21: =IF(H20<=E20,H20+G21,$G$4) -> 0 | F21: =E21-G21 -> 0 | G21: =C21*(D21/365)*30 -> 0 | H21: =IF((D21+G21-E21)<0,0,D21+G21-E21) -> 0 | O21: =IF(H21=0,B21,"n.a.") -> 2
B22: =B21+1 -> 3 | C22: =IF(D22>0,$F$4,0) -> 0 | D22: =H21 -> 0 | E22: =IF(H21<=E21,H21+G22,$G$4) -> 0 | F22: =E22-G22 -> 0 | G22: =C22*(D22/365)*30 -> 0 | H22: =IF((D22+G22-E22)<0,0,D22+G22-E22) -> 0 | O22: =IF(H22=0,B22,"n.a.") -> 3
B23: =B22+1 -> 4 | C23: =IF(D23>0,$F$4,0) -> 0 | D23: =H22 -> 0 | E23: =IF(H22<=E22,H22+G23,$G$4) -> 0 | F23: =E23-G23 -> 0 | G23: =C23*(D23/365)*30 -> 0 | H23: =IF((D23+G23-E23)<0,0,D23+G23-E23) -> 0 | O23: =IF(H23=0,B23,"n.a.") -> 4
B24: =B23+1 -> 5 | C24: =IF(D24>0,$F$4,0) -> 0 | D24: =H23 -> 0 | E24: =IF(H23<=E23,H23+G24,$G$4) -> 0 | F24: =E24-G24 -> 0 | G24: =C24*(D24/365)*30 -> 0 | H24: =IF((D24+G24-E24)<0,0,D24+G24-E24) -> 0 | O24: =IF(H24=0,B24,"n.a.") -> 5
B25: =B24+1 -> 6 | C25: =IF(D25>0,$F$4,0) -> 0 | D25: =H24 -> 0 | E25: =IF(H24<=E24,H24+G25,$G$4) -> 0 | F25: =E25-G25 -> 0 | G25: =C25*(D25/365)*30 -> 0 | H25: =IF((D25+G25-E25)<0,0,D25+G25-E25) -> 0 | O25: =IF(H25=0,B25,"n.a.") -> 6
B26: =B25+1 -> 7 | C26: =IF(D26>0,$F$4,0) -> 0 | D26: =H25 -> 0 | E26: =IF(H25<=E25,H25+G26,$G$4) -> 0 | F26: =E26-G26 -> 0 | G26: =C26*(D26/365)*30 -> 0 | H26: =IF((D26+G26-E26)<0,0,D26+G26-E26) -> 0 | O26: =IF(H26=0,B26,"n.a.") -> 7
B27: =B26+1 -> 8 | C27: =IF(D27>0,$F$4,0) -> 0 | D27: =H26 -> 0 | E27: =IF(H26<=E26,H26+G27,$G$4) -> 0 | F27: =E27-G27 -> 0 | G27: =C27*(D27/365)*30 -> 0 | H27: =IF((D27+G27-E27)<0,0,D27+G27-E27) -> 0 | O27: =IF(H27=0,B27,"n.a.") -> 8
B28: =B27+1 -> 9 | C28: =IF(D28>0,$F$4,0) -> 0 | D28: =H27 -> 0 | E28: =IF(H27<=E27,H27+G28,$G$4) -> 0 | F28: =E28-G28 -> 0 | G28: =C28*(D28/365)*30 -> 0 | H28: =IF((D28+G28-E28)<0,0,D28+G28-E28) -> 0 | O28: =IF(H28=0,B28,"n.a.") -> 9
B29: =B28+1 -> 10 | C29: =IF(D29>0,$F$4,0) -> 0 | D29: =H28 -> 0 | E29: =IF(H28<=E28,H28+G29,$G$4) -> 0 | F29: =E29-G29 -> 0 | G29: =C29*(D29/365)*30 -> 0 | H29: =IF((D29+G29-E29)<0,0,D29+G29-E29) -> 0 | O29: =IF(H29=0,B29,"n.a.") -> 10
B30: =B29+1 -> 11 | C30: =IF(D30>0,$F$4,0) -> 0 | D30: =H29 -> 0 | E30: =IF(H29<=E29,H29+G30,$G$4) -> 0 | F30: =E30-G30 -> 0 | G30: =C30*(D30/365)*30 -> 0 | H30: =IF((D30+G30-E30)<0,0,D30+G30-E30) -> 0 | O30: =IF(H30=0,B30,"n.a.") -> 11
B31: =B30+1 -> 12 | C31: =IF(D31>0,$F$4,0) -> 0 | D31: =H30 -> 0 | E31: =IF(H30<=E30,H30+G31,$G$4) -> 0 | F31: =E31-G31 -> 0 | G31: =C31*(D31/365)*30 -> 0 | H31: =IF((D31+G31-E31)<0,0,D31+G31-E31) -> 0 | I31: =H31/$D$5 -> #VALUE! | O31: =IF(H31=0,B31,"n.a.") -> 12
B32: =B31+1 -> 13 | C32: =IF(D32>0,$F$5,0) -> 0 | D32: =H31 -> 0 | E32: =IF(H31<=E31,H31+G32,$G$5) -> 0 | F32: =E32-G32 -> 0 | G32: =C32*(D32/365)*30 -> 0 | H32: =IF((D32+G32-E32)<0,0,D32+G32-E32) -> 0 | O32: =IF(H32=0,B32,"n.a.") -> 13
B33: =B32+1 -> 14 | C33: =IF(D33>0,$F$5,0) -> 0 | D33: =H32 -> 0 | E33: =IF(H32<=E32,H32+G33,$G$5) -> 0 | F33: =E33-G33 -> 0 | G33: =C33*(D33/365)*30 -> 0 | H33: =IF((D33+G33-E33)<0,0,D33+G33-E33) -> 0 | O33: =IF(H33=0,B33,"n.a.") -> 14
B34: =B33+1 -> 15 | C34: =IF(D34>0,$F$5,0) -> 0 | D34: =H33 -> 0 | E34: =IF(H33<=E33,H33+G34,$G$5) -> 0 | F34: =E34-G34 -> 0 | G34: =C34*(D34/365)*30 -> 0 | H34: =IF((D34+G34-E34)<0,0,D34+G34-E34) -> 0 | O34: =IF(H34=0,B34,"n.a.") -> 15
B35: =B34+1 -> 16 | C35: =IF(D35>0,$F$5,0) -> 0 | D35: =H34 -> 0 | E35: =IF(H34<=E34,H34+G35,$G$5) -> 0 | F35: =E35-G35 -> 0 | G35: =C35*(D35/365)*30 -> 0 | H35: =IF((D35+G35-E35)<0,0,D35+G35-E35) -> 0 | O35: =IF(H35=0,B35,"n.a.") -> 16
B36: =B35+1 -> 17 | C36: =IF(D36>0,$F$5,0) -> 0 | D36: =H35 -> 0 | E36: =IF(H35<=E35,H35+G36,$G$5) -> 0 | F36: =E36-G36 -> 0 | G36: =C36*(D36/365)*30 -> 0 | H36: =IF((D36+G36-E36)<0,0,D36+G36-E36) -> 0 | O36: =IF(H36=0,B36,"n.a.") -> 17
B37: =B36+1 -> 18 | C37: =IF(D37>0,$F$5,0) -> 0 | D37: =H36 -> 0 | E37: =IF(H36<=E36,H36+G37,$G$5) -> 0 | F37: =E37-G37 -> 0 | G37: =C37*(D37/365)*30 -> 0 | H37: =IF((D37+G37-E37)<0,0,D37+G37-E37) -> 0 | O37: =IF(H37=0,B37,"n.a.") -> 18
B38: =B37+1 -> 19 | C38: =IF(D38>0,$F$5,0) -> 0 | D38: =H37 -> 0 | E38: =IF(H37<=E37,H37+G38,$G$5) -> 0 | F38: =E38-G38 -> 0 | G38: =C38*(D38/365)*30 -> 0 | H38: =IF((D38+G38-E38)<0,0,D38+G38-E38) -> 0 | O38: =IF(H38=0,B38,"n.a.") -> 19
B39: =B38+1 -> 20 | C39: =IF(D39>0,$F$5,0) -> 0 | D39: =H38 -> 0 | E39: =IF(H38<=E38,H38+G39,$G$5) -> 0 | F39: =E39-G39 -> 0 | G39: =C39*(D39/365)*30 -> 0 | H39: =IF((D39+G39-E39)<0,0,D39+G39-E39) -> 0 | O39: =IF(H39=0,B39,"n.a.") -> 20
B40: =B39+1 -> 21 | C40: =IF(D40>0,$F$5,0) -> 0 | D40: =H39 -> 0 | E40: =IF(H39<=E39,H39+G40,$G$5) -> 0 | F40: =E40-G40 -> 0 | G40: =C40*(D40/365)*30 -> 0 | H40: =IF((D40+G40-E40)<0,0,D40+G40-E40) -> 0 | O40: =IF(H40=0,B40,"n.a.") -> 21
B41: =B40+1 -> 22 | C41: =IF(D41>0,$F$5,0) -> 0 | D41: =H40 -> 0 | E41: =IF(H40<=E40,H40+G41,$G$5) -> 0 | F41: =E41-G41 -> 0 | G41: =C41*(D41/365)*30 -> 0 | H41: =IF((D41+G41-E41)<0,0,D41+G41-E41) -> 0 | O41: =IF(H41=0,B41,"n.a.") -> 22
B42: =B41+1 -> 23 | C42: =IF(D42>0,$F$5,0) -> 0 | D42: =H41 -> 0 | E42: =IF(H41<=E41,H41+G42,$G$5) -> 0 | F42: =E42-G42 -> 0 | G42: =C42*(D42/365)*30 -> 0 | H42: =IF((D42+G42-E42)<0,0,D42+G42-E42) -> 0 | O42: =IF(H42=0,B42,"n.a.") -> 23
B43: =B42+1 -> 24 | C43: =IF(D43>0,$F$5,0) -> 0 | D43: =H42 -> 0 | E43: =IF(H42<=E42,H42+G43,$G$5) -> 0 | F43: =E43-G43 -> 0 | G43: =C43*(D43/365)*30 -> 0 | H43: =IF((D43+G43-E43)<0,0,D43+G43-E43) -> 0 | I43: =H43/$D$5 -> #VALUE! | O43: =IF(H43=0,B43,"n.a.") -> 24
B44: =B43+1 -> 25 | C44: =IF(D44>0,$F$6,0) -> 0 | D44: =H43 -> 0 | E44: =IF(H43<=E43,H43+G44,$G$6) -> 0 | F44: =E44-G44 -> 0 | G44: =C44*(D44/365)*30 -> 0 | H44: =IF((D44+G44-E44)<0,0,D44+G44-E44) -> 0 | O44: =IF(H44=0,B44,"n.a.") -> 25
B45: =B44+1 -> 26 | C45: =IF(D45>0,$F$6,0) -> 0 | D45: =H44 -> 0 | E45: =IF(H44<=E44,H44+G45,$G$6) -> 0 | F45: =E45-G45 -> 0 | G45: =C45*(D45/365)*30 -> 0 | H45: =IF((D45+G45-E45)<0,0,D45+G45-E45) -> 0 | O45: =IF(H45=0,B45,"n.a.") -> 26
B46: =B45+1 -> 27 | C46: =IF(D46>0,$F$6,0) -> 0 | D46: =H45 -> 0 | E46: =IF(H45<=E45,H45+G46,$G$6) -> 0 | F46: =E46-G46 -> 0 | G46: =C46*(D46/365)*30 -> 0 | H46: =IF((D46+G46-E46)<0,0,D46+G46-E46) -> 0 | O46: =IF(H46=0,B46,"n.a.") -> 27
B47: =B46+1 -> 28 | C47: =IF(D47>0,$F$6,0) -> 0 | D47: =H46 -> 0 | E47: =IF(H46<=E46,H46+G47,$G$6) -> 0 | F47: =E47-G47 -> 0 | G47: =C47*(D47/365)*30 -> 0 | H47: =IF((D47+G47-E47)<0,0,D47+G47-E47) -> 0 | O47: =IF(H47=0,B47,"n.a.") -> 28
B48: =B47+1 -> 29 | C48: =IF(D48>0,$F$6,0) -> 0 | D48: =H47 -> 0 | E48: =IF(H47<=E47,H47+G48,$G$6) -> 0 | F48: =E48-G48 -> 0 | G48: =C48*(D48/365)*30 -> 0 | H48: =IF((D48+G48-E48)<0,0,D48+G48-E48) -> 0 | O48: =IF(H48=0,B48,"n.a.") -> 29
B49: =B48+1 -> 30 | C49: =IF(D49>0,$F$6,0) -> 0 | D49: =H48 -> 0 | E49: =IF(H48<=E48,H48+G49,$G$6) -> 0 | F49: =E49-G49 -> 0 | G49: =C49*(D49/365)*30 -> 0 | H49: =IF((D49+G49-E49)<0,0,D49+G49-E49) -> 0 | O49: =IF(H49=0,B49,"n.a.") -> 30
B50: =B49+1 -> 31 | C50: =IF(D50>0,$F$6,0) -> 0 | D50: =H49 -> 0 | E50: =IF(H49<=E49,H49+G50,$G$6) -> 0 | F50: =E50-G50 -> 0 | G50: =C50*(D50/365)*30 -> 0 | H50: =IF((D50+G50-E50)<0,0,D50+G50-E50) -> 0 | O50: =IF(H50=0,B50,"n.a.") -> 31
B51: =B50+1 -> 32 | C51: =IF(D51>0,$F$6,0) -> 0 | D51: =H50 -> 0 | E51: =IF(H50<=E50,H50+G51,$G$6) -> 0 | F51: =E51-G51 -> 0 | G51: =C51*(D51/365)*30 -> 0 | H51: =IF((D51+G51-E51)<0,0,D51+G51-E51) -> 0 | O51: =IF(H51=0,B51,"n.a.") -> 32
B52: =B51+1 -> 33 | C52: =IF(D52>0,$F$6,0) -> 0 | D52: =H51 -> 0 | E52: =IF(H51<=E51,H51+G52,$G$6) -> 0 | F52: =E52-G52 -> 0 | G52: =C52*(D52/365)*30 -> 0 | H52: =IF((D52+G52-E52)<0,0,D52+G52-E52) -> 0 | O52: =IF(H52=0,B52,"n.a.") -> 33
B53: =B52+1 -> 34 | C53: =IF(D53>0,$F$6,0) -> 0 | D53: =H52 -> 0 | E53: =IF(H52<=E52,H52+G53,$G$6) -> 0 | F53: =E53-G53 -> 0 | G53: =C53*(D53/365)*30 -> 0 | H53: =IF((D53+G53-E53)<0,0,D53+G53-E53) -> 0 | O53: =IF(H53=0,B53,"n.a.") -> 34
B54: =B53+1 -> 35 | C54: =IF(D54>0,$F$6,0) -> 0 | D54: =H53 -> 0 | E54: =IF(H53<=E53,H53+G54,$G$6) -> 0 | F54: =E54-G54 -> 0 | G54: =C54*(D54/365)*30 -> 0 | H54: =IF((D54+G54-E54)<0,0,D54+G54-E54) -> 0 | O54: =IF(H54=0,B54,"n.a.") -> 35
B55: =B54+1 -> 36 | C55: =IF(D55>0,$F$6,0) -> 0 | D55: =H54 -> 0 | E55: =IF(H54<=E54,H54+G55,$G$6) -> 0 | F55: =E55-G55 -> 0 | G55: =C55*(D55/365)*30 -> 0 | H55: =IF((D55+G55-E55)<0,0,D55+G55-E55) -> 0 | I55: =H55/$D$5 -> #VALUE! | O55: =IF(H55=0,B55,"n.a.") -> 36
B56: =B55+1 -> 37 | C56: =IF(D56>0,$F$7,0) -> 0 | D56: =H55 -> 0 | E56: =IF(H55<=E55,H55+G56,$G$7) -> 0 | F56: =E56-G56 -> 0 | G56: =C56*(D56/365)*30 -> 0 | H56: =IF((D56+G56-E56)<0,0,D56+G56-E56) -> 0 | O56: =IF(H56=0,B56,"n.a.") -> 37
B57: =B56+1 -> 38 | C57: =IF(D57>0,$F$7,0) -> 0 | D57: =H56 -> 0 | E57: =IF(H56<=E56,H56+G57,$G$7) -> 0 | F57: =E57-G57 -> 0 | G57: =C57*(D57/365)*30 -> 0 | H57: =IF((D57+G57-E57)<0,0,D57+G57-E57) -> 0 | O57: =IF(H57=0,B57,"n.a.") -> 38
B58: =B57+1 -> 39 | C58: =IF(D58>0,$F$7,0) -> 0 | D58: =H57 -> 0 | E58: =IF(H57<=E57,H57+G58,$G$7) -> 0 | F58: =E58-G58 -> 0 | G58: =C58*(D58/365)*30 -> 0 | H58: =IF((D58+G58-E58)<0,0,D58+G58-E58) -> 0 | O58: =IF(H58=0,B58,"n.a.") -> 39
B59: =B58+1 -> 40 | C59: =IF(D59>0,$F$7,0) -> 0 | D59: =H58 -> 0 | E59: =IF(H58<=E58,H58+G59,$G$7) -> 0 | F59: =E59-G59 -> 0 | G59: =C59*(D59/365)*30 -> 0 | H59: =IF((D59+G59-E59)<0,0,D59+G59-E59) -> 0 | O59: =IF(H59=0,B59,"n.a.") -> 40
B60: =B59+1 -> 41 | C60: =IF(D60>0,$F$7,0) -> 0 | D60: =H59 -> 0 | E60: =IF(H59<=E59,H59+G60,$G$7) -> 0 | F60: =E60-G60 -> 0 | G60: =C60*(D60/365)*30 -> 0 | H60: =IF((D60+G60-E60)<0,0,D60+G60-E60) -> 0 | O60: =IF(H60=0,B60,"n.a.") -> 41
B61: =B60+1 -> 42 | C61: =IF(D61>0,$F$7,0) -> 0 | D61: =H60 -> 0 | E61: =IF(H60<=E60,H60+G61,$G$7) -> 0 | F61: =E61-G61 -> 0 | G61: =C61*(D61/365)*30 -> 0 | H61: =IF((D61+G61-E61)<0,0,D61+G61-E61) -> 0 | O61: =IF(H61=0,B61,"n.a.") -> 42
B62: =B61+1 -> 43 | C62: =IF(D62>0,$F$7,0) -> 0 | D62: =H61 -> 0 | E62: =IF(H61<=E61,H61+G62,$G$7) -> 0 | F62: =E62-G62 -> 0 | G62: =C62*(D62/365)*30 -> 0 | H62: =IF((D62+G62-E62)<0,0,D62+G62-E62) -> 0 | O62: =IF(H62=0,B62,"n.a.") -> 43
B63: =B62+1 -> 44 | C63: =IF(D63>0,$F$7,0) -> 0 | D63: =H62 -> 0 | E63: =IF(H62<=E62,H62+G63,$G$7) -> 0 | F63: =E63-G63 -> 0 | G63: =C63*(D63/365)*30 -> 0 | H63: =IF((D63+G63-E63)<0,0,D63+G63-E63) -> 0 | O63: =IF(H63=0,B63,"n.a.") -> 44
B64: =B63+1 -> 45 | C64: =IF(D64>0,$F$7,0) -> 0 | D64: =H63 -> 0 | E64: =IF(H63<=E63,H63+G64,$G$7) -> 0 | F64: =E64-G64 -> 0 | G64: =C64*(D64/365)*30 -> 0 | H64: =IF((D64+G64-E64)<0,0,D64+G64-E64) -> 0 | O64: =IF(H64=0,B64,"n.a.") -> 45
B65: =B64+1 -> 46 | C65: =IF(D65>0,$F$7,0) -> 0 | D65: =H64 -> 0 | E65: =IF(H64<=E64,H64+G65,$G$7) -> 0 | F65: =E65-G65 -> 0 | G65: =C65*(D65/365)*30 -> 0 | H65: =IF((D65+G65-E65)<0,0,D65+G65-E65) -> 0 | O65: =IF(H65=0,B65,"n.a.") -> 46
B66: =B65+1 -> 47 | C66: =IF(D66>0,$F$7,0) -> 0 | D66: =H65 -> 0 | E66: =IF(H65<=E65,H65+G66,$G$7) -> 0 | F66: =E66-G66 -> 0 | G66: =C66*(D66/365)*30 -> 0 | H66: =IF((D66+G66-E66)<0,0,D66+G66-E66) -> 0 | O66: =IF(H66=0,B66,"n.a.") -> 47
B67: =B66+1 -> 48 | C67: =IF(D67>0,$F$7,0) -> 0 | D67: =H66 -> 0 | E67: =IF(H66<=E66,H66+G67,$G$7) -> 0 | F67: =E67-G67 -> 0 | G67: =C67*(D67/365)*30 -> 0 | H67: =IF((D67+G67-E67)<0,0,D67+G67-E67) -> 0 | I67: =H67/$D$5 -> #VALUE! | O67: =IF(H67=0,B67,"n.a.") -> 48
B68: =B67+1 -> 49 | C68: =IF(D68>0,$F$7,0) -> 0 | D68: =H67 -> 0 | E68: =IF(H67<=E67,H67+G68,$H$10) -> 0 | F68: =E68-G68 -> 0 | G68: =C68*(D68/365)*30 -> 0 | H68: =IF((D68+G68-E68)<0,0,D68+G68-E68) -> 0 | O68: =IF(H68=0,B68,"n.a.") -> 49
B69: =B68+1 -> 50 | C69: =IF(D69>0,$F$7,0) -> 0 | D69: =H68 -> 0 | E69: =IF(H68<=E68,H68+G69,$H$10) -> 0 | F69: =E69-G69 -> 0 | G69: =C69*(D69/365)*30 -> 0 | H69: =IF((D69+G69-E69)<0,0,D69+G69-E69) -> 0 | O69: =IF(H69=0,B69,"n.a.") -> 50
B70: =B69+1 -> 51 | C70: =IF(D70>0,$F$7,0) -> 0 | D70: =H69 -> 0 | E70: =IF(H69<=E69,H69+G70,$H$10) -> 0 | F70: =E70-G70 -> 0 | G70: =C70*(D70/365)*30 -> 0 | H70: =IF((D70+G70-E70)<0,0,D70+G70-E70) -> 0 | O70: =IF(H70=0,B70,"n.a.") -> 51
B71: =B70+1 -> 52 | C71: =IF(D71>0,$F$7,0) -> 0 | D71: =H70 -> 0 | E71: =IF(H70<=E70,H70+G71,$H$10) -> 0 | F71: =E71-G71 -> 0 | G71: =C71*(D71/365)*30 -> 0 | H71: =IF((D71+G71-E71)<0,0,D71+G71-E71) -> 0 | O71: =IF(H71=0,B71,"n.a.") -> 52
B72: =B71+1 -> 53 | C72: =IF(D72>0,$F$7,0) -> 0 | D72: =H71 -> 0 | E72: =IF(H71<=E71,H71+G72,$H$10) -> 0 | F72: =E72-G72 -> 0 | G72: =C72*(D72/365)*30 -> 0 | H72: =IF((D72+G72-E72)<0,0,D72+G72-E72) -> 0 | O72: =IF(H72=0,B72,"n.a.") -> 53
B73: =B72+1 -> 54 | C73: =IF(D73>0,$F$7,0) -> 0 | D73: =H72 -> 0 | E73: =IF(H72<=E72,H72+G73,$H$10) -> 0 | F73: =E73-G73 -> 0 | G73: =C73*(D73/365)*30 -> 0 | H73: =IF((D73+G73-E73)<0,0,D73+G73-E73) -> 0 | O73: =IF(H73=0,B73,"n.a.") -> 54
B74: =B73+1 -> 55 | C74: =IF(D74>0,$F$7,0) -> 0 | D74: =H73 -> 0 | E74: =IF(H73<=E73,H73+G74,$H$10) -> 0 | F74: =E74-G74 -> 0 | G74: =C74*(D74/365)*30 -> 0 | H74: =IF((D74+G74-E74)<0,0,D74+G74-E74) -> 0 | O74: =IF(H74=0,B74,"n.a.") -> 55
B75: =B74+1 -> 56 | C75: =IF(D75>0,$F$7,0) -> 0 | D75: =H74 -> 0 | E75: =IF(H74<=E74,H74+G75,$H$10) -> 0 | F75: =E75-G75 -> 0 | G75: =C75*(D75/365)*30 -> 0 | H75: =IF((D75+G75-E75)<0,0,D75+G75-E75) -> 0 | O75: =IF(H75=0,B75,"n.a.") -> 56
B76: =B75+1 -> 57 | C76: =IF(D76>0,$F$7,0) -> 0 | D76: =H75 -> 0 | E76: =IF(H75<=E75,H75+G76,$H$10) -> 0 | F76: =E76-G76 -> 0 | G76: =C76*(D76/365)*30 -> 0 | H76: =IF((D76+G76-E76)<0,0,D76+G76-E76) -> 0 | O76: =IF(H76=0,B76,"n.a.") -> 57
B77: =B76+1 -> 58 | C77: =IF(D77>0,$F$7,0) -> 0 | D77: =H76 -> 0 | E77: =IF(H76<=E76,H76+G77,$H$10) -> 0 | F77: =E77-G77 -> 0 | G77: =C77*(D77/365)*30 -> 0 | H77: =IF((D77+G77-E77)<0,0,D77+G77-E77) -> 0 | O77: =IF(H77=0,B77,"n.a.") -> 58
B78: =B77+1 -> 59 | C78: =IF(D78>0,$F$7,0) -> 0 | D78: =H77 -> 0 | E78: =IF(H77<=E77,H77+G78,$H$10) -> 0 | F78: =E78-G78 -> 0 | G78: =C78*(D78/365)*30 -> 0 | H78: =IF((D78+G78-E78)<0,0,D78+G78-E78) -> 0 | O78: =IF(H78=0,B78,"n.a.") -> 59
B79: =B78+1 -> 60 | C79: =IF(D79>0,$F$7,0) -> 0 | D79: =H78 -> 0 | E79: =IF(H78<=E78,H78+G79,$H$10) -> 0 | F79: =E79-G79 -> 0 | G79: =C79*(D79/365)*30 -> 0 | H79: =IF((D79+G79-E79)<0,0,D79+G79-E79) -> 0 | I79: =H79/$D$5 -> #VALUE! | O79: =IF(H79=0,B79,"n.a.") -> 60
B80: =B79+1 -> 61 | C80: =IF(D80>0,$F$7,0) -> 0 | D80: =H79 -> 0 | E80: =IF(H79<=E79,H79+G80,$H$10) -> 0 | F80: =E80-G80 -> 0 | G80: =C80*(D80/365)*30 -> 0 | H80: =IF((D80+G80-E80)<0,0,D80+G80-E80) -> 0 | O80: =IF(H80=0,B80,"n.a.") -> 61
B81: =B80+1 -> 62 | C81: =IF(D81>0,$F$7,0) -> 0 | D81: =H80 -> 0 | E81: =IF(H80<=E80,H80+G81,$H$10) -> 0 | F81: =E81-G81 -> 0 | G81: =C81*(D81/365)*30 -> 0 | H81: =IF((D81+G81-E81)<0,0,D81+G81-E81) -> 0 | O81: =IF(H81=0,B81,"n.a.") -> 62
B82: =B81+1 -> 63 | C82: =IF(D82>0,$F$7,0) -> 0 | D82: =H81 -> 0 | E82: =IF(H81<=E81,H81+G82,$H$10) -> 0 | F82: =E82-G82 -> 0 | G82: =C82*(D82/365)*30 -> 0 | H82: =IF((D82+G82-E82)<0,0,D82+G82-E82) -> 0 | O82: =IF(H82=0,B82,"n.a.") -> 63
B83: =B82+1 -> 64 | C83: =IF(D83>0,$F$7,0) -> 0 | D83: =H82 -> 0 | E83: =IF(H82<=E82,H82+G83,$H$10) -> 0 | F83: =E83-G83 -> 0 | G83: =C83*(D83/365)*30 -> 0 | H83: =IF((D83+G83-E83)<0,0,D83+G83-E83) -> 0 | O83: =IF(H83=0,B83,"n.a.") -> 64
B84: =B83+1 -> 65 | C84: =IF(D84>0,$F$7,0) -> 0 | D84: =H83 -> 0 | E84: =IF(H83<=E83,H83+G84,$H$10) -> 0 | F84: =E84-G84 -> 0 | G84: =C84*(D84/365)*30 -> 0 | H84: =IF((D84+G84-E84)<0,0,D84+G84-E84) -> 0 | O84: =IF(H84=0,B84,"n.a.") -> 65
B85: =B84+1 -> 66 | C85: =IF(D85>0,$F$7,0) -> 0 | D85: =H84 -> 0 | E85: =IF(H84<=E84,H84+G85,$H$10) -> 0 | F85: =E85-G85 -> 0 | G85: =C85*(D85/365)*30 -> 0 | H85: =IF((D85+G85-E85)<0,0,D85+G85-E85) -> 0 | O85: =IF(H85=0,B85,"n.a.") -> 66
B86: =B85+1 -> 67 | C86: =IF(D86>0,$F$7,0) -> 0 | D86: =H85 -> 0 | E86: =IF(H85<=E85,H85+G86,$H$10) -> 0 | F86: =E86-G86 -> 0 | G86: =C86*(D86/365)*30 -> 0 | H86: =IF((D86+G86-E86)<0,0,D86+G86-E86) -> 0 | O86: =IF(H86=0,B86,"n.a.") -> 67
B87: =B86+1 -> 68 | C87: =IF(D87>0,$F$7,0) -> 0 | D87: =H86 -> 0 | E87: =IF(H86<=E86,H86+G87,$H$10) -> 0 | F87: =E87-G87 -> 0 | G87: =C87*(D87/365)*30 -> 0 | H87: =IF((D87+G87-E87)<0,0,D87+G87-E87) -> 0 | O87: =IF(H87=0,B87,"n.a.") -> 68
B88: =B87+1 -> 69 | C88: =IF(D88>0,$F$7,0) -> 0 | D88: =H87 -> 0 | E88: =IF(H87<=E87,H87+G88,$H$10) -> 0 | F88: =E88-G88 -> 0 | G88: =C88*(D88/365)*30 -> 0 | H88: =IF((D88+G88-E88)<0,0,D88+G88-E88) -> 0 | O88: =IF(H88=0,B88,"n.a.") -> 69
B89: =B88+1 -> 70 | C89: =IF(D89>0,$F$7,0) -> 0 | D89: =H88 -> 0 | E89: =IF(H88<=E88,H88+G89,$H$10) -> 0 | F89: =E89-G89 -> 0 | G89: =C89*(D89/365)*30 -> 0 | H89: =IF((D89+G89-E89)<0,0,D89+G89-E89) -> 0 | O89: =IF(H89=0,B89,"n.a.") -> 70
B90: =B89+1 -> 71 | C90: =IF(D90>0,$F$7,0) -> 0 | D90: =H89 -> 0 | E90: =IF(H89<=E89,H89+G90,$H$10) -> 0 | F90: =E90-G90 -> 0 | G90: =C90*(D90/365)*30 -> 0 | H90: =IF((D90+G90-E90)<0,0,D90+G90-E90) -> 0 | O90: =IF(H90=0,B90,"n.a.") -> 71
B91: =B90+1 -> 72 | C91: =IF(D91>0,$F$7,0) -> 0 | D91: =H90 -> 0 | E91: =IF(H90<=E90,H90+G91,$H$10) -> 0 | F91: =E91-G91 -> 0 | G91: =C91*(D91/365)*30 -> 0 | H91: =IF((D91+G91-E91)<0,0,D91+G91-E91) -> 0 | I91: =H91/$D$5 -> #VALUE! | O91: =IF(H91=0,B91,"n.a.") -> 72
B92: =B91+1 -> 73 | C92: =IF(D92>0,$F$7,0) -> 0 | D92: =H91 -> 0 | E92: =IF(H91<=E91,H91+G92,$H$10) -> 0 | F92: =E92-G92 -> 0 | G92: =C92*(D92/365)*30 -> 0 | H92: =IF((D92+G92-E92)<0,0,D92+G92-E92) -> 0 | O92: =IF(H92=0,B92,"n.a.") -> 73
B93: =B92+1 -> 74 | C93: =IF(D93>0,$F$7,0) -> 0 | D93: =H92 -> 0 | E93: =IF(H92<=E92,H92+G93,$H$10) -> 0 | F93: =E93-G93 -> 0 | G93: =C93*(D93/365)*30 -> 0 | H93: =IF((D93+G93-E93)<0,0,D93+G93-E93) -> 0 | O93: =IF(H93=0,B93,"n.a.") -> 74
B94: =B93+1 -> 75 | C94: =IF(D94>0,$F$7,0) -> 0 | D94: =H93 -> 0 | E94: =IF(H93<=E93,H93+G94,$H$10) -> 0 | F94: =E94-G94 -> 0 | G94: =C94*(D94/365)*30 -> 0 | H94: =IF((D94+G94-E94)<0,0,D94+G94-E94) -> 0 | O94: =IF(H94=0,B94,"n.a.") -> 75
B95: =B94+1 -> 76 | C95: =IF(D95>0,$F$7,0) -> 0 | D95: =H94 -> 0 | E95: =IF(H94<=E94,H94+G95,$H$10) -> 0 | F95: =E95-G95 -> 0 | G95: =C95*(D95/365)*30 -> 0 | H95: =IF((D95+G95-E95)<0,0,D95+G95-E95) -> 0 | O95: =IF(H95=0,B95,"n.a.") -> 76
B96: =B95+1 -> 77 | C96: =IF(D96>0,$F$7,0) -> 0 | D96: =H95 -> 0 | E96: =IF(H95<=E95,H95+G96,$H$10) -> 0 | F96: =E96-G96 -> 0 | G96: =C96*(D96/365)*30 -> 0 | H96: =IF((D96+G96-E96)<0,0,D96+G96-E96) -> 0 | O96: =IF(H96=0,B96,"n.a.") -> 77
B97: =B96+1 -> 78 | C97: =IF(D97>0,$F$7,0) -> 0 | D97: =H96 -> 0 | E97: =IF(H96<=E96,H96+G97,$H$10) -> 0 | F97: =E97-G97 -> 0 | G97: =C97*(D97/365)*30 -> 0 | H97: =IF((D97+G97-E97)<0,0,D97+G97-E97) -> 0 | O97: =IF(H97=0,B97,"n.a.") -> 78
B98: =B97+1 -> 79 | C98: =IF(D98>0,$F$7,0) -> 0 | D98: =H97 -> 0 | E98: =IF(H97<=E97,H97+G98,$H$10) -> 0 | F98: =E98-G98 -> 0 | G98: =C98*(D98/365)*30 -> 0 | H98: =IF((D98+G98-E98)<0,0,D98+G98-E98) -> 0 | O98: =IF(H98=0,B98,"n.a.") -> 79
B99: =B98+1 -> 80 | C99: =IF(D99>0,$F$7,0) -> 0 | D99: =H98 -> 0 | E99: =IF(H98<=E98,H98+G99,$H$10) -> 0 | F99: =E99-G99 -> 0 | G99: =C99*(D99/365)*30 -> 0 | H99: =IF((D99+G99-E99)<0,0,D99+G99-E99) -> 0 | O99: =IF(H99=0,B99,"n.a.") -> 80
B100: =B99+1 -> 81 | C100: =IF(D100>0,$F$7,0) -> 0 | D100: =H99 -> 0 | E100: =IF(H99<=E99,H99+G100,$H$10) -> 0 | F100: =E100-G100 -> 0 | G100: =C100*(D100/365)*30 -> 0 | H100: =IF((D100+G100-E100)<0,0,D100+G100-E100) -> 0 | O100: =IF(H100=0,B100,"n.a.") -> 81
B101: =B100+1 -> 82 | C101: =IF(D101>0,$F$7,0) -> 0 | D101: =H100 -> 0 | E101: =IF(H100<=E100,H100+G101,$H$10) -> 0 | F101: =E101-G101 -> 0 | G101: =C101*(D101/365)*30 -> 0 | H101: =IF((D101+G101-E101)<0,0,D101+G101-E101) -> 0 | O101: =IF(H101=0,B101,"n.a.") -> 82
B102: =B101+1 -> 83 | C102: =IF(D102>0,$F$7,0) -> 0 | D102: =H101 -> 0 | E102: =IF(H101<=E101,H101+G102,$H$10) -> 0 | F102: =E102-G102 -> 0 | G102: =C102*(D102/365)*30 -> 0 | H102: =IF((D102+G102-E102)<0,0,D102+G102-E102) -> 0 | O102: =IF(H102=0,B102,"n.a.") -> 83
...

Sheet ตาราง-MP-ตามมติ
B1: ตารางผ่อนชำระเบื้องต้น MP (อัตราดอกเบี้ยตามมติ)
B2: ชื่อ | C2: ='1.ลดดอกเบี้ย'!C3 -> 0 | G2: ผ่อนชำระ
B3: App No | C3: ='1.ลดดอกเบี้ย'!C4 -> 0 | F3: อัตราดอกเบี้ย | G3: เท่ากันทุกเดือน
B4: วงเงิน | C4: ='1.ลดดอกเบี้ย'!E8 -> 0 | D4: บาท | E4: ปีที่ 1 | F4: ='2.นำเสนอดอกเบี้ย'!H23 -> 0 | G4: ='1.ลดดอกเบี้ย'!E28 -> 0
B5: ระยะเวลา | C5: ='1.ลดดอกเบี้ย'!E9 -> 0 | D5: ปี | E5: ปีที่ 2 | F5: ='2.นำเสนอดอกเบี้ย'!H24 -> 0 | G5: ='1.ลดดอกเบี้ย'!E29 -> 0 | H5: =SUM(I6:I10)/#REF! -> #REF!
E6: ปีที่ 3 | F6: ='2.นำเสนอดอกเบี้ย'!H25 -> 0 | G6: ='1.ลดดอกเบี้ย'!E30 -> 0 | H6: =F4*12 -> 0
C7: Buffer | D7: 0.01 | E7: ปีที่ 4+ | F7: ='2.นำเสนอดอกเบี้ย'!H26 -> 0 | G7: ='1.ลดดอกเบี้ย'!E31 -> 0 | H7: =F5*12 -> 0
H8: =F6*12 -> 0
H9: =F7*12 -> 0
F10: Int. Yr. 5+ | G10: =F7 -> 0 | H10: =G7 -> 0 | I10: =G10*(#REF!-48) -> #REF!
D11: =12*3 -> 36 | E11: =12*5 -> 60 | F11: =12*7 -> 84 | G11: =12*10 -> 120 | H11: =12*30 -> 360 | I11: =12*15 -> 180
D12: 3 Yrs. | E12: 5 Yrs. | F12: 7 Yrs. | G12: 10 Yrs. | H12: 30 Yrs. | I12: 15 Yrs
B13: Total Int. | D13: =SUM($G$20:$G$55) -> 0 | E13: =SUM($G$20:$G$79) -> 0 | F13: =SUM($G$20:$G$103) -> 0 | G13: =SUM($G$20:$G$139) -> 0 | H13: =SUM($G$20:$G$379) -> 0 | I13: =SUM($G$20:$G$199) -> 0
B14: Average O/S | D14: =AVERAGE($D$20:$D$55) -> 0 | E14: =AVERAGE($D$20:$D$79) -> 0 | F14: =AVERAGE($D$20:$D$103) -> 0 | G14: =AVERAGE($D$20:$D$139) -> 0 | H14: =AVERAGE($D$20:$D$379) -> 0 | I14: =AVERAGE($D$20:$D$199) -> 0
B15: EIR | D15: =D13/D14/(D11/12) -> #DIV/0! | E15: =E13/E14/(E11/12) -> #DIV/0! | F15: =F13/F14/(F11/12) -> #DIV/0! | G15: =G13/G14/(G11/12) -> #DIV/0! | H15: =H13/H14/(H11/12) -> #DIV/0! | I15: =I13/I14/(I11/12) -> #DIV/0!
B17: Average | D17: =AVERAGE($C$20:$C$55) -> 0 | E17: =AVERAGE($C$20:$C$79) -> 0 | F17: =AVERAGE($C$20:$C$103) -> 0 | G17: =AVERAGE($C$20:$C$139) -> 0 | H17: =AVERAGE($C$20:$C$379) -> 0 | I17: =AVERAGE(C20:C199) -> 0
B19: เดือน | C19: อัตราดอกเบี้ย | D19: ยอดคงค้าง | E19: ยอดผ่อนชำระ | F19: ยอดเงินต้น | G19: ยอดดอกเบี้ย | H19: ยอดคงค้าง | I19: LTV | O19: Tenor
B20: 1 | C20: =IF(D20>0,$F$4,0) -> 0 | D20: =C4 -> 0 | E20: =G4 -> 0 | F20: =E20-G20 -> 0 | G20: =C20*(D20/365)*30 -> 0 | H20: =IF((D20+G20-E20)<0,0,D20+G20-E20) -> 0 | O20: =IF(H20=0,B20,"n.a.") -> 1
B21: =B20+1 -> 2 | C21: =IF(D21>0,$F$4,0) -> 0 | D21: =H20 -> 0 | E21: =IF(H20<=E20,H20+G21,$G$4) -> 0 | F21: =E21-G21 -> 0 | G21: =C21*(D21/365)*30 -> 0 | H21: =IF((D21+G21-E21)<0,0,D21+G21-E21) -> 0 | O21: =IF(H21=0,B21,"n.a.") -> 2
B22: =B21+1 -> 3 | C22: =IF(D22>0,$F$4,0) -> 0 | D22: =H21 -> 0 | E22: =IF(H21<=E21,H21+G22,$G$4) -> 0 | F22: =E22-G22 -> 0 | G22: =C22*(D22/365)*30 -> 0 | H22: =IF((D22+G22-E22)<0,0,D22+G22-E22) -> 0 | O22: =IF(H22=0,B22,"n.a.") -> 3
B23: =B22+1 -> 4 | C23: =IF(D23>0,$F$4,0) -> 0 | D23: =H22 -> 0 | E23: =IF(H22<=E22,H22+G23,$G$4) -> 0 | F23: =E23-G23 -> 0 | G23: =C23*(D23/365)*30 -> 0 | H23: =IF((D23+G23-E23)<0,0,D23+G23-E23) -> 0 | O23: =IF(H23=0,B23,"n.a.") -> 4
B24: =B23+1 -> 5 | C24: =IF(D24>0,$F$4,0) -> 0 | D24: =H23 -> 0 | E24: =IF(H23<=E23,H23+G24,$G$4) -> 0 | F24: =E24-G24 -> 0 | G24: =C24*(D24/365)*30 -> 0 | H24: =IF((D24+G24-E24)<0,0,D24+G24-E24) -> 0 | O24: =IF(H24=0,B24,"n.a.") -> 5
B25: =B24+1 -> 6 | C25: =IF(D25>0,$F$4,0) -> 0 | D25: =H24 -> 0 | E25: =IF(H24<=E24,H24+G25,$G$4) -> 0 | F25: =E25-G25 -> 0 | G25: =C25*(D25/365)*30 -> 0 | H25: =IF((D25+G25-E25)<0,0,D25+G25-E25) -> 0 | O25: =IF(H25=0,B25,"n.a.") -> 6
B26: =B25+1 -> 7 | C26: =IF(D26>0,$F$4,0) -> 0 | D26: =H25 -> 0 | E26: =IF(H25<=E25,H25+G26,$G$4) -> 0 | F26: =E26-G26 -> 0 | G26: =C26*(D26/365)*30 -> 0 | H26: =IF((D26+G26-E26)<0,0,D26+G26-E26) -> 0 | O26: =IF(H26=0,B26,"n.a.") -> 7
B27: =B26+1 -> 8 | C27: =IF(D27>0,$F$4,0) -> 0 | D27: =H26 -> 0 | E27: =IF(H26<=E26,H26+G27,$G$4) -> 0 | F27: =E27-G27 -> 0 | G27: =C27*(D27/365)*30 -> 0 | H27: =IF((D27+G27-E27)<0,0,D27+G27-E27) -> 0 | O27: =IF(H27=0,B27,"n.a.") -> 8
B28: =B27+1 -> 9 | C28: =IF(D28>0,$F$4,0) -> 0 | D28: =H27 -> 0 | E28: =IF(H27<=E27,H27+G28,$G$4) -> 0 | F28: =E28-G28 -> 0 | G28: =C28*(D28/365)*30 -> 0 | H28: =IF((D28+G28-E28)<0,0,D28+G28-E28) -> 0 | O28: =IF(H28=0,B28,"n.a.") -> 9
B29: =B28+1 -> 10 | C29: =IF(D29>0,$F$4,0) -> 0 | D29: =H28 -> 0 | E29: =IF(H28<=E28,H28+G29,$G$4) -> 0 | F29: =E29-G29 -> 0 | G29: =C29*(D29/365)*30 -> 0 | H29: =IF((D29+G29-E29)<0,0,D29+G29-E29) -> 0 | O29: =IF(H29=0,B29,"n.a.") -> 10
B30: =B29+1 -> 11 | C30: =IF(D30>0,$F$4,0) -> 0 | D30: =H29 -> 0 | E30: =IF(H29<=E29,H29+G30,$G$4) -> 0 | F30: =E30-G30 -> 0 | G30: =C30*(D30/365)*30 -> 0 | H30: =IF((D30+G30-E30)<0,0,D30+G30-E30) -> 0 | O30: =IF(H30=0,B30,"n.a.") -> 11
B31: =B30+1 -> 12 | C31: =IF(D31>0,$F$4,0) -> 0 | D31: =H30 -> 0 | E31: =IF(H30<=E30,H30+G31,$G$4) -> 0 | F31: =E31-G31 -> 0 | G31: =C31*(D31/365)*30 -> 0 | H31: =IF((D31+G31-E31)<0,0,D31+G31-E31) -> 0 | I31: =H31/$D$5 -> #VALUE! | O31: =IF(H31=0,B31,"n.a.") -> 12
B32: =B31+1 -> 13 | C32: =IF(D32>0,$F$5,0) -> 0 | D32: =H31 -> 0 | E32: =IF(H31<=E31,H31+G32,$G$5) -> 0 | F32: =E32-G32 -> 0 | G32: =C32*(D32/365)*30 -> 0 | H32: =IF((D32+G32-E32)<0,0,D32+G32-E32) -> 0 | O32: =IF(H32=0,B32,"n.a.") -> 13
B33: =B32+1 -> 14 | C33: =IF(D33>0,$F$5,0) -> 0 | D33: =H32 -> 0 | E33: =IF(H32<=E32,H32+G33,$G$5) -> 0 | F33: =E33-G33 -> 0 | G33: =C33*(D33/365)*30 -> 0 | H33: =IF((D33+G33-E33)<0,0,D33+G33-E33) -> 0 | O33: =IF(H33=0,B33,"n.a.") -> 14
B34: =B33+1 -> 15 | C34: =IF(D34>0,$F$5,0) -> 0 | D34: =H33 -> 0 | E34: =IF(H33<=E33,H33+G34,$G$5) -> 0 | F34: =E34-G34 -> 0 | G34: =C34*(D34/365)*30 -> 0 | H34: =IF((D34+G34-E34)<0,0,D34+G34-E34) -> 0 | O34: =IF(H34=0,B34,"n.a.") -> 15
B35: =B34+1 -> 16 | C35: =IF(D35>0,$F$5,0) -> 0 | D35: =H34 -> 0 | E35: =IF(H34<=E34,H34+G35,$G$5) -> 0 | F35: =E35-G35 -> 0 | G35: =C35*(D35/365)*30 -> 0 | H35: =IF((D35+G35-E35)<0,0,D35+G35-E35) -> 0 | O35: =IF(H35=0,B35,"n.a.") -> 16
B36: =B35+1 -> 17 | C36: =IF(D36>0,$F$5,0) -> 0 | D36: =H35 -> 0 | E36: =IF(H35<=E35,H35+G36,$G$5) -> 0 | F36: =E36-G36 -> 0 | G36: =C36*(D36/365)*30 -> 0 | H36: =IF((D36+G36-E36)<0,0,D36+G36-E36) -> 0 | O36: =IF(H36=0,B36,"n.a.") -> 17
B37: =B36+1 -> 18 | C37: =IF(D37>0,$F$5,0) -> 0 | D37: =H36 -> 0 | E37: =IF(H36<=E36,H36+G37,$G$5) -> 0 | F37: =E37-G37 -> 0 | G37: =C37*(D37/365)*30 -> 0 | H37: =IF((D37+G37-E37)<0,0,D37+G37-E37) -> 0 | O37: =IF(H37=0,B37,"n.a.") -> 18
B38: =B37+1 -> 19 | C38: =IF(D38>0,$F$5,0) -> 0 | D38: =H37 -> 0 | E38: =IF(H37<=E37,H37+G38,$G$5) -> 0 | F38: =E38-G38 -> 0 | G38: =C38*(D38/365)*30 -> 0 | H38: =IF((D38+G38-E38)<0,0,D38+G38-E38) -> 0 | O38: =IF(H38=0,B38,"n.a.") -> 19
B39: =B38+1 -> 20 | C39: =IF(D39>0,$F$5,0) -> 0 | D39: =H38 -> 0 | E39: =IF(H38<=E38,H38+G39,$G$5) -> 0 | F39: =E39-G39 -> 0 | G39: =C39*(D39/365)*30 -> 0 | H39: =IF((D39+G39-E39)<0,0,D39+G39-E39) -> 0 | O39: =IF(H39=0,B39,"n.a.") -> 20
B40: =B39+1 -> 21 | C40: =IF(D40>0,$F$5,0) -> 0 | D40: =H39 -> 0 | E40: =IF(H39<=E39,H39+G40,$G$5) -> 0 | F40: =E40-G40 -> 0 | G40: =C40*(D40/365)*30 -> 0 | H40: =IF((D40+G40-E40)<0,0,D40+G40-E40) -> 0 | O40: =IF(H40=0,B40,"n.a.") -> 21
B41: =B40+1 -> 22 | C41: =IF(D41>0,$F$5,0) -> 0 | D41: =H40 -> 0 | E41: =IF(H40<=E40,H40+G41,$G$5) -> 0 | F41: =E41-G41 -> 0 | G41: =C41*(D41/365)*30 -> 0 | H41: =IF((D41+G41-E41)<0,0,D41+G41-E41) -> 0 | O41: =IF(H41=0,B41,"n.a.") -> 22
B42: =B41+1 -> 23 | C42: =IF(D42>0,$F$5,0) -> 0 | D42: =H41 -> 0 | E42: =IF(H41<=E41,H41+G42,$G$5) -> 0 | F42: =E42-G42 -> 0 | G42: =C42*(D42/365)*30 -> 0 | H42: =IF((D42+G42-E42)<0,0,D42+G42-E42) -> 0 | O42: =IF(H42=0,B42,"n.a.") -> 23
B43: =B42+1 -> 24 | C43: =IF(D43>0,$F$5,0) -> 0 | D43: =H42 -> 0 | E43: =IF(H42<=E42,H42+G43,$G$5) -> 0 | F43: =E43-G43 -> 0 | G43: =C43*(D43/365)*30 -> 0 | H43: =IF((D43+G43-E43)<0,0,D43+G43-E43) -> 0 | I43: =H43/$D$5 -> #VALUE! | O43: =IF(H43=0,B43,"n.a.") -> 24
B44: =B43+1 -> 25 | C44: =IF(D44>0,$F$6,0) -> 0 | D44: =H43 -> 0 | E44: =IF(H43<=E43,H43+G44,$G$6) -> 0 | F44: =E44-G44 -> 0 | G44: =C44*(D44/365)*30 -> 0 | H44: =IF((D44+G44-E44)<0,0,D44+G44-E44) -> 0 | O44: =IF(H44=0,B44,"n.a.") -> 25
B45: =B44+1 -> 26 | C45: =IF(D45>0,$F$6,0) -> 0 | D45: =H44 -> 0 | E45: =IF(H44<=E44,H44+G45,$G$6) -> 0 | F45: =E45-G45 -> 0 | G45: =C45*(D45/365)*30 -> 0 | H45: =IF((D45+G45-E45)<0,0,D45+G45-E45) -> 0 | O45: =IF(H45=0,B45,"n.a.") -> 26
B46: =B45+1 -> 27 | C46: =IF(D46>0,$F$6,0) -> 0 | D46: =H45 -> 0 | E46: =IF(H45<=E45,H45+G46,$G$6) -> 0 | F46: =E46-G46 -> 0 | G46: =C46*(D46/365)*30 -> 0 | H46: =IF((D46+G46-E46)<0,0,D46+G46-E46) -> 0 | O46: =IF(H46=0,B46,"n.a.") -> 27
B47: =B46+1 -> 28 | C47: =IF(D47>0,$F$6,0) -> 0 | D47: =H46 -> 0 | E47: =IF(H46<=E46,H46+G47,$G$6) -> 0 | F47: =E47-G47 -> 0 | G47: =C47*(D47/365)*30 -> 0 | H47: =IF((D47+G47-E47)<0,0,D47+G47-E47) -> 0 | O47: =IF(H47=0,B47,"n.a.") -> 28
B48: =B47+1 -> 29 | C48: =IF(D48>0,$F$6,0) -> 0 | D48: =H47 -> 0 | E48: =IF(H47<=E47,H47+G48,$G$6) -> 0 | F48: =E48-G48 -> 0 | G48: =C48*(D48/365)*30 -> 0 | H48: =IF((D48+G48-E48)<0,0,D48+G48-E48) -> 0 | O48: =IF(H48=0,B48,"n.a.") -> 29
B49: =B48+1 -> 30 | C49: =IF(D49>0,$F$6,0) -> 0 | D49: =H48 -> 0 | E49: =IF(H48<=E48,H48+G49,$G$6) -> 0 | F49: =E49-G49 -> 0 | G49: =C49*(D49/365)*30 -> 0 | H49: =IF((D49+G49-E49)<0,0,D49+G49-E49) -> 0 | O49: =IF(H49=0,B49,"n.a.") -> 30
B50: =B49+1 -> 31 | C50: =IF(D50>0,$F$6,0) -> 0 | D50: =H49 -> 0 | E50: =IF(H49<=E49,H49+G50,$G$6) -> 0 | F50: =E50-G50 -> 0 | G50: =C50*(D50/365)*30 -> 0 | H50: =IF((D50+G50-E50)<0,0,D50+G50-E50) -> 0 | O50: =IF(H50=0,B50,"n.a.") -> 31
B51: =B50+1 -> 32 | C51: =IF(D51>0,$F$6,0) -> 0 | D51: =H50 -> 0 | E51: =IF(H50<=E50,H50+G51,$G$6) -> 0 | F51: =E51-G51 -> 0 | G51: =C51*(D51/365)*30 -> 0 | H51: =IF((D51+G51-E51)<0,0,D51+G51-E51) -> 0 | O51: =IF(H51=0,B51,"n.a.") -> 32
B52: =B51+1 -> 33 | C52: =IF(D52>0,$F$6,0) -> 0 | D52: =H51 -> 0 | E52: =IF(H51<=E51,H51+G52,$G$6) -> 0 | F52: =E52-G52 -> 0 | G52: =C52*(D52/365)*30 -> 0 | H52: =IF((D52+G52-E52)<0,0,D52+G52-E52) -> 0 | O52: =IF(H52=0,B52,"n.a.") -> 33
B53: =B52+1 -> 34 | C53: =IF(D53>0,$F$6,0) -> 0 | D53: =H52 -> 0 | E53: =IF(H52<=E52,H52+G53,$G$6) -> 0 | F53: =E53-G53 -> 0 | G53: =C53*(D53/365)*30 -> 0 | H53: =IF((D53+G53-E53)<0,0,D53+G53-E53) -> 0 | O53: =IF(H53=0,B53,"n.a.") -> 34
B54: =B53+1 -> 35 | C54: =IF(D54>0,$F$6,0) -> 0 | D54: =H53 -> 0 | E54: =IF(H53<=E53,H53+G54,$G$6) -> 0 | F54: =E54-G54 -> 0 | G54: =C54*(D54/365)*30 -> 0 | H54: =IF((D54+G54-E54)<0,0,D54+G54-E54) -> 0 | O54: =IF(H54=0,B54,"n.a.") -> 35
B55: =B54+1 -> 36 | C55: =IF(D55>0,$F$6,0) -> 0 | D55: =H54 -> 0 | E55: =IF(H54<=E54,H54+G55,$G$6) -> 0 | F55: =E55-G55 -> 0 | G55: =C55*(D55/365)*30 -> 0 | H55: =IF((D55+G55-E55)<0,0,D55+G55-E55) -> 0 | I55: =H55/$D$5 -> #VALUE! | O55: =IF(H55=0,B55,"n.a.") -> 36
B56: =B55+1 -> 37 | C56: =IF(D56>0,$F$7,0) -> 0 | D56: =H55 -> 0 | E56: =IF(H55<=E55,H55+G56,$G$7) -> 0 | F56: =E56-G56 -> 0 | G56: =C56*(D56/365)*30 -> 0 | H56: =IF((D56+G56-E56)<0,0,D56+G56-E56) -> 0 | O56: =IF(H56=0,B56,"n.a.") -> 37
B57: =B56+1 -> 38 | C57: =IF(D57>0,$F$7,0) -> 0 | D57: =H56 -> 0 | E57: =IF(H56<=E56,H56+G57,$G$7) -> 0 | F57: =E57-G57 -> 0 | G57: =C57*(D57/365)*30 -> 0 | H57: =IF((D57+G57-E57)<0,0,D57+G57-E57) -> 0 | O57: =IF(H57=0,B57,"n.a.") -> 38
B58: =B57+1 -> 39 | C58: =IF(D58>0,$F$7,0) -> 0 | D58: =H57 -> 0 | E58: =IF(H57<=E57,H57+G58,$G$7) -> 0 | F58: =E58-G58 -> 0 | G58: =C58*(D58/365)*30 -> 0 | H58: =IF((D58+G58-E58)<0,0,D58+G58-E58) -> 0 | O58: =IF(H58=0,B58,"n.a.") -> 39
B59: =B58+1 -> 40 | C59: =IF(D59>0,$F$7,0) -> 0 | D59: =H58 -> 0 | E59: =IF(H58<=E58,H58+G59,$G$7) -> 0 | F59: =E59-G59 -> 0 | G59: =C59*(D59/365)*30 -> 0 | H59: =IF((D59+G59-E59)<0,0,D59+G59-E59) -> 0 | O59: =IF(H59=0,B59,"n.a.") -> 40
B60: =B59+1 -> 41 | C60: =IF(D60>0,$F$7,0) -> 0 | D60: =H59 -> 0 | E60: =IF(H59<=E59,H59+G60,$G$7) -> 0 | F60: =E60-G60 -> 0 | G60: =C60*(D60/365)*30 -> 0 | H60: =IF((D60+G60-E60)<0,0,D60+G60-E60) -> 0 | O60: =IF(H60=0,B60,"n.a.") -> 41
B61: =B60+1 -> 42 | C61: =IF(D61>0,$F$7,0) -> 0 | D61: =H60 -> 0 | E61: =IF(H60<=E60,H60+G61,$G$7) -> 0 | F61: =E61-G61 -> 0 | G61: =C61*(D61/365)*30 -> 0 | H61: =IF((D61+G61-E61)<0,0,D61+G61-E61) -> 0 | O61: =IF(H61=0,B61,"n.a.") -> 42
B62: =B61+1 -> 43 | C62: =IF(D62>0,$F$7,0) -> 0 | D62: =H61 -> 0 | E62: =IF(H61<=E61,H61+G62,$G$7) -> 0 | F62: =E62-G62 -> 0 | G62: =C62*(D62/365)*30 -> 0 | H62: =IF((D62+G62-E62)<0,0,D62+G62-E62) -> 0 | O62: =IF(H62=0,B62,"n.a.") -> 43
B63: =B62+1 -> 44 | C63: =IF(D63>0,$F$7,0) -> 0 | D63: =H62 -> 0 | E63: =IF(H62<=E62,H62+G63,$G$7) -> 0 | F63: =E63-G63 -> 0 | G63: =C63*(D63/365)*30 -> 0 | H63: =IF((D63+G63-E63)<0,0,D63+G63-E63) -> 0 | O63: =IF(H63=0,B63,"n.a.") -> 44
B64: =B63+1 -> 45 | C64: =IF(D64>0,$F$7,0) -> 0 | D64: =H63 -> 0 | E64: =IF(H63<=E63,H63+G64,$G$7) -> 0 | F64: =E64-G64 -> 0 | G64: =C64*(D64/365)*30 -> 0 | H64: =IF((D64+G64-E64)<0,0,D64+G64-E64) -> 0 | O64: =IF(H64=0,B64,"n.a.") -> 45
B65: =B64+1 -> 46 | C65: =IF(D65>0,$F$7,0) -> 0 | D65: =H64 -> 0 | E65: =IF(H64<=E64,H64+G65,$G$7) -> 0 | F65: =E65-G65 -> 0 | G65: =C65*(D65/365)*30 -> 0 | H65: =IF((D65+G65-E65)<0,0,D65+G65-E65) -> 0 | O65: =IF(H65=0,B65,"n.a.") -> 46
B66: =B65+1 -> 47 | C66: =IF(D66>0,$F$7,0) -> 0 | D66: =H65 -> 0 | E66: =IF(H65<=E65,H65+G66,$G$7) -> 0 | F66: =E66-G66 -> 0 | G66: =C66*(D66/365)*30 -> 0 | H66: =IF((D66+G66-E66)<0,0,D66+G66-E66) -> 0 | O66: =IF(H66=0,B66,"n.a.") -> 47
B67: =B66+1 -> 48 | C67: =IF(D67>0,$F$7,0) -> 0 | D67: =H66 -> 0 | E67: =IF(H66<=E66,H66+G67,$G$7) -> 0 | F67: =E67-G67 -> 0 | G67: =C67*(D67/365)*30 -> 0 | H67: =IF((D67+G67-E67)<0,0,D67+G67-E67) -> 0 | I67: =H67/$D$5 -> #VALUE! | O67: =IF(H67=0,B67,"n.a.") -> 48
B68: =B67+1 -> 49 | C68: =IF(D68>0,$F$7,0) -> 0 | D68: =H67 -> 0 | E68: =IF(H67<=E67,H67+G68,$H$10) -> 0 | F68: =E68-G68 -> 0 | G68: =C68*(D68/365)*30 -> 0 | H68: =IF((D68+G68-E68)<0,0,D68+G68-E68) -> 0 | O68: =IF(H68=0,B68,"n.a.") -> 49
B69: =B68+1 -> 50 | C69: =IF(D69>0,$F$7,0) -> 0 | D69: =H68 -> 0 | E69: =IF(H68<=E68,H68+G69,$H$10) -> 0 | F69: =E69-G69 -> 0 | G69: =C69*(D69/365)*30 -> 0 | H69: =IF((D69+G69-E69)<0,0,D69+G69-E69) -> 0 | O69: =IF(H69=0,B69,"n.a.") -> 50
B70: =B69+1 -> 51 | C70: =IF(D70>0,$F$7,0) -> 0 | D70: =H69 -> 0 | E70: =IF(H69<=E69,H69+G70,$H$10) -> 0 | F70: =E70-G70 -> 0 | G70: =C70*(D70/365)*30 -> 0 | H70: =IF((D70+G70-E70)<0,0,D70+G70-E70) -> 0 | O70: =IF(H70=0,B70,"n.a.") -> 51
B71: =B70+1 -> 52 | C71: =IF(D71>0,$F$7,0) -> 0 | D71: =H70 -> 0 | E71: =IF(H70<=E70,H70+G71,$H$10) -> 0 | F71: =E71-G71 -> 0 | G71: =C71*(D71/365)*30 -> 0 | H71: =IF((D71+G71-E71)<0,0,D71+G71-E71) -> 0 | O71: =IF(H71=0,B71,"n.a.") -> 52
B72: =B71+1 -> 53 | C72: =IF(D72>0,$F$7,0) -> 0 | D72: =H71 -> 0 | E72: =IF(H71<=E71,H71+G72,$H$10) -> 0 | F72: =E72-G72 -> 0 | G72: =C72*(D72/365)*30 -> 0 | H72: =IF((D72+G72-E72)<0,0,D72+G72-E72) -> 0 | O72: =IF(H72=0,B72,"n.a.") -> 53
B73: =B72+1 -> 54 | C73: =IF(D73>0,$F$7,0) -> 0 | D73: =H72 -> 0 | E73: =IF(H72<=E72,H72+G73,$H$10) -> 0 | F73: =E73-G73 -> 0 | G73: =C73*(D73/365)*30 -> 0 | H73: =IF((D73+G73-E73)<0,0,D73+G73-E73) -> 0 | O73: =IF(H73=0,B73,"n.a.") -> 54
B74: =B73+1 -> 55 | C74: =IF(D74>0,$F$7,0) -> 0 | D74: =H73 -> 0 | E74: =IF(H73<=E73,H73+G74,$H$10) -> 0 | F74: =E74-G74 -> 0 | G74: =C74*(D74/365)*30 -> 0 | H74: =IF((D74+G74-E74)<0,0,D74+G74-E74) -> 0 | O74: =IF(H74=0,B74,"n.a.") -> 55
B75: =B74+1 -> 56 | C75: =IF(D75>0,$F$7,0) -> 0 | D75: =H74 -> 0 | E75: =IF(H74<=E74,H74+G75,$H$10) -> 0 | F75: =E75-G75 -> 0 | G75: =C75*(D75/365)*30 -> 0 | H75: =IF((D75+G75-E75)<0,0,D75+G75-E75) -> 0 | O75: =IF(H75=0,B75,"n.a.") -> 56
B76: =B75+1 -> 57 | C76: =IF(D76>0,$F$7,0) -> 0 | D76: =H75 -> 0 | E76: =IF(H75<=E75,H75+G76,$H$10) -> 0 | F76: =E76-G76 -> 0 | G76: =C76*(D76/365)*30 -> 0 | H76: =IF((D76+G76-E76)<0,0,D76+G76-E76) -> 0 | O76: =IF(H76=0,B76,"n.a.") -> 57
B77: =B76+1 -> 58 | C77: =IF(D77>0,$F$7,0) -> 0 | D77: =H76 -> 0 | E77: =IF(H76<=E76,H76+G77,$H$10) -> 0 | F77: =E77-G77 -> 0 | G77: =C77*(D77/365)*30 -> 0 | H77: =IF((D77+G77-E77)<0,0,D77+G77-E77) -> 0 | O77: =IF(H77=0,B77,"n.a.") -> 58
B78: =B77+1 -> 59 | C78: =IF(D78>0,$F$7,0) -> 0 | D78: =H77 -> 0 | E78: =IF(H77<=E77,H77+G78,$H$10) -> 0 | F78: =E78-G78 -> 0 | G78: =C78*(D78/365)*30 -> 0 | H78: =IF((D78+G78-E78)<0,0,D78+G78-E78) -> 0 | O78: =IF(H78=0,B78,"n.a.") -> 59
B79: =B78+1 -> 60 | C79: =IF(D79>0,$F$7,0) -> 0 | D79: =H78 -> 0 | E79: =IF(H78<=E78,H78+G79,$H$10) -> 0 | F79: =E79-G79 -> 0 | G79: =C79*(D79/365)*30 -> 0 | H79: =IF((D79+G79-E79)<0,0,D79+G79-E79) -> 0 | I79: =H79/$D$5 -> #VALUE! | O79: =IF(H79=0,B79,"n.a.") -> 60
B80: =B79+1 -> 61 | C80: =IF(D80>0,$F$7,0) -> 0 | D80: =H79 -> 0 | E80: =IF(H79<=E79,H79+G80,$H$10) -> 0 | F80: =E80-G80 -> 0 | G80: =C80*(D80/365)*30 -> 0 | H80: =IF((D80+G80-E80)<0,0,D80+G80-E80) -> 0 | O80: =IF(H80=0,B80,"n.a.") -> 61
B81: =B80+1 -> 62 | C81: =IF(D81>0,$F$7,0) -> 0 | D81: =H80 -> 0 | E81: =IF(H80<=E80,H80+G81,$H$10) -> 0 | F81: =E81-G81 -> 0 | G81: =C81*(D81/365)*30 -> 0 | H81: =IF((D81+G81-E81)<0,0,D81+G81-E81) -> 0 | O81: =IF(H81=0,B81,"n.a.") -> 62
B82: =B81+1 -> 63 | C82: =IF(D82>0,$F$7,0) -> 0 | D82: =H81 -> 0 | E82: =IF(H81<=E81,H81+G82,$H$10) -> 0 | F82: =E82-G82 -> 0 | G82: =C82*(D82/365)*30 -> 0 | H82: =IF((D82+G82-E82)<0,0,D82+G82-E82) -> 0 | O82: =IF(H82=0,B82,"n.a.") -> 63
B83: =B82+1 -> 64 | C83: =IF(D83>0,$F$7,0) -> 0 | D83: =H82 -> 0 | E83: =IF(H82<=E82,H82+G83,$H$10) -> 0 | F83: =E83-G83 -> 0 | G83: =C83*(D83/365)*30 -> 0 | H83: =IF((D83+G83-E83)<0,0,D83+G83-E83) -> 0 | O83: =IF(H83=0,B83,"n.a.") -> 64
B84: =B83+1 -> 65 | C84: =IF(D84>0,$F$7,0) -> 0 | D84: =H83 -> 0 | E84: =IF(H83<=E83,H83+G84,$H$10) -> 0 | F84: =E84-G84 -> 0 | G84: =C84*(D84/365)*30 -> 0 | H84: =IF((D84+G84-E84)<0,0,D84+G84-E84) -> 0 | O84: =IF(H84=0,B84,"n.a.") -> 65
B85: =B84+1 -> 66 | C85: =IF(D85>0,$F$7,0) -> 0 | D85: =H84 -> 0 | E85: =IF(H84<=E84,H84+G85,$H$10) -> 0 | F85: =E85-G85 -> 0 | G85: =C85*(D85/365)*30 -> 0 | H85: =IF((D85+G85-E85)<0,0,D85+G85-E85) -> 0 | O85: =IF(H85=0,B85,"n.a.") -> 66
B86: =B85+1 -> 67 | C86: =IF(D86>0,$F$7,0) -> 0 | D86: =H85 -> 0 | E86: =IF(H85<=E85,H85+G86,$H$10) -> 0 | F86: =E86-G86 -> 0 | G86: =C86*(D86/365)*30 -> 0 | H86: =IF((D86+G86-E86)<0,0,D86+G86-E86) -> 0 | O86: =IF(H86=0,B86,"n.a.") -> 67
B87: =B86+1 -> 68 | C87: =IF(D87>0,$F$7,0) -> 0 | D87: =H86 -> 0 | E87: =IF(H86<=E86,H86+G87,$H$10) -> 0 | F87: =E87-G87 -> 0 | G87: =C87*(D87/365)*30 -> 0 | H87: =IF((D87+G87-E87)<0,0,D87+G87-E87) -> 0 | O87: =IF(H87=0,B87,"n.a.") -> 68
B88: =B87+1 -> 69 | C88: =IF(D88>0,$F$7,0) -> 0 | D88: =H87 -> 0 | E88: =IF(H87<=E87,H87+G88,$H$10) -> 0 | F88: =E88-G88 -> 0 | G88: =C88*(D88/365)*30 -> 0 | H88: =IF((D88+G88-E88)<0,0,D88+G88-E88) -> 0 | O88: =IF(H88=0,B88,"n.a.") -> 69
B89: =B88+1 -> 70 | C89: =IF(D89>0,$F$7,0) -> 0 | D89: =H88 -> 0 | E89: =IF(H88<=E88,H88+G89,$H$10) -> 0 | F89: =E89-G89 -> 0 | G89: =C89*(D89/365)*30 -> 0 | H89: =IF((D89+G89-E89)<0,0,D89+G89-E89) -> 0 | O89: =IF(H89=0,B89,"n.a.") -> 70
B90: =B89+1 -> 71 | C90: =IF(D90>0,$F$7,0) -> 0 | D90: =H89 -> 0 | E90: =IF(H89<=E89,H89+G90,$H$10) -> 0 | F90: =E90-G90 -> 0 | G90: =C90*(D90/365)*30 -> 0 | H90: =IF((D90+G90-E90)<0,0,D90+G90-E90) -> 0 | O90: =IF(H90=0,B90,"n.a.") -> 71
B91: =B90+1 -> 72 | C91: =IF(D91>0,$F$7,0) -> 0 | D91: =H90 -> 0 | E91: =IF(H90<=E90,H90+G91,$H$10) -> 0 | F91: =E91-G91 -> 0 | G91: =C91*(D91/365)*30 -> 0 | H91: =IF((D91+G91-E91)<0,0,D91+G91-E91) -> 0 | I91: =H91/$D$5 -> #VALUE! | O91: =IF(H91=0,B91,"n.a.") -> 72
B92: =B91+1 -> 73 | C92: =IF(D92>0,$F$7,0) -> 0 | D92: =H91 -> 0 | E92: =IF(H91<=E91,H91+G92,$H$10) -> 0 | F92: =E92-G92 -> 0 | G92: =C92*(D92/365)*30 -> 0 | H92: =IF((D92+G92-E92)<0,0,D92+G92-E92) -> 0 | O92: =IF(H92=0,B92,"n.a.") -> 73
B93: =B92+1 -> 74 | C93: =IF(D93>0,$F$7,0) -> 0 | D93: =H92 -> 0 | E93: =IF(H92<=E92,H92+G93,$H$10) -> 0 | F93: =E93-G93 -> 0 | G93: =C93*(D93/365)*30 -> 0 | H93: =IF((D93+G93-E93)<0,0,D93+G93-E93) -> 0 | O93: =IF(H93=0,B93,"n.a.") -> 74
B94: =B93+1 -> 75 | C94: =IF(D94>0,$F$7,0) -> 0 | D94: =H93 -> 0 | E94: =IF(H93<=E93,H93+G94,$H$10) -> 0 | F94: =E94-G94 -> 0 | G94: =C94*(D94/365)*30 -> 0 | H94: =IF((D94+G94-E94)<0,0,D94+G94-E94) -> 0 | O94: =IF(H94=0,B94,"n.a.") -> 75
B95: =B94+1 -> 76 | C95: =IF(D95>0,$F$7,0) -> 0 | D95: =H94 -> 0 | E95: =IF(H94<=E94,H94+G95,$H$10) -> 0 | F95: =E95-G95 -> 0 | G95: =C95*(D95/365)*30 -> 0 | H95: =IF((D95+G95-E95)<0,0,D95+G95-E95) -> 0 | O95: =IF(H95=0,B95,"n.a.") -> 76
B96: =B95+1 -> 77 | C96: =IF(D96>0,$F$7,0) -> 0 | D96: =H95 -> 0 | E96: =IF(H95<=E95,H95+G96,$H$10) -> 0 | F96: =E96-G96 -> 0 | G96: =C96*(D96/365)*30 -> 0 | H96: =IF((D96+G96-E96)<0,0,D96+G96-E96) -> 0 | O96: =IF(H96=0,B96,"n.a.") -> 77
B97: =B96+1 -> 78 | C97: =IF(D97>0,$F$7,0) -> 0 | D97: =H96 -> 0 | E97: =IF(H96<=E96,H96+G97,$H$10) -> 0 | F97: =E97-G97 -> 0 | G97: =C97*(D97/365)*30 -> 0 | H97: =IF((D97+G97-E97)<0,0,D97+G97-E97) -> 0 | O97: =IF(H97=0,B97,"n.a.") -> 78
B98: =B97+1 -> 79 | C98: =IF(D98>0,$F$7,0) -> 0 | D98: =H97 -> 0 | E98: =IF(H97<=E97,H97+G98,$H$10) -> 0 | F98: =E98-G98 -> 0 | G98: =C98*(D98/365)*30 -> 0 | H98: =IF((D98+G98-E98)<0,0,D98+G98-E98) -> 0 | O98: =IF(H98=0,B98,"n.a.") -> 79
B99: =B98+1 -> 80 | C99: =IF(D99>0,$F$7,0) -> 0 | D99: =H98 -> 0 | E99: =IF(H98<=E98,H98+G99,$H$10) -> 0 | F99: =E99-G99 -> 0 | G99: =C99*(D99/365)*30 -> 0 | H99: =IF((D99+G99-E99)<0,0,D99+G99-E99) -> 0 | O99: =IF(H99=0,B99,"n.a.") -> 80
B100: =B99+1 -> 81 | C100: =IF(D100>0,$F$7,0) -> 0 | D100: =H99 -> 0 | E100: =IF(H99<=E99,H99+G100,$H$10) -> 0 | F100: =E100-G100 -> 0 | G100: =C100*(D100/365)*30 -> 0 | H100: =IF((D100+G100-E100)<0,0,D100+G100-E100) -> 0 | O100: =IF(H100=0,B100,"n.a.") -> 81
B101: =B100+1 -> 82 | C101: =IF(D101>0,$F$7,0) -> 0 | D101: =H100 -> 0 | E101: =IF(H100<=E100,H100+G101,$H$10) -> 0 | F101: =E101-G101 -> 0 | G101: =C101*(D101/365)*30 -> 0 | H101: =IF((D101+G101-E101)<0,0,D101+G101-E101) -> 0 | O101: =IF(H101=0,B101,"n.a.") -> 82
B102: =B101+1 -> 83 | C102: =IF(D102>0,$F$7,0) -> 0 | D102: =H101 -> 0 | E102: =IF(H101<=E101,H101+G102,$H$10) -> 0 | F102: =E102-G102 -> 0 | G102: =C102*(D102/365)*30 -> 0 | H102: =IF((D102+G102-E102)<0,0,D102+G102-E102) -> 0 | O102: =IF(H102=0,B102,"n.a.") -> 83
...

Sheet ตาราง-MP-เสนอลด
B1: ตารางผ่อนชำระเบื้องต้น MP (อัตราดอกเบี้ยนำเสนอลด)
B2: ชื่อ | C2: ='1.ลดดอกเบี้ย'!C3 -> 0 | G2: ผ่อนชำระ
B3: App No | C3: ='1.ลดดอกเบี้ย'!C4 -> 0 | F3: อัตราดอกเบี้ย | G3: เท่ากันทุกเดือน
B4: วงเงิน | C4: ='1.ลดดอกเบี้ย'!E8 -> 0 | D4: บาท | E4: ปีที่ 1 | F4: ='2.นำเสนอดอกเบี้ย'!K23 -> 0 | G4: ='1.ลดดอกเบี้ย'!E28 -> 0
B5: ระยะเวลา | C5: ='1.ลดดอกเบี้ย'!E9 -> 0 | D5: ปี | E5: ปีที่ 2 | F5: ='2.นำเสนอดอกเบี้ย'!K24 -> 0 | G5: ='1.ลดดอกเบี้ย'!E29 -> 0 | H5: =SUM(I6:I10)/#REF! -> #REF!
E6: ปีที่ 3 | F6: ='2.นำเสนอดอกเบี้ย'!K25 -> 0 | G6: ='1.ลดดอกเบี้ย'!E30 -> 0 | H6: =F4*12 -> 0
C7: Buffer | D7: 0.01 | E7: ปีที่ 4+ | F7: ='2.นำเสนอดอกเบี้ย'!K26 -> 0 | G7: ='1.ลดดอกเบี้ย'!E31 -> 0 | H7: =F5*12 -> 0
H8: =F6*12 -> 0
H9: =F7*12 -> 0
F10: Int. Yr. 5+ | G10: =F7 -> 0 | H10: =G7 -> 0 | I10: =G10*(#REF!-48) -> #REF!
D11: =12*3 -> 36 | E11: =12*5 -> 60 | F11: =12*7 -> 84 | G11: =12*10 -> 120 | H11: =12*30 -> 360 | I11: =12*15 -> 180
D12: 3 Yrs. | E12: 5 Yrs. | F12: 7 Yrs. | G12: 10 Yrs. | H12: 30 Yrs. | I12: 15 Yrs
B13: Total Int. | D13: =SUM($G$20:$G$55) -> 0 | E13: =SUM($G$20:$G$79) -> 0 | F13: =SUM($G$20:$G$103) -> 0 | G13: =SUM($G$20:$G$139) -> 0 | H13: =SUM($G$20:$G$379) -> 0 | I13: =SUM($G$20:$G$199) -> 0
B14: Average O/S | D14: =AVERAGE($D$20:$D$55) -> 0 | E14: =AVERAGE($D$20:$D$79) -> 0 | F14: =AVERAGE($D$20:$D$103) -> 0 | G14: =AVERAGE($D$20:$D$139) -> 0 | H14: =AVERAGE($D$20:$D$379) -> 0 | I14: =AVERAGE($D$20:$D$199) -> 0
B15: EIR | D15: =D13/D14/(D11/12) -> #DIV/0! | E15: =E13/E14/(E11/12) -> #DIV/0! | F15: =F13/F14/(F11/12) -> #DIV/0! | G15: =G13/G14/(G11/12) -> #DIV/0! | H15: =H13/H14/(H11/12) -> #DIV/0! | I15: =I13/I14/(I11/12) -> #DIV/0!
B17: Average | D17: =AVERAGE($C$20:$C$55) -> 0 | E17: =AVERAGE($C$20:$C$79) -> 0 | F17: =AVERAGE($C$20:$C$103) -> 0 | G17: =AVERAGE($C$20:$C$139) -> 0 | H17: =AVERAGE($C$20:$C$379) -> 0 | I17: =AVERAGE(C20:C199) -> 0
B19: เดือน | C19: อัตราดอกเบี้ย | D19: ยอดคงค้าง | E19: ยอดผ่อนชำระ | F19: ยอดเงินต้น | G19: ยอดดอกเบี้ย | H19: ยอดคงค้าง | I19: LTV | O19: Tenor
B20: 1 | C20: =IF(D20>0,$F$4,0) -> 0 | D20: =C4 -> 0 | E20: =G4 -> 0 | F20: =E20-G20 -> 0 | G20: =C20*(D20/365)*30 -> 0 | H20: =IF((D20+G20-E20)<0,0,D20+G20-E20) -> 0 | O20: =IF(H20=0,B20,"n.a.") -> 1
B21: =B20+1 -> 2 | C21: =IF(D21>0,$F$4,0) -> 0 | D21: =H20 -> 0 | E21: =IF(H20<=E20,H20+G21,$G$4) -> 0 | F21: =E21-G21 -> 0 | G21: =C21*(D21/365)*30 -> 0 | H21: =IF((D21+G21-E21)<0,0,D21+G21-E21) -> 0 | O21: =IF(H21=0,B21,"n.a.") -> 2
B22: =B21+1 -> 3 | C22: =IF(D22>0,$F$4,0) -> 0 | D22: =H21 -> 0 | E22: =IF(H21<=E21,H21+G22,$G$4) -> 0 | F22: =E22-G22 -> 0 | G22: =C22*(D22/365)*30 -> 0 | H22: =IF((D22+G22-E22)<0,0,D22+G22-E22) -> 0 | O22: =IF(H22=0,B22,"n.a.") -> 3
B23: =B22+1 -> 4 | C23: =IF(D23>0,$F$4,0) -> 0 | D23: =H22 -> 0 | E23: =IF(H22<=E22,H22+G23,$G$4) -> 0 | F23: =E23-G23 -> 0 | G23: =C23*(D23/365)*30 -> 0 | H23: =IF((D23+G23-E23)<0,0,D23+G23-E23) -> 0 | O23: =IF(H23=0,B23,"n.a.") -> 4
B24: =B23+1 -> 5 | C24: =IF(D24>0,$F$4,0) -> 0 | D24: =H23 -> 0 | E24: =IF(H23<=E23,H23+G24,$G$4) -> 0 | F24: =E24-G24 -> 0 | G24: =C24*(D24/365)*30 -> 0 | H24: =IF((D24+G24-E24)<0,0,D24+G24-E24) -> 0 | O24: =IF(H24=0,B24,"n.a.") -> 5
B25: =B24+1 -> 6 | C25: =IF(D25>0,$F$4,0) -> 0 | D25: =H24 -> 0 | E25: =IF(H24<=E24,H24+G25,$G$4) -> 0 | F25: =E25-G25 -> 0 | G25: =C25*(D25/365)*30 -> 0 | H25: =IF((D25+G25-E25)<0,0,D25+G25-E25) -> 0 | O25: =IF(H25=0,B25,"n.a.") -> 6
B26: =B25+1 -> 7 | C26: =IF(D26>0,$F$4,0) -> 0 | D26: =H25 -> 0 | E26: =IF(H25<=E25,H25+G26,$G$4) -> 0 | F26: =E26-G26 -> 0 | G26: =C26*(D26/365)*30 -> 0 | H26: =IF((D26+G26-E26)<0,0,D26+G26-E26) -> 0 | O26: =IF(H26=0,B26,"n.a.") -> 7
B27: =B26+1 -> 8 | C27: =IF(D27>0,$F$4,0) -> 0 | D27: =H26 -> 0 | E27: =IF(H26<=E26,H26+G27,$G$4) -> 0 | F27: =E27-G27 -> 0 | G27: =C27*(D27/365)*30 -> 0 | H27: =IF((D27+G27-E27)<0,0,D27+G27-E27) -> 0 | O27: =IF(H27=0,B27,"n.a.") -> 8
B28: =B27+1 -> 9 | C28: =IF(D28>0,$F$4,0) -> 0 | D28: =H27 -> 0 | E28: =IF(H27<=E27,H27+G28,$G$4) -> 0 | F28: =E28-G28 -> 0 | G28: =C28*(D28/365)*30 -> 0 | H28: =IF((D28+G28-E28)<0,0,D28+G28-E28) -> 0 | O28: =IF(H28=0,B28,"n.a.") -> 9
B29: =B28+1 -> 10 | C29: =IF(D29>0,$F$4,0) -> 0 | D29: =H28 -> 0 | E29: =IF(H28<=E28,H28+G29,$G$4) -> 0 | F29: =E29-G29 -> 0 | G29: =C29*(D29/365)*30 -> 0 | H29: =IF((D29+G29-E29)<0,0,D29+G29-E29) -> 0 | O29: =IF(H29=0,B29,"n.a.") -> 10
B30: =B29+1 -> 11 | C30: =IF(D30>0,$F$4,0) -> 0 | D30: =H29 -> 0 | E30: =IF(H29<=E29,H29+G30,$G$4) -> 0 | F30: =E30-G30 -> 0 | G30: =C30*(D30/365)*30 -> 0 | H30: =IF((D30+G30-E30)<0,0,D30+G30-E30) -> 0 | O30: =IF(H30=0,B30,"n.a.") -> 11
B31: =B30+1 -> 12 | C31: =IF(D31>0,$F$4,0) -> 0 | D31: =H30 -> 0 | E31: =IF(H30<=E30,H30+G31,$G$4) -> 0 | F31: =E31-G31 -> 0 | G31: =C31*(D31/365)*30 -> 0 | H31: =IF((D31+G31-E31)<0,0,D31+G31-E31) -> 0 | I31: =H31/$D$5 -> #VALUE! | O31: =IF(H31=0,B31,"n.a.") -> 12
B32: =B31+1 -> 13 | C32: =IF(D32>0,$F$5,0) -> 0 | D32: =H31 -> 0 | E32: =IF(H31<=E31,H31+G32,$G$5) -> 0 | F32: =E32-G32 -> 0 | G32: =C32*(D32/365)*30 -> 0 | H32: =IF((D32+G32-E32)<0,0,D32+G32-E32) -> 0 | O32: =IF(H32=0,B32,"n.a.") -> 13
B33: =B32+1 -> 14 | C33: =IF(D33>0,$F$5,0) -> 0 | D33: =H32 -> 0 | E33: =IF(H32<=E32,H32+G33,$G$5) -> 0 | F33: =E33-G33 -> 0 | G33: =C33*(D33/365)*30 -> 0 | H33: =IF((D33+G33-E33)<0,0,D33+G33-E33) -> 0 | O33: =IF(H33=0,B33,"n.a.") -> 14
B34: =B33+1 -> 15 | C34: =IF(D34>0,$F$5,0) -> 0 | D34: =H33 -> 0 | E34: =IF(H33<=E33,H33+G34,$G$5) -> 0 | F34: =E34-G34 -> 0 | G34: =C34*(D34/365)*30 -> 0 | H34: =IF((D34+G34-E34)<0,0,D34+G34-E34) -> 0 | O34: =IF(H34=0,B34,"n.a.") -> 15
B35: =B34+1 -> 16 | C35: =IF(D35>0,$F$5,0) -> 0 | D35: =H34 -> 0 | E35: =IF(H34<=E34,H34+G35,$G$5) -> 0 | F35: =E35-G35 -> 0 | G35: =C35*(D35/365)*30 -> 0 | H35: =IF((D35+G35-E35)<0,0,D35+G35-E35) -> 0 | O35: =IF(H35=0,B35,"n.a.") -> 16
B36: =B35+1 -> 17 | C36: =IF(D36>0,$F$5,0) -> 0 | D36: =H35 -> 0 | E36: =IF(H35<=E35,H35+G36,$G$5) -> 0 | F36: =E36-G36 -> 0 | G36: =C36*(D36/365)*30 -> 0 | H36: =IF((D36+G36-E36)<0,0,D36+G36-E36) -> 0 | O36: =IF(H36=0,B36,"n.a.") -> 17
B37: =B36+1 -> 18 | C37: =IF(D37>0,$F$5,0) -> 0 | D37: =H36 -> 0 | E37: =IF(H36<=E36,H36+G37,$G$5) -> 0 | F37: =E37-G37 -> 0 | G37: =C37*(D37/365)*30 -> 0 | H37: =IF((D37+G37-E37)<0,0,D37+G37-E37) -> 0 | O37: =IF(H37=0,B37,"n.a.") -> 18
B38: =B37+1 -> 19 | C38: =IF(D38>0,$F$5,0) -> 0 | D38: =H37 -> 0 | E38: =IF(H37<=E37,H37+G38,$G$5) -> 0 | F38: =E38-G38 -> 0 | G38: =C38*(D38/365)*30 -> 0 | H38: =IF((D38+G38-E38)<0,0,D38+G38-E38) -> 0 | O38: =IF(H38=0,B38,"n.a.") -> 19
B39: =B38+1 -> 20 | C39: =IF(D39>0,$F$5,0) -> 0 | D39: =H38 -> 0 | E39: =IF(H38<=E38,H38+G39,$G$5) -> 0 | F39: =E39-G39 -> 0 | G39: =C39*(D39/365)*30 -> 0 | H39: =IF((D39+G39-E39)<0,0,D39+G39-E39) -> 0 | O39: =IF(H39=0,B39,"n.a.") -> 20
B40: =B39+1 -> 21 | C40: =IF(D40>0,$F$5,0) -> 0 | D40: =H39 -> 0 | E40: =IF(H39<=E39,H39+G40,$G$5) -> 0 | F40: =E40-G40 -> 0 | G40: =C40*(D40/365)*30 -> 0 | H40: =IF((D40+G40-E40)<0,0,D40+G40-E40) -> 0 | O40: =IF(H40=0,B40,"n.a.") -> 21
B41: =B40+1 -> 22 | C41: =IF(D41>0,$F$5,0) -> 0 | D41: =H40 -> 0 | E41: =IF(H40<=E40,H40+G41,$G$5) -> 0 | F41: =E41-G41 -> 0 | G41: =C41*(D41/365)*30 -> 0 | H41: =IF((D41+G41-E41)<0,0,D41+G41-E41) -> 0 | O41: =IF(H41=0,B41,"n.a.") -> 22
B42: =B41+1 -> 23 | C42: =IF(D42>0,$F$5,0) -> 0 | D42: =H41 -> 0 | E42: =IF(H41<=E41,H41+G42,$G$5) -> 0 | F42: =E42-G42 -> 0 | G42: =C42*(D42/365)*30 -> 0 | H42: =IF((D42+G42-E42)<0,0,D42+G42-E42) -> 0 | O42: =IF(H42=0,B42,"n.a.") -> 23
B43: =B42+1 -> 24 | C43: =IF(D43>0,$F$5,0) -> 0 | D43: =H42 -> 0 | E43: =IF(H42<=E42,H42+G43,$G$5) -> 0 | F43: =E43-G43 -> 0 | G43: =C43*(D43/365)*30 -> 0 | H43: =IF((D43+G43-E43)<0,0,D43+G43-E43) -> 0 | I43: =H43/$D$5 -> #VALUE! | O43: =IF(H43=0,B43,"n.a.") -> 24
B44: =B43+1 -> 25 | C44: =IF(D44>0,$F$6,0) -> 0 | D44: =H43 -> 0 | E44: =IF(H43<=E43,H43+G44,$G$6) -> 0 | F44: =E44-G44 -> 0 | G44: =C44*(D44/365)*30 -> 0 | H44: =IF((D44+G44-E44)<0,0,D44+G44-E44) -> 0 | O44: =IF(H44=0,B44,"n.a.") -> 25
B45: =B44+1 -> 26 | C45: =IF(D45>0,$F$6,0) -> 0 | D45: =H44 -> 0 | E45: =IF(H44<=E44,H44+G45,$G$6) -> 0 | F45: =E45-G45 -> 0 | G45: =C45*(D45/365)*30 -> 0 | H45: =IF((D45+G45-E45)<0,0,D45+G45-E45) -> 0 | O45: =IF(H45=0,B45,"n.a.") -> 26
B46: =B45+1 -> 27 | C46: =IF(D46>0,$F$6,0) -> 0 | D46: =H45 -> 0 | E46: =IF(H45<=E45,H45+G46,$G$6) -> 0 | F46: =E46-G46 -> 0 | G46: =C46*(D46/365)*30 -> 0 | H46: =IF((D46+G46-E46)<0,0,D46+G46-E46) -> 0 | O46: =IF(H46=0,B46,"n.a.") -> 27
B47: =B46+1 -> 28 | C47: =IF(D47>0,$F$6,0) -> 0 | D47: =H46 -> 0 | E47: =IF(H46<=E46,H46+G47,$G$6) -> 0 | F47: =E47-G47 -> 0 | G47: =C47*(D47/365)*30 -> 0 | H47: =IF((D47+G47-E47)<0,0,D47+G47-E47) -> 0 | O47: =IF(H47=0,B47,"n.a.") -> 28
B48: =B47+1 -> 29 | C48: =IF(D48>0,$F$6,0) -> 0 | D48: =H47 -> 0 | E48: =IF(H47<=E47,H47+G48,$G$6) -> 0 | F48: =E48-G48 -> 0 | G48: =C48*(D48/365)*30 -> 0 | H48: =IF((D48+G48-E48)<0,0,D48+G48-E48) -> 0 | O48: =IF(H48=0,B48,"n.a.") -> 29
B49: =B48+1 -> 30 | C49: =IF(D49>0,$F$6,0) -> 0 | D49: =H48 -> 0 | E49: =IF(H48<=E48,H48+G49,$G$6) -> 0 | F49: =E49-G49 -> 0 | G49: =C49*(D49/365)*30 -> 0 | H49: =IF((D49+G49-E49)<0,0,D49+G49-E49) -> 0 | O49: =IF(H49=0,B49,"n.a.") -> 30
B50: =B49+1 -> 31 | C50: =IF(D50>0,$F$6,0) -> 0 | D50: =H49 -> 0 | E50: =IF(H49<=E49,H49+G50,$G$6) -> 0 | F50: =E50-G50 -> 0 | G50: =C50*(D50/365)*30 -> 0 | H50: =IF((D50+G50-E50)<0,0,D50+G50-E50) -> 0 | O50: =IF(H50=0,B50,"n.a.") -> 31
B51: =B50+1 -> 32 | C51: =IF(D51>0,$F$6,0) -> 0 | D51: =H50 -> 0 | E51: =IF(H50<=E50,H50+G51,$G$6) -> 0 | F51: =E51-G51 -> 0 | G51: =C51*(D51/365)*30 -> 0 | H51: =IF((D51+G51-E51)<0,0,D51+G51-E51) -> 0 | O51: =IF(H51=0,B51,"n.a.") -> 32
B52: =B51+1 -> 33 | C52: =IF(D52>0,$F$6,0) -> 0 | D52: =H51 -> 0 | E52: =IF(H51<=E51,H51+G52,$G$6) -> 0 | F52: =E52-G52 -> 0 | G52: =C52*(D52/365)*30 -> 0 | H52: =IF((D52+G52-E52)<0,0,D52+G52-E52) -> 0 | O52: =IF(H52=0,B52,"n.a.") -> 33
B53: =B52+1 -> 34 | C53: =IF(D53>0,$F$6,0) -> 0 | D53: =H52 -> 0 | E53: =IF(H52<=E52,H52+G53,$G$6) -> 0 | F53: =E53-G53 -> 0 | G53: =C53*(D53/365)*30 -> 0 | H53: =IF((D53+G53-E53)<0,0,D53+G53-E53) -> 0 | O53: =IF(H53=0,B53,"n.a.") -> 34
B54: =B53+1 -> 35 | C54: =IF(D54>0,$F$6,0) -> 0 | D54: =H53 -> 0 | E54: =IF(H53<=E53,H53+G54,$G$6) -> 0 | F54: =E54-G54 -> 0 | G54: =C54*(D54/365)*30 -> 0 | H54: =IF((D54+G54-E54)<0,0,D54+G54-E54) -> 0 | O54: =IF(H54=0,B54,"n.a.") -> 35
B55: =B54+1 -> 36 | C55: =IF(D55>0,$F$6,0) -> 0 | D55: =H54 -> 0 | E55: =IF(H54<=E54,H54+G55,$G$6) -> 0 | F55: =E55-G55 -> 0 | G55: =C55*(D55/365)*30 -> 0 | H55: =IF((D55+G55-E55)<0,0,D55+G55-E55) -> 0 | I55: =H55/$D$5 -> #VALUE! | O55: =IF(H55=0,B55,"n.a.") -> 36
B56: =B55+1 -> 37 | C56: =IF(D56>0,$F$7,0) -> 0 | D56: =H55 -> 0 | E56: =IF(H55<=E55,H55+G56,$G$7) -> 0 | F56: =E56-G56 -> 0 | G56: =C56*(D56/365)*30 -> 0 | H56: =IF((D56+G56-E56)<0,0,D56+G56-E56) -> 0 | O56: =IF(H56=0,B56,"n.a.") -> 37
B57: =B56+1 -> 38 | C57: =IF(D57>0,$F$7,0) -> 0 | D57: =H56 -> 0 | E57: =IF(H56<=E56,H56+G57,$G$7) -> 0 | F57: =E57-G57 -> 0 | G57: =C57*(D57/365)*30 -> 0 | H57: =IF((D57+G57-E57)<0,0,D57+G57-E57) -> 0 | O57: =IF(H57=0,B57,"n.a.") -> 38
B58: =B57+1 -> 39 | C58: =IF(D58>0,$F$7,0) -> 0 | D58: =H57 -> 0 | E58: =IF(H57<=E57,H57+G58,$G$7) -> 0 | F58: =E58-G58 -> 0 | G58: =C58*(D58/365)*30 -> 0 | H58: =IF((D58+G58-E58)<0,0,D58+G58-E58) -> 0 | O58: =IF(H58=0,B58,"n.a.") -> 39
B59: =B58+1 -> 40 | C59: =IF(D59>0,$F$7,0) -> 0 | D59: =H58 -> 0 | E59: =IF(H58<=E58,H58+G59,$G$7) -> 0 | F59: =E59-G59 -> 0 | G59: =C59*(D59/365)*30 -> 0 | H59: =IF((D59+G59-E59)<0,0,D59+G59-E59) -> 0 | O59: =IF(H59=0,B59,"n.a.") -> 40
B60: =B59+1 -> 41 | C60: =IF(D60>0,$F$7,0) -> 0 | D60: =H59 -> 0 | E60: =IF(H59<=E59,H59+G60,$G$7) -> 0 | F60: =E60-G60 -> 0 | G60: =C60*(D60/365)*30 -> 0 | H60: =IF((D60+G60-E60)<0,0,D60+G60-E60) -> 0 | O60: =IF(H60=0,B60,"n.a.") -> 41
B61: =B60+1 -> 42 | C61: =IF(D61>0,$F$7,0) -> 0 | D61: =H60 -> 0 | E61: =IF(H60<=E60,H60+G61,$G$7) -> 0 | F61: =E61-G61 -> 0 | G61: =C61*(D61/365)*30 -> 0 | H61: =IF((D61+G61-E61)<0,0,D61+G61-E61) -> 0 | O61: =IF(H61=0,B61,"n.a.") -> 42
B62: =B61+1 -> 43 | C62: =IF(D62>0,$F$7,0) -> 0 | D62: =H61 -> 0 | E62: =IF(H61<=E61,H61+G62,$G$7) -> 0 | F62: =E62-G62 -> 0 | G62: =C62*(D62/365)*30 -> 0 | H62: =IF((D62+G62-E62)<0,0,D62+G62-E62) -> 0 | O62: =IF(H62=0,B62,"n.a.") -> 43
B63: =B62+1 -> 44 | C63: =IF(D63>0,$F$7,0) -> 0 | D63: =H62 -> 0 | E63: =IF(H62<=E62,H62+G63,$G$7) -> 0 | F63: =E63-G63 -> 0 | G63: =C63*(D63/365)*30 -> 0 | H63: =IF((D63+G63-E63)<0,0,D63+G63-E63) -> 0 | O63: =IF(H63=0,B63,"n.a.") -> 44
B64: =B63+1 -> 45 | C64: =IF(D64>0,$F$7,0) -> 0 | D64: =H63 -> 0 | E64: =IF(H63<=E63,H63+G64,$G$7) -> 0 | F64: =E64-G64 -> 0 | G64: =C64*(D64/365)*30 -> 0 | H64: =IF((D64+G64-E64)<0,0,D64+G64-E64) -> 0 | O64: =IF(H64=0,B64,"n.a.") -> 45
B65: =B64+1 -> 46 | C65: =IF(D65>0,$F$7,0) -> 0 | D65: =H64 -> 0 | E65: =IF(H64<=E64,H64+G65,$G$7) -> 0 | F65: =E65-G65 -> 0 | G65: =C65*(D65/365)*30 -> 0 | H65: =IF((D65+G65-E65)<0,0,D65+G65-E65) -> 0 | O65: =IF(H65=0,B65,"n.a.") -> 46
B66: =B65+1 -> 47 | C66: =IF(D66>0,$F$7,0) -> 0 | D66: =H65 -> 0 | E66: =IF(H65<=E65,H65+G66,$G$7) -> 0 | F66: =E66-G66 -> 0 | G66: =C66*(D66/365)*30 -> 0 | H66: =IF((D66+G66-E66)<0,0,D66+G66-E66) -> 0 | O66: =IF(H66=0,B66,"n.a.") -> 47
B67: =B66+1 -> 48 | C67: =IF(D67>0,$F$7,0) -> 0 | D67: =H66 -> 0 | E67: =IF(H66<=E66,H66+G67,$G$7) -> 0 | F67: =E67-G67 -> 0 | G67: =C67*(D67/365)*30 -> 0 | H67: =IF((D67+G67-E67)<0,0,D67+G67-E67) -> 0 | I67: =H67/$D$5 -> #VALUE! | O67: =IF(H67=0,B67,"n.a.") -> 48
B68: =B67+1 -> 49 | C68: =IF(D68>0,$F$7,0) -> 0 | D68: =H67 -> 0 | E68: =IF(H67<=E67,H67+G68,$H$10) -> 0 | F68: =E68-G68 -> 0 | G68: =C68*(D68/365)*30 -> 0 | H68: =IF((D68+G68-E68)<0,0,D68+G68-E68) -> 0 | O68: =IF(H68=0,B68,"n.a.") -> 49
B69: =B68+1 -> 50 | C69: =IF(D69>0,$F$7,0) -> 0 | D69: =H68 -> 0 | E69: =IF(H68<=E68,H68+G69,$H$10) -> 0 | F69: =E69-G69 -> 0 | G69: =C69*(D69/365)*30 -> 0 | H69: =IF((D69+G69-E69)<0,0,D69+G69-E69) -> 0 | O69: =IF(H69=0,B69,"n.a.") -> 50
B70: =B69+1 -> 51 | C70: =IF(D70>0,$F$7,0) -> 0 | D70: =H69 -> 0 | E70: =IF(H69<=E69,H69+G70,$H$10) -> 0 | F70: =E70-G70 -> 0 | G70: =C70*(D70/365)*30 -> 0 | H70: =IF((D70+G70-E70)<0,0,D70+G70-E70) -> 0 | O70: =IF(H70=0,B70,"n.a.") -> 51
B71: =B70+1 -> 52 | C71: =IF(D71>0,$F$7,0) -> 0 | D71: =H70 -> 0 | E71: =IF(H70<=E70,H70+G71,$H$10) -> 0 | F71: =E71-G71 -> 0 | G71: =C71*(D71/365)*30 -> 0 | H71: =IF((D71+G71-E71)<0,0,D71+G71-E71) -> 0 | O71: =IF(H71=0,B71,"n.a.") -> 52
B72: =B71+1 -> 53 | C72: =IF(D72>0,$F$7,0) -> 0 | D72: =H71 -> 0 | E72: =IF(H71<=E71,H71+G72,$H$10) -> 0 | F72: =E72-G72 -> 0 | G72: =C72*(D72/365)*30 -> 0 | H72: =IF((D72+G72-E72)<0,0,D72+G72-E72) -> 0 | O72: =IF(H72=0,B72,"n.a.") -> 53
B73: =B72+1 -> 54 | C73: =IF(D73>0,$F$7,0) -> 0 | D73: =H72 -> 0 | E73: =IF(H72<=E72,H72+G73,$H$10) -> 0 | F73: =E73-G73 -> 0 | G73: =C73*(D73/365)*30 -> 0 | H73: =IF((D73+G73-E73)<0,0,D73+G73-E73) -> 0 | O73: =IF(H73=0,B73,"n.a.") -> 54
B74: =B73+1 -> 55 | C74: =IF(D74>0,$F$7,0) -> 0 | D74: =H73 -> 0 | E74: =IF(H73<=E73,H73+G74,$H$10) -> 0 | F74: =E74-G74 -> 0 | G74: =C74*(D74/365)*30 -> 0 | H74: =IF((D74+G74-E74)<0,0,D74+G74-E74) -> 0 | O74: =IF(H74=0,B74,"n.a.") -> 55
B75: =B74+1 -> 56 | C75: =IF(D75>0,$F$7,0) -> 0 | D75: =H74 -> 0 | E75: =IF(H74<=E74,H74+G75,$H$10) -> 0 | F75: =E75-G75 -> 0 | G75: =C75*(D75/365)*30 -> 0 | H75: =IF((D75+G75-E75)<0,0,D75+G75-E75) -> 0 | O75: =IF(H75=0,B75,"n.a.") -> 56
B76: =B75+1 -> 57 | C76: =IF(D76>0,$F$7,0) -> 0 | D76: =H75 -> 0 | E76: =IF(H75<=E75,H75+G76,$H$10) -> 0 | F76: =E76-G76 -> 0 | G76: =C76*(D76/365)*30 -> 0 | H76: =IF((D76+G76-E76)<0,0,D76+G76-E76) -> 0 | O76: =IF(H76=0,B76,"n.a.") -> 57
B77: =B76+1 -> 58 | C77: =IF(D77>0,$F$7,0) -> 0 | D77: =H76 -> 0 | E77: =IF(H76<=E76,H76+G77,$H$10) -> 0 | F77: =E77-G77 -> 0 | G77: =C77*(D77/365)*30 -> 0 | H77: =IF((D77+G77-E77)<0,0,D77+G77-E77) -> 0 | O77: =IF(H77=0,B77,"n.a.") -> 58
B78: =B77+1 -> 59 | C78: =IF(D78>0,$F$7,0) -> 0 | D78: =H77 -> 0 | E78: =IF(H77<=E77,H77+G78,$H$10) -> 0 | F78: =E78-G78 -> 0 | G78: =C78*(D78/365)*30 -> 0 | H78: =IF((D78+G78-E78)<0,0,D78+G78-E78) -> 0 | O78: =IF(H78=0,B78,"n.a.") -> 59
B79: =B78+1 -> 60 | C79: =IF(D79>0,$F$7,0) -> 0 | D79: =H78 -> 0 | E79: =IF(H78<=E78,H78+G79,$H$10) -> 0 | F79: =E79-G79 -> 0 | G79: =C79*(D79/365)*30 -> 0 | H79: =IF((D79+G79-E79)<0,0,D79+G79-E79) -> 0 | I79: =H79/$D$5 -> #VALUE! | O79: =IF(H79=0,B79,"n.a.") -> 60
B80: =B79+1 -> 61 | C80: =IF(D80>0,$F$7,0) -> 0 | D80: =H79 -> 0 | E80: =IF(H79<=E79,H79+G80,$H$10) -> 0 | F80: =E80-G80 -> 0 | G80: =C80*(D80/365)*30 -> 0 | H80: =IF((D80+G80-E80)<0,0,D80+G80-E80) -> 0 | O80: =IF(H80=0,B80,"n.a.") -> 61
B81: =B80+1 -> 62 | C81: =IF(D81>0,$F$7,0) -> 0 | D81: =H80 -> 0 | E81: =IF(H80<=E80,H80+G81,$H$10) -> 0 | F81: =E81-G81 -> 0 | G81: =C81*(D81/365)*30 -> 0 | H81: =IF((D81+G81-E81)<0,0,D81+G81-E81) -> 0 | O81: =IF(H81=0,B81,"n.a.") -> 62
B82: =B81+1 -> 63 | C82: =IF(D82>0,$F$7,0) -> 0 | D82: =H81 -> 0 | E82: =IF(H81<=E81,H81+G82,$H$10) -> 0 | F82: =E82-G82 -> 0 | G82: =C82*(D82/365)*30 -> 0 | H82: =IF((D82+G82-E82)<0,0,D82+G82-E82) -> 0 | O82: =IF(H82=0,B82,"n.a.") -> 63
B83: =B82+1 -> 64 | C83: =IF(D83>0,$F$7,0) -> 0 | D83: =H82 -> 0 | E83: =IF(H82<=E82,H82+G83,$H$10) -> 0 | F83: =E83-G83 -> 0 | G83: =C83*(D83/365)*30 -> 0 | H83: =IF((D83+G83-E83)<0,0,D83+G83-E83) -> 0 | O83: =IF(H83=0,B83,"n.a.") -> 64
B84: =B83+1 -> 65 | C84: =IF(D84>0,$F$7,0) -> 0 | D84: =H83 -> 0 | E84: =IF(H83<=E83,H83+G84,$H$10) -> 0 | F84: =E84-G84 -> 0 | G84: =C84*(D84/365)*30 -> 0 | H84: =IF((D84+G84-E84)<0,0,D84+G84-E84) -> 0 | O84: =IF(H84=0,B84,"n.a.") -> 65
B85: =B84+1 -> 66 | C85: =IF(D85>0,$F$7,0) -> 0 | D85: =H84 -> 0 | E85: =IF(H84<=E84,H84+G85,$H$10) -> 0 | F85: =E85-G85 -> 0 | G85: =C85*(D85/365)*30 -> 0 | H85: =IF((D85+G85-E85)<0,0,D85+G85-E85) -> 0 | O85: =IF(H85=0,B85,"n.a.") -> 66
B86: =B85+1 -> 67 | C86: =IF(D86>0,$F$7,0) -> 0 | D86: =H85 -> 0 | E86: =IF(H85<=E85,H85+G86,$H$10) -> 0 | F86: =E86-G86 -> 0 | G86: =C86*(D86/365)*30 -> 0 | H86: =IF((D86+G86-E86)<0,0,D86+G86-E86) -> 0 | O86: =IF(H86=0,B86,"n.a.") -> 67
B87: =B86+1 -> 68 | C87: =IF(D87>0,$F$7,0) -> 0 | D87: =H86 -> 0 | E87: =IF(H86<=E86,H86+G87,$H$10) -> 0 | F87: =E87-G87 -> 0 | G87: =C87*(D87/365)*30 -> 0 | H87: =IF((D87+G87-E87)<0,0,D87+G87-E87) -> 0 | O87: =IF(H87=0,B87,"n.a.") -> 68
B88: =B87+1 -> 69 | C88: =IF(D88>0,$F$7,0) -> 0 | D88: =H87 -> 0 | E88: =IF(H87<=E87,H87+G88,$H$10) -> 0 | F88: =E88-G88 -> 0 | G88: =C88*(D88/365)*30 -> 0 | H88: =IF((D88+G88-E88)<0,0,D88+G88-E88) -> 0 | O88: =IF(H88=0,B88,"n.a.") -> 69
B89: =B88+1 -> 70 | C89: =IF(D89>0,$F$7,0) -> 0 | D89: =H88 -> 0 | E89: =IF(H88<=E88,H88+G89,$H$10) -> 0 | F89: =E89-G89 -> 0 | G89: =C89*(D89/365)*30 -> 0 | H89: =IF((D89+G89-E89)<0,0,D89+G89-E89) -> 0 | O89: =IF(H89=0,B89,"n.a.") -> 70
B90: =B89+1 -> 71 | C90: =IF(D90>0,$F$7,0) -> 0 | D90: =H89 -> 0 | E90: =IF(H89<=E89,H89+G90,$H$10) -> 0 | F90: =E90-G90 -> 0 | G90: =C90*(D90/365)*30 -> 0 | H90: =IF((D90+G90-E90)<0,0,D90+G90-E90) -> 0 | O90: =IF(H90=0,B90,"n.a.") -> 71
B91: =B90+1 -> 72 | C91: =IF(D91>0,$F$7,0) -> 0 | D91: =H90 -> 0 | E91: =IF(H90<=E90,H90+G91,$H$10) -> 0 | F91: =E91-G91 -> 0 | G91: =C91*(D91/365)*30 -> 0 | H91: =IF((D91+G91-E91)<0,0,D91+G91-E91) -> 0 | I91: =H91/$D$5 -> #VALUE! | O91: =IF(H91=0,B91,"n.a.") -> 72
B92: =B91+1 -> 73 | C92: =IF(D92>0,$F$7,0) -> 0 | D92: =H91 -> 0 | E92: =IF(H91<=E91,H91+G92,$H$10) -> 0 | F92: =E92-G92 -> 0 | G92: =C92*(D92/365)*30 -> 0 | H92: =IF((D92+G92-E92)<0,0,D92+G92-E92) -> 0 | O92: =IF(H92=0,B92,"n.a.") -> 73
B93: =B92+1 -> 74 | C93: =IF(D93>0,$F$7,0) -> 0 | D93: =H92 -> 0 | E93: =IF(H92<=E92,H92+G93,$H$10) -> 0 | F93: =E93-G93 -> 0 | G93: =C93*(D93/365)*30 -> 0 | H93: =IF((D93+G93-E93)<0,0,D93+G93-E93) -> 0 | O93: =IF(H93=0,B93,"n.a.") -> 74
B94: =B93+1 -> 75 | C94: =IF(D94>0,$F$7,0) -> 0 | D94: =H93 -> 0 | E94: =IF(H93<=E93,H93+G94,$H$10) -> 0 | F94: =E94-G94 -> 0 | G94: =C94*(D94/365)*30 -> 0 | H94: =IF((D94+G94-E94)<0,0,D94+G94-E94) -> 0 | O94: =IF(H94=0,B94,"n.a.") -> 75
B95: =B94+1 -> 76 | C95: =IF(D95>0,$F$7,0) -> 0 | D95: =H94 -> 0 | E95: =IF(H94<=E94,H94+G95,$H$10) -> 0 | F95: =E95-G95 -> 0 | G95: =C95*(D95/365)*30 -> 0 | H95: =IF((D95+G95-E95)<0,0,D95+G95-E95) -> 0 | O95: =IF(H95=0,B95,"n.a.") -> 76
B96: =B95+1 -> 77 | C96: =IF(D96>0,$F$7,0) -> 0 | D96: =H95 -> 0 | E96: =IF(H95<=E95,H95+G96,$H$10) -> 0 | F96: =E96-G96 -> 0 | G96: =C96*(D96/365)*30 -> 0 | H96: =IF((D96+G96-E96)<0,0,D96+G96-E96) -> 0 | O96: =IF(H96=0,B96,"n.a.") -> 77
B97: =B96+1 -> 78 | C97: =IF(D97>0,$F$7,0) -> 0 | D97: =H96 -> 0 | E97: =IF(H96<=E96,H96+G97,$H$10) -> 0 | F97: =E97-G97 -> 0 | G97: =C97*(D97/365)*30 -> 0 | H97: =IF((D97+G97-E97)<0,0,D97+G97-E97) -> 0 | O97: =IF(H97=0,B97,"n.a.") -> 78
B98: =B97+1 -> 79 | C98: =IF(D98>0,$F$7,0) -> 0 | D98: =H97 -> 0 | E98: =IF(H97<=E97,H97+G98,$H$10) -> 0 | F98: =E98-G98 -> 0 | G98: =C98*(D98/365)*30 -> 0 | H98: =IF((D98+G98-E98)<0,0,D98+G98-E98) -> 0 | O98: =IF(H98=0,B98,"n.a.") -> 79
B99: =B98+1 -> 80 | C99: =IF(D99>0,$F$7,0) -> 0 | D99: =H98 -> 0 | E99: =IF(H98<=E98,H98+G99,$H$10) -> 0 | F99: =E99-G99 -> 0 | G99: =C99*(D99/365)*30 -> 0 | H99: =IF((D99+G99-E99)<0,0,D99+G99-E99) -> 0 | O99: =IF(H99=0,B99,"n.a.") -> 80
B100: =B99+1 -> 81 | C100: =IF(D100>0,$F$7,0) -> 0 | D100: =H99 -> 0 | E100: =IF(H99<=E99,H99+G100,$H$10) -> 0 | F100: =E100-G100 -> 0 | G100: =C100*(D100/365)*30 -> 0 | H100: =IF((D100+G100-E100)<0,0,D100+G100-E100) -> 0 | O100: =IF(H100=0,B100,"n.a.") -> 81
B101: =B100+1 -> 82 | C101: =IF(D101>0,$F$7,0) -> 0 | D101: =H100 -> 0 | E101: =IF(H100<=E100,H100+G101,$H$10) -> 0 | F101: =E101-G101 -> 0 | G101: =C101*(D101/365)*30 -> 0 | H101: =IF((D101+G101-E101)<0,0,D101+G101-E101) -> 0 | O101: =IF(H101=0,B101,"n.a.") -> 82
B102: =B101+1 -> 83 | C102: =IF(D102>0,$F$7,0) -> 0 | D102: =H101 -> 0 | E102: =IF(H101<=E101,H101+G102,$H$10) -> 0 | F102: =E102-G102 -> 0 | G102: =C102*(D102/365)*30 -> 0 | H102: =IF((D102+G102-E102)<0,0,D102+G102-E102) -> 0 | O102: =IF(H102=0,B102,"n.a.") -> 83
...

Sheet pam
D1: com.variance
B2: None | D2: MRTA <2% | E2: MRTA >=2% | O2: Total | P2: Base | Q2: LP
B3: Lock 3Y | C3: BT | D3: 0.8 | E3: 1 | F3: Low | G3: DS1 | H3: Not Pre-Recommend | I3: Yes | J3: วงเงิน HL | K3: บ้านเดี่ยว | L3: เท่ากันทุกเดือน | N3: Fix Rate | O3: =SUM(P3:Q3) -> 0 | R3: FX | U3: %CC confirm by Adrian 12-Nov-24 | AH3: %CC confirm by Adrian 12-Nov-24
B4: Lock 5Y | C4: Focus | D4: 1.2 | E4: 1.25 | F4: Medium | G4: DS2 | H4: Pre-Recommend | I4: No | J4: วงเงิน MP | K4: บ้านแฝด | L4: ขั้นบันได | N4: Float Rate | O4: =SUM(P4:Q4) -> 0 | R4: FL | V4: BT | W4: Focus | X4: 2ndHand | Y4: RBP | Z4: PVL | AA4: Project | AB4: MP | AC4: PP | AD4: Other | AE4: ------- | AI4: BT | AJ4: Focus | AK4: RBP | AL4: PVL | AM4: Project | AN4: MP | AO4: PP | AP4: Other | AQ4: -------
C5: 2ndHand | D5: 1.2 | E5: 1.25 | F5: High | G5: E-Lending | H5: Final Approve | K5: ทาวน์เฮ้าส์ | P5: asof 31.03.26 | Q5: asof 01.04.26 | U5: 1 | V5: 2 | W5: 3 | X5: 4 | Y5: 5 | Z5: 6 | AA5: 7 | AB5: 8 | AC5: 9 | AD5: 10 | AE5: 11 | AF5: Total | AH5: 1 | AI5: 2 | AJ5: 3 | AK5: 4 | AL5: 5 | AM5: 6 | AN5: 7 | AO5: 8 | AP5: 9 | AQ5: 10 | AR5: Total
C6: RBP | D6: 1.2 | E6: 1.25 | F6: Very High | K6: ทาวน์โฮม | U6: Low | V6: =AI6/1.5 -> -0.0013333333 | W6: =AJ6/1.5 -> -0.001 | X6: =AJ6/1.5 -> -0.001 | Y6: =AK6/1.5 -> -0.0013333333 | Z6: =AL6/1.5 -> -0.001 | AA6: =AM6/1.5 -> -0.001 | AB6: =AN6/1.5 -> -0.002 | AC6: =AO6/1.5 -> -0.0046666667 | AD6: =AP6/1.5 -> -0.0013333333 | AE6: =AQ6/1.5 -> 0 | AF6: =AR6/1.5 -> -0.0015333333 | AH6: Low | AI6: -0.002 | AJ6: -0.0015 | AK6: -0.002 | AL6: -0.0015 | AM6: -0.0015 | AN6: -0.003 | AO6: -0.007 | AP6: -0.002 | AQ6: 0 | AR6: -0.0023
C7: PVL | D7: 1.2 | E7: 1.25 | K7: คอนโด | O7: O/N | P7: Y1 | Q7: Y2 | R7: Y3 | S7: LP | U7: Medium | V7: =AI7/1.5 -> -0.0013333333 | W7: =AJ7/1.5 -> -0.0016666667 | X7: =AJ7/1.5 -> -0.0016666667 | Y7: =AK7/1.5 -> -0.0026666667 | Z7: =AL7/1.5 -> -0.001 | AA7: =AM7/1.5 -> -0.0016666667 | AB7: =AN7/1.5 -> -0.004 | AC7: =AO7/1.5 -> -0.0046666667 | AD7: =AP7/1.5 -> -0.004 | AE7: =AQ7/1.5 -> 0 | AF7: =AR7/1.5 -> -0.002 | AH7: Medium | AI7: -0.002 | AJ7: -0.0025 | AK7: -0.004 | AL7: -0.0015 | AM7: -0.0025 | AN7: -0.006 | AO7: -0.007 | AP7: -0.006 | AQ7: 0 | AR7: -0.003
C8: Project | D8: 1.2 | E8: 1.25 | K8: Shop House | N8: FTP | O8: 0.01 | P8: 0.012 | Q8: 0.0155 | R8: 0.017 | S8: 0.0057 | U8: High | V8: =AI8/1.5 -> -0.0033333333 | W8: =AJ8/1.5 -> -0.0033333333 | X8: =AJ8/1.5 -> -0.0033333333 | Y8: =AK8/1.5 -> -0.0053333333 | Z8: =AL8/1.5 -> -0.001 | AA8: =AM8/1.5 -> -0.0033333333 | AB8: =AN8/1.5 -> -0.0086666667 | AC8: =AO8/1.5 -> -0.01 | AD8: =AP8/1.5 -> -0.006 | AE8: =AQ8/1.5 -> 0 | AF8: =AR8/1.5 -> -0.004 | AH8: High | AI8: -0.005 | AJ8: -0.005 | AK8: -0.008 | AL8: -0.0015 | AM8: -0.005 | AN8: -0.013 | AO8: -0.015 | AP8: -0.009 | AQ8: 0 | AR8: -0.006
C9: Other | K9: โกดัง | U9: Very High | V9: =AI9/1.5 -> -0.0066666667 | W9: =AJ9/1.5 -> -0.0066666667 | X9: =AJ9/1.5 -> -0.0066666667 | Y9: =AK9/1.5 -> -0.011333333 | Z9: =AL9/1.5 -> -0.002 | AA9: =AM9/1.5 -> -0.0066666667 | AB9: =AN9/1.5 -> -0.018 | AC9: =AO9/1.5 -> -0.020666667 | AD9: =AP9/1.5 -> -0.012666667 | AE9: =AQ9/1.5 -> 0 | AF9: =AR9/1.5 -> -0.0082 | AH9: Very High | AI9: -0.01 | AJ9: -0.01 | AK9: -0.017 | AL9: -0.003 | AM9: -0.01 | AN9: -0.027 | AO9: -0.031 | AP9: -0.019 | AQ9: 0 | AR9: -0.0123
C10: ------- | K10: โรงงาน | O10: FXFLFL | P10: =P8+S8 -> 0.0177 | Q10: =O8+S8 -> 0.0157 | R10: =O8+S8 -> 0.0157 | S10: =AVERAGE(P10:R10) -> 0.016366667 | U10: Total | V10: =AI10/1.5 -> 0 | W10: =AJ10/1.5 -> 0 | X10: =AJ10/1.5 -> 0 | Y10: =AK10/1.5 -> 0 | Z10: =AL10/1.5 -> 0 | AA10: =AM10/1.5 -> 0 | AB10: =AN10/1.5 -> 0 | AC10: =AO10/1.5 -> 0 | AD10: =AP10/1.5 -> 0 | AE10: =AQ10/1.5 -> 0 | AF10: =AR10/1.5 -> 0
K11: ออฟฟิส | O11: FXFXFL | P11: =Q8+S8 -> 0.0212 | Q11: =Q8+S8 -> 0.0212 | R11: =O8+S8 -> 0.0157 | S11: =AVERAGE(P11:R11) -> 0.019366667
K12: อพาร์ทเม้นท์ | O12: FXFXFX | P12: =R8+S8 -> 0.0227 | Q12: =R8+S8 -> 0.0227 | R12: =R8+S8 -> 0.0227 | S12: =AVERAGE(P12:R12) -> 0.0227 | U12: Index | V12: =HLOOKUP('1.ลดดอกเบี้ย'!C18,pam!$V$4:$AE$5,2,FALSE) -> #N/A
K13: อื่นๆ | O13: FLFXFX | P13: =O8+S8 -> 0.0157 | Q13: =R8+S8 -> 0.0227 | R13: =R8+S8 -> 0.0227 | S13: =AVERAGE(P13:R13) -> 0.020366667
O14: FLFLFX | P14: =O8+S8 -> 0.0157 | Q14: =O8+S8 -> 0.0157 | R14: =R8+S8 -> 0.0227 | S14: =AVERAGE(P14:R14) -> 0.018033333
O15: FLFLFL | P15: =O8+S8 -> 0.0157 | Q15: =O8+S8 -> 0.0157 | R15: =O8+S8 -> 0.0157 | S15: =AVERAGE(P15:R15) -> 0.0157 | V15: Total Y24 | W15: CLD | X15: DSA | Y15: E-lending
O16: FLFXFL | P16: 0.1 | Q16: 0.1 | R16: 0.1 | S16: 0.1 | U16: Salary Base | V16: 73419674 | W16: 51799836 | X16: 20366928 | Y16: 1252910
O17: FXFLFX | P17: 0.1 | Q17: 0.1 | R17: 0.1 | S17: 0.1 | U17: Staff Incentive | V17: 11125092 | W17: 2815200.8 | X17: 6460979.6 | Y17: 1848912
U18: Agent Commission | V18: 40726342 | W18: - | X18: 39906467 | Y18: 819875
U19: Total | V19: 1.2527111e+08 | W19: 54615037 | X19: 66734374 | Y19: 3921697
O21: HL | P21: =VLOOKUP('1.ลดดอกเบี้ย'!C11,pam!N3:R4,5,FALSE)&VLOOKUP('1.ลดดอกเบี้ย'!C12,pam!N3:R4,5,FALSE)&VLOOKUP('1.ลดดอกเบี้ย'!C13,pam!N3:R4,5,FALSE) -> #N/A | Q21: =VLOOKUP(P21,$O$10:$S$18,5,FALSE) -> #N/A | U21: FY24 Loan Vol. | V21: =SUM(W21:Y21) -> 24180.788 | W21: 8925.1129 | X21: 12972.039 | Y21: 2283.6355
O22: MP | P22: =VLOOKUP('1.ลดดอกเบี้ย'!E11,pam!N3:R4,5,FALSE)&VLOOKUP('1.ลดดอกเบี้ย'!E12,pam!N3:R4,5,FALSE)&VLOOKUP('1.ลดดอกเบี้ย'!E13,pam!N3:R4,5,FALSE) -> #N/A | Q22: =VLOOKUP(P22,$O$10:$S$17,5,FALSE) -> #N/A | U22: %CPL | V22: =V19/(V21*1000000) -> 0.005180605 | W22: =W19/(W21*1000000) -> 0.0061192544 | X22: =X19/(X21*1000000) -> 0.0051444783 | Y22: =Y19/(Y21*1000000) -> 0.0017173043

Sheet province
A1: กรุงเทพมหานคร | B1: กระบี่ | C1: กาญจนบุรี | D1: กาฬสินธุ์ | E1: กำแพงเพชร | F1: ขอนแก่น | G1: จันทบุรี | H1: ฉะเชิงเทรา | I1: ชลบุรี | J1: ชัยนาท | K1: ชัยภูมิ | L1: ชุมพร | M1: เชียงราย | N1: เชียงใหม่ | O1: ตรัง | P1: ตราด | Q1: ตาก | R1: นครนายก | S1: นครปฐม | T1: นครพนม | U1: นครราชสีมา | V1: นครศรีธรรมราช | W1: นครสวรรค์ | X1: นนทบุรี | Y1: นราธิวาส | Z1: น่าน | AA1: บุรีรัมย์ | AB1: ปทุมธานี | AC1: ประจวบคีรีขันธ์ | AD1: ปราจีนบุรี | AE1: ปัตตานี | AF1: พระนครศรีอยุธยา | AG1: พังงา | AH1: พัทลุง | AI1: พิจิตร | AJ1: พิษณุโลก | AK1: เพชรบุรี | AL1: เพชรบูรณ์ | AM1: แพร่ | AN1: พะเยา | AO1: ภูเก็ต | AP1: มหาสารคาม | AQ1: มุกดาหาร | AR1: แม่ฮ่องสอน | AS1: ยะลา | AT1: ยโสธร | AU1: ร้อยเอ็ด | AV1: ระนอง | AW1: ระยอง | AX1: ราชบุรี | AY1: ลพบุรี | AZ1: ลำปาง | BA1: ลำพูน | BB1: เลย | BC1: ศีรสะเกษ | BD1: สกลนคร | BE1: สงขลา | BF1: สตูล | BG1: สมุทรปราการ | BH1: สมุทรสงคราม | BI1: สมุทรสาคร | BJ1: สระแก้ว | BK1: สระบุรี | BL1: สิงห์บุรี | BM1: สุโขทัย | BN1: สุพรรณบุรี | BO1: สุราษฎร์ธานี | BP1: สุรินทร์ | BQ1: หนองคาย | BR1: หนองบัวลำภู | BS1: อ่างทอง | BT1: อุดรธานี | BU1: อุทัยธานี | BV1: อุตรดิตถ์ | BW1: อุบลราชธานี | BX1: อำนาจเจริญ
A2: คลองสาน | B2: เมืองกระบี่ | C2: เมืองกาญจนบุรี | D2: เมืองกาฬสินธุ์ | E2: เมืองกำแพงเพชร | F2: เมืองขอนแก่น | G2: เมืองจันทบุรี | H2: เมืองฉะเชิงเทรา | I2: เมืองชลบุรี | J2: เมืองชัยนาท | K2: เมืองชัยภูมิ | L2: เมืองชุมพร | M2: เมืองเชียงราย | N2: เมืองเชียงใหม่ | O2: เมืองตรัง | P2: เมืองตราด | Q2: เมืองตาก | R2: เมืองนครนายก | S2: เมืองนครปฐม | T2: เมืองนครพนม | U2: เมืองนครราชสีมา | V2: เมืองนครศรีธรรมราช | W2: เมืองนครสวรรค์ | X2: เมืองนนทบุรี | Y2: เมืองนราธิวาส | Z2: เมืองน่าน | AA2: เมืองบุรีรัมย์ | AB2: เมืองปทุมธานี | AC2: เมืองประจวบคีรีขันธ์ | AD2: เมืองปราจีนบุรี | AE2: เมืองปัตตานี | AF2: พระนครศรีอยุธยา | AG2: เมืองพังงา | AH2: เมืองพัทลุง | AI2: เมืองพิจิตร | AJ2: เมืองพิษณุโลก | AK2: เมืองเพชรบุรี | AL2: เมืองเพชรบูรณ์ | AM2: เมืองแพร่ | AN2: เมืองพะเยา | AO2: เมืองภูเก็ต | AP2: เมืองมหาสารคาม | AQ2: เมืองมุกดาหาร | AR2: เมืองแม่ฮ่องสอน | AS2: เมืองยะลา | AT2: เมืองยโสธร | AU2: เมืองร้อยเอ็ด | AV2: เมืองระนอง | AW2: เมืองระยอง | AX2: เมืองราชบุรี | AY2: เมืองลพบุรี | AZ2: เมืองลำปาง | BA2: เมืองลำพูน | BB2: เมืองเลย | BC2: เมืองศีรสะเกษ | BD2: เมืองสกลนคร | BE2: เมืองสงขลา | BF2: เมืองสตูล | BG2: เมืองสมุทรปราการ | BH2: เมืองสมุทรสงคราม | BI2: เมืองสมุทรสาคร | BJ2: เมืองสระแก้ว | BK2: เมืองสระบุรี | BL2: เมืองสิงห์บุรี | BM2: เมืองสุโขทัย | BN2: เมืองสุพรรณบุรี | BO2: เมืองสุราษฎร์ธานี | BP2: เมืองสุรินทร์ | BQ2: เมืองหนองคาย | BR2: เมืองหนองบัวลำภู | BS2: เมืองอ่างทอง | BT2: เมืองอุดรธานี | BU2: เมืองอุทัยธานี | BV2: เมืองอุตรดิตถ์ | BW2: เมืองอุบลราชธานี | BX2: เมืองอำนาจเจริญ
A3: คลองเตย | B3: เกาะลันตา | C3: ด่านมะขามเตี้ย | D3: กมลาไสย | E3: ขาณุวรลักษบุรี | F3: กระนวน | G3: แก่งหางแมว | H3: บางคล้า | I3: เกาะสีชัง | J3: มโนรมย์ | K3: เกษตรสมบูรณ์ | L3: ท่าแซะ | M3: ขุนตาล | N3: จอมทอง | O3: กันตัง | P3: เกาะช้าง | Q3: ท่าสองยาง | R3: บ้านนา | S3: กำแพงแสน | T3: ท่าอุเทน | U3: แก้งสนามนาง | V3: ขนอม | W3: เก้าเลี้ยว | X3: ไทรน้อย | Y3: จะแนะ | Z3: เชียงกลาง | AA3: กระสัง | AB3: คลองหลวง | AC3: กุยบุรี | AD3: กบินทร์บุรี | AE3: กะพ้อ | AF3: ท่าเรือ | AG3: กะปง | AH3: กงหรา | AI3: ตะพานหิน | AJ3: นครไทย | AK3: แก่งกระจาน | AL3: เขาค้อ | AM3: เด่นชัย | AN3: จุน | AO3: กะทู้ | AP3: กันทรวิชัย | AQ3: คำชะอี | AR3: ขุนยวม | AS3: กาบัง | AT3: กุดชุม | AU3: เกษตรวิสัย | AV3: กระบุรี | AW3: แกลง | AX3: จอมบึง | AY3: โคกเจริญ | AZ3: เกาะคา | BA3: ทุ่งหัวช้าง | BB3: เชียงคาน | BC3: กันทรลักษ์ | BD3: กุดบาก | BE3: กระแสสินธุ์ | BF3: ควนกาหลง | BG3: บางบ่อ | BH3: บางคณที | BI3: กระทุ่มแบน | BJ3: เขาฉกรรจ์ | BK3: แก่งคอย | BL3: ค่ายบางระจัน | BM3: กงไกรลาศ | BN3: ดอนเจดีย์ | BO3: กาญจนดิษฐ์ | BP3: กาบเชิง | BQ3: เซกา | BR3: นากลาง | BS3: ไชโย | BT3: กู่แก้ว | BU3: ทัพทัน | BV3: ตรอน | BW3: กุดข้าวปุ้น | BX3: ชานุมาน
A4: จอมทอง | B4: เขาพนม | C4: ทองผาภูมิ | D4: กุฉินารายณ์ | E4: คลองขลุง | F4: เขาสวนกวาง | G4: ขลุง | H4: บางน้ำเปรี้ยว | I4: บ่อทอง | J4: วัดสิงห์ | K4: แก้งคร้อ | L4: ทุ่งตะโก | M4: เชียงของ | N4: เชียงดาว | O4: ปะเหลียน | P4: เขาสมิง | Q4: บ้านตาก | R4: ปากพลี | S4: ดอนตูม | T4: ธาตุพนม | U4: ขามทะเลสอ | V4: ฉวาง | W4: โกรกพระ | X4: บางกรวย | Y4: ตากใบ | Z4: ท่าวังผา | AA4: คูเมือง | AB4: ธัญบุรี | AC4: ทับสะแก | AD4: ศรีมโหสถ | AE4: โคกโพธิ์ | AF4: นครหลวง | AG4: เกาะยาว | AH4: เขาชัยสน | AI4: ทับคล้อ | AJ4: ชาติตระการ | AK4: เขาย้อย | AL4: ชนแดน | AM4: ร้องกวาง | AN4: เชียงคำ | AO4: ถลาง | AP4: แกดำ | AQ4: ดงหลวง | AR4: ปางมะผ้า | AS4: กรงปินัง | AT4: ค้อวัง | AU4: จตุรพักตร์พิมาน | AV4: กะเปอร์ | AW4: บ้านค่าย | AX4: ดำเนินสะดวก | AY4: โคกสำโรง | AZ4: งาว | BA4: บ้านโฮ่ง | BB4: ด่านซ้าย | BC4: กันทรารมย์ | BD4: กุสุมาลย์ | BE4: ควนเนียง | BF4: ควนโดน | BG4: บางพลี | BH4: อัมพวา | BI4: บ้านแพ้ว | BJ4: คลองหาด | BK4: ดอนพุด | BL4: ท่าช้าง | BM4: คีรีมาศ | BN4: ด่านช้าง | BO4: เกาะพะงัน | BP4: จอมพระ | BQ4: โซ่พิสัย | BR4: โนนสัง | BS4: ป่าโมก | BT4: กุดจับ | BU4: บ้านไร่ | BV4: ทองแสนขัน | BW4: เขมราฐ | BX4: ปทุมราชวงศา
A5: จตุจักร | B5: คลองท่อม | C5: ท่าม่วง | D5: เขาวง | E5: คลองลาน | F5: โคกโพธิ์ไชย | G5: ท่าใหม่ | H5: บางปะกง | I5: บางละมุง | J5: สรรคบุรี | K5: คอนสวรรค์ | L5: ปะทิว | M5: เชียงแสน | N5: ไชยปราการ | O5: ย่านตาขาว | P5: คลองใหญ่ | Q5: พบพระ | R5: องครักษ์ | S5: นครชัยศรี | T5: นาแก | U5: ขามสะแกแสง | V5: ชะอวด | W5: ชุมแสง | X5: บางบัวทอง | Y5: บาเจาะ | Z5: ทุ่งช้าง | AA5: ชำนิ | AB5: ลาดหลุมแก้ว | AC5: บางสะพาน | AD5: นาดี | AE5: ทุ่งยางแดง | AF5: บางซ้าย | AG5: คุระบุรี | AH5: ควนขนุน | AI5: บางมูลนาก | AJ5: เนินมะปราง | AK5: ชะอำ | AL5: น้ำหนาว | AM5: ลอง | AN5: เชียงม่วน | AP5: โกสุมพิสัย | AQ5: ดอนตาล | AR5: ปาย | AS5: ธารโต | AT5: คำเขื่อนแก้ว | AU5: จังหาร | AV5: ละอุ่น | AW5: บ้านฉาง | AX5: บางแพ | AY5: ชัยบาดาล | AZ5: แจ้ห่ม | BA5: ป่าซาง | BB5: ท่าลี่ | BC5: ขุขันธ์ | BD5: คำตากล้า | BE5: จะนะ | BF5: ท่าแพ | BG5: พระประแดง | BJ5: ตาพระยา | BK5: บ้านหมอ | BL5: บางระจัน | BM5: ทุ่งเสลี่ยม | BN5: เดิมบางนางบวช | BO5: เกาะสมุย | BP5: ชุมพลบุรี | BQ5: ท่าบ่อ | BR5: ศรีบุญเรือง | BS5: โพธิ์ทอง | BT5: กุมภวาปี | BU5: ลานสัก | BV5: ท่าปลา | BW5: เขื่องใน | BX5: พนา
A6: ดุสิต | B6: ปลายพระยา | C6: ท่ามะกา | D6: คำม่วง | E6: ทรายทองวัฒนา | F6: ชำสูง | G6: นายายอาม | H6: บ้านโพธิ์ | I6: บ้านบึง | J6: สรรพยา | K6: คอนสาร | L6: พะโต๊ะ | M6: เทิง | N6: ดอยเต่า | O6: รัษฎา | P6: บ่อไร่ | Q6: แม่ระมาด | S6: บางเลน | T6: นาหว้า | U6: คง | V6: เชียรใหญ่ | W6: ตากฟ้า | X6: บางใหญ่ | Y6: ยี่งอ | Z6: นาน้อย | AA6: นาโพธิ์ | AB6: ลำลูกกา | AC6: บางสะพานน้อย | AD6: บ้านสร้าง | AE6: ปะนาเระ | AF6: บางไทร | AG6: ตะกั่วทุ่ง | AH6: ตะโหมด | AI6: โพทะเล | AJ6: บางกระทุ่ม | AK6: ท่ายาง | AL6: บึงสามพัน | AM6: วังชิ้น | AN6: ดอกคำใต้ | AP6: เชียงยืน | AQ6: นิคมคำสร้อย | AR6: แม่ลาน้อย | AS6: บันนังสตา | AT6: ไทยเจริญ | AU6: ธวัชบุรี | AV6: สุขสำราญ | AW6: ปลวกแดง | AX6: บ้านโป่ง | AY6: ท่าวุ้ง | AZ6: เถิน | BA6: แม่ทา | BB6: นาด้วง | BC6: ขุนหาญ | BD6: เจริญศิลป์ | BE6: เทพา | BF6: ทุ่งหว้า | BG6: พระสมุทรเจดีย์ | BJ6: วังน้ำเย็น | BK6: พระพุทธบาท | BL6: พรหมบุรี | BM6: บ้านด่านลานหอย | BN6: บางปลาม้า | BO6: คีรีรัฐนิคม | BP6: ท่าตูม | BQ6: บึงกาฬ | BR6: สุวรรณคูหา | BS6: วิเศษชัยชาญ | BT6: ไชยวาน | BU6: สว่างอารมณ์ | BV6: น้ำปาด | BW6: โขงเจียม | BX6: เสนางคนิคม
A7: ดอนเมือง | B7: ลำทับ | C7: ไทรโยค | D7: ท่าคันโท | E7: ไทรงาม | F7: ชนบท | G7: โป่งน้ำร้อน | H7: แปลงยาว | I7: พานทอง | J7: หันคา | K7: จัตุรัส | L7: ละแม | M7: ป่าแดด | N7: ดอยหล่อ | O7: สิเกา | P7: แหลมงอบ | Q7: แม่สอด | S7: พุทธมณฑล | T7: บ้านแพง | U7: ครบุรี | V7: ท่าศาลา | W7: ตาคลี | X7: ปากเกร็ด | Y7: ระแงะ | Z7: นาหมื่น | AA7: นางรอง | AB7: สามโคก | AC7: ปราณบุรี | AD7: ประจันตคาม | AE7: มายอ | AF7: บางบาล | AG7: ตะกั่วป่า | AH7: ปากพะยูน | AI7: โพธิ์ประทับช้าง | AJ7: บางระกำ | AK7: บ้านลาด | AL7: วิเชียรบุรี | AM7: สอง | AN7: ปง | AP7: นาเชือก | AQ7: หนองสูง | AR7: แม่สะเรียง | AS7: เบตง | AT7: ทรายมูล | AU7: ปทุมรัตน์ | AW7: วังจันทร์ | AX7: ปากท่อ | AY7: ท่าหลวง | AZ7: แม่ทะ | BA7: ลี้ | BB7: นาแห้ว | BC7: น้ำเกลี้ยง | BD7: เต่างอย | BE7: นาทวี | BF7: ละงู | BG7: บางเสาธง | BJ7: วัฒนานคร | BK7: มวกเหล็ก | BL7: อินทร์บุรี | BM7: ศรีนคร | BN7: ศรีประจันต์ | BO7: เคียนซา | BP7: บัวเชด | BQ7: บึงโขลงหลง | BR7: นาวัง | BS7: สามโก้ | BT7: ทุ่งฝน | BU7: หนองขาหย่าง | BV7: บ้านโคก | BW7: เดชอุดม | BX7: หัวตะพาน
A8: ตลิ่งชัน | B8: เหนือคลอง | C8: บ่อพลอย | D8: นามน | E8: ปางศิลาทอง | F8: ชุมแพ | G8: มะขาม | H8: พนมสารคาม | I8: พนัสนิคม | J8: หนองมะโมง | K8: เทพสถิต | L8: สวี | M8: พาน | N8: ดอยสะเก็ด | O8: ห้วยยอด | P8: เกาะกูด | Q8: สามเงา | S8: สามพราน | T8: ปลาปาก | U8: จักราช | V8: ทุ่งใหญ่ | W8: ท่าตะโก | Y8: รือเสาะ | Z8: บ้านหลวง | AA8: โนนดินแดง | AB8: หนองเสือ | AC8: หัวหิน | AD8: ศรีมหาโพธิ | AE8: ไม้แก่น | AF8: บางปะหัน | AG8: ทับปุด | AH8: ป่าบอน | AI8: สามง่าม | AJ8: พรหมพิราม | AK8: บ้านแหลม | AL8: ศรีเทพ | AM8: หนองม่วงไข่ | AN8: แม่ใจ | AP8: นาดูน | AQ8: หว้านใหญ่ | AR8: สบเมย | AS8: ยะหา | AT8: ป่าติ้ว | AU8: พนมไพร | AW8: เขาชะเมา | AX8: โพธาราม | AY8: บ้านหมี่ | AZ8: แม่พริก | BA8: บ้านธิ | BB8: ปากชม | BC8: โนนคูณ | BD8: นิคมน้ำอูน | BE8: นาหม่อม | BF8: มะนัง | BJ8: อรัญประเทศ | BK8: วิหารแดง | BM8: ศรีสัชนาลัย | BN8: สองพี่น้อง | BO8: ชัยบุรี | BP8: ปราสาท | BQ8: ปากคาด | BS8: แสวงหา | BT8: นายูง | BU8: หนองฉาง | BV8: พิชัย | BW8: ตระการพืชผล | BX8: ลืออำนาจ
A9: ธนบุรี | B9: อ่าวลึก | C9: พนมทวน | D9: ยางตลาด | E9: พรานกระต่าย | F9: น้ำพอง | G9: สอยดาว | H9: ราชสาส์น | I9: ศรีราชา | J9: เนินขาม | K9: เนินสง่า | L9: หลังสวน | M9: แม่จัน | N9: ฝาง | O9: วังวิเศษ | Q9: อุ้มผาง | T9: โพนสวรรค์ | U9: ชุมพวง | V9: ทุ่งสง | W9: บรรพตพิสัย | Y9: แว้ง | Z9: ปัว | AA9: โนนสุวรรณ | AC9: สามร้อยยอด | AE9: ยะรัง | AF9: บางปะอิน | AG9: ท้ายเหมือง | AH9: ป่าพะยอม | AI9: วังทรายพูน | AJ9: วังทอง | AK9: หนองหญ้าปล้อง | AL9: หนองไผ่ | AM9: สูงเม่น | AN9: ภูซาง | AP9: บรบือ | AS9: รามัน | AT9: มหาชนะชัย | AU9: โพธิ์ชัย | AW9: นิคมพัฒนา | AX9: วัดเพลง | AY9: พัฒนานิคม | AZ9: เมืองปาน | BA9: เวียงหนองล่อง | BB9: ผาขาว | BC9: บึงบูรพ์ | BD9: บ้านม่วง | BE9: บางกล่ำ | BJ9: โคกสูง | BK9: เสาไห้ | BM9: ศรีสำโรง | BN9: สามชุก | BO9: ไชยา | BP9: รัตนบุรี | BQ9: พรเจริญ | BT9: น้ำโสม | BU9: ห้วยคต | BV9: ฟากท่า | BW9: ตาลสุม
A10: บางกอกน้อย | C10: เลาขวัญ | D10: ร่องคำ | E10: ลานกระบือ | F10: บ้านไผ่ | G10: แหลมสิงห์ | H10: สนามชัยเขต | I10: สัตหีบ | K10: บ้านเขว้า | M10: แม่ฟ้าหลวง | N10: พร้าว | O10: หาดสำราญ | Q10: วังเจ้า | T10: เรณูนคร | U10: โชคชัย | V10: พระพรหม | W10: พยุหคีรี | Y10: ศรีสาคร | Z10: แม่จริม | AA10: บ้านกรวด | AE10: ยะหริ่ง | AF10: บ้านแพรก | AH10: ศรีบรรพต | AI10: สากเหล็ก | AJ10: วัดโบสถ์ | AL10: หล่มเก่า | AN10: ภูกามยาว | AP10: พยัคฆภูมิพิสัย | AT10: เลิงนกทา | AU10: โพนทราย | AX10: สวนผึ้ง | AY10: ลำสนธิ | AZ10: แม่เมาะ | BB10: ภูกระดึง | BC10: เบญจลักษณ์ | BD10: พรรณานิคม | BE10: ระโนด | BJ10: วังสมบูรณ์ | BK10: หนองแค | BM10: สวรรคโลก | BN10: อู่ทอง | BO10: ดอนสัก | BP10: ลำดวน | BQ10: โพนพิสัย | BT10: โนนสะอาด | BV10: ลับแล | BW10: ทุ่งศรีอุดม
A11: บางกอกใหญ่ | C11: ศรีสวัสดิ์ | D11: สมเด็จ | E11: บึงสามัคคี | F11: บ้านฝาง | G11: เขาคิชฌกูฏ | H11: ท่าตะเกียบ | I11: หนองใหญ่ | K11: บ้านแท่น | M11: แม่สรวย | N11: แม่แจ่ม | O11: นาโยง | T11: ศรีสงคราม | U11: ด่านขุนทด | V11: นาบอน | W11: ไพศาลี | Y11: สุคิริน | Z11: เวียงสา | AA11: พลับพลาชัย | AE11: สายบุรี | AF11: ผักไห่ | AH11: บางแก้ว | AI11: บึงนาราง | AL11: หล่มสัก | AP11: วาปีปทุม | AU11: โพนทอง | AX11: บ้านคา | AY11: สระโบถส์ | AZ11: วังเหนือ | BB11: ภูเรือ | BC11: ปรางค์กู่ | BD11: พังโคน | BE11: รัตภูมิ | BK11: หนองแซง | BN11: หนองหญ้าไซ | BO11: ท่าฉาง | BP11: ศีขรภูมิ | BQ11: ศรีเชียงใหม่ | BT11: บ้านดุง | BW11: นาจะหลวย
A12: บางกะปิ | C12: สังขละบุรี | D12: สหัสขันธ์ | E12: โกสัมพีนคร | F12: เปือยน้อย | H12: คลองเขื่อน | I12: เกาะจันทร์ | K12: บำเหน็จณรงค์ | M12: แม่สาย | N12: แม่แตง | T12: วังยาง | U12: โนนแดง | V12: บางขัน | W12: แม่วงก์ | Y12: สุไหงโกลก | Z12: สันติสุข | AA12: บ้านใหม่ไชยพจน์ | AE12: หนองจิก | AF12: ภาชี | AH12: ศรีนครินทร์ | AI12: ดงเจริญ | AL12: วังโป่ง | AP12: กุดรัง | AU12: เมยวดี | AY12: หนองม่วง | AZ12: สบปราบ | BB12: ภูหลวง | BC12: พยุห์ | BD12: วานรนิวาส | BE12: สทิงพระ | BK12: หนองโดน | BO12: ท่าชนะ | BP12: สนม | BQ12: ศรีวิไล | BT12: บ้านผือ | BW12: น้ำยืน
A13: บางขุนเทียน | C13: หนองปรือ | D13: หนองกุงศรี | F13: พล | K13: ภูเขียว | M13: เวียงแก่น | N13: แม่ริม | T13: นาทม | U13: โนนไทย | V13: ปากพนัง | W13: ลาดยาว | Y13: สุไหงปาดี | Z13: บ่อเกลือ | AA13: ประโคนชัย | AE13: แม่ลาน | AF13: มหาราช | AI13: วชิรบารมี | AP13: ยางสีสุราช | AU13: เมืองสรวง | AZ13: เสริมงาม | BB13: วังสะพุง | BC13: ไพรบึง | BD13: วาริชภูมิ | BE13: สะเดา | BK13: วังม่วง | BO13: บ้านตาขุน | BP13: สังขะ | BQ13: สังคม | BT13: พิบูลย์รักษ์ | BW13: บุณฑริก
A14: บางเขน | C14: ห้วยกระเจา | D14: ห้วยผึ้ง | F14: พระยืน | K14: ภักดีชุมพล | M14: เวียงชัย | N14: แม่วาง | U14: โนนสูง | V14: พรหมคีรี | W14: หนองบัว | Y14: เจาะไอร้อง | Z14: สองแคว | AA14: ปะคำ | AF14: ลาดบัวหลวง | AP14: ชื่นชม | AU14: ศรีสมเด็จ | AZ14: ห้างฉัตร | BB14: เอราวัณ | BC14: โพธิ์ศรีสุวรรณ | BD14: โคกศรีสุพรรณ | BE14: สะบ้าย้อย | BK14: เฉลิมพระเกียรติ | BO14: บ้านนาเดิม | BP14: สำโรงทาบ | BQ14: สระใคร่ | BT14: เพ็ญ | BW14: พิบูลมังสาหาร
A15: บางคอแหลม | D15: ห้วยเม็ก | F15: ภูเวียง | K15: หนองบัวแดง | M15: เวียงป่าเป้า | N15: แม่อาย | U15: บัวใหญ่ | V15: พิปูน | W15: แม่เปิน | Z15: เฉลิมพระเกียรติ | AA15: พุทไธสง | AF15: วังน้อย | AU15: เสลภูมิ | BB15: หนองหิน | BC15: ภูสิงห์ | BD15: สว่างแดนดิน | BE15: สิงหนคร | BO15: บ้านนาสาร | BP15: ศรีณรงค์ | BQ15: บุ่งคล้า | BT15: วังสามหมอ | BW15: โพธิ์ไทร
A16: บางซื่อ | D16: นาคู | F16: ภูผาม่าน | K16: หนองบัวระเหว | M16: พญาเม็งราย | N16: แม่ออน | U16: บ้านเหลื่อม | V16: ร่อนพิบูลย์ | W16: ชุมตาบง | Z16: ภูเพียง | AA16: ละหานทราย | AF16: เสนา | AU16: สุวรรณภูมิ | BC16: เมืองจันทร์ | BD16: ส่องดาว | BE16: หาดใหญ่ | BO16: พนม | BP16: พนมดงรัก | BQ16: รัตนวาปี | BT16: ศรีธาตุ | BW16: ม่วงสามสิบ
A17: บางพลัด | D17: สามชัย | F17: มัญจาคีรี | K17: ซับใหญ่ | M17: แม่ลาว | N17: เวียงแหง | U17: ประทาย | V17: ลานสะกา | AA17: ลำปลายมาศ | AF17: อุทัย | AU17: หนองพอก | BC17: ยางชุมน้อย | BD17: อากาศอำนวย | BE17: คลองหอยโข่ง | BO17: พระแสง | BP17: เขวาสินรินทร์ | BQ17: เฝ้าไร่ | BT17: สร้างคอม | BW17: เหล่าเสือโก้ก
A18: บางรัก | D18: ดอนจาน | F18: แวงน้อย | M18: ดอยหลวง | N18: สะเมิง | U18: ปักธงชัย | V18: สิชล | AA18: สตึก | AU18: อาจสามารถ | BC18: ราษีไศล | BD18: ภูพาน | BO18: พุนพิน | BP18: โนนนารายณ์ | BQ18: โพธิ์ตาก | BT18: หนองวัวซอ | BW18: วารินชำราบ
A19: บึงกุ่ม | D19: ฆ้องชัย | F19: แวงใหญ่ | M19: เวียงเชียงรุ้ง | N19: สันกำแพง | U19: ปากช่อง | V19: หัวไทร | AA19: หนองกี่ | AU19: เชียงขวัญ | BC19: วังหิน | BD19: โพนนาแก้ว | BO19: วิภาวดี | BT19: หนองหาน | BW19: ศรีเมืองใหม่
A20: ประเวศ | F20: สีชมพู | N20: สันทราย | U20: พิมาย | V20: จุฬาภรณ์ | AA20: หนองหงส์ | AU20: หนองฮี | BC20: ศรีรัตนะ | BO20: เวียงสระ | BT20: หนองแสง | BW20: สำโรง
A21: ปทุมวัน | F21: หนองสองห้อง | N21: สันป่าตอง | U21: วังน้ำเขียว | V21: นบพิตำ | AA21: ห้วยราช | AU21: ทุ่งเขาหลวง | BC21: ห้วยทับทัน | BT21: ประจักษ์ศิลปาคาม | BW21: สิรินธร
A22: ป้อมปราบศัตรูพ่าย | F22: หนองเรือ | N22: สารภี | U22: สีคิ้ว | V22: ช้างกลาง | AA22: บ้านด่าน | BC22: อุทุมพรพิสัย | BW22: นาเยีย
A23: พญาไท | F23: หนองนาคำ | N23: หางดง | U23: สูงเนิน | V23: ถ้ำพรรณรา | AA23: เฉลิมพระเกียรติ | BC23: ศิลาลาด | BW23: นาตาล
A24: พระโขนง | F24: อุบลรัตน์ | N24: อมก๋อย | U24: เสิงสาง | V24: เฉลิมพระเกียรติ | AA24: แคนดง | BW24: สว่างวีระวงศ์
A25: พระนคร | F25: โนนศิลา | N25: ฮอด | U25: ห้วยแถลง | BW25: น้ำขุ่น
A26: ภาษีเจริญ | F26: บ้านแฮด | U26: หนองบุนนาก | BW26: ดอนมดแดง
A27: มีนบุรี | U27: เทพารักษ์
A28: ยานนาวา | U28: เมืองยาง
A29: ราชเทวี | U29: พระทองคำ
A30: ราษฎร์บูรณะ | U30: ลำทะเมนชัย
A31: ลาดกระบัง | U31: เฉลิมพระเกียรติ
A32: ลาดพร้าว | U32: สีดา
A33: สาทร | U33: บัวลาย
A34: สัมพันธวงศ์
A35: หนองแขม
A36: หนองจอก
A37: ห้วยขวาง
A38: สวนหลวง
A39: ดินแดง
A40: หลักสี่
A41: สายไหม
A42: คันนายาว
A43: สะพานสูง
A44: วังทองหลาง
A45: คลองสามวา
... A51: บางบอน

Sheet Straight-HL
B1: Loan | C1: ='1.ลดดอกเบี้ย'!C8 -> 0 | G1: =[2]ตาราง!T25 -> No Insurance | H1: Y1 | I1: Y2 | J1: Y3 | K1: Y4+
B2: Tenor | C2: ='1.ลดดอกเบี้ย'!C9 -> 0 | G2: Insurance | H2: 0.055 | I2: 0.055 | J2: 0.055 | K2: 0.07725
B3: Interest 1 | C3: ='1.ลดดอกเบี้ย'!D11 -> 0 | D3: 12 | E3: =C3*D3 -> 0 | G3: No Insurance | H3: 0.057 | I3: 0.057 | J3: 0.057 | K3: 0.07725
B4: Interest 2 | C4: ='1.ลดดอกเบี้ย'!D12 -> 0 | D4: 12 | E4: =C4*D4 -> 0
B5: Interest 3 | C5: ='1.ลดดอกเบี้ย'!D13 -> 0 | D5: 12 | E5: =C5*D5 -> 0
B6: Interest 4+ | C6: ='1.ลดดอกเบี้ย'!D14 -> 0 | D6: =(C2*12)-SUM(D3:D5) -> -36 | E6: =C6*D6 -> 0
E7: =SUM(E3:E6)/(C2*12) -> #DIV/0!
B9: Buffer (+1%) | C9: =E7+0.75% -> #DIV/0! | D9: Bal 0 in mth | E9: {=CELL("row",INDEX(C14:C493,MATCH(MIN(C14:C493),C14:C493,0)))-ROW(C14)+1} -> 1 | I9: %COF
B10: Installment | C10: =IFERROR(ROUNDUP(PMT(C9/12,C2*12,-C1),-1),0) -> 0 | I10: 0.028
A12: No. | B12: Int Rate | C12: Beg.OS | D12: Mthy Pay | E12: Int Paid | F12: OS Paid | G12: End.OS | H12: LTV | I12: COF
D13: =-C14 -> 0
A14: 1 | B14: =$C$3 -> 0 | C14: =C1 -> 0 | D14: =IF(C14+E14>$C$10,$C$10,C14+E14) -> 0 | E14: =C14*(B14/12) -> 0 | F14: =IF(C14<$C$10,C14,D14-E14) -> 0 | G14: =C14-F14 -> 0 | H14: =G14/$C$1 -> #DIV/0! | I14: =C14*$I$10/12 -> 0
A15: 2 | B15: =$C$3 -> 0 | C15: =G14 -> 0 | D15: =IF(C15+E15>$C$10,$C$10,C15+E15) -> 0 | E15: =C15*(B15/12) -> 0 | F15: =IF(C15<$C$10,C15,D15-E15) -> 0 | G15: =C15-F15 -> 0 | H15: =G15/$C$1 -> #DIV/0! | I15: =C15*$I$10/12 -> 0
A16: 3 | B16: =$C$3 -> 0 | C16: =G15 -> 0 | D16: =IF(C16+E16>$C$10,$C$10,C16+E16) -> 0 | E16: =C16*(B16/12) -> 0 | F16: =IF(C16<$C$10,C16,D16-E16) -> 0 | G16: =C16-F16 -> 0 | H16: =G16/$C$1 -> #DIV/0! | I16: =C16*$I$10/12 -> 0
A17: 4 | B17: =$C$3 -> 0 | C17: =G16 -> 0 | D17: =IF(C17+E17>$C$10,$C$10,C17+E17) -> 0 | E17: =C17*(B17/12) -> 0 | F17: =IF(C17<$C$10,C17,D17-E17) -> 0 | G17: =C17-F17 -> 0 | H17: =G17/$C$1 -> #DIV/0! | I17: =C17*$I$10/12 -> 0
A18: 5 | B18: =$C$3 -> 0 | C18: =G17 -> 0 | D18: =IF(C18+E18>$C$10,$C$10,C18+E18) -> 0 | E18: =C18*(B18/12) -> 0 | F18: =IF(C18<$C$10,C18,D18-E18) -> 0 | G18: =C18-F18 -> 0 | H18: =G18/$C$1 -> #DIV/0! | I18: =C18*$I$10/12 -> 0
A19: 6 | B19: =$C$3 -> 0 | C19: =G18 -> 0 | D19: =IF(C19+E19>$C$10,$C$10,C19+E19) -> 0 | E19: =C19*(B19/12) -> 0 | F19: =IF(C19<$C$10,C19,D19-E19) -> 0 | G19: =C19-F19 -> 0 | H19: =G19/$C$1 -> #DIV/0! | I19: =C19*$I$10/12 -> 0
A20: 7 | B20: =$C$3 -> 0 | C20: =G19 -> 0 | D20: =IF(C20+E20>$C$10,$C$10,C20+E20) -> 0 | E20: =C20*(B20/12) -> 0 | F20: =IF(C20<$C$10,C20,D20-E20) -> 0 | G20: =C20-F20 -> 0 | H20: =G20/$C$1 -> #DIV/0! | I20: =C20*$I$10/12 -> 0
A21: 8 | B21: =$C$3 -> 0 | C21: =G20 -> 0 | D21: =IF(C21+E21>$C$10,$C$10,C21+E21) -> 0 | E21: =C21*(B21/12) -> 0 | F21: =IF(C21<$C$10,C21,D21-E21) -> 0 | G21: =C21-F21 -> 0 | H21: =G21/$C$1 -> #DIV/0! | I21: =C21*$I$10/12 -> 0
A22: 9 | B22: =$C$3 -> 0 | C22: =G21 -> 0 | D22: =IF(C22+E22>$C$10,$C$10,C22+E22) -> 0 | E22: =C22*(B22/12) -> 0 | F22: =IF(C22<$C$10,C22,D22-E22) -> 0 | G22: =C22-F22 -> 0 | H22: =G22/$C$1 -> #DIV/0! | I22: =C22*$I$10/12 -> 0
A23: 10 | B23: =$C$3 -> 0 | C23: =G22 -> 0 | D23: =IF(C23+E23>$C$10,$C$10,C23+E23) -> 0 | E23: =C23*(B23/12) -> 0 | F23: =IF(C23<$C$10,C23,D23-E23) -> 0 | G23: =C23-F23 -> 0 | H23: =G23/$C$1 -> #DIV/0! | I23: =C23*$I$10/12 -> 0
A24: 11 | B24: =$C$3 -> 0 | C24: =G23 -> 0 | D24: =IF(C24+E24>$C$10,$C$10,C24+E24) -> 0 | E24: =C24*(B24/12) -> 0 | F24: =IF(C24<$C$10,C24,D24-E24) -> 0 | G24: =C24-F24 -> 0 | H24: =G24/$C$1 -> #DIV/0! | I24: =C24*$I$10/12 -> 0
A25: 12 | B25: =$C$3 -> 0 | C25: =G24 -> 0 | D25: =IF(C25+E25>$C$10,$C$10,C25+E25) -> 0 | E25: =C25*(B25/12) -> 0 | F25: =IF(C25<$C$10,C25,D25-E25) -> 0 | G25: =C25-F25 -> 0 | H25: =G25/$C$1 -> #DIV/0! | I25: =C25*$I$10/12 -> 0
A26: 13 | B26: =$C$4 -> 0 | C26: =G25 -> 0 | D26: =IF(C26+E26>$C$10,$C$10,C26+E26) -> 0 | E26: =C26*(B26/12) -> 0 | F26: =IF(C26<$C$10,C26,D26-E26) -> 0 | G26: =C26-F26 -> 0 | H26: =G26/$C$1 -> #DIV/0! | I26: =C26*$I$10/12 -> 0
A27: 14 | B27: =$C$4 -> 0 | C27: =G26 -> 0 | D27: =IF(C27+E27>$C$10,$C$10,C27+E27) -> 0 | E27: =C27*(B27/12) -> 0 | F27: =IF(C27<$C$10,C27,D27-E27) -> 0 | G27: =C27-F27 -> 0 | H27: =G27/$C$1 -> #DIV/0! | I27: =C27*$I$10/12 -> 0
A28: 15 | B28: =$C$4 -> 0 | C28: =G27 -> 0 | D28: =IF(C28+E28>$C$10,$C$10,C28+E28) -> 0 | E28: =C28*(B28/12) -> 0 | F28: =IF(C28<$C$10,C28,D28-E28) -> 0 | G28: =C28-F28 -> 0 | H28: =G28/$C$1 -> #DIV/0! | I28: =C28*$I$10/12 -> 0
A29: 16 | B29: =$C$4 -> 0 | C29: =G28 -> 0 | D29: =IF(C29+E29>$C$10,$C$10,C29+E29) -> 0 | E29: =C29*(B29/12) -> 0 | F29: =IF(C29<$C$10,C29,D29-E29) -> 0 | G29: =C29-F29 -> 0 | H29: =G29/$C$1 -> #DIV/0! | I29: =C29*$I$10/12 -> 0
A30: 17 | B30: =$C$4 -> 0 | C30: =G29 -> 0 | D30: =IF(C30+E30>$C$10,$C$10,C30+E30) -> 0 | E30: =C30*(B30/12) -> 0 | F30: =IF(C30<$C$10,C30,D30-E30) -> 0 | G30: =C30-F30 -> 0 | H30: =G30/$C$1 -> #DIV/0! | I30: =C30*$I$10/12 -> 0
A31: 18 | B31: =$C$4 -> 0 | C31: =G30 -> 0 | D31: =IF(C31+E31>$C$10,$C$10,C31+E31) -> 0 | E31: =C31*(B31/12) -> 0 | F31: =IF(C31<$C$10,C31,D31-E31) -> 0 | G31: =C31-F31 -> 0 | H31: =G31/$C$1 -> #DIV/0! | I31: =C31*$I$10/12 -> 0
A32: 19 | B32: =$C$4 -> 0 | C32: =G31 -> 0 | D32: =IF(C32+E32>$C$10,$C$10,C32+E32) -> 0 | E32: =C32*(B32/12) -> 0 | F32: =IF(C32<$C$10,C32,D32-E32) -> 0 | G32: =C32-F32 -> 0 | H32: =G32/$C$1 -> #DIV/0! | I32: =C32*$I$10/12 -> 0
A33: 20 | B33: =$C$4 -> 0 | C33: =G32 -> 0 | D33: =IF(C33+E33>$C$10,$C$10,C33+E33) -> 0 | E33: =C33*(B33/12) -> 0 | F33: =IF(C33<$C$10,C33,D33-E33) -> 0 | G33: =C33-F33 -> 0 | H33: =G33/$C$1 -> #DIV/0! | I33: =C33*$I$10/12 -> 0
A34: 21 | B34: =$C$4 -> 0 | C34: =G33 -> 0 | D34: =IF(C34+E34>$C$10,$C$10,C34+E34) -> 0 | E34: =C34*(B34/12) -> 0 | F34: =IF(C34<$C$10,C34,D34-E34) -> 0 | G34: =C34-F34 -> 0 | H34: =G34/$C$1 -> #DIV/0! | I34: =C34*$I$10/12 -> 0
A35: 22 | B35: =$C$4 -> 0 | C35: =G34 -> 0 | D35: =IF(C35+E35>$C$10,$C$10,C35+E35) -> 0 | E35: =C35*(B35/12) -> 0 | F35: =IF(C35<$C$10,C35,D35-E35) -> 0 | G35: =C35-F35 -> 0 | H35: =G35/$C$1 -> #DIV/0! | I35: =C35*$I$10/12 -> 0
A36: 23 | B36: =$C$4 -> 0 | C36: =G35 -> 0 | D36: =IF(C36+E36>$C$10,$C$10,C36+E36) -> 0 | E36: =C36*(B36/12) -> 0 | F36: =IF(C36<$C$10,C36,D36-E36) -> 0 | G36: =C36-F36 -> 0 | H36: =G36/$C$1 -> #DIV/0! | I36: =C36*$I$10/12 -> 0
A37: 24 | B37: =$C$4 -> 0 | C37: =G36 -> 0 | D37: =IF(C37+E37>$C$10,$C$10,C37+E37) -> 0 | E37: =C37*(B37/12) -> 0 | F37: =IF(C37<$C$10,C37,D37-E37) -> 0 | G37: =C37-F37 -> 0 | H37: =G37/$C$1 -> #DIV/0! | I37: =C37*$I$10/12 -> 0
A38: 25 | B38: =$C$5 -> 0 | C38: =G37 -> 0 | D38: =IF(C38+E38>$C$10,$C$10,C38+E38) -> 0 | E38: =C38*(B38/12) -> 0 | F38: =IF(C38<$C$10,C38,D38-E38) -> 0 | G38: =C38-F38 -> 0 | H38: =G38/$C$1 -> #DIV/0! | I38: =C38*$I$10/12 -> 0
A39: 26 | B39: =$C$5 -> 0 | C39: =G38 -> 0 | D39: =IF(C39+E39>$C$10,$C$10,C39+E39) -> 0 | E39: =C39*(B39/12) -> 0 | F39: =IF(C39<$C$10,C39,D39-E39) -> 0 | G39: =C39-F39 -> 0 | H39: =G39/$C$1 -> #DIV/0! | I39: =C39*$I$10/12 -> 0
A40: 27 | B40: =$C$5 -> 0 | C40: =G39 -> 0 | D40: =IF(C40+E40>$C$10,$C$10,C40+E40) -> 0 | E40: =C40*(B40/12) -> 0 | F40: =IF(C40<$C$10,C40,D40-E40) -> 0 | G40: =C40-F40 -> 0 | H40: =G40/$C$1 -> #DIV/0! | I40: =C40*$I$10/12 -> 0
A41: 28 | B41: =$C$5 -> 0 | C41: =G40 -> 0 | D41: =IF(C41+E41>$C$10,$C$10,C41+E41) -> 0 | E41: =C41*(B41/12) -> 0 | F41: =IF(C41<$C$10,C41,D41-E41) -> 0 | G41: =C41-F41 -> 0 | H41: =G41/$C$1 -> #DIV/0! | I41: =C41*$I$10/12 -> 0
A42: 29 | B42: =$C$5 -> 0 | C42: =G41 -> 0 | D42: =IF(C42+E42>$C$10,$C$10,C42+E42) -> 0 | E42: =C42*(B42/12) -> 0 | F42: =IF(C42<$C$10,C42,D42-E42) -> 0 | G42: =C42-F42 -> 0 | H42: =G42/$C$1 -> #DIV/0! | I42: =C42*$I$10/12 -> 0
A43: 30 | B43: =$C$5 -> 0 | C43: =G42 -> 0 | D43: =IF(C43+E43>$C$10,$C$10,C43+E43) -> 0 | E43: =C43*(B43/12) -> 0 | F43: =IF(C43<$C$10,C43,D43-E43) -> 0 | G43: =C43-F43 -> 0 | H43: =G43/$C$1 -> #DIV/0! | I43: =C43*$I$10/12 -> 0
A44: 31 | B44: =$C$5 -> 0 | C44: =G43 -> 0 | D44: =IF(C44+E44>$C$10,$C$10,C44+E44) -> 0 | E44: =C44*(B44/12) -> 0 | F44: =IF(C44<$C$10,C44,D44-E44) -> 0 | G44: =C44-F44 -> 0 | H44: =G44/$C$1 -> #DIV/0! | I44: =C44*$I$10/12 -> 0
A45: 32 | B45: =$C$5 -> 0 | C45: =G44 -> 0 | D45: =IF(C45+E45>$C$10,$C$10,C45+E45) -> 0 | E45: =C45*(B45/12) -> 0 | F45: =IF(C45<$C$10,C45,D45-E45) -> 0 | G45: =C45-F45 -> 0 | H45: =G45/$C$1 -> #DIV/0! | I45: =C45*$I$10/12 -> 0
A46: 33 | B46: =$C$5 -> 0 | C46: =G45 -> 0 | D46: =IF(C46+E46>$C$10,$C$10,C46+E46) -> 0 | E46: =C46*(B46/12) -> 0 | F46: =IF(C46<$C$10,C46,D46-E46) -> 0 | G46: =C46-F46 -> 0 | H46: =G46/$C$1 -> #DIV/0! | I46: =C46*$I$10/12 -> 0
A47: 34 | B47: =$C$5 -> 0 | C47: =G46 -> 0 | D47: =IF(C47+E47>$C$10,$C$10,C47+E47) -> 0 | E47: =C47*(B47/12) -> 0 | F47: =IF(C47<$C$10,C47,D47-E47) -> 0 | G47: =C47-F47 -> 0 | H47: =G47/$C$1 -> #DIV/0! | I47: =C47*$I$10/12 -> 0
A48: 35 | B48: =$C$5 -> 0 | C48: =G47 -> 0 | D48: =IF(C48+E48>$C$10,$C$10,C48+E48) -> 0 | E48: =C48*(B48/12) -> 0 | F48: =IF(C48<$C$10,C48,D48-E48) -> 0 | G48: =C48-F48 -> 0 | H48: =G48/$C$1 -> #DIV/0! | I48: =C48*$I$10/12 -> 0
A49: 36 | B49: =$C$5 -> 0 | C49: =G48 -> 0 | D49: =IF(C49+E49>$C$10,$C$10,C49+E49) -> 0 | E49: =C49*(B49/12) -> 0 | F49: =IF(C49<$C$10,C49,D49-E49) -> 0 | G49: =C49-F49 -> 0 | H49: =G49/$C$1 -> #DIV/0! | I49: =C49*$I$10/12 -> 0
A50: 37 | B50: =$C$6 -> 0 | C50: =G49 -> 0 | D50: =IF(C50+E50>$C$10,$C$10,C50+E50) -> 0 | E50: =C50*(B50/12) -> 0 | F50: =IF(C50<$C$10,C50,D50-E50) -> 0 | G50: =C50-F50 -> 0 | H50: =G50/$C$1 -> #DIV/0! | I50: =C50*$I$10/12 -> 0
A51: 38 | B51: =$C$6 -> 0 | C51: =G50 -> 0 | D51: =IF(C51+E51>$C$10,$C$10,C51+E51) -> 0 | E51: =C51*(B51/12) -> 0 | F51: =IF(C51<$C$10,C51,D51-E51) -> 0 | G51: =C51-F51 -> 0 | H51: =G51/$C$1 -> #DIV/0! | I51: =C51*$I$10/12 -> 0
A52: 39 | B52: =$C$6 -> 0 | C52: =G51 -> 0 | D52: =IF(C52+E52>$C$10,$C$10,C52+E52) -> 0 | E52: =C52*(B52/12) -> 0 | F52: =IF(C52<$C$10,C52,D52-E52) -> 0 | G52: =C52-F52 -> 0 | H52: =G52/$C$1 -> #DIV/0! | I52: =C52*$I$10/12 -> 0
A53: 40 | B53: =$C$6 -> 0 | C53: =G52 -> 0 | D53: =IF(C53+E53>$C$10,$C$10,C53+E53) -> 0 | E53: =C53*(B53/12) -> 0 | F53: =IF(C53<$C$10,C53,D53-E53) -> 0 | G53: =C53-F53 -> 0 | H53: =G53/$C$1 -> #DIV/0! | I53: =C53*$I$10/12 -> 0
A54: 41 | B54: =$C$6 -> 0 | C54: =G53 -> 0 | D54: =IF(C54+E54>$C$10,$C$10,C54+E54) -> 0 | E54: =C54*(B54/12) -> 0 | F54: =IF(C54<$C$10,C54,D54-E54) -> 0 | G54: =C54-F54 -> 0 | H54: =G54/$C$1 -> #DIV/0! | I54: =C54*$I$10/12 -> 0
A55: 42 | B55: =$C$6 -> 0 | C55: =G54 -> 0 | D55: =IF(C55+E55>$C$10,$C$10,C55+E55) -> 0 | E55: =C55*(B55/12) -> 0 | F55: =IF(C55<$C$10,C55,D55-E55) -> 0 | G55: =C55-F55 -> 0 | H55: =G55/$C$1 -> #DIV/0! | I55: =C55*$I$10/12 -> 0
A56: 43 | B56: =$C$6 -> 0 | C56: =G55 -> 0 | D56: =IF(C56+E56>$C$10,$C$10,C56+E56) -> 0 | E56: =C56*(B56/12) -> 0 | F56: =IF(C56<$C$10,C56,D56-E56) -> 0 | G56: =C56-F56 -> 0 | H56: =G56/$C$1 -> #DIV/0! | I56: =C56*$I$10/12 -> 0
A57: 44 | B57: =$C$6 -> 0 | C57: =G56 -> 0 | D57: =IF(C57+E57>$C$10,$C$10,C57+E57) -> 0 | E57: =C57*(B57/12) -> 0 | F57: =IF(C57<$C$10,C57,D57-E57) -> 0 | G57: =C57-F57 -> 0 | H57: =G57/$C$1 -> #DIV/0! | I57: =C57*$I$10/12 -> 0
A58: 45 | B58: =$C$6 -> 0 | C58: =G57 -> 0 | D58: =IF(C58+E58>$C$10,$C$10,C58+E58) -> 0 | E58: =C58*(B58/12) -> 0 | F58: =IF(C58<$C$10,C58,D58-E58) -> 0 | G58: =C58-F58 -> 0 | H58: =G58/$C$1 -> #DIV/0! | I58: =C58*$I$10/12 -> 0
A59: 46 | B59: =$C$6 -> 0 | C59: =G58 -> 0 | D59: =IF(C59+E59>$C$10,$C$10,C59+E59) -> 0 | E59: =C59*(B59/12) -> 0 | F59: =IF(C59<$C$10,C59,D59-E59) -> 0 | G59: =C59-F59 -> 0 | H59: =G59/$C$1 -> #DIV/0! | I59: =C59*$I$10/12 -> 0
A60: 47 | B60: =$C$6 -> 0 | C60: =G59 -> 0 | D60: =IF(C60+E60>$C$10,$C$10,C60+E60) -> 0 | E60: =C60*(B60/12) -> 0 | F60: =IF(C60<$C$10,C60,D60-E60) -> 0 | G60: =C60-F60 -> 0 | H60: =G60/$C$1 -> #DIV/0! | I60: =C60*$I$10/12 -> 0
A61: 48 | B61: =$C$6 -> 0 | C61: =G60 -> 0 | D61: =IF(C61+E61>$C$10,$C$10,C61+E61) -> 0 | E61: =C61*(B61/12) -> 0 | F61: =IF(C61<$C$10,C61,D61-E61) -> 0 | G61: =C61-F61 -> 0 | H61: =G61/$C$1 -> #DIV/0! | I61: =C61*$I$10/12 -> 0
... A493: 480 | B493: =$C$6 -> 0 | C493: =G492 -> 0 | D493: =IF(C493+E493>$C$10,$C$10,C493+E493) -> 0 | E493: =C493*(B493/12) -> 0 | F493: =IF(C493<$C$10,C493,D493-E493) -> 0 | G493: =C493-F493 -> 0 | H493: =G493/$C$1 -> #DIV/0! | I493: =C493*$I$10/12 -> 0

Sheet Straight-MP
B1: Loan | C1: ='1.ลดดอกเบี้ย'!E8 -> 0 | G1: =[2]ตาราง!T25 -> No Insurance | H1: Y1 | I1: Y2 | J1: Y3 | K1: Y4+
B2: Tenor | C2: ='1.ลดดอกเบี้ย'!E9 -> 0 | G2: Insurance | H2: 0.055 | I2: 0.055 | J2: 0.055 | K2: 0.07725
B3: Interest 1 | C3: ='1.ลดดอกเบี้ย'!F11 -> 0 | D3: 12 | E3: =C3*D3 -> 0 | G3: No Insurance | H3: 0.057 | I3: 0.057 | J3: 0.057 | K3: 0.07725
B4: Interest 2 | C4: ='1.ลดดอกเบี้ย'!F12 -> 0 | D4: 12 | E4: =C4*D4 -> 0
B5: Interest 3 | C5: ='1.ลดดอกเบี้ย'!F13 -> 0 | D5: 12 | E5: =C5*D5 -> 0
B6: Interest 4+ | C6: ='1.ลดดอกเบี้ย'!F14 -> 0 | D6: =(C2*12)-SUM(D3:D5) -> -36 | E6: =C6*D6 -> 0
E7: =SUM(E3:E6)/(C2*12) -> #DIV/0!
B9: Buffer (+1%) | C9: =E7+0.75% -> #DIV/0! | D9: Bal 0 in mth | E9: {=CELL("row",INDEX(C14:C493,MATCH(MIN(C14:C493),C14:C493,0)))-ROW(C14)+1} -> 1 | I9: %COF
B10: Installment | C10: =IFERROR(ROUNDUP(PMT(C9/12,C2*12,-C1),-1),0) -> 0 | I10: 0.028
A12: No. | B12: Int Rate | C12: Beg.OS | D12: Mthy Pay | E12: Int Paid | F12: OS Paid | G12: End.OS | H12: LTV | I12: COF
D13: =-C14 -> 0
A14: 1 | B14: =$C$3 -> 0 | C14: =C1 -> 0 | D14: =IF(C14+E14>$C$10,$C$10,C14+E14) -> 0 | E14: =C14*(B14/12) -> 0 | F14: =IF(C14<$C$10,C14,D14-E14) -> 0 | G14: =C14-F14 -> 0 | H14: =G14/$C$1 -> #DIV/0! | I14: =C14*$I$10/12 -> 0
A15: 2 | B15: =$C$3 -> 0 | C15: =G14 -> 0 | D15: =IF(C15+E15>$C$10,$C$10,C15+E15) -> 0 | E15: =C15*(B15/12) -> 0 | F15: =IF(C15<$C$10,C15,D15-E15) -> 0 | G15: =C15-F15 -> 0 | H15: =G15/$C$1 -> #DIV/0! | I15: =C15*$I$10/12 -> 0
A16: 3 | B16: =$C$3 -> 0 | C16: =G15 -> 0 | D16: =IF(C16+E16>$C$10,$C$10,C16+E16) -> 0 | E16: =C16*(B16/12) -> 0 | F16: =IF(C16<$C$10,C16,D16-E16) -> 0 | G16: =C16-F16 -> 0 | H16: =G16/$C$1 -> #DIV/0! | I16: =C16*$I$10/12 -> 0
A17: 4 | B17: =$C$3 -> 0 | C17: =G16 -> 0 | D17: =IF(C17+E17>$C$10,$C$10,C17+E17) -> 0 | E17: =C17*(B17/12) -> 0 | F17: =IF(C17<$C$10,C17,D17-E17) -> 0 | G17: =C17-F17 -> 0 | H17: =G17/$C$1 -> #DIV/0! | I17: =C17*$I$10/12 -> 0
A18: 5 | B18: =$C$3 -> 0 | C18: =G17 -> 0 | D18: =IF(C18+E18>$C$10,$C$10,C18+E18) -> 0 | E18: =C18*(B18/12) -> 0 | F18: =IF(C18<$C$10,C18,D18-E18) -> 0 | G18: =C18-F18 -> 0 | H18: =G18/$C$1 -> #DIV/0! | I18: =C18*$I$10/12 -> 0
A19: 6 | B19: =$C$3 -> 0 | C19: =G18 -> 0 | D19: =IF(C19+E19>$C$10,$C$10,C19+E19) -> 0 | E19: =C19*(B19/12) -> 0 | F19: =IF(C19<$C$10,C19,D19-E19) -> 0 | G19: =C19-F19 -> 0 | H19: =G19/$C$1 -> #DIV/0! | I19: =C19*$I$10/12 -> 0
A20: 7 | B20: =$C$3 -> 0 | C20: =G19 -> 0 | D20: =IF(C20+E20>$C$10,$C$10,C20+E20) -> 0 | E20: =C20*(B20/12) -> 0 | F20: =IF(C20<$C$10,C20,D20-E20) -> 0 | G20: =C20-F20 -> 0 | H20: =G20/$C$1 -> #DIV/0! | I20: =C20*$I$10/12 -> 0
A21: 8 | B21: =$C$3 -> 0 | C21: =G20 -> 0 | D21: =IF(C21+E21>$C$10,$C$10,C21+E21) -> 0 | E21: =C21*(B21/12) -> 0 | F21: =IF(C21<$C$10,C21,D21-E21) -> 0 | G21: =C21-F21 -> 0 | H21: =G21/$C$1 -> #DIV/0! | I21: =C21*$I$10/12 -> 0
A22: 9 | B22: =$C$3 -> 0 | C22: =G21 -> 0 | D22: =IF(C22+E22>$C$10,$C$10,C22+E22) -> 0 | E22: =C22*(B22/12) -> 0 | F22: =IF(C22<$C$10,C22,D22-E22) -> 0 | G22: =C22-F22 -> 0 | H22: =G22/$C$1 -> #DIV/0! | I22: =C22*$I$10/12 -> 0
A23: 10 | B23: =$C$3 -> 0 | C23: =G22 -> 0 | D23: =IF(C23+E23>$C$10,$C$10,C23+E23) -> 0 | E23: =C23*(B23/12) -> 0 | F23: =IF(C23<$C$10,C23,D23-E23) -> 0 | G23: =C23-F23 -> 0 | H23: =G23/$C$1 -> #DIV/0! | I23: =C23*$I$10/12 -> 0
A24: 11 | B24: =$C$3 -> 0 | C24: =G23 -> 0 | D24: =IF(C24+E24>$C$10,$C$10,C24+E24) -> 0 | E24: =C24*(B24/12) -> 0 | F24: =IF(C24<$C$10,C24,D24-E24) -> 0 | G24: =C24-F24 -> 0 | H24: =G24/$C$1 -> #DIV/0! | I24: =C24*$I$10/12 -> 0
A25: 12 | B25: =$C$3 -> 0 | C25: =G24 -> 0 | D25: =IF(C25+E25>$C$10,$C$10,C25+E25) -> 0 | E25: =C25*(B25/12) -> 0 | F25: =IF(C25<$C$10,C25,D25-E25) -> 0 | G25: =C25-F25 -> 0 | H25: =G25/$C$1 -> #DIV/0! | I25: =C25*$I$10/12 -> 0
A26: 13 | B26: =$C$4 -> 0 | C26: =G25 -> 0 | D26: =IF(C26+E26>$C$10,$C$10,C26+E26) -> 0 | E26: =C26*(B26/12) -> 0 | F26: =IF(C26<$C$10,C26,D26-E26) -> 0 | G26: =C26-F26 -> 0 | H26: =G26/$C$1 -> #DIV/0! | I26: =C26*$I$10/12 -> 0
A27: 14 | B27: =$C$4 -> 0 | C27: =G26 -> 0 | D27: =IF(C27+E27>$C$10,$C$10,C27+E27) -> 0 | E27: =C27*(B27/12) -> 0 | F27: =IF(C27<$C$10,C27,D27-E27) -> 0 | G27: =C27-F27 -> 0 | H27: =G27/$C$1 -> #DIV/0! | I27: =C27*$I$10/12 -> 0
A28: 15 | B28: =$C$4 -> 0 | C28: =G27 -> 0 | D28: =IF(C28+E28>$C$10,$C$10,C28+E28) -> 0 | E28: =C28*(B28/12) -> 0 | F28: =IF(C28<$C$10,C28,D28-E28) -> 0 | G28: =C28-F28 -> 0 | H28: =G28/$C$1 -> #DIV/0! | I28: =C28*$I$10/12 -> 0
A29: 16 | B29: =$C$4 -> 0 | C29: =G28 -> 0 | D29: =IF(C29+E29>$C$10,$C$10,C29+E29) -> 0 | E29: =C29*(B29/12) -> 0 | F29: =IF(C29<$C$10,C29,D29-E29) -> 0 | G29: =C29-F29 -> 0 | H29: =G29/$C$1 -> #DIV/0! | I29: =C29*$I$10/12 -> 0
A30: 17 | B30: =$C$4 -> 0 | C30: =G29 -> 0 | D30: =IF(C30+E30>$C$10,$C$10,C30+E30) -> 0 | E30: =C30*(B30/12) -> 0 | F30: =IF(C30<$C$10,C30,D30-E30) -> 0 | G30: =C30-F30 -> 0 | H30: =G30/$C$1 -> #DIV/0! | I30: =C30*$I$10/12 -> 0
A31: 18 | B31: =$C$4 -> 0 | C31: =G30 -> 0 | D31: =IF(C31+E31>$C$10,$C$10,C31+E31) -> 0 | E31: =C31*(B31/12) -> 0 | F31: =IF(C31<$C$10,C31,D31-E31) -> 0 | G31: =C31-F31 -> 0 | H31: =G31/$C$1 -> #DIV/0! | I31: =C31*$I$10/12 -> 0
A32: 19 | B32: =$C$4 -> 0 | C32: =G31 -> 0 | D32: =IF(C32+E32>$C$10,$C$10,C32+E32) -> 0 | E32: =C32*(B32/12) -> 0 | F32: =IF(C32<$C$10,C32,D32-E32) -> 0 | G32: =C32-F32 -> 0 | H32: =G32/$C$1 -> #DIV/0! | I32: =C32*$I$10/12 -> 0
A33: 20 | B33: =$C$4 -> 0 | C33: =G32 -> 0 | D33: =IF(C33+E33>$C$10,$C$10,C33+E33) -> 0 | E33: =C33*(B33/12) -> 0 | F33: =IF(C33<$C$10,C33,D33-E33) -> 0 | G33: =C33-F33 -> 0 | H33: =G33/$C$1 -> #DIV/0! | I33: =C33*$I$10/12 -> 0
A34: 21 | B34: =$C$4 -> 0 | C34: =G33 -> 0 | D34: =IF(C34+E34>$C$10,$C$10,C34+E34) -> 0 | E34: =C34*(B34/12) -> 0 | F34: =IF(C34<$C$10,C34,D34-E34) -> 0 | G34: =C34-F34 -> 0 | H34: =G34/$C$1 -> #DIV/0! | I34: =C34*$I$10/12 -> 0
A35: 22 | B35: =$C$4 -> 0 | C35: =G34 -> 0 | D35: =IF(C35+E35>$C$10,$C$10,C35+E35) -> 0 | E35: =C35*(B35/12) -> 0 | F35: =IF(C35<$C$10,C35,D35-E35) -> 0 | G35: =C35-F35 -> 0 | H35: =G35/$C$1 -> #DIV/0! | I35: =C35*$I$10/12 -> 0
A36: 23 | B36: =$C$4 -> 0 | C36: =G35 -> 0 | D36: =IF(C36+E36>$C$10,$C$10,C36+E36) -> 0 | E36: =C36*(B36/12) -> 0 | F36: =IF(C36<$C$10,C36,D36-E36) -> 0 | G36: =C36-F36 -> 0 | H36: =G36/$C$1 -> #DIV/0! | I36: =C36*$I$10/12 -> 0
A37: 24 | B37: =$C$4 -> 0 | C37: =G36 -> 0 | D37: =IF(C37+E37>$C$10,$C$10,C37+E37) -> 0 | E37: =C37*(B37/12) -> 0 | F37: =IF(C37<$C$10,C37,D37-E37) -> 0 | G37: =C37-F37 -> 0 | H37: =G37/$C$1 -> #DIV/0! | I37: =C37*$I$10/12 -> 0
A38: 25 | B38: =$C$5 -> 0 | C38: =G37 -> 0 | D38: =IF(C38+E38>$C$10,$C$10,C38+E38) -> 0 | E38: =C38*(B38/12) -> 0 | F38: =IF(C38<$C$10,C38,D38-E38) -> 0 | G38: =C38-F38 -> 0 | H38: =G38/$C$1 -> #DIV/0! | I38: =C38*$I$10/12 -> 0
A39: 26 | B39: =$C$5 -> 0 | C39: =G38 -> 0 | D39: =IF(C39+E39>$C$10,$C$10,C39+E39) -> 0 | E39: =C39*(B39/12) -> 0 | F39: =IF(C39<$C$10,C39,D39-E39) -> 0 | G39: =C39-F39 -> 0 | H39: =G39/$C$1 -> #DIV/0! | I39: =C39*$I$10/12 -> 0
A40: 27 | B40: =$C$5 -> 0 | C40: =G39 -> 0 | D40: =IF(C40+E40>$C$10,$C$10,C40+E40) -> 0 | E40: =C40*(B40/12) -> 0 | F40: =IF(C40<$C$10,C40,D40-E40) -> 0 | G40: =C40-F40 -> 0 | H40: =G40/$C$1 -> #DIV/0! | I40: =C40*$I$10/12 -> 0
A41: 28 | B41: =$C$5 -> 0 | C41: =G40 -> 0 | D41: =IF(C41+E41>$C$10,$C$10,C41+E41) -> 0 | E41: =C41*(B41/12) -> 0 | F41: =IF(C41<$C$10,C41,D41-E41) -> 0 | G41: =C41-F41 -> 0 | H41: =G41/$C$1 -> #DIV/0! | I41: =C41*$I$10/12 -> 0
A42: 29 | B42: =$C$5 -> 0 | C42: =G41 -> 0 | D42: =IF(C42+E42>$C$10,$C$10,C42+E42) -> 0 | E42: =C42*(B42/12) -> 0 | F42: =IF(C42<$C$10,C42,D42-E42) -> 0 | G42: =C42-F42 -> 0 | H42: =G42/$C$1 -> #DIV/0! | I42: =C42*$I$10/12 -> 0
A43: 30 | B43: =$C$5 -> 0 | C43: =G42 -> 0 | D43: =IF(C43+E43>$C$10,$C$10,C43+E43) -> 0 | E43: =C43*(B43/12) -> 0 | F43: =IF(C43<$C$10,C43,D43-E43) -> 0 | G43: =C43-F43 -> 0 | H43: =G43/$C$1 -> #DIV/0! | I43: =C43*$I$10/12 -> 0
A44: 31 | B44: =$C$5 -> 0 | C44: =G43 -> 0 | D44: =IF(C44+E44>$C$10,$C$10,C44+E44) -> 0 | E44: =C44*(B44/12) -> 0 | F44: =IF(C44<$C$10,C44,D44-E44) -> 0 | G44: =C44-F44 -> 0 | H44: =G44/$C$1 -> #DIV/0! | I44: =C44*$I$10/12 -> 0
A45: 32 | B45: =$C$5 -> 0 | C45: =G44 -> 0 | D45: =IF(C45+E45>$C$10,$C$10,C45+E45) -> 0 | E45: =C45*(B45/12) -> 0 | F45: =IF(C45<$C$10,C45,D45-E45) -> 0 | G45: =C45-F45 -> 0 | H45: =G45/$C$1 -> #DIV/0! | I45: =C45*$I$10/12 -> 0
A46: 33 | B46: =$C$5 -> 0 | C46: =G45 -> 0 | D46: =IF(C46+E46>$C$10,$C$10,C46+E46) -> 0 | E46: =C46*(B46/12) -> 0 | F46: =IF(C46<$C$10,C46,D46-E46) -> 0 | G46: =C46-F46 -> 0 | H46: =G46/$C$1 -> #DIV/0! | I46: =C46*$I$10/12 -> 0
A47: 34 | B47: =$C$5 -> 0 | C47: =G46 -> 0 | D47: =IF(C47+E47>$C$10,$C$10,C47+E47) -> 0 | E47: =C47*(B47/12) -> 0 | F47: =IF(C47<$C$10,C47,D47-E47) -> 0 | G47: =C47-F47 -> 0 | H47: =G47/$C$1 -> #DIV/0! | I47: =C47*$I$10/12 -> 0
A48: 35 | B48: =$C$5 -> 0 | C48: =G47 -> 0 | D48: =IF(C48+E48>$C$10,$C$10,C48+E48) -> 0 | E48: =C48*(B48/12) -> 0 | F48: =IF(C48<$C$10,C48,D48-E48) -> 0 | G48: =C48-F48 -> 0 | H48: =G48/$C$1 -> #DIV/0! | I48: =C48*$I$10/12 -> 0
A49: 36 | B49: =$C$5 -> 0 | C49: =G48 -> 0 | D49: =IF(C49+E49>$C$10,$C$10,C49+E49) -> 0 | E49: =C49*(B49/12) -> 0 | F49: =IF(C49<$C$10,C49,D49-E49) -> 0 | G49: =C49-F49 -> 0 | H49: =G49/$C$1 -> #DIV/0! | I49: =C49*$I$10/12 -> 0
A50: 37 | B50: =$C$6 -> 0 | C50: =G49 -> 0 | D50: =IF(C50+E50>$C$10,$C$10,C50+E50) -> 0 | E50: =C50*(B50/12) -> 0 | F50: =IF(C50<$C$10,C50,D50-E50) -> 0 | G50: =C50-F50 -> 0 | H50: =G50/$C$1 -> #DIV/0! | I50: =C50*$I$10/12 -> 0
A51: 38 | B51: =$C$6 -> 0 | C51: =G50 -> 0 | D51: =IF(C51+E51>$C$10,$C$10,C51+E51) -> 0 | E51: =C51*(B51/12) -> 0 | F51: =IF(C51<$C$10,C51,D51-E51) -> 0 | G51: =C51-F51 -> 0 | H51: =G51/$C$1 -> #DIV/0! | I51: =C51*$I$10/12 -> 0
A52: 39 | B52: =$C$6 -> 0 | C52: =G51 -> 0 | D52: =IF(C52+E52>$C$10,$C$10,C52+E52) -> 0 | E52: =C52*(B52/12) -> 0 | F52: =IF(C52<$C$10,C52,D52-E52) -> 0 | G52: =C52-F52 -> 0 | H52: =G52/$C$1 -> #DIV/0! | I52: =C52*$I$10/12 -> 0
A53: 40 | B53: =$C$6 -> 0 | C53: =G52 -> 0 | D53: =IF(C53+E53>$C$10,$C$10,C53+E53) -> 0 | E53: =C53*(B53/12) -> 0 | F53: =IF(C53<$C$10,C53,D53-E53) -> 0 | G53: =C53-F53 -> 0 | H53: =G53/$C$1 -> #DIV/0! | I53: =C53*$I$10/12 -> 0
A54: 41 | B54: =$C$6 -> 0 | C54: =G53 -> 0 | D54: =IF(C54+E54>$C$10,$C$10,C54+E54) -> 0 | E54: =C54*(B54/12) -> 0 | F54: =IF(C54<$C$10,C54,D54-E54) -> 0 | G54: =C54-F54 -> 0 | H54: =G54/$C$1 -> #DIV/0! | I54: =C54*$I$10/12 -> 0
A55: 42 | B55: =$C$6 -> 0 | C55: =G54 -> 0 | D55: =IF(C55+E55>$C$10,$C$10,C55+E55) -> 0 | E55: =C55*(B55/12) -> 0 | F55: =IF(C55<$C$10,C55,D55-E55) -> 0 | G55: =C55-F55 -> 0 | H55: =G55/$C$1 -> #DIV/0! | I55: =C55*$I$10/12 -> 0
A56: 43 | B56: =$C$6 -> 0 | C56: =G55 -> 0 | D56: =IF(C56+E56>$C$10,$C$10,C56+E56) -> 0 | E56: =C56*(B56/12) -> 0 | F56: =IF(C56<$C$10,C56,D56-E56) -> 0 | G56: =C56-F56 -> 0 | H56: =G56/$C$1 -> #DIV/0! | I56: =C56*$I$10/12 -> 0
A57: 44 | B57: =$C$6 -> 0 | C57: =G56 -> 0 | D57: =IF(C57+E57>$C$10,$C$10,C57+E57) -> 0 | E57: =C57*(B57/12) -> 0 | F57: =IF(C57<$C$10,C57,D57-E57) -> 0 | G57: =C57-F57 -> 0 | H57: =G57/$C$1 -> #DIV/0! | I57: =C57*$I$10/12 -> 0
A58: 45 | B58: =$C$6 -> 0 | C58: =G57 -> 0 | D58: =IF(C58+E58>$C$10,$C$10,C58+E58) -> 0 | E58: =C58*(B58/12) -> 0 | F58: =IF(C58<$C$10,C58,D58-E58) -> 0 | G58: =C58-F58 -> 0 | H58: =G58/$C$1 -> #DIV/0! | I58: =C58*$I$10/12 -> 0
A59: 46 | B59: =$C$6 -> 0 | C59: =G58 -> 0 | D59: =IF(C59+E59>$C$10,$C$10,C59+E59) -> 0 | E59: =C59*(B59/12) -> 0 | F59: =IF(C59<$C$10,C59,D59-E59) -> 0 | G59: =C59-F59 -> 0 | H59: =G59/$C$1 -> #DIV/0! | I59: =C59*$I$10/12 -> 0
A60: 47 | B60: =$C$6 -> 0 | C60: =G59 -> 0 | D60: =IF(C60+E60>$C$10,$C$10,C60+E60) -> 0 | E60: =C60*(B60/12) -> 0 | F60: =IF(C60<$C$10,C60,D60-E60) -> 0 | G60: =C60-F60 -> 0 | H60: =G60/$C$1 -> #DIV/0! | I60: =C60*$I$10/12 -> 0
A61: 48 | B61: =$C$6 -> 0 | C61: =G60 -> 0 | D61: =IF(C61+E61>$C$10,$C$10,C61+E61) -> 0 | E61: =C61*(B61/12) -> 0 | F61: =IF(C61<$C$10,C61,D61-E61) -> 0 | G61: =C61-F61 -> 0 | H61: =G61/$C$1 -> #DIV/0! | I61: =C61*$I$10/12 -> 0
... A493: 480 | B493: =$C$6 -> 0 | C493: =G492 -> 0 | D493: =IF(C493+E493>$C$10,$C$10,C493+E493) -> 0 | E493: =C493*(B493/12) -> 0 | F493: =IF(C493<$C$10,C493,D493-E493) -> 0 | G493: =C493-F493 -> 0 | H493: =G493/$C$1 -> #DIV/0! | I493: =C493*$I$10/12 -> 0

Sheet Step-HL
A1: Limit | B1: ='1.ลดดอกเบี้ย'!C8 -> 0 | C1: no of Year
A2: Term(month) | B2: =$C$2*12 -> 0 | C2: ='1.ลดดอกเบี้ย'!C9 -> 0
A3: Special Approved | B3: 0.0225
A4: Period | B4: BufferRate
A5: Normal | B5: 0.0075
A6: First 3 years | B6: 0.0075
A7: Facility Package for Option5.1
E8: แบบดอกเบี้ยจริง&เงินต้นคงเหลือ | I8: แบบดอกเบี้ยจริง+BufferRate&เงินต้นคงเหลือ | M8: แบบดอกเบี้ยจริง+BufferRate&เงินต้นคงเหลือ Grace Period
A9: Start term | B9: Term | C9: Rete | D9: Year | E9: Principal | F9: Rate | G9: Term | H9: Installment | I9: Principal | J9: Rate | K9: Term | L9: Installment | M9: Principal | N9: Rate | O9: Term | P9: Installment
A10: 1 | B10: 12 | C10: ='1.ลดดอกเบี้ย'!D11 -> 0 | D10: 1 | E10: =$B$1 -> 0 | F10: =$C10 -> 0 | G10: =$B$2 -> 0 | H10: =PMT(F10/12,G10,E10*-1) -> #NUM! | I10: =$B$1 -> 0 | J10: =$C10+$B$5+$B$6 -> 0.015 | K10: =$B$2 -> 0 | L10: =ROUNDUP($I$10*J10/12,-1) -> 0 | M10: =$B$1 -> 0 | N10: =$C10 -> 0 | O10: =$B$2 -> 0 | P10: =ROUNDUP($M$10*N10/12,-1) -> 0
A11: =A10+B10 -> 13 | B11: 12 | C11: ='1.ลดดอกเบี้ย'!D12 -> 0 | D11: 2 | E11: =E32 -> 0 | F11: =$C11 -> 0 | G11: =G10-12 -> -12 | H11: =PMT(F11/12,G11,E11*-1) -> 0 | I11: =I32 -> 0 | J11: =$C11+$B$5+$B$6 -> 0.015 | K11: =K10-$B$10 -> -12 | L11: =ROUNDUP($I$10*J11/12,-1) -> 0 | M11: =M32 -> 0 | N11: =$C11+$B$5+$B$6 -> 0.015 | O11: =O10-$B$10 -> -12 | P11: =ROUNDUP($M$10*N11/12,-1) -> 0
A12: =A11+B11 -> 25 | B12: 12 | C12: ='1.ลดดอกเบี้ย'!D13 -> 0 | D12: 3 | E12: =E44 -> 0 | F12: =$C12 -> 0 | G12: =G11-12 -> -24 | H12: =PMT(F12/12,G12,E12*-1) -> 0 | I12: =I44 -> 0 | J12: =$C12+$B$5+$B$6 -> 0.015 | K12: =K11-$B$11 -> -24 | L12: =ROUNDUP($I$10*J12/12,-1) -> 0 | M12: =M44 -> 0 | N12: =$C12+$B$5+$B$6 -> 0.015 | O12: =O11-$B$11 -> -24 | P12: =ROUNDUP($M$10*N12/12,-1) -> 0
A13: =A12+B12 -> 37 | B13: 12 | C13: ='1.ลดดอกเบี้ย'!D14 -> 0 | D13: 4 | E13: =E56 -> 0 | F13: =$C13 -> 0 | G13: =G12-12 -> -36 | H13: =PMT(F13/12,G13,E13*-1) -> 0 | I13: =I56 -> 0 | J13: =($C$14)+$B$5 -> 0.0075 | K13: =K12-$B$12 -> -36 | L13: =ROUNDUP(PMT(J13/12,B2-36,$I$13*-1),-1) -> 0 | M13: =M56 -> 0 | N13: =$C13+$B$5+$B$6 -> 0.015 | O13: =O12-$B$12 -> -36 | P13: =ROUNDUP($M$10*N13/12,-1) -> 0
A14: =A13+B13 -> 49 | B14: =$B$2-SUM(B10:B13) -> -48 | C14: ='1.ลดดอกเบี้ย'!D14 -> 0 | D14: 5+ | E14: =E68 -> 0 | F14: =$C14 -> 0 | G14: =G13-12 -> -48 | H14: =ROUNDUP(PMT(F14/12,G14,E14*-1),-1) -> 0 | M14: =M68 -> 0 | N14: =$C14+$B$5 -> 0.0075 | O14: =O13-$B$13 -> -48 | P14: =ROUNDUP(PMT(N14/12,B2-48,$M$14*-1),-1) -> 0
A15: Total Term | B15: =SUM(B10:B14) -> 0 | G15: Paid_Month | H15: =396-COUNTIF(H$19:H$415,0) -> -1 | K15: Paid_Month | L15: =396-COUNTIF(L$19:L$415,0) -> -1 | O15: Paid_Month | P15: =396-COUNTIF(P$19:P$415,0) -> -1 | X15: Payment | Y15: =PMT(Y16/12,B2,B1*-1) -> #NUM!
T16: IRR | U16: =IRR(U$19:U$415)*12 -> #NUM! | X16: IRR | Y16: =IRR(Y$19:Y$415)*12 -> #NUM! | Z16: =IRR(Z$19:Z$415)*12 -> #NUM! | AA16: =IRR(AA$19:AA$415)*12 -> #NUM! | AB16: =IRR(AB$19:AB$415)*12 -> #NUM! | AC16: =IRR(AC$19:AC$415)*12 -> #NUM!
E17: แบบดอกเบี้ยจริง & เงินต้นคงเหลือ | I17: แบบดอกเบี้ยจริง+เผื่อดอกเบี้ยขาขึ้น & เงินต้นคงเหลือ | M17: แบบดอกเบี้ยจริง+เผื่อดอกเบี้ยขาขึ้น & เงินต้นคงเหลือ | R17: ค่างวดคงที่ | V17: ค่างวดจริง
A18: Annual rate | B18: Monthly rate | C18: Year | D18: Month | E18: เงินต้นคงเหลือ | F18: ดอกเบี้ยผ่อนชำระ | G18: เงินต้นผ่อนชำระ | H18: เงินงวด | I18: เงินต้นคงเหลือ | J18: ดอกเบี้ยผ่อนชำระ | K18: เงินต้นผ่อนชำระ | L18: เงินงวด | M18: เงินต้นคงเหลือ | N18: ดอกเบี้ยผ่อนชำระ | O18: เงินต้นผ่อนชำระ | P18: เงินงวด | R18: เงินต้นคงเหลือ | S18: ดอกเบี้ยผ่อนชำระ | T18: เงินต้นผ่อนชำระ | U18: เงินงวด | V18: เงินต้นคงเหลือ | W18: ดอกเบี้ยผ่อนชำระ | X18: เงินต้นผ่อนชำระ | Y18: เงินงวด
C19: 0 | D19: 0 | H19: =-E20 -> 0 | L19: =-I20 -> 0 | P19: =-M20 -> 0 | U19: =-R20 -> 0 | Y19: =-V20 -> 0 | Z19: =Y19 -> 0 | AA19: =Z19 -> 0 | AB19: =AA19 -> 0 | AC19: =AB19 -> 0
A20: =VLOOKUP(D20,$A$10:$C$14,3) -> 0 | B20: =A20/12 -> 0 | C20: =INT((D20+11)/12) -> 1 | D20: 1 | E20: =$B$1 -> 0 | F20: =ROUND(E20*$B20,2) -> 0 | G20: =IF(E20<H20,E20,H20-F20) -> 0 | H20: =IF(E20<=0,0,H$10) -> 0 | I20: =$B$1 -> 0 | J20: =ROUND(I20*$B20,2) -> 0 | K20: =IF(I20<L20,I20,L20-J20) -> 0 | L20: =IF(I20<=0,0,L$10) -> 0 | M20: =$B$1 -> 0 | N20: =ROUND(M20*$B20,2) -> 0 | O20: =IF(M20<P20,M20,P20-N20) -> 0 | P20: =IF(M20<=0,0,P$10) -> 0 | R20: =$B$1 -> 0 | S20: =ROUND(R20*$B20,2) -> 0 | T20: =IF(R20<U20,R20,U20-S20) -> 0 | U20: =IF(R20<=0,0,$Y$15) -> 0 | V20: =$B$1 -> 0 | W20: =ROUND(V20*$B20,2) -> 0 | X20: =IF(V20<Y20,V20,Y20-W20) -> 0 | Y20: =IF(V20<=0,0,PMT(B20,($B$2-D20+1),V20*-1)) -> 0 | Z20: =$Y20 -> 0 | AA20: =$Y20 -> 0 | AB20: =$Y20 -> 0 | AC20: =$Y20 -> 0
A21: =VLOOKUP(D21,$A$10:$C$14,3) -> 0 | B21: =A21/12 -> 0 | C21: =INT((D21+11)/12) -> 1 | D21: 2 | E21: =IF(E20<H20,0,E20-G20) -> 0 | F21: =ROUND(E21*$B21,2) -> 0 | G21: =IF(E21<H21,E21,H21-F21) -> 0 | H21: =IF(E21<=0,0,H$10) -> 0 | I21: =IF(I20<L20,0,I20-K20) -> 0 | J21: =ROUND(I21*$B21,2) -> 0 | K21: =IF(I21<L21,I21,L21-J21) -> 0 | L21: =IF(I21<=0,0,L$10) -> 0 | M21: =IF(M20<P20,0,M20-O20) -> 0 | N21: =ROUND(M21*$B21,2) -> 0 | O21: =IF(M21<P21,M21,P21-N21) -> 0 | P21: =IF(M21<=0,0,P$10) -> 0 | R21: =IF(R20<U20,0,R20-T20) -> 0 | S21: =ROUND(R21*$B21,2) -> 0 | T21: =IF(R21<U21,R21,U21-S21) -> 0 | U21: =IF(R21<=0,0,$Y$15) -> 0 | V21: =IF(V20<Y20,0,V20-X20) -> 0 | W21: =ROUND(V21*$B21,2) -> 0 | X21: =IF(V21<Y21,V21,Y21-W21) -> 0 | Y21: =IF(V21<=0,0,PMT(B21,($B$2-D21+1),V21*-1)) -> 0 | Z21: =$Y21 -> 0 | AA21: =$Y21 -> 0 | AB21: =$Y21 -> 0 | AC21: =$Y21 -> 0
A22: =VLOOKUP(D22,$A$10:$C$14,3) -> 0 | B22: =A22/12 -> 0 | C22: =INT((D22+11)/12) -> 1 | D22: 3 | E22: =IF(E21<H21,0,E21-G21) -> 0 | F22: =ROUND(E22*$B22,2) -> 0 | G22: =IF(E22<H22,E22,H22-F22) -> 0 | H22: =IF(E22<=0,0,H$10) -> 0 | I22: =IF(I21<L21,0,I21-K21) -> 0 | J22: =ROUND(I22*$B22,2) -> 0 | K22: =IF(I22<L22,I22,L22-J22) -> 0 | L22: =IF(I22<=0,0,L$10) -> 0 | M22: =IF(M21<P21,0,M21-O21) -> 0 | N22: =ROUND(M22*$B22,2) -> 0 | O22: =IF(M22<P22,M22,P22-N22) -> 0 | P22: =IF(M22<=0,0,P$10) -> 0 | R22: =IF(R21<U21,0,R21-T21) -> 0 | S22: =ROUND(R22*$B22,2) -> 0 | T22: =IF(R22<U22,R22,U22-S22) -> 0 | U22: =IF(R22<=0,0,$Y$15) -> 0 | V22: =IF(V21<Y21,0,V21-X21) -> 0 | W22: =ROUND(V22*$B22,2) -> 0 | X22: =IF(V22<Y22,V22,Y22-W22) -> 0 | Y22: =IF(V22<=0,0,PMT(B22,($B$2-D22+1),V22*-1)) -> 0 | Z22: =$Y22 -> 0 | AA22: =$Y22 -> 0 | AB22: =$Y22 -> 0 | AC22: =$Y22 -> 0
A23: =VLOOKUP(D23,$A$10:$C$14,3) -> 0 | B23: =A23/12 -> 0 | C23: =INT((D23+11)/12) -> 1 | D23: 4 | E23: =IF(E22<H22,0,E22-G22) -> 0 | F23: =ROUND(E23*$B23,2) -> 0 | G23: =IF(E23<H23,E23,H23-F23) -> 0 | H23: =IF(E23<=0,0,H$10) -> 0 | I23: =IF(I22<L22,0,I22-K22) -> 0 | J23: =ROUND(I23*$B23,2) -> 0 | K23: =IF(I23<L23,I23,L23-J23) -> 0 | L23: =IF(I23<=0,0,L$10) -> 0 | M23: =IF(M22<P22,0,M22-O22) -> 0 | N23: =ROUND(M23*$B23,2) -> 0 | O23: =IF(M23<P23,M23,P23-N23) -> 0 | P23: =IF(M23<=0,0,P$10) -> 0 | R23: =IF(R22<U22,0,R22-T22) -> 0 | S23: =ROUND(R23*$B23,2) -> 0 | T23: =IF(R23<U23,R23,U23-S23) -> 0 | U23: =IF(R23<=0,0,$Y$15) -> 0 | V23: =IF(V22<Y22,0,V22-X22) -> 0 | W23: =ROUND(V23*$B23,2) -> 0 | X23: =IF(V23<Y23,V23,Y23-W23) -> 0 | Y23: =IF(V23<=0,0,PMT(B23,($B$2-D23+1),V23*-1)) -> 0 | Z23: =$Y23 -> 0 | AA23: =$Y23 -> 0 | AB23: =$Y23 -> 0 | AC23: =$Y23 -> 0
A24: =VLOOKUP(D24,$A$10:$C$14,3) -> 0 | B24: =A24/12 -> 0 | C24: =INT((D24+11)/12) -> 1 | D24: 5 | E24: =IF(E23<H23,0,E23-G23) -> 0 | F24: =ROUND(E24*$B24,2) -> 0 | G24: =IF(E24<H24,E24,H24-F24) -> 0 | H24: =IF(E24<=0,0,H$10) -> 0 | I24: =IF(I23<L23,0,I23-K23) -> 0 | J24: =ROUND(I24*$B24,2) -> 0 | K24: =IF(I24<L24,I24,L24-J24) -> 0 | L24: =IF(I24<=0,0,L$10) -> 0 | M24: =IF(M23<P23,0,M23-O23) -> 0 | N24: =ROUND(M24*$B24,2) -> 0 | O24: =IF(M24<P24,M24,P24-N24) -> 0 | P24: =IF(M24<=0,0,P$10) -> 0 | R24: =IF(R23<U23,0,R23-T23) -> 0 | S24: =ROUND(R24*$B24,2) -> 0 | T24: =IF(R24<U24,R24,U24-S24) -> 0 | U24: =IF(R24<=0,0,$Y$15) -> 0 | V24: =IF(V23<Y23,0,V23-X23) -> 0 | W24: =ROUND(V24*$B24,2) -> 0 | X24: =IF(V24<Y24,V24,Y24-W24) -> 0 | Y24: =IF(V24<=0,0,PMT(B24,($B$2-D24+1),V24*-1)) -> 0 | Z24: =$Y24 -> 0 | AA24: =$Y24 -> 0 | AB24: =$Y24 -> 0 | AC24: =$Y24 -> 0
A25: =VLOOKUP(D25,$A$10:$C$14,3) -> 0 | B25: =A25/12 -> 0 | C25: =INT((D25+11)/12) -> 1 | D25: 6 | E25: =IF(E24<H24,0,E24-G24) -> 0 | F25: =ROUND(E25*$B25,2) -> 0 | G25: =IF(E25<H25,E25,H25-F25) -> 0 | H25: =IF(E25<=0,0,H$10) -> 0 | I25: =IF(I24<L24,0,I24-K24) -> 0 | J25: =ROUND(I25*$B25,2) -> 0 | K25: =IF(I25<L25,I25,L25-J25) -> 0 | L25: =IF(I25<=0,0,L$10) -> 0 | M25: =IF(M24<P24,0,M24-O24) -> 0 | N25: =ROUND(M25*$B25,2) -> 0 | O25: =IF(M25<P25,M25,P25-N25) -> 0 | P25: =IF(M25<=0,0,P$10) -> 0 | R25: =IF(R24<U24,0,R24-T24) -> 0 | S25: =ROUND(R25*$B25,2) -> 0 | T25: =IF(R25<U25,R25,U25-S25) -> 0 | U25: =IF(R25<=0,0,$Y$15) -> 0 | V25: =IF(V24<Y24,0,V24-X24) -> 0 | W25: =ROUND(V25*$B25,2) -> 0 | X25: =IF(V25<Y25,V25,Y25-W25) -> 0 | Y25: =IF(V25<=0,0,PMT(B25,($B$2-D25+1),V25*-1)) -> 0 | Z25: =$Y25 -> 0 | AA25: =$Y25 -> 0 | AB25: =$Y25 -> 0 | AC25: =$Y25 -> 0
A26: =VLOOKUP(D26,$A$10:$C$14,3) -> 0 | B26: =A26/12 -> 0 | C26: =INT((D26+11)/12) -> 1 | D26: 7 | E26: =IF(E25<H25,0,E25-G25) -> 0 | F26: =ROUND(E26*$B26,2) -> 0 | G26: =IF(E26<H26,E26,H26-F26) -> 0 | H26: =IF(E26<=0,0,H$10) -> 0 | I26: =IF(I25<L25,0,I25-K25) -> 0 | J26: =ROUND(I26*$B26,2) -> 0 | K26: =IF(I26<L26,I26,L26-J26) -> 0 | L26: =IF(I26<=0,0,L$10) -> 0 | M26: =IF(M25<P25,0,M25-O25) -> 0 | N26: =ROUND(M26*$B26,2) -> 0 | O26: =IF(M26<P26,M26,P26-N26) -> 0 | P26: =IF(M26<=0,0,P$10) -> 0 | R26: =IF(R25<U25,0,R25-T25) -> 0 | S26: =ROUND(R26*$B26,2) -> 0 | T26: =IF(R26<U26,R26,U26-S26) -> 0 | U26: =IF(R26<=0,0,$Y$15) -> 0 | V26: =IF(V25<Y25,0,V25-X25) -> 0 | W26: =ROUND(V26*$B26,2) -> 0 | X26: =IF(V26<Y26,V26,Y26-W26) -> 0 | Y26: =IF(V26<=0,0,PMT(B26,($B$2-D26+1),V26*-1)) -> 0 | Z26: =$Y26 -> 0 | AA26: =$Y26 -> 0 | AB26: =$Y26 -> 0 | AC26: =$Y26 -> 0
A27: =VLOOKUP(D27,$A$10:$C$14,3) -> 0 | B27: =A27/12 -> 0 | C27: =INT((D27+11)/12) -> 1 | D27: 8 | E27: =IF(E26<H26,0,E26-G26) -> 0 | F27: =ROUND(E27*$B27,2) -> 0 | G27: =IF(E27<H27,E27,H27-F27) -> 0 | H27: =IF(E27<=0,0,H$10) -> 0 | I27: =IF(I26<L26,0,I26-K26) -> 0 | J27: =ROUND(I27*$B27,2) -> 0 | K27: =IF(I27<L27,I27,L27-J27) -> 0 | L27: =IF(I27<=0,0,L$10) -> 0 | M27: =IF(M26<P26,0,M26-O26) -> 0 | N27: =ROUND(M27*$B27,2) -> 0 | O27: =IF(M27<P27,M27,P27-N27) -> 0 | P27: =IF(M27<=0,0,P$10) -> 0 | R27: =IF(R26<U26,0,R26-T26) -> 0 | S27: =ROUND(R27*$B27,2) -> 0 | T27: =IF(R27<U27,R27,U27-S27) -> 0 | U27: =IF(R27<=0,0,$Y$15) -> 0 | V27: =IF(V26<Y26,0,V26-X26) -> 0 | W27: =ROUND(V27*$B27,2) -> 0 | X27: =IF(V27<Y27,V27,Y27-W27) -> 0 | Y27: =IF(V27<=0,0,PMT(B27,($B$2-D27+1),V27*-1)) -> 0 | Z27: =$Y27 -> 0 | AA27: =$Y27 -> 0 | AB27: =$Y27 -> 0 | AC27: =$Y27 -> 0
A28: =VLOOKUP(D28,$A$10:$C$14,3) -> 0 | B28: =A28/12 -> 0 | C28: =INT((D28+11)/12) -> 1 | D28: 9 | E28: =IF(E27<H27,0,E27-G27) -> 0 | F28: =ROUND(E28*$B28,2) -> 0 | G28: =IF(E28<H28,E28,H28-F28) -> 0 | H28: =IF(E28<=0,0,H$10) -> 0 | I28: =IF(I27<L27,0,I27-K27) -> 0 | J28: =ROUND(I28*$B28,2) -> 0 | K28: =IF(I28<L28,I28,L28-J28) -> 0 | L28: =IF(I28<=0,0,L$10) -> 0 | M28: =IF(M27<P27,0,M27-O27) -> 0 | N28: =ROUND(M28*$B28,2) -> 0 | O28: =IF(M28<P28,M28,P28-N28) -> 0 | P28: =IF(M28<=0,0,P$10) -> 0 | R28: =IF(R27<U27,0,R27-T27) -> 0 | S28: =ROUND(R28*$B28,2) -> 0 | T28: =IF(R28<U28,R28,U28-S28) -> 0 | U28: =IF(R28<=0,0,$Y$15) -> 0 | V28: =IF(V27<Y27,0,V27-X27) -> 0 | W28: =ROUND(V28*$B28,2) -> 0 | X28: =IF(V28<Y28,V28,Y28-W28) -> 0 | Y28: =IF(V28<=0,0,PMT(B28,($B$2-D28+1),V28*-1)) -> 0 | Z28: =$Y28 -> 0 | AA28: =$Y28 -> 0 | AB28: =$Y28 -> 0 | AC28: =$Y28 -> 0
A29: =VLOOKUP(D29,$A$10:$C$14,3) -> 0 | B29: =A29/12 -> 0 | C29: =INT((D29+11)/12) -> 1 | D29: 10 | E29: =IF(E28<H28,0,E28-G28) -> 0 | F29: =ROUND(E29*$B29,2) -> 0 | G29: =IF(E29<H29,E29,H29-F29) -> 0 | H29: =IF(E29<=0,0,H$10) -> 0 | I29: =IF(I28<L28,0,I28-K28) -> 0 | J29: =ROUND(I29*$B29,2) -> 0 | K29: =IF(I29<L29,I29,L29-J29) -> 0 | L29: =IF(I29<=0,0,L$10) -> 0 | M29: =IF(M28<P28,0,M28-O28) -> 0 | N29: =ROUND(M29*$B29,2) -> 0 | O29: =IF(M29<P29,M29,P29-N29) -> 0 | P29: =IF(M29<=0,0,P$10) -> 0 | R29: =IF(R28<U28,0,R28-T28) -> 0 | S29: =ROUND(R29*$B29,2) -> 0 | T29: =IF(R29<U29,R29,U29-S29) -> 0 | U29: =IF(R29<=0,0,$Y$15) -> 0 | V29: =IF(V28<Y28,0,V28-X28) -> 0 | W29: =ROUND(V29*$B29,2) -> 0 | X29: =IF(V29<Y29,V29,Y29-W29) -> 0 | Y29: =IF(V29<=0,0,PMT(B29,($B$2-D29+1),V29*-1)) -> 0 | Z29: =$Y29 -> 0 | AA29: =$Y29 -> 0 | AB29: =$Y29 -> 0 | AC29: =$Y29 -> 0
A30: =VLOOKUP(D30,$A$10:$C$14,3) -> 0 | B30: =A30/12 -> 0 | C30: =INT((D30+11)/12) -> 1 | D30: 11 | E30: =IF(E29<H29,0,E29-G29) -> 0 | F30: =ROUND(E30*$B30,2) -> 0 | G30: =IF(E30<H30,E30,H30-F30) -> 0 | H30: =IF(E30<=0,0,H$10) -> 0 | I30: =IF(I29<L29,0,I29-K29) -> 0 | J30: =ROUND(I30*$B30,2) -> 0 | K30: =IF(I30<L30,I30,L30-J30) -> 0 | L30: =IF(I30<=0,0,L$10) -> 0 | M30: =IF(M29<P29,0,M29-O29) -> 0 | N30: =ROUND(M30*$B30,2) -> 0 | O30: =IF(M30<P30,M30,P30-N30) -> 0 | P30: =IF(M30<=0,0,P$10) -> 0 | R30: =IF(R29<U29,0,R29-T29) -> 0 | S30: =ROUND(R30*$B30,2) -> 0 | T30: =IF(R30<U30,R30,U30-S30) -> 0 | U30: =IF(R30<=0,0,$Y$15) -> 0 | V30: =IF(V29<Y29,0,V29-X29) -> 0 | W30: =ROUND(V30*$B30,2) -> 0 | X30: =IF(V30<Y30,V30,Y30-W30) -> 0 | Y30: =IF(V30<=0,0,PMT(B30,($B$2-D30+1),V30*-1)) -> 0 | Z30: =$Y30 -> 0 | AA30: =$Y30 -> 0 | AB30: =$Y30 -> 0 | AC30: =$Y30 -> 0
A31: =VLOOKUP(D31,$A$10:$C$14,3) -> 0 | B31: =A31/12 -> 0 | C31: =INT((D31+11)/12) -> 1 | D31: 12 | E31: =IF(E30<H30,0,E30-G30) -> 0 | F31: =ROUND(E31*$B31,2) -> 0 | G31: =IF(E31<H31,E31,H31-F31) -> 0 | H31: =IF(E31<=0,0,H$10) -> 0 | I31: =IF(I30<L30,0,I30-K30) -> 0 | J31: =ROUND(I31*$B31,2) -> 0 | K31: =IF(I31<L31,I31,L31-J31) -> 0 | L31: =IF(I31<=0,0,L$10) -> 0 | M31: =IF(M30<P30,0,M30-O30) -> 0 | N31: =ROUND(M31*$B31,2) -> 0 | O31: =IF(M31<P31,M31,P31-N31) -> 0 | P31: =IF(M31<=0,0,P$10) -> 0 | R31: =IF(R30<U30,0,R30-T30) -> 0 | S31: =ROUND(R31*$B31,2) -> 0 | T31: =IF(R31<U31,R31,U31-S31) -> 0 | U31: =IF(R31<=0,0,$Y$15) -> 0 | V31: =IF(V30<Y30,0,V30-X30) -> 0 | W31: =ROUND(V31*$B31,2) -> 0 | X31: =IF(V31<Y31,V31,Y31-W31) -> 0 | Y31: =IF(V31<=0,0,PMT(B31,($B$2-D31+1),V31*-1)) -> 0 | Z31: =$V31+$W31 -> 0 | AA31: =$Y31 -> 0 | AB31: =$Y31 -> 0 | AC31: =$Y31 -> 0
A32: =VLOOKUP(D32,$A$10:$C$14,3) -> 0 | B32: =A32/12 -> 0 | C32: =INT((D32+11)/12) -> 2 | D32: 13 | E32: =IF(E31<H31,0,E31-G31) -> 0 | F32: =ROUND(E32*$B32,2) -> 0 | G32: =IF(E32<H32,E32,H32-F32) -> 0 | H32: =IF(E32<=0,0,H$11) -> 0 | I32: =IF(I31<L31,0,I31-K31) -> 0 | J32: =ROUND(I32*$B32,2) -> 0 | K32: =IF(I32<L32,I32,L32-J32) -> 0 | L32: =IF(I32<=0,0,L$11) -> 0 | M32: =IF(M31<P31,0,M31-O31) -> 0 | N32: =ROUND(M32*$B32,2) -> 0 | O32: =IF(M32<P32,M32,P32-N32) -> 0 | P32: =IF(M32<=0,0,P$11) -> 0 | R32: =IF(R31<U31,0,R31-T31) -> 0 | S32: =ROUND(R32*$B32,2) -> 0 | T32: =IF(R32<U32,R32,U32-S32) -> 0 | U32: =IF(R32<=0,0,$Y$15) -> 0 | V32: =IF(V31<Y31,0,V31-X31) -> 0 | W32: =ROUND(V32*$B32,2) -> 0 | X32: =IF(V32<Y32,V32,Y32-W32) -> 0 | Y32: =IF(V32<=0,0,PMT(B32,($B$2-D32+1),V32*-1)) -> 0 | Z32: 0 | AA32: =$Y32 -> 0 | AB32: =$Y32 -> 0 | AC32: =$Y32 -> 0
A33: =VLOOKUP(D33,$A$10:$C$14,3) -> 0 | B33: =A33/12 -> 0 | C33: =INT((D33+11)/12) -> 2 | D33: 14 | E33: =IF(E32<H32,0,E32-G32) -> 0 | F33: =ROUND(E33*$B33,2) -> 0 | G33: =IF(E33<H33,E33,H33-F33) -> 0 | H33: =IF(E33<=0,0,H$11) -> 0 | I33: =IF(I32<L32,0,I32-K32) -> 0 | J33: =ROUND(I33*$B33,2) -> 0 | K33: =IF(I33<L33,I33,L33-J33) -> 0 | L33: =IF(I33<=0,0,L$11) -> 0 | M33: =IF(M32<P32,0,M32-O32) -> 0 | N33: =ROUND(M33*$B33,2) -> 0 | O33: =IF(M33<P33,M33,P33-N33) -> 0 | P33: =IF(M33<=0,0,P$11) -> 0 | R33: =IF(R32<U32,0,R32-T32) -> 0 | S33: =ROUND(R33*$B33,2) -> 0 | T33: =IF(R33<U33,R33,U33-S33) -> 0 | U33: =IF(R33<=0,0,$Y$15) -> 0 | V33: =IF(V32<Y32,0,V32-X32) -> 0 | W33: =ROUND(V33*$B33,2) -> 0 | X33: =IF(V33<Y33,V33,Y33-W33) -> 0 | Y33: =IF(V33<=0,0,PMT(B33,($B$2-D33+1),V33*-1)) -> 0 | Z33: 0 | AA33: =$Y33 -> 0 | AB33: =$Y33 -> 0 | AC33: =$Y33 -> 0
A34: =VLOOKUP(D34,$A$10:$C$14,3) -> 0 | B34: =A34/12 -> 0 | C34: =INT((D34+11)/12) -> 2 | D34: 15 | E34: =IF(E33<H33,0,E33-G33) -> 0 | F34: =ROUND(E34*$B34,2) -> 0 | G34: =IF(E34<H34,E34,H34-F34) -> 0 | H34: =IF(E34<=0,0,H$11) -> 0 | I34: =IF(I33<L33,0,I33-K33) -> 0 | J34: =ROUND(I34*$B34,2) -> 0 | K34: =IF(I34<L34,I34,L34-J34) -> 0 | L34: =IF(I34<=0,0,L$11) -> 0 | M34: =IF(M33<P33,0,M33-O33) -> 0 | N34: =ROUND(M34*$B34,2) -> 0 | O34: =IF(M34<P34,M34,P34-N34) -> 0 | P34: =IF(M34<=0,0,P$11) -> 0 | R34: =IF(R33<U33,0,R33-T33) -> 0 | S34: =ROUND(R34*$B34,2) -> 0 | T34: =IF(R34<U34,R34,U34-S34) -> 0 | U34: =IF(R34<=0,0,$Y$15) -> 0 | V34: =IF(V33<Y33,0,V33-X33) -> 0 | W34: =ROUND(V34*$B34,2) -> 0 | X34: =IF(V34<Y34,V34,Y34-W34) -> 0 | Y34: =IF(V34<=0,0,PMT(B34,($B$2-D34+1),V34*-1)) -> 0 | Z34: 0 | AA34: =$Y34 -> 0 | AB34: =$Y34 -> 0 | AC34: =$Y34 -> 0
A35: =VLOOKUP(D35,$A$10:$C$14,3) -> 0 | B35: =A35/12 -> 0 | C35: =INT((D35+11)/12) -> 2 | D35: 16 | E35: =IF(E34<H34,0,E34-G34) -> 0 | F35: =ROUND(E35*$B35,2) -> 0 | G35: =IF(E35<H35,E35,H35-F35) -> 0 | H35: =IF(E35<=0,0,H$11) -> 0 | I35: =IF(I34<L34,0,I34-K34) -> 0 | J35: =ROUND(I35*$B35,2) -> 0 | K35: =IF(I35<L35,I35,L35-J35) -> 0 | L35: =IF(I35<=0,0,L$11) -> 0 | M35: =IF(M34<P34,0,M34-O34) -> 0 | N35: =ROUND(M35*$B35,2) -> 0 | O35: =IF(M35<P35,M35,P35-N35) -> 0 | P35: =IF(M35<=0,0,P$11) -> 0 | R35: =IF(R34<U34,0,R34-T34) -> 0 | S35: =ROUND(R35*$B35,2) -> 0 | T35: =IF(R35<U35,R35,U35-S35) -> 0 | U35: =IF(R35<=0,0,$Y$15) -> 0 | V35: =IF(V34<Y34,0,V34-X34) -> 0 | W35: =ROUND(V35*$B35,2) -> 0 | X35: =IF(V35<Y35,V35,Y35-W35) -> 0 | Y35: =IF(V35<=0,0,PMT(B35,($B$2-D35+1),V35*-1)) -> 0 | Z35: 0 | AA35: =$Y35 -> 0 | AB35: =$Y35 -> 0 | AC35: =$Y35 -> 0
A36: =VLOOKUP(D36,$A$10:$C$14,3) -> 0 | B36: =A36/12 -> 0 | C36: =INT((D36+11)/12) -> 2 | D36: 17 | E36: =IF(E35<H35,0,E35-G35) -> 0 | F36: =ROUND(E36*$B36,2) -> 0 | G36: =IF(E36<H36,E36,H36-F36) -> 0 | H36: =IF(E36<=0,0,H$11) -> 0 | I36: =IF(I35<L35,0,I35-K35) -> 0 | J36: =ROUND(I36*$B36,2) -> 0 | K36: =IF(I36<L36,I36,L36-J36) -> 0 | L36: =IF(I36<=0,0,L$11) -> 0 | M36: =IF(M35<P35,0,M35-O35) -> 0 | N36: =ROUND(M36*$B36,2) -> 0 | O36: =IF(M36<P36,M36,P36-N36) -> 0 | P36: =IF(M36<=0,0,P$11) -> 0 | R36: =IF(R35<U35,0,R35-T35) -> 0 | S36: =ROUND(R36*$B36,2) -> 0 | T36: =IF(R36<U36,R36,U36-S36) -> 0 | U36: =IF(R36<=0,0,$Y$15) -> 0 | V36: =IF(V35<Y35,0,V35-X35) -> 0 | W36: =ROUND(V36*$B36,2) -> 0 | X36: =IF(V36<Y36,V36,Y36-W36) -> 0 | Y36: =IF(V36<=0,0,PMT(B36,($B$2-D36+1),V36*-1)) -> 0 | Z36: 0 | AA36: =$Y36 -> 0 | AB36: =$Y36 -> 0 | AC36: =$Y36 -> 0
A37: =VLOOKUP(D37,$A$10:$C$14,3) -> 0 | B37: =A37/12 -> 0 | C37: =INT((D37+11)/12) -> 2 | D37: 18 | E37: =IF(E36<H36,0,E36-G36) -> 0 | F37: =ROUND(E37*$B37,2) -> 0 | G37: =IF(E37<H37,E37,H37-F37) -> 0 | H37: =IF(E37<=0,0,H$11) -> 0 | I37: =IF(I36<L36,0,I36-K36) -> 0 | J37: =ROUND(I37*$B37,2) -> 0 | K37: =IF(I37<L37,I37,L37-J37) -> 0 | L37: =IF(I37<=0,0,L$11) -> 0 | M37: =IF(M36<P36,0,M36-O36) -> 0 | N37: =ROUND(M37*$B37,2) -> 0 | O37: =IF(M37<P37,M37,P37-N37) -> 0 | P37: =IF(M37<=0,0,P$11) -> 0 | R37: =IF(R36<U36,0,R36-T36) -> 0 | S37: =ROUND(R37*$B37,2) -> 0 | T37: =IF(R37<U37,R37,U37-S37) -> 0 | U37: =IF(R37<=0,0,$Y$15) -> 0 | V37: =IF(V36<Y36,0,V36-X36) -> 0 | W37: =ROUND(V37*$B37,2) -> 0 | X37: =IF(V37<Y37,V37,Y37-W37) -> 0 | Y37: =IF(V37<=0,0,PMT(B37,($B$2-D37+1),V37*-1)) -> 0 | Z37: 0 | AA37: =$Y37 -> 0 | AB37: =$Y37 -> 0 | AC37: =$Y37 -> 0
A38: =VLOOKUP(D38,$A$10:$C$14,3) -> 0 | B38: =A38/12 -> 0 | C38: =INT((D38+11)/12) -> 2 | D38: 19 | E38: =IF(E37<H37,0,E37-G37) -> 0 | F38: =ROUND(E38*$B38,2) -> 0 | G38: =IF(E38<H38,E38,H38-F38) -> 0 | H38: =IF(E38<=0,0,H$11) -> 0 | I38: =IF(I37<L37,0,I37-K37) -> 0 | J38: =ROUND(I38*$B38,2) -> 0 | K38: =IF(I38<L38,I38,L38-J38) -> 0 | L38: =IF(I38<=0,0,L$11) -> 0 | M38: =IF(M37<P37,0,M37-O37) -> 0 | N38: =ROUND(M38*$B38,2) -> 0 | O38: =IF(M38<P38,M38,P38-N38) -> 0 | P38: =IF(M38<=0,0,P$11) -> 0 | R38: =IF(R37<U37,0,R37-T37) -> 0 | S38: =ROUND(R38*$B38,2) -> 0 | T38: =IF(R38<U38,R38,U38-S38) -> 0 | U38: =IF(R38<=0,0,$Y$15) -> 0 | V38: =IF(V37<Y37,0,V37-X37) -> 0 | W38: =ROUND(V38*$B38,2) -> 0 | X38: =IF(V38<Y38,V38,Y38-W38) -> 0 | Y38: =IF(V38<=0,0,PMT(B38,($B$2-D38+1),V38*-1)) -> 0 | Z38: 0 | AA38: =$Y38 -> 0 | AB38: =$Y38 -> 0 | AC38: =$Y38 -> 0
A39: =VLOOKUP(D39,$A$10:$C$14,3) -> 0 | B39: =A39/12 -> 0 | C39: =INT((D39+11)/12) -> 2 | D39: 20 | E39: =IF(E38<H38,0,E38-G38) -> 0 | F39: =ROUND(E39*$B39,2) -> 0 | G39: =IF(E39<H39,E39,H39-F39) -> 0 | H39: =IF(E39<=0,0,H$11) -> 0 | I39: =IF(I38<L38,0,I38-K38) -> 0 | J39: =ROUND(I39*$B39,2) -> 0 | K39: =IF(I39<L39,I39,L39-J39) -> 0 | L39: =IF(I39<=0,0,L$11) -> 0 | M39: =IF(M38<P38,0,M38-O38) -> 0 | N39: =ROUND(M39*$B39,2) -> 0 | O39: =IF(M39<P39,M39,P39-N39) -> 0 | P39: =IF(M39<=0,0,P$11) -> 0 | R39: =IF(R38<U38,0,R38-T38) -> 0 | S39: =ROUND(R39*$B39,2) -> 0 | T39: =IF(R39<U39,R39,U39-S39) -> 0 | U39: =IF(R39<=0,0,$Y$15) -> 0 | V39: =IF(V38<Y38,0,V38-X38) -> 0 | W39: =ROUND(V39*$B39,2) -> 0 | X39: =IF(V39<Y39,V39,Y39-W39) -> 0 | Y39: =IF(V39<=0,0,PMT(B39,($B$2-D39+1),V39*-1)) -> 0 | Z39: 0 | AA39: =$Y39 -> 0 | AB39: =$Y39 -> 0 | AC39: =$Y39 -> 0
A40: =VLOOKUP(D40,$A$10:$C$14,3) -> 0 | B40: =A40/12 -> 0 | C40: =INT((D40+11)/12) -> 2 | D40: 21 | E40: =IF(E39<H39,0,E39-G39) -> 0 | F40: =ROUND(E40*$B40,2) -> 0 | G40: =IF(E40<H40,E40,H40-F40) -> 0 | H40: =IF(E40<=0,0,H$11) -> 0 | I40: =IF(I39<L39,0,I39-K39) -> 0 | J40: =ROUND(I40*$B40,2) -> 0 | K40: =IF(I40<L40,I40,L40-J40) -> 0 | L40: =IF(I40<=0,0,L$11) -> 0 | M40: =IF(M39<P39,0,M39-O39) -> 0 | N40: =ROUND(M40*$B40,2) -> 0 | O40: =IF(M40<P40,M40,P40-N40) -> 0 | P40: =IF(M40<=0,0,P$11) -> 0 | R40: =IF(R39<U39,0,R39-T39) -> 0 | S40: =ROUND(R40*$B40,2) -> 0 | T40: =IF(R40<U40,R40,U40-S40) -> 0 | U40: =IF(R40<=0,0,$Y$15) -> 0 | V40: =IF(V39<Y39,0,V39-X39) -> 0 | W40: =ROUND(V40*$B40,2) -> 0 | X40: =IF(V40<Y40,V40,Y40-W40) -> 0 | Y40: =IF(V40<=0,0,PMT(B40,($B$2-D40+1),V40*-1)) -> 0 | Z40: 0 | AA40: =$Y40 -> 0 | AB40: =$Y40 -> 0 | AC40: =$Y40 -> 0
A41: =VLOOKUP(D41,$A$10:$C$14,3) -> 0 | B41: =A41/12 -> 0 | C41: =INT((D41+11)/12) -> 2 | D41: 22 | E41: =IF(E40<H40,0,E40-G40) -> 0 | F41: =ROUND(E41*$B41,2) -> 0 | G41: =IF(E41<H41,E41,H41-F41) -> 0 | H41: =IF(E41<=0,0,H$11) -> 0 | I41: =IF(I40<L40,0,I40-K40) -> 0 | J41: =ROUND(I41*$B41,2) -> 0 | K41: =IF(I41<L41,I41,L41-J41) -> 0 | L41: =IF(I41<=0,0,L$11) -> 0 | M41: =IF(M40<P40,0,M40-O40) -> 0 | N41: =ROUND(M41*$B41,2) -> 0 | O41: =IF(M41<P41,M41,P41-N41) -> 0 | P41: =IF(M41<=0,0,P$11) -> 0 | R41: =IF(R40<U40,0,R40-T40) -> 0 | S41: =ROUND(R41*$B41,2) -> 0 | T41: =IF(R41<U41,R41,U41-S41) -> 0 | U41: =IF(R41<=0,0,$Y$15) -> 0 | V41: =IF(V40<Y40,0,V40-X40) -> 0 | W41: =ROUND(V41*$B41,2) -> 0 | X41: =IF(V41<Y41,V41,Y41-W41) -> 0 | Y41: =IF(V41<=0,0,PMT(B41,($B$2-D41+1),V41*-1)) -> 0 | Z41: 0 | AA41: =$Y41 -> 0 | AB41: =$Y41 -> 0 | AC41: =$Y41 -> 0
A42: =VLOOKUP(D42,$A$10:$C$14,3) -> 0 | B42: =A42/12 -> 0 | C42: =INT((D42+11)/12) -> 2 | D42: 23 | E42: =IF(E41<H41,0,E41-G41) -> 0 | F42: =ROUND(E42*$B42,2) -> 0 | G42: =IF(E42<H42,E42,H42-F42) -> 0 | H42: =IF(E42<=0,0,H$11) -> 0 | I42: =IF(I41<L41,0,I41-K41) -> 0 | J42: =ROUND(I42*$B42,2) -> 0 | K42: =IF(I42<L42,I42,L42-J42) -> 0 | L42: =IF(I42<=0,0,L$11) -> 0 | M42: =IF(M41<P41,0,M41-O41) -> 0 | N42: =ROUND(M42*$B42,2) -> 0 | O42: =IF(M42<P42,M42,P42-N42) -> 0 | P42: =IF(M42<=0,0,P$11) -> 0 | R42: =IF(R41<U41,0,R41-T41) -> 0 | S42: =ROUND(R42*$B42,2) -> 0 | T42: =IF(R42<U42,R42,U42-S42) -> 0 | U42: =IF(R42<=0,0,$Y$15) -> 0 | V42: =IF(V41<Y41,0,V41-X41) -> 0 | W42: =ROUND(V42*$B42,2) -> 0 | X42: =IF(V42<Y42,V42,Y42-W42) -> 0 | Y42: =IF(V42<=0,0,PMT(B42,($B$2-D42+1),V42*-1)) -> 0 | Z42: 0 | AA42: =$Y42 -> 0 | AB42: =$Y42 -> 0 | AC42: =$Y42 -> 0
A43: =VLOOKUP(D43,$A$10:$C$14,3) -> 0 | B43: =A43/12 -> 0 | C43: =INT((D43+11)/12) -> 2 | D43: 24 | E43: =IF(E42<H42,0,E42-G42) -> 0 | F43: =ROUND(E43*$B43,2) -> 0 | G43: =IF(E43<H43,E43,H43-F43) -> 0 | H43: =IF(E43<=0,0,H$11) -> 0 | I43: =IF(I42<L42,0,I42-K42) -> 0 | J43: =ROUND(I43*$B43,2) -> 0 | K43: =IF(I43<L43,I43,L43-J43) -> 0 | L43: =IF(I43<=0,0,L$11) -> 0 | M43: =IF(M42<P42,0,M42-O42) -> 0 | N43: =ROUND(M43*$B43,2) -> 0 | O43: =IF(M43<P43,M43,P43-N43) -> 0 | P43: =IF(M43<=0,0,P$11) -> 0 | R43: =IF(R42<U42,0,R42-T42) -> 0 | S43: =ROUND(R43*$B43,2) -> 0 | T43: =IF(R43<U43,R43,U43-S43) -> 0 | U43: =IF(R43<=0,0,$Y$15) -> 0 | V43: =IF(V42<Y42,0,V42-X42) -> 0 | W43: =ROUND(V43*$B43,2) -> 0 | X43: =IF(V43<Y43,V43,Y43-W43) -> 0 | Y43: =IF(V43<=0,0,PMT(B43,($B$2-D43+1),V43*-1)) -> 0 | Z43: 0 | AA43: =$V43+$W43 -> 0 | AB43: =$Y43 -> 0 | AC43: =$Y43 -> 0
A44: =VLOOKUP(D44,$A$10:$C$14,3) -> 0 | B44: =A44/12 -> 0 | C44: =INT((D44+11)/12) -> 3 | D44: 25 | E44: =IF(E43<H43,0,E43-G43) -> 0 | F44: =ROUND(E44*$B44,2) -> 0 | G44: =IF(E44<H44,E44,H44-F44) -> 0 | H44: =IF(E44<=0,0,H$12) -> 0 | I44: =IF(I43<L43,0,I43-K43) -> 0 | J44: =ROUND(I44*$B44,2) -> 0 | K44: =IF(I44<L44,I44,L44-J44) -> 0 | L44: =IF(I44<=0,0,L$12) -> 0 | M44: =IF(M43<P43,0,M43-O43) -> 0 | N44: =ROUND(M44*$B44,2) -> 0 | O44: =IF(M44<P44,M44,P44-N44) -> 0 | P44: =IF(M44<=0,0,P$12) -> 0 | R44: =IF(R43<U43,0,R43-T43) -> 0 | S44: =ROUND(R44*$B44,2) -> 0 | T44: =IF(R44<U44,R44,U44-S44) -> 0 | U44: =IF(R44<=0,0,$Y$15) -> 0 | V44: =IF(V43<Y43,0,V43-X43) -> 0 | W44: =ROUND(V44*$B44,2) -> 0 | X44: =IF(V44<Y44,V44,Y44-W44) -> 0 | Y44: =IF(V44<=0,0,PMT(B44,($B$2-D44+1),V44*-1)) -> 0 | Z44: 0 | AA44: 0 | AB44: =$Y44 -> 0 | AC44: =$Y44 -> 0
A45: =VLOOKUP(D45,$A$10:$C$14,3) -> 0 | B45: =A45/12 -> 0 | C45: =INT((D45+11)/12) -> 3 | D45: 26 | E45: =IF(E44<H44,0,E44-G44) -> 0 | F45: =ROUND(E45*$B45,2) -> 0 | G45: =IF(E45<H45,E45,H45-F45) -> 0 | H45: =IF(E45<=0,0,H$12) -> 0 | I45: =IF(I44<L44,0,I44-K44) -> 0 | J45: =ROUND(I45*$B45,2) -> 0 | K45: =IF(I45<L45,I45,L45-J45) -> 0 | L45: =IF(I45<=0,0,L$12) -> 0 | M45: =IF(M44<P44,0,M44-O44) -> 0 | N45: =ROUND(M45*$B45,2) -> 0 | O45: =IF(M45<P45,M45,P45-N45) -> 0 | P45: =IF(M45<=0,0,P$12) -> 0 | R45: =IF(R44<U44,0,R44-T44) -> 0 | S45: =ROUND(R45*$B45,2) -> 0 | T45: =IF(R45<U45,R45,U45-S45) -> 0 | U45: =IF(R45<=0,0,$Y$15) -> 0 | V45: =IF(V44<Y44,0,V44-X44) -> 0 | W45: =ROUND(V45*$B45,2) -> 0 | X45: =IF(V45<Y45,V45,Y45-W45) -> 0 | Y45: =IF(V45<=0,0,PMT(B45,($B$2-D45+1),V45*-1)) -> 0 | Z45: 0 | AA45: 0 | AB45: =$Y45 -> 0 | AC45: =$Y45 -> 0
A46: =VLOOKUP(D46,$A$10:$C$14,3) -> 0 | B46: =A46/12 -> 0 | C46: =INT((D46+11)/12) -> 3 | D46: 27 | E46: =IF(E45<H45,0,E45-G45) -> 0 | F46: =ROUND(E46*$B46,2) -> 0 | G46: =IF(E46<H46,E46,H46-F46) -> 0 | H46: =IF(E46<=0,0,H$12) -> 0 | I46: =IF(I45<L45,0,I45-K45) -> 0 | J46: =ROUND(I46*$B46,2) -> 0 | K46: =IF(I46<L46,I46,L46-J46) -> 0 | L46: =IF(I46<=0,0,L$12) -> 0 | M46: =IF(M45<P45,0,M45-O45) -> 0 | N46: =ROUND(M46*$B46,2) -> 0 | O46: =IF(M46<P46,M46,P46-N46) -> 0 | P46: =IF(M46<=0,0,P$12) -> 0 | R46: =IF(R45<U45,0,R45-T45) -> 0 | S46: =ROUND(R46*$B46,2) -> 0 | T46: =IF(R46<U46,R46,U46-S46) -> 0 | U46: =IF(R46<=0,0,$Y$15) -> 0 | V46: =IF(V45<Y45,0,V45-X45) -> 0 | W46: =ROUND(V46*$B46,2) -> 0 | X46: =IF(V46<Y46,V46,Y46-W46) -> 0 | Y46: =IF(V46<=0,0,PMT(B46,($B$2-D46+1),V46*-1)) -> 0 | Z46: 0 | AA46: 0 | AB46: =$Y46 -> 0 | AC46: =$Y46 -> 0
A47: =VLOOKUP(D47,$A$10:$C$14,3) -> 0 | B47: =A47/12 -> 0 | C47: =INT((D47+11)/12) -> 3 | D47: 28 | E47: =IF(E46<H46,0,E46-G46) -> 0 | F47: =ROUND(E47*$B47,2) -> 0 | G47: =IF(E47<H47,E47,H47-F47) -> 0 | H47: =IF(E47<=0,0,H$12) -> 0 | I47: =IF(I46<L46,0,I46-K46) -> 0 | J47: =ROUND(I47*$B47,2) -> 0 | K47: =IF(I47<L47,I47,L47-J47) -> 0 | L47: =IF(I47<=0,0,L$12) -> 0 | M47: =IF(M46<P46,0,M46-O46) -> 0 | N47: =ROUND(M47*$B47,2) -> 0 | O47: =IF(M47<P47,M47,P47-N47) -> 0 | P47: =IF(M47<=0,0,P$12) -> 0 | R47: =IF(R46<U46,0,R46-T46) -> 0 | S47: =ROUND(R47*$B47,2) -> 0 | T47: =IF(R47<U47,R47,U47-S47) -> 0 | U47: =IF(R47<=0,0,$Y$15) -> 0 | V47: =IF(V46<Y46,0,V46-X46) -> 0 | W47: =ROUND(V47*$B47,2) -> 0 | X47: =IF(V47<Y47,V47,Y47-W47) -> 0 | Y47: =IF(V47<=0,0,PMT(B47,($B$2-D47+1),V47*-1)) -> 0 | Z47: 0 | AA47: 0 | AB47: =$Y47 -> 0 | AC47: =$Y47 -> 0
A48: =VLOOKUP(D48,$A$10:$C$14,3) -> 0 | B48: =A48/12 -> 0 | C48: =INT((D48+11)/12) -> 3 | D48: 29 | E48: =IF(E47<H47,0,E47-G47) -> 0 | F48: =ROUND(E48*$B48,2) -> 0 | G48: =IF(E48<H48,E48,H48-F48) -> 0 | H48: =IF(E48<=0,0,H$12) -> 0 | I48: =IF(I47<L47,0,I47-K47) -> 0 | J48: =ROUND(I48*$B48,2) -> 0 | K48: =IF(I48<L48,I48,L48-J48) -> 0 | L48: =IF(I48<=0,0,L$12) -> 0 | M48: =IF(M47<P47,0,M47-O47) -> 0 | N48: =ROUND(M48*$B48,2) -> 0 | O48: =IF(M48<P48,M48,P48-N48) -> 0 | P48: =IF(M48<=0,0,P$12) -> 0 | R48: =IF(R47<U47,0,R47-T47) -> 0 | S48: =ROUND(R48*$B48,2) -> 0 | T48: =IF(R48<U48,R48,U48-S48) -> 0 | U48: =IF(R48<=0,0,$Y$15) -> 0 | V48: =IF(V47<Y47,0,V47-X47) -> 0 | W48: =ROUND(V48*$B48,2) -> 0 | X48: =IF(V48<Y48,V48,Y48-W48) -> 0 | Y48: =IF(V48<=0,0,PMT(B48,($B$2-D48+1),V48*-1)) -> 0 | Z48: 0 | AA48: 0 | AB48: =$Y48 -> 0 | AC48: =$Y48 -> 0
A49: =VLOOKUP(D49,$A$10:$C$14,3) -> 0 | B49: =A49/12 -> 0 | C49: =INT((D49+11)/12) -> 3 | D49: 30 | E49: =IF(E48<H48,0,E48-G48) -> 0 | F49: =ROUND(E49*$B49,2) -> 0 | G49: =IF(E49<H49,E49,H49-F49) -> 0 | H49: =IF(E49<=0,0,H$12) -> 0 | I49: =IF(I48<L48,0,I48-K48) -> 0 | J49: =ROUND(I49*$B49,2) -> 0 | K49: =IF(I49<L49,I49,L49-J49) -> 0 | L49: =IF(I49<=0,0,L$12) -> 0 | M49: =IF(M48<P48,0,M48-O48) -> 0 | N49: =ROUND(M49*$B49,2) -> 0 | O49: =IF(M49<P49,M49,P49-N49) -> 0 | P49: =IF(M49<=0,0,P$12) -> 0 | R49: =IF(R48<U48,0,R48-T48) -> 0 | S49: =ROUND(R49*$B49,2) -> 0 | T49: =IF(R49<U49,R49,U49-S49) -> 0 | U49: =IF(R49<=0,0,$Y$15) -> 0 | V49: =IF(V48<Y48,0,V48-X48) -> 0 | W49: =ROUND(V49*$B49,2) -> 0 | X49: =IF(V49<Y49,V49,Y49-W49) -> 0 | Y49: =IF(V49<=0,0,PMT(B49,($B$2-D49+1),V49*-1)) -> 0 | Z49: 0 | AA49: 0 | AB49: =$Y49 -> 0 | AC49: =$Y49 -> 0
A50: =VLOOKUP(D50,$A$10:$C$14,3) -> 0 | B50: =A50/12 -> 0 | C50: =INT((D50+11)/12) -> 3 | D50: 31 | E50: =IF(E49<H49,0,E49-G49) -> 0 | F50: =ROUND(E50*$B50,2) -> 0 | G50: =IF(E50<H50,E50,H50-F50) -> 0 | H50: =IF(E50<=0,0,H$12) -> 0 | I50: =IF(I49<L49,0,I49-K49) -> 0 | J50: =ROUND(I50*$B50,2) -> 0 | K50: =IF(I50<L50,I50,L50-J50) -> 0 | L50: =IF(I50<=0,0,L$12) -> 0 | M50: =IF(M49<P49,0,M49-O49) -> 0 | N50: =ROUND(M50*$B50,2) -> 0 | O50: =IF(M50<P50,M50,P50-N50) -> 0 | P50: =IF(M50<=0,0,P$12) -> 0 | R50: =IF(R49<U49,0,R49-T49) -> 0 | S50: =ROUND(R50*$B50,2) -> 0 | T50: =IF(R50<U50,R50,U50-S50) -> 0 | U50: =IF(R50<=0,0,$Y$15) -> 0 | V50: =IF(V49<Y49,0,V49-X49) -> 0 | W50: =ROUND(V50*$B50,2) -> 0 | X50: =IF(V50<Y50,V50,Y50-W50) -> 0 | Y50: =IF(V50<=0,0,PMT(B50,($B$2-D50+1),V50*-1)) -> 0 | Z50: 0 | AA50: 0 | AB50: =$Y50 -> 0 | AC50: =$Y50 -> 0
A51: =VLOOKUP(D51,$A$10:$C$14,3) -> 0 | B51: =A51/12 -> 0 | C51: =INT((D51+11)/12) -> 3 | D51: 32 | E51: =IF(E50<H50,0,E50-G50) -> 0 | F51: =ROUND(E51*$B51,2) -> 0 | G51: =IF(E51<H51,E51,H51-F51) -> 0 | H51: =IF(E51<=0,0,H$12) -> 0 | I51: =IF(I50<L50,0,I50-K50) -> 0 | J51: =ROUND(I51*$B51,2) -> 0 | K51: =IF(I51<L51,I51,L51-J51) -> 0 | L51: =IF(I51<=0,0,L$12) -> 0 | M51: =IF(M50<P50,0,M50-O50) -> 0 | N51: =ROUND(M51*$B51,2) -> 0 | O51: =IF(M51<P51,M51,P51-N51) -> 0 | P51: =IF(M51<=0,0,P$12) -> 0 | R51: =IF(R50<U50,0,R50-T50) -> 0 | S51: =ROUND(R51*$B51,2) -> 0 | T51: =IF(R51<U51,R51,U51-S51) -> 0 | U51: =IF(R51<=0,0,$Y$15) -> 0 | V51: =IF(V50<Y50,0,V50-X50) -> 0 | W51: =ROUND(V51*$B51,2) -> 0 | X51: =IF(V51<Y51,V51,Y51-W51) -> 0 | Y51: =IF(V51<=0,0,PMT(B51,($B$2-D51+1),V51*-1)) -> 0 | Z51: 0 | AA51: 0 | AB51: =$Y51 -> 0 | AC51: =$Y51 -> 0
A52: =VLOOKUP(D52,$A$10:$C$14,3) -> 0 | B52: =A52/12 -> 0 | C52: =INT((D52+11)/12) -> 3 | D52: 33 | E52: =IF(E51<H51,0,E51-G51) -> 0 | F52: =ROUND(E52*$B52,2) -> 0 | G52: =IF(E52<H52,E52,H52-F52) -> 0 | H52: =IF(E52<=0,0,H$12) -> 0 | I52: =IF(I51<L51,0,I51-K51) -> 0 | J52: =ROUND(I52*$B52,2) -> 0 | K52: =IF(I52<L52,I52,L52-J52) -> 0 | L52: =IF(I52<=0,0,L$12) -> 0 | M52: =IF(M51<P51,0,M51-O51) -> 0 | N52: =ROUND(M52*$B52,2) -> 0 | O52: =IF(M52<P52,M52,P52-N52) -> 0 | P52: =IF(M52<=0,0,P$12) -> 0 | R52: =IF(R51<U51,0,R51-T51) -> 0 | S52: =ROUND(R52*$B52,2) -> 0 | T52: =IF(R52<U52,R52,U52-S52) -> 0 | U52: =IF(R52<=0,0,$Y$15) -> 0 | V52: =IF(V51<Y51,0,V51-X51) -> 0 | W52: =ROUND(V52*$B52,2) -> 0 | X52: =IF(V52<Y52,V52,Y52-W52) -> 0 | Y52: =IF(V52<=0,0,PMT(B52,($B$2-D52+1),V52*-1)) -> 0 | Z52: 0 | AA52: 0 | AB52: =$Y52 -> 0 | AC52: =$Y52 -> 0
A53: =VLOOKUP(D53,$A$10:$C$14,3) -> 0 | B53: =A53/12 -> 0 | C53: =INT((D53+11)/12) -> 3 | D53: 34 | E53: =IF(E52<H52,0,E52-G52) -> 0 | F53: =ROUND(E53*$B53,2) -> 0 | G53: =IF(E53<H53,E53,H53-F53) -> 0 | H53: =IF(E53<=0,0,H$12) -> 0 | I53: =IF(I52<L52,0,I52-K52) -> 0 | J53: =ROUND(I53*$B53,2) -> 0 | K53: =IF(I53<L53,I53,L53-J53) -> 0 | L53: =IF(I53<=0,0,L$12) -> 0 | M53: =IF(M52<P52,0,M52-O52) -> 0 | N53: =ROUND(M53*$B53,2) -> 0 | O53: =IF(M53<P53,M53,P53-N53) -> 0 | P53: =IF(M53<=0,0,P$12) -> 0 | R53: =IF(R52<U52,0,R52-T52) -> 0 | S53: =ROUND(R53*$B53,2) -> 0 | T53: =IF(R53<U53,R53,U53-S53) -> 0 | U53: =IF(R53<=0,0,$Y$15) -> 0 | V53: =IF(V52<Y52,0,V52-X52) -> 0 | W53: =ROUND(V53*$B53,2) -> 0 | X53: =IF(V53<Y53,V53,Y53-W53) -> 0 | Y53: =IF(V53<=0,0,PMT(B53,($B$2-D53+1),V53*-1)) -> 0 | Z53: 0 | AA53: 0 | AB53: =$Y53 -> 0 | AC53: =$Y53 -> 0
A54: =VLOOKUP(D54,$A$10:$C$14,3) -> 0 | B54: =A54/12 -> 0 | C54: =INT((D54+11)/12) -> 3 | D54: 35 | E54: =IF(E53<H53,0,E53-G53) -> 0 | F54: =ROUND(E54*$B54,2) -> 0 | G54: =IF(E54<H54,E54,H54-F54) -> 0 | H54: =IF(E54<=0,0,H$12) -> 0 | I54: =IF(I53<L53,0,I53-K53) -> 0 | J54: =ROUND(I54*$B54,2) -> 0 | K54: =IF(I54<L54,I54,L54-J54) -> 0 | L54: =IF(I54<=0,0,L$12) -> 0 | M54: =IF(M53<P53,0,M53-O53) -> 0 | N54: =ROUND(M54*$B54,2) -> 0 | O54: =IF(M54<P54,M54,P54-N54) -> 0 | P54: =IF(M54<=0,0,P$12) -> 0 | R54: =IF(R53<U53,0,R53-T53) -> 0 | S54: =ROUND(R54*$B54,2) -> 0 | T54: =IF(R54<U54,R54,U54-S54) -> 0 | U54: =IF(R54<=0,0,$Y$15) -> 0 | V54: =IF(V53<Y53,0,V53-X53) -> 0 | W54: =ROUND(V54*$B54,2) -> 0 | X54: =IF(V54<Y54,V54,Y54-W54) -> 0 | Y54: =IF(V54<=0,0,PMT(B54,($B$2-D54+1),V54*-1)) -> 0 | Z54: 0 | AA54: 0 | AB54: =$Y54 -> 0 | AC54: =$Y54 -> 0
A55: =VLOOKUP(D55,$A$10:$C$14,3) -> 0 | B55: =A55/12 -> 0 | C55: =INT((D55+11)/12) -> 3 | D55: 36 | E55: =IF(E54<H54,0,E54-G54) -> 0 | F55: =ROUND(E55*$B55,2) -> 0 | G55: =IF(E55<H55,E55,H55-F55) -> 0 | H55: =IF(E55<=0,0,H$12) -> 0 | I55: =IF(I54<L54,0,I54-K54) -> 0 | J55: =ROUND(I55*$B55,2) -> 0 | K55: =IF(I55<L55,I55,L55-J55) -> 0 | L55: =IF(I55<=0,0,L$12) -> 0 | M55: =IF(M54<P54,0,M54-O54) -> 0 | N55: =ROUND(M55*$B55,2) -> 0 | O55: =IF(M55<P55,M55,P55-N55) -> 0 | P55: =IF(M55<=0,0,P$12) -> 0 | R55: =IF(R54<U54,0,R54-T54) -> 0 | S55: =ROUND(R55*$B55,2) -> 0 | T55: =IF(R55<U55,R55,U55-S55) -> 0 | U55: =IF(R55<=0,0,$Y$15) -> 0 | V55: =IF(V54<Y54,0,V54-X54) -> 0 | W55: =ROUND(V55*$B55,2) -> 0 | X55: =IF(V55<Y55,V55,Y55-W55) -> 0 | Y55: =IF(V55<=0,0,PMT(B55,($B$2-D55+1),V55*-1)) -> 0 | Z55: 0 | AA55: 0 | AB55: =$V55+$W55 -> 0 | AC55: =$Y55 -> 0
A56: =VLOOKUP(D56,$A$10:$C$14,3) -> 0 | B56: =A56/12 -> 0 | C56: =INT((D56+11)/12) -> 4 | D56: 37 | E56: =IF(E55<H55,0,E55-G55) -> 0 | F56: =ROUND(E56*$B56,2) -> 0 | G56: =IF(E56<H56,E56,H56-F56) -> 0 | H56: =IF(E56<=0,0,H$13) -> 0 | I56: =IF(I55<L55,0,I55-K55) -> 0 | J56: =ROUND(I56*$B56,2) -> 0 | K56: =IF(I56<L56,I56,L56-J56) -> 0 | L56: =IF(I56<=0,0,L$13) -> 0 | M56: =IF(M55<P55,0,M55-O55) -> 0 | N56: =ROUND(M56*$B56,2) -> 0 | O56: =IF(M56<P56,M56,P56-N56) -> 0 | P56: =IF(M56<=0,0,P$13) -> 0 | R56: =IF(R55<U55,0,R55-T55) -> 0 | S56: =ROUND(R56*$B56,2) -> 0 | T56: =IF(R56<U56,R56,U56-S56) -> 0 | U56: =IF(R56<=0,0,$Y$15) -> 0 | V56: =IF(V55<Y55,0,V55-X55) -> 0 | W56: =ROUND(V56*$B56,2) -> 0 | X56: =IF(V56<Y56,V56,Y56-W56) -> 0 | Y56: =IF(V56<=0,0,PMT(B56,($B$2-D56+1),V56*-1)) -> 0 | Z56: 0 | AA56: 0 | AB56: 0 | AC56: =$Y56 -> 0
A57: =VLOOKUP(D57,$A$10:$C$14,3) -> 0 | B57: =A57/12 -> 0 | C57: =INT((D57+11)/12) -> 4 | D57: 38 | E57: =IF(E56<H56,0,E56-G56) -> 0 | F57: =ROUND(E57*$B57,2) -> 0 | G57: =IF(E57<H57,E57,H57-F57) -> 0 | H57: =IF(E57<=0,0,H$13) -> 0 | I57: =IF(I56<L56,0,I56-K56) -> 0 | J57: =ROUND(I57*$B57,2) -> 0 | K57: =IF(I57<L57,I57,L57-J57) -> 0 | L57: =IF(I57<=0,0,L$13) -> 0 | M57: =IF(M56<P56,0,M56-O56) -> 0 | N57: =ROUND(M57*$B57,2) -> 0 | O57: =IF(M57<P57,M57,P57-N57) -> 0 | P57: =IF(M57<=0,0,P$13) -> 0 | R57: =IF(R56<U56,0,R56-T56) -> 0 | S57: =ROUND(R57*$B57,2) -> 0 | T57: =IF(R57<U57,R57,U57-S57) -> 0 | U57: =IF(R57<=0,0,$Y$15) -> 0 | V57: =IF(V56<Y56,0,V56-X56) -> 0 | W57: =ROUND(V57*$B57,2) -> 0 | X57: =IF(V57<Y57,V57,Y57-W57) -> 0 | Y57: =IF(V57<=0,0,PMT(B57,($B$2-D57+1),V57*-1)) -> 0 | Z57: 0 | AA57: 0 | AB57: 0 | AC57: =$Y57 -> 0
A58: =VLOOKUP(D58,$A$10:$C$14,3) -> 0 | B58: =A58/12 -> 0 | C58: =INT((D58+11)/12) -> 4 | D58: 39 | E58: =IF(E57<H57,0,E57-G57) -> 0 | F58: =ROUND(E58*$B58,2) -> 0 | G58: =IF(E58<H58,E58,H58-F58) -> 0 | H58: =IF(E58<=0,0,H$13) -> 0 | I58: =IF(I57<L57,0,I57-K57) -> 0 | J58: =ROUND(I58*$B58,2) -> 0 | K58: =IF(I58<L58,I58,L58-J58) -> 0 | L58: =IF(I58<=0,0,L$13) -> 0 | M58: =IF(M57<P57,0,M57-O57) -> 0 | N58: =ROUND(M58*$B58,2) -> 0 | O58: =IF(M58<P58,M58,P58-N58) -> 0 | P58: =IF(M58<=0,0,P$13) -> 0 | R58: =IF(R57<U57,0,R57-T57) -> 0 | S58: =ROUND(R58*$B58,2) -> 0 | T58: =IF(R58<U58,R58,U58-S58) -> 0 | U58: =IF(R58<=0,0,$Y$15) -> 0 | V58: =IF(V57<Y57,0,V57-X57) -> 0 | W58: =ROUND(V58*$B58,2) -> 0 | X58: =IF(V58<Y58,V58,Y58-W58) -> 0 | Y58: =IF(V58<=0,0,PMT(B58,($B$2-D58+1),V58*-1)) -> 0 | Z58: 0 | AA58: 0 | AB58: 0 | AC58: =$Y58 -> 0
A59: =VLOOKUP(D59,$A$10:$C$14,3) -> 0 | B59: =A59/12 -> 0 | C59: =INT((D59+11)/12) -> 4 | D59: 40 | E59: =IF(E58<H58,0,E58-G58) -> 0 | F59: =ROUND(E59*$B59,2) -> 0 | G59: =IF(E59<H59,E59,H59-F59) -> 0 | H59: =IF(E59<=0,0,H$13) -> 0 | I59: =IF(I58<L58,0,I58-K58) -> 0 | J59: =ROUND(I59*$B59,2) -> 0 | K59: =IF(I59<L59,I59,L59-J59) -> 0 | L59: =IF(I59<=0,0,L$13) -> 0 | M59: =IF(M58<P58,0,M58-O58) -> 0 | N59: =ROUND(M59*$B59,2) -> 0 | O59: =IF(M59<P59,M59,P59-N59) -> 0 | P59: =IF(M59<=0,0,P$13) -> 0 | R59: =IF(R58<U58,0,R58-T58) -> 0 | S59: =ROUND(R59*$B59,2) -> 0 | T59: =IF(R59<U59,R59,U59-S59) -> 0 | U59: =IF(R59<=0,0,$Y$15) -> 0 | V59: =IF(V58<Y58,0,V58-X58) -> 0 | W59: =ROUND(V59*$B59,2) -> 0 | X59: =IF(V59<Y59,V59,Y59-W59) -> 0 | Y59: =IF(V59<=0,0,PMT(B59,($B$2-D59+1),V59*-1)) -> 0 | Z59: 0 | AA59: 0 | AB59: 0 | AC59: =$Y59 -> 0
A60: =VLOOKUP(D60,$A$10:$C$14,3) -> 0 | B60: =A60/12 -> 0 | C60: =INT((D60+11)/12) -> 4 | D60: 41 | E60: =IF(E59<H59,0,E59-G59) -> 0 | F60: =ROUND(E60*$B60,2) -> 0 | G60: =IF(E60<H60,E60,H60-F60) -> 0 | H60: =IF(E60<=0,0,H$13) -> 0 | I60: =IF(I59<L59,0,I59-K59) -> 0 | J60: =ROUND(I60*$B60,2) -> 0 | K60: =IF(I60<L60,I60,L60-J60) -> 0 | L60: =IF(I60<=0,0,L$13) -> 0 | M60: =IF(M59<P59,0,M59-O59) -> 0 | N60: =ROUND(M60*$B60,2) -> 0 | O60: =IF(M60<P60,M60,P60-N60) -> 0 | P60: =IF(M60<=0,0,P$13) -> 0 | R60: =IF(R59<U59,0,R59-T59) -> 0 | S60: =ROUND(R60*$B60,2) -> 0 | T60: =IF(R60<U60,R60,U60-S60) -> 0 | U60: =IF(R60<=0,0,$Y$15) -> 0 | V60: =IF(V59<Y59,0,V59-X59) -> 0 | W60: =ROUND(V60*$B60,2) -> 0 | X60: =IF(V60<Y60,V60,Y60-W60) -> 0 | Y60: =IF(V60<=0,0,PMT(B60,($B$2-D60+1),V60*-1)) -> 0 | Z60: 0 | AA60: 0 | AB60: 0 | AC60: =$Y60 -> 0
A61: =VLOOKUP(D61,$A$10:$C$14,3) -> 0 | B61: =A61/12 -> 0 | C61: =INT((D61+11)/12) -> 4 | D61: 42 | E61: =IF(E60<H60,0,E60-G60) -> 0 | F61: =ROUND(E61*$B61,2) -> 0 | G61: =IF(E61<H61,E61,H61-F61) -> 0 | H61: =IF(E61<=0,0,H$13) -> 0 | I61: =IF(I60<L60,0,I60-K60) -> 0 | J61: =ROUND(I61*$B61,2) -> 0 | K61: =IF(I61<L61,I61,L61-J61) -> 0 | L61: =IF(I61<=0,0,L$13) -> 0 | M61: =IF(M60<P60,0,M60-O60) -> 0 | N61: =ROUND(M61*$B61,2) -> 0 | O61: =IF(M61<P61,M61,P61-N61) -> 0 | P61: =IF(M61<=0,0,P$13) -> 0 | R61: =IF(R60<U60,0,R60-T60) -> 0 | S61: =ROUND(R61*$B61,2) -> 0 | T61: =IF(R61<U61,R61,U61-S61) -> 0 | U61: =IF(R61<=0,0,$Y$15) -> 0 | V61: =IF(V60<Y60,0,V60-X60) -> 0 | W61: =ROUND(V61*$B61,2) -> 0 | X61: =IF(V61<Y61,V61,Y61-W61) -> 0 | Y61: =IF(V61<=0,0,PMT(B61,($B$2-D61+1),V61*-1)) -> 0 | Z61: 0 | AA61: 0 | AB61: 0 | AC61: =$Y61 -> 0
A62: =VLOOKUP(D62,$A$10:$C$14,3) -> 0 | B62: =A62/12 -> 0 | C62: =INT((D62+11)/12) -> 4 | D62: 43 | E62: =IF(E61<H61,0,E61-G61) -> 0 | F62: =ROUND(E62*$B62,2) -> 0 | G62: =IF(E62<H62,E62,H62-F62) -> 0 | H62: =IF(E62<=0,0,H$13) -> 0 | I62: =IF(I61<L61,0,I61-K61) -> 0 | J62: =ROUND(I62*$B62,2) -> 0 | K62: =IF(I62<L62,I62,L62-J62) -> 0 | L62: =IF(I62<=0,0,L$13) -> 0 | M62: =IF(M61<P61,0,M61-O61) -> 0 | N62: =ROUND(M62*$B62,2) -> 0 | O62: =IF(M62<P62,M62,P62-N62) -> 0 | P62: =IF(M62<=0,0,P$13) -> 0 | R62: =IF(R61<U61,0,R61-T61) -> 0 | S62: =ROUND(R62*$B62,2) -> 0 | T62: =IF(R62<U62,R62,U62-S62) -> 0 | U62: =IF(R62<=0,0,$Y$15) -> 0 | V62: =IF(V61<Y61,0,V61-X61) -> 0 | W62: =ROUND(V62*$B62,2) -> 0 | X62: =IF(V62<Y62,V62,Y62-W62) -> 0 | Y62: =IF(V62<=0,0,PMT(B62,($B$2-D62+1),V62*-1)) -> 0 | Z62: 0 | AA62: 0 | AB62: 0 | AC62: =$Y62 -> 0
A63: =VLOOKUP(D63,$A$10:$C$14,3) -> 0 | B63: =A63/12 -> 0 | C63: =INT((D63+11)/12) -> 4 | D63: 44 | E63: =IF(E62<H62,0,E62-G62) -> 0 | F63: =ROUND(E63*$B63,2) -> 0 | G63: =IF(E63<H63,E63,H63-F63) -> 0 | H63: =IF(E63<=0,0,H$13) -> 0 | I63: =IF(I62<L62,0,I62-K62) -> 0 | J63: =ROUND(I63*$B63,2) -> 0 | K63: =IF(I63<L63,I63,L63-J63) -> 0 | L63: =IF(I63<=0,0,L$13) -> 0 | M63: =IF(M62<P62,0,M62-O62) -> 0 | N63: =ROUND(M63*$B63,2) -> 0 | O63: =IF(M63<P63,M63,P63-N63) -> 0 | P63: =IF(M63<=0,0,P$13) -> 0 | R63: =IF(R62<U62,0,R62-T62) -> 0 | S63: =ROUND(R63*$B63,2) -> 0 | T63: =IF(R63<U63,R63,U63-S63) -> 0 | U63: =IF(R63<=0,0,$Y$15) -> 0 | V63: =IF(V62<Y62,0,V62-X62) -> 0 | W63: =ROUND(V63*$B63,2) -> 0 | X63: =IF(V63<Y63,V63,Y63-W63) -> 0 | Y63: =IF(V63<=0,0,PMT(B63,($B$2-D63+1),V63*-1)) -> 0 | Z63: 0 | AA63: 0 | AB63: 0 | AC63: =$Y63 -> 0
A64: =VLOOKUP(D64,$A$10:$C$14,3) -> 0 | B64: =A64/12 -> 0 | C64: =INT((D64+11)/12) -> 4 | D64: 45 | E64: =IF(E63<H63,0,E63-G63) -> 0 | F64: =ROUND(E64*$B64,2) -> 0 | G64: =IF(E64<H64,E64,H64-F64) -> 0 | H64: =IF(E64<=0,0,H$13) -> 0 | I64: =IF(I63<L63,0,I63-K63) -> 0 | J64: =ROUND(I64*$B64,2) -> 0 | K64: =IF(I64<L64,I64,L64-J64) -> 0 | L64: =IF(I64<=0,0,L$13) -> 0 | M64: =IF(M63<P63,0,M63-O63) -> 0 | N64: =ROUND(M64*$B64,2) -> 0 | O64: =IF(M64<P64,M64,P64-N64) -> 0 | P64: =IF(M64<=0,0,P$13) -> 0 | R64: =IF(R63<U63,0,R63-T63) -> 0 | S64: =ROUND(R64*$B64,2) -> 0 | T64: =IF(R64<U64,R64,U64-S64) -> 0 | U64: =IF(R64<=0,0,$Y$15) -> 0 | V64: =IF(V63<Y63,0,V63-X63) -> 0 | W64: =ROUND(V64*$B64,2) -> 0 | X64: =IF(V64<Y64,V64,Y64-W64) -> 0 | Y64: =IF(V64<=0,0,PMT(B64,($B$2-D64+1),V64*-1)) -> 0 | Z64: 0 | AA64: 0 | AB64: 0 | AC64: =$Y64 -> 0
A65: =VLOOKUP(D65,$A$10:$C$14,3) -> 0 | B65: =A65/12 -> 0 | C65: =INT((D65+11)/12) -> 4 | D65: 46 | E65: =IF(E64<H64,0,E64-G64) -> 0 | F65: =ROUND(E65*$B65,2) -> 0 | G65: =IF(E65<H65,E65,H65-F65) -> 0 | H65: =IF(E65<=0,0,H$13) -> 0 | I65: =IF(I64<L64,0,I64-K64) -> 0 | J65: =ROUND(I65*$B65,2) -> 0 | K65: =IF(I65<L65,I65,L65-J65) -> 0 | L65: =IF(I65<=0,0,L$13) -> 0 | M65: =IF(M64<P64,0,M64-O64) -> 0 | N65: =ROUND(M65*$B65,2) -> 0 | O65: =IF(M65<P65,M65,P65-N65) -> 0 | P65: =IF(M65<=0,0,P$13) -> 0 | R65: =IF(R64<U64,0,R64-T64) -> 0 | S65: =ROUND(R65*$B65,2) -> 0 | T65: =IF(R65<U65,R65,U65-S65) -> 0 | U65: =IF(R65<=0,0,$Y$15) -> 0 | V65: =IF(V64<Y64,0,V64-X64) -> 0 | W65: =ROUND(V65*$B65,2) -> 0 | X65: =IF(V65<Y65,V65,Y65-W65) -> 0 | Y65: =IF(V65<=0,0,PMT(B65,($B$2-D65+1),V65*-1)) -> 0 | Z65: 0 | AA65: 0 | AB65: 0 | AC65: =$Y65 -> 0
A66: =VLOOKUP(D66,$A$10:$C$14,3) -> 0 | B66: =A66/12 -> 0 | C66: =INT((D66+11)/12) -> 4 | D66: 47 | E66: =IF(E65<H65,0,E65-G65) -> 0 | F66: =ROUND(E66*$B66,2) -> 0 | G66: =IF(E66<H66,E66,H66-F66) -> 0 | H66: =IF(E66<=0,0,H$13) -> 0 | I66: =IF(I65<L65,0,I65-K65) -> 0 | J66: =ROUND(I66*$B66,2) -> 0 | K66: =IF(I66<L66,I66,L66-J66) -> 0 | L66: =IF(I66<=0,0,L$13) -> 0 | M66: =IF(M65<P65,0,M65-O65) -> 0 | N66: =ROUND(M66*$B66,2) -> 0 | O66: =IF(M66<P66,M66,P66-N66) -> 0 | P66: =IF(M66<=0,0,P$13) -> 0 | R66: =IF(R65<U65,0,R65-T65) -> 0 | S66: =ROUND(R66*$B66,2) -> 0 | T66: =IF(R66<U66,R66,U66-S66) -> 0 | U66: =IF(R66<=0,0,$Y$15) -> 0 | V66: =IF(V65<Y65,0,V65-X65) -> 0 | W66: =ROUND(V66*$B66,2) -> 0 | X66: =IF(V66<Y66,V66,Y66-W66) -> 0 | Y66: =IF(V66<=0,0,PMT(B66,($B$2-D66+1),V66*-1)) -> 0 | Z66: 0 | AA66: 0 | AB66: 0 | AC66: =$Y66 -> 0
A67: =VLOOKUP(D67,$A$10:$C$14,3) -> 0 | B67: =A67/12 -> 0 | C67: =INT((D67+11)/12) -> 4 | D67: 48 | E67: =IF(E66<H66,0,E66-G66) -> 0 | F67: =ROUND(E67*$B67,2) -> 0 | G67: =IF(E67<H67,E67,H67-F67) -> 0 | H67: =IF(E67<=0,0,H$13) -> 0 | I67: =IF(I66<L66,0,I66-K66) -> 0 | J67: =ROUND(I67*$B67,2) -> 0 | K67: =IF(I67<L67,I67,L67-J67) -> 0 | L67: =IF(I67<=0,0,L$13) -> 0 | M67: =IF(M66<P66,0,M66-O66) -> 0 | N67: =ROUND(M67*$B67,2) -> 0 | O67: =IF(M67<P67,M67,P67-N67) -> 0 | P67: =IF(M67<=0,0,P$13) -> 0 | R67: =IF(R66<U66,0,R66-T66) -> 0 | S67: =ROUND(R67*$B67,2) -> 0 | T67: =IF(R67<U67,R67,U67-S67) -> 0 | U67: =IF(R67<=0,0,$Y$15) -> 0 | V67: =IF(V66<Y66,0,V66-X66) -> 0 | W67: =ROUND(V67*$B67,2) -> 0 | X67: =IF(V67<Y67,V67,Y67-W67) -> 0 | Y67: =IF(V67<=0,0,PMT(B67,($B$2-D67+1),V67*-1)) -> 0 | Z67: 0 | AA67: 0 | AB67: 0 | AC67: =$V67+$W67 -> 0
A68: =VLOOKUP(D68,$A$10:$C$14,3) -> 0 | B68: =A68/12 -> 0 | C68: =INT((D68+11)/12) -> 5 | D68: 49 | E68: =IF(E67<H67,0,E67-G67) -> 0 | F68: =ROUND(E68*$B68,2) -> 0 | G68: =IF(E68<H68,E68,H68-F68) -> 0 | H68: =IF(E68<=0,0,H$14) -> 0 | I68: =IF(I67<L67,0,I67-K67) -> 0 | J68: =ROUND(I68*$B68,2) -> 0 | K68: =IF(I68<L68,I68,L68-J68) -> 0 | L68: =IF(I68<=0,0,L$13) -> 0 | M68: =IF(M67<P67,0,M67-O67) -> 0 | N68: =ROUND(M68*$B68,2) -> 0 | O68: =IF(M68<P68,M68,P68-N68) -> 0 | P68: =IF(M68<=0,0,P$14) -> 0 | R68: =IF(R67<U67,0,R67-T67) -> 0 | S68: =ROUND(R68*$B68,2) -> 0 | T68: =IF(R68<U68,R68,U68-S68) -> 0 | U68: =IF(R68<=0,0,$Y$15) -> 0 | V68: =IF(V67<Y67,0,V67-X67) -> 0 | W68: =ROUND(V68*$B68,2) -> 0 | X68: =IF(V68<Y68,V68,Y68-W68) -> 0 | Y68: =IF(V68<=0,0,PMT(B68,($B$2-D68+1),V68*-1)) -> 0 | Z68: 0 | AA68: 0 | AB68: 0 | AC68: 0
A69: =VLOOKUP(D69,$A$10:$C$14,3) -> 0 | B69: =A69/12 -> 0 | C69: =INT((D69+11)/12) -> 5 | D69: 50 | E69: =IF(E68<H68,0,E68-G68) -> 0 | F69: =ROUND(E69*$B69,2) -> 0 | G69: =IF(E69<H69,E69,H69-F69) -> 0 | H69: =IF(E69<=0,0,H$14) -> 0 | I69: =IF(I68<L68,0,I68-K68) -> 0 | J69: =ROUND(I69*$B69,2) -> 0 | K69: =IF(I69<L69,I69,L69-J69) -> 0 | L69: =IF(I69<=0,0,L$13) -> 0 | M69: =IF(M68<P68,0,M68-O68) -> 0 | N69: =ROUND(M69*$B69,2) -> 0 | O69: =IF(M69<P69,M69,P69-N69) -> 0 | P69: =IF(M69<=0,0,P$14) -> 0 | R69: =IF(R68<U68,0,R68-T68) -> 0 | S69: =ROUND(R69*$B69,2) -> 0 | T69: =IF(R69<U69,R69,U69-S69) -> 0 | U69: =IF(R69<=0,0,$Y$15) -> 0 | V69: =IF(V68<Y68,0,V68-X68) -> 0 | W69: =ROUND(V69*$B69,2) -> 0 | X69: =IF(V69<Y69,V69,Y69-W69) -> 0 | Y69: =IF(V69<=0,0,PMT(B69,($B$2-D69+1),V69*-1)) -> 0 | Z69: 0 | AA69: 0 | AB69: 0 | AC69: 0
A70: =VLOOKUP(D70,$A$10:$C$14,3) -> 0 | B70: =A70/12 -> 0 | C70: =INT((D70+11)/12) -> 5 | D70: 51 | E70: =IF(E69<H69,0,E69-G69) -> 0 | F70: =ROUND(E70*$B70,2) -> 0 | G70: =IF(E70<H70,E70,H70-F70) -> 0 | H70: =IF(E70<=0,0,H$14) -> 0 | I70: =IF(I69<L69,0,I69-K69) -> 0 | J70: =ROUND(I70*$B70,2) -> 0 | K70: =IF(I70<L70,I70,L70-J70) -> 0 | L70: =IF(I70<=0,0,L$13) -> 0 | M70: =IF(M69<P69,0,M69-O69) -> 0 | N70: =ROUND(M70*$B70,2) -> 0 | O70: =IF(M70<P70,M70,P70-N70) -> 0 | P70: =IF(M70<=0,0,P$14) -> 0 | R70: =IF(R69<U69,0,R69-T69) -> 0 | S70: =ROUND(R70*$B70,2) -> 0 | T70: =IF(R70<U70,R70,U70-S70) -> 0 | U70: =IF(R70<=0,0,$Y$15) -> 0 | V70: =IF(V69<Y69,0,V69-X69) -> 0 | W70: =ROUND(V70*$B70,2) -> 0 | X70: =IF(V70<Y70,V70,Y70-W70) -> 0 | Y70: =IF(V70<=0,0,PMT(B70,($B$2-D70+1),V70*-1)) -> 0 | Z70: 0 | AA70: 0 | AB70: 0 | AC70: 0
A71: =VLOOKUP(D71,$A$10:$C$14,3) -> 0 | B71: =A71/12 -> 0 | C71: =INT((D71+11)/12) -> 5 | D71: 52 | E71: =IF(E70<H70,0,E70-G70) -> 0 | F71: =ROUND(E71*$B71,2) -> 0 | G71: =IF(E71<H71,E71,H71-F71) -> 0 | H71: =IF(E71<=0,0,H$14) -> 0 | I71: =IF(I70<L70,0,I70-K70) -> 0 | J71: =ROUND(I71*$B71,2) -> 0 | K71: =IF(I71<L71,I71,L71-J71) -> 0 | L71: =IF(I71<=0,0,L$13) -> 0 | M71: =IF(M70<P70,0,M70-O70) -> 0 | N71: =ROUND(M71*$B71,2) -> 0 | O71: =IF(M71<P71,M71,P71-N71) -> 0 | P71: =IF(M71<=0,0,P$14) -> 0 | R71: =IF(R70<U70,0,R70-T70) -> 0 | S71: =ROUND(R71*$B71,2) -> 0 | T71: =IF(R71<U71,R71,U71-S71) -> 0 | U71: =IF(R71<=0,0,$Y$15) -> 0 | V71: =IF(V70<Y70,0,V70-X70) -> 0 | W71: =ROUND(V71*$B71,2) -> 0 | X71: =IF(V71<Y71,V71,Y71-W71) -> 0 | Y71: =IF(V71<=0,0,PMT(B71,($B$2-D71+1),V71*-1)) -> 0 | Z71: 0 | AA71: 0 | AB71: 0 | AC71: 0
A72: =VLOOKUP(D72,$A$10:$C$14,3) -> 0 | B72: =A72/12 -> 0 | C72: =INT((D72+11)/12) -> 5 | D72: 53 | E72: =IF(E71<H71,0,E71-G71) -> 0 | F72: =ROUND(E72*$B72,2) -> 0 | G72: =IF(E72<H72,E72,H72-F72) -> 0 | H72: =IF(E72<=0,0,H$14) -> 0 | I72: =IF(I71<L71,0,I71-K71) -> 0 | J72: =ROUND(I72*$B72,2) -> 0 | K72: =IF(I72<L72,I72,L72-J72) -> 0 | L72: =IF(I72<=0,0,L$13) -> 0 | M72: =IF(M71<P71,0,M71-O71) -> 0 | N72: =ROUND(M72*$B72,2) -> 0 | O72: =IF(M72<P72,M72,P72-N72) -> 0 | P72: =IF(M72<=0,0,P$14) -> 0 | R72: =IF(R71<U71,0,R71-T71) -> 0 | S72: =ROUND(R72*$B72,2) -> 0 | T72: =IF(R72<U72,R72,U72-S72) -> 0 | U72: =IF(R72<=0,0,$Y$15) -> 0 | V72: =IF(V71<Y71,0,V71-X71) -> 0 | W72: =ROUND(V72*$B72,2) -> 0 | X72: =IF(V72<Y72,V72,Y72-W72) -> 0 | Y72: =IF(V72<=0,0,PMT(B72,($B$2-D72+1),V72*-1)) -> 0 | Z72: 0 | AA72: 0 | AB72: 0 | AC72: 0
A73: =VLOOKUP(D73,$A$10:$C$14,3) -> 0 | B73: =A73/12 -> 0 | C73: =INT((D73+11)/12) -> 5 | D73: 54 | E73: =IF(E72<H72,0,E72-G72) -> 0 | F73: =ROUND(E73*$B73,2) -> 0 | G73: =IF(E73<H73,E73,H73-F73) -> 0 | H73: =IF(E73<=0,0,H$14) -> 0 | I73: =IF(I72<L72,0,I72-K72) -> 0 | J73: =ROUND(I73*$B73,2) -> 0 | K73: =IF(I73<L73,I73,L73-J73) -> 0 | L73: =IF(I73<=0,0,L$13) -> 0 | M73: =IF(M72<P72,0,M72-O72) -> 0 | N73: =ROUND(M73*$B73,2) -> 0 | O73: =IF(M73<P73,M73,P73-N73) -> 0 | P73: =IF(M73<=0,0,P$14) -> 0 | R73: =IF(R72<U72,0,R72-T72) -> 0 | S73: =ROUND(R73*$B73,2) -> 0 | T73: =IF(R73<U73,R73,U73-S73) -> 0 | U73: =IF(R73<=0,0,$Y$15) -> 0 | V73: =IF(V72<Y72,0,V72-X72) -> 0 | W73: =ROUND(V73*$B73,2) -> 0 | X73: =IF(V73<Y73,V73,Y73-W73) -> 0 | Y73: =IF(V73<=0,0,PMT(B73,($B$2-D73+1),V73*-1)) -> 0 | Z73: 0 | AA73: 0 | AB73: 0 | AC73: 0
A74: =VLOOKUP(D74,$A$10:$C$14,3) -> 0 | B74: =A74/12 -> 0 | C74: =INT((D74+11)/12) -> 5 | D74: 55 | E74: =IF(E73<H73,0,E73-G73) -> 0 | F74: =ROUND(E74*$B74,2) -> 0 | G74: =IF(E74<H74,E74,H74-F74) -> 0 | H74: =IF(E74<=0,0,H$14) -> 0 | I74: =IF(I73<L73,0,I73-K73) -> 0 | J74: =ROUND(I74*$B74,2) -> 0 | K74: =IF(I74<L74,I74,L74-J74) -> 0 | L74: =IF(I74<=0,0,L$13) -> 0 | M74: =IF(M73<P73,0,M73-O73) -> 0 | N74: =ROUND(M74*$B74,2) -> 0 | O74: =IF(M74<P74,M74,P74-N74) -> 0 | P74: =IF(M74<=0,0,P$14) -> 0 | R74: =IF(R73<U73,0,R73-T73) -> 0 | S74: =ROUND(R74*$B74,2) -> 0 | T74: =IF(R74<U74,R74,U74-S74) -> 0 | U74: =IF(R74<=0,0,$Y$15) -> 0 | V74: =IF(V73<Y73,0,V73-X73) -> 0 | W74: =ROUND(V74*$B74,2) -> 0 | X74: =IF(V74<Y74,V74,Y74-W74) -> 0 | Y74: =IF(V74<=0,0,PMT(B74,($B$2-D74+1),V74*-1)) -> 0 | Z74: 0 | AA74: 0 | AB74: 0 | AC74: 0
