Workbook
Name Banca: Product[Banca]
Name BT_with_5_year_lock_in_period: Dropdown_Deviate[BT_with_5_year_lock_in_period]
Name Direct_Sales_1: _xlfn.ANCHORARRAY(Dropdown_DS_Zone!$A$2)
Name Direct_Sales_2: _xlfn.ANCHORARRAY(Dropdown_DS_Zone!$B$2)
Name DS1_1_1: Dropdown_DS_Staff!$A$2:$A$100
Name DS1_1_2: Dropdown_DS_Staff!$B$2:$B$100
Name DS1_1_3: Dropdown_DS_Staff!$C$2:$C$100
Name DS1_1_4: Dropdown_DS_Staff!$D$2:$D$100
Name DS1_2_1: Dropdown_DS_Staff!$E$2:$E$100
Name DS1_2_2: Dropdown_DS_Staff!$F$2:$F$100
Name DS1_2_3: Dropdown_DS_Staff!$G$2:$G$100
Name DS1_2_4: Dropdown_DS_Staff!$H$2:$H$100
Name DS1_3_1: Dropdown_DS_Staff!$I$2:$I$100
Name DS1_3_2: Dropdown_DS_Staff!$J$2:$J$100
Name DS1_3_3: Dropdown_DS_Staff!$K$2:$K$100
Name DS1_3_4: Dropdown_DS_Staff!$L$2:$L$100
Name DS1_4_1: Dropdown_DS_Staff!$M$2:$M$100
Name DS1_4_2: Dropdown_DS_Staff!$N$2:$N$100
Name DS1_4_3: Dropdown_DS_Staff!$O$2:$O$100
Name DS1_4_4: Dropdown_DS_Staff!$P$2:$P$100
Name DS1_5_1: Dropdown_DS_Staff!$Q$2:$Q$100
Name DS1_5_2: Dropdown_DS_Staff!$R$2:$R$100
Name DS1_5_3: Dropdown_DS_Staff!$S$2:$S$100
Name DS1_5_4: Dropdown_DS_Staff!$T$2:$T$100
Name DS1_6_1: Dropdown_DS_Staff!$U$2:$U$100
Name DS1_6_2: Dropdown_DS_Staff!$V$2:$V$100
Name DS1_6_3: Dropdown_DS_Staff!$W$2:$W$100
Name DS1_6_4: Dropdown_DS_Staff!$X$2:$X$100
Name DS2_1_1: Dropdown_DS_Staff!$Y$2:$Y$100
Name DS2_1_2: Dropdown_DS_Staff!$Z$2:$Z$100
Name DS2_1_3: Dropdown_DS_Staff!$AA$2:$AA$100
Name DS2_1_4: Dropdown_DS_Staff!$AB$2:$AB$100
Name DS2_1_5: Dropdown_DS_Staff!$AC$2:$AC$100
Name DS2_2_1: Dropdown_DS_Staff!$AD$2:$AD$100
Name DS2_2_2: Dropdown_DS_Staff!$AE$2:$AE$100
Name DS2_2_3: Dropdown_DS_Staff!$AF$2:$AF$100
Name DS2_2_4: Dropdown_DS_Staff!$AG$2:$AG$100
Name DS2_2_5: Dropdown_DS_Staff!$AH$2:$AH$100
Name DS2_3_1: Dropdown_DS_Staff!$AI$2:$AI$100
Name DS2_3_2: Dropdown_DS_Staff!$AJ$2:$AJ$100
Name DS2_3_3: Dropdown_DS_Staff!$AK$2:$AK$100
Name DS2_3_4: Dropdown_DS_Staff!$AL$2:$AL$100
Name DS2_3_5: Dropdown_DS_Staff!$AM$2:$AM$100
Name DS2_4_1: Dropdown_DS_Staff!$AN$2:$AN$100
Name DS2_4_2: Dropdown_DS_Staff!$AO$2:$AO$100
Name DS2_4_3: Dropdown_DS_Staff!$AP$2:$AP$100
Name DS2_4_4: Dropdown_DS_Staff!$AQ$2:$AQ$100
Name DS2_4_5: Dropdown_DS_Staff!$AR$2:$AR$100
Name DS2_5_1: Dropdown_DS_Staff!$AS$2:$AS$100
Name DS2_5_2: Dropdown_DS_Staff!$AT$2:$AT$100
Name DS2_5_3: Dropdown_DS_Staff!$AU$2:$AU$100
Name DS2_5_4: Dropdown_DS_Staff!$AV$2:$AV$100
Name DS2_5_5: Dropdown_DS_Staff!$AW$2:$AW$100
Name Extra_Cash: HLBT_Year[Extra_Cash]
Name HomeLoan_BT_less_than_2_Percent: HLBT_Year[HomeLoan_BT_less_than_2_Percent]
Name HomeLoan_BT_more_than_2_Percent: HLBT_Year[HomeLoan_BT_more_than_2_Percent]
Name HomeLoan_Non_BT: HLBT_Year[HomeLoan_Non_BT]
Name Mortgage_Power_Term: HLBT_Year[Mortgage_Power_Term]
Name MRTA_3_Percent: HLBT_Year[MRTA_3_Percent]
Name MRTA_6_Percent: HLBT_Year[MRTA_6_Percent]

Sheet Detail_Simulation
A2: Channel | B2: Direct_Sales_1
A3: Team | B3: DS1_3_2
F4: =SUM(F$6:F$201) -> 24400000 | K4: =SUM(K$6:K$201) -> 11900000 | L4: =SUM(L$6:L$201) -> 0
A5: No. | B5: Sales ID | C5: Products | D5: Sub Products | E5: Year (Home Loan BT Only) | F5: Amount | G5: Secured_Type | H5: Deviate Range (Secured Loan Only) | I5: Big Loan Size (Secured Loan Only) | J5: Deviate (Secured Loan Only) | K5: Drawdown Calculate | L5: Commission
A6: 1 | B6: 6560479 | C6: Unsecured | E6: 5 | F6: 10000000 | G6: {=_xlfn.IFS( AND($C6="Secured", OR($D6="HomeLoan_BT_more_than_2_Percent", $D6="HomeLoan_BT_less_than_2_Percent"), $E6=""), "", AND($C6="Secured",$E6=""),"others", AND($C6="Secured",$E6=3),"others", AND($C6="Secured",$E6=5),"BT_with_5_year_lock_in_period", TRUE, "")} -> #NAME? | H6: > 0.40% to 0.50% | I6: {=_xlfn.IFS( AND($C6="Secured", OR($D6="HomeLoan_BT_more_than_2_Percent", $D6="HomeLoan_BT_less_than_2_Percent"), OR($E6="", $E6=0)), "Please input Year !!!", AND($C6="Secured", OR($F6="", $F6=0)), "Please input Amount !!!", AND($C6="Secured", $F6<5000000), 1, AND($C6="Secured", $F6>=5000000), 1.1, TRUE, "")} -> #NAME? | J6: {=IFERROR(_xlfn.IFS( $G6="BT_with_5_year_lock_in_period", _xlfn.XLOOKUP($H6, Deviate_Table[Pricing discount], Deviate_Table[BT_with_5_year_lock_in_period]), $G6="others", _xlfn.XLOOKUP($H6, Deviate_Table[Pricing discount], Deviate_Table[others]), TRUE, ""), "Please input Deviate Range !!!")} -> Please input Deviate Range !!! | K6: =IF($C6="Secured",IFERROR($F6*$I6*$J6, ""), $F6) -> 10000000 | L6: {=IFERROR( _xlfn.IFS( D6="HomeLoan_BT_less_than_2_Percent", VLOOKUP(SUMIFS($K:$K, $D:$D, "HomeLoan_BT_more_than_2_Percent", $B:$B, B6)+SUMIFS($K:$K, $D:$D, "HomeLoan_BT_less_than_2_Percent", $B:$B, B6)+SUMIFS($K:$K, $D:$D, "HomeLoan_Non_BT", $B:$B, B6)+SUMIFS($K:$K, $D:$D, "Mortgage_Power_Term", $B:$B, B6), Secured_Commission!$A:$F, 2, 1)*(K6/10^6), D6="HomeLoan_BT_more_than_2_Percent", VLOOKUP(SUMIFS($K:$K, $D:$D, "HomeLoan_BT_more_than_2_Percent", $B:$B, B6)+SUMIFS($K:$K, $D:$D, "HomeLoan_BT_less_than_2_Percent", $B:$B, B6)+SUMIFS($K:$K, $D:$D, "HomeLoan_Non_BT", $B:$B, B6)+SUMIFS($K:$K, $D:$D, "Mortgage_Power_Term", $B:$B, B6), Secured_Commission!$A:$F, 3, 1)*(K6/10^6), D6="HomeLoan_Non_BT", VLOOKUP(SUMIFS($K:$K, $D:$D, "HomeLoan_BT_more_than_2_Percent", $B:$B, B6)+SUMIFS($K:$K, $D:$D, "HomeLoan_BT_less_than_2_Percent", $B:$B, B6)+SUMIFS($K:$K, $D:$D, "HomeLoan_Non_BT", $B:$B, B6)+SUMIFS($K:$K, $D:$D, "Mortgage_Power_Term", $B:$B, B6), Secured_Commission!$A:$F, 4, 1)*(K6/10^6), D6="Mortgage_Power_Term", VLOOKUP(SUMIFS($K:$K, $D:$D, "HomeLoan_BT_more_than_2_Percent", $B:$B, B6)+SUMIFS($K:$K, $D:$D, "HomeLoan_BT_less_than_2_Percent", $B:$B, B6)+SUMIFS($K:$K, $D:$D, "HomeLoan_Non_BT", $B:$B, B6)+SUMIFS($K:$K, $D:$D, "Mortgage_Power_Term", $B:$B, B6), Secured_Commission!$A:$F, 5, 1)*(K6/10^6), D6="Personal_Cash", VLOOKUP(SUMIFS($K:$K, $D:$D, "Personal_Cash", $B:$B, B6), Unsecured_Commission!$A:$B, 2, 1)*K6, OR(D6="MRTA_3_Percent", D6="SOMPO"), K6*0.03, D6="MRTA_6_Percent", K6*0.06), 0)} -> 0
A7: 2 | B7: 6860211 | C7: Secured | F7: 5000000 | G7: {=_xlfn.IFS( AND($C7="Secured", OR($D7="HomeLoan_BT_more_than_2_Percent", $D7="HomeLoan_BT_less_than_2_Percent"), $E7=""), "", AND($C7="Secured",$E7=""),"others", AND($C7="Secured",$E7=3),"others", AND($C7="Secured",$E7=5),"BT_with_5_year_lock_in_period", TRUE, "")} -> #NAME? | H7: <= 0.25% | I7: {=_xlfn.IFS( AND($C7="Secured", OR($D7="HomeLoan_BT_more_than_2_Percent", $D7="HomeLoan_BT_less_than_2_Percent"), OR($E7="", $E7=0)), "Please input Year !!!", AND($C7="Secured", OR($F7="", $F7=0)), "Please input Amount !!!", AND($C7="Secured", $F7<5000000), 1, AND($C7="Secured", $F7>=5000000), 1.1, TRUE, "")} -> #NAME? | J7: {=IFERROR(_xlfn.IFS( $G7="BT_with_5_year_lock_in_period", _xlfn.XLOOKUP($H7, Deviate_Table[Pricing discount], Deviate_Table[BT_with_5_year_lock_in_period]), $G7="others", _xlfn.XLOOKUP($H7, Deviate_Table[Pricing discount], Deviate_Table[others]), TRUE, ""), "Please input Deviate Range !!!")} -> Please input Deviate Range !!! | K7: =IF($C7="Secured",IFERROR($F7*$I7*$J7, ""), $F7) | L7: {=IFERROR( _xlfn.IFS( D7="HomeLoan_BT_less_than_2_Percent", VLOOKUP(SUMIFS($K:$K, $D:$D, "HomeLoan_BT_more_than_2_Percent", $B:$B, B7)+SUMIFS($K:$K, $D:$D, "HomeLoan_BT_less_than_2_Percent", $B:$B, B7)+SUMIFS($K:$K, $D:$D, "HomeLoan_Non_BT", $B:$B, B7)+SUMIFS($K:$K, $D:$D, "Mortgage_Power_Term", $B:$B, B7), Secured_Commission!$A:$F, 2, 1)*(K7/10^6), D7="HomeLoan_BT_more_than_2_Percent", VLOOKUP(SUMIFS($K:$K, $D:$D, "HomeLoan_BT_more_than_2_Percent", $B:$B, B7)+SUMIFS($K:$K, $D:$D, "HomeLoan_BT_less_than_2_Percent", $B:$B, B7)+SUMIFS($K:$K, $D:$D, "HomeLoan_Non_BT", $B:$B, B7)+SUMIFS($K:$K, $D:$D, "Mortgage_Power_Term", $B:$B, B7), Secured_Commission!$A:$F, 3, 1)*(K7/10^6), D7="HomeLoan_Non_BT", VLOOKUP(SUMIFS($K:$K, $D:$D, "HomeLoan_BT_more_than_2_Percent", $B:$B, B7)+SUMIFS($K:$K, $D:$D, "HomeLoan_BT_less_than_2_Percent", $B:$B, B7)+SUMIFS($K:$K, $D:$D, "HomeLoan_Non_BT", $B:$B, B7)+SUMIFS($K:$K, $D:$D, "Mortgage_Power_Term", $B:$B, B7), Secured_Commission!$A:$F, 4, 1)*(K7/10^6), D7="Mortgage_Power_Term", VLOOKUP(SUMIFS($K:$K, $D:$D, "HomeLoan_BT_more_than_2_Percent", $B:$B, B7)+SUMIFS($K:$K, $D:$D, "HomeLoan_BT_less_than_2_Percent", $B:$B, B7)+SUMIFS($K:$K, $D:$D, "HomeLoan_Non_BT", $B:$B, B7)+SUMIFS($K:$K, $D:$D, "Mortgage_Power_Term", $B:$B, B7), Secured_Commission!$A:$F, 5, 1)*(K7/10^6), D7="Personal_Cash", VLOOKUP(SUMIFS($K:$K, $D:$D, "Personal_Cash", $B:$B, B7), Unsecured_Commission!$A:$B, 2, 1)*K7, OR(D7="MRTA_3_Percent", D7="SOMPO"), K7*0.03, D7="MRTA_6_Percent", K7*0.06), 0)} -> 0
A8: 3 | B8: 6860211 | C8: Secured | D8: HomeLoan_BT_less_than_2_Percent | F8: 2000000 | G8: {=_xlfn.IFS( AND($C8="Secured", OR($D8="HomeLoan_BT_more_than_2_Percent", $D8="HomeLoan_BT_less_than_2_Percent"), $E8=""), "", AND($C8="Secured",$E8=""),"others", AND($C8="Secured",$E8=3),"others", AND($C8="Secured",$E8=5),"BT_with_5_year_lock_in_period", TRUE, "")} -> #NAME? | H8: No discount | I8: {=_xlfn.IFS( AND($C8="Secured", OR($D8="HomeLoan_BT_more_than_2_Percent", $D8="HomeLoan_BT_less_than_2_Percent"), OR($E8="", $E8=0)), "Please input Year !!!", AND($C8="Secured", OR($F8="", $F8=0)), "Please input Amount !!!", AND($C8="Secured", $F8<5000000), 1, AND($C8="Secured", $F8>=5000000), 1.1, TRUE, "")} -> #NAME? | J8: {=IFERROR(_xlfn.IFS( $G8="BT_with_5_year_lock_in_period", _xlfn.XLOOKUP($H8, Deviate_Table[Pricing discount], Deviate_Table[BT_with_5_year_lock_in_period]), $G8="others", _xlfn.XLOOKUP($H8, Deviate_Table[Pricing discount], Deviate_Table[others]), TRUE, ""), "Please input Deviate Range !!!")} -> Please input Deviate Range !!! | K8: =IF($C8="Secured",IFERROR($F8*$I8*$J8, ""), $F8) | L8: {=IFERROR( _xlfn.IFS( D8="HomeLoan_BT_less_than_2_Percent", VLOOKUP(SUMIFS($K:$K, $D:$D, "HomeLoan_BT_more_than_2_Percent", $B:$B, B8)+SUMIFS($K:$K, $D:$D, "HomeLoan_BT_less_than_2_Percent", $B:$B, B8)+SUMIFS($K:$K, $D:$D, "HomeLoan_Non_BT", $B:$B, B8)+SUMIFS($K:$K, $D:$D, "Mortgage_Power_Term", $B:$B, B8), Secured_Commission!$A:$F, 2, 1)*(K8/10^6), D8="HomeLoan_BT_more_than_2_Percent", VLOOKUP(SUMIFS($K:$K, $D:$D, "HomeLoan_BT_more_than_2_Percent", $B:$B, B8)+SUMIFS($K:$K, $D:$D, "HomeLoan_BT_less_than_2_Percent", $B:$B, B8)+SUMIFS($K:$K, $D:$D, "HomeLoan_Non_BT", $B:$B, B8)+SUMIFS($K:$K, $D:$D, "Mortgage_Power_Term", $B:$B, B8), Secured_Commission!$A:$F, 3, 1)*(K8/10^6), D8="HomeLoan_Non_BT", VLOOKUP(SUMIFS($K:$K, $D:$D, "HomeLoan_BT_more_than_2_Percent", $B:$B, B8)+SUMIFS($K:$K, $D:$D, "HomeLoan_BT_less_than_2_Percent", $B:$B, B8)+SUMIFS($K:$K, $D:$D, "HomeLoan_Non_BT", $B:$B, B8)+SUMIFS($K:$K, $D:$D, "Mortgage_Power_Term", $B:$B, B8), Secured_Commission!$A:$F, 4, 1)*(K8/10^6), D8="Mortgage_Power_Term", VLOOKUP(SUMIFS($K:$K, $D:$D, "HomeLoan_BT_more_than_2_Percent", $B:$B, B8)+SUMIFS($K:$K, $D:$D, "HomeLoan_BT_less_than_2_Percent", $B:$B, B8)+SUMIFS($K:$K, $D:$D, "HomeLoan_Non_BT", $B:$B, B8)+SUMIFS($K:$K, $D:$D, "Mortgage_Power_Term", $B:$B, B8), Secured_Commission!$A:$F, 5, 1)*(K8/10^6), D8="Personal_Cash", VLOOKUP(SUMIFS($K:$K, $D:$D, "Personal_Cash", $B:$B, B8), Unsecured_Commission!$A:$B, 2, 1)*K8, OR(D8="MRTA_3_Percent", D8="SOMPO"), K8*0.03, D8="MRTA_6_Percent", K8*0.06), 0)} -> 0
A9: 4 | B9: 6860211 | C9: Unsecured | D9: Personal_Cash | F9: 1000000 | G9: {=_xlfn.IFS( AND($C9="Secured", OR($D9="HomeLoan_BT_more_than_2_Percent", $D9="HomeLoan_BT_less_than_2_Percent"), $E9=""), "", AND($C9="Secured",$E9=""),"others", AND($C9="Secured",$E9=3),"others", AND($C9="Secured",$E9=5),"BT_with_5_year_lock_in_period", TRUE, "")} -> #NAME? | I9: {=_xlfn.IFS( AND($C9="Secured", OR($D9="HomeLoan_BT_more_than_2_Percent", $D9="HomeLoan_BT_less_than_2_Percent"), OR($E9="", $E9=0)), "Please input Year !!!", AND($C9="Secured", OR($F9="", $F9=0)), "Please input Amount !!!", AND($C9="Secured", $F9<5000000), 1, AND($C9="Secured", $F9>=5000000), 1.1, TRUE, "")} -> #NAME? | J9: {=IFERROR(_xlfn.IFS( $G9="BT_with_5_year_lock_in_period", _xlfn.XLOOKUP($H9, Deviate_Table[Pricing discount], Deviate_Table[BT_with_5_year_lock_in_period]), $G9="others", _xlfn.XLOOKUP($H9, Deviate_Table[Pricing discount], Deviate_Table[others]), TRUE, ""), "Please input Deviate Range !!!")} -> Please input Deviate Range !!! | K9: =IF($C9="Secured",IFERROR($F9*$I9*$J9, ""), $F9) -> 1000000 | L9: {=IFERROR( _xlfn.IFS( D9="HomeLoan_BT_less_than_2_Percent", VLOOKUP(SUMIFS($K:$K, $D:$D, "HomeLoan_BT_more_than_2_Percent", $B:$B, B9)+SUMIFS($K:$K, $D:$D, "HomeLoan_BT_less_than_2_Percent", $B:$B, B9)+SUMIFS($K:$K, $D:$D, "HomeLoan_Non_BT", $B:$B, B9)+SUMIFS($K:$K, $D:$D, "Mortgage_Power_Term", $B:$B, B9), Secured_Commission!$A:$F, 2, 1)*(K9/10^6), D9="HomeLoan_BT_more_than_2_Percent", VLOOKUP(SUMIFS($K:$K, $D:$D, "HomeLoan_BT_more_than_2_Percent", $B:$B, B9)+SUMIFS($K:$K, $D:$D, "HomeLoan_BT_less_than_2_Percent", $B:$B, B9)+SUMIFS($K:$K, $D:$D, "HomeLoan_Non_BT", $B:$B, B9)+SUMIFS($K:$K, $D:$D, "Mortgage_Power_Term", $B:$B, B9), Secured_Commission!$A:$F, 3, 1)*(K9/10^6), D9="HomeLoan_Non_BT", VLOOKUP(SUMIFS($K:$K, $D:$D, "HomeLoan_BT_more_than_2_Percent", $B:$B, B9)+SUMIFS($K:$K, $D:$D, "HomeLoan_BT_less_than_2_Percent", $B:$B, B9)+SUMIFS($K:$K, $D:$D, "HomeLoan_Non_BT", $B:$B, B9)+SUMIFS($K:$K, $D:$D, "Mortgage_Power_Term", $B:$B, B9), Secured_Commission!$A:$F, 4, 1)*(K9/10^6), D9="Mortgage_Power_Term", VLOOKUP(SUMIFS($K:$K, $D:$D, "HomeLoan_BT_more_than_2_Percent", $B:$B, B9)+SUMIFS($K:$K, $D:$D, "HomeLoan_BT_less_than_2_Percent", $B:$B, B9)+SUMIFS($K:$K, $D:$D, "HomeLoan_Non_BT", $B:$B, B9)+SUMIFS($K:$K, $D:$D, "Mortgage_Power_Term", $B:$B, B9), Secured_Commission!$A:$F, 5, 1)*(K9/10^6), D9="Personal_Cash", VLOOKUP(SUMIFS($K:$K, $D:$D, "Personal_Cash", $B:$B, B9), Unsecured_Commission!$A:$B, 2, 1)*K9, OR(D9="MRTA_3_Percent", D9="SOMPO"), K9*0.03, D9="MRTA_6_Percent", K9*0.06), 0)} -> 0
A10: 5 | B10: 6860211 | C10: Banca | D10: MRTA_6_Percent | F10: 200000 | G10: {=_xlfn.IFS( AND($C10="Secured", OR($D10="HomeLoan_BT_more_than_2_Percent", $D10="HomeLoan_BT_less_than_2_Percent"), $E10=""), "", AND($C10="Secured",$E10=""),"others", AND($C10="Secured",$E10=3),"others", AND($C10="Secured",$E10=5),"BT_with_5_year_lock_in_period", TRUE, "")} -> #NAME? | I10: {=_xlfn.IFS( AND($C10="Secured", OR($D10="HomeLoan_BT_more_than_2_Percent", $D10="HomeLoan_BT_less_than_2_Percent"), OR($E10="", $E10=0)), "Please input Year !!!", AND($C10="Secured", OR($F10="", $F10=0)), "Please input Amount !!!", AND($C10="Secured", $F10<5000000), 1, AND($C10="Secured", $F10>=5000000), 1.1, TRUE, "")} -> #NAME? | J10: {=IFERROR(_xlfn.IFS( $G10="BT_with_5_year_lock_in_period", _xlfn.XLOOKUP($H10, Deviate_Table[Pricing discount], Deviate_Table[BT_with_5_year_lock_in_period]), $G10="others", _xlfn.XLOOKUP($H10, Deviate_Table[Pricing discount], Deviate_Table[others]), TRUE, ""), "Please input Deviate Range !!!")} -> Please input Deviate Range !!! | K10: =IF($C10="Secured",IFERROR($F10*$I10*$J10, ""), $F10) -> 200000 | L10: {=IFERROR( _xlfn.IFS( D10="HomeLoan_BT_less_than_2_Percent", VLOOKUP(SUMIFS($K:$K, $D:$D, "HomeLoan_BT_more_than_2_Percent", $B:$B, B10)+SUMIFS($K:$K, $D:$D, "HomeLoan_BT_less_than_2_Percent", $B:$B, B10)+SUMIFS($K:$K, $D:$D, "HomeLoan_Non_BT", $B:$B, B10)+SUMIFS($K:$K, $D:$D, "Mortgage_Power_Term", $B:$B, B10), Secured_Commission!$A:$F, 2, 1)*(K10/10^6), D10="HomeLoan_BT_more_than_2_Percent", VLOOKUP(SUMIFS($K:$K, $D:$D, "HomeLoan_BT_more_than_2_Percent", $B:$B, B10)+SUMIFS($K:$K, $D:$D, "HomeLoan_BT_less_than_2_Percent", $B:$B, B10)+SUMIFS($K:$K, $D:$D, "HomeLoan_Non_BT", $B:$B, B10)+SUMIFS($K:$K, $D:$D, "Mortgage_Power_Term", $B:$B, B10), Secured_Commission!$A:$F, 3, 1)*(K10/10^6), D10="HomeLoan_Non_BT", VLOOKUP(SUMIFS($K:$K, $D:$D, "HomeLoan_BT_more_than_2_Percent", $B:$B, B10)+SUMIFS($K:$K, $D:$D, "HomeLoan_BT_less_than_2_Percent", $B:$B, B10)+SUMIFS($K:$K, $D:$D, "HomeLoan_Non_BT", $B:$B, B10)+SUMIFS($K:$K, $D:$D, "Mortgage_Power_Term", $B:$B, B10), Secured_Commission!$A:$F, 4, 1)*(K10/10^6), D10="Mortgage_Power_Term", VLOOKUP(SUMIFS($K:$K, $D:$D, "HomeLoan_BT_more_than_2_Percent", $B:$B, B10)+SUMIFS($K:$K, $D:$D, "HomeLoan_BT_less_than_2_Percent", $B:$B, B10)+SUMIFS($K:$K, $D:$D, "HomeLoan_Non_BT", $B:$B, B10)+SUMIFS($K:$K, $D:$D, "Mortgage_Power_Term", $B:$B, B10), Secured_Commission!$A:$F, 5, 1)*(K10/10^6), D10="Personal_Cash", VLOOKUP(SUMIFS($K:$K, $D:$D, "Personal_Cash", $B:$B, B10), Unsecured_Commission!$A:$B, 2, 1)*K10, OR(D10="MRTA_3_Percent", D10="SOMPO"), K10*0.03, D10="MRTA_6_Percent", K10*0.06), 0)} -> 0
A11: 6 | B11: 6860211 | C11: Unsecured | D11: Personal_Cash | F11: 400000 | G11: {=_xlfn.IFS( AND($C11="Secured", OR($D11="HomeLoan_BT_more_than_2_Percent", $D11="HomeLoan_BT_less_than_2_Percent"), $E11=""), "", AND($C11="Secured",$E11=""),"others", AND($C11="Secured",$E11=3),"others", AND($C11="Secured",$E11=5),"BT_with_5_year_lock_in_period", TRUE, "")} -> #NAME? | I11: {=_xlfn.IFS( AND($C11="Secured", OR($D11="HomeLoan_BT_more_than_2_Percent", $D11="HomeLoan_BT_less_than_2_Percent"), OR($E11="", $E11=0)), "Please input Year !!!", AND($C11="Secured", OR($F11="", $F11=0)), "Please input Amount !!!", AND($C11="Secured", $F11<5000000), 1, AND($C11="Secured", $F11>=5000000), 1.1, TRUE, "")} -> #NAME? | J11: {=IFERROR(_xlfn.IFS( $G11="BT_with_5_year_lock_in_period", _xlfn.XLOOKUP($H11, Deviate_Table[Pricing discount], Deviate_Table[BT_with_5_year_lock_in_period]), $G11="others", _xlfn.XLOOKUP($H11, Deviate_Table[Pricing discount], Deviate_Table[others]), TRUE, ""), "Please input Deviate Range !!!")} -> Please input Deviate Range !!! | K11: =IF($C11="Secured",IFERROR($F11*$I11*$J11, ""), $F11) -> 400000 | L11: {=IFERROR( _xlfn.IFS( D11="HomeLoan_BT_less_than_2_Percent", VLOOKUP(SUMIFS($K:$K, $D:$D, "HomeLoan_BT_more_than_2_Percent", $B:$B, B11)+SUMIFS($K:$K, $D:$D, "HomeLoan_BT_less_than_2_Percent", $B:$B, B11)+SUMIFS($K:$K, $D:$D, "HomeLoan_Non_BT", $B:$B, B11)+SUMIFS($K:$K, $D:$D, "Mortgage_Power_Term", $B:$B, B11), Secured_Commission!$A:$F, 2, 1)*(K11/10^6), D11="HomeLoan_BT_more_than_2_Percent", VLOOKUP(SUMIFS($K:$K, $D:$D, "HomeLoan_BT_more_than_2_Percent", $B:$B, B11)+SUMIFS($K:$K, $D:$D, "HomeLoan_BT_less_than_2_Percent", $B:$B, B11)+SUMIFS($K:$K, $D:$D, "HomeLoan_Non_BT", $B:$B, B11)+SUMIFS($K:$K, $D:$D, "Mortgage_Power_Term", $B:$B, B11), Secured_Commission!$A:$F, 3, 1)*(K11/10^6), D11="HomeLoan_Non_BT", VLOOKUP(SUMIFS($K:$K, $D:$D, "HomeLoan_BT_more_than_2_Percent", $B:$B, B11)+SUMIFS($K:$K, $D:$D, "HomeLoan_BT_less_than_2_Percent", $B:$B, B11)+SUMIFS($K:$K, $D:$D, "HomeLoan_Non_BT", $B:$B, B11)+SUMIFS($K:$K, $D:$D, "Mortgage_Power_Term", $B:$B, B11), Secured_Commission!$A:$F, 4, 1)*(K11/10^6), D11="Mortgage_Power_Term", VLOOKUP(SUMIFS($K:$K, $D:$D, "HomeLoan_BT_more_than_2_Percent", $B:$B, B11)+SUMIFS($K:$K, $D:$D, "HomeLoan_BT_less_than_2_Percent", $B:$B, B11)+SUMIFS($K:$K, $D:$D, "HomeLoan_Non_BT", $B:$B, B11)+SUMIFS($K:$K, $D:$D, "Mortgage_Power_Term", $B:$B, B11), Secured_Commission!$A:$F, 5, 1)*(K11/10^6), D11="Personal_Cash", VLOOKUP(SUMIFS($K:$K, $D:$D, "Personal_Cash", $B:$B, B11), Unsecured_Commission!$A:$B, 2, 1)*K11, OR(D11="MRTA_3_Percent", D11="SOMPO"), K11*0.03, D11="MRTA_6_Percent", K11*0.06), 0)} -> 0
A12: 7 | B12: 6860211 | C12: Secured | D12: HomeLoan_BT_less_than_2_Percent | E12: 5 | F12: 5500000 | G12: {=_xlfn.IFS( AND($C12="Secured", OR($D12="HomeLoan_BT_more_than_2_Percent", $D12="HomeLoan_BT_less_than_2_Percent"), $E12=""), "", AND($C12="Secured",$E12=""),"others", AND($C12="Secured",$E12=3),"others", AND($C12="Secured",$E12=5),"BT_with_5_year_lock_in_period", TRUE, "")} -> #NAME? | H12: <= 0.25% | I12: {=_xlfn.IFS( AND($C12="Secured", OR($D12="HomeLoan_BT_more_than_2_Percent", $D12="HomeLoan_BT_less_than_2_Percent"), OR($E12="", $E12=0)), "Please input Year !!!", AND($C12="Secured", OR($F12="", $F12=0)), "Please input Amount !!!", AND($C12="Secured", $F12<5000000), 1, AND($C12="Secured", $F12>=5000000), 1.1, TRUE, "")} -> #NAME? | J12: {=IFERROR(_xlfn.IFS( $G12="BT_with_5_year_lock_in_period", _xlfn.XLOOKUP($H12, Deviate_Table[Pricing discount], Deviate_Table[BT_with_5_year_lock_in_period]), $G12="others", _xlfn.XLOOKUP($H12, Deviate_Table[Pricing discount], Deviate_Table[others]), TRUE, ""), "Please input Deviate Range !!!")} -> Please input Deviate Range !!! | K12: =IF($C12="Secured",IFERROR($F12*$I12*$J12, ""), $F12) | L12: {=IFERROR( _xlfn.IFS( D12="HomeLoan_BT_less_than_2_Percent", VLOOKUP(SUMIFS($K:$K, $D:$D, "HomeLoan_BT_more_than_2_Percent", $B:$B, B12)+SUMIFS($K:$K, $D:$D, "HomeLoan_BT_less_than_2_Percent", $B:$B, B12)+SUMIFS($K:$K, $D:$D, "HomeLoan_Non_BT", $B:$B, B12)+SUMIFS($K:$K, $D:$D, "Mortgage_Power_Term", $B:$B, B12), Secured_Commission!$A:$F, 2, 1)*(K12/10^6), D12="HomeLoan_BT_more_than_2_Percent", VLOOKUP(SUMIFS($K:$K, $D:$D, "HomeLoan_BT_more_than_2_Percent", $B:$B, B12)+SUMIFS($K:$K, $D:$D, "HomeLoan_BT_less_than_2_Percent", $B:$B, B12)+SUMIFS($K:$K, $D:$D, "HomeLoan_Non_BT", $B:$B, B12)+SUMIFS($K:$K, $D:$D, "Mortgage_Power_Term", $B:$B, B12), Secured_Commission!$A:$F, 3, 1)*(K12/10^6), D12="HomeLoan_Non_BT", VLOOKUP(SUMIFS($K:$K, $D:$D, "HomeLoan_BT_more_than_2_Percent", $B:$B, B12)+SUMIFS($K:$K, $D:$D, "HomeLoan_BT_less_than_2_Percent", $B:$B, B12)+SUMIFS($K:$K, $D:$D, "HomeLoan_Non_BT", $B:$B, B12)+SUMIFS($K:$K, $D:$D, "Mortgage_Power_Term", $B:$B, B12), Secured_Commission!$A:$F, 4, 1)*(K12/10^6), D12="Mortgage_Power_Term", VLOOKUP(SUMIFS($K:$K, $D:$D, "HomeLoan_BT_more_than_2_Percent", $B:$B, B12)+SUMIFS($K:$K, $D:$D, "HomeLoan_BT_less_than_2_Percent", $B:$B, B12)+SUMIFS($K:$K, $D:$D, "HomeLoan_Non_BT", $B:$B, B12)+SUMIFS($K:$K, $D:$D, "Mortgage_Power_Term", $B:$B, B12), Secured_Commission!$A:$F, 5, 1)*(K12/10^6), D12="Personal_Cash", VLOOKUP(SUMIFS($K:$K, $D:$D, "Personal_Cash", $B:$B, B12), Unsecured_Commission!$A:$B, 2, 1)*K12, OR(D12="MRTA_3_Percent", D12="SOMPO"), K12*0.03, D12="MRTA_6_Percent", K12*0.06), 0)} -> 0
A13: 8 | B13: 6860015 | C13: Banca | D13: SOMPO | F13: 300000 | G13: {=_xlfn.IFS( AND($C13="Secured", OR($D13="HomeLoan_BT_more_than_2_Percent", $D13="HomeLoan_BT_less_than_2_Percent"), $E13=""), "", AND($C13="Secured",$E13=""),"others", AND($C13="Secured",$E13=3),"others", AND($C13="Secured",$E13=5),"BT_with_5_year_lock_in_period", TRUE, "")} -> #NAME? | I13: {=_xlfn.IFS( AND($C13="Secured", OR($D13="HomeLoan_BT_more_than_2_Percent", $D13="HomeLoan_BT_less_than_2_Percent"), OR($E13="", $E13=0)), "Please input Year !!!", AND($C13="Secured", OR($F13="", $F13=0)), "Please input Amount !!!", AND($C13="Secured", $F13<5000000), 1, AND($C13="Secured", $F13>=5000000), 1.1, TRUE, "")} -> #NAME? | J13: {=IFERROR(_xlfn.IFS( $G13="BT_with_5_year_lock_in_period", _xlfn.XLOOKUP($H13, Deviate_Table[Pricing discount], Deviate_Table[BT_with_5_year_lock_in_period]), $G13="others", _xlfn.XLOOKUP($H13, Deviate_Table[Pricing discount], Deviate_Table[others]), TRUE, ""), "Please input Deviate Range !!!")} -> Please input Deviate Range !!! | K13: =IF($C13="Secured",IFERROR($F13*$I13*$J13, ""), $F13) -> 300000 | L13: {=IFERROR( _xlfn.IFS( D13="HomeLoan_BT_less_than_2_Percent", VLOOKUP(SUMIFS($K:$K, $D:$D, "HomeLoan_BT_more_than_2_Percent", $B:$B, B13)+SUMIFS($K:$K, $D:$D, "HomeLoan_BT_less_than_2_Percent", $B:$B, B13)+SUMIFS($K:$K, $D:$D, "HomeLoan_Non_BT", $B:$B, B13)+SUMIFS($K:$K, $D:$D, "Mortgage_Power_Term", $B:$B, B13), Secured_Commission!$A:$F, 2, 1)*(K13/10^6), D13="HomeLoan_BT_more_than_2_Percent", VLOOKUP(SUMIFS($K:$K, $D:$D, "HomeLoan_BT_more_than_2_Percent", $B:$B, B13)+SUMIFS($K:$K, $D:$D, "HomeLoan_BT_less_than_2_Percent", $B:$B, B13)+SUMIFS($K:$K, $D:$D, "HomeLoan_Non_BT", $B:$B, B13)+SUMIFS($K:$K, $D:$D, "Mortgage_Power_Term", $B:$B, B13), Secured_Commission!$A:$F, 3, 1)*(K13/10^6), D13="HomeLoan_Non_BT", VLOOKUP(SUMIFS($K:$K, $D:$D, "HomeLoan_BT_more_than_2_Percent", $B:$B, B13)+SUMIFS($K:$K, $D:$D, "HomeLoan_BT_less_than_2_Percent", $B:$B, B13)+SUMIFS($K:$K, $D:$D, "HomeLoan_Non_BT", $B:$B, B13)+SUMIFS($K:$K, $D:$D, "Mortgage_Power_Term", $B:$B, B13), Secured_Commission!$A:$F, 4, 1)*(K13/10^6), D13="Mortgage_Power_Term", VLOOKUP(SUMIFS($K:$K, $D:$D, "HomeLoan_BT_more_than_2_Percent", $B:$B, B13)+SUMIFS($K:$K, $D:$D, "HomeLoan_BT_less_than_2_Percent", $B:$B, B13)+SUMIFS($K:$K, $D:$D, "HomeLoan_Non_BT", $B:$B, B13)+SUMIFS($K:$K, $D:$D, "Mortgage_Power_Term", $B:$B, B13), Secured_Commission!$A:$F, 5, 1)*(K13/10^6), D13="Personal_Cash", VLOOKUP(SUMIFS($K:$K, $D:$D, "Personal_Cash", $B:$B, B13), Unsecured_Commission!$A:$B, 2, 1)*K13, OR(D13="MRTA_3_Percent", D13="SOMPO"), K13*0.03, D13="MRTA_6_Percent", K13*0.06), 0)} -> 0
A14: 9 | G14: {=_xlfn.IFS( AND($C14="Secured", OR($D14="HomeLoan_BT_more_than_2_Percent", $D14="HomeLoan_BT_less_than_2_Percent"), $E14=""), "", AND($C14="Secured",$E14=""),"others", AND($C14="Secured",$E14=3),"others", AND($C14="Secured",$E14=5),"BT_with_5_year_lock_in_period", TRUE, "")} | I14: {=_xlfn.IFS( AND($C14="Secured", OR($D14="HomeLoan_BT_more_than_2_Percent", $D14="HomeLoan_BT_less_than_2_Percent"), OR($E14="", $E14=0)), "Please input Year !!!", AND($C14="Secured", OR($F14="", $F14=0)), "Please input Amount !!!", AND($C14="Secured", $F14<5000000), 1, AND($C14="Secured", $F14>=5000000), 1.1, TRUE, "")} | J14: {=IFERROR(_xlfn.IFS( $G14="BT_with_5_year_lock_in_period", _xlfn.XLOOKUP($H14, Deviate_Table[Pricing discount], Deviate_Table[BT_with_5_year_lock_in_period]), $G14="others", _xlfn.XLOOKUP($H14, Deviate_Table[Pricing discount], Deviate_Table[others]), TRUE, ""), "Please input Deviate Range !!!")} | K14: =IF($C14="Secured",IFERROR($F14*$I14*$J14, ""), $F14) -> 0 | L14: {=IFERROR( _xlfn.IFS( D14="HomeLoan_BT_less_than_2_Percent", VLOOKUP(SUMIFS($K:$K, $D:$D, "HomeLoan_BT_more_than_2_Percent", $B:$B, B14)+SUMIFS($K:$K, $D:$D, "HomeLoan_BT_less_than_2_Percent", $B:$B, B14)+SUMIFS($K:$K, $D:$D, "HomeLoan_Non_BT", $B:$B, B14)+SUMIFS($K:$K, $D:$D, "Mortgage_Power_Term", $B:$B, B14), Secured_Commission!$A:$F, 2, 1)*(K14/10^6), D14="HomeLoan_BT_more_than_2_Percent", VLOOKUP(SUMIFS($K:$K, $D:$D, "HomeLoan_BT_more_than_2_Percent", $B:$B, B14)+SUMIFS($K:$K, $D:$D, "HomeLoan_BT_less_than_2_Percent", $B:$B, B14)+SUMIFS($K:$K, $D:$D, "HomeLoan_Non_BT", $B:$B, B14)+SUMIFS($K:$K, $D:$D, "Mortgage_Power_Term", $B:$B, B14), Secured_Commission!$A:$F, 3, 1)*(K14/10^6), D14="HomeLoan_Non_BT", VLOOKUP(SUMIFS($K:$K, $D:$D, "HomeLoan_BT_more_than_2_Percent", $B:$B, B14)+SUMIFS($K:$K, $D:$D, "HomeLoan_BT_less_than_2_Percent", $B:$B, B14)+SUMIFS($K:$K, $D:$D, "HomeLoan_Non_BT", $B:$B, B14)+SUMIFS($K:$K, $D:$D, "Mortgage_Power_Term", $B:$B, B14), Secured_Commission!$A:$F, 4, 1)*(K14/10^6), D14="Mortgage_Power_Term", VLOOKUP(SUMIFS($K:$K, $D:$D, "HomeLoan_BT_more_than_2_Percent", $B:$B, B14)+SUMIFS($K:$K, $D:$D, "HomeLoan_BT_less_than_2_Percent", $B:$B, B14)+SUMIFS($K:$K, $D:$D, "HomeLoan_Non_BT", $B:$B, B14)+SUMIFS($K:$K, $D:$D, "Mortgage_Power_Term", $B:$B, B14), Secured_Commission!$A:$F, 5, 1)*(K14/10^6), D14="Personal_Cash", VLOOKUP(SUMIFS($K:$K, $D:$D, "Personal_Cash", $B:$B, B14), Unsecured_Commission!$A:$B, 2, 1)*K14, OR(D14="MRTA_3_Percent", D14="SOMPO"), K14*0.03, D14="MRTA_6_Percent", K14*0.06), 0)} -> 0
A15: 10 | G15: {=_xlfn.IFS( AND($C15="Secured", OR($D15="HomeLoan_BT_more_than_2_Percent", $D15="HomeLoan_BT_less_than_2_Percent"), $E15=""), "", AND($C15="Secured",$E15=""),"others", AND($C15="Secured",$E15=3),"others", AND($C15="Secured",$E15=5),"BT_with_5_year_lock_in_period", TRUE, "")} | I15: {=_xlfn.IFS( AND($C15="Secured", OR($D15="HomeLoan_BT_more_than_2_Percent", $D15="HomeLoan_BT_less_than_2_Percent"), OR($E15="", $E15=0)), "Please input Year !!!", AND($C15="Secured", OR($F15="", $F15=0)), "Please input Amount !!!", AND($C15="Secured", $F15<5000000), 1, AND($C15="Secured", $F15>=5000000), 1.1, TRUE, "")} | J15: {=IFERROR(_xlfn.IFS( $G15="BT_with_5_year_lock_in_period", _xlfn.XLOOKUP($H15, Deviate_Table[Pricing discount], Deviate_Table[BT_with_5_year_lock_in_period]), $G15="others", _xlfn.XLOOKUP($H15, Deviate_Table[Pricing discount], Deviate_Table[others]), TRUE, ""), "Please input Deviate Range !!!")} | K15: =IF($C15="Secured",IFERROR($F15*$I15*$J15, ""), $F15) -> 0 | L15: {=IFERROR( _xlfn.IFS( D15="HomeLoan_BT_less_than_2_Percent", VLOOKUP(SUMIFS($K:$K, $D:$D, "HomeLoan_BT_more_than_2_Percent", $B:$B, B15)+SUMIFS($K:$K, $D:$D, "HomeLoan_BT_less_than_2_Percent", $B:$B, B15)+SUMIFS($K:$K, $D:$D, "HomeLoan_Non_BT", $B:$B, B15)+SUMIFS($K:$K, $D:$D, "Mortgage_Power_Term", $B:$B, B15), Secured_Commission!$A:$F, 2, 1)*(K15/10^6), D15="HomeLoan_BT_more_than_2_Percent", VLOOKUP(SUMIFS($K:$K, $D:$D, "HomeLoan_BT_more_than_2_Percent", $B:$B, B15)+SUMIFS($K:$K, $D:$D, "HomeLoan_BT_less_than_2_Percent", $B:$B, B15)+SUMIFS($K:$K, $D:$D, "HomeLoan_Non_BT", $B:$B, B15)+SUMIFS($K:$K, $D:$D, "Mortgage_Power_Term", $B:$B, B15), Secured_Commission!$A:$F, 3, 1)*(K15/10^6), D15="HomeLoan_Non_BT", VLOOKUP(SUMIFS($K:$K, $D:$D, "HomeLoan_BT_more_than_2_Percent", $B:$B, B15)+SUMIFS($K:$K, $D:$D, "HomeLoan_BT_less_than_2_Percent", $B:$B, B15)+SUMIFS($K:$K, $D:$D, "HomeLoan_Non_BT", $B:$B, B15)+SUMIFS($K:$K, $D:$D, "Mortgage_Power_Term", $B:$B, B15), Secured_Commission!$A:$F, 4, 1)*(K15/10^6), D15="Mortgage_Power_Term", VLOOKUP(SUMIFS($K:$K, $D:$D, "HomeLoan_BT_more_than_2_Percent", $B:$B, B15)+SUMIFS($K:$K, $D:$D, "HomeLoan_BT_less_than_2_Percent", $B:$B, B15)+SUMIFS($K:$K, $D:$D, "HomeLoan_Non_BT", $B:$B, B15)+SUMIFS($K:$K, $D:$D, "Mortgage_Power_Term", $B:$B, B15), Secured_Commission!$A:$F, 5, 1)*(K15/10^6), D15="Personal_Cash", VLOOKUP(SUMIFS($K:$K, $D:$D, "Personal_Cash", $B:$B, B15), Unsecured_Commission!$A:$B, 2, 1)*K15, OR(D15="MRTA_3_Percent", D15="SOMPO"), K15*0.03, D15="MRTA_6_Percent", K15*0.06), 0)} -> 0
A16: 11 | G16: {=_xlfn.IFS( AND($C16="Secured", OR($D16="HomeLoan_BT_more_than_2_Percent", $D16="HomeLoan_BT_less_than_2_Percent"), $E16=""), "", AND($C16="Secured",$E16=""),"others", AND($C16="Secured",$E16=3),"others", AND($C16="Secured",$E16=5),"BT_with_5_year_lock_in_period", TRUE, "")} | I16: {=_xlfn.IFS( AND($C16="Secured", OR($D16="HomeLoan_BT_more_than_2_Percent", $D16="HomeLoan_BT_less_than_2_Percent"), OR($E16="", $E16=0)), "Please input Year !!!", AND($C16="Secured", OR($F16="", $F16=0)), "Please input Amount !!!", AND($C16="Secured", $F16<5000000), 1, AND($C16="Secured", $F16>=5000000), 1.1, TRUE, "")} | J16: {=IFERROR(_xlfn.IFS( $G16="BT_with_5_year_lock_in_period", _xlfn.XLOOKUP($H16, Deviate_Table[Pricing discount], Deviate_Table[BT_with_5_year_lock_in_period]), $G16="others", _xlfn.XLOOKUP($H16, Deviate_Table[Pricing discount], Deviate_Table[others]), TRUE, ""), "Please input Deviate Range !!!")} | K16: =IF($C16="Secured",IFERROR($F16*$I16*$J16, ""), $F16) -> 0 | L16: {=IFERROR( _xlfn.IFS( D16="HomeLoan_BT_less_than_2_Percent", VLOOKUP(SUMIFS($K:$K, $D:$D, "HomeLoan_BT_more_than_2_Percent", $B:$B, B16)+SUMIFS($K:$K, $D:$D, "HomeLoan_BT_less_than_2_Percent", $B:$B, B16)+SUMIFS($K:$K, $D:$D, "HomeLoan_Non_BT", $B:$B, B16)+SUMIFS($K:$K, $D:$D, "Mortgage_Power_Term", $B:$B, B16), Secured_Commission!$A:$F, 2, 1)*(K16/10^6), D16="HomeLoan_BT_more_than_2_Percent", VLOOKUP(SUMIFS($K:$K, $D:$D, "HomeLoan_BT_more_than_2_Percent", $B:$B, B16)+SUMIFS($K:$K, $D:$D, "HomeLoan_BT_less_than_2_Percent", $B:$B, B16)+SUMIFS($K:$K, $D:$D, "HomeLoan_Non_BT", $B:$B, B16)+SUMIFS($K:$K, $D:$D, "Mortgage_Power_Term", $B:$B, B16), Secured_Commission!$A:$F, 3, 1)*(K16/10^6), D16="HomeLoan_Non_BT", VLOOKUP(SUMIFS($K:$K, $D:$D, "HomeLoan_BT_more_than_2_Percent", $B:$B, B16)+SUMIFS($K:$K, $D:$D, "HomeLoan_BT_less_than_2_Percent", $B:$B, B16)+SUMIFS($K:$K, $D:$D, "HomeLoan_Non_BT", $B:$B, B16)+SUMIFS($K:$K, $D:$D, "Mortgage_Power_Term", $B:$B, B16), Secured_Commission!$A:$F, 4, 1)*(K16/10^6), D16="Mortgage_Power_Term", VLOOKUP(SUMIFS($K:$K, $D:$D, "HomeLoan_BT_more_than_2_Percent", $B:$B, B16)+SUMIFS($K:$K, $D:$D, "HomeLoan_BT_less_than_2_Percent", $B:$B, B16)+SUMIFS($K:$K, $D:$D, "HomeLoan_Non_BT", $B:$B, B16)+SUMIFS($K:$K, $D:$D, "Mortgage_Power_Term", $B:$B, B16), Secured_Commission!$A:$F, 5, 1)*(K16/10^6), D16="Personal_Cash", VLOOKUP(SUMIFS($K:$K, $D:$D, "Personal_Cash", $B:$B, B16), Unsecured_Commission!$A:$B, 2, 1)*K16, OR(D16="MRTA_3_Percent", D16="SOMPO"), K16*0.03, D16="MRTA_6_Percent", K16*0.06), 0)} -> 0
A17: 12 | G17: {=_xlfn.IFS( AND($C17="Secured", OR($D17="HomeLoan_BT_more_than_2_Percent", $D17="HomeLoan_BT_less_than_2_Percent"), $E17=""), "", AND($C17="Secured",$E17=""),"others", AND($C17="Secured",$E17=3),"others", AND($C17="Secured",$E17=5),"BT_with_5_year_lock_in_period", TRUE, "")} | I17: {=_xlfn.IFS( AND($C17="Secured", OR($D17="HomeLoan_BT_more_than_2_Percent", $D17="HomeLoan_BT_less_than_2_Percent"), OR($E17="", $E17=0)), "Please input Year !!!", AND($C17="Secured", OR($F17="", $F17=0)), "Please input Amount !!!", AND($C17="Secured", $F17<5000000), 1, AND($C17="Secured", $F17>=5000000), 1.1, TRUE, "")} | J17: {=IFERROR(_xlfn.IFS( $G17="BT_with_5_year_lock_in_period", _xlfn.XLOOKUP($H17, Deviate_Table[Pricing discount], Deviate_Table[BT_with_5_year_lock_in_period]), $G17="others", _xlfn.XLOOKUP($H17, Deviate_Table[Pricing discount], Deviate_Table[others]), TRUE, ""), "Please input Deviate Range !!!")} | K17: =IF($C17="Secured",IFERROR($F17*$I17*$J17, ""), $F17) -> 0 | L17: {=IFERROR( _xlfn.IFS( D17="HomeLoan_BT_less_than_2_Percent", VLOOKUP(SUMIFS($K:$K, $D:$D, "HomeLoan_BT_more_than_2_Percent", $B:$B, B17)+SUMIFS($K:$K, $D:$D, "HomeLoan_BT_less_than_2_Percent", $B:$B, B17)+SUMIFS($K:$K, $D:$D, "HomeLoan_Non_BT", $B:$B, B17)+SUMIFS($K:$K, $D:$D, "Mortgage_Power_Term", $B:$B, B17), Secured_Commission!$A:$F, 2, 1)*(K17/10^6), D17="HomeLoan_BT_more_than_2_Percent", VLOOKUP(SUMIFS($K:$K, $D:$D, "HomeLoan_BT_more_than_2_Percent", $B:$B, B17)+SUMIFS($K:$K, $D:$D, "HomeLoan_BT_less_than_2_Percent", $B:$B, B17)+SUMIFS($K:$K, $D:$D, "HomeLoan_Non_BT", $B:$B, B17)+SUMIFS($K:$K, $D:$D, "Mortgage_Power_Term", $B:$B, B17), Secured_Commission!$A:$F, 3, 1)*(K17/10^6), D17="HomeLoan_Non_BT", VLOOKUP(SUMIFS($K:$K, $D:$D, "HomeLoan_BT_more_than_2_Percent", $B:$B, B17)+SUMIFS($K:$K, $D:$D, "HomeLoan_BT_less_than_2_Percent", $B:$B, B17)+SUMIFS($K:$K, $D:$D, "HomeLoan_Non_BT", $B:$B, B17)+SUMIFS($K:$K, $D:$D, "Mortgage_Power_Term", $B:$B, B17), Secured_Commission!$A:$F, 4, 1)*(K17/10^6), D17="Mortgage_Power_Term", VLOOKUP(SUMIFS($K:$K, $D:$D, "HomeLoan_BT_more_than_2_Percent", $B:$B, B17)+SUMIFS($K:$K, $D:$D, "HomeLoan_BT_less_than_2_Percent", $B:$B, B17)+SUMIFS($K:$K, $D:$D, "HomeLoan_Non_BT", $B:$B, B17)+SUMIFS($K:$K, $D:$D, "Mortgage_Power_Term", $B:$B, B17), Secured_Commission!$A:$F, 5, 1)*(K17/10^6), D17="Personal_Cash", VLOOKUP(SUMIFS($K:$K, $D:$D, "Personal_Cash", $B:$B, B17), Unsecured_Commission!$A:$B, 2, 1)*K17, OR(D17="MRTA_3_Percent", D17="SOMPO"), K17*0.03, D17="MRTA_6_Percent", K17*0.06), 0)} -> 0
A18: 13 | G18: {=_xlfn.IFS( AND($C18="Secured", OR($D18="HomeLoan_BT_more_than_2_Percent", $D18="HomeLoan_BT_less_than_2_Percent"), $E18=""), "", AND($C18="Secured",$E18=""),"others", AND($C18="Secured",$E18=3),"others", AND($C18="Secured",$E18=5),"BT_with_5_year_lock_in_period", TRUE, "")} | I18: {=_xlfn.IFS( AND($C18="Secured", OR($D18="HomeLoan_BT_more_than_2_Percent", $D18="HomeLoan_BT_less_than_2_Percent"), OR($E18="", $E18=0)), "Please input Year !!!", AND($C18="Secured", OR($F18="", $F18=0)), "Please input Amount !!!", AND($C18="Secured", $F18<5000000), 1, AND($C18="Secured", $F18>=5000000), 1.1, TRUE, "")} | J18: {=IFERROR(_xlfn.IFS( $G18="BT_with_5_year_lock_in_period", _xlfn.XLOOKUP($H18, Deviate_Table[Pricing discount], Deviate_Table[BT_with_5_year_lock_in_period]), $G18="others", _xlfn.XLOOKUP($H18, Deviate_Table[Pricing discount], Deviate_Table[others]), TRUE, ""), "Please input Deviate Range !!!")} | K18: =IF($C18="Secured",IFERROR($F18*$I18*$J18, ""), $F18) -> 0 | L18: {=IFERROR( _xlfn.IFS( D18="HomeLoan_BT_less_than_2_Percent", VLOOKUP(SUMIFS($K:$K, $D:$D, "HomeLoan_BT_more_than_2_Percent", $B:$B, B18)+SUMIFS($K:$K, $D:$D, "HomeLoan_BT_less_than_2_Percent", $B:$B, B18)+SUMIFS($K:$K, $D:$D, "HomeLoan_Non_BT", $B:$B, B18)+SUMIFS($K:$K, $D:$D, "Mortgage_Power_Term", $B:$B, B18), Secured_Commission!$A:$F, 2, 1)*(K18/10^6), D18="HomeLoan_BT_more_than_2_Percent", VLOOKUP(SUMIFS($K:$K, $D:$D, "HomeLoan_BT_more_than_2_Percent", $B:$B, B18)+SUMIFS($K:$K, $D:$D, "HomeLoan_BT_less_than_2_Percent", $B:$B, B18)+SUMIFS($K:$K, $D:$D, "HomeLoan_Non_BT", $B:$B, B18)+SUMIFS($K:$K, $D:$D, "Mortgage_Power_Term", $B:$B, B18), Secured_Commission!$A:$F, 3, 1)*(K18/10^6), D18="HomeLoan_Non_BT", VLOOKUP(SUMIFS($K:$K, $D:$D, "HomeLoan_BT_more_than_2_Percent", $B:$B, B18)+SUMIFS($K:$K, $D:$D, "HomeLoan_BT_less_than_2_Percent", $B:$B, B18)+SUMIFS($K:$K, $D:$D, "HomeLoan_Non_BT", $B:$B, B18)+SUMIFS($K:$K, $D:$D, "Mortgage_Power_Term", $B:$B, B18), Secured_Commission!$A:$F, 4, 1)*(K18/10^6), D18="Mortgage_Power_Term", VLOOKUP(SUMIFS($K:$K, $D:$D, "HomeLoan_BT_more_than_2_Percent", $B:$B, B18)+SUMIFS($K:$K, $D:$D, "HomeLoan_BT_less_than_2_Percent", $B:$B, B18)+SUMIFS($K:$K, $D:$D, "HomeLoan_Non_BT", $B:$B, B18)+SUMIFS($K:$K, $D:$D, "Mortgage_Power_Term", $B:$B, B18), Secured_Commission!$A:$F, 5, 1)*(K18/10^6), D18="Personal_Cash", VLOOKUP(SUMIFS($K:$K, $D:$D, "Personal_Cash", $B:$B, B18), Unsecured_Commission!$A:$B, 2, 1)*K18, OR(D18="MRTA_3_Percent", D18="SOMPO"), K18*0.03, D18="MRTA_6_Percent", K18*0.06), 0)} -> 0
A19: 14 | G19: {=_xlfn.IFS( AND($C19="Secured", OR($D19="HomeLoan_BT_more_than_2_Percent", $D19="HomeLoan_BT_less_than_2_Percent"), $E19=""), "", AND($C19="Secured",$E19=""),"others", AND($C19="Secured",$E19=3),"others", AND($C19="Secured",$E19=5),"BT_with_5_year_lock_in_period", TRUE, "")} | I19: {=_xlfn.IFS( AND($C19="Secured", OR($D19="HomeLoan_BT_more_than_2_Percent", $D19="HomeLoan_BT_less_than_2_Percent"), OR($E19="", $E19=0)), "Please input Year !!!", AND($C19="Secured", OR($F19="", $F19=0)), "Please input Amount !!!", AND($C19="Secured", $F19<5000000), 1, AND($C19="Secured", $F19>=5000000), 1.1, TRUE, "")} | J19: {=IFERROR(_xlfn.IFS( $G19="BT_with_5_year_lock_in_period", _xlfn.XLOOKUP($H19, Deviate_Table[Pricing discount], Deviate_Table[BT_with_5_year_lock_in_period]), $G19="others", _xlfn.XLOOKUP($H19, Deviate_Table[Pricing discount], Deviate_Table[others]), TRUE, ""), "Please input Deviate Range !!!")} | K19: =IF($C19="Secured",IFERROR($F19*$I19*$J19, ""), $F19) -> 0 | L19: {=IFERROR( _xlfn.IFS( D19="HomeLoan_BT_less_than_2_Percent", VLOOKUP(SUMIFS($K:$K, $D:$D, "HomeLoan_BT_more_than_2_Percent", $B:$B, B19)+SUMIFS($K:$K, $D:$D, "HomeLoan_BT_less_than_2_Percent", $B:$B, B19)+SUMIFS($K:$K, $D:$D, "HomeLoan_Non_BT", $B:$B, B19)+SUMIFS($K:$K, $D:$D, "Mortgage_Power_Term", $B:$B, B19), Secured_Commission!$A:$F, 2, 1)*(K19/10^6), D19="HomeLoan_BT_more_than_2_Percent", VLOOKUP(SUMIFS($K:$K, $D:$D, "HomeLoan_BT_more_than_2_Percent", $B:$B, B19)+SUMIFS($K:$K, $D:$D, "HomeLoan_BT_less_than_2_Percent", $B:$B, B19)+SUMIFS($K:$K, $D:$D, "HomeLoan_Non_BT", $B:$B, B19)+SUMIFS($K:$K, $D:$D, "Mortgage_Power_Term", $B:$B, B19), Secured_Commission!$A:$F, 3, 1)*(K19/10^6), D19="HomeLoan_Non_BT", VLOOKUP(SUMIFS($K:$K, $D:$D, "HomeLoan_BT_more_than_2_Percent", $B:$B, B19)+SUMIFS($K:$K, $D:$D, "HomeLoan_BT_less_than_2_Percent", $B:$B, B19)+SUMIFS($K:$K, $D:$D, "HomeLoan_Non_BT", $B:$B, B19)+SUMIFS($K:$K, $D:$D, "Mortgage_Power_Term", $B:$B, B19), Secured_Commission!$A:$F, 4, 1)*(K19/10^6), D19="Mortgage_Power_Term", VLOOKUP(SUMIFS($K:$K, $D:$D, "HomeLoan_BT_more_than_2_Percent", $B:$B, B19)+SUMIFS($K:$K, $D:$D, "HomeLoan_BT_less_than_2_Percent", $B:$B, B19)+SUMIFS($K:$K, $D:$D, "HomeLoan_Non_BT", $B:$B, B19)+SUMIFS($K:$K, $D:$D, "Mortgage_Power_Term", $B:$B, B19), Secured_Commission!$A:$F, 5, 1)*(K19/10^6), D19="Personal_Cash", VLOOKUP(SUMIFS($K:$K, $D:$D, "Personal_Cash", $B:$B, B19), Unsecured_Commission!$A:$B, 2, 1)*K19, OR(D19="MRTA_3_Percent", D19="SOMPO"), K19*0.03, D19="MRTA_6_Percent", K19*0.06), 0)} -> 0
A20: 15 | G20: {=_xlfn.IFS( AND($C20="Secured", OR($D20="HomeLoan_BT_more_than_2_Percent", $D20="HomeLoan_BT_less_than_2_Percent"), $E20=""), "", AND($C20="Secured",$E20=""),"others", AND($C20="Secured",$E20=3),"others", AND($C20="Secured",$E20=5),"BT_with_5_year_lock_in_period", TRUE, "")} | I20: {=_xlfn.IFS( AND($C20="Secured", OR($D20="HomeLoan_BT_more_than_2_Percent", $D20="HomeLoan_BT_less_than_2_Percent"), OR($E20="", $E20=0)), "Please input Year !!!", AND($C20="Secured", OR($F20="", $F20=0)), "Please input Amount !!!", AND($C20="Secured", $F20<5000000), 1, AND($C20="Secured", $F20>=5000000), 1.1, TRUE, "")} | J20: {=IFERROR(_xlfn.IFS( $G20="BT_with_5_year_lock_in_period", _xlfn.XLOOKUP($H20, Deviate_Table[Pricing discount], Deviate_Table[BT_with_5_year_lock_in_period]), $G20="others", _xlfn.XLOOKUP($H20, Deviate_Table[Pricing discount], Deviate_Table[others]), TRUE, ""), "Please input Deviate Range !!!")} | K20: =IF($C20="Secured",IFERROR($F20*$I20*$J20, ""), $F20) -> 0 | L20: {=IFERROR( _xlfn.IFS( D20="HomeLoan_BT_less_than_2_Percent", VLOOKUP(SUMIFS($K:$K, $D:$D, "HomeLoan_BT_more_than_2_Percent", $B:$B, B20)+SUMIFS($K:$K, $D:$D, "HomeLoan_BT_less_than_2_Percent", $B:$B, B20)+SUMIFS($K:$K, $D:$D, "HomeLoan_Non_BT", $B:$B, B20)+SUMIFS($K:$K, $D:$D, "Mortgage_Power_Term", $B:$B, B20), Secured_Commission!$A:$F, 2, 1)*(K20/10^6), D20="HomeLoan_BT_more_than_2_Percent", VLOOKUP(SUMIFS($K:$K, $D:$D, "HomeLoan_BT_more_than_2_Percent", $B:$B, B20)+SUMIFS($K:$K, $D:$D, "HomeLoan_BT_less_than_2_Percent", $B:$B, B20)+SUMIFS($K:$K, $D:$D, "HomeLoan_Non_BT", $B:$B, B20)+SUMIFS($K:$K, $D:$D, "Mortgage_Power_Term", $B:$B, B20), Secured_Commission!$A:$F, 3, 1)*(K20/10^6), D20="HomeLoan_Non_BT", VLOOKUP(SUMIFS($K:$K, $D:$D, "HomeLoan_BT_more_than_2_Percent", $B:$B, B20)+SUMIFS($K:$K, $D:$D, "HomeLoan_BT_less_than_2_Percent", $B:$B, B20)+SUMIFS($K:$K, $D:$D, "HomeLoan_Non_BT", $B:$B, B20)+SUMIFS($K:$K, $D:$D, "Mortgage_Power_Term", $B:$B, B20), Secured_Commission!$A:$F, 4, 1)*(K20/10^6), D20="Mortgage_Power_Term", VLOOKUP(SUMIFS($K:$K, $D:$D, "HomeLoan_BT_more_than_2_Percent", $B:$B, B20)+SUMIFS($K:$K, $D:$D, "HomeLoan_BT_less_than_2_Percent", $B:$B, B20)+SUMIFS($K:$K, $D:$D, "HomeLoan_Non_BT", $B:$B, B20)+SUMIFS($K:$K, $D:$D, "Mortgage_Power_Term", $B:$B, B20), Secured_Commission!$A:$F, 5, 1)*(K20/10^6), D20="Personal_Cash", VLOOKUP(SUMIFS($K:$K, $D:$D, "Personal_Cash", $B:$B, B20), Unsecured_Commission!$A:$B, 2, 1)*K20, OR(D20="MRTA_3_Percent", D20="SOMPO"), K20*0.03, D20="MRTA_6_Percent", K20*0.06), 0)} -> 0
A21: 16 | G21: {=_xlfn.IFS( AND($C21="Secured", OR($D21="HomeLoan_BT_more_than_2_Percent", $D21="HomeLoan_BT_less_than_2_Percent"), $E21=""), "", AND($C21="Secured",$E21=""),"others", AND($C21="Secured",$E21=3),"others", AND($C21="Secured",$E21=5),"BT_with_5_year_lock_in_period", TRUE, "")} | I21: {=_xlfn.IFS( AND($C21="Secured", OR($D21="HomeLoan_BT_more_than_2_Percent", $D21="HomeLoan_BT_less_than_2_Percent"), OR($E21="", $E21=0)), "Please input Year !!!", AND($C21="Secured", OR($F21="", $F21=0)), "Please input Amount !!!", AND($C21="Secured", $F21<5000000), 1, AND($C21="Secured", $F21>=5000000), 1.1, TRUE, "")} | J21: {=IFERROR(_xlfn.IFS( $G21="BT_with_5_year_lock_in_period", _xlfn.XLOOKUP($H21, Deviate_Table[Pricing discount], Deviate_Table[BT_with_5_year_lock_in_period]), $G21="others", _xlfn.XLOOKUP($H21, Deviate_Table[Pricing discount], Deviate_Table[others]), TRUE, ""), "Please input Deviate Range !!!")} | K21: =IF($C21="Secured",IFERROR($F21*$I21*$J21, ""), $F21) -> 0 | L21: {=IFERROR( _xlfn.IFS( D21="HomeLoan_BT_less_than_2_Percent", VLOOKUP(SUMIFS($K:$K, $D:$D, "HomeLoan_BT_more_than_2_Percent", $B:$B, B21)+SUMIFS($K:$K, $D:$D, "HomeLoan_BT_less_than_2_Percent", $B:$B, B21)+SUMIFS($K:$K, $D:$D, "HomeLoan_Non_BT", $B:$B, B21)+SUMIFS($K:$K, $D:$D, "Mortgage_Power_Term", $B:$B, B21), Secured_Commission!$A:$F, 2, 1)*(K21/10^6), D21="HomeLoan_BT_more_than_2_Percent", VLOOKUP(SUMIFS($K:$K, $D:$D, "HomeLoan_BT_more_than_2_Percent", $B:$B, B21)+SUMIFS($K:$K, $D:$D, "HomeLoan_BT_less_than_2_Percent", $B:$B, B21)+SUMIFS($K:$K, $D:$D, "HomeLoan_Non_BT", $B:$B, B21)+SUMIFS($K:$K, $D:$D, "Mortgage_Power_Term", $B:$B, B21), Secured_Commission!$A:$F, 3, 1)*(K21/10^6), D21="HomeLoan_Non_BT", VLOOKUP(SUMIFS($K:$K, $D:$D, "HomeLoan_BT_more_than_2_Percent", $B:$B, B21)+SUMIFS($K:$K, $D:$D, "HomeLoan_BT_less_than_2_Percent", $B:$B, B21)+SUMIFS($K:$K, $D:$D, "HomeLoan_Non_BT", $B:$B, B21)+SUMIFS($K:$K, $D:$D, "Mortgage_Power_Term", $B:$B, B21), Secured_Commission!$A:$F, 4, 1)*(K21/10^6), D21="Mortgage_Power_Term", VLOOKUP(SUMIFS($K:$K, $D:$D, "HomeLoan_BT_more_than_2_Percent", $B:$B, B21)+SUMIFS($K:$K, $D:$D, "HomeLoan_BT_less_than_2_Percent", $B:$B, B21)+SUMIFS($K:$K, $D:$D, "HomeLoan_Non_BT", $B:$B, B21)+SUMIFS($K:$K, $D:$D, "Mortgage_Power_Term", $B:$B, B21), Secured_Commission!$A:$F, 5, 1)*(K21/10^6), D21="Personal_Cash", VLOOKUP(SUMIFS($K:$K, $D:$D, "Personal_Cash", $B:$B, B21), Unsecured_Commission!$A:$B, 2, 1)*K21, OR(D21="MRTA_3_Percent", D21="SOMPO"), K21*0.03, D21="MRTA_6_Percent", K21*0.06), 0)} -> 0
A22: 17 | G22: {=_xlfn.IFS( AND($C22="Secured", OR($D22="HomeLoan_BT_more_than_2_Percent", $D22="HomeLoan_BT_less_than_2_Percent"), $E22=""), "", AND($C22="Secured",$E22=""),"others", AND($C22="Secured",$E22=3),"others", AND($C22="Secured",$E22=5),"BT_with_5_year_lock_in_period", TRUE, "")} | I22: {=_xlfn.IFS( AND($C22="Secured", OR($D22="HomeLoan_BT_more_than_2_Percent", $D22="HomeLoan_BT_less_than_2_Percent"), OR($E22="", $E22=0)), "Please input Year !!!", AND($C22="Secured", OR($F22="", $F22=0)), "Please input Amount !!!", AND($C22="Secured", $F22<5000000), 1, AND($C22="Secured", $F22>=5000000), 1.1, TRUE, "")} | J22: {=IFERROR(_xlfn.IFS( $G22="BT_with_5_year_lock_in_period", _xlfn.XLOOKUP($H22, Deviate_Table[Pricing discount], Deviate_Table[BT_with_5_year_lock_in_period]), $G22="others", _xlfn.XLOOKUP($H22, Deviate_Table[Pricing discount], Deviate_Table[others]), TRUE, ""), "Please input Deviate Range !!!")} | K22: =IF($C22="Secured",IFERROR($F22*$I22*$J22, ""), $F22) -> 0 | L22: {=IFERROR( _xlfn.IFS( D22="HomeLoan_BT_less_than_2_Percent", VLOOKUP(SUMIFS($K:$K, $D:$D, "HomeLoan_BT_more_than_2_Percent", $B:$B, B22)+SUMIFS($K:$K, $D:$D, "HomeLoan_BT_less_than_2_Percent", $B:$B, B22)+SUMIFS($K:$K, $D:$D, "HomeLoan_Non_BT", $B:$B, B22)+SUMIFS($K:$K, $D:$D, "Mortgage_Power_Term", $B:$B, B22), Secured_Commission!$A:$F, 2, 1)*(K22/10^6), D22="HomeLoan_BT_more_than_2_Percent", VLOOKUP(SUMIFS($K:$K, $D:$D, "HomeLoan_BT_more_than_2_Percent", $B:$B, B22)+SUMIFS($K:$K, $D:$D, "HomeLoan_BT_less_than_2_Percent", $B:$B, B22)+SUMIFS($K:$K, $D:$D, "HomeLoan_Non_BT", $B:$B, B22)+SUMIFS($K:$K, $D:$D, "Mortgage_Power_Term", $B:$B, B22), Secured_Commission!$A:$F, 3, 1)*(K22/10^6), D22="HomeLoan_Non_BT", VLOOKUP(SUMIFS($K:$K, $D:$D, "HomeLoan_BT_more_than_2_Percent", $B:$B, B22)+SUMIFS($K:$K, $D:$D, "HomeLoan_BT_less_than_2_Percent", $B:$B, B22)+SUMIFS($K:$K, $D:$D, "HomeLoan_Non_BT", $B:$B, B22)+SUMIFS($K:$K, $D:$D, "Mortgage_Power_Term", $B:$B, B22), Secured_Commission!$A:$F, 4, 1)*(K22/10^6), D22="Mortgage_Power_Term", VLOOKUP(SUMIFS($K:$K, $D:$D, "HomeLoan_BT_more_than_2_Percent", $B:$B, B22)+SUMIFS($K:$K, $D:$D, "HomeLoan_BT_less_than_2_Percent", $B:$B, B22)+SUMIFS($K:$K, $D:$D, "HomeLoan_Non_BT", $B:$B, B22)+SUMIFS($K:$K, $D:$D, "Mortgage_Power_Term", $B:$B, B22), Secured_Commission!$A:$F, 5, 1)*(K22/10^6), D22="Personal_Cash", VLOOKUP(SUMIFS($K:$K, $D:$D, "Personal_Cash", $B:$B, B22), Unsecured_Commission!$A:$B, 2, 1)*K22, OR(D22="MRTA_3_Percent", D22="SOMPO"), K22*0.03, D22="MRTA_6_Percent", K22*0.06), 0)} -> 0
A23: 18 | G23: {=_xlfn.IFS( AND($C23="Secured", OR($D23="HomeLoan_BT_more_than_2_Percent", $D23="HomeLoan_BT_less_than_2_Percent"), $E23=""), "", AND($C23="Secured",$E23=""),"others", AND($C23="Secured",$E23=3),"others", AND($C23="Secured",$E23=5),"BT_with_5_year_lock_in_period", TRUE, "")} | I23: {=_xlfn.IFS( AND($C23="Secured", OR($D23="HomeLoan_BT_more_than_2_Percent", $D23="HomeLoan_BT_less_than_2_Percent"), OR($E23="", $E23=0)), "Please input Year !!!", AND($C23="Secured", OR($F23="", $F23=0)), "Please input Amount !!!", AND($C23="Secured", $F23<5000000), 1, AND($C23="Secured", $F23>=5000000), 1.1, TRUE, "")} | J23: {=IFERROR(_xlfn.IFS( $G23="BT_with_5_year_lock_in_period", _xlfn.XLOOKUP($H23, Deviate_Table[Pricing discount], Deviate_Table[BT_with_5_year_lock_in_period]), $G23="others", _xlfn.XLOOKUP($H23, Deviate_Table[Pricing discount], Deviate_Table[others]), TRUE, ""), "Please input Deviate Range !!!")} | K23: =IF($C23="Secured",IFERROR($F23*$I23*$J23, ""), $F23) -> 0 | L23: {=IFERROR( _xlfn.IFS( D23="HomeLoan_BT_less_than_2_Percent", VLOOKUP(SUMIFS($K:$K, $D:$D, "HomeLoan_BT_more_than_2_Percent", $B:$B, B23)+SUMIFS($K:$K, $D:$D, "HomeLoan_BT_less_than_2_Percent", $B:$B, B23)+SUMIFS($K:$K, $D:$D, "HomeLoan_Non_BT", $B:$B, B23)+SUMIFS($K:$K, $D:$D, "Mortgage_Power_Term", $B:$B, B23), Secured_Commission!$A:$F, 2, 1)*(K23/10^6), D23="HomeLoan_BT_more_than_2_Percent", VLOOKUP(SUMIFS($K:$K, $D:$D, "HomeLoan_BT_more_than_2_Percent", $B:$B, B23)+SUMIFS($K:$K, $D:$D, "HomeLoan_BT_less_than_2_Percent", $B:$B, B23)+SUMIFS($K:$K, $D:$D, "HomeLoan_Non_BT", $B:$B, B23)+SUMIFS($K:$K, $D:$D, "Mortgage_Power_Term", $B:$B, B23), Secured_Commission!$A:$F, 3, 1)*(K23/10^6), D23="HomeLoan_Non_BT", VLOOKUP(SUMIFS($K:$K, $D:$D, "HomeLoan_BT_more_than_2_Percent", $B:$B, B23)+SUMIFS($K:$K, $D:$D, "HomeLoan_BT_less_than_2_Percent", $B:$B, B23)+SUMIFS($K:$K, $D:$D, "HomeLoan_Non_BT", $B:$B, B23)+SUMIFS($K:$K, $D:$D, "Mortgage_Power_Term", $B:$B, B23), Secured_Commission!$A:$F, 4, 1)*(K23/10^6), D23="Mortgage_Power_Term", VLOOKUP(SUMIFS($K:$K, $D:$D, "HomeLoan_BT_more_than_2_Percent", $B:$B, B23)+SUMIFS($K:$K, $D:$D, "HomeLoan_BT_less_than_2_Percent", $B:$B, B23)+SUMIFS($K:$K, $D:$D, "HomeLoan_Non_BT", $B:$B, B23)+SUMIFS($K:$K, $D:$D, "Mortgage_Power_Term", $B:$B, B23), Secured_Commission!$A:$F, 5, 1)*(K23/10^6), D23="Personal_Cash", VLOOKUP(SUMIFS($K:$K, $D:$D, "Personal_Cash", $B:$B, B23), Unsecured_Commission!$A:$B, 2, 1)*K23, OR(D23="MRTA_3_Percent", D23="SOMPO"), K23*0.03, D23="MRTA_6_Percent", K23*0.06), 0)} -> 0
A24: 19 | G24: {=_xlfn.IFS( AND($C24="Secured", OR($D24="HomeLoan_BT_more_than_2_Percent", $D24="HomeLoan_BT_less_than_2_Percent"), $E24=""), "", AND($C24="Secured",$E24=""),"others", AND($C24="Secured",$E24=3),"others", AND($C24="Secured",$E24=5),"BT_with_5_year_lock_in_period", TRUE, "")} | I24: {=_xlfn.IFS( AND($C24="Secured", OR($D24="HomeLoan_BT_more_than_2_Percent", $D24="HomeLoan_BT_less_than_2_Percent"), OR($E24="", $E24=0)), "Please input Year !!!", AND($C24="Secured", OR($F24="", $F24=0)), "Please input Amount !!!", AND($C24="Secured", $F24<5000000), 1, AND($C24="Secured", $F24>=5000000), 1.1, TRUE, "")} | J24: {=IFERROR(_xlfn.IFS( $G24="BT_with_5_year_lock_in_period", _xlfn.XLOOKUP($H24, Deviate_Table[Pricing discount], Deviate_Table[BT_with_5_year_lock_in_period]), $G24="others", _xlfn.XLOOKUP($H24, Deviate_Table[Pricing discount], Deviate_Table[others]), TRUE, ""), "Please input Deviate Range !!!")} | K24: =IF($C24="Secured",IFERROR($F24*$I24*$J24, ""), $F24) -> 0 | L24: {=IFERROR( _xlfn.IFS( D24="HomeLoan_BT_less_than_2_Percent", VLOOKUP(SUMIFS($K:$K, $D:$D, "HomeLoan_BT_more_than_2_Percent", $B:$B, B24)+SUMIFS($K:$K, $D:$D, "HomeLoan_BT_less_than_2_Percent", $B:$B, B24)+SUMIFS($K:$K, $D:$D, "HomeLoan_Non_BT", $B:$B, B24)+SUMIFS($K:$K, $D:$D, "Mortgage_Power_Term", $B:$B, B24), Secured_Commission!$A:$F, 2, 1)*(K24/10^6), D24="HomeLoan_BT_more_than_2_Percent", VLOOKUP(SUMIFS($K:$K, $D:$D, "HomeLoan_BT_more_than_2_Percent", $B:$B, B24)+SUMIFS($K:$K, $D:$D, "HomeLoan_BT_less_than_2_Percent", $B:$B, B24)+SUMIFS($K:$K, $D:$D, "HomeLoan_Non_BT", $B:$B, B24)+SUMIFS($K:$K, $D:$D, "Mortgage_Power_Term", $B:$B, B24), Secured_Commission!$A:$F, 3, 1)*(K24/10^6), D24="HomeLoan_Non_BT", VLOOKUP(SUMIFS($K:$K, $D:$D, "HomeLoan_BT_more_than_2_Percent", $B:$B, B24)+SUMIFS($K:$K, $D:$D, "HomeLoan_BT_less_than_2_Percent", $B:$B, B24)+SUMIFS($K:$K, $D:$D, "HomeLoan_Non_BT", $B:$B, B24)+SUMIFS($K:$K, $D:$D, "Mortgage_Power_Term", $B:$B, B24), Secured_Commission!$A:$F, 4, 1)*(K24/10^6), D24="Mortgage_Power_Term", VLOOKUP(SUMIFS($K:$K, $D:$D, "HomeLoan_BT_more_than_2_Percent", $B:$B, B24)+SUMIFS($K:$K, $D:$D, "HomeLoan_BT_less_than_2_Percent", $B:$B, B24)+SUMIFS($K:$K, $D:$D, "HomeLoan_Non_BT", $B:$B, B24)+SUMIFS($K:$K, $D:$D, "Mortgage_Power_Term", $B:$B, B24), Secured_Commission!$A:$F, 5, 1)*(K24/10^6), D24="Personal_Cash", VLOOKUP(SUMIFS($K:$K, $D:$D, "Personal_Cash", $B:$B, B24), Unsecured_Commission!$A:$B, 2, 1)*K24, OR(D24="MRTA_3_Percent", D24="SOMPO"), K24*0.03, D24="MRTA_6_Percent", K24*0.06), 0)} -> 0
A25: 20 | G25: {=_xlfn.IFS( AND($C25="Secured", OR($D25="HomeLoan_BT_more_than_2_Percent", $D25="HomeLoan_BT_less_than_2_Percent"), $E25=""), "", AND($C25="Secured",$E25=""),"others", AND($C25="Secured",$E25=3),"others", AND($C25="Secured",$E25=5),"BT_with_5_year_lock_in_period", TRUE, "")} | I25: {=_xlfn.IFS( AND($C25="Secured", OR($D25="HomeLoan_BT_more_than_2_Percent", $D25="HomeLoan_BT_less_than_2_Percent"), OR($E25="", $E25=0)), "Please input Year !!!", AND($C25="Secured", OR($F25="", $F25=0)), "Please input Amount !!!", AND($C25="Secured", $F25<5000000), 1, AND($C25="Secured", $F25>=5000000), 1.1, TRUE, "")} | J25: {=IFERROR(_xlfn.IFS( $G25="BT_with_5_year_lock_in_period", _xlfn.XLOOKUP($H25, Deviate_Table[Pricing discount], Deviate_Table[BT_with_5_year_lock_in_period]), $G25="others", _xlfn.XLOOKUP($H25, Deviate_Table[Pricing discount], Deviate_Table[others]), TRUE, ""), "Please input Deviate Range !!!")} | K25: =IF($C25="Secured",IFERROR($F25*$I25*$J25, ""), $F25) -> 0 | L25: {=IFERROR( _xlfn.IFS( D25="HomeLoan_BT_less_than_2_Percent", VLOOKUP(SUMIFS($K:$K, $D:$D, "HomeLoan_BT_more_than_2_Percent", $B:$B, B25)+SUMIFS($K:$K, $D:$D, "HomeLoan_BT_less_than_2_Percent", $B:$B, B25)+SUMIFS($K:$K, $D:$D, "HomeLoan_Non_BT", $B:$B, B25)+SUMIFS($K:$K, $D:$D, "Mortgage_Power_Term", $B:$B, B25), Secured_Commission!$A:$F, 2, 1)*(K25/10^6), D25="HomeLoan_BT_more_than_2_Percent", VLOOKUP(SUMIFS($K:$K, $D:$D, "HomeLoan_BT_more_than_2_Percent", $B:$B, B25)+SUMIFS($K:$K, $D:$D, "HomeLoan_BT_less_than_2_Percent", $B:$B, B25)+SUMIFS($K:$K, $D:$D, "HomeLoan_Non_BT", $B:$B, B25)+SUMIFS($K:$K, $D:$D, "Mortgage_Power_Term", $B:$B, B25), Secured_Commission!$A:$F, 3, 1)*(K25/10^6), D25="HomeLoan_Non_BT", VLOOKUP(SUMIFS($K:$K, $D:$D, "HomeLoan_BT_more_than_2_Percent", $B:$B, B25)+SUMIFS($K:$K, $D:$D, "HomeLoan_BT_less_than_2_Percent", $B:$B, B25)+SUMIFS($K:$K, $D:$D, "HomeLoan_Non_BT", $B:$B, B25)+SUMIFS($K:$K, $D:$D, "Mortgage_Power_Term", $B:$B, B25), Secured_Commission!$A:$F, 4, 1)*(K25/10^6), D25="Mortgage_Power_Term", VLOOKUP(SUMIFS($K:$K, $D:$D, "HomeLoan_BT_more_than_2_Percent", $B:$B, B25)+SUMIFS($K:$K, $D:$D, "HomeLoan_BT_less_than_2_Percent", $B:$B, B25)+SUMIFS($K:$K, $D:$D, "HomeLoan_Non_BT", $B:$B, B25)+SUMIFS($K:$K, $D:$D, "Mortgage_Power_Term", $B:$B, B25), Secured_Commission!$A:$F, 5, 1)*(K25/10^6), D25="Personal_Cash", VLOOKUP(SUMIFS($K:$K, $D:$D, "Personal_Cash", $B:$B, B25), Unsecured_Commission!$A:$B, 2, 1)*K25, OR(D25="MRTA_3_Percent", D25="SOMPO"), K25*0.03, D25="MRTA_6_Percent", K25*0.06), 0)} -> 0
... A201: 196 | G201: {=_xlfn.IFS( AND($C201="Secured", OR($D201="HomeLoan_BT_more_than_2_Percent", $D201="HomeLoan_BT_less_than_2_Percent"), $E201=""), "", AND($C201="Secured",$E201=""),"others", AND($C201="Secured",$E201=3),"others", AND($C201="Secured",$E201=5),"BT_with_5_year_lock_in_period", TRUE, "")} | I201: {=_xlfn.IFS( AND($C201="Secured", OR($D201="HomeLoan_BT_more_than_2_Percent", $D201="HomeLoan_BT_less_than_2_Percent"), OR($E201="", $E201=0)), "Please input Year !!!", AND($C201="Secured", OR($F201="", $F201=0)), "Please input Amount !!!", AND($C201="Secured", $F201<5000000), 1, AND($C201="Secured", $F201>=5000000), 1.1, TRUE, "")} | J201: {=IFERROR(_xlfn.IFS( $G201="BT_with_5_year_lock_in_period", _xlfn.XLOOKUP($H201, Deviate_Table[Pricing discount], Deviate_Table[BT_with_5_year_lock_in_period]), $G201="others", _xlfn.XLOOKUP($H201, Deviate_Table[Pricing discount], Deviate_Table[others]), TRUE, ""), "Please input Deviate Range !!!")} | K201: =IF($C201="Secured",IFERROR($F201*$I201*$J201, ""), $F201) -> 0 | L201: {=IFERROR( _xlfn.IFS( D201="HomeLoan_BT_less_than_2_Percent", VLOOKUP(SUMIFS($K:$K, $D:$D, "HomeLoan_BT_more_than_2_Percent", $B:$B, B201)+SUMIFS($K:$K, $D:$D, "HomeLoan_BT_less_than_2_Percent", $B:$B, B201)+SUMIFS($K:$K, $D:$D, "HomeLoan_Non_BT", $B:$B, B201)+SUMIFS($K:$K, $D:$D, "Mortgage_Power_Term", $B:$B, B201), Secured_Commission!$A:$F, 2, 1)*(K201/10^6), D201="HomeLoan_BT_more_than_2_Percent", VLOOKUP(SUMIFS($K:$K, $D:$D, "HomeLoan_BT_more_than_2_Percent", $B:$B, B201)+SUMIFS($K:$K, $D:$D, "HomeLoan_BT_less_than_2_Percent", $B:$B, B201)+SUMIFS($K:$K, $D:$D, "HomeLoan_Non_BT", $B:$B, B201)+SUMIFS($K:$K, $D:$D, "Mortgage_Power_Term", $B:$B, B201), Secured_Commission!$A:$F, 3, 1)*(K201/10^6), D201="HomeLoan_Non_BT", VLOOKUP(SUMIFS($K:$K, $D:$D, "HomeLoan_BT_more_than_2_Percent", $B:$B, B201)+SUMIFS($K:$K, $D:$D, "HomeLoan_BT_less_than_2_Percent", $B:$B, B201)+SUMIFS($K:$K, $D:$D, "HomeLoan_Non_BT", $B:$B, B201)+SUMIFS($K:$K, $D:$D, "Mortgage_Power_Term", $B:$B, B201), Secured_Commission!$A:$F, 4, 1)*(K201/10^6), D201="Mortgage_Power_Term", VLOOKUP(SUMIFS($K:$K, $D:$D, "HomeLoan_BT_more_than_2_Percent", $B:$B, B201)+SUMIFS($K:$K, $D:$D, "HomeLoan_BT_less_than_2_Percent", $B:$B, B201)+SUMIFS($K:$K, $D:$D, "HomeLoan_Non_BT", $B:$B, B201)+SUMIFS($K:$K, $D:$D, "Mortgage_Power_Term", $B:$B, B201), Secured_Commission!$A:$F, 5, 1)*(K201/10^6), D201="Personal_Cash", VLOOKUP(SUMIFS($K:$K, $D:$D, "Personal_Cash", $B:$B, B201), Unsecured_Commission!$A:$B, 2, 1)*K201, OR(D201="MRTA_3_Percent", D201="SOMPO"), K201*0.03, D201="MRTA_6_Percent", K201*0.06), 0)} -> 0

Sheet Summary_Commission_Simulation
B2: Channel | C2: =Detail_Simulation!$B2 -> Direct_Sales_1
B3: Team | C3: =Detail_Simulation!$B3 -> DS1_3_2
E5: Secured | I5: Unsecured | J5: Banca
D6: =SUBTOTAL(9, D$8:D$41) -> 0 | E6: =SUBTOTAL(9, E$8:E$41) -> 0 | F6: =SUBTOTAL(9, F$8:F$41) -> 0 | G6: =SUBTOTAL(9, G$8:G$41) -> 0 | H6: =SUBTOTAL(9, H$8:H$41) -> 0 | I6: =SUBTOTAL(9, I$8:I$41) -> 0 | J6: =SUBTOTAL(9, J$8:J$41) -> 0 | K6: =SUBTOTAL(9, K$8:K$41) -> 0
B7: No. | C7: Sales ID | D7: Total Commission | E7: HomeLoan_BT (<2%) | F7: HomeLoan_BT (>2%) | G7: HomeLoan Non_BT | H7: MP&PP | I7: PC | J7: MRTA | K7: SOMPO
B8: 1 | C8: {=_xlfn.UNIQUE(_xlfn._xlws.FILTER(Detail_Simulation!$B$6:$B$201, Detail_Simulation!$B$6:$B$201<>0))} -> 6560479 | D8: =SUM(E8,F8,G8,H8,I8,J8,K8) -> 0 | E8: =SUMIFS(Detail_Simulation!$L:$L, Detail_Simulation!$B:$B, $C8, Detail_Simulation!$D:$D, "HomeLoan_BT_less_than_2_Percent") -> 0 | F8: =SUMIFS(Detail_Simulation!$L:$L, Detail_Simulation!$B:$B, $C8, Detail_Simulation!$D:$D, "HomeLoan_BT_more_than_2_Percent") -> 0 | G8: =SUMIFS(Detail_Simulation!$L:$L, Detail_Simulation!$B:$B, $C8, Detail_Simulation!$D:$D, "HomeLoan_Non_BT") -> 0 | H8: =SUMIFS(Detail_Simulation!$L:$L, Detail_Simulation!$B:$B, $C8, Detail_Simulation!$D:$D, "Mortgage_Power_Term") -> 0 | I8: =SUMIFS(Detail_Simulation!$L:$L, Detail_Simulation!$B:$B, $C8, Detail_Simulation!$D:$D, "Personal_Cash") -> 0 | J8: =SUMIFS(Detail_Simulation!$L:$L, Detail_Simulation!$B:$B, $C8, Detail_Simulation!$D:$D, "MRTA_3_Percent")+ SUMIFS(Detail_Simulation!$L:$L, Detail_Simulation!$B:$B, $C8, Detail_Simulation!$D:$D, "MRTA_6_Percent") -> 0 | K8: =SUMIFS(Detail_Simulation!$L:$L, Detail_Simulation!$B:$B, $C8, Detail_Simulation!$D:$D, "SOMPO") -> 0
B9: 2 | C9: 6860211 | D9: =SUM(E9,F9,G9,H9,I9,J9,K9) -> 0 | E9: =SUMIFS(Detail_Simulation!$L:$L, Detail_Simulation!$B:$B, $C9, Detail_Simulation!$D:$D, "HomeLoan_BT_less_than_2_Percent") -> 0 | F9: =SUMIFS(Detail_Simulation!$L:$L, Detail_Simulation!$B:$B, $C9, Detail_Simulation!$D:$D, "HomeLoan_BT_more_than_2_Percent") -> 0 | G9: =SUMIFS(Detail_Simulation!$L:$L, Detail_Simulation!$B:$B, $C9, Detail_Simulation!$D:$D, "HomeLoan_Non_BT") -> 0 | H9: =SUMIFS(Detail_Simulation!$L:$L, Detail_Simulation!$B:$B, $C9, Detail_Simulation!$D:$D, "Mortgage_Power_Term") -> 0 | I9: =SUMIFS(Detail_Simulation!$L:$L, Detail_Simulation!$B:$B, $C9, Detail_Simulation!$D:$D, "Personal_Cash") -> 0 | J9: =SUMIFS(Detail_Simulation!$L:$L, Detail_Simulation!$B:$B, $C9, Detail_Simulation!$D:$D, "MRTA_3_Percent")+ SUMIFS(Detail_Simulation!$L:$L, Detail_Simulation!$B:$B, $C9, Detail_Simulation!$D:$D, "MRTA_6_Percent") -> 0 | K9: =SUMIFS(Detail_Simulation!$L:$L, Detail_Simulation!$B:$B, $C9, Detail_Simulation!$D:$D, "SOMPO") -> 0
B10: 3 | C10: 6860015 | D10: =SUM(E10,F10,G10,H10,I10,J10,K10) -> 0 | E10: =SUMIFS(Detail_Simulation!$L:$L, Detail_Simulation!$B:$B, $C10, Detail_Simulation!$D:$D, "HomeLoan_BT_less_than_2_Percent") -> 0 | F10: =SUMIFS(Detail_Simulation!$L:$L, Detail_Simulation!$B:$B, $C10, Detail_Simulation!$D:$D, "HomeLoan_BT_more_than_2_Percent") -> 0 | G10: =SUMIFS(Detail_Simulation!$L:$L, Detail_Simulation!$B:$B, $C10, Detail_Simulation!$D:$D, "HomeLoan_Non_BT") -> 0 | H10: =SUMIFS(Detail_Simulation!$L:$L, Detail_Simulation!$B:$B, $C10, Detail_Simulation!$D:$D, "Mortgage_Power_Term") -> 0 | I10: =SUMIFS(Detail_Simulation!$L:$L, Detail_Simulation!$B:$B, $C10, Detail_Simulation!$D:$D, "Personal_Cash") -> 0 | J10: =SUMIFS(Detail_Simulation!$L:$L, Detail_Simulation!$B:$B, $C10, Detail_Simulation!$D:$D, "MRTA_3_Percent")+ SUMIFS(Detail_Simulation!$L:$L, Detail_Simulation!$B:$B, $C10, Detail_Simulation!$D:$D, "MRTA_6_Percent") -> 0 | K10: =SUMIFS(Detail_Simulation!$L:$L, Detail_Simulation!$B:$B, $C10, Detail_Simulation!$D:$D, "SOMPO") -> 0
B11: 4 | D11: =SUM(E11,F11,G11,H11,I11,J11,K11) -> 0 | E11: =SUMIFS(Detail_Simulation!$L:$L, Detail_Simulation!$B:$B, $C11, Detail_Simulation!$D:$D, "HomeLoan_BT_less_than_2_Percent") -> 0 | F11: =SUMIFS(Detail_Simulation!$L:$L, Detail_Simulation!$B:$B, $C11, Detail_Simulation!$D:$D, "HomeLoan_BT_more_than_2_Percent") -> 0 | G11: =SUMIFS(Detail_Simulation!$L:$L, Detail_Simulation!$B:$B, $C11, Detail_Simulation!$D:$D, "HomeLoan_Non_BT") -> 0 | H11: =SUMIFS(Detail_Simulation!$L:$L, Detail_Simulation!$B:$B, $C11, Detail_Simulation!$D:$D, "Mortgage_Power_Term") -> 0 | I11: =SUMIFS(Detail_Simulation!$L:$L, Detail_Simulation!$B:$B, $C11, Detail_Simulation!$D:$D, "Personal_Cash") -> 0 | J11: =SUMIFS(Detail_Simulation!$L:$L, Detail_Simulation!$B:$B, $C11, Detail_Simulation!$D:$D, "MRTA_3_Percent")+ SUMIFS(Detail_Simulation!$L:$L, Detail_Simulation!$B:$B, $C11, Detail_Simulation!$D:$D, "MRTA_6_Percent") -> 0 | K11: =SUMIFS(Detail_Simulation!$L:$L, Detail_Simulation!$B:$B, $C11, Detail_Simulation!$D:$D, "SOMPO") -> 0
B12: 5 | D12: =SUM(E12,F12,G12,H12,I12,J12,K12) -> 0 | E12: =SUMIFS(Detail_Simulation!$L:$L, Detail_Simulation!$B:$B, $C12, Detail_Simulation!$D:$D, "HomeLoan_BT_less_than_2_Percent") -> 0 | F12: =SUMIFS(Detail_Simulation!$L:$L, Detail_Simulation!$B:$B, $C12, Detail_Simulation!$D:$D, "HomeLoan_BT_more_than_2_Percent") -> 0 | G12: =SUMIFS(Detail_Simulation!$L:$L, Detail_Simulation!$B:$B, $C12, Detail_Simulation!$D:$D, "HomeLoan_Non_BT") -> 0 | H12: =SUMIFS(Detail_Simulation!$L:$L, Detail_Simulation!$B:$B, $C12, Detail_Simulation!$D:$D, "Mortgage_Power_Term") -> 0 | I12: =SUMIFS(Detail_Simulation!$L:$L, Detail_Simulation!$B:$B, $C12, Detail_Simulation!$D:$D, "Personal_Cash") -> 0 | J12: =SUMIFS(Detail_Simulation!$L:$L, Detail_Simulation!$B:$B, $C12, Detail_Simulation!$D:$D, "MRTA_3_Percent")+ SUMIFS(Detail_Simulation!$L:$L, Detail_Simulation!$B:$B, $C12, Detail_Simulation!$D:$D, "MRTA_6_Percent") -> 0 | K12: =SUMIFS(Detail_Simulation!$L:$L, Detail_Simulation!$B:$B, $C12, Detail_Simulation!$D:$D, "SOMPO") -> 0
B13: 6 | D13: =SUM(E13,F13,G13,H13,I13,J13,K13) -> 0 | E13: =SUMIFS(Detail_Simulation!$L:$L, Detail_Simulation!$B:$B, $C13, Detail_Simulation!$D:$D, "HomeLoan_BT_less_than_2_Percent") -> 0 | F13: =SUMIFS(Detail_Simulation!$L:$L, Detail_Simulation!$B:$B, $C13, Detail_Simulation!$D:$D, "HomeLoan_BT_more_than_2_Percent") -> 0 | G13: =SUMIFS(Detail_Simulation!$L:$L, Detail_Simulation!$B:$B, $C13, Detail_Simulation!$D:$D, "HomeLoan_Non_BT") -> 0 | H13: =SUMIFS(Detail_Simulation!$L:$L, Detail_Simulation!$B:$B, $C13, Detail_Simulation!$D:$D, "Mortgage_Power_Term") -> 0 | I13: =SUMIFS(Detail_Simulation!$L:$L, Detail_Simulation!$B:$B, $C13, Detail_Simulation!$D:$D, "Personal_Cash") -> 0 | J13: =SUMIFS(Detail_Simulation!$L:$L, Detail_Simulation!$B:$B, $C13, Detail_Simulation!$D:$D, "MRTA_3_Percent")+ SUMIFS(Detail_Simulation!$L:$L, Detail_Simulation!$B:$B, $C13, Detail_Simulation!$D:$D, "MRTA_6_Percent") -> 0 | K13: =SUMIFS(Detail_Simulation!$L:$L, Detail_Simulation!$B:$B, $C13, Detail_Simulation!$D:$D, "SOMPO") -> 0
B14: 7 | D14: =SUM(E14,F14,G14,H14,I14,J14,K14) -> 0 | E14: =SUMIFS(Detail_Simulation!$L:$L, Detail_Simulation!$B:$B, $C14, Detail_Simulation!$D:$D, "HomeLoan_BT_less_than_2_Percent") -> 0 | F14: =SUMIFS(Detail_Simulation!$L:$L, Detail_Simulation!$B:$B, $C14, Detail_Simulation!$D:$D, "HomeLoan_BT_more_than_2_Percent") -> 0 | G14: =SUMIFS(Detail_Simulation!$L:$L, Detail_Simulation!$B:$B, $C14, Detail_Simulation!$D:$D, "HomeLoan_Non_BT") -> 0 | H14: =SUMIFS(Detail_Simulation!$L:$L, Detail_Simulation!$B:$B, $C14, Detail_Simulation!$D:$D, "Mortgage_Power_Term") -> 0 | I14: =SUMIFS(Detail_Simulation!$L:$L, Detail_Simulation!$B:$B, $C14, Detail_Simulation!$D:$D, "Personal_Cash") -> 0 | J14: =SUMIFS(Detail_Simulation!$L:$L, Detail_Simulation!$B:$B, $C14, Detail_Simulation!$D:$D, "MRTA_3_Percent")+ SUMIFS(Detail_Simulation!$L:$L, Detail_Simulation!$B:$B, $C14, Detail_Simulation!$D:$D, "MRTA_6_Percent") -> 0 | K14: =SUMIFS(Detail_Simulation!$L:$L, Detail_Simulation!$B:$B, $C14, Detail_Simulation!$D:$D, "SOMPO") -> 0
B15: 8 | D15: =SUM(E15,F15,G15,H15,I15,J15,K15) -> 0 | E15: =SUMIFS(Detail_Simulation!$L:$L, Detail_Simulation!$B:$B, $C15, Detail_Simulation!$D:$D, "HomeLoan_BT_less_than_2_Percent") -> 0 | F15: =SUMIFS(Detail_Simulation!$L:$L, Detail_Simulation!$B:$B, $C15, Detail_Simulation!$D:$D, "HomeLoan_BT_more_than_2_Percent") -> 0 | G15: =SUMIFS(Detail_Simulation!$L:$L, Detail_Simulation!$B:$B, $C15, Detail_Simulation!$D:$D, "HomeLoan_Non_BT") -> 0 | H15: =SUMIFS(Detail_Simulation!$L:$L, Detail_Simulation!$B:$B, $C15, Detail_Simulation!$D:$D, "Mortgage_Power_Term") -> 0 | I15: =SUMIFS(Detail_Simulation!$L:$L, Detail_Simulation!$B:$B, $C15, Detail_Simulation!$D:$D, "Personal_Cash") -> 0 | J15: =SUMIFS(Detail_Simulation!$L:$L, Detail_Simulation!$B:$B, $C15, Detail_Simulation!$D:$D, "MRTA_3_Percent")+ SUMIFS(Detail_Simulation!$L:$L, Detail_Simulation!$B:$B, $C15, Detail_Simulation!$D:$D, "MRTA_6_Percent") -> 0 | K15: =SUMIFS(Detail_Simulation!$L:$L, Detail_Simulation!$B:$B, $C15, Detail_Simulation!$D:$D, "SOMPO") -> 0
B16: 9 | D16: =SUM(E16,F16,G16,H16,I16,J16,K16) -> 0 | E16: =SUMIFS(Detail_Simulation!$L:$L, Detail_Simulation!$B:$B, $C16, Detail_Simulation!$D:$D, "HomeLoan_BT_less_than_2_Percent") -> 0 | F16: =SUMIFS(Detail_Simulation!$L:$L, Detail_Simulation!$B:$B, $C16, Detail_Simulation!$D:$D, "HomeLoan_BT_more_than_2_Percent") -> 0 | G16: =SUMIFS(Detail_Simulation!$L:$L, Detail_Simulation!$B:$B, $C16, Detail_Simulation!$D:$D, "HomeLoan_Non_BT") -> 0 | H16: =SUMIFS(Detail_Simulation!$L:$L, Detail_Simulation!$B:$B, $C16, Detail_Simulation!$D:$D, "Mortgage_Power_Term") -> 0 | I16: =SUMIFS(Detail_Simulation!$L:$L, Detail_Simulation!$B:$B, $C16, Detail_Simulation!$D:$D, "Personal_Cash") -> 0 | J16: =SUMIFS(Detail_Simulation!$L:$L, Detail_Simulation!$B:$B, $C16, Detail_Simulation!$D:$D, "MRTA_3_Percent")+ SUMIFS(Detail_Simulation!$L:$L, Detail_Simulation!$B:$B, $C16, Detail_Simulation!$D:$D, "MRTA_6_Percent") -> 0 | K16: =SUMIFS(Detail_Simulation!$L:$L, Detail_Simulation!$B:$B, $C16, Detail_Simulation!$D:$D, "SOMPO") -> 0
B17: 10 | D17: =SUM(E17,F17,G17,H17,I17,J17,K17) -> 0 | E17: =SUMIFS(Detail_Simulation!$L:$L, Detail_Simulation!$B:$B, $C17, Detail_Simulation!$D:$D, "HomeLoan_BT_less_than_2_Percent") -> 0 | F17: =SUMIFS(Detail_Simulation!$L:$L, Detail_Simulation!$B:$B, $C17, Detail_Simulation!$D:$D, "HomeLoan_BT_more_than_2_Percent") -> 0 | G17: =SUMIFS(Detail_Simulation!$L:$L, Detail_Simulation!$B:$B, $C17, Detail_Simulation!$D:$D, "HomeLoan_Non_BT") -> 0 | H17: =SUMIFS(Detail_Simulation!$L:$L, Detail_Simulation!$B:$B, $C17, Detail_Simulation!$D:$D, "Mortgage_Power_Term") -> 0 | I17: =SUMIFS(Detail_Simulation!$L:$L, Detail_Simulation!$B:$B, $C17, Detail_Simulation!$D:$D, "Personal_Cash") -> 0 | J17: =SUMIFS(Detail_Simulation!$L:$L, Detail_Simulation!$B:$B, $C17, Detail_Simulation!$D:$D, "MRTA_3_Percent")+ SUMIFS(Detail_Simulation!$L:$L, Detail_Simulation!$B:$B, $C17, Detail_Simulation!$D:$D, "MRTA_6_Percent") -> 0 | K17: =SUMIFS(Detail_Simulation!$L:$L, Detail_Simulation!$B:$B, $C17, Detail_Simulation!$D:$D, "SOMPO") -> 0
B18: 11 | D18: =SUM(E18,F18,G18,H18,I18,J18,K18) -> 0 | E18: =SUMIFS(Detail_Simulation!$L:$L, Detail_Simulation!$B:$B, $C18, Detail_Simulation!$D:$D, "HomeLoan_BT_less_than_2_Percent") -> 0 | F18: =SUMIFS(Detail_Simulation!$L:$L, Detail_Simulation!$B:$B, $C18, Detail_Simulation!$D:$D, "HomeLoan_BT_more_than_2_Percent") -> 0 | G18: =SUMIFS(Detail_Simulation!$L:$L, Detail_Simulation!$B:$B, $C18, Detail_Simulation!$D:$D, "HomeLoan_Non_BT") -> 0 | H18: =SUMIFS(Detail_Simulation!$L:$L, Detail_Simulation!$B:$B, $C18, Detail_Simulation!$D:$D, "Mortgage_Power_Term") -> 0 | I18: =SUMIFS(Detail_Simulation!$L:$L, Detail_Simulation!$B:$B, $C18, Detail_Simulation!$D:$D, "Personal_Cash") -> 0 | J18: =SUMIFS(Detail_Simulation!$L:$L, Detail_Simulation!$B:$B, $C18, Detail_Simulation!$D:$D, "MRTA_3_Percent")+ SUMIFS(Detail_Simulation!$L:$L, Detail_Simulation!$B:$B, $C18, Detail_Simulation!$D:$D, "MRTA_6_Percent") -> 0 | K18: =SUMIFS(Detail_Simulation!$L:$L, Detail_Simulation!$B:$B, $C18, Detail_Simulation!$D:$D, "SOMPO") -> 0
B19: 12 | D19: =SUM(E19,F19,G19,H19,I19,J19,K19) -> 0 | E19: =SUMIFS(Detail_Simulation!$L:$L, Detail_Simulation!$B:$B, $C19, Detail_Simulation!$D:$D, "HomeLoan_BT_less_than_2_Percent") -> 0 | F19: =SUMIFS(Detail_Simulation!$L:$L, Detail_Simulation!$B:$B, $C19, Detail_Simulation!$D:$D, "HomeLoan_BT_more_than_2_Percent") -> 0 | G19: =SUMIFS(Detail_Simulation!$L:$L, Detail_Simulation!$B:$B, $C19, Detail_Simulation!$D:$D, "HomeLoan_Non_BT") -> 0 | H19: =SUMIFS(Detail_Simulation!$L:$L, Detail_Simulation!$B:$B, $C19, Detail_Simulation!$D:$D, "Mortgage_Power_Term") -> 0 | I19: =SUMIFS(Detail_Simulation!$L:$L, Detail_Simulation!$B:$B, $C19, Detail_Simulation!$D:$D, "Personal_Cash") -> 0 | J19: =SUMIFS(Detail_Simulation!$L:$L, Detail_Simulation!$B:$B, $C19, Detail_Simulation!$D:$D, "MRTA_3_Percent")+ SUMIFS(Detail_Simulation!$L:$L, Detail_Simulation!$B:$B, $C19, Detail_Simulation!$D:$D, "MRTA_6_Percent") -> 0 | K19: =SUMIFS(Detail_Simulation!$L:$L, Detail_Simulation!$B:$B, $C19, Detail_Simulation!$D:$D, "SOMPO") -> 0
B20: 13 | D20: =SUM(E20,F20,G20,H20,I20,J20,K20) -> 0 | E20: =SUMIFS(Detail_Simulation!$L:$L, Detail_Simulation!$B:$B, $C20, Detail_Simulation!$D:$D, "HomeLoan_BT_less_than_2_Percent") -> 0 | F20: =SUMIFS(Detail_Simulation!$L:$L, Detail_Simulation!$B:$B, $C20, Detail_Simulation!$D:$D, "HomeLoan_BT_more_than_2_Percent") -> 0 | G20: =SUMIFS(Detail_Simulation!$L:$L, Detail_Simulation!$B:$B, $C20, Detail_Simulation!$D:$D, "HomeLoan_Non_BT") -> 0 | H20: =SUMIFS(Detail_Simulation!$L:$L, Detail_Simulation!$B:$B, $C20, Detail_Simulation!$D:$D, "Mortgage_Power_Term") -> 0 | I20: =SUMIFS(Detail_Simulation!$L:$L, Detail_Simulation!$B:$B, $C20, Detail_Simulation!$D:$D, "Personal_Cash") -> 0 | J20: =SUMIFS(Detail_Simulation!$L:$L, Detail_Simulation!$B:$B, $C20, Detail_Simulation!$D:$D, "MRTA_3_Percent")+ SUMIFS(Detail_Simulation!$L:$L, Detail_Simulation!$B:$B, $C20, Detail_Simulation!$D:$D, "MRTA_6_Percent") -> 0 | K20: =SUMIFS(Detail_Simulation!$L:$L, Detail_Simulation!$B:$B, $C20, Detail_Simulation!$D:$D, "SOMPO") -> 0
B21: 14 | D21: =SUM(E21,F21,G21,H21,I21,J21,K21) -> 0 | E21: =SUMIFS(Detail_Simulation!$L:$L, Detail_Simulation!$B:$B, $C21, Detail_Simulation!$D:$D, "HomeLoan_BT_less_than_2_Percent") -> 0 | F21: =SUMIFS(Detail_Simulation!$L:$L, Detail_Simulation!$B:$B, $C21, Detail_Simulation!$D:$D, "HomeLoan_BT_more_than_2_Percent") -> 0 | G21: =SUMIFS(Detail_Simulation!$L:$L, Detail_Simulation!$B:$B, $C21, Detail_Simulation!$D:$D, "HomeLoan_Non_BT") -> 0 | H21: =SUMIFS(Detail_Simulation!$L:$L, Detail_Simulation!$B:$B, $C21, Detail_Simulation!$D:$D, "Mortgage_Power_Term") -> 0 | I21: =SUMIFS(Detail_Simulation!$L:$L, Detail_Simulation!$B:$B, $C21, Detail_Simulation!$D:$D, "Personal_Cash") -> 0 | J21: =SUMIFS(Detail_Simulation!$L:$L, Detail_Simulation!$B:$B, $C21, Detail_Simulation!$D:$D, "MRTA_3_Percent")+ SUMIFS(Detail_Simulation!$L:$L, Detail_Simulation!$B:$B, $C21, Detail_Simulation!$D:$D, "MRTA_6_Percent") -> 0 | K21: =SUMIFS(Detail_Simulation!$L:$L, Detail_Simulation!$B:$B, $C21, Detail_Simulation!$D:$D, "SOMPO") -> 0
B22: 15 | D22: =SUM(E22,F22,G22,H22,I22,J22,K22) -> 0 | E22: =SUMIFS(Detail_Simulation!$L:$L, Detail_Simulation!$B:$B, $C22, Detail_Simulation!$D:$D, "HomeLoan_BT_less_than_2_Percent") -> 0 | F22: =SUMIFS(Detail_Simulation!$L:$L, Detail_Simulation!$B:$B, $C22, Detail_Simulation!$D:$D, "HomeLoan_BT_more_than_2_Percent") -> 0 | G22: =SUMIFS(Detail_Simulation!$L:$L, Detail_Simulation!$B:$B, $C22, Detail_Simulation!$D:$D, "HomeLoan_Non_BT") -> 0 | H22: =SUMIFS(Detail_Simulation!$L:$L, Detail_Simulation!$B:$B, $C22, Detail_Simulation!$D:$D, "Mortgage_Power_Term") -> 0 | I22: =SUMIFS(Detail_Simulation!$L:$L, Detail_Simulation!$B:$B, $C22, Detail_Simulation!$D:$D, "Personal_Cash") -> 0 | J22: =SUMIFS(Detail_Simulation!$L:$L, Detail_Simulation!$B:$B, $C22, Detail_Simulation!$D:$D, "MRTA_3_Percent")+ SUMIFS(Detail_Simulation!$L:$L, Detail_Simulation!$B:$B, $C22, Detail_Simulation!$D:$D, "MRTA_6_Percent") -> 0 | K22: =SUMIFS(Detail_Simulation!$L:$L, Detail_Simulation!$B:$B, $C22, Detail_Simulation!$D:$D, "SOMPO") -> 0
... B41: 34 | D41: =SUM(E41,F41,G41,H41,I41,J41,K41) -> 0 | E41: =SUMIFS(Detail_Simulation!$L:$L, Detail_Simulation!$B:$B, $C41, Detail_Simulation!$D:$D, "HomeLoan_BT_less_than_2_Percent") -> 0 | F41: =SUMIFS(Detail_Simulation!$L:$L, Detail_Simulation!$B:$B, $C41, Detail_Simulation!$D:$D, "HomeLoan_BT_more_than_2_Percent") -> 0 | G41: =SUMIFS(Detail_Simulation!$L:$L, Detail_Simulation!$B:$B, $C41, Detail_Simulation!$D:$D, "HomeLoan_Non_BT") -> 0 | H41: =SUMIFS(Detail_Simulation!$L:$L, Detail_Simulation!$B:$B, $C41, Detail_Simulation!$D:$D, "Mortgage_Power_Term") -> 0 | I41: =SUMIFS(Detail_Simulation!$L:$L, Detail_Simulation!$B:$B, $C41, Detail_Simulation!$D:$D, "Personal_Cash") -> 0 | J41: =SUMIFS(Detail_Simulation!$L:$L, Detail_Simulation!$B:$B, $C41, Detail_Simulation!$D:$D, "MRTA_3_Percent")+ SUMIFS(Detail_Simulation!$L:$L, Detail_Simulation!$B:$B, $C41, Detail_Simulation!$D:$D, "MRTA_6_Percent") -> 0 | K41: =SUMIFS(Detail_Simulation!$L:$L, Detail_Simulation!$B:$B, $C41, Detail_Simulation!$D:$D, "SOMPO") -> 0

Sheet Secured_Commission
A1: Drawdown | B1: HomeLoan_BT_less_than_2_Percent | C1: HomeLoan_BT_more_than_2_Percent | D1: HomeLoan_Non_BT | E1: Mortgage_Power_Term | F1: Tier
A2: 0.1 | B2: 1400 | C2: 2000 | D2: 2400 | E2: 5000 | F2: ≤ 3 mb
A3: 3000001 | B3: 1750 | C3: 2500 | D3: 3000 | E3: 5000 | F3: > 3 – 6 mb
A4: 6000001 | B4: 2100 | C4: 3000 | D4: 3600 | E4: 5000 | F4: > 6 – 8 mb
A5: 8000001 | B5: 2600 | C5: 3700 | D5: 4400 | E5: 5000 | F5: > 8 – 12 mb
A6: 12000001 | B6: 2800 | C6: 4000 | D6: 4800 | E6: 5000 | F6: > 12 mb

Sheet Unsecured_Commission
A1: Personal Cash Drawdown Amt | B1: %Comm
A2: 0 | B2: 0
A3: 1000 | B3: 0.02
A4: 600000 | B4: 0.023
A5: 800000 | B5: 0.029
A6: 1300000 | B6: 0.033
A7: 2000000 | B7: 0.0345

Sheet Sales_Agent_info
A1: ลำดับ | B1: รหัส | C1: คำนำหน้า | D1: ชื่อ | E1: สกุล | F1: Status | G1: Status New | H1: Join Date | I1: Code Team | J1: Channel 2 digit | K1: Channel | L1: ID | M1: Bank Account | N1: Zone | O1: Team Manager | P1: รหัสพนักงาน Agent Lead | Q1: Agent Lead Name_ Surname_Sales | R1: รหัสพนักงาน Team Manager | S1: Team Manager Name_ Surname_Sales | T1: รหัสพนักงาน Team Leader | U1: Team Leader Name_ Surname_Sales | V1: รหัสพนักงาน Head | W1: Head Surname_Sales | X1: วันที่Adminรับบัตร | Y1: ชื่อ-สกุล Sales | Z1: Check status | AA1: Code_Team_Dropdown
A2: 1 | B2: 2010607 | C2: นางสาว | D2: วราภรณ์ | E2: รัฐฐานนท์ | F2: TM | I2: DS1-1/1 | J2: DS1 | K2: Direct Sales 1 | N2: BKK | O2: DS1-1/1 | P2: - | Q2: - | R2: 2010607 | S2: Waraporn Rattanon | T2: 2019804 | U2: Patpoom Poompij | V2: 2013757 | W2: Saruda Chaloemjan | Y2: วราภรณ์ รัฐฐานนท์ | Z2: Active | AA2: DS1_1_1
A3: 2 | B3: 2020440 | C3: นางสาว | D3: พชร | E3: พิมพ์ประสานต์ | F3: TM | I3: DS1-1/2 | J3: DS1 | K3: Direct Sales 1 | N3: BKK | O3: DS1-1/2 | P3: - | Q3: - | R3: 2020440 | S3: Pachara Phimprasant | T3: 2019804 | U3: Patpoom Poompij | V3: 2013757 | W3: Saruda Chaloemjan | Y3: พชร พิมพ์ประสานต์ | Z3: Active | AA3: DS1_1_2
A4: 3 | B4: 2020799 | C4: นาย | D4: ดลพล | E4: รชตะพฤกษา | F4: TM | I4: DS1-1/3 | J4: DS1 | K4: Direct Sales 1 | N4: BKK | O4: DS1-1/3 | P4: - | Q4: - | R4: 2020799 | S4: Dollapol Rachatapueksa | T4: 2019804 | U4: Patpoom Poompij | V4: 2013757 | W4: Saruda Chaloemjan | Y4: ดลพล รชตะพฤกษา | Z4: Active | AA4: DS1_1_3
A5: 4 | B5: 2020911 | C5: นาย | D5: มาโนช | E5: วิพัฒน์พงค์ | F5: TM | I5: DS1-1/4 | J5: DS1 | K5: Direct Sales 1 | N5: BKK | O5: DS1-1/4 | P5: - | Q5: - | R5: 2020911 | S5: Manoch Wiphatpong | T5: 2019804 | U5: Patpoom Poompij | V5: 2013757 | W5: Saruda Chaloemjan | Y5: มาโนช วิพัฒน์พงค์ | Z5: Active | AA5: DS1_1_4
A6: 5 | B6: 2020887 | C6: นาย | D6: ชัยธนวัฒน์ | E6: วงศ์ซื่อ | F6: TM | I6: DS1-2/1 | J6: DS1 | K6: Direct Sales 1 | N6: BKK | O6: DS1-2/1 | P6: - | Q6: - | R6: 2020887 | S6: Chaitanawat Wongcue | T6: 2015674 | U6: Dacha Jandaket | V6: 2013757 | W6: Saruda Chaloemjan | Y6: ชัยธนวัฒน์ วงศ์ซื่อ | Z6: Active | AA6: DS1_2_1
A7: 6 | B7: 5300754 | C7: นางสาว | D7: อัญรินทร์ | E7: กีรติอักษรวัชร์ | F7: TM | H7: 43787 | I7: DS1-2/2 | J7: DS1 | K7: Direct Sales 1 | N7: BKK | O7: DS1-2/2 | P7: - | Q7: - | R7: 5300754 | S7: Aunyarin Keeratiauksornwat | T7: 2015674 | U7: Dacha Jandaket | V7: 2013757 | W7: Saruda Chaloemjan | Y7: อัญรินทร์ กีรติอักษรวัชร์ | Z7: Active | AA7: DS1_2_2
A8: 7 | B8: 5349609 | C8: นางสาว | D8: เบญจวรรณ | E8: เทียนดำ | F8: TM | I8: DS1-2/3 | J8: DS1 | K8: Direct Sales 1 | N8: BKK | O8: DS1-2/3 | P8: - | Q8: - | R8: 5349609 | S8: Benjawan Teandam | T8: 2015674 | U8: Dacha Jandaket | V8: 2013757 | W8: Saruda Chaloemjan | Y8: เบญจวรรณ เทียนดำ | Z8: Active | AA8: DS1_2_3
A9: 8 | B9: 5421894 | C9: นางสาว | D9: กาญจน์สิตา | E9: ของกิ่ง | F9: TM | H9: 45718 | I9: DS1-2/4 | J9: DS1 | K9: Direct Sales 1 | N9: BKK | O9: DS1-2/4 | P9: - | Q9: - | R9: 5421894 | S9: Kansita Khongking | T9: 2015674 | U9: Dacha Jandaket | V9: 2013757 | W9: Saruda Chaloemjan | Y9: กาญจน์สิตา ของกิ่ง | Z9: Active | AA9: DS1_2_4
A10: 9 | B10: 2017843 | C10: นาย | D10: ชาชณะ | E10: รัตนกิตตินัน | F10: TM | I10: DS1-3/1 | J10: DS1 | K10: Direct Sales 1 | N10: BKK | O10: DS1-3/1 | P10: - | Q10: - | R10: 2017843 | S10: Chachana Rattanakittinun | T10: 2016654 | U10: Weerakit Keeratichaitam | V10: 2013757 | W10: Saruda Chaloemjan | Y10: ชาชณะ รัตนกิตตินัน | Z10: Active | AA10: DS1_3_1
A11: 10 | B11: 2017884 | C11: นาย | D11: สายัณห์ | E11: โกมัย | F11: TM | I11: DS1-3/2 | J11: DS1 | K11: Direct Sales 1 | N11: PVA | O11: DS1-3/2 | P11: - | Q11: - | R11: 2017884 | S11: Sayun Komai | T11: 2016654 | U11: Weerakit Keeratichaitam | V11: 2013757 | W11: Saruda Chaloemjan | Y11: สายัณห์ โกมัย | Z11: Active | AA11: DS1_3_2
A12: 11 | B12: 2018033 | C12: นางสาว | D12: นวรัตน์ | E12: แหทอง | F12: TM | H12: 42681 | I12: DS1-3/3 | J12: DS1 | K12: Direct Sales 1 | N12: BKK | O12: DS1-3/3 | P12: - | Q12: - | R12: 2018033 | S12: Nawarat Hae-tong | T12: 2016654 | U12: Weerakit Keeratichaitam | V12: 2013757 | W12: Saruda Chaloemjan | Y12: นวรัตน์ แหทอง | Z12: Active | AA12: DS1_3_3
A13: 12 | B13: 2020624 | C13: นาย | D13: ทิวากร | E13: วงษ์ลุน | F13: TM | H13: 43556 | I13: DS1-3/4 | J13: DS1 | K13: Direct Sales 1 | N13: BKK | O13: DS1-3/4 | P13: - | Q13: - | R13: 2020624 | S13: Tivakon Wonglun | T13: 2016654 | U13: Weerakit Keeratichaitam | V13: 2013757 | W13: Saruda Chaloemjan | Y13: ทิวากร วงษ์ลุน | Z13: Active | AA13: DS1_3_4
A14: 13 | B14: 2017137 | C14: นาย | D14: ชยกฤต | E14: ลำเทียน | F14: TM | I14: DS1-4/1 | J14: DS1 | K14: Direct Sales 1 | N14: PVA | O14: DS1-4/1 | P14: - | Q14: - | R14: 2017137 | S14: Chayakrit Lumtien | T14: 2019567 | U14: Peemphat Panprommin | V14: 2013757 | W14: Saruda Chaloemjan | Y14: ชยกฤต ลำเทียน | Z14: Active | AA14: DS1_4_1
A15: 14 | B15: 2020497 | C15: นาย | D15: วีรพงษ์ | E15: ลังกาวงค์ | F15: TM | I15: DS1-4/2 | J15: DS1 | K15: Direct Sales 1 | N15: PVA | O15: DS1-4/2 | P15: - | Q15: - | R15: 2020497 | S15: Weeraphong Lungkawong | T15: 2019567 | U15: Peemphat Panprommin | V15: 2013757 | W15: Saruda Chaloemjan | Y15: วีรพงษ์ ลังกาวงค์ | Z15: Active | AA15: DS1_4_2
A16: 15 | B16: 5349231 | C16: นาย | D16: พชร | E16: แสงสร้อย | F16: TM | H16: 44440 | I16: DS1-4/3 | J16: DS1 | K16: Direct Sales 1 | N16: BKK | O16: DS1-4/3 | P16: - | Q16: - | R16: 5349231 | S16: Phatchara Sangsroi | T16: 2019567 | U16: Peemphat Panprommin | V16: 2013757 | W16: Saruda Chaloemjan | Y16: พชร แสงสร้อย | Z16: Active | AA16: DS1_4_3
A17: 16 | B17: 5422177 | C17: นาย | D17: อัครินทร์ | E17: ลำพุทธา | F17: TM | H17: 45719 | I17: DS1-4/4 | J17: DS1 | K17: Direct Sales 1 | N17: BKK | O17: DS1-4/4 | P17: - | Q17: - | R17: 5422177 | S17: Akarin Lamphuttha | T17: 2019567 | U17: Peemphat Panprommin | V17: 2013757 | W17: Saruda Chaloemjan | Y17: อัครินทร์ ลำพุทธา | Z17: Active | AA17: DS1_4_4
A18: 17 | B18: 2014504 | C18: นางสาว | D18: อาภารัศมิ์ | E18: พิชยวัฒน์เดชากุล | F18: TM | I18: DS1-5/1 | J18: DS1 | K18: Direct Sales 1 | N18: PVA | O18: DS1-5/1 | P18: - | Q18: - | R18: 2014504 | S18: Arbharus Pichayawatdhachakul | T18: 2019655 | U18: Kittichet Phattanajiranon | V18: 2013757 | W18: Saruda Chaloemjan | Y18: อาภารัศมิ์ พิชยวัฒน์เดชากุล | Z18: Active | AA18: DS1_5_1
A19: 18 | B19: 2020314 | C19: นางสาว | D19: สามิตรี | E19: สมินเย | F19: TM | I19: DS1-5/2 | J19: DS1 | K19: Direct Sales 1 | N19: PVA | O19: DS1-5/2 | P19: - | Q19: - | R19: 2020314 | S19: Samittree Saminye | T19: 2019655 | U19: Kittichet Phattanajiranon | V19: 2013757 | W19: Saruda Chaloemjan | Y19: สามิตรี สมินเย | Z19: Active | AA19: DS1_5_2
A20: 19 | B20: 2020309 | C20: นาย | D20: ปวินทร์ฉัตร์ | E20: พุ่มระย้า | F20: TM | I20: DS1-5/3 | J20: DS1 | K20: Direct Sales 1 | N20: PVA | O20: DS1-5/3 | P20: - | Q20: - | R20: 2020309 | S20: Pawinchat Pumraya | T20: 2019655 | U20: Kittichet Phattanajiranon | V20: 2013757 | W20: Saruda Chaloemjan | Y20: ปวินทร์ฉัตร์ พุ่มระย้า | Z20: Active | AA20: DS1_5_3
A21: 20 | B21: 5424797 | C21: นาย | D21: พรเทพ | E21: ผิวเผื่อน | F21: TM | H21: 45779 | I21: DS1-5/4 | J21: DS1 | K21: Direct Sales 1 | N21: PVA | O21: DS1-5/4 | P21: - | Q21: - | R21: 5424797 | S21: Pornthap Piwpuan | T21: 2019655 | U21: Kittichet Phattanajiranon | V21: 2013757 | W21: Saruda Chaloemjan | Y21: พรเทพ ผิวเผื่อน | Z21: Active | AA21: DS1_5_4
A22: 21 | B22: 2014899 | C22: นาย | D22: ณัฐปภัสร์ | E22: เอนกวศินชัย | F22: TM | I22: DS1-6/1 | J22: DS1 | K22: Direct Sales 1 | N22: PVA | O22: DS1-6/1 | P22: - | Q22: - | R22: 2014899 | S22: Natpaphat Anakvasinchai | T22: 2018414 | U22: Narabodee Srisuphap | V22: 2013757 | W22: Saruda Chaloemjan | Y22: ณัฐปภัสร์ เอนกวศินชัย | Z22: Active | AA22: DS1_6_1
A23: 22 | B23: 2020310 | C23: นางสาว | D23: อมลวรรณ | E23: โตสงค์ | F23: TM | I23: DS1-6/2 | J23: DS1 | K23: Direct Sales 1 | N23: PVA | O23: DS1-6/2 | P23: - | Q23: - | R23: 2020310 | S23: Amonwan Tosong | T23: 2018414 | U23: Narabodee Srisuphap | V23: 2013757 | W23: Saruda Chaloemjan | Y23: อมลวรรณ โตสงค์ | Z23: Active | AA23: DS1_6_2
A24: 23 | B24: 5397723 | C24: นางสาว | D24: นริศรา | E24: ใจเสือกุล | F24: TM | H24: 45201 | I24: DS1-6/3 | J24: DS1 | K24: Direct Sales 1 | N24: PVA | O24: DS1-6/3 | P24: - | Q24: - | R24: 5397723 | S24: Narisara Jaisueakun | T24: 2018414 | U24: Narabodee Srisuphap | V24: 2013757 | W24: Saruda Chaloemjan | Y24: นริศรา ใจเสือกุล | Z24: Active | AA24: DS1_6_3
A25: 24 | B25: 5429310 | C25: นาย | D25: ณัฐพล | E25: สุกใส | F25: TM | H25: 45931 | I25: DS1-6/4 | J25: DS1 | K25: Direct Sales 1 | N25: PVA | O25: DS1-6/4 | P25: - | Q25: - | R25: 5429310 | S25: Nuttapon Suksai | T25: 2018414 | U25: Narabodee Srisuphap | V25: 2013757 | W25: Saruda Chaloemjan | Y25: ณัฐพล สุกใส | Z25: Active | AA25: DS1_6_4
A26: 25 | B26: 2018437 | C26: นางสาว | D26: พิมพ์ณัฐชญา | E26: อยู่ญาติมาก | F26: TM | H26: 43601 | I26: DS2-1/1 | J26: DS2 | K26: Direct Sales 2 | N26: BKK | O26: DS2-1/1 | P26: - | Q26: - | R26: 2018437 | S26: Pimnutchaya Youyatmak | T26: 2008274 | U26: Kataree Sudhasawin | V26: 2014180 | W26: Wichian Tanyawong | Y26: พิมพ์ณัฐชญา อยู่ญาติมาก | Z26: Active | AA26: DS2_1_1
A27: 26 | B27: 2020598 | C27: นางสาว | D27: นันท์ณรัตน์ | E27: วิลัยศรี | F27: TM | H27: 43556 | I27: DS2-5/2 | J27: DS2 | K27: Direct Sales 2 | N27: BKK | O27: DS2-5/2 | P27: - | Q27: - | R27: 2020598 | S27: Nunnarat Vilaisri | T27: 2009365 | U27: Phakin Thanakwinchok | V27: 2014180 | W27: Wichian Tanyawong | Y27: นันท์ณรัตน์ วิลัยศรี | Z27: Active | AA27: DS2_5_2
A28: 27 | B28: 2019298 | C28: นางสาว | D28: อรวรรณ | E28: บุนนาค | F28: TM | H28: 43175 | I28: DS2-1/2 | J28: DS2 | K28: Direct Sales 2 | N28: BKK | O28: DS2-1/2 | P28: - | Q28: - | R28: 2019298 | S28: Oravan Boonnak | T28: 2008274 | U28: Kataree Sudhasawin | V28: 2014180 | W28: Wichian Tanyawong | Y28: อรวรรณ บุนนาค | Z28: Active | AA28: DS2_1_2
A29: 28 | B29: 2019243 | C29: นาย | D29: ไพโรจน์ | E29: พลเยี่ยม | F29: TM | H29: 43161 | I29: DS2-1/5 | J29: DS2 | K29: Direct Sales 2 | N29: PVA | O29: DS2-1/5 | P29: - | Q29: - | R29: 2019243 | S29: Phairoj Ponyiem | T29: 2008274 | U29: Kataree Sudhasawin | V29: 2014180 | W29: Wichian Tanyawong | Y29: ไพโรจน์ พลเยี่ยม | Z29: Active | AA29: DS2_1_5
A30: 29 | B30: 2013948 | C30: นาย | D30: ศุภชัย | E30: มากอุสาห์ | F30: TM | H30: 43862 | I30: DS2-4/5 | J30: DS2 | K30: Direct Sales 2 | N30: PVA | O30: DS2-4/5 | P30: - | Q30: - | R30: 2013948 | S30: Suppachai Markusa | T30: 2013471 | U30: Piyawan Treecharoen | V30: 2014180 | W30: Wichian Tanyawong | Y30: ศุภชัย มากอุสาห์ | Z30: Active | AA30: DS2_4_5
A31: 30 | B31: 2015066 | C31: นางสาว | D31: ชัญญกัลย์ | E31: อุดมลาภ | F31: TM | H31: 43862 | I31: DS2-1/3 | J31: DS2 | K31: Direct Sales 2 | N31: BKK | O31: DS2-1/3 | P31: - | Q31: - | R31: 2015066 | S31: Chanyakhal Udomlarp | T31: 2008274 | U31: Kataree Sudhasawin | V31: 2014180 | W31: Wichian Tanyawong | Y31: ชัญญกัลย์ อุดมลาภ | Z31: Active | AA31: DS2_1_3
A32: 31 | B32: 2010212 | C32: นาย | D32: ประทีป | E32: แซ่โจ้ง | F32: TM | H32: 42370 | I32: DS2-1/4 | J32: DS2 | K32: Direct Sales 2 | N32: PVA | O32: DS2-1/4 | P32: - | Q32: - | R32: 2010212 | S32: Prateep Saejong | T32: 2008274 | U32: Kataree Sudhasawin | V32: 2014180 | W32: Wichian Tanyawong | Y32: ประทีป แซ่โจ้ง | Z32: Active | AA32: DS2_1_4
A33: 32 | B33: 5404943 | C33: นางสาว | D33: สมลักษณ์ | E33: โพธิศา | F33: TM | H33: 45369 | I33: DS2-5/3 | J33: DS2 | K33: Direct Sales 2 | N33: PVA | O33: DS2-5/3 | P33: - | Q33: - | R33: 5404943 | S33: Somlak Potisa | T33: 2009365 | U33: Phakin Thanakwinchok | V33: 2014180 | W33: Wichian Tanyawong | Y33: สมลักษณ์ โพธิศา | Z33: Active | AA33: DS2_5_3
A34: 33 | B34: 5304046 | C34: นางสาว | D34: สิริกัญจน์ | E34: พันธ์บูรณานนท์ | F34: TM | H34: 43739 | I34: DS2-2/1 | J34: DS2 | K34: Direct Sales 2 | N34: BKK | O34: DS2-2/1 | P34: - | Q34: - | R34: 5304046 | S34: Sirikan Phanburananont | T34: 2018025 | U34: Kitiyaphorn Rakyos | V34: 2014180 | W34: Wichian Tanyawong | Y34: สิริกัญจน์ พันธ์บูรณานนท์ | Z34: Active | AA34: DS2_2_1
A35: 34 | B35: 5362157 | C35: นางสาว | D35: ชัญญาภัค | E35: ฟูอินต๊ะ | F35: TM | H35: 44578 | I35: DS2-2/2 | J35: DS2 | K35: Direct Sales 2 | N35: BKK | O35: DS2-2/2 | P35: - | Q35: - | R35: 5362157 | S35: Chanyaphak Fuinta | T35: 2018025 | U35: Kitiyaphorn Rakyos | V35: 2014180 | W35: Wichian Tanyawong | Y35: ชัญญาภัค ฟูอินต๊ะ | Z35: Active | AA35: DS2_2_2
... A50: 49 | B50: 5392829 | C50: นางสาว | D50: ญาณิน | E50: ศาลารักษ์ | F50: TM | H50: 45124 | I50: DS2-5/5 | J50: DS2 | K50: Direct Sales 2 | N50: PVA | O50: DS2-5/5 | P50: - | Q50: - | R50: 5392829 | S50: Yanin Salarak | T50: 2009365 | U50: Phakin Thanakwinchok | V50: 2014180 | W50: Wichian Tanyawong | Y50: ญาณิน ศาลารักษ์ | Z50: Active | AA50: DS2_5_5
A51: 66 | B51: 6560465 | C51: นาย | D51: เอกรัฐ | E51: ประสานสุข | F51: Sales | H51: 41858 | I51: DS1-4/1 | J51: DS1 | K51: Direct Sales 1 | L51: 3500900664738 | M51: 7006473490 | N51: PVA | O51: DS1-4/1 | P51: - | Q51: - | R51: 2017137 | S51: Chayakrit Lumtien | T51: 2019567 | U51: Peemphat Panprommin | V51: 2013757 | W51: Saruda Chaloemjan | X51: 45147 | Y51: เอกรัฐ ประสานสุข | Z51: Active | AA51: DS1_4_1
A52: 73 | B52: 6560471 | C52: นางสาว | D52: บุณฑริกา | E52: บุญมูล | F52: Sales | H52: 42251 | I52: DS1-4/1 | J52: DS1 | K52: Direct Sales 1 | L52: 1509900520614 | M52: 7007759255 | N52: PVA | O52: DS1-4/1 | P52: - | Q52: - | R52: 2017137 | S52: Chayakrit Lumtien | T52: 2019567 | U52: Peemphat Panprommin | V52: 2013757 | W52: Saruda Chaloemjan | X52: 45147 | Y52: บุณฑริกา บุญมูล | Z52: Active | AA52: DS1_4_1
A53: 74 | B53: 6560369 | C53: นางสาว | D53: ณัฐฐิกา | E53: อักษรนิตย์ | F53: Sales | H53: 42261 | I53: DS1-2/1 | J53: DS1 | K53: Direct Sales 1 | L53: 1103700389644 | M53: 7007767216 | N53: BKK | O53: DS1-2/1 | P53: - | Q53: - | R53: 2020887 | S53: Chaitanawat Wongcue | T53: 2015674 | U53: Dacha Jandaket | V53: 2013757 | W53: Saruda Chaloemjan | X53: 45119 | Y53: ณัฐฐิกา อักษรนิตย์ | Z53: Active | AA53: DS1_2_1
A54: 78 | B54: 6560475 | C54: นาย | D54: ฐณธรณ์ | E54: อาริยะ | F54: Sales | H54: 42921 | I54: DS1-4/1 | J54: DS1 | K54: Direct Sales 1 | L54: 3510100891641 | M54: 7009684149 | N54: PVA | O54: DS1-4/1 | P54: - | Q54: - | R54: 2017137 | S54: Chayakrit Lumtien | T54: 2019567 | U54: Peemphat Panprommin | V54: 2013757 | W54: Saruda Chaloemjan | X54: 45147 | Y54: ฐณธรณ์ อาริยะ | Z54: Active | AA54: DS1_4_1
A55: 82 | B55: 6560385 | C55: นางสาว | D55: ขนิษฐา | E55: จันทร์บัว | F55: Sales | H55: 43140 | I55: DS1-1/1 | J55: DS1 | K55: Direct Sales 1 | L55: 5660500005180 | M55: 7010000941 | N55: BKK | O55: DS1-1/1 | P55: - | Q55: - | R55: 2010607 | S55: Waraporn Rattanon | T55: 2019804 | U55: Patpoom Poompij | V55: 2013757 | W55: Saruda Chaloemjan | X55: 45118 | Y55: ขนิษฐา จันทร์บัว | Z55: Active | AA55: DS1_1_1
A56: 84 | B56: 6560479 | C56: นางสาว | D56: สุนิสา | E56: สมัครกิจ | F56: Sales | H56: 43229 | I56: DS1-3/2 | J56: DS1 | K56: Direct Sales 1 | L56: 1820400010179 | M56: 7010106106 | N56: PVA | O56: DS1-3/2 | P56: - | Q56: - | R56: 2017884 | S56: Sayun Komai | T56: 2016654 | U56: Weerakit Keeratichaitam | V56: 2013757 | W56: Saruda Chaloemjan | X56: 45128 | Y56: สุนิสา สมัครกิจ | Z56: Active | AA56: DS1_3_2
A57: 85 | B57: 6560395 | C57: นางสาว | D57: ละอองฝน | E57: อ่อมให้ | F57: Sales | H57: 43244 | I57: DS1-1/1 | J57: DS1 | K57: Direct Sales 1 | L57: 3760300004166 | M57: 7009646139 | N57: BKK | O57: DS1-1/1 | P57: - | Q57: - | R57: 2010607 | S57: Waraporn Rattanon | T57: 2019804 | U57: Patpoom Poompij | V57: 2013757 | W57: Saruda Chaloemjan | X57: 45118 | Y57: ละอองฝน อ่อมให้ | Z57: Active | AA57: DS1_1_1
A58: 86 | B58: 6560330 | C58: นาย | D58: วรพล | E58: ศรีพิชิต | F58: Sales | H58: 43378 | I58: DS1-3/4 | J58: DS1 | K58: Direct Sales 1 | L58: 3101701030172 | M58: 7000576462 | N58: BKK | O58: DS1-3/4 | P58: - | Q58: - | R58: 2020624 | S58: Tivakon Wonglun | T58: 2016654 | U58: Weerakit Keeratichaitam | V58: 2013757 | W58: Saruda Chaloemjan | X58: 45118 | Y58: วรพล ศรีพิชิต | Z58: Active | AA58: DS1_3_4
A59: 87 | B59: 6560362 | C59: นางสาว | D59: ศศิธร | E59: จงเจริญสวัสดิ์ | F59: Sales | H59: 43418 | I59: DS1-2/3 | J59: DS1 | K59: Direct Sales 1 | L59: 3101500465180 | M59: 7010393059 | N59: BKK | O59: DS1-2/3 | P59: - | Q59: - | R59: 5349609 | S59: Benjawan Teandam | T59: 2015674 | U59: Dacha Jandaket | V59: 2013757 | W59: Saruda Chaloemjan | X59: 45119 | Y59: ศศิธร จงเจริญสวัสดิ์ | Z59: Active | AA59: DS1_2_3
A60: 88 | B60: 6560449 | C60: นาย | D60: สิทธิพงษ์ | E60: ฟุ้งสวาท | F60: Sales | H60: 43500 | I60: DS1-6/1 | J60: DS1 | K60: Direct Sales 1 | L60: 1209900008622 | M60: 7004847388 | N60: PVA | O60: DS1-6/1 | P60: - | Q60: - | R60: 2014899 | S60: Natpaphat Anakvasinchai | T60: 2018414 | U60: Narabodee Srisuphap | V60: 2013757 | W60: Saruda Chaloemjan | X60: 45133 | Y60: สิทธิพงษ์ ฟุ้งสวาท | Z60: Active | AA60: DS1_6_1
A61: 89 | B61: 6560513 | C61: นาย | D61: วรยุทธ | E61: ดีศรีเกตุ | F61: Sales | H61: 43508 | I61: DS1-5/4 | J61: DS1 | K61: Direct Sales 1 | L61: 3100800883580 | M61: 7010510337 | N61: PVA | O61: DS1-5/4 | P61: - | Q61: - | R61: 5424797 | S61: Pornthap Piwpuan | T61: 2019655 | U61: Kittichet Phattanajiranon | V61: 2013757 | W61: Saruda Chaloemjan | X61: 45126 | Y61: วรยุทธ ดีศรีเกตุ | Z61: Active | AA61: DS1_5_4
A62: 90 | B62: 6560488 | C62: นางสาว | D62: ศศิธร | E62: ปวีณวงษ์วรรณ | F62: Sales | H62: 43546 | I62: DS1-5/3 | J62: DS1 | K62: Direct Sales 1 | L62: 1200100121094 | M62: 7010570404 | N62: PVA | O62: DS1-5/3 | P62: - | Q62: - | R62: 2020309 | S62: Pawinchat Pumraya | T62: 2019655 | U62: Kittichet Phattanajiranon | V62: 2013757 | W62: Saruda Chaloemjan | X62: 45126 | Y62: ศศิธร ปวีณวงษ์วรรณ | Z62: Active | AA62: DS1_5_3
... A178: 287 | B178: 6960077 | C178: นางสาว | D178: ณิชาพัฒน์ | E178: บุญชาลี | F178: Sales | H178: 46147 | I178: DS1-6/3 | J178: DS1 | K178: Direct Sales 1 | L178: 3340100274333 | M178: 7015099589 | N178: PVA | O178: DS1-6/3 | P178: - | Q178: - | R178: 5397723 | S178: Narisara Jaisueakun | T178: 2018414 | U178: Narabodee Srisuphap | V178: 2013757 | W178: Saruda Chaloemjan | X178: 46160 | Y178: ณิชาพัฒน์ บุญชาลี | Z178: Active | AA178: DS1_6_3
A179: 294 | B179: 6960095 | C179: นาย | D179: ภูมิพิทักษ์ | E179: มั่งคั่ง | F179: Sales | G179: New | H179: 46175 | I179: DS1-1/2 | J179: DS1 | K179: Direct Sales 1 | L179: 1103702906468 | M179: 7015754953 | N179: BKK | O179: DS1-1/2 | P179: - | Q179: - | R179: 2020440 | S179: Pachara Phimprasant | T179: 2019804 | U179: Patpoom Poompij | V179: 2013757 | W179: Saruda Chaloemjan | X179: 46177 | Y179: ภูมิพิทักษ์ มั่งคั่ง | Z179: Active | AA179: DS1_1_2
A180: 295 | B180: 6960096 | C180: นางสาว | D180: ชัญญภัทร | E180: ธนวิชธาวิน | F180: Sales | G180: New | H180: 46175 | I180: DS1-2/1 | J180: DS1 | K180: Direct Sales 1 | L180: 1239900142281 | M180: 7015756090 | N180: BKK | O180: DS1-2/1 | P180: - | Q180: - | R180: 2020887 | S180: Chaitanawat Wongcue | T180: 2015674 | U180: Dacha Jandaket | V180: 2013757 | W180: Saruda Chaloemjan | X180: 46177 | Y180: ชัญญภัทร ธนวิชธาวิน | Z180: Active | AA180: DS1_2_1
A181: 296 | B181: 6960097 | C181: นางสาว | D181: สุจิตรา | E181: อิ่มเอิบ | F181: Sales Rejoin | H181: 46175 | I181: DS1-1/4 | J181: DS1 | K181: Direct Sales 1 | L181: 3100100485131 | M181: 7014949408 | N181: BKK | O181: DS1-1/4 | P181: - | Q181: - | R181: 2020911 | S181: Manoch Wiphatpong | T181: 2019804 | U181: Patpoom Poompij | V181: 2013757 | W181: Saruda Chaloemjan | X181: 46177 | Y181: สุจิตรา อิ่มเอิบ | Z181: Active | AA181: DS1_1_4
A182: 297 | B182: 6960098 | C182: นางสาว | D182: ชญานี | E182: มอนไข่ | F182: Sales | G182: New | H182: 46175 | I182: DS1-4/2 | J182: DS1 | K182: Direct Sales 1 | L182: 1509900462827 | M182: 7015730347 | N182: PVA | O182: DS1-4/2 | P182: - | Q182: - | R182: 2020497 | S182: Weeraphong Lungkawong | T182: 2019567 | U182: Peemphat Panprommin | V182: 2013757 | W182: Saruda Chaloemjan | X182: 46177 | Y182: ชญานี มอนไข่ | Z182: Active | AA182: DS1_4_2
A183: 299 | B183: 6960100 | C183: นางสาว | D183: กวินทรา | E183: นำพล | F183: Sales | G183: New | H183: 46175 | I183: DS1-1/2 | J183: DS1 | K183: Direct Sales 1 | L183: 3540300158556 | M183: 7015742001 | N183: BKK | O183: DS1-1/2 | P183: - | Q183: - | R183: 2020440 | S183: Pachara Phimprasant | T183: 2019804 | U183: Patpoom Poompij | V183: 2013757 | W183: Saruda Chaloemjan | X183: 46190 | Y183: กวินทรา นำพล | Z183: Active | AA183: DS1_1_2
A184: 300 | B184: 6960101 | C184: นาย | D184: ชูศักดิ์ | E184: วังวงค์ | F184: Sales | G184: New | H184: 46175 | I184: DS1-2/4 | J184: DS1 | K184: Direct Sales 1 | L184: 3490500199796 | M184: 7015755805 | N184: BKK | O184: DS1-2/4 | P184: - | Q184: - | R184: 5421894 | S184: Kansita Khongking | T184: 2015674 | U184: Dacha Jandaket | V184: 2013757 | W184: Saruda Chaloemjan | X184: 46190 | Y184: ชูศักดิ์ วังวงค์ | Z184: Active | AA184: DS1_2_4
A185: 326 | B185: 6930127 | C185: นางสาว | D185: ปิยนุช | E185: ทองแท้ | F185: Sales | G185: New | H185: 46204 | I185: DS2-1/1 | J185: DS2 | K185: Direct Sales 2 | L185: 1739900583011 | M185: 7015750981 | N185: BKK | O185: DS2-1/1 | P185: - | Q185: - | R185: 2018437 | S185: Pimnutchaya Youyatmak | T185: 2008274 | U185: Kataree Sudhasawin | V185: 2014180 | W185: Wichian Tanyawong | X185: 46204 | Y185: ปิยนุช ทองแท้ | Z185: Active | AA185: DS2_1_1
A186: 327 | B186: 6930128 | C186: นาย | D186: ธุมากร | E186: ประเสริฐศรีเจริญ | F186: Sales Rejoin | H186: 46204 | I186: DS2-1/1 | J186: DS2 | K186: Direct Sales 2 | L186: 3110101164509 | M186: 7007662810 | N186: BKK | O186: DS2-1/1 | P186: - | Q186: - | R186: 2018437 | S186: Pimnutchaya Youyatmak | T186: 2008274 | U186: Kataree Sudhasawin | V186: 2014180 | W186: Wichian Tanyawong | X186: 46204 | Y186: ธุมากร ประเสริฐศรีเจริญ | Z186: Active | AA186: DS2_1_1
A187: 328 | B187: 6930129 | C187: นาย | D187: เอกชาติ | E187: เอี่ยมสอาด | F187: Sales Rejoin | H187: 46204 | I187: DS2-1/2 | J187: DS2 | K187: Direct Sales 2 | L187: 1100800088121 | M187: 7011355455 | N187: BKK | O187: DS2-1/2 | P187: - | Q187: - | R187: 2019298 | S187: Oravan Boonnak | T187: 2008274 | U187: Kataree Sudhasawin | V187: 2014180 | W187: Wichian Tanyawong | X187: 46204 | Y187: เอกชาติ เอี่ยมสอาด | Z187: Active | AA187: DS2_1_2
A188: 329 | B188: 6930130 | C188: นาง | D188: สาลินี | E188: นรรัตน์ | F188: Sales Rejoin | H188: 46204 | I188: DS2-2/1 | J188: DS2 | K188: Direct Sales 2 | L188: 3470800001550 | M188: 7014794868 | N188: BKK | O188: DS2-2/1 | P188: - | Q188: - | R188: 5304046 | S188: Sirikan Phanburananont | T188: 2018025 | U188: Kitiyaphorn Rakyos | V188: 2014180 | W188: Wichian Tanyawong | X188: 46205 | Y188: สาลินี นรรัตน์ | Z188: Active | AA188: DS2_2_1
A189: 330 | B189: 6930131 | C189: นางสาว | D189: พรรณธิรา | E189: สุขจับจันทร์ | F189: Sales Rejoin | H189: 46204 | I189: DS2-2/1 | J189: DS2 | K189: Direct Sales 2 | L189: 1719900232757 | M189: 7011105741 | N189: BKK | O189: DS2-2/1 | P189: - | Q189: - | R189: 5304046 | S189: Sirikan Phanburananont | T189: 2018025 | U189: Kitiyaphorn Rakyos | V189: 2014180 | W189: Wichian Tanyawong | X189: 46205 | Y189: พรรณธิรา สุขจับจันทร์ | Z189: Active | AA189: DS2_2_1
A190: 331 | B190: 6930133 | C190: นาย | D190: ทรงธรรม | E190: ทวีวิภาสพงศ์ | F190: Sales Rejoin | H190: 46204 | I190: DS2-2/2 | J190: DS2 | K190: Direct Sales 2 | L190: 1100400454162 | M190: 7011316624 | N190: BKK | O190: DS2-2/2 | P190: - | Q190: - | R190: 5362157 | S190: Chanyaphak Fuinta | T190: 2018025 | U190: Kitiyaphorn Rakyos | V190: 2014180 | W190: Wichian Tanyawong | X190: 46205 | Y190: ทรงธรรม ทวีวิภาสพงศ์ | Z190: Active | AA190: DS2_2_2
A191: 332 | B191: 6930134 | C191: นางสาว | D191: ปริสฐา | E191: สโมสร | F191: Sales Rejoin | H191: 46204 | I191: DS2-2/2 | J191: DS2 | K191: Direct Sales 2 | L191: 3849900118640 | M191: 7001664303 | N191: BKK | O191: DS2-2/2 | P191: - | Q191: - | R191: 5362157 | S191: Chanyaphak Fuinta | T191: 2018025 | U191: Kitiyaphorn Rakyos | V191: 2014180 | W191: Wichian Tanyawong | X191: 46205 | Y191: ปริสฐา สโมสร | Z191: Active | AA191: DS2_2_2
A192: 333 | B192: 6930135 | C192: นางสาว | D192: ปฏิมา | E192: บัวแก้ว | F192: Sales Rejoin | H192: 46204 | I192: DS2-2/3 | J192: DS2 | K192: Direct Sales 2 | L192: 3900700713600 | M192: 7010918244 | N192: BKK | O192: DS2-2/3 | P192: - | Q192: - | R192: 2009436 | S192: Nattinee Sakuntanat | T192: 2018025 | U192: Kitiyaphorn Rakyos | V192: 2014180 | W192: Wichian Tanyawong | X192: 46205 | Y192: ปฏิมา บัวแก้ว | Z192: Active | AA192: DS2_2_3
A193: 334 | B193: 6930136 | C193: นาง | D193: ฐิติมา | E193: เนียมเรือง | F193: Sales | G193: New | H193: 46204 | I193: DS2-2/3 | J193: DS2 | K193: Direct Sales 2 | L193: 1339900368806 | M193: 7011268189 | N193: BKK | O193: DS2-2/3 | P193: - | Q193: - | R193: 2009436 | S193: Nattinee Sakuntanat | T193: 2018025 | U193: Kitiyaphorn Rakyos | V193: 2014180 | W193: Wichian Tanyawong | X193: 46205 | Y193: ฐิติมา เนียมเรือง | Z193: Active | AA193: DS2_2_3
A194: 335 | B194: 6930137 | C194: นางสาว | D194: สิริพร | E194: พลับทอง | F194: Sales Rejoin | H194: 46204 | I194: DS2-2/3 | J194: DS2 | K194: Direct Sales 2 | L194: 3220400293776 | M194: 7013421683 | N194: BKK | O194: DS2-2/3 | P194: - | Q194: - | R194: 2009436 | S194: Nattinee Sakuntanat | T194: 2018025 | U194: Kitiyaphorn Rakyos | V194: 2014180 | W194: Wichian Tanyawong | X194: 46205 | Y194: สิริพร พลับทอง | Z194: Active | AA194: DS2_2_3
A195: 336 | B195: 6930138 | C195: นาย | D195: อัศฎา | E195: รักษาเพชร | F195: Sales Rejoin | H195: 46204 | I195: DS2-2/4 | J195: DS2 | K195: Direct Sales 2 | L195: 1840100076557 | M195: 7014824670 | N195: PVA | O195: DS2-2/4 | P195: - | Q195: - | R195: 2015946 | S195: Santichai Ounyoung | T195: 2018025 | U195: Kitiyaphorn Rakyos | V195: 2014180 | W195: Wichian Tanyawong | X195: 46205 | Y195: อัศฎา รักษาเพชร | Z195: Active | AA195: DS2_2_4
A196: 337 | B196: 6930139 | C196: นางสาว | D196: อรวรรณ | E196: สุวรรณรินทร์ | F196: Sales Rejoin | H196: 46204 | I196: DS2-2/5 | J196: DS2 | K196: Direct Sales 2 | L196: 1520800090482 | M196: 7013575201 | N196: PVA | O196: DS2-2/5 | P196: - | Q196: - | R196: 2017666 | S196: Paweena Pholsub | T196: 2018025 | U196: Kitiyaphorn Rakyos | V196: 2014180 | W196: Wichian Tanyawong | X196: 46205 | Y196: อรวรรณ สุวรรณรินทร์ | Z196: Active | AA196: DS2_2_5
A197: 338 | B197: 6930140 | C197: นาง | D197: นาถนรินทร์ | E197: เยาว์ทุม | F197: Sales Rejoin | H197: 46204 | I197: DS2-3/1 | J197: DS2 | K197: Direct Sales 2 | L197: 3100700371200 | M197: 7010757528 | N197: BKK | O197: DS2-3/1 | P197: - | Q197: - | R197: 2020089 | S197: Nuttapong Khunvilai | T197: 2014427 | U197: Pachara Pinyarassamie | V197: 2014180 | W197: Wichian Tanyawong | X197: 46205 | Y197: นาถนรินทร์ เยาว์ทุม | Z197: Active | AA197: DS2_3_1
A198: 339 | B198: 6930141 | C198: นาย | D198: เบิร์น | E198: วิรติกุล | F198: Sales Rejoin | H198: 46204 | I198: DS2-3/1 | J198: DS2 | K198: Direct Sales 2 | L198: 1101401586594 | M198: 7000964790 | N198: BKK | O198: DS2-3/1 | P198: - | Q198: - | R198: 2020089 | S198: Nuttapong Khunvilai | T198: 2014427 | U198: Pachara Pinyarassamie | V198: 2014180 | W198: Wichian Tanyawong | X198: 46205 | Y198: เบิร์น วิรติกุล | Z198: Active | AA198: DS2_3_1
A199: 340 | B199: 6930142 | C199: นางสาว | D199: อัจฉรา | E199: โสภาวัฒน์ | F199: Sales Rejoin | H199: 46204 | I199: DS2-3/4 | J199: DS2 | K199: Direct Sales 2 | L199: 1259700064774 | M199: 7010639525 | N199: PVA | O199: DS2-3/4 | P199: - | Q199: - | R199: 2013925 | S199: Saowaluk Sutthinunthakorn | T199: 2014427 | U199: Pachara Pinyarassamie | V199: 2014180 | W199: Wichian Tanyawong | X199: 46205 | Y199: อัจฉรา โสภาวัฒน์ | Z199: Active | AA199: DS2_3_4
A200: 341 | B200: 6930143 | C200: นางสาว | D200: ณัฐรดาพร | E200: พุ่มงาม | F200: Sales Rejoin | H200: 46204 | I200: DS2-4/1 | J200: DS2 | K200: Direct Sales 2 | L200: 3700101165101 | M200: 7004264325 | N200: BKK | O200: DS2-4/1 | P200: - | Q200: - | R200: 2017368 | S200: Radamanee Santipharppongsa | T200: 2013471 | U200: Piyawan Treecharoen | V200: 2014180 | W200: Wichian Tanyawong | X200: 46204 | Y200: ณัฐรดาพร พุ่มงาม | Z200: Active | AA200: DS2_4_1
A201: 342 | B201: 6930144 | C201: นาย | D201: จักรัตน์ | E201: สิมารักษ์ | F201: Sales | G201: New | H201: 46204 | I201: DS2-4/2 | J201: DS2 | K201: Direct Sales 2 | L201: 1440700089858 | M201: 7008788932 | N201: BKK | O201: DS2-4/2 | P201: - | Q201: - | R201: 2010690 | S201: Kanthaya Thantongdee | T201: 2013471 | U201: Piyawan Treecharoen | V201: 2014180 | W201: Wichian Tanyawong | X201: 46204 | Y201: จักรัตน์ สิมารักษ์ | Z201: Active | AA201: DS2_4_2
A202: 343 | B202: 6930145 | C202: นางสาว | D202: ทิพวรรณ | E202: กังอนันต์ | F202: Sales Rejoin | H202: 46204 | I202: DS2-4/2 | J202: DS2 | K202: Direct Sales 2 | L202: 3801400004192 | M202: 7011122841 | N202: BKK | O202: DS2-4/2 | P202: - | Q202: - | R202: 2010690 | S202: Kanthaya Thantongdee | T202: 2013471 | U202: Piyawan Treecharoen | V202: 2014180 | W202: Wichian Tanyawong | X202: 46204 | Y202: ทิพวรรณ กังอนันต์ | Z202: Active | AA202: DS2_4_2
A203: 344 | B203: 6930146 | C203: นาย | D203: นิรุจส์ | E203: สุทธิชัยธีรกุล | F203: Sales Rejoin | H203: 46204 | I203: DS2-5/1 | J203: DS2 | K203: Direct Sales 2 | L203: 3100502596019 | M203: 7014872469 | N203: BKK | O203: DS2-5/1 | P203: - | Q203: - | R203: 5300931 | S203: Chanidnan Kransomsit | T203: 2009365 | U203: Phakin Thanakwinchok | V203: 2014180 | W203: Wichian Tanyawong | X203: 46204 | Y203: นิรุจส์ สุทธิชัยธีรกุล | Z203: Active | AA203: DS2_5_1
A204: 345 | B204: 6930147 | C204: นางสาว | D204: ณัฏฐ์ชุดา | E204: สมพันธ์แพ | F204: Sales | G204: New | H204: 46204 | I204: DS2-5/2 | J204: DS2 | K204: Direct Sales 2 | L204: 3102400514309 | M204: 7015756252 | N204: BKK | O204: DS2-5/2 | P204: - | Q204: - | R204: 2020598 | S204: Nunnarat Vilaisri | T204: 2009365 | U204: Phakin Thanakwinchok | V204: 2014180 | W204: Wichian Tanyawong | X204: 46204 | Y204: ณัฏฐ์ชุดา สมพันธ์แพ | Z204: Active | AA204: DS2_5_2
A205: 346 | B205: 6930148 | C205: นางสาว | D205: ปิ่นแก้ว | E205: ภูศรีโสม | F205: Sales | G205: New | H205: 46204 | I205: DS2-5/3 | J205: DS2 | K205: Direct Sales 2 | L205: 3300200228198 | M205: 7015766148 | N205: PVA | O205: DS2-5/3 | P205: - | Q205: - | R205: 5404943 | S205: Somlak Potisa | T205: 2009365 | U205: Phakin Thanakwinchok | V205: 2014180 | W205: Wichian Tanyawong | X205: 46204 | Y205: ปิ่นแก้ว ภูศรีโสม | Z205: Active | AA205: DS2_5_3
A206: 347 | B206: 6930149 | C206: นางสาว | D206: ภัทรชิรพร | E206: เขื่อนคำ | F206: Sales Rejoin | H206: 46204 | I206: DS2-5/4 | J206: DS2 | K206: Direct Sales 2 | L206: 1100200467783 | M206: 7013580166 | N206: BKK | O206: DS2-5/4 | P206: - | Q206: - | R206: 5366603 | S206: Thianwipa Sangmanee | T206: 2009365 | U206: Phakin Thanakwinchok | V206: 2014180 | W206: Wichian Tanyawong | X206: 46204 | Y206: ภัทรชิรพร เขื่อนคำ | Z206: Active | AA206: DS2_5_4
A207: 348 | B207: 6930150 | C207: นางสาว | D207: วนิดา | E207: มาสา | F207: Sales Rejoin | H207: 46204 | I207: DS2-1/2 | J207: DS2 | K207: Direct Sales 2 | L207: 1600400006891 | M207: 7010561789 | N207: BKK | O207: DS2-1/2 | P207: - | Q207: - | R207: 2019298 | S207: Oravan Boonnak | T207: 2008274 | U207: Kataree Sudhasawin | V207: 2014180 | W207: Wichian Tanyawong | X207: 46204 | Y207: วนิดา มาสา | Z207: Active | AA207: DS2_1_2
A208: 349 | B208: 6930151 | C208: นางสาว | D208: จริยา | E208: ขวัญทอง | F208: Sales Rejoin | H208: 46204 | I208: DS2-1/4 | J208: DS2 | K208: Direct Sales 2 | L208: 1909900210590 | M208: 7010809485 | N208: PVA | O208: DS2-1/4 | P208: - | Q208: - | R208: 2010212 | S208: Prateep Saejong | T208: 2008274 | U208: Kataree Sudhasawin | V208: 2014180 | W208: Wichian Tanyawong | X208: 46204 | Y208: จริยา ขวัญทอง | Z208: Active | AA208: DS2_1_4
A209: 350 | B209: 6930152 | C209: นางสาว | D209: พรทิพย์ | E209: ศรีนวลขาว | F209: Sales Rejoin | H209: 46204 | I209: DS2-1/4 | J209: DS2 | K209: Direct Sales 2 | L209: 1930300013744 | M209: 7012668082 | N209: PVA | O209: DS2-1/4 | P209: - | Q209: - | R209: 2010212 | S209: Prateep Saejong | T209: 2008274 | U209: Kataree Sudhasawin | V209: 2014180 | W209: Wichian Tanyawong | X209: 46204 | Y209: พรทิพย์ ศรีนวลขาว | Z209: Active | AA209: DS2_1_4
A210: 351 | B210: 6930153 | C210: นางสาว | D210: สิริรัตน์ | E210: ล้อมวงค์ | F210: Sales Rejoin | H210: 46204 | I210: DS2-2/1 | J210: DS2 | K210: Direct Sales 2 | L210: 1739900475692 | M210: 7012710044 | N210: BKK | O210: DS2-2/1 | P210: - | Q210: - | R210: 5304046 | S210: Sirikan Phanburananont | T210: 2018025 | U210: Kitiyaphorn Rakyos | V210: 2014180 | W210: Wichian Tanyawong | X210: 46205 | Y210: สิริรัตน์ ล้อมวงค์ | Z210: Active | AA210: DS2_2_1
A211: 352 | B211: 6930154 | C211: นาย | D211: วิทวัฒน์ | E211: ชัยมั่น | F211: Sales Rejoin | H211: 46204 | I211: DS2-2/1 | J211: DS2 | K211: Direct Sales 2 | L211: 3311100290313 | M211: 7009668377 | N211: BKK | O211: DS2-2/1 | P211: - | Q211: - | R211: 5304046 | S211: Sirikan Phanburananont | T211: 2018025 | U211: Kitiyaphorn Rakyos | V211: 2014180 | W211: Wichian Tanyawong | X211: 46205 | Y211: วิทวัฒน์ ชัยมั่น | Z211: Active | AA211: DS2_2_1
A212: 353 | B212: 6930155 | C212: นาย | D212: กิตติณัฐ์ | E212: ฟูอินต๊ะ | F212: Sales | G212: New | H212: 46204 | I212: DS2-2/2 | J212: DS2 | K212: Direct Sales 2 | L212: 1529902329091 | M212: 7015845203 | N212: BKK | O212: DS2-2/2 | P212: - | Q212: - | R212: 5362157 | S212: Chanyaphak Fuinta | T212: 2018025 | U212: Kitiyaphorn Rakyos | V212: 2014180 | W212: Wichian Tanyawong | X212: 46205 | Y212: กิตติณัฐ์ ฟูอินต๊ะ | Z212: Active | AA212: DS2_2_2
A213: 354 | B213: 6930156 | C213: นางสาว | D213: ภูริชญา | E213: ประสาธน์สุวรรณ | F213: Sales Rejoin | H213: 46204 | I213: DS2-2/5 | J213: DS2 | K213: Direct Sales 2 | L213: 1539900235731 | M213: 7011091599 | N213: PVA | O213: DS2-2/5 | P213: - | Q213: - | R213: 2017666 | S213: Paweena Pholsub | T213: 2018025 | U213: Kitiyaphorn Rakyos | V213: 2014180 | W213: Wichian Tanyawong | X213: 46205 | Y213: ภูริชญา ประสาธน์สุวรรณ | Z213: Active | AA213: DS2_2_5
A214: 355 | B214: 6930158 | C214: นางสาว | D214: สุภาพร | E214: หอมแก้ว | F214: Sales Rejoin | H214: 46204 | I214: DS2-3/1 | J214: DS2 | K214: Direct Sales 2 | L214: 1141000053846 | M214: 7012898695 | N214: BKK | O214: DS2-3/1 | P214: - | Q214: - | R214: 2020089 | S214: Nuttapong Khunvilai | T214: 2014427 | U214: Pachara Pinyarassamie | V214: 2014180 | W214: Wichian Tanyawong | X214: 46205 | Y214: สุภาพร หอมแก้ว | Z214: Active | AA214: DS2_3_1
A215: 356 | B215: 6930159 | C215: นางสาว | D215: ศิริรักษ์ | E215: เกตุเอี่ยม | F215: Sales | G215: New | H215: 46204 | I215: DS2-3/2 | J215: DS2 | K215: Direct Sales 2 | L215: 1209700075181 | M215: 7015800220 | N215: PVA | O215: DS2-3/2 | P215: - | Q215: - | R215: 2017705 | S215: Phakphoom Suksai | T215: 2014427 | U215: Pachara Pinyarassamie | V215: 2014180 | W215: Wichian Tanyawong | X215: 46205 | Y215: ศิริรักษ์ เกตุเอี่ยม | Z215: Active | AA215: DS2_3_2
A216: 357 | B216: 6930160 | C216: นาย | D216: คงศักดิ์ | E216: สันติภาพพงศา | F216: Sales | G216: New | H216: 46204 | I216: DS2-4/1 | J216: DS2 | K216: Direct Sales 2 | L216: 3110101465380 | M216: 7015773445 | N216: BKK | O216: DS2-4/1 | P216: - | Q216: - | R216: 2017368 | S216: Radamanee Santipharppongsa | T216: 2013471 | U216: Piyawan Treecharoen | V216: 2014180 | W216: Wichian Tanyawong | X216: 46204 | Y216: คงศักดิ์ สันติภาพพงศา | Z216: Active | AA216: DS2_4_1
A217: 358 | B217: 6930161 | C217: นางสาว | D217: ปิติยาภรณ์ | E217: แซ่ลี้ | F217: Sales Rejoin | H217: 46204 | I217: DS2-4/1 | J217: DS2 | K217: Direct Sales 2 | L217: 1101800095594 | M217: 7012423102 | N217: BKK | O217: DS2-4/1 | P217: - | Q217: - | R217: 2017368 | S217: Radamanee Santipharppongsa | T217: 2013471 | U217: Piyawan Treecharoen | V217: 2014180 | W217: Wichian Tanyawong | X217: 46204 | Y217: ปิติยาภรณ์ แซ่ลี้ | Z217: Active | AA217: DS2_4_1
A218: 359 | B218: 6930162 | C218: นางสาว | D218: ดวงนภา | E218: ศรีหะวงษ์ | F218: Sales Rejoin | H218: 46204 | I218: DS2-4/2 | J218: DS2 | K218: Direct Sales 2 | L218: 3330500980022 | M218: 7009861356 | N218: BKK | O218: DS2-4/2 | P218: - | Q218: - | R218: 2010690 | S218: Kanthaya Thantongdee | T218: 2013471 | U218: Piyawan Treecharoen | V218: 2014180 | W218: Wichian Tanyawong | X218: 46204 | Y218: ดวงนภา ศรีหะวงษ์ | Z218: Active | AA218: DS2_4_2
A219: 360 | B219: 6930163 | C219: นางสาว | D219: กัลยานิษฐ์ | E219: โพธิ์ขาว | F219: Sales Rejoin | H219: 46204 | I219: DS2-4/2 | J219: DS2 | K219: Direct Sales 2 | L219: 1101200174540 | M219: 7013282274 | N219: BKK | O219: DS2-4/2 | P219: - | Q219: - | R219: 2010690 | S219: Kanthaya Thantongdee | T219: 2013471 | U219: Piyawan Treecharoen | V219: 2014180 | W219: Wichian Tanyawong | X219: 46204 | Y219: กัลยานิษฐ์ โพธิ์ขาว | Z219: Active | AA219: DS2_4_2
A220: 361 | B220: 6930164 | C220: นางสาว | D220: ธารินี | E220: ยอดมา | F220: Sales Rejoin | H220: 46204 | I220: DS2-4/3 | J220: DS2 | K220: Direct Sales 2 | L220: 3209800123701 | M220: 7003467112 | N220: PVA | O220: DS2-4/3 | P220: - | Q220: - | R220: 2020753 | S220: Ketsuda Chonlakit | T220: 2013471 | U220: Piyawan Treecharoen | V220: 2014180 | W220: Wichian Tanyawong | X220: 46204 | Y220: ธารินี ยอดมา | Z220: Active | AA220: DS2_4_3
A221: 362 | B221: 6930165 | C221: นาง | D221: อัญชนา | E221: เผือกวัฒนะ | F221: Sales | G221: New | H221: 46204 | I221: DS2-5/1 | J221: DS2 | K221: Direct Sales 2 | L221: 3200900153388 | M221: 7015783886 | N221: BKK | O221: DS2-5/1 | P221: - | Q221: - | R221: 5300931 | S221: Chanidnan Kransomsit | T221: 2009365 | U221: Phakin Thanakwinchok | V221: 2014180 | W221: Wichian Tanyawong | X221: 46204 | Y221: อัญชนา เผือกวัฒนะ | Z221: Active | AA221: DS2_5_1
A222: 363 | B222: 6930166 | C222: นางสาว | D222: สุกัลยา | E222: สิทธิชาคำ | F222: Sales Rejoin | H222: 46204 | I222: DS2-5/2 | J222: DS2 | K222: Direct Sales 2 | L222: 1410500083091 | M222: 7013636952 | N222: BKK | O222: DS2-5/2 | P222: - | Q222: - | R222: 2020598 | S222: Nunnarat Vilaisri | T222: 2009365 | U222: Phakin Thanakwinchok | V222: 2014180 | W222: Wichian Tanyawong | X222: 46204 | Y222: สุกัลยา สิทธิชาคำ | Z222: Active | AA222: DS2_5_2
A223: 364 | B223: 6930167 | C223: นางสาว | D223: ขวัญใจ | E223: สงแจ้งใหญ่ | F223: Sales | G223: New | H223: 46204 | I223: DS2-5/2 | J223: DS2 | K223: Direct Sales 2 | L223: 3730500004461 | M223: 7015784302 | N223: BKK | O223: DS2-5/2 | P223: - | Q223: - | R223: 2020598 | S223: Nunnarat Vilaisri | T223: 2009365 | U223: Phakin Thanakwinchok | V223: 2014180 | W223: Wichian Tanyawong | X223: 46204 | Y223: ขวัญใจ สงแจ้งใหญ่ | Z223: Active | AA223: DS2_5_2
A224: 365 | B224: 6930168 | C224: นาง | D224: วันเพ็ญ | E224: ศูนย์กลาง | F224: Sales | G224: New | H224: 46204 | I224: DS2-5/3 | J224: DS2 | K224: Direct Sales 2 | L224: 3471100317300 | M224: 7015852481 | N224: PVA | O224: DS2-5/3 | P224: - | Q224: - | R224: 5404943 | S224: Somlak Potisa | T224: 2009365 | U224: Phakin Thanakwinchok | V224: 2014180 | W224: Wichian Tanyawong | X224: 46204 | Y224: วันเพ็ญ ศูนย์กลาง | Z224: Active | AA224: DS2_5_3
A225: 366 | B225: 6930169 | C225: นางสาว | D225: นิรดา | E225: วงสุวรรณ์ | F225: Sales | G225: New | H225: 46204 | I225: DS2-5/3 | J225: DS2 | K225: Direct Sales 2 | L225: 1309900946567 | M225: 7015852336 | N225: PVA | O225: DS2-5/3 | P225: - | Q225: - | R225: 5404943 | S225: Somlak Potisa | T225: 2009365 | U225: Phakin Thanakwinchok | V225: 2014180 | W225: Wichian Tanyawong | X225: 46204 | Y225: นิรดา วงสุวรรณ์ | Z225: Active | AA225: DS2_5_3
A226: 367 | B226: 6930170 | C226: นางสาว | D226: ญาณัจฉรา | E226: สืบสิงห์ | F226: Sales Rejoin | H226: 46204 | I226: DS2-5/5 | J226: DS2 | K226: Direct Sales 2 | L226: 1349900397997 | M226: 7012331443 | N226: PVA | O226: DS2-5/5 | P226: - | Q226: - | R226: 5392829 | S226: Yanin Salarak | T226: 2009365 | U226: Phakin Thanakwinchok | V226: 2014180 | W226: Wichian Tanyawong | X226: 46204 | Y226: ญาณัจฉรา สืบสิงห์ | Z226: Active | AA226: DS2_5_5
A227: 368 | B227: 6930171 | C227: นาย | D227: ชินวัฒน์ | E227: ภู่ดอก | F227: Sales | G227: New | H227: 46204 | I227: DS2-1/3 | J227: DS2 | K227: Direct Sales 2 | L227: 1809900031866 | M227: 7015823546 | N227: BKK | O227: DS2-1/3 | P227: - | Q227: - | R227: 2015066 | S227: Chanyakhal Udomlarp | T227: 2008274 | U227: Kataree Sudhasawin | V227: 2014180 | W227: Wichian Tanyawong | X227: 46204 | Y227: ชินวัฒน์ ภู่ดอก | Z227: Active | AA227: DS2_1_3
A228: 369 | B228: 6930172 | C228: นางสาว | D228: ณัฐรวี | E228: แสงมงคลพิพัฒน์ | F228: Sales | G228: New | H228: 46204 | I228: DS2-1/3 | J228: DS2 | K228: Direct Sales 2 | L228: 1200100335167 | M228: 7012107575 | N228: BKK | O228: DS2-1/3 | P228: - | Q228: - | R228: 2015066 | S228: Chanyakhal Udomlarp | T228: 2008274 | U228: Kataree Sudhasawin | V228: 2014180 | W228: Wichian Tanyawong | X228: 46204 | Y228: ณัฐรวี แสงมงคลพิพัฒน์ | Z228: Active | AA228: DS2_1_3
A229: 370 | B229: 6930173 | C229: นางสาว | D229: จีรวรรณ | E229: แสงแก้ว | F229: Sales | G229: New | H229: 46204 | I229: DS2-1/3 | J229: DS2 | K229: Direct Sales 2 | L229: 1209700010488 | M229: 7008435090 | N229: BKK | O229: DS2-1/3 | P229: - | Q229: - | R229: 2015066 | S229: Chanyakhal Udomlarp | T229: 2008274 | U229: Kataree Sudhasawin | V229: 2014180 | W229: Wichian Tanyawong | X229: 46204 | Y229: จีรวรรณ แสงแก้ว | Z229: Active | AA229: DS2_1_3
...

Sheet Dropdown_DS_Zone
A1: Direct_Sales_1 | B1: Direct_Sales_2
A2: {=_xlfn._xlws.SORT(_xlfn.UNIQUE(_xlfn._xlws.FILTER(Sales_Agent_info!$AA:$AA, Sales_Agent_info!$K:$K="Direct Sales 1")), 1, 1)} -> DS1_1_1 | B2: {=_xlfn._xlws.SORT(_xlfn.UNIQUE(_xlfn._xlws.FILTER(Sales_Agent_info!$AA:$AA, Sales_Agent_info!$K:$K="Direct Sales 2")), 1, 1)} -> DS2_1_1
A3: DS1_1_2 | B3: DS2_1_2
A4: DS1_1_3 | B4: DS2_1_3
A5: DS1_1_4 | B5: DS2_1_4
A6: DS1_2_1 | B6: DS2_1_5
A7: DS1_2_2 | B7: DS2_2_1
A8: DS1_2_3 | B8: DS2_2_2
A9: DS1_2_4 | B9: DS2_2_3
A10: DS1_3_1 | B10: DS2_2_4
A11: DS1_3_2 | B11: DS2_2_5
A12: DS1_3_3 | B12: DS2_3_1
A13: DS1_3_4 | B13: DS2_3_2
A14: DS1_4_1 | B14: DS2_3_3
... A25: DS1_6_4 | B25: DS2_5_4
B26: DS2_5_5

Sheet Dropdown_DS_Staff
A1: DS1_1_1 | B1: DS1_1_2 | C1: DS1_1_3 | D1: DS1_1_4 | E1: DS1_2_1 | F1: DS1_2_2 | G1: DS1_2_3 | H1: DS1_2_4 | I1: DS1_3_1 | J1: DS1_3_2 | K1: DS1_3_3 | L1: DS1_3_4 | M1: DS1_4_1 | N1: DS1_4_2 | O1: DS1_4_3 | P1: DS1_4_4 | Q1: DS1_5_1 | R1: DS1_5_2 | S1: DS1_5_3 | T1: DS1_5_4 | U1: DS1_6_1 | V1: DS1_6_2 | W1: DS1_6_3 | X1: DS1_6_4 | Y1: DS2_1_1 | Z1: DS2_1_2 | AA1: DS2_1_3 | AB1: DS2_1_4 | AC1: DS2_1_5 | AD1: DS2_2_1 | AE1: DS2_2_2 | AF1: DS2_2_3 | AG1: DS2_2_4 | AH1: DS2_2_5 | AI1: DS2_3_1 | AJ1: DS2_3_2 | AK1: DS2_3_3 | AL1: DS2_3_4 | AM1: DS2_3_5 | AN1: DS2_4_1 | AO1: DS2_4_2 | AP1: DS2_4_3 | AQ1: DS2_4_4 | AR1: DS2_4_5 | AS1: DS2_5_1 | AT1: DS2_5_2 | AU1: DS2_5_3 | AV1: DS2_5_4 | AW1: DS2_5_5
A2: {=_xlfn._xlws.FILTER(Sales_Agent_info!$B:$B, Sales_Agent_info!$AA:$AA= A$1)} -> 2010607 | B2: {=_xlfn._xlws.FILTER(Sales_Agent_info!$B:$B, Sales_Agent_info!$AA:$AA= B$1)} -> 2020440 | C2: {=_xlfn._xlws.FILTER(Sales_Agent_info!$B:$B, Sales_Agent_info!$AA:$AA= C$1)} -> 2020799 | D2: {=_xlfn._xlws.FILTER(Sales_Agent_info!$B:$B, Sales_Agent_info!$AA:$AA= D$1)} -> 2020911 | E2: {=_xlfn._xlws.FILTER(Sales_Agent_info!$B:$B, Sales_Agent_info!$AA:$AA= E$1)} -> 2020887 | F2: {=_xlfn._xlws.FILTER(Sales_Agent_info!$B:$B, Sales_Agent_info!$AA:$AA= F$1)} -> 5300754 | G2: {=_xlfn._xlws.FILTER(Sales_Agent_info!$B:$B, Sales_Agent_info!$AA:$AA= G$1)} -> 5349609 | H2: {=_xlfn._xlws.FILTER(Sales_Agent_info!$B:$B, Sales_Agent_info!$AA:$AA= H$1)} -> 5421894 | ... AW2: {=_xlfn._xlws.FILTER(Sales_Agent_info!$B:$B, Sales_Agent_info!$AA:$AA= AW$1)} -> 5392829
A3: 6560385 | B3: 6560394 | C3: 6560407 | D3: 6560414 | E3: 6560369 | F3: 6560378 | G3: 6560362 | H3: 6560436 | I3: 6560342 | J3: 6560479 | K3: 6860049 | L3: 6560330 | M3: 6560465 | N3: 6960052 | O3: 6560426 | P3: 6860023 | Q3: 6560522 | R3: 6560508 | S3: 6560488 | T3: 6560513 | U3: 6560449 | V3: 6560498 | W3: 6560372 | X3: 6560497 | Y3: 6930127 | Z3: 6930129 | AA3: 6930171 | AB3: 6930151 | AC3: 6930175 | AD3: 6930130 | AE3: 6930133 | AF3: 6930135 | AG3: 6930138 | AH3: 6930139 | AI3: 6930140 | AJ3: 6930159 | AK3: 6930193 | AL3: 6930142 | AM3: 6930184 | AN3: 6930143 | AO3: 6930144 | AP3: 6930164 | AQ3: 6930187 | AR3: 6930189 | AS3: 6930146 | AT3: 6930147 | AU3: 6930148 | AV3: 6930149 | AW3: 6930170
A4: 6560395 | B4: 6560401 | C4: 6560409 | D4: 6860015 | E4: 6560447 | F4: 6560374 | G4: 6560354 | H4: 6860042 | I4: 6560353 | J4: 6560480 | K4: 6860063 | L4: 6860084 | M4: 6560471 | N4: 6960053 | O4: 6560440 | P4: 6860039 | Q4: 6560523 | R4: 6560516 | S4: 6560491 | T4: 6860139 | U4: 6560451 | V4: 6560504 | W4: 6760250 | X4: 6760421 | Y4: 6930128 | Z4: 6930150 | AA4: 6930172 | AB4: 6930152 | AC4: 6930176 | AD4: 6930131 | AE4: 6930134 | AF4: 6930136 | AG4: 6930190 | AH4: 6930156 | AI4: 6930141 | AJ4: 6930191 | AK4: 6930236 | AL4: 6930180 | AM4: 6930185 | AN4: 6930160 | AO4: 6930145 | AP4: 6930235 | AQ4: 6930188 | AS4: 6930165 | AT4: 6930166 | AU4: 6930168 | AV4: 6930195
A5: 6660278 | B5: 6660262 | C5: 6660008 | D5: 6860211 | E5: 6660582 | F5: 6560376 | G5: 6560355 | H5: 6960033 | I5: 6660002 | J5: 6560484 | K5: 6860210 | L5: 6960023 | M5: 6560475 | N5: 6960058 | O5: 6560433 | P5: 6860040 | Q5: 6560525 | R5: 6560517 | S5: 6560492 | T5: 6860147 | U5: 6860274 | V5: 6660029 | W5: 6960077 | X5: 6860175 | AA5: 6930173 | AB5: 6930174 | AC5: 6930177 | AD5: 6930153 | AE5: 6930155 | AF5: 6930137 | AI5: 6930158 | AL5: 6930181 | AM5: 6930240 | AN5: 6930161 | AO5: 6930162 | AQ5: 6930224 | AT5: 6930167 | AU5: 6930169 | AV5: 6930196
A6: 6660446 | B6: 6760372 | C6: 6660159 | D6: 6960097 | E6: 6760420 | F6: 6760124 | G6: 6560356 | H6: 6960055 | I6: 6660210 | J6: 6560481 | K6: 6860286 | L6: 6960202 | M6: 6560466 | N6: 6960098 | O6: 6660173 | P6: 6860065 | Q6: 6660026 | R6: 6560518 | S6: 6760062 | T6: 6860149 | U6: 6860315 | V6: 6860294 | W6: 6960234 | X6: 6860273 | AC6: 6930178 | AD6: 6930154 | AE6: 6930192 | AL6: 6930182 | AO6: 6930163 | AQ6: 6930225 | AT6: 6930194
A7: 6660631 | B7: 6860239 | C7: 6660211 | E7: 6960032 | F7: 6960197 | G7: 6560360 | H7: 6960101 | I7: 6660293 | J7: 6860276 | K7: 6960037 | M7: 6560467 | N7: 6960241 | O7: 6660193 | P7: 6860067 | Q7: 6660517 | R7: 6760135 | S7: 6760190 | T7: 6860174 | U7: 6960238 | V7: 6860295 | X7: 6860280 | AD7: 6930222 | AE7: 6930199 | AL7: 6930183 | AO7: 6930179 | AQ7: 6930237
B8: 6960054 | C8: 6860170 | E8: 6960096 | G8: 6660574 | H8: 6960200 | I8: 6760011 | K8: 6960198 | M8: 6560468 | O8: 6660462 | P8: 6860311 | R8: 6860142 | T8: 6860243 | X8: 6960057 | AD8: 6930223 | AO8: 6930186
B9: 6960095 | K9: 6960201 | M9: 6560472 | O9: 6760388 | P9: 6960056 | T9: 6860305 | X9: 6960076
B10: 6960100 | M10: 6560476 | O10: 6860287 | P10: 6960232 | T10: 6960239
M11: 6560477 | P11: 6960233
M12: 6960014

Sheet Dropdown_Product
A1: Secured | B1: Unsecured | C1: Banca
A2: HomeLoan_BT_less_than_2_Percent | B2: Personal_Cash | C2: MRTA_3_Percent
A3: HomeLoan_BT_more_than_2_Percent | C3: MRTA_6_Percent
A4: HomeLoan_Non_BT | C4: SOMPO
A5: Mortgage_Power_Term

Sheet Dropdown_HomeLoan
A1: HomeLoan_BT_less_than_2_Percent | B1: HomeLoan_BT_more_than_2_Percent | C1: HomeLoan_Non_BT | D1: Mortgage_Power_Term | E1: Extra_Cash | F1: MRTA_3_Percent | G1: MRTA_6_Percent | H1: SOMPO
A2: 3 | B2: 3
A3: 5 | B3: 5

Sheet Dropdown_Deviate
A1: BT_with_5_year_lock_in_period | B1: others
A2: No discount | B2: No discount
A3: <= 0.25% | B3: <= 0.25%
A4: > 0.25% to 0.3% | B4: > 0.25% to 0.3%
A5: > 0.30% to 0.4% | B5: > 0.30% to 0.4%
A6: > 0.40% to 0.50% | B6: > 0.40% to 0.50%
A7: > 0.50% to 0.60% | B7: > 0.50% to 0.60%
A8: > 0.60% to 0.70% | B8: > 0.60% to 0.70%
A9: > 0.70% to 0.75% | B9: > 0.70% to 0.75%
A10: > 0.75% | B10: > 0.75%

Sheet Deviate_Table
A1: Pricing discount | B1: BT_with_5_year_lock_in_period | C1: others
A2: No discount | B2: 1.1 | C2: 1.1
A3: <= 0.25% | B3: 1 | C3: 1
A4: > 0.25% to 0.3% | B4: 1 | C4: 0.95
A5: > 0.30% to 0.4% | B5: 1 | C5: 0.9
A6: > 0.40% to 0.50% | B6: 0.95 | C6: 0.85
A7: > 0.50% to 0.60% | B7: 0.9 | C7: 0.8
A8: > 0.60% to 0.70% | B8: 0.85 | C8: 0.75
A9: > 0.70% to 0.75% | B9: 0.8 | C9: 0.7
A10: > 0.75% | B10: 0.6 | C10: 0.5
