Workbook
Name _Sex11: [1]Home!$M$3
Name _TMO1997: #REF!
Name _TMO1997: #REF!
Name _TMO1997: #REF!
Name _TMO1997: #REF!
Name _TMO1997: #REF!
Name _TMO1997: #REF!
Name _TMO1997: #REF!
Name _TMO1997: #REF!
Name _TMO1997: #REF!
Name _TMO1997: #REF!
Name _TMO1997: #REF!
Name _TMO1997: #REF!
Name _TMO1997: #REF!
Name _TMO1997: #REF!
Name _TMO1997: #REF!
Name _TMO1997: #REF!
Name _TMO1997: #REF!
Name _TMO2008: #REF!
Name _TMO2008: #REF!
Name _TMO2008: #REF!
Name _TMO2008: #REF!
Name _TMO2008: #REF!
Name _TMO2008: #REF!
Name _TMO2008: #REF!
Name _TMO2008: #REF!
Name _TMO2008: #REF!
Name _TMO2008: #REF!
Name _TMO2008: #REF!
Name _TMO2008: #REF!
Name _TMO2008: #REF!
Name _TMO2008: #REF!
Name _TMO2008: #REF!
Name _TMO2008: #REF!
Name _TMO2008: #REF!
Name Age: [1]Home!$M$4
Name camp: #REF!
Name camp: #REF!
Name camp: #REF!
Name camp: #REF!
Name camp: #REF!
Name camp: #REF!
Name camp: #REF!
Name camp: #REF!
Name camp: #REF!
Name camp: #REF!
Name camp: #REF!
Name camp: #REF!
Name CampML: #REF!
Name CampML: #REF!
Name CampML: #REF!
Name CampML: #REF!
Name CampML: #REF!
Name CampML: #REF!
Name CampML: #REF!
Name CampML: #REF!
Name CampML: #REF!
Name CampML: #REF!
Name CampML: #REF!
Name CampML: #REF!

Sheet Secured - Table 1
B1: cr08035 | C1: สินเชื่อบุคคล (ประเภทมีหลักประกัน) | L1: ประกันกู้หลัก
B3: วงเงินสินเชื่อ / อัตราดอกเบี้ย / ยอดผ่อนชำระ/ เบี้ยประกัน/ DIR/สรุปวงเงิน | M3: รายได้ | N3: 20637 | O3: 20668 | P3: 20699 | Q3: 20729 | R3: 20760 | S3: 20790 | T3: 20821 | U3: ชำระงวดจริง | V3: ='eBHomeLoan - Table 1'!N4 -> 281
B4: Home Loan | C4: อายุ | D4: เพศ | E4: คุ้มครองสูงสุด | F4: ระยะเวลาคุ้มครอง (ปี) | G4: อัตราส่วน | H4: ทุนประกัน | I4: MRTA | J4: ระยะเวลากู้สูงสุด | K4: วงเงิน Home Loan 1 | L4: เงินเดือน | M4: 17330 | N4: 17330 | P4: 17330 | Q4: 17330 | R4: 17330 | T4: 18460 | U4: ดอกเบี้ยรวม | V4: ='eBHomeLoan - Table 1'!O4-'eBHomeLoan - Table 1'!G4 -> 2228808.9
B5: กู้หลัก | C5: 30 | D5: หญิง | E5: =IF(C5<=35,30,65-C5) -> 30 | F5: 10 | G5: 55.5 | H5: =K5 -> 2500000 | I5: =G5*H5/1000 -> 138750 | J5: =65-IF(MIN(C5:C7)<=35,35,MIN(C5:C7))&" ปี" -> 30 ปี | K5: 2500000 | L5: เบี้ยเลี้ยง | M5: =SUM(N5:T5)/6 -> 55 | N5: 120 | P5: 120 | Q5: 90 | U5: ประเมิน | V5: 3200
B6: กู้ร่วม 1 | C6: 43 | D6: ชาย | E6: =IF(C6<=35,30,65-C6) -> 22 | F6: 10 | J6: กู้ระยะเวลากู้(ปี) | L6: ค่าล่วงเวลา | M6: =SUM(N6:T6)/6 -> 198.33333 | N6: 649 | P6: 541 | U6: จำนอง | V6: =K8*1/100 -> 26387.5
B7: กู้ร่วม 2 | C7: 43 | D7: ชาย | E7: =IF(C7<=35,30,65-C7) -> 22 | F7: 10 | H7: อัคคีภัยฟรี 3 ปี | J7: =คีย์ข้อมูล!G15 -> 35 | L7: โบนัส | M7: =SUM(N7:S7)/12 -> 2888.3333 | N7: 17330 | S7: 17330 | U7: จ่ายรวม | V7: =V4+V5+V6 -> 2258396.4
B8: ธนาคารอาคารสงเคราะห์ | C8: ยอดคงเหลือ | D8: วงเงินกู้ตามสัญญา | E8: ค่างวด | F8: LTV | H8: รวม MRTA | I8: =SUM(I5:I7) -> 138750 | J8: วงเงินรวม | K8: =K5+I8 -> 2638750 | L8: ค่าโทรศัพท์ | M8: =SUM(N8:S8)/6 -> 50 | Q8: 300
B9: วงเงินบ้าน | C9: 3376000 | D9: 4500000 | E9: 23700 | F9: =C9/D9 -> 0.75022222 | K9: =K8/D16 -> 0.58638889 | L9: เบี้ยเลี้ยงค่าเดินทาง | M9: =SUM(N9:S9)/6 -> 150 | R9: 600 | S9: 300
B10: Mortgage Top UP | C10: อายุ | D10: เพศ | E10: คุ้มครองสูงสุด | F10: ระยะเวลาคุ้มครอง (ปี) | H10: ทุนประกัน | I10: MRTA | J10: ระยะเวลากู้สูงสุด | K10: วงเงิน Home Loan 2 | L10: เงินช่วยเหลือ | M10: =SUM(N10:S10)/6 -> 100 | R10: 300 | S10: 300 | U10: ดอกเบี้ยรวม | V10: ='eBMortgageLoan - Table 1'!O4-'eBMortgageLoan - Table 1'!G4 -> 0
B11: กู้หลัก | C11: =C5 -> 30 | D11: =D5 -> หญิง | E11: =IF(C11=" "," ",IF(B10=I81,IF(C11<=50,15,65-C11),IF(C11<=35,30,65-C11))) -> 30 | F11: 10 | H11: =K11*70/100 -> 0 | I11: =IF(ISERROR(IF(D11="ชาย",(HLOOKUP(F11,OIC_MRTA_bundling!$5:$46,VLOOKUP(C11,OIC_MRTA_bundling!$A$4:$AF$46,32,0),0)*H11),IF(D11="หญิง",(HLOOKUP(F11,OIC_MRTA_bundling!$52:$93,VLOOKUP(C11,OIC_MRTA_bundling!$A$52:$AF$93,32,0),0)*H11))))=TRUE,"",IF(D11="ชาย",(HLOOKUP(F11,OIC_MRTA_bundling!$5:$46,VLOOKUP(C11,OIC_MRTA_bundling!$A$4:$AF$46,32,0),0)*H11),IF(D11="หญิง",(HLOOKUP(F11,OIC_MRTA_bundling!$52:$93,VLOOKUP(C11,OIC_MRTA_bundling!$A$52:$AF$93,32,0),0)*H11)))) -> 0 | J11: =65-IF(MIN(C11:C13)<=35,35,MIN(C11:C13))&" ปี" -> 30 ปี | K11: 0 | L11: ค่าเช่าบ้าน | M11: 10000 | N11: 10000 | O11: 10000 | P11: 10000 | Q11: 10000 | R11: 10000 | S11: 10000 | U11: ชำระงวดจริง | V11: ='eBMortgageLoan - Table 1'!N4 -> 0
B12: กู้ร่วม 1 | J12: ระยะเวลากู้(ปี) | L12: โบนัส ก.พ.56 | M12: =N12/12 -> 5117.75 | N12: 61413
B13: กู้ร่วม 2 | J13: 26 | L13: รับเงินสดจากการออกงานนอกสถานที่ | M13: =SUM(N13:S13)/6 -> 5664.1667 | N13: 6090 | O13: 6822 | P13: 5771 | Q13: 5825 | R13: 6089 | S13: 3388
B14: หลักประกัน บ้านเดี่ยว | C14: LTV สูงสุด 95% ของราคาประเมิน | E14: รายได้ | H14: รวม MRTA | I14: =IF(C19="เงินกู้ปกติ , No MRTA",0,(SUM(I11:I13))) -> 0 | J14: วงเงินรวม | K14: =K11+I14 -> 0 | L14: รวม | M14: =SUM(M4:M13) -> 41553.583
B15: หลักประกัน บ้านเดี่ยว | C15: LTV สูงสุด 95% ของราคาประเมิน | E15: รายได้
B16: ราคาประเมิน = วงเงินกู้ตามสัญญา | D16: 4500000 | E16: เงินเดือน | F16: 53000
B17: เลือกอัตราดอกเบี้ย | E17: Bonus | F17: 0 | H17: คำนวณ DIR | J17: สรุปวงเงิน
B18: Home Loan | C18: ลูกค้า Re-Finance II , No MRTA (waive all fees) | F18: 0 | H18: รายได้รวม | I18: =F19 -> 53000 | J18: Home Loan | K18: =K5 -> 2500000
B19: Mortgage Loan | C19: เงินกู้ปกติ , MRTA | E19: รวม | F19: =SUM(F16:F18) -> 53000 | H19: ภาระใน NCB | I19: =F32 -> 23000 | J19: Mortgage Loan | K19: =K11 -> 0
B20: วันที่ทำสัญญาเงินกู้ ธอส | C20: 30/12/2558 | D20: ( 3 ปีพอดี) | E20: ภาระ | H20: รูปแบบการชำระ | I20: ผ่อนเท่ากันทุกเดือน | J20: MRTA | K20: =I8+I14 -> 138750
B21: ยอดผ่อนต่อเดือน | C21: 54700 | E21: ภาระใน NCB | F21: 23000 | H21: ผ่อน Home Loan | I21: ='ตารางผ่อนวงเงินที่ 1'!F24 -> 6530 | J21: วงเงินรวม | K21: =K18+K19+K20 -> 2638750
B22: อัตราดอกเบี้ยปัจจุบัน | C22: 0.0575 | E22: หักค่างวดบ้านเดิม | F22: 0 | H22: ผ่อน Property Loan | I22: 0 | J22: ผ่อนชำระต่อเดือน | K22: =I21+I22 -> 6530 | CS22: =16000*80/100 -> 12800
F23: 0 | H23: DSR | I23: =(I19+I21+I22)/I18 -> 0.55716981 | J23: LTV | K23: =(K5+K11)/D16 -> 0.55555556
E24: รวม | F24: =SUM(F21:F23) -> 23000 | H24: Net Income | I24: =F19-K22-I19 -> 23470 | J24: MAX LTV | K24: =K21/D16 -> 0.58638889
E32: รวม | F32: =SUM(F21:F23) -> 23000
B33: Home Loan | C33: =C18 -> ลูกค้า Re-Finance II , No MRTA (waive all fees) | E33: Property Loan | F33: =C19 -> เงินกู้ปกติ , MRTA | I33: Mortgage OD
B34: วงเงินกู้ (บาท) | C34: =K8 -> 2638750 | E34: วงเงินกู้ (บาท) | F34: =K14 -> 0 | I34: วงเงินกู้ (บาท) | J34: 0
B35: ระยะเวลากู้ (ปี) | C35: =J7 -> 35 | E35: ระยะเวลากู้ (ปี) | F35: =J13 -> 26 | J35: OD Protection | K35: No OD Protection
C36: อัตราดอกเบี้ย (ต่อปี) | F36: อัตราดอกเบี้ย (ต่อปี) | J36: อัตราดอกเบี้ย (ต่อปี) | K36: อัตราดอกเบี้ย (ต่อปี)
B37: =VLOOKUP($C$33,$L$79:$AY$98,AH$76,FALSE) -> 420 | C37: MRR-4.50% | D37: 0.034 | E37: =VLOOKUP($F$33,$L$104:$AW$108,AH$76,FALSE) -> 420 | F37: MRR-2.00% | H37: 0.069 | J37: =$J$40 -> 0.08 | K37: =$J$40+0.5% -> 0.085
B38: =VLOOKUP($C$33,$L$79:$AY$98,AI$76,FALSE) -> ปีที่ 1 | C38: MRR-2.50% | D38: 0.054 | E38: =VLOOKUP($F$33,$L$104:$AW$108,AI$76,FALSE) -> ปีที่ 1 | F38: =VLOOKUP($F$33,$L$104:$AW$108,AN$76,FALSE) -> MLR-1.25% | H38: =VLOOKUP($F$33,$L$104:$AW$108,AS$76,FALSE) -> 0.079
B39: =VLOOKUP($C$33,$L$79:$AY$98,AJ$76,FALSE) -> ปีที่ 2 | C39: MRR-2.50% | D39: 0.054 | E39: =VLOOKUP($F$33,$L$104:$AW$108,AJ$76,FALSE) | F39: =VLOOKUP($F$33,$L$104:$AW$108,AO$76,FALSE) -> -1 | H39: =VLOOKUP($F$33,$L$104:$AW$108,AT$76,FALSE) -> 0.079 | J39: MOR | K39: MOR+0.5%
B40: =VLOOKUP($C$33,$L$79:$AY$98,AK$76,FALSE) -> ปีที่ 3 | C40: =VLOOKUP($C$33,$L$79:$AY$98,AP$76,FALSE) -> MLR-1.25% | D40: =VLOOKUP($C$33,$L$79:$AY$98,AU$76,FALSE) -> 0.079 | E40: =VLOOKUP($F$33,$L$104:$AW$108,AK$76,FALSE) | F40: =VLOOKUP($F$33,$L$104:$AW$108,AP$76,FALSE) -> -1 | H40: =VLOOKUP($F$33,$L$104:$AW$108,AU$76,FALSE) -> 0.079 | I40: MOR = : | J40: 0.08
B41: =VLOOKUP($C$33,$L$79:$AY$98,AL$76,FALSE) | C41: MRR-1.50% | D41: 0.064 | E41: =VLOOKUP($F$33,$L$104:$AW$108,AL$76,FALSE) | F41: MRR-0.75% | H41: =D44-0.75% -> 0.0715
C42: Grace Period | D42: =VLOOKUP($C$33,$L$79:$AY$98,38,FALSE) -> N | H42: ยอดผ่อนชำระต่อเดือน (บาท) | J42: ยอดผ่อนชำระต่อเดือน (บาท) | K42: ยอดผ่อนชำระต่อเดือน (บาท)
D43: =VLOOKUP($C$33,$L$79:$AY$98,39,FALSE) -> Y
C44: MRR = : | D44: 0.079 | H44: ='eBMortgageLoan - Table 1'!$M$4 -> 0 | J44: =ROUNDUP(J34*(J37/12),-1) -> 0 | K44: =ROUNDUP(J34*(K37/12),-1) -> 0
B48: แบบที่ 1 Option 1 | D48: แบบที่ 2 Option 2 | F48: แบบที่ 3 Option 3 | I48: แบบที่ 4 Option 4
B49: ผ่อนเท่ากันทุกเดือน Flat Rate | D49: ผ่อนเท่ากันทุกเดือน Flat Rate | F49: ผ่อนแบบขั้นบันได Step Rate | I49: ผ่อนแบบขั้นบันได Step Rate
B50: ไม่มี No Grace Period | D50: มี With Grace Period | F50: ไม่มี No Grace Period | I50: มี With Grace Period
B51: ยอดผ่อนชำระต่อเดือน (บาท)
C52: =IF(LEFT($C$33,8)="Mortgage"," ",'eBHomeLoan - Table 1'!$M$4) -> 17340 | D52: ปีที่ 1 | E52: =IF($D$42="N"," ",'eBHomeLoan - Table 1'!$M$14) | F52: ปีที่ 1 และ 2 | H52: =IF(LEFT($C$33,8)="Mortgage"," ",'eBHomeLoan - Table 1'!$M$9) -> 14040 | I52: ปีที่ 1 | J52: ='eBHomeLoan - Table 1'!M14 -> 7620
D53: ปีที่ 2 เป็นต้นไป | E53: =IF($D$42="N"," ",'eBHomeLoan - Table 1'!$M$5) | F53: ปีที่ 3 และ 4 | H53: =IF(LEFT($C$33,8)="Mortgage"," ",'eBHomeLoan - Table 1'!$M$10) -> 15440 | I53: ปีที่ 2 และ 3 | J53: ='eBHomeLoan - Table 1'!M15 -> 14130
F54: ปีที่ 5 เป็นต้นไป | H54: =IF(LEFT($C$33,8)="Mortgage"," ",'eBHomeLoan - Table 1'!$M$11) -> 18400 | I54: ปีที่ 4 และ 5 | J54: ='eBHomeLoan - Table 1'!M16 -> 15540
I55: ปีที่ 6 เป็นต้นไป | J55: ='eBHomeLoan - Table 1'!M17 -> 18490
B58: แบบที่ 1 Option 1 | D58: แบบที่ 2 Option 2 | F58: แบบที่ 3 Option 3 | I58: แบบที่ 4 Option 4
B59: ผ่อนเท่ากันทุกเดือน Flat Rate | D59: ผ่อนเท่ากันทุกเดือน Flat Rate | F59: ผ่อนแบบขั้นบันได Step Rate | I59: ผ่อนแบบขั้นบันได Step Rate
B60: ไม่มี No Grace Period | D60: มี With Grace Period | F60: ไม่มี No Grace Period | I60: มี With Grace Period
B61: ยอดผ่อนชำระต่อเดือน (บาท)
C62: =IF(LEFT($C$33,8)="Mortgage"," ",'eBMortgageLoan - Table 1'!$M$4) -> 0 | D62: ปีที่ 1 | E62: =IF(LEFT($C$33,8)="Mortgage"," ",'eBMortgageLoan - Table 1'!$M$14) -> 0 | F62: ปีที่ 1 และ 2 | H62: =IF(LEFT($C$33,8)="Mortgage"," ",'eBMortgageLoan - Table 1'!$M$9) -> 0 | I62: ปีที่ 1 | J62: =IF(LEFT($C$33,8)="Mortgage"," ",'eBMortgageLoan - Table 1'!$M$14) -> 0
D63: ปีที่ 2 เป็นต้นไป | E63: =IF(LEFT($C$33,8)="Mortgage"," ",'eBMortgageLoan - Table 1'!$M$5) -> 0 | F63: ปีที่ 3 และ 4 | H63: =IF(LEFT($C$33,8)="Mortgage"," ",'eBMortgageLoan - Table 1'!$M$10) -> 0 | I63: ปีที่ 2 และ 3 | J63: =IF(LEFT($C$33,8)="Mortgage"," ",'eBMortgageLoan - Table 1'!$M$15) -> 0
F64: ปีที่ 5 เป็นต้นไป | H64: =IF(LEFT($C$33,8)="Mortgage"," ",'eBMortgageLoan - Table 1'!$M$11) -> 0 | I64: ปีที่ 4 และ 5 | J64: =IF(LEFT($C$33,8)="Mortgage"," ",'eBMortgageLoan - Table 1'!$M$16) -> 0
I65: ปีที่ 6 เป็นต้นไป | J65: =IF(LEFT($C$33,8)="Mortgage"," ",'eBMortgageLoan - Table 1'!$M$17) -> 0
B67: ค่าใช้จ่ายเบื้องต้นโดยประมาณ Other Expense (Estimated)
B68: ค่าประเมินราคา | C68: =ROUNDUP(2500*1.07,0) -> 2675 | E68: ค่าธรรมเนียมสินเชื่อ | F68: =ROUNDUP(MAX(IF($C$34*0.1%<1500,1500,$C$34*0.1%),IF(SUM($F$34,$J$34)=0,0,IF(SUM($F$34,$J$34)*0.2%<2500,2500,IF(SUM($F$34,$J$34)*0.2%>10000,10000,SUM($F$34,$J$34)*0.2%)))),0) -> 2639 | I68: ค่าอากรแสตมป์ | J68: =SUM(ROUNDUP($C$34*0.05%,0),ROUNDUP($F$34*0.05%,0),ROUNDUP($J$34*0.05%,0)) -> 1320
I69: ค่าใช้จ่ายรวม | J69: =SUM($C$68,$J$68) -> 3995
B72: 1. ค่าประเมินราคาหลักประกัน (กทม.&ปริมณฑล 2,500 บาท +VAT)
B73: 2. ค่าธรรมเนียมสินเชื่อ ; คิดจากค่าธรรมเนียมที่สูงกว่าระหว่าง Home Loan และ Mortgage Power เพียงจำนวนเดียว
B74: (Home Loan 0.25% ของวงเงินกู้ ขั้นต่ำ 1,500 บาท ; Mortgage Loan 0.2% ของวงเงินกู้ ขั้นต่ำ 2,500 บาท สูงสุด 10,000 บาท)
B75: 2. ค่าอากรแสตมป์ สำหรับติดในสัญญาต่าง ๆ (0.05% ของวงเงินกู้ สูงสุด 10,000 บาท)
B76: 3. ค่าเบี้ยประกันอัคคีภัย ราย 5 ปี (บ้านเดี่ยว / บ้านไม่โดดเดี่ยว) | L76: 1 | M76: 2 | N76: 3 | O76: 4 | P76: 5 | Q76: 6 | R76: 7 | S76: 8 | T76: 9 | U76: 10 | V76: 11 | AA76: 16 | AC76: 17 | AD76: 18 | AE76: 19 | AF76: 20 | AG76: 21 | AH76: 22 | AI76: 23 | AJ76: 24 | AK76: 25 | AL76: 26 | AM76: 27 | AN76: 28 | AO76: 29 | AP76: 30 | AQ76: 31 | AR76: 32 | AS76: 33 | AT76: 34 | AU76: 35 | AV76: 36 | AW76: 37 | AX76: 38 | AY76: 39
K77: ชาย | L77: Home Loan 4U | M77: จำนวนงวด (เดือน) | R77: อัตราดอกเบี้ยอ้างอิง | AC77: จำนวนงวดสะสม (เดือน) | AH77: ระยะเวลา | AM77: อัตราดอกเบี้ยอ้างอิง | AR77: อัตราดอกเบี้ย / ส่วนต่าง
K78: หญิง | L78: Campaign | M78: Tier 1 | N78: Tier 2 | O78: Tier 3 | P78: Tier 4 | Q78: Tier 5 | R78: Tier 1 | S78: Tier 2 | T78: Tier 3 | U78: Tier 4 | V78: Tier 5 | AA78: Tier 5 | AC78: Tier 1 | AD78: Tier 2 | AE78: Tier 3 | AF78: Tier 4 | AG78: Tier 5 | AH78: Tier 1 | AI78: Tier 2 | AJ78: Tier 3 | AK78: Tier 4 | AL78: Tier 5 | AM78: Tier 1 | AN78: Tier 2 | AO78: Tier 3 | AP78: Tier 4 | AQ78: Tier 5 | AR78: Tier 1 | AS78: Tier 2 | AT78: Tier 3 | AU78: Tier 4 | AV78: Tier 5 | AW78: Grace | AX78: Grace | AY78: Grace
L79: ลูกค้าทั่วไป , MRTA | M79: 12 | Q79: =420-SUM(M79:P79) -> 408 | R79: FR | S79: FR | V79: MLR | AA79: -0.005 | AC79: =SUM($M79:M79) -> 12 | AD79: =SUM($M79:N79) -> 12 | AE79: =SUM($M79:O79) -> 12 | AF79: =SUM($M79:P79) -> 12 | AG79: =SUM($M79:Q79) -> 420 | AH79: ปีที่ 1 | AL79: ปีที่ 2 เป็นต้นไป | AM79: คงที่ | AN79: -1 | AO79: -1 | AP79: -1 | AQ79: MLR-0.50% | AR79: =IF(R79="FR",W79,$D$44+W79) -> 0 | AS79: =IF(N79=0,AR79,IF(S79="FR",X79,$D$44+X79)) -> 0 | AT79: =IF(O79=0,AS79,IF(T79="FR",Y79,$D$44+Y79)) -> 0 | AU79: =IF(P79=0,AT79,IF(U79="FR",Z79,$D$44+Z79)) -> 0 | AV79: =IF(Q79=0,AU79,IF(V79="FR",AA79,$D$44+AA79)) -> 0.074 | AW79: =IF(M79>=12,IF(R79="FR","Y","N"),IF(AND(R79="FR",S79="FR"),"Y","N")) -> Y | AX79: Y | AY79: =IF(M79>=12,IF(R79="FR","Y","N"),IF(AND(R79="MLR",S79="MLR"),"Y","N")) -> Y
L80: ลูกค้าทั่วไป , No MRTA | M80: 12 | Q80: =420-SUM(M80:P80) -> 408 | R80: FR | S80: FR | V80: MLR | AA80: -0.005 | AC80: =SUM($M80:M80) -> 12 | AD80: =SUM($M80:N80) -> 12 | AE80: =SUM($M80:O80) -> 12 | AF80: =SUM($M80:P80) -> 12 | AG80: =SUM($M80:Q80) -> 420 | AH80: ปีที่ 1 | AL80: ปีที่ 2 เป็นต้นไป | AM80: คงที่ | AN80: -1 | AO80: -1 | AP80: -1 | AQ80: MLR-0.50% | AR80: =IF(R80="FR",W80,$D$44+W80) -> 0 | AS80: =IF(N80=0,AR80,IF(S80="FR",X80,$D$44+X80)) -> 0 | AT80: =IF(O80=0,AS80,IF(T80="FR",Y80,$D$44+Y80)) -> 0 | AU80: =IF(P80=0,AT80,IF(U80="FR",Z80,$D$44+Z80)) -> 0 | AV80: =IF(Q80=0,AU80,IF(V80="FR",AA80,$D$44+AA80)) -> 0.074 | AW80: =IF(M80>=12,IF(R80="FR","Y","N"),IF(AND(R80="FR",S80="FR"),"Y","N")) -> Y | AX80: Y | AY80: =IF(M80>=12,IF(R80="FR","Y","N"),IF(AND(R80="MLR",S80="MLR"),"Y","N")) -> Y
I81: Mortgage ปกติ | J81: รูปแบบการผ่อนชำระ | K81: รูปแบบการผ่อนชำระ | L81: ลูกค้า Re-Finance I , MRTA | M81: 6 | N81: 6 | O81: 12 | P81: 12 | Q81: =420-SUM(M81:P81) -> 384 | R81: FR | S81: MLR | T81: MLR | U81: MLR | V81: MLR | AA81: -0.015 | AC81: =SUM($M81:M81) -> 6 | AD81: =SUM($M81:N81) -> 12 | AE81: =SUM($M81:O81) -> 24 | AF81: =SUM($M81:P81) -> 36 | AG81: =SUM($M81:Q81) -> 420 | AH81: เดือนที่ 1 - 6 | AI81: เดือนที่ 7 - 12 | AJ81: ปีที่ 2 | AK81: ปีที่ 3 | AL81: ปีที่ 4 เป็นต้นไป | AM81: คงที่ | AN81: MLR-3.50% | AO81: MLR-2.00% | AP81: MLR-1.75% | AQ81: MLR-1.50% | AR81: =IF(R81="FR",W81,$D$44+W81) -> 0 | AS81: =IF(N81=0,AR81,IF(S81="FR",X81,$D$44+X81)) -> 0.079 | AT81: =IF(O81=0,AS81,IF(T81="FR",Y81,$D$44+Y81)) -> 0.079 | AU81: =IF(P81=0,AT81,IF(U81="FR",Z81,$D$44+Z81)) -> 0.079 | AV81: =IF(Q81=0,AU81,IF(V81="FR",AA81,$D$44+AA81)) -> 0.064 | AW81: =IF(M81>=12,IF(R81="FR","Y","N"),IF(AND(R81="FR",S81="FR"),"Y","N")) -> N | AX81: =IF(M81>=12,IF(S81="MLR","Y","N"),IF(OR(R81="MLR",S81="MLR"),"Y","N")) -> Y | AY81: =IF(M81>=12,IF(R81="FR","Y","N"),IF(AND(R81="MLR",S81="MLR"),"Y","N")) -> N
I82: Mortgage Top UP | J82: ผ่อนเท่ากันทุกเดือน | K82: =B49 -> ผ่อนเท่ากันทุกเดือน Flat Rate | L82: ลูกค้า Re-Finance I , No MRTA | M82: 6 | N82: 6 | O82: 12 | P82: 12 | Q82: =420-SUM(M82:P82) -> 384 | R82: FR | S82: MLR | T82: MLR | U82: MLR | V82: MLR | AA82: -0.015 | AC82: =SUM($M82:M82) -> 6 | AD82: =SUM($M82:N82) -> 12 | AE82: =SUM($M82:O82) -> 24 | AF82: =SUM($M82:P82) -> 36 | AG82: =SUM($M82:Q82) -> 420 | AH82: เดือนที่ 1 - 6 | AI82: เดือนที่ 7 - 12 | AJ82: ปีที่ 2 | AK82: ปีที่ 3 | AL82: ปีที่ 4 เป็นต้นไป | AM82: คงที่ | AN82: MLR-3.50% | AO82: MLR-2.00% | AP82: MLR-1.75% | AQ82: MLR-1.50% | AR82: =IF(R82="FR",W82,$D$44+W82) -> 0 | AS82: =IF(N82=0,AR82,IF(S82="FR",X82,$D$44+X82)) -> 0.079 | AT82: =IF(O82=0,AS82,IF(T82="FR",Y82,$D$44+Y82)) -> 0.079 | AU82: =IF(P82=0,AT82,IF(U82="FR",Z82,$D$44+Z82)) -> 0.079 | AV82: =IF(Q82=0,AU82,IF(V82="FR",AA82,$D$44+AA82)) -> 0.064 | AW82: =IF(M82>=12,IF(R82="FR","Y","N"),IF(AND(R82="FR",S82="FR"),"Y","N")) -> N | AX82: =IF(M82>=12,IF(S82="MLR","Y","N"),IF(OR(R82="MLR",S82="MLR"),"Y","N")) -> Y | AY82: =IF(M82>=12,IF(R82="FR","Y","N"),IF(AND(R82="MLR",S82="MLR"),"Y","N")) -> N
J83: ดอกเบี้ยปีแรกหลังจากนั้น ผ่อนเท่ากันทุกเดือน | K83: =D49 -> ผ่อนเท่ากันทุกเดือน Flat Rate | L83: ลูกค้า Re-Finance II , MRTA (waive all fees) | M83: 12 | N83: 12 | O83: 12 | Q83: =420-SUM(M83:P83) -> 384 | R83: MLR | S83: MLR | T83: MLR | V83: MLR | AA83: -0.01 | AC83: =SUM($M83:M83) -> 12 | AD83: =SUM($M83:N83) -> 24 | AE83: =SUM($M83:O83) -> 36 | AF83: =SUM($M83:P83) -> 36 | AG83: =SUM($M83:Q83) -> 420 | AH83: ปีที่ 1 | AI83: ปีที่ 2 | AJ83: ปีที่ 3 | AL83: ปีที่ 4 เป็นต้นไป | AM83: MLR-4.00% | AN83: MLR-1.50% | AO83: MLR-1.50% | AP83: -1 | AQ83: MLR-1.00% | AR83: =IF(R83="FR",W83,$D$44+W83) -> 0.079 | AS83: =IF(N83=0,AR83,IF(S83="FR",X83,$D$44+X83)) -> 0.079 | AT83: =IF(O83=0,AS83,IF(T83="FR",Y83,$D$44+Y83)) -> 0.079 | AU83: =IF(P83=0,AT83,IF(U83="FR",Z83,$D$44+Z83)) -> 0.079 | AV83: =IF(Q83=0,AU83,IF(V83="FR",AA83,$D$44+AA83)) -> 0.069 | AW83: =IF(M83>=12,IF(R83="FR","Y","N"),IF(AND(R83="FR",S83="FR"),"Y","N")) -> N | AX83: =IF(M83>=12,IF(S83="MLR","Y","N"),IF(OR(R83="MLR",S83="MLR"),"Y","N")) -> Y | AY83: =IF(M83>=12,IF(R83="FR","Y","N"),IF(AND(R83="MLR",S83="MLR"),"Y","N")) -> N
J84: ผ่อนชำระแบบขั้นบันได | K84: =F49 -> ผ่อนแบบขั้นบันได Step Rate | L84: ลูกค้า Re-Finance II , No MRTA (waive all fees) | M84: 12 | N84: 12 | O84: 12 | Q84: =420-SUM(M84:P84) -> 384 | R84: MLR | S84: MLR | T84: MLR | V84: MLR | AA84: -0.01 | AC84: =SUM($M84:M84) -> 12 | AD84: =SUM($M84:N84) -> 24 | AE84: =SUM($M84:O84) -> 36 | AF84: =SUM($M84:P84) -> 36 | AG84: =SUM($M84:Q84) -> 420 | AH84: ปีที่ 1 | AI84: ปีที่ 2 | AJ84: ปีที่ 3 | AL84: ปีที่ 4 เป็นต้นไป | AM84: MLR-3.00% | AN84: MLR-1.50% | AO84: MLR-1.25% | AP84: -1 | AQ84: MLR-1.00% | AR84: =IF(R84="FR",W84,$D$44+W84) -> 0.079 | AS84: =IF(N84=0,AR84,IF(S84="FR",X84,$D$44+X84)) -> 0.079 | AT84: =IF(O84=0,AS84,IF(T84="FR",Y84,$D$44+Y84)) -> 0.079 | AU84: =IF(P84=0,AT84,IF(U84="FR",Z84,$D$44+Z84)) -> 0.079 | AV84: =IF(Q84=0,AU84,IF(V84="FR",AA84,$D$44+AA84)) -> 0.069 | AW84: =IF(M84>=12,IF(R84="FR","Y","N"),IF(AND(R84="FR",S84="FR"),"Y","N")) -> N | AX84: =IF(M84>=12,IF(S84="MLR","Y","N"),IF(OR(R84="MLR",S84="MLR"),"Y","N")) -> Y | AY84: =IF(M84>=12,IF(R84="FR","Y","N"),IF(AND(R84="MLR",S84="MLR"),"Y","N")) -> N
J85: ดอกเบี้ยปีแรกหลังจากนั้น ผ่อนขั้นบันได | K85: =I49 -> ผ่อนแบบขั้นบันได Step Rate | L85: ลูกค้า Project 0% 6 เดือน , MRTA | M85: 6 | N85: 6 | Q85: =420-SUM(M85:P85) -> 408 | R85: FR | S85: MLR | V85: MLR | AA85: -0.015 | AC85: =SUM($M85:M85) -> 6 | AD85: =SUM($M85:N85) -> 12 | AE85: =SUM($M85:O85) -> 12 | AF85: =SUM($M85:P85) -> 12 | AG85: =SUM($M85:Q85) -> 420 | AH85: เดือนที่ 1 - 6 | AI85: เดือนที่ 7 - 12 | AL85: ปีที่ 2 เป็นต้นไป | AM85: คงที่ | AN85: MLR-2.00% | AO85: -1 | AP85: -1 | AQ85: MLR-1.50% | AR85: =IF(R85="FR",W85,$D$44+W85) -> 0 | AS85: =IF(N85=0,AR85,IF(S85="FR",X85,$D$44+X85)) -> 0.079 | AT85: =IF(O85=0,AS85,IF(T85="FR",Y85,$D$44+Y85)) -> 0.079 | AU85: =IF(P85=0,AT85,IF(U85="FR",Z85,$D$44+Z85)) -> 0.079 | AV85: =IF(Q85=0,AU85,IF(V85="FR",AA85,$D$44+AA85)) -> 0.064 | AW85: =IF(M85>=12,IF(R85="FR","Y","N"),IF(AND(R85="FR",S85="FR"),"Y","N")) -> N | AX85: N | AY85: =IF(M85>=12,IF(R85="FR","Y","N"),IF(AND(R85="MLR",S85="MLR"),"Y","N")) -> N
L86: ลูกค้า Project 0.99% 11 เดือน , MRTA | M86: 11 | N86: 1 | Q86: =420-SUM(M86:P86) -> 408 | R86: FR | S86: MLR | V86: MLR | AA86: -0.015 | AC86: =SUM($M86:M86) -> 11 | AD86: =SUM($M86:N86) -> 12 | AE86: =SUM($M86:O86) -> 12 | AF86: =SUM($M86:P86) -> 12 | AG86: =SUM($M86:Q86) -> 420 | AH86: เดือนที่ 1 - 11 | AI86: เดือนที่ 12 - 12 | AL86: ปีที่ 2 เป็นต้นไป | AM86: คงที่ | AN86: MLR-1.50% | AO86: -1 | AP86: -1 | AQ86: MLR-1.50% | AR86: =IF(R86="FR",W86,$D$44+W86) -> 0 | AS86: =IF(N86=0,AR86,IF(S86="FR",X86,$D$44+X86)) -> 0.079 | AT86: =IF(O86=0,AS86,IF(T86="FR",Y86,$D$44+Y86)) -> 0.079 | AU86: =IF(P86=0,AT86,IF(U86="FR",Z86,$D$44+Z86)) -> 0.079 | AV86: =IF(Q86=0,AU86,IF(V86="FR",AA86,$D$44+AA86)) -> 0.064 | AW86: =IF(M86>=12,IF(R86="FR","Y","N"),IF(AND(R86="FR",S86="FR"),"Y","N")) -> N | AX86: =IF(M86>=12,IF(S86="MLR","Y","N"),IF(OR(R86="MLR",S86="MLR"),"Y","N")) -> Y | AY86: Y
L87: ลูกค้า Project Float Rate , MRTA | M87: 12 | N87: 12 | O87: 12 | Q87: =420-SUM(M87:P87) -> 384 | R87: MLR | S87: MLR | T87: MLR | V87: MLR | AA87: -0.015 | AC87: =SUM($M87:M87) -> 12 | AD87: =SUM($M87:N87) -> 24 | AE87: =SUM($M87:O87) -> 36 | AF87: =SUM($M87:P87) -> 36 | AG87: =SUM($M87:Q87) -> 420 | AH87: ปีที่ 1 | AI87: ปีที่ 2 | AJ87: ปีที่ 3 | AL87: ปีที่ 4 เป็นต้นไป | AM87: MLR-4.00% | AN87: MLR-3.50% | AO87: MLR-2.00% | AP87: -1 | AQ87: MLR-1.50% | AR87: =IF(R87="FR",W87,$D$44+W87) -> 0.079 | AS87: =IF(N87=0,AR87,IF(S87="FR",X87,$D$44+X87)) -> 0.079 | AT87: =IF(O87=0,AS87,IF(T87="FR",Y87,$D$44+Y87)) -> 0.079 | AU87: =IF(P87=0,AT87,IF(U87="FR",Z87,$D$44+Z87)) -> 0.079 | AV87: =IF(Q87=0,AU87,IF(V87="FR",AA87,$D$44+AA87)) -> 0.064 | AW87: =IF(M87>=12,IF(R87="FR","Y","N"),IF(AND(R87="FR",S87="FR"),"Y","N")) -> N | AX87: =IF(M87>=12,IF(S87="MLR","Y","N"),IF(OR(R87="MLR",S87="MLR"),"Y","N")) -> Y | AY87: Y
L88: ลูกค้า Project Float Rate , No MRTA | M88: 12 | N88: 12 | Q88: =420-SUM(M88:P88) -> 396 | R88: MLR | S88: MLR | V88: MLR | AA88: -0.015 | AC88: =SUM($M88:M88) -> 12 | AD88: =SUM($M88:N88) -> 24 | AE88: =SUM($M88:O88) -> 24 | AF88: =SUM($M88:P88) -> 24 | AG88: =SUM($M88:Q88) -> 420 | AH88: ปีที่ 1 | AI88: ปีที่ 2 | AL88: ปีที่ 3 เป็นต้นไป | AM88: MLR-4.00% | AN88: MLR-2.00% | AO88: -1 | AP88: -1 | AQ88: MLR-1.50% | AR88: =IF(R88="FR",W88,$D$44+W88) -> 0.079 | AS88: =IF(N88=0,AR88,IF(S88="FR",X88,$D$44+X88)) -> 0.079 | AT88: =IF(O88=0,AS88,IF(T88="FR",Y88,$D$44+Y88)) -> 0.079 | AU88: =IF(P88=0,AT88,IF(U88="FR",Z88,$D$44+Z88)) -> 0.079 | AV88: =IF(Q88=0,AU88,IF(V88="FR",AA88,$D$44+AA88)) -> 0.064 | AW88: =IF(M88>=12,IF(R88="FR","Y","N"),IF(AND(R88="FR",S88="FR"),"Y","N")) -> N | AX88: =IF(M88>=12,IF(S88="MLR","Y","N"),IF(OR(R88="MLR",S88="MLR"),"Y","N")) -> Y | AY88: Y
Q89: =420-SUM(M89:P89) -> 420 | AC89: =SUM($M89:M89) -> 0 | AD89: =SUM($M89:N89) -> 0 | AE89: =SUM($M89:O89) -> 0 | AF89: =SUM($M89:P89) -> 0 | AG89: =SUM($M89:Q89) -> 420 | AH89: ปีที่ 0 | AL89: ปีที่ 1 เป็นต้นไป | AM89: -1 | AN89: -1 | AO89: -1 | AP89: -1 | AR89: =IF(R89="FR",W89,$D$44+W89) -> 0.079 | AS89: =IF(N89=0,AR89,IF(S89="FR",X89,$D$44+X89)) -> 0.079 | AT89: =IF(O89=0,AS89,IF(T89="FR",Y89,$D$44+Y89)) -> 0.079 | AU89: =IF(P89=0,AT89,IF(U89="FR",Z89,$D$44+Z89)) -> 0.079 | AV89: =IF(Q89=0,AU89,IF(V89="FR",AA89,$D$44+AA89)) -> 0.079 | AW89: =IF(M89>=12,IF(R89="FR","Y","N"),IF(AND(R89="FR",S89="FR"),"Y","N")) -> N | AX89: =IF(M89>=12,IF(S89="MLR","Y","N"),IF(OR(R89="MLR",S89="MLR"),"Y","N")) -> N | AY89: =IF(M89>=12,IF(R89="FR","Y","N"),IF(AND(R89="MLR",S89="MLR"),"Y","N")) -> N
Q90: =420-SUM(M90:P90) -> 420 | AC90: =SUM($M90:M90) -> 0 | AD90: =SUM($M90:N90) -> 0 | AE90: =SUM($M90:O90) -> 0 | AF90: =SUM($M90:P90) -> 0 | AG90: =SUM($M90:Q90) -> 420 | AH90: ปีที่ 0 | AL90: ปีที่ 1 เป็นต้นไป | AM90: -1 | AN90: -1 | AO90: -1 | AP90: -1 | AR90: =IF(R90="FR",W90,$D$44+W90) -> 0.079 | AS90: =IF(N90=0,AR90,IF(S90="FR",X90,$D$44+X90)) -> 0.079 | AT90: =IF(O90=0,AS90,IF(T90="FR",Y90,$D$44+Y90)) -> 0.079 | AU90: =IF(P90=0,AT90,IF(U90="FR",Z90,$D$44+Z90)) -> 0.079 | AV90: =IF(Q90=0,AU90,IF(V90="FR",AA90,$D$44+AA90)) -> 0.079 | AW90: =IF(M90>=12,IF(R90="FR","Y","N"),IF(AND(R90="FR",S90="FR"),"Y","N")) -> N | AX90: =IF(M90>=12,IF(S90="MLR","Y","N"),IF(OR(R90="MLR",S90="MLR"),"Y","N")) -> N | AY90: =IF(M90>=12,IF(R90="FR","Y","N"),IF(AND(R90="MLR",S90="MLR"),"Y","N")) -> N
Q91: =420-SUM(M91:P91) -> 420 | AC91: =SUM($M91:M91) -> 0 | AD91: =SUM($M91:N91) -> 0 | AE91: =SUM($M91:O91) -> 0 | AF91: =SUM($M91:P91) -> 0 | AG91: =SUM($M91:Q91) -> 420 | AH91: ปีที่ 0 | AL91: ปีที่ 1 เป็นต้นไป | AM91: -1 | AN91: -1 | AO91: -1 | AP91: -1 | AR91: =IF(R91="FR",W91,$D$44+W91) -> 0.079 | AS91: =IF(N91=0,AR91,IF(S91="FR",X91,$D$44+X91)) -> 0.079 | AT91: =IF(O91=0,AS91,IF(T91="FR",Y91,$D$44+Y91)) -> 0.079 | AU91: =IF(P91=0,AT91,IF(U91="FR",Z91,$D$44+Z91)) -> 0.079 | AV91: =IF(Q91=0,AU91,IF(V91="FR",AA91,$D$44+AA91)) -> 0.079 | AW91: =IF(M91>=12,IF(R91="FR","Y","N"),IF(AND(R91="FR",S91="FR"),"Y","N")) -> N | AX91: =IF(M91>=12,IF(S91="MLR","Y","N"),IF(OR(R91="MLR",S91="MLR"),"Y","N")) -> N | AY91: =IF(M91>=12,IF(R91="FR","Y","N"),IF(AND(R91="MLR",S91="MLR"),"Y","N")) -> N
Q92: =420-SUM(M92:P92) -> 420 | AC92: =SUM($M92:M92) -> 0 | AD92: =SUM($M92:N92) -> 0 | AE92: =SUM($M92:O92) -> 0 | AF92: =SUM($M92:P92) -> 0 | AG92: =SUM($M92:Q92) -> 420 | AH92: ปีที่ 0 | AL92: ปีที่ 1 เป็นต้นไป | AM92: -1 | AN92: -1 | AO92: -1 | AP92: -1 | AR92: =IF(R92="FR",W92,$D$44+W92) -> 0.079 | AS92: =IF(N92=0,AR92,IF(S92="FR",X92,$D$44+X92)) -> 0.079 | AT92: =IF(O92=0,AS92,IF(T92="FR",Y92,$D$44+Y92)) -> 0.079 | AU92: =IF(P92=0,AT92,IF(U92="FR",Z92,$D$44+Z92)) -> 0.079 | AV92: =IF(Q92=0,AU92,IF(V92="FR",AA92,$D$44+AA92)) -> 0.079 | AW92: =IF(M92>=12,IF(R92="FR","Y","N"),IF(AND(R92="FR",S92="FR"),"Y","N")) -> N | AX92: =IF(M92>=12,IF(S92="MLR","Y","N"),IF(OR(R92="MLR",S92="MLR"),"Y","N")) -> N | AY92: =IF(M92>=12,IF(R92="FR","Y","N"),IF(AND(R92="MLR",S92="MLR"),"Y","N")) -> N
Q93: =420-SUM(M93:P93) -> 420 | AC93: =SUM($M93:M93) -> 0 | AD93: =SUM($M93:N93) -> 0 | AE93: =SUM($M93:O93) -> 0 | AF93: =SUM($M93:P93) -> 0 | AG93: =SUM($M93:Q93) -> 420 | AH93: ปีที่ 0 | AL93: ปีที่ 1 เป็นต้นไป | AM93: -1 | AN93: -1 | AO93: -1 | AP93: -1 | AR93: =IF(R93="FR",W93,$D$44+W93) -> 0.079 | AS93: =IF(N93=0,AR93,IF(S93="FR",X93,$D$44+X93)) -> 0.079 | AT93: =IF(O93=0,AS93,IF(T93="FR",Y93,$D$44+Y93)) -> 0.079 | AU93: =IF(P93=0,AT93,IF(U93="FR",Z93,$D$44+Z93)) -> 0.079 | AV93: =IF(Q93=0,AU93,IF(V93="FR",AA93,$D$44+AA93)) -> 0.079 | AW93: =IF(M93>=12,IF(R93="FR","Y","N"),IF(AND(R93="FR",S93="FR"),"Y","N")) -> N | AX93: =IF(M93>=12,IF(S93="MLR","Y","N"),IF(OR(R93="MLR",S93="MLR"),"Y","N")) -> N | AY93: =IF(M93>=12,IF(R93="FR","Y","N"),IF(AND(R93="MLR",S93="MLR"),"Y","N")) -> N
Q94: =420-SUM(M94:P94) -> 420 | AC94: =SUM($M94:M94) -> 0 | AD94: =SUM($M94:N94) -> 0 | AE94: =SUM($M94:O94) -> 0 | AF94: =SUM($M94:P94) -> 0 | AG94: =SUM($M94:Q94) -> 420 | AH94: ปีที่ 0 | AL94: ปีที่ 1 เป็นต้นไป | AM94: -1 | AN94: -1 | AO94: -1 | AP94: -1 | AR94: =IF(R94="FR",W94,$D$44+W94) -> 0.079 | AS94: =IF(N94=0,AR94,IF(S94="FR",X94,$D$44+X94)) -> 0.079 | AT94: =IF(O94=0,AS94,IF(T94="FR",Y94,$D$44+Y94)) -> 0.079 | AU94: =IF(P94=0,AT94,IF(U94="FR",Z94,$D$44+Z94)) -> 0.079 | AV94: =IF(Q94=0,AU94,IF(V94="FR",AA94,$D$44+AA94)) -> 0.079 | AW94: =IF(M94>=12,IF(R94="FR","Y","N"),IF(AND(R94="FR",S94="FR"),"Y","N")) -> N | AX94: =IF(M94>=12,IF(S94="MLR","Y","N"),IF(OR(R94="MLR",S94="MLR"),"Y","N")) -> N | AY94: =IF(M94>=12,IF(R94="FR","Y","N"),IF(AND(R94="MLR",S94="MLR"),"Y","N")) -> N
Q95: =420-SUM(M95:P95) -> 420 | AC95: =SUM($M95:M95) -> 0 | AD95: =SUM($M95:N95) -> 0 | AE95: =SUM($M95:O95) -> 0 | AF95: =SUM($M95:P95) -> 0 | AG95: =SUM($M95:Q95) -> 420 | AH95: ปีที่ 0 | AL95: ปีที่ 1 เป็นต้นไป | AM95: -1 | AN95: -1 | AO95: -1 | AP95: -1 | AR95: =IF(R95="FR",W95,$D$44+W95) -> 0.079 | AS95: =IF(N95=0,AR95,IF(S95="FR",X95,$D$44+X95)) -> 0.079 | AT95: =IF(O95=0,AS95,IF(T95="FR",Y95,$D$44+Y95)) -> 0.079 | AU95: =IF(P95=0,AT95,IF(U95="FR",Z95,$D$44+Z95)) -> 0.079 | AV95: =IF(Q95=0,AU95,IF(V95="FR",AA95,$D$44+AA95)) -> 0.079 | AW95: =IF(M95>=12,IF(R95="FR","Y","N"),IF(AND(R95="FR",S95="FR"),"Y","N")) -> N | AX95: =IF(M95>=12,IF(S95="MLR","Y","N"),IF(OR(R95="MLR",S95="MLR"),"Y","N")) -> N | AY95: =IF(M95>=12,IF(R95="FR","Y","N"),IF(AND(R95="MLR",S95="MLR"),"Y","N")) -> N
Q96: =420-SUM(M96:P96) -> 420 | AC96: =SUM($M96:M96) -> 0 | AD96: =SUM($M96:N96) -> 0 | AE96: =SUM($M96:O96) -> 0 | AF96: =SUM($M96:P96) -> 0 | AG96: =SUM($M96:Q96) -> 420 | AH96: ปีที่ 0 | AL96: ปีที่ 1 เป็นต้นไป | AM96: -1 | AN96: -1 | AO96: -1 | AP96: -1 | AR96: =IF(R96="FR",W96,$D$44+W96) -> 0.079 | AS96: =IF(N96=0,AR96,IF(S96="FR",X96,$D$44+X96)) -> 0.079 | AT96: =IF(O96=0,AS96,IF(T96="FR",Y96,$D$44+Y96)) -> 0.079 | AU96: =IF(P96=0,AT96,IF(U96="FR",Z96,$D$44+Z96)) -> 0.079 | AV96: =IF(Q96=0,AU96,IF(V96="FR",AA96,$D$44+AA96)) -> 0.079 | AW96: =IF(M96>=12,IF(R96="FR","Y","N"),IF(AND(R96="FR",S96="FR"),"Y","N")) -> N | AX96: =IF(M96>=12,IF(S96="MLR","Y","N"),IF(OR(R96="MLR",S96="MLR"),"Y","N")) -> N | AY96: =IF(M96>=12,IF(R96="FR","Y","N"),IF(AND(R96="MLR",S96="MLR"),"Y","N")) -> N
L101: 1 | M101: 2 | N101: 3 | O101: 4 | P101: 5 | Q101: 6 | R101: 7 | S101: 8 | T101: 9 | U101: 10 | V101: 11 | AA101: 16 | AC101: 17 | AD101: 18 | AE101: 19 | AF101: 20 | AG101: 21 | AH101: 22 | AI101: 23 | AJ101: 24 | AK101: 25 | AL101: 26 | AM101: 27 | AN101: 28 | AO101: 29 | AP101: 30 | AQ101: 31 | AR101: 32 | AS101: 33 | AT101: 34 | AU101: 35 | AV101: 36 | AW101: 37
L102: Mortgage Power | M102: จำนวนงวด (เดือน) | R102: อัตราดอกเบี้ยอ้างอิง | AC102: จำนวนงวดสะสม (เดือน) | AH102: ระยะเวลา | AM102: อัตราดอกเบี้ยอ้างอิง | AR102: อัตราดอกเบี้ย / ส่วนต่าง
L103: Campaign | M103: Tier 1 | N103: Tier 2 | O103: Tier 3 | P103: Tier 4 | Q103: Tier 5 | R103: Tier 1 | S103: Tier 2 | T103: Tier 3 | U103: Tier 4 | V103: Tier 5 | AA103: Tier 5 | AC103: Tier 1 | AD103: Tier 2 | AE103: Tier 3 | AF103: Tier 4 | AG103: Tier 5 | AH103: Tier 1 | AI103: Tier 2 | AJ103: Tier 3 | AK103: Tier 4 | AL103: Tier 5 | AM103: Tier 1 | AN103: Tier 2 | AO103: Tier 3 | AP103: Tier 4 | AQ103: Tier 5 | AR103: Tier 1 | AS103: Tier 2 | AT103: Tier 3 | AU103: Tier 4 | AV103: Tier 5 | AW103: Grace
L104: เงินกู้ปกติ , MRTA | M104: 12 | Q104: =420-SUM(M104:P104) -> 408 | R104: MLR | V104: MLR | AC104: =SUM($M104:M104) -> 12 | AD104: =SUM($M104:N104) -> 12 | AE104: =SUM($M104:O104) -> 12 | AF104: =SUM($M104:P104) -> 12 | AG104: =SUM($M104:Q104) -> 420 | AH104: ปีที่ 1 | AL104: ปีที่ 2 เป็นต้นไป | AM104: MLR-1.25% | AN104: -1 | AO104: -1 | AP104: -1 | AQ104: MLR | AR104: =IF(R104="FR",W104,$D$44+W104) -> 0.079 | AS104: =IF(N104=0,AR104,IF(S104="FR",X104,$D$44+X104)) -> 0.079 | AT104: =IF(O104=0,AS104,IF(T104="FR",Y104,$D$44+Y104)) -> 0.079 | AU104: =IF(P104=0,AT104,IF(U104="FR",Z104,$D$44+Z104)) -> 0.079 | AV104: =IF(Q104=0,AU104,IF(V104="FR",AA104,$D$44+AA104)) -> 0.079 | AW104: =IF(M104>=12,IF(R104="FR","Y","N"),IF(AND(R104="FR",S104="FR"),"Y","N")) -> N
L105: เงินกู้ปกติ , No MRTA | M105: 12 | Q105: =420-SUM(M105:P105) -> 408 | R105: MLR | V105: MLR | AC105: 12 | AD105: 12 | AE105: 12 | AF105: 12 | AG105: =SUM($M105:Q105) -> 420 | AH105: ปีที่ 1 | AL105: ปีที่ 2 เป็นต้นไป | AM105: MLR-0.50% | AN105: -1 | AO105: -1 | AP105: -1 | AQ105: MLR | AR105: =IF(R105="FR",W105,$D$44+W105) -> 0.079 | AS105: =IF(N105=0,AR105,IF(S105="FR",X105,$D$44+X105)) -> 0.079 | AT105: =IF(O105=0,AS105,IF(T105="FR",Y105,$D$44+Y105)) -> 0.079 | AU105: =IF(P105=0,AT105,IF(U105="FR",Z105,$D$44+Z105)) -> 0.079 | AV105: =IF(Q105=0,AU105,IF(V105="FR",AA105,$D$44+AA105)) -> 0.079 | AW105: =IF(M105>=12,IF(R105="FR","Y","N"),IF(AND(R105="FR",S105="FR"),"Y","N")) -> N
L106: เงินกู้ Top Up , MRTA | M106: 12 | N106: 12 | O106: 12 | Q106: =420-SUM(M106:P106) -> 384 | R106: MLR | S106: MLR | T106: MLR
L107: เงินกู้ Top Up , No MRTA | M107: 12 | N107: 12 | O107: 12 | Q107: =420-SUM(M107:P107) -> 384 | R107: MLR | S107: MLR | T107: MLR
H182: ผ่อนต่อเดือน 10,000 บาท | I182: วงเงินกู้ BAY | J182: วงเงินคงเหลือ
H183: HL | I183: 1600000 | J183: 1400000
H184: MP | I184: 0 | J184: 0
H185: วงเงินที่อยากขอเพิ่ม | J185: 30000
H186: Total | J186: =J183+J184+J185 -> 1430000
B227: MRTA
B228: NO MRTA

Sheet eBHomeLoan - Table 1
D1: ="ตารางคำนวณ "&'Secured - Table 1'!$C$33 -> ตารางคำนวณ ลูกค้า Re-Finance II , No MRTA (waive all fees)
G3: วงเงินกู้ (บาท) | H3: ค่าธรรมเนียม (บาท) | I3: เวลา (เดือน) | J3: อัตราดอกเบี้ย (%) | K3: เงินงวด (บาท) | L3: ผ่อนแบบ ขั้นบันได | M3: เงินงวด (บาท) เผื่อดอกเบี้ย 1% | N3: งวดชำระจริง (งวด) | O3: ยอดชำระรวม (บาท) | P3: ดอกเบี้ยชำระ 3 ปีแรก (บาท)
D4: 1. แบบคงที่ | G4: ='Secured - Table 1'!$C$34 -> 2638750 | I4: ='Secured - Table 1'!$C$35*12 -> 420 | J4: =($J$7*$C$7+$J$8*$C$8+$J$9*$C$9+$J$10*$C$10+$J$11*('Secured - Table 1'!$C$35*12-SUM($C$7:$C$10)))/('Secured - Table 1'!$C$35*12) -> 0.062571429 | K4: =IF(OR($G$7=0,$I$8=0),0,PMT($J4/12,$I4,-$G4)) -> 15504.287 | M4: =IF(OR($G$7=0,$I$8=0),0,ROUNDUP(PMT(($J4+1%)/12,$I4,-$G4),-1)) -> 17340 | N4: =IF(OR($G$7=0,$I$8=0),0,370-COUNTIF(G23:G392,0)) -> 281 | O4: =SUM(H23:H392) -> 4867558.9 | P4: =IF(OR($G$7=0,$I$8=0),0,SUM(F23:F58)) -> 352143.89 | Q4: =O4+3200+3310 -> 4874068.9
D5: 2. แบบคงที่ มี Grace Period | G5: ='Secured - Table 1'!$C$34 -> 2638750 | I5: =I4-12 -> 408 | J5: =($J$7*$C$7+$J$8*$C$8+$J$9*$C$9+$J$10*$C$10+$J$11*('Secured - Table 1'!$C$35*12-SUM($C$7:$C$10)))/('Secured - Table 1'!$C$35*12) -> 0.062571429 | K5: =IF(OR($G$7=0,$I$8=0),0,PMT($J5/12,$I5,-$G5)) -> 15631.962 | M5: =IF(OR($G$7=0,$I$8=0),0,ROUNDUP(PMT(($J5+1%)/12,$I5,-$G5),-1)) -> 17450 | N5: =IF(OR($G$7=0,$I$8=0),0,370-COUNTIF(K35:K392,0)) -> 307 | O5: =SUM(L23:L392) -> 5230710.9 | P5: =IF(OR($G$7=0,$I$8=0),0,SUM(J23:J58)) -> 367317.39
D6: 3. แบบขั้นบันได
A7: 0 | B7: =J7 -> 0.034 | C7: =VLOOKUP('Secured - Table 1'!$C$33,'Secured - Table 1'!$L$79:$AY$98,'Secured - Table 1'!M$76,FALSE) -> 12 | E7: ='Secured - Table 1'!B37 -> 420 | F7: ='Secured - Table 1'!C37 -> MRR-4.50% | G7: ='Secured - Table 1'!$C$34 -> 2638750 | I7: ='Secured - Table 1'!$C$35*12 -> 420 | J7: ='Secured - Table 1'!D37 -> 0.034 | K7: =IF(OR($G$7=0,$I$8=0),0,PMT($J7/12,$I7,-$G7)) -> 10753.372
A8: =SUM(C$7:C7)+1 -> 13 | B8: =J8 -> 0.054 | C8: =VLOOKUP('Secured - Table 1'!$C$33,'Secured - Table 1'!$L$79:$AY$98,'Secured - Table 1'!N$76,FALSE) -> 12 | E8: ='Secured - Table 1'!B38 -> ปีที่ 1 | F8: ='Secured - Table 1'!C38 -> MRR-2.50% | G8: =VLOOKUP(A8,$D$22:$T$392,10,FALSE) -> 2558748.4 | I8: =I7-C7 -> 408 | J8: ='Secured - Table 1'!D38 -> 0.054 | K8: =IF(OR($G$7=0,$I$8=0),0,PMT($J8/12,$I8,-$G8)) -> 13709.41 | Q8: =$V$20 -> % ปรับปรุงค่างวดแบบขั้นบันได | R8: % ค่างวดเพิ่ม | S8: ค่างวดเพิ่ม
A9: =SUM(C$7:C8)+1 -> 25 | B9: =J9 -> 0.054 | C9: =VLOOKUP('Secured - Table 1'!$C$33,'Secured - Table 1'!$L$79:$AY$98,'Secured - Table 1'!O$76,FALSE) -> 12 | E9: ='Secured - Table 1'!B39 -> ปีที่ 2 | F9: ='Secured - Table 1'!C39 -> MRR-2.50% | G9: =VLOOKUP(A9,$D$22:$T$392,10,FALSE) -> 2527679.4 | I9: =I8-C8 -> 396 | J9: ='Secured - Table 1'!D39 -> 0.054 | K9: =IF(OR($G$7=0,$I$8=0),0,PMT($J9/12,$I9,-$G9)) -> 13687.388 | L9: ปีที่ 1 และ 2 | M9: =ROUNDUP($M10/$Q9,-1) -> 14040 | Q9: 1.1
A10: =SUM(C$7:C9)+1 -> 37 | B10: =J10 -> 0.079 | C10: =VLOOKUP('Secured - Table 1'!$C$33,'Secured - Table 1'!$L$79:$AY$98,'Secured - Table 1'!P$76,FALSE) -> 0 | E10: ='Secured - Table 1'!B40 -> ปีที่ 3 | F10: ='Secured - Table 1'!C40 -> MLR-1.25% | G10: =VLOOKUP(A10,$D$22:$T$392,10,FALSE) -> 2477668.4 | I10: =I9-C9 -> 384 | J10: ='Secured - Table 1'!D40 -> 0.079 | K10: =IF(OR($G$7=0,$I$8=0),0,PMT($J10/12,$I10,-$G10)) -> 17738.996 | L10: ปีที่ 3 และ 4 | M10: =ROUNDUP($M$4*$Q10,-1) -> 15440 | Q10: =IF(OR($G$7=0,$I$8=0),0,VLOOKUP($I$8/12,$V$22:$X$52,2)) -> 0.89 | R10: =IF(M9=0,0,M10/M9) -> 1.0997151 | S10: =M10-M9 -> 1400
A11: =SUM(C$7:C10)+1 -> 37 | B11: =J11 -> 0.064 | E11: ='Secured - Table 1'!B41 | F11: ='Secured - Table 1'!C41 -> MRR-1.50% | G11: =VLOOKUP(A11,$D$22:$T$392,10,FALSE) -> 2477668.4 | I11: =I10-C10 -> 384 | J11: ='Secured - Table 1'!D41 -> 0.064 | K11: =IF(OR($G$7=0,$I$8=0),0,PMT($J11/12,$I11,-$G11)) -> 15183.475 | L11: ปีที่ 5 เป็นต้นไป | M11: =IF(OR($G$7=0,$I$8=0),0,ROUNDUP(PMT($J$11/12,$N$4-48,-$M$71),-1)) -> 18400 | N11: =IF(OR($G$7=0,$I$8=0),0,370-COUNTIF(O23:O392,0)) -> 281 | O11: =SUM(P23:P392) -> 4994720 | P11: =IF(OR($G$7=0,$I$8=0),0,SUM(N23:N58)) -> 361158.35 | R11: =IF(M10=0,0,M11/M10) -> 1.1917098 | S11: =M11-M10 -> 2960
D12: 4. แบบขั้นบันได มี Grace Period
A13: =A7 -> 0 | B13: =B7 -> 0.034 | C13: =C7 -> 12 | E13: =E7 -> 420 | F13: =F7 -> MRR-4.50% | G13: ='Secured - Table 1'!$C$34 -> 2638750 | I13: ='Secured - Table 1'!$C$35*12 -> 420 | J13: =J7 -> 0.034 | K13: =IF(OR($G$7=0,$I$8=0),0,$G13*IF($C$13<12,$J$14,$J13)*31/365) -> 7619.8425
A14: =A8 -> 13 | B14: =B8 -> 0.054 | C14: =C8 -> 12 | E14: =E8 -> ปีที่ 1 | F14: =F8 -> MRR-2.50% | G14: =VLOOKUP(A14,$D$22:$T$392,14,FALSE) -> 2637000.4 | I14: =I8 -> 408 | J14: =J8 -> 0.054 | K14: =IF(OR($G$7=0,$I$8=0),0,IF($C$13<12,K13,PMT($J14/12,$I14,-$G14))) -> 14128.673 | L14: ปีที่ 1 | M14: =ROUNDUP($K13,-1) -> 7620 | Q14: =$V$20 -> % ปรับปรุงค่างวดแบบขั้นบันได | R14: % ค่างวดเพิ่ม | S14: ค่างวดเพิ่ม
A15: =A9 -> 25 | B15: =B9 -> 0.054 | C15: =C9 -> 12 | E15: =E9 -> ปีที่ 2 | F15: =F9 -> MRR-2.50% | G15: =VLOOKUP(A15,$D$22:$T$392,14,FALSE) -> 2609156 | I15: =I9 -> 396 | J15: =J9 -> 0.054 | K15: =IF(OR($G$7=0,$I$8=0),0,PMT($J15/12,$I15,-$G15)) -> 14128.584 | L15: ปีที่ 2 และ 3 | M15: =ROUNDUP($M16/$Q15,-1) -> 14130 | Q15: 1.1
A16: =A10 -> 37 | B16: =B10 -> 0.079 | C16: =C10 -> 0 | E16: =E10 -> ปีที่ 3 | F16: =F10 -> MLR-1.25% | G16: =VLOOKUP(A16,$D$22:$T$392,14,FALSE) -> 2579770.2 | I16: =I10 -> 384 | J16: =J10 -> 0.079 | K16: =IF(OR($G$7=0,$I$8=0),0,PMT($J16/12,$I16,-$G16)) -> 18469.999 | L16: ปีที่ 4 และ 5 | M16: =ROUNDUP($M$5*$Q16,-1) -> 15540 | Q16: =IF(OR($G$7=0,$I$8=0),0,VLOOKUP($I$8/12,$V$22:$X$52,3)) -> 0.89 | R16: =IF(M15=0,0,M16/M15) -> 1.0997877 | S16: =M16-M15 -> 1410
A17: =A11 -> 37 | B17: =B11 -> 0.064 | E17: =E11 | F17: =F11 -> MRR-1.50% | G17: =VLOOKUP(A17,$D$22:$T$392,14,FALSE) -> 2579770.2 | I17: =I11 -> 384 | J17: =J11 -> 0.064 | K17: =IF(OR($G$7=0,$I$8=0),0,PMT($J17/12,$I17,-$G17)) -> 15809.168 | L17: ปีที่ 6 เป็นต้นไป | M17: =IF(OR($G$7=0,$I$8=0),0,ROUNDUP(PMT($J17/12,$N$5-60,-$Q$83),-1)) -> 18490 | N17: =IF(OR($G$7=0,$I$8=0),0,370-COUNTIF(S23:S392,0)) -> 307 | O17: =SUM(T23:T392) -> 5367842 | P17: =IF(OR($G$7=0,$I$8=0),0,SUM(R23:R58)) -> 371580.15 | R17: =IF(M16=0,0,M17/M16) -> 1.1898327 | S17: =M17-M16 -> 2950
E20: =D4 -> 1. แบบคงที่ | I20: =D5 -> 2. แบบคงที่ มี Grace Period | M20: =D6 -> 3. แบบขั้นบันได | Q20: =D12 -> 4. แบบขั้นบันได มี Grace Period | V20: % ปรับปรุงค่างวดแบบขั้นบันได
A21: Annual rate | B21: Monthly rate | C21: ปี | D21: งวด | E21: เงินต้นคงเหลือ | F21: ดอกเบี้ยผ่อนชำระ | G21: เงินต้นผ่อนชำระ | H21: เงินงวด | I21: เงินต้นคงเหลือ | J21: ดอกเบี้ยผ่อนชำระ | K21: เงินต้นผ่อนชำระ | L21: เงินงวด | M21: เงินต้นคงเหลือ | N21: ดอกเบี้ยผ่อนชำระ | O21: เงินต้นผ่อนชำระ | P21: เงินงวด | Q21: เงินต้นคงเหลือ | R21: ดอกเบี้ยผ่อนชำระ | S21: เงินต้นผ่อนชำระ | T21: เงินงวด | V21: ระยะเวลา (ปี) | W21: ไม่มี Grace Period | X21: มี Grace Period
C22: 0 | D22: 0 | H22: =-$G$7 -> -2638750 | L22: =-$G$7 -> -2638750 | P22: =-$G$7 -> -2638750 | T22: =-$G$7 -> -2638750 | V22: 0 | W22: 1 | X22: 1.03
A23: =VLOOKUP(D23,$A$7:$B$11,2) -> 0.034 | B23: =A23/12 -> 0.0028333333 | C23: =INT((D23+11)/12) -> 1 | D23: 1 | E23: =$G$7 -> 2638750 | F23: =ROUND(E23*$B23,2) -> 7476.46 | G23: =IF(E23<H23,E23,H23-F23) -> 9863.54 | H23: =IF(E23<$M$4,E23+F23,$M$4) -> 17340 | I23: =$G$7 -> 2638750 | J23: =ROUND(I23*$B23,2) -> 7476.46 | K23: =IF(I23<L23,I23,L23-J23) -> 143.54 | L23: =IF(I23<$M$14,I23+J23,$M$14) -> 7620 | M23: =$G$7 -> 2638750 | N23: =ROUND(M23*$B23,2) -> 7476.46 | O23: =IF(M23<P23,M23,P23-N23) -> 6563.54 | P23: =IF(M23<$M$9,M23+N23,$M$9) -> 14040 | Q23: =$G$7 -> 2638750 | R23: =ROUND(Q23*$B23,2) -> 7476.46 | S23: =IF(Q23<T23,Q23,T23-R23) -> 143.54 | T23: =IF(Q23<$M$14,Q23+R23,$M$14) -> 7620 | V23: 1 | W23: 1 | X23: 1.03
A24: =VLOOKUP(D24,$A$7:$B$11,2) -> 0.034 | B24: =A24/12 -> 0.0028333333 | C24: =INT((D24+11)/12) -> 1 | D24: 2 | E24: =IF(E23<H23,0,E23-G23) -> 2628886.5 | F24: =ROUND(E24*$B24,2) -> 7448.51 | G24: =IF(E24<H24,E24,H24-F24) -> 9891.49 | H24: =IF(E24<$M$4,E24+F24,$M$4) -> 17340 | I24: =IF(I23<L23,0,I23-K23) -> 2638606.5 | J24: =ROUND(I24*$B24,2) -> 7476.05 | K24: =IF(I24<L24,I24,L24-J24) -> 143.95 | L24: =IF(I24<$M$14,I24+J24,$M$14) -> 7620 | M24: =IF(M23<P23,0,M23-O23) -> 2632186.5 | N24: =ROUND(M24*$B24,2) -> 7457.86 | O24: =IF(M24<P24,M24,P24-N24) -> 6582.14 | P24: =IF(M24<$M$9,M24+N24,$M$9) -> 14040 | Q24: =IF(Q23<T23,0,Q23-S23) -> 2638606.5 | R24: =ROUND(Q24*$B24,2) -> 7476.05 | S24: =IF(Q24<T24,Q24,T24-R24) -> 143.95 | T24: =IF(Q24<$M$14,Q24+R24,$M$14) -> 7620 | V24: 2 | W24: 1 | X24: 1.03
A25: =VLOOKUP(D25,$A$7:$B$11,2) -> 0.034 | B25: =A25/12 -> 0.0028333333 | C25: =INT((D25+11)/12) -> 1 | D25: 3 | E25: =IF(E24<H24,0,E24-G24) -> 2618995 | F25: =ROUND(E25*$B25,2) -> 7420.49 | G25: =IF(E25<H25,E25,H25-F25) -> 9919.51 | H25: =IF(E25<$M$4,E25+F25,$M$4) -> 17340 | I25: =IF(I24<L24,0,I24-K24) -> 2638462.5 | J25: =ROUND(I25*$B25,2) -> 7475.64 | K25: =IF(I25<L25,I25,L25-J25) -> 144.36 | L25: =IF(I25<$M$14,I25+J25,$M$14) -> 7620 | M25: =IF(M24<P24,0,M24-O24) -> 2625604.3 | N25: =ROUND(M25*$B25,2) -> 7439.21 | O25: =IF(M25<P25,M25,P25-N25) -> 6600.79 | P25: =IF(M25<$M$9,M25+N25,$M$9) -> 14040 | Q25: =IF(Q24<T24,0,Q24-S24) -> 2638462.5 | R25: =ROUND(Q25*$B25,2) -> 7475.64 | S25: =IF(Q25<T25,Q25,T25-R25) -> 144.36 | T25: =IF(Q25<$M$14,Q25+R25,$M$14) -> 7620 | V25: 3 | W25: 1 | X25: 1.03
A26: =VLOOKUP(D26,$A$7:$B$11,2) -> 0.034 | B26: =A26/12 -> 0.0028333333 | C26: =INT((D26+11)/12) -> 1 | D26: 4 | E26: =IF(E25<H25,0,E25-G25) -> 2609075.5 | F26: =ROUND(E26*$B26,2) -> 7392.38 | G26: =IF(E26<H26,E26,H26-F26) -> 9947.62 | H26: =IF(E26<$M$4,E26+F26,$M$4) -> 17340 | I26: =IF(I25<L25,0,I25-K25) -> 2638318.1 | J26: =ROUND(I26*$B26,2) -> 7475.23 | K26: =IF(I26<L26,I26,L26-J26) -> 144.77 | L26: =IF(I26<$M$14,I26+J26,$M$14) -> 7620 | M26: =IF(M25<P25,0,M25-O25) -> 2619003.5 | N26: =ROUND(M26*$B26,2) -> 7420.51 | O26: =IF(M26<P26,M26,P26-N26) -> 6619.49 | P26: =IF(M26<$M$9,M26+N26,$M$9) -> 14040 | Q26: =IF(Q25<T25,0,Q25-S25) -> 2638318.1 | R26: =ROUND(Q26*$B26,2) -> 7475.23 | S26: =IF(Q26<T26,Q26,T26-R26) -> 144.77 | T26: =IF(Q26<$M$14,Q26+R26,$M$14) -> 7620 | V26: 4 | W26: 1 | X26: 1.03
A27: =VLOOKUP(D27,$A$7:$B$11,2) -> 0.034 | B27: =A27/12 -> 0.0028333333 | C27: =INT((D27+11)/12) -> 1 | D27: 5 | E27: =IF(E26<H26,0,E26-G26) -> 2599127.8 | F27: =ROUND(E27*$B27,2) -> 7364.2 | G27: =IF(E27<H27,E27,H27-F27) -> 9975.8 | H27: =IF(E27<$M$4,E27+F27,$M$4) -> 17340 | I27: =IF(I26<L26,0,I26-K26) -> 2638173.4 | J27: =ROUND(I27*$B27,2) -> 7474.82 | K27: =IF(I27<L27,I27,L27-J27) -> 145.18 | L27: =IF(I27<$M$14,I27+J27,$M$14) -> 7620 | M27: =IF(M26<P26,0,M26-O26) -> 2612384 | N27: =ROUND(M27*$B27,2) -> 7401.75 | O27: =IF(M27<P27,M27,P27-N27) -> 6638.25 | P27: =IF(M27<$M$9,M27+N27,$M$9) -> 14040 | Q27: =IF(Q26<T26,0,Q26-S26) -> 2638173.4 | R27: =ROUND(Q27*$B27,2) -> 7474.82 | S27: =IF(Q27<T27,Q27,T27-R27) -> 145.18 | T27: =IF(Q27<$M$14,Q27+R27,$M$14) -> 7620 | V27: 5 | W27: 1 | X27: 1.03
A28: =VLOOKUP(D28,$A$7:$B$11,2) -> 0.034 | B28: =A28/12 -> 0.0028333333 | C28: =INT((D28+11)/12) -> 1 | D28: 6 | E28: =IF(E27<H27,0,E27-G27) -> 2589152 | F28: =ROUND(E28*$B28,2) -> 7335.93 | G28: =IF(E28<H28,E28,H28-F28) -> 10004.07 | H28: =IF(E28<$M$4,E28+F28,$M$4) -> 17340 | I28: =IF(I27<L27,0,I27-K27) -> 2638028.2 | J28: =ROUND(I28*$B28,2) -> 7474.41 | K28: =IF(I28<L28,I28,L28-J28) -> 145.59 | L28: =IF(I28<$M$14,I28+J28,$M$14) -> 7620 | M28: =IF(M27<P27,0,M27-O27) -> 2605745.8 | N28: =ROUND(M28*$B28,2) -> 7382.95 | O28: =IF(M28<P28,M28,P28-N28) -> 6657.05 | P28: =IF(M28<$M$9,M28+N28,$M$9) -> 14040 | Q28: =IF(Q27<T27,0,Q27-S27) -> 2638028.2 | R28: =ROUND(Q28*$B28,2) -> 7474.41 | S28: =IF(Q28<T28,Q28,T28-R28) -> 145.59 | T28: =IF(Q28<$M$14,Q28+R28,$M$14) -> 7620 | V28: 6 | W28: 1 | X28: 1.03
A29: =VLOOKUP(D29,$A$7:$B$11,2) -> 0.034 | B29: =A29/12 -> 0.0028333333 | C29: =INT((D29+11)/12) -> 1 | D29: 7 | E29: =IF(E28<H28,0,E28-G28) -> 2579148 | F29: =ROUND(E29*$B29,2) -> 7307.59 | G29: =IF(E29<H29,E29,H29-F29) -> 10032.41 | H29: =IF(E29<$M$4,E29+F29,$M$4) -> 17340 | I29: =IF(I28<L28,0,I28-K28) -> 2637882.6 | J29: =ROUND(I29*$B29,2) -> 7474 | K29: =IF(I29<L29,I29,L29-J29) -> 146 | L29: =IF(I29<$M$14,I29+J29,$M$14) -> 7620 | M29: =IF(M28<P28,0,M28-O28) -> 2599088.7 | N29: =ROUND(M29*$B29,2) -> 7364.08 | O29: =IF(M29<P29,M29,P29-N29) -> 6675.92 | P29: =IF(M29<$M$9,M29+N29,$M$9) -> 14040 | Q29: =IF(Q28<T28,0,Q28-S28) -> 2637882.6 | R29: =ROUND(Q29*$B29,2) -> 7474 | S29: =IF(Q29<T29,Q29,T29-R29) -> 146 | T29: =IF(Q29<$M$14,Q29+R29,$M$14) -> 7620 | V29: 7 | W29: 0.98 | X29: 1
A30: =VLOOKUP(D30,$A$7:$B$11,2) -> 0.034 | B30: =A30/12 -> 0.0028333333 | C30: =INT((D30+11)/12) -> 1 | D30: 8 | E30: =IF(E29<H29,0,E29-G29) -> 2569115.6 | F30: =ROUND(E30*$B30,2) -> 7279.16 | G30: =IF(E30<H30,E30,H30-F30) -> 10060.84 | H30: =IF(E30<$M$4,E30+F30,$M$4) -> 17340 | I30: =IF(I29<L29,0,I29-K29) -> 2637736.6 | J30: =ROUND(I30*$B30,2) -> 7473.59 | K30: =IF(I30<L30,I30,L30-J30) -> 146.41 | L30: =IF(I30<$M$14,I30+J30,$M$14) -> 7620 | M30: =IF(M29<P29,0,M29-O29) -> 2592412.8 | N30: =ROUND(M30*$B30,2) -> 7345.17 | O30: =IF(M30<P30,M30,P30-N30) -> 6694.83 | P30: =IF(M30<$M$9,M30+N30,$M$9) -> 14040 | Q30: =IF(Q29<T29,0,Q29-S29) -> 2637736.6 | R30: =ROUND(Q30*$B30,2) -> 7473.59 | S30: =IF(Q30<T30,Q30,T30-R30) -> 146.41 | T30: =IF(Q30<$M$14,Q30+R30,$M$14) -> 7620 | V30: 8 | W30: 0.96 | X30: 0.98
A31: =VLOOKUP(D31,$A$7:$B$11,2) -> 0.034 | B31: =A31/12 -> 0.0028333333 | C31: =INT((D31+11)/12) -> 1 | D31: 9 | E31: =IF(E30<H30,0,E30-G30) -> 2559054.7 | F31: =ROUND(E31*$B31,2) -> 7250.66 | G31: =IF(E31<H31,E31,H31-F31) -> 10089.34 | H31: =IF(E31<$M$4,E31+F31,$M$4) -> 17340 | I31: =IF(I30<L30,0,I30-K30) -> 2637590.2 | J31: =ROUND(I31*$B31,2) -> 7473.17 | K31: =IF(I31<L31,I31,L31-J31) -> 146.83 | L31: =IF(I31<$M$14,I31+J31,$M$14) -> 7620 | M31: =IF(M30<P30,0,M30-O30) -> 2585718 | N31: =ROUND(M31*$B31,2) -> 7326.2 | O31: =IF(M31<P31,M31,P31-N31) -> 6713.8 | P31: =IF(M31<$M$9,M31+N31,$M$9) -> 14040 | Q31: =IF(Q30<T30,0,Q30-S30) -> 2637590.2 | R31: =ROUND(Q31*$B31,2) -> 7473.17 | S31: =IF(Q31<T31,Q31,T31-R31) -> 146.83 | T31: =IF(Q31<$M$14,Q31+R31,$M$14) -> 7620 | V31: 9 | W31: 0.95 | X31: 0.96
A32: =VLOOKUP(D32,$A$7:$B$11,2) -> 0.034 | B32: =A32/12 -> 0.0028333333 | C32: =INT((D32+11)/12) -> 1 | D32: 10 | E32: =IF(E31<H31,0,E31-G31) -> 2548965.4 | F32: =ROUND(E32*$B32,2) -> 7222.07 | G32: =IF(E32<H32,E32,H32-F32) -> 10117.93 | H32: =IF(E32<$M$4,E32+F32,$M$4) -> 17340 | I32: =IF(I31<L31,0,I31-K31) -> 2637443.4 | J32: =ROUND(I32*$B32,2) -> 7472.76 | K32: =IF(I32<L32,I32,L32-J32) -> 147.24 | L32: =IF(I32<$M$14,I32+J32,$M$14) -> 7620 | M32: =IF(M31<P31,0,M31-O31) -> 2579004.2 | N32: =ROUND(M32*$B32,2) -> 7307.18 | O32: =IF(M32<P32,M32,P32-N32) -> 6732.82 | P32: =IF(M32<$M$9,M32+N32,$M$9) -> 14040 | Q32: =IF(Q31<T31,0,Q31-S31) -> 2637443.4 | R32: =ROUND(Q32*$B32,2) -> 7472.76 | S32: =IF(Q32<T32,Q32,T32-R32) -> 147.24 | T32: =IF(Q32<$M$14,Q32+R32,$M$14) -> 7620 | V32: 10 | W32: 0.94 | X32: 0.95
A33: =VLOOKUP(D33,$A$7:$B$11,2) -> 0.034 | B33: =A33/12 -> 0.0028333333 | C33: =INT((D33+11)/12) -> 1 | D33: 11 | E33: =IF(E32<H32,0,E32-G32) -> 2538847.5 | F33: =ROUND(E33*$B33,2) -> 7193.4 | G33: =IF(E33<H33,E33,H33-F33) -> 10146.6 | H33: =IF(E33<$M$4,E33+F33,$M$4) -> 17340 | I33: =IF(I32<L32,0,I32-K32) -> 2637296.1 | J33: =ROUND(I33*$B33,2) -> 7472.34 | K33: =IF(I33<L33,I33,L33-J33) -> 147.66 | L33: =IF(I33<$M$14,I33+J33,$M$14) -> 7620 | M33: =IF(M32<P32,0,M32-O32) -> 2572271.4 | N33: =ROUND(M33*$B33,2) -> 7288.1 | O33: =IF(M33<P33,M33,P33-N33) -> 6751.9 | P33: =IF(M33<$M$9,M33+N33,$M$9) -> 14040 | Q33: =IF(Q32<T32,0,Q32-S32) -> 2637296.1 | R33: =ROUND(Q33*$B33,2) -> 7472.34 | S33: =IF(Q33<T33,Q33,T33-R33) -> 147.66 | T33: =IF(Q33<$M$14,Q33+R33,$M$14) -> 7620 | V33: 11 | W33: 0.93 | X33: 0.94
A34: =VLOOKUP(D34,$A$7:$B$11,2) -> 0.034 | B34: =A34/12 -> 0.0028333333 | C34: =INT((D34+11)/12) -> 1 | D34: 12 | E34: =IF(E33<H33,0,E33-G33) -> 2528700.9 | F34: =ROUND(E34*$B34,2) -> 7164.65 | G34: =IF(E34<H34,E34,H34-F34) -> 10175.35 | H34: =IF(E34<$M$4,E34+F34,$M$4) -> 17340 | I34: =IF(I33<L33,0,I33-K33) -> 2637148.5 | J34: =ROUND(I34*$B34,2) -> 7471.92 | K34: =IF(I34<L34,I34,L34-J34) -> 148.08 | L34: =IF(I34<$M$14,I34+J34,$M$14) -> 7620 | M34: =IF(M33<P33,0,M33-O33) -> 2565519.5 | N34: =ROUND(M34*$B34,2) -> 7268.97 | O34: =IF(M34<P34,M34,P34-N34) -> 6771.03 | P34: =IF(M34<$M$9,M34+N34,$M$9) -> 14040 | Q34: =IF(Q33<T33,0,Q33-S33) -> 2637148.5 | R34: =ROUND(Q34*$B34,2) -> 7471.92 | S34: =IF(Q34<T34,Q34,T34-R34) -> 148.08 | T34: =IF(Q34<$M$14,Q34+R34,$M$14) -> 7620 | V34: 12 | W34: 0.93 | X34: 0.93
A35: =VLOOKUP(D35,$A$7:$B$11,2) -> 0.054 | B35: =A35/12 -> 0.0045 | C35: =INT((D35+11)/12) -> 2 | D35: 13 | E35: =IF(E34<H34,0,E34-G34) -> 2518525.5 | F35: =ROUND(E35*$B35,2) -> 11333.36 | G35: =IF(E35<H35,E35,H35-F35) -> 6006.64 | H35: =IF(E35<$M$4,E35+F35,$M$4) -> 17340 | I35: =IF(I34<L34,0,I34-K34) -> 2637000.4 | J35: =ROUND(I35*$B35,2) -> 11866.5 | K35: =IF(I35<L35,I35,L35-J35) -> 5583.5 | L35: =IF(I35<$M$5,I35+J35,$M$5) -> 17450 | M35: =IF(M34<P34,0,M34-O34) -> 2558748.4 | N35: =ROUND(M35*$B35,2) -> 11514.37 | O35: =IF(M35<P35,M35,P35-N35) -> 2525.63 | P35: =IF(M35<$M$9,M35+N35,$M$9) -> 14040 | Q35: =IF(Q34<T34,0,Q34-S34) -> 2637000.4 | R35: =ROUND(Q35*$B35,2) -> 11866.5 | S35: =IF(Q35<T35,Q35,T35-R35) -> 2263.5 | T35: =IF(Q35<$M$15,Q35+R35,$M$15) -> 14130 | V35: 13 | W35: 0.92 | X35: 0.93
A36: =VLOOKUP(D36,$A$7:$B$11,2) -> 0.054 | B36: =A36/12 -> 0.0045 | C36: =INT((D36+11)/12) -> 2 | D36: 14 | E36: =IF(E35<H35,0,E35-G35) -> 2512518.9 | F36: =ROUND(E36*$B36,2) -> 11306.33 | G36: =IF(E36<H36,E36,H36-F36) -> 6033.67 | H36: =IF(E36<$M$4,E36+F36,$M$4) -> 17340 | I36: =IF(I35<L35,0,I35-K35) -> 2631416.9 | J36: =ROUND(I36*$B36,2) -> 11841.38 | K36: =IF(I36<L36,I36,L36-J36) -> 5608.62 | L36: =IF(I36<$M$5,I36+J36,$M$5) -> 17450 | M36: =IF(M35<P35,0,M35-O35) -> 2556222.8 | N36: =ROUND(M36*$B36,2) -> 11503 | O36: =IF(M36<P36,M36,P36-N36) -> 2537 | P36: =IF(M36<$M$9,M36+N36,$M$9) -> 14040 | Q36: =IF(Q35<T35,0,Q35-S35) -> 2634736.9 | R36: =ROUND(Q36*$B36,2) -> 11856.32 | S36: =IF(Q36<T36,Q36,T36-R36) -> 2273.68 | T36: =IF(Q36<$M$15,Q36+R36,$M$15) -> 14130 | V36: 14 | W36: 0.92 | X36: 0.92
A37: =VLOOKUP(D37,$A$7:$B$11,2) -> 0.054 | B37: =A37/12 -> 0.0045 | C37: =INT((D37+11)/12) -> 2 | D37: 15 | E37: =IF(E36<H36,0,E36-G36) -> 2506485.2 | F37: =ROUND(E37*$B37,2) -> 11279.18 | G37: =IF(E37<H37,E37,H37-F37) -> 6060.82 | H37: =IF(E37<$M$4,E37+F37,$M$4) -> 17340 | I37: =IF(I36<L36,0,I36-K36) -> 2625808.3 | J37: =ROUND(I37*$B37,2) -> 11816.14 | K37: =IF(I37<L37,I37,L37-J37) -> 5633.86 | L37: =IF(I37<$M$5,I37+J37,$M$5) -> 17450 | M37: =IF(M36<P36,0,M36-O36) -> 2553685.8 | N37: =ROUND(M37*$B37,2) -> 11491.59 | O37: =IF(M37<P37,M37,P37-N37) -> 2548.41 | P37: =IF(M37<$M$9,M37+N37,$M$9) -> 14040 | Q37: =IF(Q36<T36,0,Q36-S36) -> 2632463.2 | R37: =ROUND(Q37*$B37,2) -> 11846.08 | S37: =IF(Q37<T37,Q37,T37-R37) -> 2283.92 | T37: =IF(Q37<$M$15,Q37+R37,$M$15) -> 14130 | V37: 15 | W37: 0.91 | X37: 0.92
A38: =VLOOKUP(D38,$A$7:$B$11,2) -> 0.054 | B38: =A38/12 -> 0.0045 | C38: =INT((D38+11)/12) -> 2 | D38: 16 | E38: =IF(E37<H37,0,E37-G37) -> 2500424.4 | F38: =ROUND(E38*$B38,2) -> 11251.91 | G38: =IF(E38<H38,E38,H38-F38) -> 6088.09 | H38: =IF(E38<$M$4,E38+F38,$M$4) -> 17340 | I38: =IF(I37<L37,0,I37-K37) -> 2620174.4 | J38: =ROUND(I38*$B38,2) -> 11790.78 | K38: =IF(I38<L38,I38,L38-J38) -> 5659.22 | L38: =IF(I38<$M$5,I38+J38,$M$5) -> 17450 | M38: =IF(M37<P37,0,M37-O37) -> 2551137.4 | N38: =ROUND(M38*$B38,2) -> 11480.12 | O38: =IF(M38<P38,M38,P38-N38) -> 2559.88 | P38: =IF(M38<$M$9,M38+N38,$M$9) -> 14040 | Q38: =IF(Q37<T37,0,Q37-S37) -> 2630179.3 | R38: =ROUND(Q38*$B38,2) -> 11835.81 | S38: =IF(Q38<T38,Q38,T38-R38) -> 2294.19 | T38: =IF(Q38<$M$15,Q38+R38,$M$15) -> 14130 | V38: 16 | W38: 0.91 | X38: 0.91
A39: =VLOOKUP(D39,$A$7:$B$11,2) -> 0.054 | B39: =A39/12 -> 0.0045 | C39: =INT((D39+11)/12) -> 2 | D39: 17 | E39: =IF(E38<H38,0,E38-G38) -> 2494336.3 | F39: =ROUND(E39*$B39,2) -> 11224.51 | G39: =IF(E39<H39,E39,H39-F39) -> 6115.49 | H39: =IF(E39<$M$4,E39+F39,$M$4) -> 17340 | I39: =IF(I38<L38,0,I38-K38) -> 2614515.2 | J39: =ROUND(I39*$B39,2) -> 11765.32 | K39: =IF(I39<L39,I39,L39-J39) -> 5684.68 | L39: =IF(I39<$M$5,I39+J39,$M$5) -> 17450 | M39: =IF(M38<P38,0,M38-O38) -> 2548577.5 | N39: =ROUND(M39*$B39,2) -> 11468.6 | O39: =IF(M39<P39,M39,P39-N39) -> 2571.4 | P39: =IF(M39<$M$9,M39+N39,$M$9) -> 14040 | Q39: =IF(Q38<T38,0,Q38-S38) -> 2627885.1 | R39: =ROUND(Q39*$B39,2) -> 11825.48 | S39: =IF(Q39<T39,Q39,T39-R39) -> 2304.52 | T39: =IF(Q39<$M$15,Q39+R39,$M$15) -> 14130 | V39: 17 | W39: 0.91 | X39: 0.91 | AD39: ผ
A40: =VLOOKUP(D40,$A$7:$B$11,2) -> 0.054 | B40: =A40/12 -> 0.0045 | C40: =INT((D40+11)/12) -> 2 | D40: 18 | E40: =IF(E39<H39,0,E39-G39) -> 2488220.8 | F40: =ROUND(E40*$B40,2) -> 11196.99 | G40: =IF(E40<H40,E40,H40-F40) -> 6143.01 | H40: =IF(E40<$M$4,E40+F40,$M$4) -> 17340 | I40: =IF(I39<L39,0,I39-K39) -> 2608830.5 | J40: =ROUND(I40*$B40,2) -> 11739.74 | K40: =IF(I40<L40,I40,L40-J40) -> 5710.26 | L40: =IF(I40<$M$5,I40+J40,$M$5) -> 17450 | M40: =IF(M39<P39,0,M39-O39) -> 2546006.1 | N40: =ROUND(M40*$B40,2) -> 11457.03 | O40: =IF(M40<P40,M40,P40-N40) -> 2582.97 | P40: =IF(M40<$M$9,M40+N40,$M$9) -> 14040 | Q40: =IF(Q39<T39,0,Q39-S39) -> 2625580.6 | R40: =ROUND(Q40*$B40,2) -> 11815.11 | S40: =IF(Q40<T40,Q40,T40-R40) -> 2314.89 | T40: =IF(Q40<$M$15,Q40+R40,$M$15) -> 14130 | V40: 18 | W40: 0.9 | X40: 0.91
A41: =VLOOKUP(D41,$A$7:$B$11,2) -> 0.054 | B41: =A41/12 -> 0.0045 | C41: =INT((D41+11)/12) -> 2 | D41: 19 | E41: =IF(E40<H40,0,E40-G40) -> 2482077.8 | F41: =ROUND(E41*$B41,2) -> 11169.35 | G41: =IF(E41<H41,E41,H41-F41) -> 6170.65 | H41: =IF(E41<$M$4,E41+F41,$M$4) -> 17340 | I41: =IF(I40<L40,0,I40-K40) -> 2603120.2 | J41: =ROUND(I41*$B41,2) -> 11714.04 | K41: =IF(I41<L41,I41,L41-J41) -> 5735.96 | L41: =IF(I41<$M$5,I41+J41,$M$5) -> 17450 | M41: =IF(M40<P40,0,M40-O40) -> 2543423.2 | N41: =ROUND(M41*$B41,2) -> 11445.4 | O41: =IF(M41<P41,M41,P41-N41) -> 2594.6 | P41: =IF(M41<$M$9,M41+N41,$M$9) -> 14040 | Q41: =IF(Q40<T40,0,Q40-S40) -> 2623265.7 | R41: =ROUND(Q41*$B41,2) -> 11804.7 | S41: =IF(Q41<T41,Q41,T41-R41) -> 2325.3 | T41: =IF(Q41<$M$15,Q41+R41,$M$15) -> 14130 | V41: 19 | W41: 0.9 | X41: 0.9
A42: =VLOOKUP(D42,$A$7:$B$11,2) -> 0.054 | B42: =A42/12 -> 0.0045 | C42: =INT((D42+11)/12) -> 2 | D42: 20 | E42: =IF(E41<H41,0,E41-G41) -> 2475907.1 | F42: =ROUND(E42*$B42,2) -> 11141.58 | G42: =IF(E42<H42,E42,H42-F42) -> 6198.42 | H42: =IF(E42<$M$4,E42+F42,$M$4) -> 17340 | I42: =IF(I41<L41,0,I41-K41) -> 2597384.3 | J42: =ROUND(I42*$B42,2) -> 11688.23 | K42: =IF(I42<L42,I42,L42-J42) -> 5761.77 | L42: =IF(I42<$M$5,I42+J42,$M$5) -> 17450 | M42: =IF(M41<P41,0,M41-O41) -> 2540828.6 | N42: =ROUND(M42*$B42,2) -> 11433.73 | O42: =IF(M42<P42,M42,P42-N42) -> 2606.27 | P42: =IF(M42<$M$9,M42+N42,$M$9) -> 14040 | Q42: =IF(Q41<T41,0,Q41-S41) -> 2620940.4 | R42: =ROUND(Q42*$B42,2) -> 11794.23 | S42: =IF(Q42<T42,Q42,T42-R42) -> 2335.77 | T42: =IF(Q42<$M$15,Q42+R42,$M$15) -> 14130 | V42: 20 | W42: 0.9 | X42: 0.9
A43: =VLOOKUP(D43,$A$7:$B$11,2) -> 0.054 | B43: =A43/12 -> 0.0045 | C43: =INT((D43+11)/12) -> 2 | D43: 21 | E43: =IF(E42<H42,0,E42-G42) -> 2469708.7 | F43: =ROUND(E43*$B43,2) -> 11113.69 | G43: =IF(E43<H43,E43,H43-F43) -> 6226.31 | H43: =IF(E43<$M$4,E43+F43,$M$4) -> 17340 | I43: =IF(I42<L42,0,I42-K42) -> 2591622.5 | J43: =ROUND(I43*$B43,2) -> 11662.3 | K43: =IF(I43<L43,I43,L43-J43) -> 5787.7 | L43: =IF(I43<$M$5,I43+J43,$M$5) -> 17450 | M43: =IF(M42<P42,0,M42-O42) -> 2538222.3 | N43: =ROUND(M43*$B43,2) -> 11422 | O43: =IF(M43<P43,M43,P43-N43) -> 2618 | P43: =IF(M43<$M$9,M43+N43,$M$9) -> 14040 | Q43: =IF(Q42<T42,0,Q42-S42) -> 2618604.6 | R43: =ROUND(Q43*$B43,2) -> 11783.72 | S43: =IF(Q43<T43,Q43,T43-R43) -> 2346.28 | T43: =IF(Q43<$M$15,Q43+R43,$M$15) -> 14130 | V43: 21 | W43: 0.9 | X43: 0.9
A44: =VLOOKUP(D44,$A$7:$B$11,2) -> 0.054 | B44: =A44/12 -> 0.0045 | C44: =INT((D44+11)/12) -> 2 | D44: 22 | E44: =IF(E43<H43,0,E43-G43) -> 2463482.4 | F44: =ROUND(E44*$B44,2) -> 11085.67 | G44: =IF(E44<H44,E44,H44-F44) -> 6254.33 | H44: =IF(E44<$M$4,E44+F44,$M$4) -> 17340 | I44: =IF(I43<L43,0,I43-K43) -> 2585834.8 | J44: =ROUND(I44*$B44,2) -> 11636.26 | K44: =IF(I44<L44,I44,L44-J44) -> 5813.74 | L44: =IF(I44<$M$5,I44+J44,$M$5) -> 17450 | M44: =IF(M43<P43,0,M43-O43) -> 2535604.3 | N44: =ROUND(M44*$B44,2) -> 11410.22 | O44: =IF(M44<P44,M44,P44-N44) -> 2629.78 | P44: =IF(M44<$M$9,M44+N44,$M$9) -> 14040 | Q44: =IF(Q43<T43,0,Q43-S43) -> 2616258.3 | R44: =ROUND(Q44*$B44,2) -> 11773.16 | S44: =IF(Q44<T44,Q44,T44-R44) -> 2356.84 | T44: =IF(Q44<$M$15,Q44+R44,$M$15) -> 14130 | V44: 22 | W44: 0.9 | X44: 0.9
A45: =VLOOKUP(D45,$A$7:$B$11,2) -> 0.054 | B45: =A45/12 -> 0.0045 | C45: =INT((D45+11)/12) -> 2 | D45: 23 | E45: =IF(E44<H44,0,E44-G44) -> 2457228.1 | F45: =ROUND(E45*$B45,2) -> 11057.53 | G45: =IF(E45<H45,E45,H45-F45) -> 6282.47 | H45: =IF(E45<$M$4,E45+F45,$M$4) -> 17340 | I45: =IF(I44<L44,0,I44-K44) -> 2580021.1 | J45: =ROUND(I45*$B45,2) -> 11610.09 | K45: =IF(I45<L45,I45,L45-J45) -> 5839.91 | L45: =IF(I45<$M$5,I45+J45,$M$5) -> 17450 | M45: =IF(M44<P44,0,M44-O44) -> 2532974.5 | N45: =ROUND(M45*$B45,2) -> 11398.39 | O45: =IF(M45<P45,M45,P45-N45) -> 2641.61 | P45: =IF(M45<$M$9,M45+N45,$M$9) -> 14040 | Q45: =IF(Q44<T44,0,Q44-S44) -> 2613901.5 | R45: =ROUND(Q45*$B45,2) -> 11762.56 | S45: =IF(Q45<T45,Q45,T45-R45) -> 2367.44 | T45: =IF(Q45<$M$15,Q45+R45,$M$15) -> 14130 | V45: 23 | W45: 0.9 | X45: 0.9
A46: =VLOOKUP(D46,$A$7:$B$11,2) -> 0.054 | B46: =A46/12 -> 0.0045 | C46: =INT((D46+11)/12) -> 2 | D46: 24 | E46: =IF(E45<H45,0,E45-G45) -> 2450945.6 | F46: =ROUND(E46*$B46,2) -> 11029.26 | G46: =IF(E46<H46,E46,H46-F46) -> 6310.74 | H46: =IF(E46<$M$4,E46+F46,$M$4) -> 17340 | I46: =IF(I45<L45,0,I45-K45) -> 2574181.2 | J46: =ROUND(I46*$B46,2) -> 11583.82 | K46: =IF(I46<L46,I46,L46-J46) -> 5866.18 | L46: =IF(I46<$M$5,I46+J46,$M$5) -> 17450 | M46: =IF(M45<P45,0,M45-O45) -> 2530332.9 | N46: =ROUND(M46*$B46,2) -> 11386.5 | O46: =IF(M46<P46,M46,P46-N46) -> 2653.5 | P46: =IF(M46<$M$9,M46+N46,$M$9) -> 14040 | Q46: =IF(Q45<T45,0,Q45-S45) -> 2611534.1 | R46: =ROUND(Q46*$B46,2) -> 11751.9 | S46: =IF(Q46<T46,Q46,T46-R46) -> 2378.1 | T46: =IF(Q46<$M$15,Q46+R46,$M$15) -> 14130 | V46: 24 | W46: 0.89 | X46: 0.9
A47: =VLOOKUP(D47,$A$7:$B$11,2) -> 0.054 | B47: =A47/12 -> 0.0045 | C47: =INT((D47+11)/12) -> 3 | D47: 25 | E47: =IF(E46<H46,0,E46-G46) -> 2444634.9 | F47: =ROUND(E47*$B47,2) -> 11000.86 | G47: =IF(E47<H47,E47,H47-F47) -> 6339.14 | H47: =IF(E47<$M$4,E47+F47,$M$4) -> 17340 | I47: =IF(I46<L46,0,I46-K46) -> 2568315 | J47: =ROUND(I47*$B47,2) -> 11557.42 | K47: =IF(I47<L47,I47,L47-J47) -> 5892.58 | L47: =IF(I47<$M$5,I47+J47,$M$5) -> 17450 | M47: =IF(M46<P46,0,M46-O46) -> 2527679.4 | N47: =ROUND(M47*$B47,2) -> 11374.56 | O47: =IF(M47<P47,M47,P47-N47) -> 4065.44 | P47: =IF(M47<$M$10,M47+N47,$M$10) -> 15440 | Q47: =IF(Q46<T46,0,Q46-S46) -> 2609156 | R47: =ROUND(Q47*$B47,2) -> 11741.2 | S47: =IF(Q47<T47,Q47,T47-R47) -> 2388.8 | T47: =IF(Q47<$M$15,Q47+R47,$M$15) -> 14130 | V47: 25 | W47: 0.89 | X47: 0.89
A48: =VLOOKUP(D48,$A$7:$B$11,2) -> 0.054 | B48: =A48/12 -> 0.0045 | C48: =INT((D48+11)/12) -> 3 | D48: 26 | E48: =IF(E47<H47,0,E47-G47) -> 2438295.7 | F48: =ROUND(E48*$B48,2) -> 10972.33 | G48: =IF(E48<H48,E48,H48-F48) -> 6367.67 | H48: =IF(E48<$M$4,E48+F48,$M$4) -> 17340 | I48: =IF(I47<L47,0,I47-K47) -> 2562422.4 | J48: =ROUND(I48*$B48,2) -> 11530.9 | K48: =IF(I48<L48,I48,L48-J48) -> 5919.1 | L48: =IF(I48<$M$5,I48+J48,$M$5) -> 17450 | M48: =IF(M47<P47,0,M47-O47) -> 2523614 | N48: =ROUND(M48*$B48,2) -> 11356.26 | O48: =IF(M48<P48,M48,P48-N48) -> 4083.74 | P48: =IF(M48<$M$10,M48+N48,$M$10) -> 15440 | Q48: =IF(Q47<T47,0,Q47-S47) -> 2606767.2 | R48: =ROUND(Q48*$B48,2) -> 11730.45 | S48: =IF(Q48<T48,Q48,T48-R48) -> 2399.55 | T48: =IF(Q48<$M$15,Q48+R48,$M$15) -> 14130 | V48: 26 | W48: 0.89 | X48: 0.89
A49: =VLOOKUP(D49,$A$7:$B$11,2) -> 0.054 | B49: =A49/12 -> 0.0045 | C49: =INT((D49+11)/12) -> 3 | D49: 27 | E49: =IF(E48<H48,0,E48-G48) -> 2431928 | F49: =ROUND(E49*$B49,2) -> 10943.68 | G49: =IF(E49<H49,E49,H49-F49) -> 6396.32 | H49: =IF(E49<$M$4,E49+F49,$M$4) -> 17340 | I49: =IF(I48<L48,0,I48-K48) -> 2556503.3 | J49: =ROUND(I49*$B49,2) -> 11504.26 | K49: =IF(I49<L49,I49,L49-J49) -> 5945.74 | L49: =IF(I49<$M$5,I49+J49,$M$5) -> 17450 | M49: =IF(M48<P48,0,M48-O48) -> 2519530.2 | N49: =ROUND(M49*$B49,2) -> 11337.89 | O49: =IF(M49<P49,M49,P49-N49) -> 4102.11 | P49: =IF(M49<$M$10,M49+N49,$M$10) -> 15440 | Q49: =IF(Q48<T48,0,Q48-S48) -> 2604367.6 | R49: =ROUND(Q49*$B49,2) -> 11719.65 | S49: =IF(Q49<T49,Q49,T49-R49) -> 2410.35 | T49: =IF(Q49<$M$15,Q49+R49,$M$15) -> 14130 | V49: 27 | W49: 0.89 | X49: 0.89
A50: =VLOOKUP(D50,$A$7:$B$11,2) -> 0.054 | B50: =A50/12 -> 0.0045 | C50: =INT((D50+11)/12) -> 3 | D50: 28 | E50: =IF(E49<H49,0,E49-G49) -> 2425531.7 | F50: =ROUND(E50*$B50,2) -> 10914.89 | G50: =IF(E50<H50,E50,H50-F50) -> 6425.11 | H50: =IF(E50<$M$4,E50+F50,$M$4) -> 17340 | I50: =IF(I49<L49,0,I49-K49) -> 2550557.6 | J50: =ROUND(I50*$B50,2) -> 11477.51 | K50: =IF(I50<L50,I50,L50-J50) -> 5972.49 | L50: =IF(I50<$M$5,I50+J50,$M$5) -> 17450 | M50: =IF(M49<P49,0,M49-O49) -> 2515428.1 | N50: =ROUND(M50*$B50,2) -> 11319.43 | O50: =IF(M50<P50,M50,P50-N50) -> 4120.57 | P50: =IF(M50<$M$10,M50+N50,$M$10) -> 15440 | Q50: =IF(Q49<T49,0,Q49-S49) -> 2601957.3 | R50: =ROUND(Q50*$B50,2) -> 11708.81 | S50: =IF(Q50<T50,Q50,T50-R50) -> 2421.19 | T50: =IF(Q50<$M$15,Q50+R50,$M$15) -> 14130 | V50: 28 | W50: 0.89 | X50: 0.89
A51: =VLOOKUP(D51,$A$7:$B$11,2) -> 0.054 | B51: =A51/12 -> 0.0045 | C51: =INT((D51+11)/12) -> 3 | D51: 29 | E51: =IF(E50<H50,0,E50-G50) -> 2419106.6 | F51: =ROUND(E51*$B51,2) -> 10885.98 | G51: =IF(E51<H51,E51,H51-F51) -> 6454.02 | H51: =IF(E51<$M$4,E51+F51,$M$4) -> 17340 | I51: =IF(I50<L50,0,I50-K50) -> 2544585.1 | J51: =ROUND(I51*$B51,2) -> 11450.63 | K51: =IF(I51<L51,I51,L51-J51) -> 5999.37 | L51: =IF(I51<$M$5,I51+J51,$M$5) -> 17450 | M51: =IF(M50<P50,0,M50-O50) -> 2511307.5 | N51: =ROUND(M51*$B51,2) -> 11300.88 | O51: =IF(M51<P51,M51,P51-N51) -> 4139.12 | P51: =IF(M51<$M$10,M51+N51,$M$10) -> 15440 | Q51: =IF(Q50<T50,0,Q50-S50) -> 2599536.1 | R51: =ROUND(Q51*$B51,2) -> 11697.91 | S51: =IF(Q51<T51,Q51,T51-R51) -> 2432.09 | T51: =IF(Q51<$M$15,Q51+R51,$M$15) -> 14130 | V51: 29 | W51: 0.89 | X51: 0.89
A52: =VLOOKUP(D52,$A$7:$B$11,2) -> 0.054 | B52: =A52/12 -> 0.0045 | C52: =INT((D52+11)/12) -> 3 | D52: 30 | E52: =IF(E51<H51,0,E51-G51) -> 2412652.6 | F52: =ROUND(E52*$B52,2) -> 10856.94 | G52: =IF(E52<H52,E52,H52-F52) -> 6483.06 | H52: =IF(E52<$M$4,E52+F52,$M$4) -> 17340 | I52: =IF(I51<L51,0,I51-K51) -> 2538585.7 | J52: =ROUND(I52*$B52,2) -> 11423.64 | K52: =IF(I52<L52,I52,L52-J52) -> 6026.36 | L52: =IF(I52<$M$5,I52+J52,$M$5) -> 17450 | M52: =IF(M51<P51,0,M51-O51) -> 2507168.4 | N52: =ROUND(M52*$B52,2) -> 11282.26 | O52: =IF(M52<P52,M52,P52-N52) -> 4157.74 | P52: =IF(M52<$M$10,M52+N52,$M$10) -> 15440 | Q52: =IF(Q51<T51,0,Q51-S51) -> 2597104 | R52: =ROUND(Q52*$B52,2) -> 11686.97 | S52: =IF(Q52<T52,Q52,T52-R52) -> 2443.03 | T52: =IF(Q52<$M$15,Q52+R52,$M$15) -> 14130 | V52: 30 | W52: 0.89 | X52: 0.89
A53: =VLOOKUP(D53,$A$7:$B$11,2) -> 0.054 | B53: =A53/12 -> 0.0045 | C53: =INT((D53+11)/12) -> 3 | D53: 31 | E53: =IF(E52<H52,0,E52-G52) -> 2406169.5 | F53: =ROUND(E53*$B53,2) -> 10827.76 | G53: =IF(E53<H53,E53,H53-F53) -> 6512.24 | H53: =IF(E53<$M$4,E53+F53,$M$4) -> 17340 | I53: =IF(I52<L52,0,I52-K52) -> 2532559.3 | J53: =ROUND(I53*$B53,2) -> 11396.52 | K53: =IF(I53<L53,I53,L53-J53) -> 6053.48 | L53: =IF(I53<$M$5,I53+J53,$M$5) -> 17450 | M53: =IF(M52<P52,0,M52-O52) -> 2503010.7 | N53: =ROUND(M53*$B53,2) -> 11263.55 | O53: =IF(M53<P53,M53,P53-N53) -> 4176.45 | P53: =IF(M53<$M$10,M53+N53,$M$10) -> 15440 | Q53: =IF(Q52<T52,0,Q52-S52) -> 2594661 | R53: =ROUND(Q53*$B53,2) -> 11675.97 | S53: =IF(Q53<T53,Q53,T53-R53) -> 2454.03 | T53: =IF(Q53<$M$15,Q53+R53,$M$15) -> 14130
A54: =VLOOKUP(D54,$A$7:$B$11,2) -> 0.054 | B54: =A54/12 -> 0.0045 | C54: =INT((D54+11)/12) -> 3 | D54: 32 | E54: =IF(E53<H53,0,E53-G53) -> 2399657.3 | F54: =ROUND(E54*$B54,2) -> 10798.46 | G54: =IF(E54<H54,E54,H54-F54) -> 6541.54 | H54: =IF(E54<$M$4,E54+F54,$M$4) -> 17340 | I54: =IF(I53<L53,0,I53-K53) -> 2526505.9 | J54: =ROUND(I54*$B54,2) -> 11369.28 | K54: =IF(I54<L54,I54,L54-J54) -> 6080.72 | L54: =IF(I54<$M$5,I54+J54,$M$5) -> 17450 | M54: =IF(M53<P53,0,M53-O53) -> 2498834.2 | N54: =ROUND(M54*$B54,2) -> 11244.75 | O54: =IF(M54<P54,M54,P54-N54) -> 4195.25 | P54: =IF(M54<$M$10,M54+N54,$M$10) -> 15440 | Q54: =IF(Q53<T53,0,Q53-S53) -> 2592206.9 | R54: =ROUND(Q54*$B54,2) -> 11664.93 | S54: =IF(Q54<T54,Q54,T54-R54) -> 2465.07 | T54: =IF(Q54<$M$15,Q54+R54,$M$15) -> 14130
A55: =VLOOKUP(D55,$A$7:$B$11,2) -> 0.054 | B55: =A55/12 -> 0.0045 | C55: =INT((D55+11)/12) -> 3 | D55: 33 | E55: =IF(E54<H54,0,E54-G54) -> 2393115.8 | F55: =ROUND(E55*$B55,2) -> 10769.02 | G55: =IF(E55<H55,E55,H55-F55) -> 6570.98 | H55: =IF(E55<$M$4,E55+F55,$M$4) -> 17340 | I55: =IF(I54<L54,0,I54-K54) -> 2520425.1 | J55: =ROUND(I55*$B55,2) -> 11341.91 | K55: =IF(I55<L55,I55,L55-J55) -> 6108.09 | L55: =IF(I55<$M$5,I55+J55,$M$5) -> 17450 | M55: =IF(M54<P54,0,M54-O54) -> 2494639 | N55: =ROUND(M55*$B55,2) -> 11225.88 | O55: =IF(M55<P55,M55,P55-N55) -> 4214.12 | P55: =IF(M55<$M$10,M55+N55,$M$10) -> 15440 | Q55: =IF(Q54<T54,0,Q54-S54) -> 2589741.9 | R55: =ROUND(Q55*$B55,2) -> 11653.84 | S55: =IF(Q55<T55,Q55,T55-R55) -> 2476.16 | T55: =IF(Q55<$M$15,Q55+R55,$M$15) -> 14130
A56: =VLOOKUP(D56,$A$7:$B$11,2) -> 0.054 | B56: =A56/12 -> 0.0045 | C56: =INT((D56+11)/12) -> 3 | D56: 34 | E56: =IF(E55<H55,0,E55-G55) -> 2386544.8 | F56: =ROUND(E56*$B56,2) -> 10739.45 | G56: =IF(E56<H56,E56,H56-F56) -> 6600.55 | H56: =IF(E56<$M$4,E56+F56,$M$4) -> 17340 | I56: =IF(I55<L55,0,I55-K55) -> 2514317.1 | J56: =ROUND(I56*$B56,2) -> 11314.43 | K56: =IF(I56<L56,I56,L56-J56) -> 6135.57 | L56: =IF(I56<$M$5,I56+J56,$M$5) -> 17450 | M56: =IF(M55<P55,0,M55-O55) -> 2490424.9 | N56: =ROUND(M56*$B56,2) -> 11206.91 | O56: =IF(M56<P56,M56,P56-N56) -> 4233.09 | P56: =IF(M56<$M$10,M56+N56,$M$10) -> 15440 | Q56: =IF(Q55<T55,0,Q55-S55) -> 2587265.7 | R56: =ROUND(Q56*$B56,2) -> 11642.7 | S56: =IF(Q56<T56,Q56,T56-R56) -> 2487.3 | T56: =IF(Q56<$M$15,Q56+R56,$M$15) -> 14130
A57: =VLOOKUP(D57,$A$7:$B$11,2) -> 0.054 | B57: =A57/12 -> 0.0045 | C57: =INT((D57+11)/12) -> 3 | D57: 35 | E57: =IF(E56<H56,0,E56-G56) -> 2379944.2 | F57: =ROUND(E57*$B57,2) -> 10709.75 | G57: =IF(E57<H57,E57,H57-F57) -> 6630.25 | H57: =IF(E57<$M$4,E57+F57,$M$4) -> 17340 | I57: =IF(I56<L56,0,I56-K56) -> 2508181.5 | J57: =ROUND(I57*$B57,2) -> 11286.82 | K57: =IF(I57<L57,I57,L57-J57) -> 6163.18 | L57: =IF(I57<$M$5,I57+J57,$M$5) -> 17450 | M57: =IF(M56<P56,0,M56-O56) -> 2486191.8 | N57: =ROUND(M57*$B57,2) -> 11187.86 | O57: =IF(M57<P57,M57,P57-N57) -> 4252.14 | P57: =IF(M57<$M$10,M57+N57,$M$10) -> 15440 | Q57: =IF(Q56<T56,0,Q56-S56) -> 2584778.4 | R57: =ROUND(Q57*$B57,2) -> 11631.5 | S57: =IF(Q57<T57,Q57,T57-R57) -> 2498.5 | T57: =IF(Q57<$M$15,Q57+R57,$M$15) -> 14130
A58: =VLOOKUP(D58,$A$7:$B$11,2) -> 0.054 | B58: =A58/12 -> 0.0045 | C58: =INT((D58+11)/12) -> 3 | D58: 36 | E58: =IF(E57<H57,0,E57-G57) -> 2373314 | F58: =ROUND(E58*$B58,2) -> 10679.91 | G58: =IF(E58<H58,E58,H58-F58) -> 6660.09 | H58: =IF(E58<$M$4,E58+F58,$M$4) -> 17340 | I58: =IF(I57<L57,0,I57-K57) -> 2502018.3 | J58: =ROUND(I58*$B58,2) -> 11259.08 | K58: =IF(I58<L58,I58,L58-J58) -> 6190.92 | L58: =IF(I58<$M$5,I58+J58,$M$5) -> 17450 | M58: =IF(M57<P57,0,M57-O57) -> 2481939.6 | N58: =ROUND(M58*$B58,2) -> 11168.73 | O58: =IF(M58<P58,M58,P58-N58) -> 4271.27 | P58: =IF(M58<$M$10,M58+N58,$M$10) -> 15440 | Q58: =IF(Q57<T57,0,Q57-S57) -> 2582279.9 | R58: =ROUND(Q58*$B58,2) -> 11620.26 | S58: =IF(Q58<T58,Q58,T58-R58) -> 2509.74 | T58: =IF(Q58<$M$15,Q58+R58,$M$15) -> 14130
A59: =VLOOKUP(D59,$A$7:$B$11,2) -> 0.064 | B59: =A59/12 -> 0.0053333333 | C59: =INT((D59+11)/12) -> 4 | D59: 37 | E59: =IF(E58<H58,0,E58-G58) -> 2366653.9 | F59: =ROUND(E59*$B59,2) -> 12622.15 | G59: =IF(E59<H59,E59,H59-F59) -> 4717.85 | H59: =IF(E59<$M$4,E59+F59,$M$4) -> 17340 | I59: =IF(I58<L58,0,I58-K58) -> 2495827.4 | J59: =ROUND(I59*$B59,2) -> 13311.08 | K59: =IF(I59<L59,I59,L59-J59) -> 4138.92 | L59: =IF(I59<$M$5,I59+J59,$M$5) -> 17450 | M59: =IF(M58<P58,0,M58-O58) -> 2477668.4 | N59: =ROUND(M59*$B59,2) -> 13214.23 | O59: =IF(M59<P59,M59,P59-N59) -> 2225.77 | P59: =IF(M59<$M$10,M59+N59,$M$10) -> 15440 | Q59: =IF(Q58<T58,0,Q58-S58) -> 2579770.2 | R59: =ROUND(Q59*$B59,2) -> 13758.77 | S59: =IF(Q59<T59,Q59,T59-R59) -> 1781.23 | T59: =IF(Q59<$M$16,Q59+R59,$M$16) -> 15540
A60: =VLOOKUP(D60,$A$7:$B$11,2) -> 0.064 | B60: =A60/12 -> 0.0053333333 | C60: =INT((D60+11)/12) -> 4 | D60: 38 | E60: =IF(E59<H59,0,E59-G59) -> 2361936 | F60: =ROUND(E60*$B60,2) -> 12596.99 | G60: =IF(E60<H60,E60,H60-F60) -> 4743.01 | H60: =IF(E60<$M$4,E60+F60,$M$4) -> 17340 | I60: =IF(I59<L59,0,I59-K59) -> 2491688.5 | J60: =ROUND(I60*$B60,2) -> 13289.01 | K60: =IF(I60<L60,I60,L60-J60) -> 4160.99 | L60: =IF(I60<$M$5,I60+J60,$M$5) -> 17450 | M60: =IF(M59<P59,0,M59-O59) -> 2475442.6 | N60: =ROUND(M60*$B60,2) -> 13202.36 | O60: =IF(M60<P60,M60,P60-N60) -> 2237.64 | P60: =IF(M60<$M$10,M60+N60,$M$10) -> 15440 | Q60: =IF(Q59<T59,0,Q59-S59) -> 2577988.9 | R60: =ROUND(Q60*$B60,2) -> 13749.27 | S60: =IF(Q60<T60,Q60,T60-R60) -> 1790.73 | T60: =IF(Q60<$M$16,Q60+R60,$M$16) -> 15540
A61: =VLOOKUP(D61,$A$7:$B$11,2) -> 0.064 | B61: =A61/12 -> 0.0053333333 | C61: =INT((D61+11)/12) -> 4 | D61: 39 | E61: =IF(E60<H60,0,E60-G60) -> 2357193 | F61: =ROUND(E61*$B61,2) -> 12571.7 | G61: =IF(E61<H61,E61,H61-F61) -> 4768.3 | H61: =IF(E61<$M$4,E61+F61,$M$4) -> 17340 | I61: =IF(I60<L60,0,I60-K60) -> 2487527.5 | J61: =ROUND(I61*$B61,2) -> 13266.81 | K61: =IF(I61<L61,I61,L61-J61) -> 4183.19 | L61: =IF(I61<$M$5,I61+J61,$M$5) -> 17450 | M61: =IF(M60<P60,0,M60-O60) -> 2473204.9 | N61: =ROUND(M61*$B61,2) -> 13190.43 | O61: =IF(M61<P61,M61,P61-N61) -> 2249.57 | P61: =IF(M61<$M$10,M61+N61,$M$10) -> 15440 | Q61: =IF(Q60<T60,0,Q60-S60) -> 2576198.2 | R61: =ROUND(Q61*$B61,2) -> 13739.72 | S61: =IF(Q61<T61,Q61,T61-R61) -> 1800.28 | T61: =IF(Q61<$M$16,Q61+R61,$M$16) -> 15540
A62: =VLOOKUP(D62,$A$7:$B$11,2) -> 0.064 | B62: =A62/12 -> 0.0053333333 | C62: =INT((D62+11)/12) -> 4 | D62: 40 | E62: =IF(E61<H61,0,E61-G61) -> 2352424.7 | F62: =ROUND(E62*$B62,2) -> 12546.27 | G62: =IF(E62<H62,E62,H62-F62) -> 4793.73 | H62: =IF(E62<$M$4,E62+F62,$M$4) -> 17340 | I62: =IF(I61<L61,0,I61-K61) -> 2483344.3 | J62: =ROUND(I62*$B62,2) -> 13244.5 | K62: =IF(I62<L62,I62,L62-J62) -> 4205.5 | L62: =IF(I62<$M$5,I62+J62,$M$5) -> 17450 | M62: =IF(M61<P61,0,M61-O61) -> 2470955.4 | N62: =ROUND(M62*$B62,2) -> 13178.43 | O62: =IF(M62<P62,M62,P62-N62) -> 2261.57 | P62: =IF(M62<$M$10,M62+N62,$M$10) -> 15440 | Q62: =IF(Q61<T61,0,Q61-S61) -> 2574397.9 | R62: =ROUND(Q62*$B62,2) -> 13730.12 | S62: =IF(Q62<T62,Q62,T62-R62) -> 1809.88 | T62: =IF(Q62<$M$16,Q62+R62,$M$16) -> 15540
A63: =VLOOKUP(D63,$A$7:$B$11,2) -> 0.064 | B63: =A63/12 -> 0.0053333333 | C63: =INT((D63+11)/12) -> 4 | D63: 41 | E63: =IF(E62<H62,0,E62-G62) -> 2347631 | F63: =ROUND(E63*$B63,2) -> 12520.7 | G63: =IF(E63<H63,E63,H63-F63) -> 4819.3 | H63: =IF(E63<$M$4,E63+F63,$M$4) -> 17340 | I63: =IF(I62<L62,0,I62-K62) -> 2479138.8 | J63: =ROUND(I63*$B63,2) -> 13222.07 | K63: =IF(I63<L63,I63,L63-J63) -> 4227.93 | L63: =IF(I63<$M$5,I63+J63,$M$5) -> 17450 | M63: =IF(M62<P62,0,M62-O62) -> 2468693.8 | N63: =ROUND(M63*$B63,2) -> 13166.37 | O63: =IF(M63<P63,M63,P63-N63) -> 2273.63 | P63: =IF(M63<$M$10,M63+N63,$M$10) -> 15440 | Q63: =IF(Q62<T62,0,Q62-S62) -> 2572588 | R63: =ROUND(Q63*$B63,2) -> 13720.47 | S63: =IF(Q63<T63,Q63,T63-R63) -> 1819.53 | T63: =IF(Q63<$M$16,Q63+R63,$M$16) -> 15540
A64: =VLOOKUP(D64,$A$7:$B$11,2) -> 0.064 | B64: =A64/12 -> 0.0053333333 | C64: =INT((D64+11)/12) -> 4 | D64: 42 | E64: =IF(E63<H63,0,E63-G63) -> 2342811.7 | F64: =ROUND(E64*$B64,2) -> 12495 | G64: =IF(E64<H64,E64,H64-F64) -> 4845 | H64: =IF(E64<$M$4,E64+F64,$M$4) -> 17340 | I64: =IF(I63<L63,0,I63-K63) -> 2474910.9 | J64: =ROUND(I64*$B64,2) -> 13199.52 | K64: =IF(I64<L64,I64,L64-J64) -> 4250.48 | L64: =IF(I64<$M$5,I64+J64,$M$5) -> 17450 | M64: =IF(M63<P63,0,M63-O63) -> 2466420.2 | N64: =ROUND(M64*$B64,2) -> 13154.24 | O64: =IF(M64<P64,M64,P64-N64) -> 2285.76 | P64: =IF(M64<$M$10,M64+N64,$M$10) -> 15440 | Q64: =IF(Q63<T63,0,Q63-S63) -> 2570768.5 | R64: =ROUND(Q64*$B64,2) -> 13710.77 | S64: =IF(Q64<T64,Q64,T64-R64) -> 1829.23 | T64: =IF(Q64<$M$16,Q64+R64,$M$16) -> 15540
A65: =VLOOKUP(D65,$A$7:$B$11,2) -> 0.064 | B65: =A65/12 -> 0.0053333333 | C65: =INT((D65+11)/12) -> 4 | D65: 43 | E65: =IF(E64<H64,0,E64-G64) -> 2337966.7 | F65: =ROUND(E65*$B65,2) -> 12469.16 | G65: =IF(E65<H65,E65,H65-F65) -> 4870.84 | H65: =IF(E65<$M$4,E65+F65,$M$4) -> 17340 | I65: =IF(I64<L64,0,I64-K64) -> 2470660.4 | J65: =ROUND(I65*$B65,2) -> 13176.86 | K65: =IF(I65<L65,I65,L65-J65) -> 4273.14 | L65: =IF(I65<$M$5,I65+J65,$M$5) -> 17450 | M65: =IF(M64<P64,0,M64-O64) -> 2464134.4 | N65: =ROUND(M65*$B65,2) -> 13142.05 | O65: =IF(M65<P65,M65,P65-N65) -> 2297.95 | P65: =IF(M65<$M$10,M65+N65,$M$10) -> 15440 | Q65: =IF(Q64<T64,0,Q64-S64) -> 2568939.3 | R65: =ROUND(Q65*$B65,2) -> 13701.01 | S65: =IF(Q65<T65,Q65,T65-R65) -> 1838.99 | T65: =IF(Q65<$M$16,Q65+R65,$M$16) -> 15540
A66: =VLOOKUP(D66,$A$7:$B$11,2) -> 0.064 | B66: =A66/12 -> 0.0053333333 | C66: =INT((D66+11)/12) -> 4 | D66: 44 | E66: =IF(E65<H65,0,E65-G65) -> 2333095.9 | F66: =ROUND(E66*$B66,2) -> 12443.18 | G66: =IF(E66<H66,E66,H66-F66) -> 4896.82 | H66: =IF(E66<$M$4,E66+F66,$M$4) -> 17340 | I66: =IF(I65<L65,0,I65-K65) -> 2466387.2 | J66: =ROUND(I66*$B66,2) -> 13154.07 | K66: =IF(I66<L66,I66,L66-J66) -> 4295.93 | L66: =IF(I66<$M$5,I66+J66,$M$5) -> 17450 | M66: =IF(M65<P65,0,M65-O65) -> 2461836.5 | N66: =ROUND(M66*$B66,2) -> 13129.79 | O66: =IF(M66<P66,M66,P66-N66) -> 2310.21 | P66: =IF(M66<$M$10,M66+N66,$M$10) -> 15440 | Q66: =IF(Q65<T65,0,Q65-S65) -> 2567100.3 | R66: =ROUND(Q66*$B66,2) -> 13691.2 | S66: =IF(Q66<T66,Q66,T66-R66) -> 1848.8 | T66: =IF(Q66<$M$16,Q66+R66,$M$16) -> 15540
A67: =VLOOKUP(D67,$A$7:$B$11,2) -> 0.064 | B67: =A67/12 -> 0.0053333333 | C67: =INT((D67+11)/12) -> 4 | D67: 45 | E67: =IF(E66<H66,0,E66-G66) -> 2328199 | F67: =ROUND(E67*$B67,2) -> 12417.06 | G67: =IF(E67<H67,E67,H67-F67) -> 4922.94 | H67: =IF(E67<$M$4,E67+F67,$M$4) -> 17340 | I67: =IF(I66<L66,0,I66-K66) -> 2462091.3 | J67: =ROUND(I67*$B67,2) -> 13131.15 | K67: =IF(I67<L67,I67,L67-J67) -> 4318.85 | L67: =IF(I67<$M$5,I67+J67,$M$5) -> 17450 | M67: =IF(M66<P66,0,M66-O66) -> 2459526.3 | N67: =ROUND(M67*$B67,2) -> 13117.47 | O67: =IF(M67<P67,M67,P67-N67) -> 2322.53 | P67: =IF(M67<$M$10,M67+N67,$M$10) -> 15440 | Q67: =IF(Q66<T66,0,Q66-S66) -> 2565251.5 | R67: =ROUND(Q67*$B67,2) -> 13681.34 | S67: =IF(Q67<T67,Q67,T67-R67) -> 1858.66 | T67: =IF(Q67<$M$16,Q67+R67,$M$16) -> 15540
A68: =VLOOKUP(D68,$A$7:$B$11,2) -> 0.064 | B68: =A68/12 -> 0.0053333333 | C68: =INT((D68+11)/12) -> 4 | D68: 46 | E68: =IF(E67<H67,0,E67-G67) -> 2323276.1 | F68: =ROUND(E68*$B68,2) -> 12390.81 | G68: =IF(E68<H68,E68,H68-F68) -> 4949.19 | H68: =IF(E68<$M$4,E68+F68,$M$4) -> 17340 | I68: =IF(I67<L67,0,I67-K67) -> 2457772.5 | J68: =ROUND(I68*$B68,2) -> 13108.12 | K68: =IF(I68<L68,I68,L68-J68) -> 4341.88 | L68: =IF(I68<$M$5,I68+J68,$M$5) -> 17450 | M68: =IF(M67<P67,0,M67-O67) -> 2457203.7 | N68: =ROUND(M68*$B68,2) -> 13105.09 | O68: =IF(M68<P68,M68,P68-N68) -> 2334.91 | P68: =IF(M68<$M$10,M68+N68,$M$10) -> 15440 | Q68: =IF(Q67<T67,0,Q67-S67) -> 2563392.8 | R68: =ROUND(Q68*$B68,2) -> 13671.43 | S68: =IF(Q68<T68,Q68,T68-R68) -> 1868.57 | T68: =IF(Q68<$M$16,Q68+R68,$M$16) -> 15540
A69: =VLOOKUP(D69,$A$7:$B$11,2) -> 0.064 | B69: =A69/12 -> 0.0053333333 | C69: =INT((D69+11)/12) -> 4 | D69: 47 | E69: =IF(E68<H68,0,E68-G68) -> 2318326.9 | F69: =ROUND(E69*$B69,2) -> 12364.41 | G69: =IF(E69<H69,E69,H69-F69) -> 4975.59 | H69: =IF(E69<$M$4,E69+F69,$M$4) -> 17340 | I69: =IF(I68<L68,0,I68-K68) -> 2453430.6 | J69: =ROUND(I69*$B69,2) -> 13084.96 | K69: =IF(I69<L69,I69,L69-J69) -> 4365.04 | L69: =IF(I69<$M$5,I69+J69,$M$5) -> 17450 | M69: =IF(M68<P68,0,M68-O68) -> 2454868.8 | N69: =ROUND(M69*$B69,2) -> 13092.63 | O69: =IF(M69<P69,M69,P69-N69) -> 2347.37 | P69: =IF(M69<$M$10,M69+N69,$M$10) -> 15440 | Q69: =IF(Q68<T68,0,Q68-S68) -> 2561524.3 | R69: =ROUND(Q69*$B69,2) -> 13661.46 | S69: =IF(Q69<T69,Q69,T69-R69) -> 1878.54 | T69: =IF(Q69<$M$16,Q69+R69,$M$16) -> 15540
A70: =VLOOKUP(D70,$A$7:$B$11,2) -> 0.064 | B70: =A70/12 -> 0.0053333333 | C70: =INT((D70+11)/12) -> 4 | D70: 48 | E70: =IF(E69<H69,0,E69-G69) -> 2313351.3 | F70: =ROUND(E70*$B70,2) -> 12337.87 | G70: =IF(E70<H70,E70,H70-F70) -> 5002.13 | H70: =IF(E70<$M$4,E70+F70,$M$4) -> 17340 | I70: =IF(I69<L69,0,I69-K69) -> 2449065.5 | J70: =ROUND(I70*$B70,2) -> 13061.68 | K70: =IF(I70<L70,I70,L70-J70) -> 4388.32 | L70: =IF(I70<$M$5,I70+J70,$M$5) -> 17450 | M70: =IF(M69<P69,0,M69-O69) -> 2452521.4 | N70: =ROUND(M70*$B70,2) -> 13080.11 | O70: =IF(M70<P70,M70,P70-N70) -> 2359.89 | P70: =IF(M70<$M$10,M70+N70,$M$10) -> 15440 | Q70: =IF(Q69<T69,0,Q69-S69) -> 2559645.7 | R70: =ROUND(Q70*$B70,2) -> 13651.44 | S70: =IF(Q70<T70,Q70,T70-R70) -> 1888.56 | T70: =IF(Q70<$M$16,Q70+R70,$M$16) -> 15540
A71: =VLOOKUP(D71,$A$7:$B$11,2) -> 0.064 | B71: =A71/12 -> 0.0053333333 | C71: =INT((D71+11)/12) -> 5 | D71: 49 | E71: =IF(E70<H70,0,E70-G70) -> 2308349.2 | F71: =ROUND(E71*$B71,2) -> 12311.2 | G71: =IF(E71<H71,E71,H71-F71) -> 5028.8 | H71: =IF(E71<$M$4,E71+F71,$M$4) -> 17340 | I71: =IF(I70<L70,0,I70-K70) -> 2444677.2 | J71: =ROUND(I71*$B71,2) -> 13038.28 | K71: =IF(I71<L71,I71,L71-J71) -> 4411.72 | L71: =IF(I71<$M$5,I71+J71,$M$5) -> 17450 | M71: =IF(M70<P70,0,M70-O70) -> 2450161.6 | N71: =ROUND(M71*$B71,2) -> 13067.53 | O71: =IF(M71<P71,M71,P71-N71) -> 5332.47 | P71: =IF(M71<$M$10,M71+N71,$M$11) -> 18400 | Q71: =IF(Q70<T70,0,Q70-S70) -> 2557757.2 | R71: =ROUND(Q71*$B71,2) -> 13641.37 | S71: =IF(Q71<T71,Q71,T71-R71) -> 1898.63 | T71: =IF(Q71<$M$16,Q71+R71,$M$16) -> 15540
A72: =VLOOKUP(D72,$A$7:$B$11,2) -> 0.064 | B72: =A72/12 -> 0.0053333333 | C72: =INT((D72+11)/12) -> 5 | D72: 50 | E72: =IF(E71<H71,0,E71-G71) -> 2303320.4 | F72: =ROUND(E72*$B72,2) -> 12284.38 | G72: =IF(E72<H72,E72,H72-F72) -> 5055.62 | H72: =IF(E72<$M$4,E72+F72,$M$4) -> 17340 | I72: =IF(I71<L71,0,I71-K71) -> 2440265.5 | J72: =ROUND(I72*$B72,2) -> 13014.75 | K72: =IF(I72<L72,I72,L72-J72) -> 4435.25 | L72: =IF(I72<$M$5,I72+J72,$M$5) -> 17450 | M72: =IF(M71<P71,0,M71-O71) -> 2444829.1 | N72: =ROUND(M72*$B72,2) -> 13039.09 | O72: =IF(M72<P72,M72,P72-N72) -> 5360.91 | P72: =IF(M72<$M$10,M72+N72,$M$11) -> 18400 | Q72: =IF(Q71<T71,0,Q71-S71) -> 2555858.5 | R72: =ROUND(Q72*$B72,2) -> 13631.25 | S72: =IF(Q72<T72,Q72,T72-R72) -> 1908.75 | T72: =IF(Q72<$M$16,Q72+R72,$M$16) -> 15540
A73: =VLOOKUP(D73,$A$7:$B$11,2) -> 0.064 | B73: =A73/12 -> 0.0053333333 | C73: =INT((D73+11)/12) -> 5 | D73: 51 | E73: =IF(E72<H72,0,E72-G72) -> 2298264.8 | F73: =ROUND(E73*$B73,2) -> 12257.41 | G73: =IF(E73<H73,E73,H73-F73) -> 5082.59 | H73: =IF(E73<$M$4,E73+F73,$M$4) -> 17340 | I73: =IF(I72<L72,0,I72-K72) -> 2435830.2 | J73: =ROUND(I73*$B73,2) -> 12991.09 | K73: =IF(I73<L73,I73,L73-J73) -> 4458.91 | L73: =IF(I73<$M$5,I73+J73,$M$5) -> 17450 | M73: =IF(M72<P72,0,M72-O72) -> 2439468.2 | N73: =ROUND(M73*$B73,2) -> 13010.5 | O73: =IF(M73<P73,M73,P73-N73) -> 5389.5 | P73: =IF(M73<$M$10,M73+N73,$M$11) -> 18400 | Q73: =IF(Q72<T72,0,Q72-S72) -> 2553949.8 | R73: =ROUND(Q73*$B73,2) -> 13621.07 | S73: =IF(Q73<T73,Q73,T73-R73) -> 1918.93 | T73: =IF(Q73<$M$16,Q73+R73,$M$16) -> 15540
A74: =VLOOKUP(D74,$A$7:$B$11,2) -> 0.064 | B74: =A74/12 -> 0.0053333333 | C74: =INT((D74+11)/12) -> 5 | D74: 52 | E74: =IF(E73<H73,0,E73-G73) -> 2293182.2 | F74: =ROUND(E74*$B74,2) -> 12230.3 | G74: =IF(E74<H74,E74,H74-F74) -> 5109.7 | H74: =IF(E74<$M$4,E74+F74,$M$4) -> 17340 | I74: =IF(I73<L73,0,I73-K73) -> 2431371.3 | J74: =ROUND(I74*$B74,2) -> 12967.31 | K74: =IF(I74<L74,I74,L74-J74) -> 4482.69 | L74: =IF(I74<$M$5,I74+J74,$M$5) -> 17450 | M74: =IF(M73<P73,0,M73-O73) -> 2434078.7 | N74: =ROUND(M74*$B74,2) -> 12981.75 | O74: =IF(M74<P74,M74,P74-N74) -> 5418.25 | P74: =IF(M74<$M$10,M74+N74,$M$11) -> 18400 | Q74: =IF(Q73<T73,0,Q73-S73) -> 2552030.8 | R74: =ROUND(Q74*$B74,2) -> 13610.83 | S74: =IF(Q74<T74,Q74,T74-R74) -> 1929.17 | T74: =IF(Q74<$M$16,Q74+R74,$M$16) -> 15540
A75: =VLOOKUP(D75,$A$7:$B$11,2) -> 0.064 | B75: =A75/12 -> 0.0053333333 | C75: =INT((D75+11)/12) -> 5 | D75: 53 | E75: =IF(E74<H74,0,E74-G74) -> 2288072.5 | F75: =ROUND(E75*$B75,2) -> 12203.05 | G75: =IF(E75<H75,E75,H75-F75) -> 5136.95 | H75: =IF(E75<$M$4,E75+F75,$M$4) -> 17340 | I75: =IF(I74<L74,0,I74-K74) -> 2426888.6 | J75: =ROUND(I75*$B75,2) -> 12943.41 | K75: =IF(I75<L75,I75,L75-J75) -> 4506.59 | L75: =IF(I75<$M$5,I75+J75,$M$5) -> 17450 | M75: =IF(M74<P74,0,M74-O74) -> 2428660.4 | N75: =ROUND(M75*$B75,2) -> 12952.86 | O75: =IF(M75<P75,M75,P75-N75) -> 5447.14 | P75: =IF(M75<$M$10,M75+N75,$M$11) -> 18400 | Q75: =IF(Q74<T74,0,Q74-S74) -> 2550101.7 | R75: =ROUND(Q75*$B75,2) -> 13600.54 | S75: =IF(Q75<T75,Q75,T75-R75) -> 1939.46 | T75: =IF(Q75<$M$16,Q75+R75,$M$16) -> 15540
A76: =VLOOKUP(D76,$A$7:$B$11,2) -> 0.064 | B76: =A76/12 -> 0.0053333333 | C76: =INT((D76+11)/12) -> 5 | D76: 54 | E76: =IF(E75<H75,0,E75-G75) -> 2282935.5 | F76: =ROUND(E76*$B76,2) -> 12175.66 | G76: =IF(E76<H76,E76,H76-F76) -> 5164.34 | H76: =IF(E76<$M$4,E76+F76,$M$4) -> 17340 | I76: =IF(I75<L75,0,I75-K75) -> 2422382.1 | J76: =ROUND(I76*$B76,2) -> 12919.37 | K76: =IF(I76<L76,I76,L76-J76) -> 4530.63 | L76: =IF(I76<$M$5,I76+J76,$M$5) -> 17450 | M76: =IF(M75<P75,0,M75-O75) -> 2423213.3 | N76: =ROUND(M76*$B76,2) -> 12923.8 | O76: =IF(M76<P76,M76,P76-N76) -> 5476.2 | P76: =IF(M76<$M$10,M76+N76,$M$11) -> 18400 | Q76: =IF(Q75<T75,0,Q75-S75) -> 2548162.2 | R76: =ROUND(Q76*$B76,2) -> 13590.2 | S76: =IF(Q76<T76,Q76,T76-R76) -> 1949.8 | T76: =IF(Q76<$M$16,Q76+R76,$M$16) -> 15540
A77: =VLOOKUP(D77,$A$7:$B$11,2) -> 0.064 | B77: =A77/12 -> 0.0053333333 | C77: =INT((D77+11)/12) -> 5 | D77: 55 | E77: =IF(E76<H76,0,E76-G76) -> 2277771.2 | F77: =ROUND(E77*$B77,2) -> 12148.11 | G77: =IF(E77<H77,E77,H77-F77) -> 5191.89 | H77: =IF(E77<$M$4,E77+F77,$M$4) -> 17340 | I77: =IF(I76<L76,0,I76-K76) -> 2417851.4 | J77: =ROUND(I77*$B77,2) -> 12895.21 | K77: =IF(I77<L77,I77,L77-J77) -> 4554.79 | L77: =IF(I77<$M$5,I77+J77,$M$5) -> 17450 | M77: =IF(M76<P76,0,M76-O76) -> 2417737.1 | N77: =ROUND(M77*$B77,2) -> 12894.6 | O77: =IF(M77<P77,M77,P77-N77) -> 5505.4 | P77: =IF(M77<$M$10,M77+N77,$M$11) -> 18400 | Q77: =IF(Q76<T76,0,Q76-S76) -> 2546212.4 | R77: =ROUND(Q77*$B77,2) -> 13579.8 | S77: =IF(Q77<T77,Q77,T77-R77) -> 1960.2 | T77: =IF(Q77<$M$16,Q77+R77,$M$16) -> 15540
A78: =VLOOKUP(D78,$A$7:$B$11,2) -> 0.064 | B78: =A78/12 -> 0.0053333333 | C78: =INT((D78+11)/12) -> 5 | D78: 56 | E78: =IF(E77<H77,0,E77-G77) -> 2272579.3 | F78: =ROUND(E78*$B78,2) -> 12120.42 | G78: =IF(E78<H78,E78,H78-F78) -> 5219.58 | H78: =IF(E78<$M$4,E78+F78,$M$4) -> 17340 | I78: =IF(I77<L77,0,I77-K77) -> 2413296.6 | J78: =ROUND(I78*$B78,2) -> 12870.92 | K78: =IF(I78<L78,I78,L78-J78) -> 4579.08 | L78: =IF(I78<$M$5,I78+J78,$M$5) -> 17450 | M78: =IF(M77<P77,0,M77-O77) -> 2412231.7 | N78: =ROUND(M78*$B78,2) -> 12865.24 | O78: =IF(M78<P78,M78,P78-N78) -> 5534.76 | P78: =IF(M78<$M$10,M78+N78,$M$11) -> 18400 | Q78: =IF(Q77<T77,0,Q77-S77) -> 2544252.2 | R78: =ROUND(Q78*$B78,2) -> 13569.35 | S78: =IF(Q78<T78,Q78,T78-R78) -> 1970.65 | T78: =IF(Q78<$M$16,Q78+R78,$M$16) -> 15540
A79: =VLOOKUP(D79,$A$7:$B$11,2) -> 0.064 | B79: =A79/12 -> 0.0053333333 | C79: =INT((D79+11)/12) -> 5 | D79: 57 | E79: =IF(E78<H78,0,E78-G78) -> 2267359.7 | F79: =ROUND(E79*$B79,2) -> 12092.59 | G79: =IF(E79<H79,E79,H79-F79) -> 5247.41 | H79: =IF(E79<$M$4,E79+F79,$M$4) -> 17340 | I79: =IF(I78<L78,0,I78-K78) -> 2408717.6 | J79: =ROUND(I79*$B79,2) -> 12846.49 | K79: =IF(I79<L79,I79,L79-J79) -> 4603.51 | L79: =IF(I79<$M$5,I79+J79,$M$5) -> 17450 | M79: =IF(M78<P78,0,M78-O78) -> 2406696.9 | N79: =ROUND(M79*$B79,2) -> 12835.72 | O79: =IF(M79<P79,M79,P79-N79) -> 5564.28 | P79: =IF(M79<$M$10,M79+N79,$M$11) -> 18400 | Q79: =IF(Q78<T78,0,Q78-S78) -> 2542281.6 | R79: =ROUND(Q79*$B79,2) -> 13558.83 | S79: =IF(Q79<T79,Q79,T79-R79) -> 1981.17 | T79: =IF(Q79<$M$16,Q79+R79,$M$16) -> 15540
A80: =VLOOKUP(D80,$A$7:$B$11,2) -> 0.064 | B80: =A80/12 -> 0.0053333333 | C80: =INT((D80+11)/12) -> 5 | D80: 58 | E80: =IF(E79<H79,0,E79-G79) -> 2262112.3 | F80: =ROUND(E80*$B80,2) -> 12064.6 | G80: =IF(E80<H80,E80,H80-F80) -> 5275.4 | H80: =IF(E80<$M$4,E80+F80,$M$4) -> 17340 | I80: =IF(I79<L79,0,I79-K79) -> 2404114 | J80: =ROUND(I80*$B80,2) -> 12821.94 | K80: =IF(I80<L80,I80,L80-J80) -> 4628.06 | L80: =IF(I80<$M$5,I80+J80,$M$5) -> 17450 | M80: =IF(M79<P79,0,M79-O79) -> 2401132.6 | N80: =ROUND(M80*$B80,2) -> 12806.04 | O80: =IF(M80<P80,M80,P80-N80) -> 5593.96 | P80: =IF(M80<$M$10,M80+N80,$M$11) -> 18400 | Q80: =IF(Q79<T79,0,Q79-S79) -> 2540300.4 | R80: =ROUND(Q80*$B80,2) -> 13548.27 | S80: =IF(Q80<T80,Q80,T80-R80) -> 1991.73 | T80: =IF(Q80<$M$16,Q80+R80,$M$16) -> 15540
A81: =VLOOKUP(D81,$A$7:$B$11,2) -> 0.064 | B81: =A81/12 -> 0.0053333333 | C81: =INT((D81+11)/12) -> 5 | D81: 59 | E81: =IF(E80<H80,0,E80-G80) -> 2256836.9 | F81: =ROUND(E81*$B81,2) -> 12036.46 | G81: =IF(E81<H81,E81,H81-F81) -> 5303.54 | H81: =IF(E81<$M$4,E81+F81,$M$4) -> 17340 | I81: =IF(I80<L80,0,I80-K80) -> 2399486 | J81: =ROUND(I81*$B81,2) -> 12797.26 | K81: =IF(I81<L81,I81,L81-J81) -> 4652.74 | L81: =IF(I81<$M$5,I81+J81,$M$5) -> 17450 | M81: =IF(M80<P80,0,M80-O80) -> 2395538.7 | N81: =ROUND(M81*$B81,2) -> 12776.21 | O81: =IF(M81<P81,M81,P81-N81) -> 5623.79 | P81: =IF(M81<$M$10,M81+N81,$M$11) -> 18400 | Q81: =IF(Q80<T80,0,Q80-S80) -> 2538308.7 | R81: =ROUND(Q81*$B81,2) -> 13537.65 | S81: =IF(Q81<T81,Q81,T81-R81) -> 2002.35 | T81: =IF(Q81<$M$16,Q81+R81,$M$16) -> 15540
A82: =VLOOKUP(D82,$A$7:$B$11,2) -> 0.064 | B82: =A82/12 -> 0.0053333333 | C82: =INT((D82+11)/12) -> 5 | D82: 60 | E82: =IF(E81<H81,0,E81-G81) -> 2251533.4 | F82: =ROUND(E82*$B82,2) -> 12008.18 | G82: =IF(E82<H82,E82,H82-F82) -> 5331.82 | H82: =IF(E82<$M$4,E82+F82,$M$4) -> 17340 | I82: =IF(I81<L81,0,I81-K81) -> 2394833.2 | J82: =ROUND(I82*$B82,2) -> 12772.44 | K82: =IF(I82<L82,I82,L82-J82) -> 4677.56 | L82: =IF(I82<$M$5,I82+J82,$M$5) -> 17450 | M82: =IF(M81<P81,0,M81-O81) -> 2389914.9 | N82: =ROUND(M82*$B82,2) -> 12746.21 | O82: =IF(M82<P82,M82,P82-N82) -> 5653.79 | P82: =IF(M82<$M$10,M82+N82,$M$11) -> 18400 | Q82: =IF(Q81<T81,0,Q81-S81) -> 2536306.3 | R82: =ROUND(Q82*$B82,2) -> 13526.97 | S82: =IF(Q82<T82,Q82,T82-R82) -> 2013.03 | T82: =IF(Q82<$M$16,Q82+R82,$M$16) -> 15540
A83: =VLOOKUP(D83,$A$7:$B$11,2) -> 0.064 | B83: =A83/12 -> 0.0053333333 | C83: =INT((D83+11)/12) -> 6 | D83: 61 | E83: =IF(E82<H82,0,E82-G82) -> 2246201.6 | F83: =ROUND(E83*$B83,2) -> 11979.74 | G83: =IF(E83<H83,E83,H83-F83) -> 5360.26 | H83: =IF(E83<$M$4,E83+F83,$M$4) -> 17340 | I83: =IF(I82<L82,0,I82-K82) -> 2390155.7 | J83: =ROUND(I83*$B83,2) -> 12747.5 | K83: =IF(I83<L83,I83,L83-J83) -> 4702.5 | L83: =IF(I83<$M$5,I83+J83,$M$5) -> 17450 | M83: =IF(M82<P82,0,M82-O82) -> 2384261.1 | N83: =ROUND(M83*$B83,2) -> 12716.06 | O83: =IF(M83<P83,M83,P83-N83) -> 5683.94 | P83: =IF(M83<$M$10,M83+N83,$M$11) -> 18400 | Q83: =IF(Q82<T82,0,Q82-S82) -> 2534293.3 | R83: =ROUND(Q83*$B83,2) -> 13516.23 | S83: =IF(Q83<T83,Q83,T83-R83) -> 4973.77 | T83: =IF(Q83<$M$17,Q83+R83,$M$17) -> 18490
A84: =VLOOKUP(D84,$A$7:$B$11,2) -> 0.064 | B84: =A84/12 -> 0.0053333333 | C84: =INT((D84+11)/12) -> 6 | D84: 62 | E84: =IF(E83<H83,0,E83-G83) -> 2240841.3 | F84: =ROUND(E84*$B84,2) -> 11951.15 | G84: =IF(E84<H84,E84,H84-F84) -> 5388.85 | H84: =IF(E84<$M$4,E84+F84,$M$4) -> 17340 | I84: =IF(I83<L83,0,I83-K83) -> 2385453.2 | J84: =ROUND(I84*$B84,2) -> 12722.42 | K84: =IF(I84<L84,I84,L84-J84) -> 4727.58 | L84: =IF(I84<$M$5,I84+J84,$M$5) -> 17450 | M84: =IF(M83<P83,0,M83-O83) -> 2378577.2 | N84: =ROUND(M84*$B84,2) -> 12685.74 | O84: =IF(M84<P84,M84,P84-N84) -> 5714.26 | P84: =IF(M84<$M$10,M84+N84,$M$11) -> 18400 | Q84: =IF(Q83<T83,0,Q83-S83) -> 2529319.5 | R84: =ROUND(Q84*$B84,2) -> 13489.7 | S84: =IF(Q84<T84,Q84,T84-R84) -> 5000.3 | T84: =IF(Q84<$M$17,Q84+R84,$M$17) -> 18490
A85: =VLOOKUP(D85,$A$7:$B$11,2) -> 0.064 | B85: =A85/12 -> 0.0053333333 | C85: =INT((D85+11)/12) -> 6 | D85: 63 | E85: =IF(E84<H84,0,E84-G84) -> 2235452.4 | F85: =ROUND(E85*$B85,2) -> 11922.41 | G85: =IF(E85<H85,E85,H85-F85) -> 5417.59 | H85: =IF(E85<$M$4,E85+F85,$M$4) -> 17340 | I85: =IF(I84<L84,0,I84-K84) -> 2380725.6 | J85: =ROUND(I85*$B85,2) -> 12697.2 | K85: =IF(I85<L85,I85,L85-J85) -> 4752.8 | L85: =IF(I85<$M$5,I85+J85,$M$5) -> 17450 | M85: =IF(M84<P84,0,M84-O84) -> 2372862.9 | N85: =ROUND(M85*$B85,2) -> 12655.27 | O85: =IF(M85<P85,M85,P85-N85) -> 5744.73 | P85: =IF(M85<$M$10,M85+N85,$M$11) -> 18400 | Q85: =IF(Q84<T84,0,Q84-S84) -> 2524319.2 | R85: =ROUND(Q85*$B85,2) -> 13463.04 | S85: =IF(Q85<T85,Q85,T85-R85) -> 5026.96 | T85: =IF(Q85<$M$17,Q85+R85,$M$17) -> 18490
A86: =VLOOKUP(D86,$A$7:$B$11,2) -> 0.064 | B86: =A86/12 -> 0.0053333333 | C86: =INT((D86+11)/12) -> 6 | D86: 64 | E86: =IF(E85<H85,0,E85-G85) -> 2230034.9 | F86: =ROUND(E86*$B86,2) -> 11893.52 | G86: =IF(E86<H86,E86,H86-F86) -> 5446.48 | H86: =IF(E86<$M$4,E86+F86,$M$4) -> 17340 | I86: =IF(I85<L85,0,I85-K85) -> 2375972.8 | J86: =ROUND(I86*$B86,2) -> 12671.85 | K86: =IF(I86<L86,I86,L86-J86) -> 4778.15 | L86: =IF(I86<$M$5,I86+J86,$M$5) -> 17450 | M86: =IF(M85<P85,0,M85-O85) -> 2367118.2 | N86: =ROUND(M86*$B86,2) -> 12624.63 | O86: =IF(M86<P86,M86,P86-N86) -> 5775.37 | P86: =IF(M86<$M$10,M86+N86,$M$11) -> 18400 | Q86: =IF(Q85<T85,0,Q85-S85) -> 2519292.3 | R86: =ROUND(Q86*$B86,2) -> 13436.23 | S86: =IF(Q86<T86,Q86,T86-R86) -> 5053.77 | T86: =IF(Q86<$M$17,Q86+R86,$M$17) -> 18490
A87: =VLOOKUP(D87,$A$7:$B$11,2) -> 0.064 | B87: =A87/12 -> 0.0053333333 | C87: =INT((D87+11)/12) -> 6 | D87: 65 | E87: =IF(E86<H86,0,E86-G86) -> 2224588.4 | F87: =ROUND(E87*$B87,2) -> 11864.47 | G87: =IF(E87<H87,E87,H87-F87) -> 5475.53 | H87: =IF(E87<$M$4,E87+F87,$M$4) -> 17340 | I87: =IF(I86<L86,0,I86-K86) -> 2371194.7 | J87: =ROUND(I87*$B87,2) -> 12646.37 | K87: =IF(I87<L87,I87,L87-J87) -> 4803.63 | L87: =IF(I87<$M$5,I87+J87,$M$5) -> 17450 | M87: =IF(M86<P86,0,M86-O86) -> 2361342.8 | N87: =ROUND(M87*$B87,2) -> 12593.83 | O87: =IF(M87<P87,M87,P87-N87) -> 5806.17 | P87: =IF(M87<$M$10,M87+N87,$M$11) -> 18400 | Q87: =IF(Q86<T86,0,Q86-S86) -> 2514238.5 | R87: =ROUND(Q87*$B87,2) -> 13409.27 | S87: =IF(Q87<T87,Q87,T87-R87) -> 5080.73 | T87: =IF(Q87<$M$17,Q87+R87,$M$17) -> 18490
A88: =VLOOKUP(D88,$A$7:$B$11,2) -> 0.064 | B88: =A88/12 -> 0.0053333333 | C88: =INT((D88+11)/12) -> 6 | D88: 66 | E88: =IF(E87<H87,0,E87-G87) -> 2219112.8 | F88: =ROUND(E88*$B88,2) -> 11835.27 | G88: =IF(E88<H88,E88,H88-F88) -> 5504.73 | H88: =IF(E88<$M$4,E88+F88,$M$4) -> 17340 | I88: =IF(I87<L87,0,I87-K87) -> 2366391 | J88: =ROUND(I88*$B88,2) -> 12620.75 | K88: =IF(I88<L88,I88,L88-J88) -> 4829.25 | L88: =IF(I88<$M$5,I88+J88,$M$5) -> 17450 | M88: =IF(M87<P87,0,M87-O87) -> 2355536.6 | N88: =ROUND(M88*$B88,2) -> 12562.86 | O88: =IF(M88<P88,M88,P88-N88) -> 5837.14 | P88: =IF(M88<$M$10,M88+N88,$M$11) -> 18400 | Q88: =IF(Q87<T87,0,Q87-S87) -> 2509157.8 | R88: =ROUND(Q88*$B88,2) -> 13382.17 | S88: =IF(Q88<T88,Q88,T88-R88) -> 5107.83 | T88: =IF(Q88<$M$17,Q88+R88,$M$17) -> 18490
A89: =VLOOKUP(D89,$A$7:$B$11,2) -> 0.064 | B89: =A89/12 -> 0.0053333333 | C89: =INT((D89+11)/12) -> 6 | D89: 67 | E89: =IF(E88<H88,0,E88-G88) -> 2213608.1 | F89: =ROUND(E89*$B89,2) -> 11805.91 | G89: =IF(E89<H89,E89,H89-F89) -> 5534.09 | H89: =IF(E89<$M$4,E89+F89,$M$4) -> 17340 | I89: =IF(I88<L88,0,I88-K88) -> 2361561.8 | J89: =ROUND(I89*$B89,2) -> 12595 | K89: =IF(I89<L89,I89,L89-J89) -> 4855 | L89: =IF(I89<$M$5,I89+J89,$M$5) -> 17450 | M89: =IF(M88<P88,0,M88-O88) -> 2349699.5 | N89: =ROUND(M89*$B89,2) -> 12531.73 | O89: =IF(M89<P89,M89,P89-N89) -> 5868.27 | P89: =IF(M89<$M$10,M89+N89,$M$11) -> 18400 | Q89: =IF(Q88<T88,0,Q88-S88) -> 2504049.9 | R89: =ROUND(Q89*$B89,2) -> 13354.93 | S89: =IF(Q89<T89,Q89,T89-R89) -> 5135.07 | T89: =IF(Q89<$M$17,Q89+R89,$M$17) -> 18490
A90: =VLOOKUP(D90,$A$7:$B$11,2) -> 0.064 | B90: =A90/12 -> 0.0053333333 | C90: =INT((D90+11)/12) -> 6 | D90: 68 | E90: =IF(E89<H89,0,E89-G89) -> 2208074 | F90: =ROUND(E90*$B90,2) -> 11776.39 | G90: =IF(E90<H90,E90,H90-F90) -> 5563.61 | H90: =IF(E90<$M$4,E90+F90,$M$4) -> 17340 | I90: =IF(I89<L89,0,I89-K89) -> 2356706.8 | J90: =ROUND(I90*$B90,2) -> 12569.1 | K90: =IF(I90<L90,I90,L90-J90) -> 4880.9 | L90: =IF(I90<$M$5,I90+J90,$M$5) -> 17450 | M90: =IF(M89<P89,0,M89-O89) -> 2343831.2 | N90: =ROUND(M90*$B90,2) -> 12500.43 | O90: =IF(M90<P90,M90,P90-N90) -> 5899.57 | P90: =IF(M90<$M$10,M90+N90,$M$11) -> 18400 | Q90: =IF(Q89<T89,0,Q89-S89) -> 2498914.9 | R90: =ROUND(Q90*$B90,2) -> 13327.55 | S90: =IF(Q90<T90,Q90,T90-R90) -> 5162.45 | T90: =IF(Q90<$M$17,Q90+R90,$M$17) -> 18490
A91: =VLOOKUP(D91,$A$7:$B$11,2) -> 0.064 | B91: =A91/12 -> 0.0053333333 | C91: =INT((D91+11)/12) -> 6 | D91: 69 | E91: =IF(E90<H90,0,E90-G90) -> 2202510.4 | F91: =ROUND(E91*$B91,2) -> 11746.72 | G91: =IF(E91<H91,E91,H91-F91) -> 5593.28 | H91: =IF(E91<$M$4,E91+F91,$M$4) -> 17340 | I91: =IF(I90<L90,0,I90-K90) -> 2351825.9 | J91: =ROUND(I91*$B91,2) -> 12543.07 | K91: =IF(I91<L91,I91,L91-J91) -> 4906.93 | L91: =IF(I91<$M$5,I91+J91,$M$5) -> 17450 | M91: =IF(M90<P90,0,M90-O90) -> 2337931.7 | N91: =ROUND(M91*$B91,2) -> 12468.97 | O91: =IF(M91<P91,M91,P91-N91) -> 5931.03 | P91: =IF(M91<$M$10,M91+N91,$M$11) -> 18400 | Q91: =IF(Q90<T90,0,Q90-S90) -> 2493752.4 | R91: =ROUND(Q91*$B91,2) -> 13300.01 | S91: =IF(Q91<T91,Q91,T91-R91) -> 5189.99 | T91: =IF(Q91<$M$17,Q91+R91,$M$17) -> 18490
A92: =VLOOKUP(D92,$A$7:$B$11,2) -> 0.064 | B92: =A92/12 -> 0.0053333333 | C92: =INT((D92+11)/12) -> 6 | D92: 70 | E92: =IF(E91<H91,0,E91-G91) -> 2196917.1 | F92: =ROUND(E92*$B92,2) -> 11716.89 | G92: =IF(E92<H92,E92,H92-F92) -> 5623.11 | H92: =IF(E92<$M$4,E92+F92,$M$4) -> 17340 | I92: =IF(I91<L91,0,I91-K91) -> 2346918.9 | J92: =ROUND(I92*$B92,2) -> 12516.9 | K92: =IF(I92<L92,I92,L92-J92) -> 4933.1 | L92: =IF(I92<$M$5,I92+J92,$M$5) -> 17450 | M92: =IF(M91<P91,0,M91-O91) -> 2332000.6 | N92: =ROUND(M92*$B92,2) -> 12437.34 | O92: =IF(M92<P92,M92,P92-N92) -> 5962.66 | P92: =IF(M92<$M$10,M92+N92,$M$11) -> 18400 | Q92: =IF(Q91<T91,0,Q91-S91) -> 2488562.4 | R92: =ROUND(Q92*$B92,2) -> 13272.33 | S92: =IF(Q92<T92,Q92,T92-R92) -> 5217.67 | T92: =IF(Q92<$M$17,Q92+R92,$M$17) -> 18490
A93: =VLOOKUP(D93,$A$7:$B$11,2) -> 0.064 | B93: =A93/12 -> 0.0053333333 | C93: =INT((D93+11)/12) -> 6 | D93: 71 | E93: =IF(E92<H92,0,E92-G92) -> 2191294 | F93: =ROUND(E93*$B93,2) -> 11686.9 | G93: =IF(E93<H93,E93,H93-F93) -> 5653.1 | H93: =IF(E93<$M$4,E93+F93,$M$4) -> 17340 | I93: =IF(I92<L92,0,I92-K92) -> 2341985.8 | J93: =ROUND(I93*$B93,2) -> 12490.59 | K93: =IF(I93<L93,I93,L93-J93) -> 4959.41 | L93: =IF(I93<$M$5,I93+J93,$M$5) -> 17450 | M93: =IF(M92<P92,0,M92-O92) -> 2326038 | N93: =ROUND(M93*$B93,2) -> 12405.54 | O93: =IF(M93<P93,M93,P93-N93) -> 5994.46 | P93: =IF(M93<$M$10,M93+N93,$M$11) -> 18400 | Q93: =IF(Q92<T92,0,Q92-S92) -> 2483344.7 | R93: =ROUND(Q93*$B93,2) -> 13244.51 | S93: =IF(Q93<T93,Q93,T93-R93) -> 5245.49 | T93: =IF(Q93<$M$17,Q93+R93,$M$17) -> 18490
A94: =VLOOKUP(D94,$A$7:$B$11,2) -> 0.064 | B94: =A94/12 -> 0.0053333333 | C94: =INT((D94+11)/12) -> 6 | D94: 72 | E94: =IF(E93<H93,0,E93-G93) -> 2185640.9 | F94: =ROUND(E94*$B94,2) -> 11656.75 | G94: =IF(E94<H94,E94,H94-F94) -> 5683.25 | H94: =IF(E94<$M$4,E94+F94,$M$4) -> 17340 | I94: =IF(I93<L93,0,I93-K93) -> 2337026.4 | J94: =ROUND(I94*$B94,2) -> 12464.14 | K94: =IF(I94<L94,I94,L94-J94) -> 4985.86 | L94: =IF(I94<$M$5,I94+J94,$M$5) -> 17450 | M94: =IF(M93<P93,0,M93-O93) -> 2320043.5 | N94: =ROUND(M94*$B94,2) -> 12373.57 | O94: =IF(M94<P94,M94,P94-N94) -> 6026.43 | P94: =IF(M94<$M$10,M94+N94,$M$11) -> 18400 | Q94: =IF(Q93<T93,0,Q93-S93) -> 2478099.3 | R94: =ROUND(Q94*$B94,2) -> 13216.53 | S94: =IF(Q94<T94,Q94,T94-R94) -> 5273.47 | T94: =IF(Q94<$M$17,Q94+R94,$M$17) -> 18490
... A392: =VLOOKUP(D392,$A$7:$B$11,2) -> 0.064 | B392: =A392/12 -> 0.0053333333 | C392: =INT((D392+11)/12) -> 31 | D392: 370 | E392: =IF(E391<H391,0,E391-G391) -> 0 | F392: =ROUND(E392*$B392,2) -> 0 | G392: =IF(E392<H392,E392,H392-F392) -> 0 | H392: =IF(E392<$M$4,E392+F392,$M$4) -> 0 | I392: =IF(I391<L391,0,I391-K391) -> 0 | J392: =ROUND(I392*$B392,2) -> 0 | K392: =IF(I392<L392,I392,L392-J392) -> 0 | L392: =IF(I392<$M$5,I392+J392,$M$5) -> 0 | M392: =IF(M391<P391,0,M391-O391) -> 0 | N392: =ROUND(M392*$B392,2) -> 0 | O392: =IF(M392<P392,M392,P392-N392) -> 0 | P392: =IF(M392<$M$10,M392+N392,$M$11) -> 0 | Q392: =IF(Q391<T391,0,Q391-S391) -> 0 | R392: =ROUND(Q392*$B392,2) -> 0 | S392: =IF(Q392<T392,Q392,T392-R392) -> 0 | T392: =IF(Q392<$M$17,Q392+R392,$M$17) -> 0

Sheet Sheet2
A1: สินเชื่อ | B1: ภาระหนี้คงเหลือ | C1: ยอดผ่อน | D1: ration
B2: 204000 | C2: 7480 | D2: =C2/B2 -> 0.036666667
B3: 50000 | C3: =B3/10 -> 5000 | D3: =C3/B3 -> 0.1
B4: 2600000 | C4: 19000 | D4: =C4/B4 -> 0.0073076923
B6: 250000 | C6: =B6*5% -> 12500
B7: 50000 | C7: 5000
B8: 30000 | C8: 3000
A9: 100000 | B9: 30000 | C9: 3000
C10: =SUM(C6:C9) -> 23500

Sheet NCB
A1: DIR | B1: 0.751 | C1: ใส่เป็นเปอร์เซ็น | E1: กู้หลัก | G1: กู้ร่วม
A2: รายได้รวมที่คีย์เข้าไปในระบบ | B2: 46500 | C2: บาท | E2: 8000 | G2: 15000 | J2: 36000
A3: งวดผ่อนต่อเดือนกับ CIMB | B3: 18820 | C3: บาท | E3: 13000 | G3: 10000
A4: ภาระใน NCB | B4: =(B1*B2)-B3 -> 16101.5 | E4: 500
E5: =SUM(E2:E4) -> 21500 | G5: =SUM(G2:G4) -> 25000
C6: รวม | D6: =E5+G5 -> 46500
E8: 6000
D9: 18820

Sheet eBMortgageLoan - Table 1
D1: ="ตารางคำนวณ "&'Secured - Table 1'!$F$33 -> ตารางคำนวณ เงินกู้ปกติ , MRTA
G3: วงเงินกู้ (บาท) | H3: ค่าธรรมเนียม (บาท) | I3: เวลา (เดือน) | J3: อัตราดอกเบี้ย (%) | K3: เงินงวด (บาท) | L3: ผ่อนแบบ ขั้นบันได | M3: เงินงวด (บาท) เผื่อดอกเบี้ย 1% | N3: งวดชำระจริง (งวด) | O3: ยอดชำระรวม (บาท) | P3: ดอกเบี้ยชำระ 3 ปีแรก (บาท)
D4: 1. แบบคงที่ | G4: ='Secured - Table 1'!$F$34 -> 0 | I4: ='Secured - Table 1'!$F$35*12 -> 312 | J4: =($J$7*$C$7+$J$8*$C$8+$J$9*$C$9+$J$10*$C$10+$J$11*('Secured - Table 1'!$F$35*12-SUM($C$7:$C$10)))/('Secured - Table 1'!$F$35*12) -> 0.071403846 | K4: =IF(OR($G$7=0,$I$8=0),0,PMT($J4/12,$I4,-$G4)) -> 0 | M4: =IF(OR($G$7=0,$I$8=0),0,ROUNDUP(PMT(($J4+1%)/12,$I4,-$G4),-1)) -> 0 | N4: =IF(OR($G$7=0,$I$8=0),0,370-COUNTIF(G23:G392,0)) -> 0 | O4: =SUM(H23:H392) -> 0 | P4: =IF(OR($G$7=0,$I$8=0),0,SUM(F23:F58)) -> 0
D5: 2. แบบคงที่ มี Grace Period | G5: ='Secured - Table 1'!$F$34 -> 0 | I5: =I4-12 -> 300 | J5: =($J$7*$C$7+$J$8*$C$8+$J$9*$C$9+$J$10*$C$10+$J$11*('Secured - Table 1'!$F$35*12-SUM($C$7:$C$10)))/('Secured - Table 1'!$F$35*12) -> 0.071403846 | K5: =IF(OR($G$7=0,$I$8=0),0,PMT($J5/12,$I5,-$G5)) -> 0 | M5: =IF(OR($G$7=0,$I$8=0),0,ROUNDUP(PMT(($J5+1%)/12,$I5,-$G5),-1)) -> 0 | N5: =IF(OR($G$7=0,$I$8=0),0,370-COUNTIF(K35:K392,0)) -> 0 | O5: =SUM(L23:L392) -> 0 | P5: =IF(OR($G$7=0,$I$8=0),0,SUM(J23:J58)) -> 0
D6: 3. แบบขั้นบันได
A7: 0 | B7: =J7 -> 0.069 | C7: =VLOOKUP('Secured - Table 1'!$F$33,'Secured - Table 1'!$L$104:$AW$108,'Secured - Table 1'!M$76,FALSE) -> 12 | E7: ='Secured - Table 1'!E37 -> 420 | F7: ='Secured - Table 1'!F37 -> MRR-2.00% | G7: ='Secured - Table 1'!$F$34 -> 0 | I7: ='Secured - Table 1'!$F$35*12 -> 312 | J7: ='Secured - Table 1'!H37 -> 0.069 | K7: =IF(OR($G$7=0,$I$8=0),0,PMT($J7/12,$I7,-$G7)) -> 0
A8: =SUM(C$7:C7)+1 -> 13 | B8: =J8 -> 0.079 | C8: =VLOOKUP('Secured - Table 1'!$F$33,'Secured - Table 1'!$L$104:$AW$108,'Secured - Table 1'!N$76,FALSE) -> 0 | E8: ='Secured - Table 1'!E38 -> ปีที่ 1 | F8: ='Secured - Table 1'!F38 -> MLR-1.25% | G8: =VLOOKUP(A8,$D$22:$T$392,10,FALSE) -> 0 | I8: =I7-C7 -> 300 | J8: ='Secured - Table 1'!H38 -> 0.079 | K8: =IF(OR($G$7=0,$I$8=0),0,PMT($J8/12,$I8,-$G8)) -> 0 | Q8: =$V$20 -> % ปรับปรุงค่างวดแบบขั้นบันได | R8: % ค่างวดเพิ่ม | S8: ค่างวดเพิ่ม
A9: =SUM(C$7:C8)+1 -> 13 | B9: =J9 -> 0.079 | C9: =VLOOKUP('Secured - Table 1'!$F$33,'Secured - Table 1'!$L$104:$AW$108,'Secured - Table 1'!O$76,FALSE) -> 0 | E9: ='Secured - Table 1'!E39 | F9: ='Secured - Table 1'!F39 -> -1 | G9: =VLOOKUP(A9,$D$22:$T$392,10,FALSE) -> 0 | I9: =I8-C8 -> 300 | J9: ='Secured - Table 1'!H39 -> 0.079 | K9: =IF(OR($G$7=0,$I$8=0),0,PMT($J9/12,$I9,-$G9)) -> 0 | L9: ปีที่ 1 และ 2 | M9: =ROUNDUP($M10/$Q9,-1) -> 0 | Q9: 1.1
A10: =SUM(C$7:C9)+1 -> 13 | B10: =J10 -> 0.079 | C10: =VLOOKUP('Secured - Table 1'!$F$33,'Secured - Table 1'!$L$104:$AW$108,'Secured - Table 1'!P$76,FALSE) -> 0 | E10: ='Secured - Table 1'!E40 | F10: ='Secured - Table 1'!F40 -> -1 | G10: =VLOOKUP(A10,$D$22:$T$392,10,FALSE) -> 0 | I10: =I9-C9 -> 300 | J10: ='Secured - Table 1'!H40 -> 0.079 | K10: =IF(OR($G$7=0,$I$8=0),0,PMT($J10/12,$I10,-$G10)) -> 0 | L10: ปีที่ 3 และ 4 | M10: =ROUNDUP($M$4*$Q10,-1) -> 0 | Q10: =IF(OR($G$7=0,$I$8=0),0,VLOOKUP($I$8/12,$V$22:$X$52,2)) -> 0 | R10: =IF(M9=0,0,M10/M9) -> 0 | S10: =M10-M9 -> 0
A11: =SUM(C$7:C10)+1 -> 13 | B11: =J11 -> 0.0715 | E11: ='Secured - Table 1'!E41 | F11: ='Secured - Table 1'!F41 -> MRR-0.75% | G11: =VLOOKUP(A11,$D$22:$T$392,10,FALSE) -> 0 | I11: =I10-C10 -> 300 | J11: ='Secured - Table 1'!H41 -> 0.0715 | K11: =IF(OR($G$7=0,$I$8=0),0,PMT($J11/12,$I11,-$G11)) -> 0 | L11: ปีที่ 5 เป็นต้นไป | M11: =IF(OR($G$7=0,$I$8=0),0,ROUNDUP(PMT($J$11/12,$N$4-48,-$M$71),-1)) -> 0 | N11: =IF(OR($G$7=0,$I$8=0),0,370-COUNTIF(O23:O392,0)) -> 0 | O11: =SUM(P23:P392) -> 0 | P11: =IF(OR($G$7=0,$I$8=0),0,SUM(N23:N58)) -> 0 | R11: =IF(M10=0,0,M11/M10) -> 0 | S11: =M11-M10 -> 0
D12: 4. แบบขั้นบันได มี Grace Period
A13: =A7 -> 0 | B13: =B7 -> 0.069 | C13: =C7 -> 12 | E13: =E7 -> 420 | F13: =F7 -> MRR-2.00% | G13: ='Secured - Table 1'!$F$34 -> 0 | I13: ='Secured - Table 1'!$F$35*12 -> 312 | J13: =J7 -> 0.069 | K13: =IF(OR($G$7=0,$I$8=0),0,$G13*IF($C$13<12,$J$14,$J13)*31/365) -> 0
A14: =A8 -> 13 | B14: =B8 -> 0.079 | C14: =C8 -> 0 | E14: =E8 -> ปีที่ 1 | F14: =F8 -> MLR-1.25% | G14: =VLOOKUP(A14,$D$22:$T$392,14,FALSE) -> 0 | I14: =I8 -> 300 | J14: =J8 -> 0.079 | K14: =IF(OR($G$7=0,$I$8=0),0,IF($C$13<12,K13,PMT($J14/12,$I14,-$G14))) -> 0 | L14: ปีที่ 1 | M14: =ROUNDUP($K13,-1) -> 0 | Q14: =$V$20 -> % ปรับปรุงค่างวดแบบขั้นบันได | R14: % ค่างวดเพิ่ม | S14: ค่างวดเพิ่ม
A15: =A9 -> 13 | B15: =B9 -> 0.079 | C15: =C9 -> 0 | E15: =E9 | F15: =F9 -> -1 | G15: =VLOOKUP(A15,$D$22:$T$392,14,FALSE) -> 0 | I15: =I9 -> 300 | J15: =J9 -> 0.079 | K15: =IF(OR($G$7=0,$I$8=0),0,PMT($J15/12,$I15,-$G15)) -> 0 | L15: ปีที่ 2 และ 3 | M15: =ROUNDUP($M16/$Q15,-1) -> 0 | Q15: 1.1
A16: =A10 -> 13 | B16: =B10 -> 0.079 | C16: =C10 -> 0 | E16: =E10 | F16: =F10 -> -1 | G16: =VLOOKUP(A16,$D$22:$T$392,14,FALSE) -> 0 | I16: =I10 -> 300 | J16: =J10 -> 0.079 | K16: =IF(OR($G$7=0,$I$8=0),0,PMT($J16/12,$I16,-$G16)) -> 0 | L16: ปีที่ 4 และ 5 | M16: =ROUNDUP($M$5*$Q16,-1) -> 0 | Q16: =IF(OR($G$7=0,$I$8=0),0,VLOOKUP($I$8/12,$V$22:$X$52,3)) -> 0 | R16: =IF(M15=0,0,M16/M15) -> 0 | S16: =M16-M15 -> 0
A17: =A11 -> 13 | B17: =B11 -> 0.0715 | E17: =E11 | F17: =F11 -> MRR-0.75% | G17: =VLOOKUP(A17,$D$22:$T$392,14,FALSE) -> 0 | I17: =I11 -> 300 | J17: =J11 -> 0.0715 | K17: =IF(OR($G$7=0,$I$8=0),0,PMT($J17/12,$I17,-$G17)) -> 0 | L17: ปีที่ 6 เป็นต้นไป | M17: =IF(OR($G$7=0,$I$8=0),0,ROUNDUP(PMT($J17/12,$N$5-60,-$Q$83),-1)) -> 0 | N17: =IF(OR($G$7=0,$I$8=0),0,370-COUNTIF(S23:S392,0)) -> 0 | O17: =SUM(T23:T392) -> 0 | P17: =IF(OR($G$7=0,$I$8=0),0,SUM(R23:R58)) -> 0 | R17: =IF(M16=0,0,M17/M16) -> 0 | S17: =M17-M16 -> 0
E20: =D4 -> 1. แบบคงที่ | I20: =D5 -> 2. แบบคงที่ มี Grace Period | M20: =D6 -> 3. แบบขั้นบันได | Q20: =D12 -> 4. แบบขั้นบันได มี Grace Period | V20: % ปรับปรุงค่างวดแบบขั้นบันได
A21: Annual rate | B21: Monthly rate | C21: ปี | D21: งวด | E21: เงินต้นคงเหลือ | F21: ดอกเบี้ยผ่อนชำระ | G21: เงินต้นผ่อนชำระ | H21: เงินงวด | I21: เงินต้นคงเหลือ | J21: ดอกเบี้ยผ่อนชำระ | K21: เงินต้นผ่อนชำระ | L21: เงินงวด | M21: เงินต้นคงเหลือ | N21: ดอกเบี้ยผ่อนชำระ | O21: เงินต้นผ่อนชำระ | P21: เงินงวด | Q21: เงินต้นคงเหลือ | R21: ดอกเบี้ยผ่อนชำระ | S21: เงินต้นผ่อนชำระ | T21: เงินงวด | V21: ระยะเวลา (ปี) | W21: ไม่มี Grace Period | X21: มี Grace Period
C22: 0 | D22: 0 | H22: =-$G$7 -> 0 | L22: =-$G$7 -> 0 | P22: =-$G$7 -> 0 | T22: =-$G$7 -> 0 | V22: 0 | W22: 1 | X22: 1.03
A23: =VLOOKUP(D23,$A$7:$B$11,2) -> 0.069 | B23: =A23/12 -> 0.00575 | C23: =INT((D23+11)/12) -> 1 | D23: 1 | E23: =$G$7 -> 0 | F23: =ROUND(E23*$B23,2) -> 0 | G23: =IF(E23<H23,E23,H23-F23) -> 0 | H23: =IF(E23<$M$4,E23+F23,$M$4) -> 0 | I23: =$G$7 -> 0 | J23: =ROUND(I23*$B23,2) -> 0 | K23: =IF(I23<L23,I23,L23-J23) -> 0 | L23: =IF(I23<$M$14,I23+J23,$M$14) -> 0 | M23: =$G$7 -> 0 | N23: =ROUND(M23*$B23,2) -> 0 | O23: =IF(M23<P23,M23,P23-N23) -> 0 | P23: =IF(M23<$M$9,M23+N23,$M$9) -> 0 | Q23: =$G$7 -> 0 | R23: =ROUND(Q23*$B23,2) -> 0 | S23: =IF(Q23<T23,Q23,T23-R23) -> 0 | T23: =IF(Q23<$M$14,Q23+R23,$M$14) -> 0 | V23: 1 | W23: 1 | X23: 1.03
A24: =VLOOKUP(D24,$A$7:$B$11,2) -> 0.069 | B24: =A24/12 -> 0.00575 | C24: =INT((D24+11)/12) -> 1 | D24: 2 | E24: =IF(E23<H23,0,E23-G23) -> 0 | F24: =ROUND(E24*$B24,2) -> 0 | G24: =IF(E24<H24,E24,H24-F24) -> 0 | H24: =IF(E24<$M$4,E24+F24,$M$4) -> 0 | I24: =IF(I23<L23,0,I23-K23) -> 0 | J24: =ROUND(I24*$B24,2) -> 0 | K24: =IF(I24<L24,I24,L24-J24) -> 0 | L24: =IF(I24<$M$14,I24+J24,$M$14) -> 0 | M24: =IF(M23<P23,0,M23-O23) -> 0 | N24: =ROUND(M24*$B24,2) -> 0 | O24: =IF(M24<P24,M24,P24-N24) -> 0 | P24: =IF(M24<$M$9,M24+N24,$M$9) -> 0 | Q24: =IF(Q23<T23,0,Q23-S23) -> 0 | R24: =ROUND(Q24*$B24,2) -> 0 | S24: =IF(Q24<T24,Q24,T24-R24) -> 0 | T24: =IF(Q24<$M$14,Q24+R24,$M$14) -> 0 | V24: 2 | W24: 1 | X24: 1.03
A25: =VLOOKUP(D25,$A$7:$B$11,2) -> 0.069 | B25: =A25/12 -> 0.00575 | C25: =INT((D25+11)/12) -> 1 | D25: 3 | E25: =IF(E24<H24,0,E24-G24) -> 0 | F25: =ROUND(E25*$B25,2) -> 0 | G25: =IF(E25<H25,E25,H25-F25) -> 0 | H25: =IF(E25<$M$4,E25+F25,$M$4) -> 0 | I25: =IF(I24<L24,0,I24-K24) -> 0 | J25: =ROUND(I25*$B25,2) -> 0 | K25: =IF(I25<L25,I25,L25-J25) -> 0 | L25: =IF(I25<$M$14,I25+J25,$M$14) -> 0 | M25: =IF(M24<P24,0,M24-O24) -> 0 | N25: =ROUND(M25*$B25,2) -> 0 | O25: =IF(M25<P25,M25,P25-N25) -> 0 | P25: =IF(M25<$M$9,M25+N25,$M$9) -> 0 | Q25: =IF(Q24<T24,0,Q24-S24) -> 0 | R25: =ROUND(Q25*$B25,2) -> 0 | S25: =IF(Q25<T25,Q25,T25-R25) -> 0 | T25: =IF(Q25<$M$14,Q25+R25,$M$14) -> 0 | V25: 3 | W25: 1 | X25: 1.03
A26: =VLOOKUP(D26,$A$7:$B$11,2) -> 0.069 | B26: =A26/12 -> 0.00575 | C26: =INT((D26+11)/12) -> 1 | D26: 4 | E26: =IF(E25<H25,0,E25-G25) -> 0 | F26: =ROUND(E26*$B26,2) -> 0 | G26: =IF(E26<H26,E26,H26-F26) -> 0 | H26: =IF(E26<$M$4,E26+F26,$M$4) -> 0 | I26: =IF(I25<L25,0,I25-K25) -> 0 | J26: =ROUND(I26*$B26,2) -> 0 | K26: =IF(I26<L26,I26,L26-J26) -> 0 | L26: =IF(I26<$M$14,I26+J26,$M$14) -> 0 | M26: =IF(M25<P25,0,M25-O25) -> 0 | N26: =ROUND(M26*$B26,2) -> 0 | O26: =IF(M26<P26,M26,P26-N26) -> 0 | P26: =IF(M26<$M$9,M26+N26,$M$9) -> 0 | Q26: =IF(Q25<T25,0,Q25-S25) -> 0 | R26: =ROUND(Q26*$B26,2) -> 0 | S26: =IF(Q26<T26,Q26,T26-R26) -> 0 | T26: =IF(Q26<$M$14,Q26+R26,$M$14) -> 0 | V26: 4 | W26: 1 | X26: 1.03
A27: =VLOOKUP(D27,$A$7:$B$11,2) -> 0.069 | B27: =A27/12 -> 0.00575 | C27: =INT((D27+11)/12) -> 1 | D27: 5 | E27: =IF(E26<H26,0,E26-G26) -> 0 | F27: =ROUND(E27*$B27,2) -> 0 | G27: =IF(E27<H27,E27,H27-F27) -> 0 | H27: =IF(E27<$M$4,E27+F27,$M$4) -> 0 | I27: =IF(I26<L26,0,I26-K26) -> 0 | J27: =ROUND(I27*$B27,2) -> 0 | K27: =IF(I27<L27,I27,L27-J27) -> 0 | L27: =IF(I27<$M$14,I27+J27,$M$14) -> 0 | M27: =IF(M26<P26,0,M26-O26) -> 0 | N27: =ROUND(M27*$B27,2) -> 0 | O27: =IF(M27<P27,M27,P27-N27) -> 0 | P27: =IF(M27<$M$9,M27+N27,$M$9) -> 0 | Q27: =IF(Q26<T26,0,Q26-S26) -> 0 | R27: =ROUND(Q27*$B27,2) -> 0 | S27: =IF(Q27<T27,Q27,T27-R27) -> 0 | T27: =IF(Q27<$M$14,Q27+R27,$M$14) -> 0 | V27: 5 | W27: 1 | X27: 1.03
A28: =VLOOKUP(D28,$A$7:$B$11,2) -> 0.069 | B28: =A28/12 -> 0.00575 | C28: =INT((D28+11)/12) -> 1 | D28: 6 | E28: =IF(E27<H27,0,E27-G27) -> 0 | F28: =ROUND(E28*$B28,2) -> 0 | G28: =IF(E28<H28,E28,H28-F28) -> 0 | H28: =IF(E28<$M$4,E28+F28,$M$4) -> 0 | I28: =IF(I27<L27,0,I27-K27) -> 0 | J28: =ROUND(I28*$B28,2) -> 0 | K28: =IF(I28<L28,I28,L28-J28) -> 0 | L28: =IF(I28<$M$14,I28+J28,$M$14) -> 0 | M28: =IF(M27<P27,0,M27-O27) -> 0 | N28: =ROUND(M28*$B28,2) -> 0 | O28: =IF(M28<P28,M28,P28-N28) -> 0 | P28: =IF(M28<$M$9,M28+N28,$M$9) -> 0 | Q28: =IF(Q27<T27,0,Q27-S27) -> 0 | R28: =ROUND(Q28*$B28,2) -> 0 | S28: =IF(Q28<T28,Q28,T28-R28) -> 0 | T28: =IF(Q28<$M$14,Q28+R28,$M$14) -> 0 | V28: 6 | W28: 1 | X28: 1.03
A29: =VLOOKUP(D29,$A$7:$B$11,2) -> 0.069 | B29: =A29/12 -> 0.00575 | C29: =INT((D29+11)/12) -> 1 | D29: 7 | E29: =IF(E28<H28,0,E28-G28) -> 0 | F29: =ROUND(E29*$B29,2) -> 0 | G29: =IF(E29<H29,E29,H29-F29) -> 0 | H29: =IF(E29<$M$4,E29+F29,$M$4) -> 0 | I29: =IF(I28<L28,0,I28-K28) -> 0 | J29: =ROUND(I29*$B29,2) -> 0 | K29: =IF(I29<L29,I29,L29-J29) -> 0 | L29: =IF(I29<$M$14,I29+J29,$M$14) -> 0 | M29: =IF(M28<P28,0,M28-O28) -> 0 | N29: =ROUND(M29*$B29,2) -> 0 | O29: =IF(M29<P29,M29,P29-N29) -> 0 | P29: =IF(M29<$M$9,M29+N29,$M$9) -> 0 | Q29: =IF(Q28<T28,0,Q28-S28) -> 0 | R29: =ROUND(Q29*$B29,2) -> 0 | S29: =IF(Q29<T29,Q29,T29-R29) -> 0 | T29: =IF(Q29<$M$14,Q29+R29,$M$14) -> 0 | V29: 7 | W29: 0.98 | X29: 1
A30: =VLOOKUP(D30,$A$7:$B$11,2) -> 0.069 | B30: =A30/12 -> 0.00575 | C30: =INT((D30+11)/12) -> 1 | D30: 8 | E30: =IF(E29<H29,0,E29-G29) -> 0 | F30: =ROUND(E30*$B30,2) -> 0 | G30: =IF(E30<H30,E30,H30-F30) -> 0 | H30: =IF(E30<$M$4,E30+F30,$M$4) -> 0 | I30: =IF(I29<L29,0,I29-K29) -> 0 | J30: =ROUND(I30*$B30,2) -> 0 | K30: =IF(I30<L30,I30,L30-J30) -> 0 | L30: =IF(I30<$M$14,I30+J30,$M$14) -> 0 | M30: =IF(M29<P29,0,M29-O29) -> 0 | N30: =ROUND(M30*$B30,2) -> 0 | O30: =IF(M30<P30,M30,P30-N30) -> 0 | P30: =IF(M30<$M$9,M30+N30,$M$9) -> 0 | Q30: =IF(Q29<T29,0,Q29-S29) -> 0 | R30: =ROUND(Q30*$B30,2) -> 0 | S30: =IF(Q30<T30,Q30,T30-R30) -> 0 | T30: =IF(Q30<$M$14,Q30+R30,$M$14) -> 0 | V30: 8 | W30: 0.96 | X30: 0.98
A31: =VLOOKUP(D31,$A$7:$B$11,2) -> 0.069 | B31: =A31/12 -> 0.00575 | C31: =INT((D31+11)/12) -> 1 | D31: 9 | E31: =IF(E30<H30,0,E30-G30) -> 0 | F31: =ROUND(E31*$B31,2) -> 0 | G31: =IF(E31<H31,E31,H31-F31) -> 0 | H31: =IF(E31<$M$4,E31+F31,$M$4) -> 0 | I31: =IF(I30<L30,0,I30-K30) -> 0 | J31: =ROUND(I31*$B31,2) -> 0 | K31: =IF(I31<L31,I31,L31-J31) -> 0 | L31: =IF(I31<$M$14,I31+J31,$M$14) -> 0 | M31: =IF(M30<P30,0,M30-O30) -> 0 | N31: =ROUND(M31*$B31,2) -> 0 | O31: =IF(M31<P31,M31,P31-N31) -> 0 | P31: =IF(M31<$M$9,M31+N31,$M$9) -> 0 | Q31: =IF(Q30<T30,0,Q30-S30) -> 0 | R31: =ROUND(Q31*$B31,2) -> 0 | S31: =IF(Q31<T31,Q31,T31-R31) -> 0 | T31: =IF(Q31<$M$14,Q31+R31,$M$14) -> 0 | V31: 9 | W31: 0.95 | X31: 0.96
A32: =VLOOKUP(D32,$A$7:$B$11,2) -> 0.069 | B32: =A32/12 -> 0.00575 | C32: =INT((D32+11)/12) -> 1 | D32: 10 | E32: =IF(E31<H31,0,E31-G31) -> 0 | F32: =ROUND(E32*$B32,2) -> 0 | G32: =IF(E32<H32,E32,H32-F32) -> 0 | H32: =IF(E32<$M$4,E32+F32,$M$4) -> 0 | I32: =IF(I31<L31,0,I31-K31) -> 0 | J32: =ROUND(I32*$B32,2) -> 0 | K32: =IF(I32<L32,I32,L32-J32) -> 0 | L32: =IF(I32<$M$14,I32+J32,$M$14) -> 0 | M32: =IF(M31<P31,0,M31-O31) -> 0 | N32: =ROUND(M32*$B32,2) -> 0 | O32: =IF(M32<P32,M32,P32-N32) -> 0 | P32: =IF(M32<$M$9,M32+N32,$M$9) -> 0 | Q32: =IF(Q31<T31,0,Q31-S31) -> 0 | R32: =ROUND(Q32*$B32,2) -> 0 | S32: =IF(Q32<T32,Q32,T32-R32) -> 0 | T32: =IF(Q32<$M$14,Q32+R32,$M$14) -> 0 | V32: 10 | W32: 0.94 | X32: 0.95
A33: =VLOOKUP(D33,$A$7:$B$11,2) -> 0.069 | B33: =A33/12 -> 0.00575 | C33: =INT((D33+11)/12) -> 1 | D33: 11 | E33: =IF(E32<H32,0,E32-G32) -> 0 | F33: =ROUND(E33*$B33,2) -> 0 | G33: =IF(E33<H33,E33,H33-F33) -> 0 | H33: =IF(E33<$M$4,E33+F33,$M$4) -> 0 | I33: =IF(I32<L32,0,I32-K32) -> 0 | J33: =ROUND(I33*$B33,2) -> 0 | K33: =IF(I33<L33,I33,L33-J33) -> 0 | L33: =IF(I33<$M$14,I33+J33,$M$14) -> 0 | M33: =IF(M32<P32,0,M32-O32) -> 0 | N33: =ROUND(M33*$B33,2) -> 0 | O33: =IF(M33<P33,M33,P33-N33) -> 0 | P33: =IF(M33<$M$9,M33+N33,$M$9) -> 0 | Q33: =IF(Q32<T32,0,Q32-S32) -> 0 | R33: =ROUND(Q33*$B33,2) -> 0 | S33: =IF(Q33<T33,Q33,T33-R33) -> 0 | T33: =IF(Q33<$M$14,Q33+R33,$M$14) -> 0 | V33: 11 | W33: 0.93 | X33: 0.94
A34: =VLOOKUP(D34,$A$7:$B$11,2) -> 0.069 | B34: =A34/12 -> 0.00575 | C34: =INT((D34+11)/12) -> 1 | D34: 12 | E34: =IF(E33<H33,0,E33-G33) -> 0 | F34: =ROUND(E34*$B34,2) -> 0 | G34: =IF(E34<H34,E34,H34-F34) -> 0 | H34: =IF(E34<$M$4,E34+F34,$M$4) -> 0 | I34: =IF(I33<L33,0,I33-K33) -> 0 | J34: =ROUND(I34*$B34,2) -> 0 | K34: =IF(I34<L34,I34,L34-J34) -> 0 | L34: =IF(I34<$M$14,I34+J34,$M$14) -> 0 | M34: =IF(M33<P33,0,M33-O33) -> 0 | N34: =ROUND(M34*$B34,2) -> 0 | O34: =IF(M34<P34,M34,P34-N34) -> 0 | P34: =IF(M34<$M$9,M34+N34,$M$9) -> 0 | Q34: =IF(Q33<T33,0,Q33-S33) -> 0 | R34: =ROUND(Q34*$B34,2) -> 0 | S34: =IF(Q34<T34,Q34,T34-R34) -> 0 | T34: =IF(Q34<$M$14,Q34+R34,$M$14) -> 0 | V34: 12 | W34: 0.93 | X34: 0.93
A35: =VLOOKUP(D35,$A$7:$B$11,2) -> 0.0715 | B35: =A35/12 -> 0.0059583333 | C35: =INT((D35+11)/12) -> 2 | D35: 13 | E35: =IF(E34<H34,0,E34-G34) -> 0 | F35: =ROUND(E35*$B35,2) -> 0 | G35: =IF(E35<H35,E35,H35-F35) -> 0 | H35: =IF(E35<$M$4,E35+F35,$M$4) -> 0 | I35: =IF(I34<L34,0,I34-K34) -> 0 | J35: =ROUND(I35*$B35,2) -> 0 | K35: =IF(I35<L35,I35,L35-J35) -> 0 | L35: =IF(I35<$M$5,I35+J35,$M$5) -> 0 | M35: =IF(M34<P34,0,M34-O34) -> 0 | N35: =ROUND(M35*$B35,2) -> 0 | O35: =IF(M35<P35,M35,P35-N35) -> 0 | P35: =IF(M35<$M$9,M35+N35,$M$9) -> 0 | Q35: =IF(Q34<T34,0,Q34-S34) -> 0 | R35: =ROUND(Q35*$B35,2) -> 0 | S35: =IF(Q35<T35,Q35,T35-R35) -> 0 | T35: =IF(Q35<$M$15,Q35+R35,$M$15) -> 0 | V35: 13 | W35: 0.92 | X35: 0.93
A36: =VLOOKUP(D36,$A$7:$B$11,2) -> 0.0715 | B36: =A36/12 -> 0.0059583333 | C36: =INT((D36+11)/12) -> 2 | D36: 14 | E36: =IF(E35<H35,0,E35-G35) -> 0 | F36: =ROUND(E36*$B36,2) -> 0 | G36: =IF(E36<H36,E36,H36-F36) -> 0 | H36: =IF(E36<$M$4,E36+F36,$M$4) -> 0 | I36: =IF(I35<L35,0,I35-K35) -> 0 | J36: =ROUND(I36*$B36,2) -> 0 | K36: =IF(I36<L36,I36,L36-J36) -> 0 | L36: =IF(I36<$M$5,I36+J36,$M$5) -> 0 | M36: =IF(M35<P35,0,M35-O35) -> 0 | N36: =ROUND(M36*$B36,2) -> 0 | O36: =IF(M36<P36,M36,P36-N36) -> 0 | P36: =IF(M36<$M$9,M36+N36,$M$9) -> 0 | Q36: =IF(Q35<T35,0,Q35-S35) -> 0 | R36: =ROUND(Q36*$B36,2) -> 0 | S36: =IF(Q36<T36,Q36,T36-R36) -> 0 | T36: =IF(Q36<$M$15,Q36+R36,$M$15) -> 0 | V36: 14 | W36: 0.92 | X36: 0.92
A37: =VLOOKUP(D37,$A$7:$B$11,2) -> 0.0715 | B37: =A37/12 -> 0.0059583333 | C37: =INT((D37+11)/12) -> 2 | D37: 15 | E37: =IF(E36<H36,0,E36-G36) -> 0 | F37: =ROUND(E37*$B37,2) -> 0 | G37: =IF(E37<H37,E37,H37-F37) -> 0 | H37: =IF(E37<$M$4,E37+F37,$M$4) -> 0 | I37: =IF(I36<L36,0,I36-K36) -> 0 | J37: =ROUND(I37*$B37,2) -> 0 | K37: =IF(I37<L37,I37,L37-J37) -> 0 | L37: =IF(I37<$M$5,I37+J37,$M$5) -> 0 | M37: =IF(M36<P36,0,M36-O36) -> 0 | N37: =ROUND(M37*$B37,2) -> 0 | O37: =IF(M37<P37,M37,P37-N37) -> 0 | P37: =IF(M37<$M$9,M37+N37,$M$9) -> 0 | Q37: =IF(Q36<T36,0,Q36-S36) -> 0 | R37: =ROUND(Q37*$B37,2) -> 0 | S37: =IF(Q37<T37,Q37,T37-R37) -> 0 | T37: =IF(Q37<$M$15,Q37+R37,$M$15) -> 0 | V37: 15 | W37: 0.91 | X37: 0.92
A38: =VLOOKUP(D38,$A$7:$B$11,2) -> 0.0715 | B38: =A38/12 -> 0.0059583333 | C38: =INT((D38+11)/12) -> 2 | D38: 16 | E38: =IF(E37<H37,0,E37-G37) -> 0 | F38: =ROUND(E38*$B38,2) -> 0 | G38: =IF(E38<H38,E38,H38-F38) -> 0 | H38: =IF(E38<$M$4,E38+F38,$M$4) -> 0 | I38: =IF(I37<L37,0,I37-K37) -> 0 | J38: =ROUND(I38*$B38,2) -> 0 | K38: =IF(I38<L38,I38,L38-J38) -> 0 | L38: =IF(I38<$M$5,I38+J38,$M$5) -> 0 | M38: =IF(M37<P37,0,M37-O37) -> 0 | N38: =ROUND(M38*$B38,2) -> 0 | O38: =IF(M38<P38,M38,P38-N38) -> 0 | P38: =IF(M38<$M$9,M38+N38,$M$9) -> 0 | Q38: =IF(Q37<T37,0,Q37-S37) -> 0 | R38: =ROUND(Q38*$B38,2) -> 0 | S38: =IF(Q38<T38,Q38,T38-R38) -> 0 | T38: =IF(Q38<$M$15,Q38+R38,$M$15) -> 0 | V38: 16 | W38: 0.91 | X38: 0.91
A39: =VLOOKUP(D39,$A$7:$B$11,2) -> 0.0715 | B39: =A39/12 -> 0.0059583333 | C39: =INT((D39+11)/12) -> 2 | D39: 17 | E39: =IF(E38<H38,0,E38-G38) -> 0 | F39: =ROUND(E39*$B39,2) -> 0 | G39: =IF(E39<H39,E39,H39-F39) -> 0 | H39: =IF(E39<$M$4,E39+F39,$M$4) -> 0 | I39: =IF(I38<L38,0,I38-K38) -> 0 | J39: =ROUND(I39*$B39,2) -> 0 | K39: =IF(I39<L39,I39,L39-J39) -> 0 | L39: =IF(I39<$M$5,I39+J39,$M$5) -> 0 | M39: =IF(M38<P38,0,M38-O38) -> 0 | N39: =ROUND(M39*$B39,2) -> 0 | O39: =IF(M39<P39,M39,P39-N39) -> 0 | P39: =IF(M39<$M$9,M39+N39,$M$9) -> 0 | Q39: =IF(Q38<T38,0,Q38-S38) -> 0 | R39: =ROUND(Q39*$B39,2) -> 0 | S39: =IF(Q39<T39,Q39,T39-R39) -> 0 | T39: =IF(Q39<$M$15,Q39+R39,$M$15) -> 0 | V39: 17 | W39: 0.91 | X39: 0.91
A40: =VLOOKUP(D40,$A$7:$B$11,2) -> 0.0715 | B40: =A40/12 -> 0.0059583333 | C40: =INT((D40+11)/12) -> 2 | D40: 18 | E40: =IF(E39<H39,0,E39-G39) -> 0 | F40: =ROUND(E40*$B40,2) -> 0 | G40: =IF(E40<H40,E40,H40-F40) -> 0 | H40: =IF(E40<$M$4,E40+F40,$M$4) -> 0 | I40: =IF(I39<L39,0,I39-K39) -> 0 | J40: =ROUND(I40*$B40,2) -> 0 | K40: =IF(I40<L40,I40,L40-J40) -> 0 | L40: =IF(I40<$M$5,I40+J40,$M$5) -> 0 | M40: =IF(M39<P39,0,M39-O39) -> 0 | N40: =ROUND(M40*$B40,2) -> 0 | O40: =IF(M40<P40,M40,P40-N40) -> 0 | P40: =IF(M40<$M$9,M40+N40,$M$9) -> 0 | Q40: =IF(Q39<T39,0,Q39-S39) -> 0 | R40: =ROUND(Q40*$B40,2) -> 0 | S40: =IF(Q40<T40,Q40,T40-R40) -> 0 | T40: =IF(Q40<$M$15,Q40+R40,$M$15) -> 0 | V40: 18 | W40: 0.9 | X40: 0.91
A41: =VLOOKUP(D41,$A$7:$B$11,2) -> 0.0715 | B41: =A41/12 -> 0.0059583333 | C41: =INT((D41+11)/12) -> 2 | D41: 19 | E41: =IF(E40<H40,0,E40-G40) -> 0 | F41: =ROUND(E41*$B41,2) -> 0 | G41: =IF(E41<H41,E41,H41-F41) -> 0 | H41: =IF(E41<$M$4,E41+F41,$M$4) -> 0 | I41: =IF(I40<L40,0,I40-K40) -> 0 | J41: =ROUND(I41*$B41,2) -> 0 | K41: =IF(I41<L41,I41,L41-J41) -> 0 | L41: =IF(I41<$M$5,I41+J41,$M$5) -> 0 | M41: =IF(M40<P40,0,M40-O40) -> 0 | N41: =ROUND(M41*$B41,2) -> 0 | O41: =IF(M41<P41,M41,P41-N41) -> 0 | P41: =IF(M41<$M$9,M41+N41,$M$9) -> 0 | Q41: =IF(Q40<T40,0,Q40-S40) -> 0 | R41: =ROUND(Q41*$B41,2) -> 0 | S41: =IF(Q41<T41,Q41,T41-R41) -> 0 | T41: =IF(Q41<$M$15,Q41+R41,$M$15) -> 0 | V41: 19 | W41: 0.9 | X41: 0.9
A42: =VLOOKUP(D42,$A$7:$B$11,2) -> 0.0715 | B42: =A42/12 -> 0.0059583333 | C42: =INT((D42+11)/12) -> 2 | D42: 20 | E42: =IF(E41<H41,0,E41-G41) -> 0 | F42: =ROUND(E42*$B42,2) -> 0 | G42: =IF(E42<H42,E42,H42-F42) -> 0 | H42: =IF(E42<$M$4,E42+F42,$M$4) -> 0 | I42: =IF(I41<L41,0,I41-K41) -> 0 | J42: =ROUND(I42*$B42,2) -> 0 | K42: =IF(I42<L42,I42,L42-J42) -> 0 | L42: =IF(I42<$M$5,I42+J42,$M$5) -> 0 | M42: =IF(M41<P41,0,M41-O41) -> 0 | N42: =ROUND(M42*$B42,2) -> 0 | O42: =IF(M42<P42,M42,P42-N42) -> 0 | P42: =IF(M42<$M$9,M42+N42,$M$9) -> 0 | Q42: =IF(Q41<T41,0,Q41-S41) -> 0 | R42: =ROUND(Q42*$B42,2) -> 0 | S42: =IF(Q42<T42,Q42,T42-R42) -> 0 | T42: =IF(Q42<$M$15,Q42+R42,$M$15) -> 0 | V42: 20 | W42: 0.9 | X42: 0.9
A43: =VLOOKUP(D43,$A$7:$B$11,2) -> 0.0715 | B43: =A43/12 -> 0.0059583333 | C43: =INT((D43+11)/12) -> 2 | D43: 21 | E43: =IF(E42<H42,0,E42-G42) -> 0 | F43: =ROUND(E43*$B43,2) -> 0 | G43: =IF(E43<H43,E43,H43-F43) -> 0 | H43: =IF(E43<$M$4,E43+F43,$M$4) -> 0 | I43: =IF(I42<L42,0,I42-K42) -> 0 | J43: =ROUND(I43*$B43,2) -> 0 | K43: =IF(I43<L43,I43,L43-J43) -> 0 | L43: =IF(I43<$M$5,I43+J43,$M$5) -> 0 | M43: =IF(M42<P42,0,M42-O42) -> 0 | N43: =ROUND(M43*$B43,2) -> 0 | O43: =IF(M43<P43,M43,P43-N43) -> 0 | P43: =IF(M43<$M$9,M43+N43,$M$9) -> 0 | Q43: =IF(Q42<T42,0,Q42-S42) -> 0 | R43: =ROUND(Q43*$B43,2) -> 0 | S43: =IF(Q43<T43,Q43,T43-R43) -> 0 | T43: =IF(Q43<$M$15,Q43+R43,$M$15) -> 0 | V43: 21 | W43: 0.9 | X43: 0.9
A44: =VLOOKUP(D44,$A$7:$B$11,2) -> 0.0715 | B44: =A44/12 -> 0.0059583333 | C44: =INT((D44+11)/12) -> 2 | D44: 22 | E44: =IF(E43<H43,0,E43-G43) -> 0 | F44: =ROUND(E44*$B44,2) -> 0 | G44: =IF(E44<H44,E44,H44-F44) -> 0 | H44: =IF(E44<$M$4,E44+F44,$M$4) -> 0 | I44: =IF(I43<L43,0,I43-K43) -> 0 | J44: =ROUND(I44*$B44,2) -> 0 | K44: =IF(I44<L44,I44,L44-J44) -> 0 | L44: =IF(I44<$M$5,I44+J44,$M$5) -> 0 | M44: =IF(M43<P43,0,M43-O43) -> 0 | N44: =ROUND(M44*$B44,2) -> 0 | O44: =IF(M44<P44,M44,P44-N44) -> 0 | P44: =IF(M44<$M$9,M44+N44,$M$9) -> 0 | Q44: =IF(Q43<T43,0,Q43-S43) -> 0 | R44: =ROUND(Q44*$B44,2) -> 0 | S44: =IF(Q44<T44,Q44,T44-R44) -> 0 | T44: =IF(Q44<$M$15,Q44+R44,$M$15) -> 0 | V44: 22 | W44: 0.9 | X44: 0.9
A45: =VLOOKUP(D45,$A$7:$B$11,2) -> 0.0715 | B45: =A45/12 -> 0.0059583333 | C45: =INT((D45+11)/12) -> 2 | D45: 23 | E45: =IF(E44<H44,0,E44-G44) -> 0 | F45: =ROUND(E45*$B45,2) -> 0 | G45: =IF(E45<H45,E45,H45-F45) -> 0 | H45: =IF(E45<$M$4,E45+F45,$M$4) -> 0 | I45: =IF(I44<L44,0,I44-K44) -> 0 | J45: =ROUND(I45*$B45,2) -> 0 | K45: =IF(I45<L45,I45,L45-J45) -> 0 | L45: =IF(I45<$M$5,I45+J45,$M$5) -> 0 | M45: =IF(M44<P44,0,M44-O44) -> 0 | N45: =ROUND(M45*$B45,2) -> 0 | O45: =IF(M45<P45,M45,P45-N45) -> 0 | P45: =IF(M45<$M$9,M45+N45,$M$9) -> 0 | Q45: =IF(Q44<T44,0,Q44-S44) -> 0 | R45: =ROUND(Q45*$B45,2) -> 0 | S45: =IF(Q45<T45,Q45,T45-R45) -> 0 | T45: =IF(Q45<$M$15,Q45+R45,$M$15) -> 0 | V45: 23 | W45: 0.9 | X45: 0.9
A46: =VLOOKUP(D46,$A$7:$B$11,2) -> 0.0715 | B46: =A46/12 -> 0.0059583333 | C46: =INT((D46+11)/12) -> 2 | D46: 24 | E46: =IF(E45<H45,0,E45-G45) -> 0 | F46: =ROUND(E46*$B46,2) -> 0 | G46: =IF(E46<H46,E46,H46-F46) -> 0 | H46: =IF(E46<$M$4,E46+F46,$M$4) -> 0 | I46: =IF(I45<L45,0,I45-K45) -> 0 | J46: =ROUND(I46*$B46,2) -> 0 | K46: =IF(I46<L46,I46,L46-J46) -> 0 | L46: =IF(I46<$M$5,I46+J46,$M$5) -> 0 | M46: =IF(M45<P45,0,M45-O45) -> 0 | N46: =ROUND(M46*$B46,2) -> 0 | O46: =IF(M46<P46,M46,P46-N46) -> 0 | P46: =IF(M46<$M$9,M46+N46,$M$9) -> 0 | Q46: =IF(Q45<T45,0,Q45-S45) -> 0 | R46: =ROUND(Q46*$B46,2) -> 0 | S46: =IF(Q46<T46,Q46,T46-R46) -> 0 | T46: =IF(Q46<$M$15,Q46+R46,$M$15) -> 0 | V46: 24 | W46: 0.89 | X46: 0.9
A47: =VLOOKUP(D47,$A$7:$B$11,2) -> 0.0715 | B47: =A47/12 -> 0.0059583333 | C47: =INT((D47+11)/12) -> 3 | D47: 25 | E47: =IF(E46<H46,0,E46-G46) -> 0 | F47: =ROUND(E47*$B47,2) -> 0 | G47: =IF(E47<H47,E47,H47-F47) -> 0 | H47: =IF(E47<$M$4,E47+F47,$M$4) -> 0 | I47: =IF(I46<L46,0,I46-K46) -> 0 | J47: =ROUND(I47*$B47,2) -> 0 | K47: =IF(I47<L47,I47,L47-J47) -> 0 | L47: =IF(I47<$M$5,I47+J47,$M$5) -> 0 | M47: =IF(M46<P46,0,M46-O46) -> 0 | N47: =ROUND(M47*$B47,2) -> 0 | O47: =IF(M47<P47,M47,P47-N47) -> 0 | P47: =IF(M47<$M$10,M47+N47,$M$10) -> 0 | Q47: =IF(Q46<T46,0,Q46-S46) -> 0 | R47: =ROUND(Q47*$B47,2) -> 0 | S47: =IF(Q47<T47,Q47,T47-R47) -> 0 | T47: =IF(Q47<$M$15,Q47+R47,$M$15) -> 0 | V47: 25 | W47: 0.89 | X47: 0.89
A48: =VLOOKUP(D48,$A$7:$B$11,2) -> 0.0715 | B48: =A48/12 -> 0.0059583333 | C48: =INT((D48+11)/12) -> 3 | D48: 26 | E48: =IF(E47<H47,0,E47-G47) -> 0 | F48: =ROUND(E48*$B48,2) -> 0 | G48: =IF(E48<H48,E48,H48-F48) -> 0 | H48: =IF(E48<$M$4,E48+F48,$M$4) -> 0 | I48: =IF(I47<L47,0,I47-K47) -> 0 | J48: =ROUND(I48*$B48,2) -> 0 | K48: =IF(I48<L48,I48,L48-J48) -> 0 | L48: =IF(I48<$M$5,I48+J48,$M$5) -> 0 | M48: =IF(M47<P47,0,M47-O47) -> 0 | N48: =ROUND(M48*$B48,2) -> 0 | O48: =IF(M48<P48,M48,P48-N48) -> 0 | P48: =IF(M48<$M$10,M48+N48,$M$10) -> 0 | Q48: =IF(Q47<T47,0,Q47-S47) -> 0 | R48: =ROUND(Q48*$B48,2) -> 0 | S48: =IF(Q48<T48,Q48,T48-R48) -> 0 | T48: =IF(Q48<$M$15,Q48+R48,$M$15) -> 0 | V48: 26 | W48: 0.89 | X48: 0.89
A49: =VLOOKUP(D49,$A$7:$B$11,2) -> 0.0715 | B49: =A49/12 -> 0.0059583333 | C49: =INT((D49+11)/12) -> 3 | D49: 27 | E49: =IF(E48<H48,0,E48-G48) -> 0 | F49: =ROUND(E49*$B49,2) -> 0 | G49: =IF(E49<H49,E49,H49-F49) -> 0 | H49: =IF(E49<$M$4,E49+F49,$M$4) -> 0 | I49: =IF(I48<L48,0,I48-K48) -> 0 | J49: =ROUND(I49*$B49,2) -> 0 | K49: =IF(I49<L49,I49,L49-J49) -> 0 | L49: =IF(I49<$M$5,I49+J49,$M$5) -> 0 | M49: =IF(M48<P48,0,M48-O48) -> 0 | N49: =ROUND(M49*$B49,2) -> 0 | O49: =IF(M49<P49,M49,P49-N49) -> 0 | P49: =IF(M49<$M$10,M49+N49,$M$10) -> 0 | Q49: =IF(Q48<T48,0,Q48-S48) -> 0 | R49: =ROUND(Q49*$B49,2) -> 0 | S49: =IF(Q49<T49,Q49,T49-R49) -> 0 | T49: =IF(Q49<$M$15,Q49+R49,$M$15) -> 0 | V49: 27 | W49: 0.89 | X49: 0.89
A50: =VLOOKUP(D50,$A$7:$B$11,2) -> 0.0715 | B50: =A50/12 -> 0.0059583333 | C50: =INT((D50+11)/12) -> 3 | D50: 28 | E50: =IF(E49<H49,0,E49-G49) -> 0 | F50: =ROUND(E50*$B50,2) -> 0 | G50: =IF(E50<H50,E50,H50-F50) -> 0 | H50: =IF(E50<$M$4,E50+F50,$M$4) -> 0 | I50: =IF(I49<L49,0,I49-K49) -> 0 | J50: =ROUND(I50*$B50,2) -> 0 | K50: =IF(I50<L50,I50,L50-J50) -> 0 | L50: =IF(I50<$M$5,I50+J50,$M$5) -> 0 | M50: =IF(M49<P49,0,M49-O49) -> 0 | N50: =ROUND(M50*$B50,2) -> 0 | O50: =IF(M50<P50,M50,P50-N50) -> 0 | P50: =IF(M50<$M$10,M50+N50,$M$10) -> 0 | Q50: =IF(Q49<T49,0,Q49-S49) -> 0 | R50: =ROUND(Q50*$B50,2) -> 0 | S50: =IF(Q50<T50,Q50,T50-R50) -> 0 | T50: =IF(Q50<$M$15,Q50+R50,$M$15) -> 0 | V50: 28 | W50: 0.89 | X50: 0.89
A51: =VLOOKUP(D51,$A$7:$B$11,2) -> 0.0715 | B51: =A51/12 -> 0.0059583333 | C51: =INT((D51+11)/12) -> 3 | D51: 29 | E51: =IF(E50<H50,0,E50-G50) -> 0 | F51: =ROUND(E51*$B51,2) -> 0 | G51: =IF(E51<H51,E51,H51-F51) -> 0 | H51: =IF(E51<$M$4,E51+F51,$M$4) -> 0 | I51: =IF(I50<L50,0,I50-K50) -> 0 | J51: =ROUND(I51*$B51,2) -> 0 | K51: =IF(I51<L51,I51,L51-J51) -> 0 | L51: =IF(I51<$M$5,I51+J51,$M$5) -> 0 | M51: =IF(M50<P50,0,M50-O50) -> 0 | N51: =ROUND(M51*$B51,2) -> 0 | O51: =IF(M51<P51,M51,P51-N51) -> 0 | P51: =IF(M51<$M$10,M51+N51,$M$10) -> 0 | Q51: =IF(Q50<T50,0,Q50-S50) -> 0 | R51: =ROUND(Q51*$B51,2) -> 0 | S51: =IF(Q51<T51,Q51,T51-R51) -> 0 | T51: =IF(Q51<$M$15,Q51+R51,$M$15) -> 0 | V51: 29 | W51: 0.89 | X51: 0.89
A52: =VLOOKUP(D52,$A$7:$B$11,2) -> 0.0715 | B52: =A52/12 -> 0.0059583333 | C52: =INT((D52+11)/12) -> 3 | D52: 30 | E52: =IF(E51<H51,0,E51-G51) -> 0 | F52: =ROUND(E52*$B52,2) -> 0 | G52: =IF(E52<H52,E52,H52-F52) -> 0 | H52: =IF(E52<$M$4,E52+F52,$M$4) -> 0 | I52: =IF(I51<L51,0,I51-K51) -> 0 | J52: =ROUND(I52*$B52,2) -> 0 | K52: =IF(I52<L52,I52,L52-J52) -> 0 | L52: =IF(I52<$M$5,I52+J52,$M$5) -> 0 | M52: =IF(M51<P51,0,M51-O51) -> 0 | N52: =ROUND(M52*$B52,2) -> 0 | O52: =IF(M52<P52,M52,P52-N52) -> 0 | P52: =IF(M52<$M$10,M52+N52,$M$10) -> 0 | Q52: =IF(Q51<T51,0,Q51-S51) -> 0 | R52: =ROUND(Q52*$B52,2) -> 0 | S52: =IF(Q52<T52,Q52,T52-R52) -> 0 | T52: =IF(Q52<$M$15,Q52+R52,$M$15) -> 0 | V52: 30 | W52: 0.89 | X52: 0.89
A53: =VLOOKUP(D53,$A$7:$B$11,2) -> 0.0715 | B53: =A53/12 -> 0.0059583333 | C53: =INT((D53+11)/12) -> 3 | D53: 31 | E53: =IF(E52<H52,0,E52-G52) -> 0 | F53: =ROUND(E53*$B53,2) -> 0 | G53: =IF(E53<H53,E53,H53-F53) -> 0 | H53: =IF(E53<$M$4,E53+F53,$M$4) -> 0 | I53: =IF(I52<L52,0,I52-K52) -> 0 | J53: =ROUND(I53*$B53,2) -> 0 | K53: =IF(I53<L53,I53,L53-J53) -> 0 | L53: =IF(I53<$M$5,I53+J53,$M$5) -> 0 | M53: =IF(M52<P52,0,M52-O52) -> 0 | N53: =ROUND(M53*$B53,2) -> 0 | O53: =IF(M53<P53,M53,P53-N53) -> 0 | P53: =IF(M53<$M$10,M53+N53,$M$10) -> 0 | Q53: =IF(Q52<T52,0,Q52-S52) -> 0 | R53: =ROUND(Q53*$B53,2) -> 0 | S53: =IF(Q53<T53,Q53,T53-R53) -> 0 | T53: =IF(Q53<$M$15,Q53+R53,$M$15) -> 0
A54: =VLOOKUP(D54,$A$7:$B$11,2) -> 0.0715 | B54: =A54/12 -> 0.0059583333 | C54: =INT((D54+11)/12) -> 3 | D54: 32 | E54: =IF(E53<H53,0,E53-G53) -> 0 | F54: =ROUND(E54*$B54,2) -> 0 | G54: =IF(E54<H54,E54,H54-F54) -> 0 | H54: =IF(E54<$M$4,E54+F54,$M$4) -> 0 | I54: =IF(I53<L53,0,I53-K53) -> 0 | J54: =ROUND(I54*$B54,2) -> 0 | K54: =IF(I54<L54,I54,L54-J54) -> 0 | L54: =IF(I54<$M$5,I54+J54,$M$5) -> 0 | M54: =IF(M53<P53,0,M53-O53) -> 0 | N54: =ROUND(M54*$B54,2) -> 0 | O54: =IF(M54<P54,M54,P54-N54) -> 0 | P54: =IF(M54<$M$10,M54+N54,$M$10) -> 0 | Q54: =IF(Q53<T53,0,Q53-S53) -> 0 | R54: =ROUND(Q54*$B54,2) -> 0 | S54: =IF(Q54<T54,Q54,T54-R54) -> 0 | T54: =IF(Q54<$M$15,Q54+R54,$M$15) -> 0
A55: =VLOOKUP(D55,$A$7:$B$11,2) -> 0.0715 | B55: =A55/12 -> 0.0059583333 | C55: =INT((D55+11)/12) -> 3 | D55: 33 | E55: =IF(E54<H54,0,E54-G54) -> 0 | F55: =ROUND(E55*$B55,2) -> 0 | G55: =IF(E55<H55,E55,H55-F55) -> 0 | H55: =IF(E55<$M$4,E55+F55,$M$4) -> 0 | I55: =IF(I54<L54,0,I54-K54) -> 0 | J55: =ROUND(I55*$B55,2) -> 0 | K55: =IF(I55<L55,I55,L55-J55) -> 0 | L55: =IF(I55<$M$5,I55+J55,$M$5) -> 0 | M55: =IF(M54<P54,0,M54-O54) -> 0 | N55: =ROUND(M55*$B55,2) -> 0 | O55: =IF(M55<P55,M55,P55-N55) -> 0 | P55: =IF(M55<$M$10,M55+N55,$M$10) -> 0 | Q55: =IF(Q54<T54,0,Q54-S54) -> 0 | R55: =ROUND(Q55*$B55,2) -> 0 | S55: =IF(Q55<T55,Q55,T55-R55) -> 0 | T55: =IF(Q55<$M$15,Q55+R55,$M$15) -> 0
A56: =VLOOKUP(D56,$A$7:$B$11,2) -> 0.0715 | B56: =A56/12 -> 0.0059583333 | C56: =INT((D56+11)/12) -> 3 | D56: 34 | E56: =IF(E55<H55,0,E55-G55) -> 0 | F56: =ROUND(E56*$B56,2) -> 0 | G56: =IF(E56<H56,E56,H56-F56) -> 0 | H56: =IF(E56<$M$4,E56+F56,$M$4) -> 0 | I56: =IF(I55<L55,0,I55-K55) -> 0 | J56: =ROUND(I56*$B56,2) -> 0 | K56: =IF(I56<L56,I56,L56-J56) -> 0 | L56: =IF(I56<$M$5,I56+J56,$M$5) -> 0 | M56: =IF(M55<P55,0,M55-O55) -> 0 | N56: =ROUND(M56*$B56,2) -> 0 | O56: =IF(M56<P56,M56,P56-N56) -> 0 | P56: =IF(M56<$M$10,M56+N56,$M$10) -> 0 | Q56: =IF(Q55<T55,0,Q55-S55) -> 0 | R56: =ROUND(Q56*$B56,2) -> 0 | S56: =IF(Q56<T56,Q56,T56-R56) -> 0 | T56: =IF(Q56<$M$15,Q56+R56,$M$15) -> 0
A57: =VLOOKUP(D57,$A$7:$B$11,2) -> 0.0715 | B57: =A57/12 -> 0.0059583333 | C57: =INT((D57+11)/12) -> 3 | D57: 35 | E57: =IF(E56<H56,0,E56-G56) -> 0 | F57: =ROUND(E57*$B57,2) -> 0 | G57: =IF(E57<H57,E57,H57-F57) -> 0 | H57: =IF(E57<$M$4,E57+F57,$M$4) -> 0 | I57: =IF(I56<L56,0,I56-K56) -> 0 | J57: =ROUND(I57*$B57,2) -> 0 | K57: =IF(I57<L57,I57,L57-J57) -> 0 | L57: =IF(I57<$M$5,I57+J57,$M$5) -> 0 | M57: =IF(M56<P56,0,M56-O56) -> 0 | N57: =ROUND(M57*$B57,2) -> 0 | O57: =IF(M57<P57,M57,P57-N57) -> 0 | P57: =IF(M57<$M$10,M57+N57,$M$10) -> 0 | Q57: =IF(Q56<T56,0,Q56-S56) -> 0 | R57: =ROUND(Q57*$B57,2) -> 0 | S57: =IF(Q57<T57,Q57,T57-R57) -> 0 | T57: =IF(Q57<$M$15,Q57+R57,$M$15) -> 0
A58: =VLOOKUP(D58,$A$7:$B$11,2) -> 0.0715 | B58: =A58/12 -> 0.0059583333 | C58: =INT((D58+11)/12) -> 3 | D58: 36 | E58: =IF(E57<H57,0,E57-G57) -> 0 | F58: =ROUND(E58*$B58,2) -> 0 | G58: =IF(E58<H58,E58,H58-F58) -> 0 | H58: =IF(E58<$M$4,E58+F58,$M$4) -> 0 | I58: =IF(I57<L57,0,I57-K57) -> 0 | J58: =ROUND(I58*$B58,2) -> 0 | K58: =IF(I58<L58,I58,L58-J58) -> 0 | L58: =IF(I58<$M$5,I58+J58,$M$5) -> 0 | M58: =IF(M57<P57,0,M57-O57) -> 0 | N58: =ROUND(M58*$B58,2) -> 0 | O58: =IF(M58<P58,M58,P58-N58) -> 0 | P58: =IF(M58<$M$10,M58+N58,$M$10) -> 0 | Q58: =IF(Q57<T57,0,Q57-S57) -> 0 | R58: =ROUND(Q58*$B58,2) -> 0 | S58: =IF(Q58<T58,Q58,T58-R58) -> 0 | T58: =IF(Q58<$M$15,Q58+R58,$M$15) -> 0
A59: =VLOOKUP(D59,$A$7:$B$11,2) -> 0.0715 | B59: =A59/12 -> 0.0059583333 | C59: =INT((D59+11)/12) -> 4 | D59: 37 | E59: =IF(E58<H58,0,E58-G58) -> 0 | F59: =ROUND(E59*$B59,2) -> 0 | G59: =IF(E59<H59,E59,H59-F59) -> 0 | H59: =IF(E59<$M$4,E59+F59,$M$4) -> 0 | I59: =IF(I58<L58,0,I58-K58) -> 0 | J59: =ROUND(I59*$B59,2) -> 0 | K59: =IF(I59<L59,I59,L59-J59) -> 0 | L59: =IF(I59<$M$5,I59+J59,$M$5) -> 0 | M59: =IF(M58<P58,0,M58-O58) -> 0 | N59: =ROUND(M59*$B59,2) -> 0 | O59: =IF(M59<P59,M59,P59-N59) -> 0 | P59: =IF(M59<$M$10,M59+N59,$M$10) -> 0 | Q59: =IF(Q58<T58,0,Q58-S58) -> 0 | R59: =ROUND(Q59*$B59,2) -> 0 | S59: =IF(Q59<T59,Q59,T59-R59) -> 0 | T59: =IF(Q59<$M$16,Q59+R59,$M$16) -> 0
A60: =VLOOKUP(D60,$A$7:$B$11,2) -> 0.0715 | B60: =A60/12 -> 0.0059583333 | C60: =INT((D60+11)/12) -> 4 | D60: 38 | E60: =IF(E59<H59,0,E59-G59) -> 0 | F60: =ROUND(E60*$B60,2) -> 0 | G60: =IF(E60<H60,E60,H60-F60) -> 0 | H60: =IF(E60<$M$4,E60+F60,$M$4) -> 0 | I60: =IF(I59<L59,0,I59-K59) -> 0 | J60: =ROUND(I60*$B60,2) -> 0 | K60: =IF(I60<L60,I60,L60-J60) -> 0 | L60: =IF(I60<$M$5,I60+J60,$M$5) -> 0 | M60: =IF(M59<P59,0,M59-O59) -> 0 | N60: =ROUND(M60*$B60,2) -> 0 | O60: =IF(M60<P60,M60,P60-N60) -> 0 | P60: =IF(M60<$M$10,M60+N60,$M$10) -> 0 | Q60: =IF(Q59<T59,0,Q59-S59) -> 0 | R60: =ROUND(Q60*$B60,2) -> 0 | S60: =IF(Q60<T60,Q60,T60-R60) -> 0 | T60: =IF(Q60<$M$16,Q60+R60,$M$16) -> 0
A61: =VLOOKUP(D61,$A$7:$B$11,2) -> 0.0715 | B61: =A61/12 -> 0.0059583333 | C61: =INT((D61+11)/12) -> 4 | D61: 39 | E61: =IF(E60<H60,0,E60-G60) -> 0 | F61: =ROUND(E61*$B61,2) -> 0 | G61: =IF(E61<H61,E61,H61-F61) -> 0 | H61: =IF(E61<$M$4,E61+F61,$M$4) -> 0 | I61: =IF(I60<L60,0,I60-K60) -> 0 | J61: =ROUND(I61*$B61,2) -> 0 | K61: =IF(I61<L61,I61,L61-J61) -> 0 | L61: =IF(I61<$M$5,I61+J61,$M$5) -> 0 | M61: =IF(M60<P60,0,M60-O60) -> 0 | N61: =ROUND(M61*$B61,2) -> 0 | O61: =IF(M61<P61,M61,P61-N61) -> 0 | P61: =IF(M61<$M$10,M61+N61,$M$10) -> 0 | Q61: =IF(Q60<T60,0,Q60-S60) -> 0 | R61: =ROUND(Q61*$B61,2) -> 0 | S61: =IF(Q61<T61,Q61,T61-R61) -> 0 | T61: =IF(Q61<$M$16,Q61+R61,$M$16) -> 0
A62: =VLOOKUP(D62,$A$7:$B$11,2) -> 0.0715 | B62: =A62/12 -> 0.0059583333 | C62: =INT((D62+11)/12) -> 4 | D62: 40 | E62: =IF(E61<H61,0,E61-G61) -> 0 | F62: =ROUND(E62*$B62,2) -> 0 | G62: =IF(E62<H62,E62,H62-F62) -> 0 | H62: =IF(E62<$M$4,E62+F62,$M$4) -> 0 | I62: =IF(I61<L61,0,I61-K61) -> 0 | J62: =ROUND(I62*$B62,2) -> 0 | K62: =IF(I62<L62,I62,L62-J62) -> 0 | L62: =IF(I62<$M$5,I62+J62,$M$5) -> 0 | M62: =IF(M61<P61,0,M61-O61) -> 0 | N62: =ROUND(M62*$B62,2) -> 0 | O62: =IF(M62<P62,M62,P62-N62) -> 0 | P62: =IF(M62<$M$10,M62+N62,$M$10) -> 0 | Q62: =IF(Q61<T61,0,Q61-S61) -> 0 | R62: =ROUND(Q62*$B62,2) -> 0 | S62: =IF(Q62<T62,Q62,T62-R62) -> 0 | T62: =IF(Q62<$M$16,Q62+R62,$M$16) -> 0
A63: =VLOOKUP(D63,$A$7:$B$11,2) -> 0.0715 | B63: =A63/12 -> 0.0059583333 | C63: =INT((D63+11)/12) -> 4 | D63: 41 | E63: =IF(E62<H62,0,E62-G62) -> 0 | F63: =ROUND(E63*$B63,2) -> 0 | G63: =IF(E63<H63,E63,H63-F63) -> 0 | H63: =IF(E63<$M$4,E63+F63,$M$4) -> 0 | I63: =IF(I62<L62,0,I62-K62) -> 0 | J63: =ROUND(I63*$B63,2) -> 0 | K63: =IF(I63<L63,I63,L63-J63) -> 0 | L63: =IF(I63<$M$5,I63+J63,$M$5) -> 0 | M63: =IF(M62<P62,0,M62-O62) -> 0 | N63: =ROUND(M63*$B63,2) -> 0 | O63: =IF(M63<P63,M63,P63-N63) -> 0 | P63: =IF(M63<$M$10,M63+N63,$M$10) -> 0 | Q63: =IF(Q62<T62,0,Q62-S62) -> 0 | R63: =ROUND(Q63*$B63,2) -> 0 | S63: =IF(Q63<T63,Q63,T63-R63) -> 0 | T63: =IF(Q63<$M$16,Q63+R63,$M$16) -> 0
A64: =VLOOKUP(D64,$A$7:$B$11,2) -> 0.0715 | B64: =A64/12 -> 0.0059583333 | C64: =INT((D64+11)/12) -> 4 | D64: 42 | E64: =IF(E63<H63,0,E63-G63) -> 0 | F64: =ROUND(E64*$B64,2) -> 0 | G64: =IF(E64<H64,E64,H64-F64) -> 0 | H64: =IF(E64<$M$4,E64+F64,$M$4) -> 0 | I64: =IF(I63<L63,0,I63-K63) -> 0 | J64: =ROUND(I64*$B64,2) -> 0 | K64: =IF(I64<L64,I64,L64-J64) -> 0 | L64: =IF(I64<$M$5,I64+J64,$M$5) -> 0 | M64: =IF(M63<P63,0,M63-O63) -> 0 | N64: =ROUND(M64*$B64,2) -> 0 | O64: =IF(M64<P64,M64,P64-N64) -> 0 | P64: =IF(M64<$M$10,M64+N64,$M$10) -> 0 | Q64: =IF(Q63<T63,0,Q63-S63) -> 0 | R64: =ROUND(Q64*$B64,2) -> 0 | S64: =IF(Q64<T64,Q64,T64-R64) -> 0 | T64: =IF(Q64<$M$16,Q64+R64,$M$16) -> 0
A65: =VLOOKUP(D65,$A$7:$B$11,2) -> 0.0715 | B65: =A65/12 -> 0.0059583333 | C65: =INT((D65+11)/12) -> 4 | D65: 43 | E65: =IF(E64<H64,0,E64-G64) -> 0 | F65: =ROUND(E65*$B65,2) -> 0 | G65: =IF(E65<H65,E65,H65-F65) -> 0 | H65: =IF(E65<$M$4,E65+F65,$M$4) -> 0 | I65: =IF(I64<L64,0,I64-K64) -> 0 | J65: =ROUND(I65*$B65,2) -> 0 | K65: =IF(I65<L65,I65,L65-J65) -> 0 | L65: =IF(I65<$M$5,I65+J65,$M$5) -> 0 | M65: =IF(M64<P64,0,M64-O64) -> 0 | N65: =ROUND(M65*$B65,2) -> 0 | O65: =IF(M65<P65,M65,P65-N65) -> 0 | P65: =IF(M65<$M$10,M65+N65,$M$10) -> 0 | Q65: =IF(Q64<T64,0,Q64-S64) -> 0 | R65: =ROUND(Q65*$B65,2) -> 0 | S65: =IF(Q65<T65,Q65,T65-R65) -> 0 | T65: =IF(Q65<$M$16,Q65+R65,$M$16) -> 0
A66: =VLOOKUP(D66,$A$7:$B$11,2) -> 0.0715 | B66: =A66/12 -> 0.0059583333 | C66: =INT((D66+11)/12) -> 4 | D66: 44 | E66: =IF(E65<H65,0,E65-G65) -> 0 | F66: =ROUND(E66*$B66,2) -> 0 | G66: =IF(E66<H66,E66,H66-F66) -> 0 | H66: =IF(E66<$M$4,E66+F66,$M$4) -> 0 | I66: =IF(I65<L65,0,I65-K65) -> 0 | J66: =ROUND(I66*$B66,2) -> 0 | K66: =IF(I66<L66,I66,L66-J66) -> 0 | L66: =IF(I66<$M$5,I66+J66,$M$5) -> 0 | M66: =IF(M65<P65,0,M65-O65) -> 0 | N66: =ROUND(M66*$B66,2) -> 0 | O66: =IF(M66<P66,M66,P66-N66) -> 0 | P66: =IF(M66<$M$10,M66+N66,$M$10) -> 0 | Q66: =IF(Q65<T65,0,Q65-S65) -> 0 | R66: =ROUND(Q66*$B66,2) -> 0 | S66: =IF(Q66<T66,Q66,T66-R66) -> 0 | T66: =IF(Q66<$M$16,Q66+R66,$M$16) -> 0
A67: =VLOOKUP(D67,$A$7:$B$11,2) -> 0.0715 | B67: =A67/12 -> 0.0059583333 | C67: =INT((D67+11)/12) -> 4 | D67: 45 | E67: =IF(E66<H66,0,E66-G66) -> 0 | F67: =ROUND(E67*$B67,2) -> 0 | G67: =IF(E67<H67,E67,H67-F67) -> 0 | H67: =IF(E67<$M$4,E67+F67,$M$4) -> 0 | I67: =IF(I66<L66,0,I66-K66) -> 0 | J67: =ROUND(I67*$B67,2) -> 0 | K67: =IF(I67<L67,I67,L67-J67) -> 0 | L67: =IF(I67<$M$5,I67+J67,$M$5) -> 0 | M67: =IF(M66<P66,0,M66-O66) -> 0 | N67: =ROUND(M67*$B67,2) -> 0 | O67: =IF(M67<P67,M67,P67-N67) -> 0 | P67: =IF(M67<$M$10,M67+N67,$M$10) -> 0 | Q67: =IF(Q66<T66,0,Q66-S66) -> 0 | R67: =ROUND(Q67*$B67,2) -> 0 | S67: =IF(Q67<T67,Q67,T67-R67) -> 0 | T67: =IF(Q67<$M$16,Q67+R67,$M$16) -> 0
A68: =VLOOKUP(D68,$A$7:$B$11,2) -> 0.0715 | B68: =A68/12 -> 0.0059583333 | C68: =INT((D68+11)/12) -> 4 | D68: 46 | E68: =IF(E67<H67,0,E67-G67) -> 0 | F68: =ROUND(E68*$B68,2) -> 0 | G68: =IF(E68<H68,E68,H68-F68) -> 0 | H68: =IF(E68<$M$4,E68+F68,$M$4) -> 0 | I68: =IF(I67<L67,0,I67-K67) -> 0 | J68: =ROUND(I68*$B68,2) -> 0 | K68: =IF(I68<L68,I68,L68-J68) -> 0 | L68: =IF(I68<$M$5,I68+J68,$M$5) -> 0 | M68: =IF(M67<P67,0,M67-O67) -> 0 | N68: =ROUND(M68*$B68,2) -> 0 | O68: =IF(M68<P68,M68,P68-N68) -> 0 | P68: =IF(M68<$M$10,M68+N68,$M$10) -> 0 | Q68: =IF(Q67<T67,0,Q67-S67) -> 0 | R68: =ROUND(Q68*$B68,2) -> 0 | S68: =IF(Q68<T68,Q68,T68-R68) -> 0 | T68: =IF(Q68<$M$16,Q68+R68,$M$16) -> 0
A69: =VLOOKUP(D69,$A$7:$B$11,2) -> 0.0715 | B69: =A69/12 -> 0.0059583333 | C69: =INT((D69+11)/12) -> 4 | D69: 47 | E69: =IF(E68<H68,0,E68-G68) -> 0 | F69: =ROUND(E69*$B69,2) -> 0 | G69: =IF(E69<H69,E69,H69-F69) -> 0 | H69: =IF(E69<$M$4,E69+F69,$M$4) -> 0 | I69: =IF(I68<L68,0,I68-K68) -> 0 | J69: =ROUND(I69*$B69,2) -> 0 | K69: =IF(I69<L69,I69,L69-J69) -> 0 | L69: =IF(I69<$M$5,I69+J69,$M$5) -> 0 | M69: =IF(M68<P68,0,M68-O68) -> 0 | N69: =ROUND(M69*$B69,2) -> 0 | O69: =IF(M69<P69,M69,P69-N69) -> 0 | P69: =IF(M69<$M$10,M69+N69,$M$10) -> 0 | Q69: =IF(Q68<T68,0,Q68-S68) -> 0 | R69: =ROUND(Q69*$B69,2) -> 0 | S69: =IF(Q69<T69,Q69,T69-R69) -> 0 | T69: =IF(Q69<$M$16,Q69+R69,$M$16) -> 0
A70: =VLOOKUP(D70,$A$7:$B$11,2) -> 0.0715 | B70: =A70/12 -> 0.0059583333 | C70: =INT((D70+11)/12) -> 4 | D70: 48 | E70: =IF(E69<H69,0,E69-G69) -> 0 | F70: =ROUND(E70*$B70,2) -> 0 | G70: =IF(E70<H70,E70,H70-F70) -> 0 | H70: =IF(E70<$M$4,E70+F70,$M$4) -> 0 | I70: =IF(I69<L69,0,I69-K69) -> 0 | J70: =ROUND(I70*$B70,2) -> 0 | K70: =IF(I70<L70,I70,L70-J70) -> 0 | L70: =IF(I70<$M$5,I70+J70,$M$5) -> 0 | M70: =IF(M69<P69,0,M69-O69) -> 0 | N70: =ROUND(M70*$B70,2) -> 0 | O70: =IF(M70<P70,M70,P70-N70) -> 0 | P70: =IF(M70<$M$10,M70+N70,$M$10) -> 0 | Q70: =IF(Q69<T69,0,Q69-S69) -> 0 | R70: =ROUND(Q70*$B70,2) -> 0 | S70: =IF(Q70<T70,Q70,T70-R70) -> 0 | T70: =IF(Q70<$M$16,Q70+R70,$M$16) -> 0
A71: =VLOOKUP(D71,$A$7:$B$11,2) -> 0.0715 | B71: =A71/12 -> 0.0059583333 | C71: =INT((D71+11)/12) -> 5 | D71: 49 | E71: =IF(E70<H70,0,E70-G70) -> 0 | F71: =ROUND(E71*$B71,2) -> 0 | G71: =IF(E71<H71,E71,H71-F71) -> 0 | H71: =IF(E71<$M$4,E71+F71,$M$4) -> 0 | I71: =IF(I70<L70,0,I70-K70) -> 0 | J71: =ROUND(I71*$B71,2) -> 0 | K71: =IF(I71<L71,I71,L71-J71) -> 0 | L71: =IF(I71<$M$5,I71+J71,$M$5) -> 0 | M71: =IF(M70<P70,0,M70-O70) -> 0 | N71: =ROUND(M71*$B71,2) -> 0 | O71: =IF(M71<P71,M71,P71-N71) -> 0 | P71: =IF(M71<$M$10,M71+N71,$M$11) -> 0 | Q71: =IF(Q70<T70,0,Q70-S70) -> 0 | R71: =ROUND(Q71*$B71,2) -> 0 | S71: =IF(Q71<T71,Q71,T71-R71) -> 0 | T71: =IF(Q71<$M$16,Q71+R71,$M$16) -> 0
A72: =VLOOKUP(D72,$A$7:$B$11,2) -> 0.0715 | B72: =A72/12 -> 0.0059583333 | C72: =INT((D72+11)/12) -> 5 | D72: 50 | E72: =IF(E71<H71,0,E71-G71) -> 0 | F72: =ROUND(E72*$B72,2) -> 0 | G72: =IF(E72<H72,E72,H72-F72) -> 0 | H72: =IF(E72<$M$4,E72+F72,$M$4) -> 0 | I72: =IF(I71<L71,0,I71-K71) -> 0 | J72: =ROUND(I72*$B72,2) -> 0 | K72: =IF(I72<L72,I72,L72-J72) -> 0 | L72: =IF(I72<$M$5,I72+J72,$M$5) -> 0 | M72: =IF(M71<P71,0,M71-O71) -> 0 | N72: =ROUND(M72*$B72,2) -> 0 | O72: =IF(M72<P72,M72,P72-N72) -> 0 | P72: =IF(M72<$M$10,M72+N72,$M$11) -> 0 | Q72: =IF(Q71<T71,0,Q71-S71) -> 0 | R72: =ROUND(Q72*$B72,2) -> 0 | S72: =IF(Q72<T72,Q72,T72-R72) -> 0 | T72: =IF(Q72<$M$16,Q72+R72,$M$16) -> 0
A73: =VLOOKUP(D73,$A$7:$B$11,2) -> 0.0715 | B73: =A73/12 -> 0.0059583333 | C73: =INT((D73+11)/12) -> 5 | D73: 51 | E73: =IF(E72<H72,0,E72-G72) -> 0 | F73: =ROUND(E73*$B73,2) -> 0 | G73: =IF(E73<H73,E73,H73-F73) -> 0 | H73: =IF(E73<$M$4,E73+F73,$M$4) -> 0 | I73: =IF(I72<L72,0,I72-K72) -> 0 | J73: =ROUND(I73*$B73,2) -> 0 | K73: =IF(I73<L73,I73,L73-J73) -> 0 | L73: =IF(I73<$M$5,I73+J73,$M$5) -> 0 | M73: =IF(M72<P72,0,M72-O72) -> 0 | N73: =ROUND(M73*$B73,2) -> 0 | O73: =IF(M73<P73,M73,P73-N73) -> 0 | P73: =IF(M73<$M$10,M73+N73,$M$11) -> 0 | Q73: =IF(Q72<T72,0,Q72-S72) -> 0 | R73: =ROUND(Q73*$B73,2) -> 0 | S73: =IF(Q73<T73,Q73,T73-R73) -> 0 | T73: =IF(Q73<$M$16,Q73+R73,$M$16) -> 0
A74: =VLOOKUP(D74,$A$7:$B$11,2) -> 0.0715 | B74: =A74/12 -> 0.0059583333 | C74: =INT((D74+11)/12) -> 5 | D74: 52 | E74: =IF(E73<H73,0,E73-G73) -> 0 | F74: =ROUND(E74*$B74,2) -> 0 | G74: =IF(E74<H74,E74,H74-F74) -> 0 | H74: =IF(E74<$M$4,E74+F74,$M$4) -> 0 | I74: =IF(I73<L73,0,I73-K73) -> 0 | J74: =ROUND(I74*$B74,2) -> 0 | K74: =IF(I74<L74,I74,L74-J74) -> 0 | L74: =IF(I74<$M$5,I74+J74,$M$5) -> 0 | M74: =IF(M73<P73,0,M73-O73) -> 0 | N74: =ROUND(M74*$B74,2) -> 0 | O74: =IF(M74<P74,M74,P74-N74) -> 0 | P74: =IF(M74<$M$10,M74+N74,$M$11) -> 0 | Q74: =IF(Q73<T73,0,Q73-S73) -> 0 | R74: =ROUND(Q74*$B74,2) -> 0 | S74: =IF(Q74<T74,Q74,T74-R74) -> 0 | T74: =IF(Q74<$M$16,Q74+R74,$M$16) -> 0
A75: =VLOOKUP(D75,$A$7:$B$11,2) -> 0.0715 | B75: =A75/12 -> 0.0059583333 | C75: =INT((D75+11)/12) -> 5 | D75: 53 | E75: =IF(E74<H74,0,E74-G74) -> 0 | F75: =ROUND(E75*$B75,2) -> 0 | G75: =IF(E75<H75,E75,H75-F75) -> 0 | H75: =IF(E75<$M$4,E75+F75,$M$4) -> 0 | I75: =IF(I74<L74,0,I74-K74) -> 0 | J75: =ROUND(I75*$B75,2) -> 0 | K75: =IF(I75<L75,I75,L75-J75) -> 0 | L75: =IF(I75<$M$5,I75+J75,$M$5) -> 0 | M75: =IF(M74<P74,0,M74-O74) -> 0 | N75: =ROUND(M75*$B75,2) -> 0 | O75: =IF(M75<P75,M75,P75-N75) -> 0 | P75: =IF(M75<$M$10,M75+N75,$M$11) -> 0 | Q75: =IF(Q74<T74,0,Q74-S74) -> 0 | R75: =ROUND(Q75*$B75,2) -> 0 | S75: =IF(Q75<T75,Q75,T75-R75) -> 0 | T75: =IF(Q75<$M$16,Q75+R75,$M$16) -> 0
A76: =VLOOKUP(D76,$A$7:$B$11,2) -> 0.0715 | B76: =A76/12 -> 0.0059583333 | C76: =INT((D76+11)/12) -> 5 | D76: 54 | E76: =IF(E75<H75,0,E75-G75) -> 0 | F76: =ROUND(E76*$B76,2) -> 0 | G76: =IF(E76<H76,E76,H76-F76) -> 0 | H76: =IF(E76<$M$4,E76+F76,$M$4) -> 0 | I76: =IF(I75<L75,0,I75-K75) -> 0 | J76: =ROUND(I76*$B76,2) -> 0 | K76: =IF(I76<L76,I76,L76-J76) -> 0 | L76: =IF(I76<$M$5,I76+J76,$M$5) -> 0 | M76: =IF(M75<P75,0,M75-O75) -> 0 | N76: =ROUND(M76*$B76,2) -> 0 | O76: =IF(M76<P76,M76,P76-N76) -> 0 | P76: =IF(M76<$M$10,M76+N76,$M$11) -> 0 | Q76: =IF(Q75<T75,0,Q75-S75) -> 0 | R76: =ROUND(Q76*$B76,2) -> 0 | S76: =IF(Q76<T76,Q76,T76-R76) -> 0 | T76: =IF(Q76<$M$16,Q76+R76,$M$16) -> 0
A77: =VLOOKUP(D77,$A$7:$B$11,2) -> 0.0715 | B77: =A77/12 -> 0.0059583333 | C77: =INT((D77+11)/12) -> 5 | D77: 55 | E77: =IF(E76<H76,0,E76-G76) -> 0 | F77: =ROUND(E77*$B77,2) -> 0 | G77: =IF(E77<H77,E77,H77-F77) -> 0 | H77: =IF(E77<$M$4,E77+F77,$M$4) -> 0 | I77: =IF(I76<L76,0,I76-K76) -> 0 | J77: =ROUND(I77*$B77,2) -> 0 | K77: =IF(I77<L77,I77,L77-J77) -> 0 | L77: =IF(I77<$M$5,I77+J77,$M$5) -> 0 | M77: =IF(M76<P76,0,M76-O76) -> 0 | N77: =ROUND(M77*$B77,2) -> 0 | O77: =IF(M77<P77,M77,P77-N77) -> 0 | P77: =IF(M77<$M$10,M77+N77,$M$11) -> 0 | Q77: =IF(Q76<T76,0,Q76-S76) -> 0 | R77: =ROUND(Q77*$B77,2) -> 0 | S77: =IF(Q77<T77,Q77,T77-R77) -> 0 | T77: =IF(Q77<$M$16,Q77+R77,$M$16) -> 0
A78: =VLOOKUP(D78,$A$7:$B$11,2) -> 0.0715 | B78: =A78/12 -> 0.0059583333 | C78: =INT((D78+11)/12) -> 5 | D78: 56 | E78: =IF(E77<H77,0,E77-G77) -> 0 | F78: =ROUND(E78*$B78,2) -> 0 | G78: =IF(E78<H78,E78,H78-F78) -> 0 | H78: =IF(E78<$M$4,E78+F78,$M$4) -> 0 | I78: =IF(I77<L77,0,I77-K77) -> 0 | J78: =ROUND(I78*$B78,2) -> 0 | K78: =IF(I78<L78,I78,L78-J78) -> 0 | L78: =IF(I78<$M$5,I78+J78,$M$5) -> 0 | M78: =IF(M77<P77,0,M77-O77) -> 0 | N78: =ROUND(M78*$B78,2) -> 0 | O78: =IF(M78<P78,M78,P78-N78) -> 0 | P78: =IF(M78<$M$10,M78+N78,$M$11) -> 0 | Q78: =IF(Q77<T77,0,Q77-S77) -> 0 | R78: =ROUND(Q78*$B78,2) -> 0 | S78: =IF(Q78<T78,Q78,T78-R78) -> 0 | T78: =IF(Q78<$M$16,Q78+R78,$M$16) -> 0
A79: =VLOOKUP(D79,$A$7:$B$11,2) -> 0.0715 | B79: =A79/12 -> 0.0059583333 | C79: =INT((D79+11)/12) -> 5 | D79: 57 | E79: =IF(E78<H78,0,E78-G78) -> 0 | F79: =ROUND(E79*$B79,2) -> 0 | G79: =IF(E79<H79,E79,H79-F79) -> 0 | H79: =IF(E79<$M$4,E79+F79,$M$4) -> 0 | I79: =IF(I78<L78,0,I78-K78) -> 0 | J79: =ROUND(I79*$B79,2) -> 0 | K79: =IF(I79<L79,I79,L79-J79) -> 0 | L79: =IF(I79<$M$5,I79+J79,$M$5) -> 0 | M79: =IF(M78<P78,0,M78-O78) -> 0 | N79: =ROUND(M79*$B79,2) -> 0 | O79: =IF(M79<P79,M79,P79-N79) -> 0 | P79: =IF(M79<$M$10,M79+N79,$M$11) -> 0 | Q79: =IF(Q78<T78,0,Q78-S78) -> 0 | R79: =ROUND(Q79*$B79,2) -> 0 | S79: =IF(Q79<T79,Q79,T79-R79) -> 0 | T79: =IF(Q79<$M$16,Q79+R79,$M$16) -> 0
A80: =VLOOKUP(D80,$A$7:$B$11,2) -> 0.0715 | B80: =A80/12 -> 0.0059583333 | C80: =INT((D80+11)/12) -> 5 | D80: 58 | E80: =IF(E79<H79,0,E79-G79) -> 0 | F80: =ROUND(E80*$B80,2) -> 0 | G80: =IF(E80<H80,E80,H80-F80) -> 0 | H80: =IF(E80<$M$4,E80+F80,$M$4) -> 0 | I80: =IF(I79<L79,0,I79-K79) -> 0 | J80: =ROUND(I80*$B80,2) -> 0 | K80: =IF(I80<L80,I80,L80-J80) -> 0 | L80: =IF(I80<$M$5,I80+J80,$M$5) -> 0 | M80: =IF(M79<P79,0,M79-O79) -> 0 | N80: =ROUND(M80*$B80,2) -> 0 | O80: =IF(M80<P80,M80,P80-N80) -> 0 | P80: =IF(M80<$M$10,M80+N80,$M$11) -> 0 | Q80: =IF(Q79<T79,0,Q79-S79) -> 0 | R80: =ROUND(Q80*$B80,2) -> 0 | S80: =IF(Q80<T80,Q80,T80-R80) -> 0 | T80: =IF(Q80<$M$16,Q80+R80,$M$16) -> 0
A81: =VLOOKUP(D81,$A$7:$B$11,2) -> 0.0715 | B81: =A81/12 -> 0.0059583333 | C81: =INT((D81+11)/12) -> 5 | D81: 59 | E81: =IF(E80<H80,0,E80-G80) -> 0 | F81: =ROUND(E81*$B81,2) -> 0 | G81: =IF(E81<H81,E81,H81-F81) -> 0 | H81: =IF(E81<$M$4,E81+F81,$M$4) -> 0 | I81: =IF(I80<L80,0,I80-K80) -> 0 | J81: =ROUND(I81*$B81,2) -> 0 | K81: =IF(I81<L81,I81,L81-J81) -> 0 | L81: =IF(I81<$M$5,I81+J81,$M$5) -> 0 | M81: =IF(M80<P80,0,M80-O80) -> 0 | N81: =ROUND(M81*$B81,2) -> 0 | O81: =IF(M81<P81,M81,P81-N81) -> 0 | P81: =IF(M81<$M$10,M81+N81,$M$11) -> 0 | Q81: =IF(Q80<T80,0,Q80-S80) -> 0 | R81: =ROUND(Q81*$B81,2) -> 0 | S81: =IF(Q81<T81,Q81,T81-R81) -> 0 | T81: =IF(Q81<$M$16,Q81+R81,$M$16) -> 0
A82: =VLOOKUP(D82,$A$7:$B$11,2) -> 0.0715 | B82: =A82/12 -> 0.0059583333 | C82: =INT((D82+11)/12) -> 5 | D82: 60 | E82: =IF(E81<H81,0,E81-G81) -> 0 | F82: =ROUND(E82*$B82,2) -> 0 | G82: =IF(E82<H82,E82,H82-F82) -> 0 | H82: =IF(E82<$M$4,E82+F82,$M$4) -> 0 | I82: =IF(I81<L81,0,I81-K81) -> 0 | J82: =ROUND(I82*$B82,2) -> 0 | K82: =IF(I82<L82,I82,L82-J82) -> 0 | L82: =IF(I82<$M$5,I82+J82,$M$5) -> 0 | M82: =IF(M81<P81,0,M81-O81) -> 0 | N82: =ROUND(M82*$B82,2) -> 0 | O82: =IF(M82<P82,M82,P82-N82) -> 0 | P82: =IF(M82<$M$10,M82+N82,$M$11) -> 0 | Q82: =IF(Q81<T81,0,Q81-S81) -> 0 | R82: =ROUND(Q82*$B82,2) -> 0 | S82: =IF(Q82<T82,Q82,T82-R82) -> 0 | T82: =IF(Q82<$M$16,Q82+R82,$M$16) -> 0
A83: =VLOOKUP(D83,$A$7:$B$11,2) -> 0.0715 | B83: =A83/12 -> 0.0059583333 | C83: =INT((D83+11)/12) -> 6 | D83: 61 | E83: =IF(E82<H82,0,E82-G82) -> 0 | F83: =ROUND(E83*$B83,2) -> 0 | G83: =IF(E83<H83,E83,H83-F83) -> 0 | H83: =IF(E83<$M$4,E83+F83,$M$4) -> 0 | I83: =IF(I82<L82,0,I82-K82) -> 0 | J83: =ROUND(I83*$B83,2) -> 0 | K83: =IF(I83<L83,I83,L83-J83) -> 0 | L83: =IF(I83<$M$5,I83+J83,$M$5) -> 0 | M83: =IF(M82<P82,0,M82-O82) -> 0 | N83: =ROUND(M83*$B83,2) -> 0 | O83: =IF(M83<P83,M83,P83-N83) -> 0 | P83: =IF(M83<$M$10,M83+N83,$M$11) -> 0 | Q83: =IF(Q82<T82,0,Q82-S82) -> 0 | R83: =ROUND(Q83*$B83,2) -> 0 | S83: =IF(Q83<T83,Q83,T83-R83) -> 0 | T83: =IF(Q83<$M$17,Q83+R83,$M$17) -> 0
A84: =VLOOKUP(D84,$A$7:$B$11,2) -> 0.0715 | B84: =A84/12 -> 0.0059583333 | C84: =INT((D84+11)/12) -> 6 | D84: 62 | E84: =IF(E83<H83,0,E83-G83) -> 0 | F84: =ROUND(E84*$B84,2) -> 0 | G84: =IF(E84<H84,E84,H84-F84) -> 0 | H84: =IF(E84<$M$4,E84+F84,$M$4) -> 0 | I84: =IF(I83<L83,0,I83-K83) -> 0 | J84: =ROUND(I84*$B84,2) -> 0 | K84: =IF(I84<L84,I84,L84-J84) -> 0 | L84: =IF(I84<$M$5,I84+J84,$M$5) -> 0 | M84: =IF(M83<P83,0,M83-O83) -> 0 | N84: =ROUND(M84*$B84,2) -> 0 | O84: =IF(M84<P84,M84,P84-N84) -> 0 | P84: =IF(M84<$M$10,M84+N84,$M$11) -> 0 | Q84: =IF(Q83<T83,0,Q83-S83) -> 0 | R84: =ROUND(Q84*$B84,2) -> 0 | S84: =IF(Q84<T84,Q84,T84-R84) -> 0 | T84: =IF(Q84<$M$17,Q84+R84,$M$17) -> 0
A85: =VLOOKUP(D85,$A$7:$B$11,2) -> 0.0715 | B85: =A85/12 -> 0.0059583333 | C85: =INT((D85+11)/12) -> 6 | D85: 63 | E85: =IF(E84<H84,0,E84-G84) -> 0 | F85: =ROUND(E85*$B85,2) -> 0 | G85: =IF(E85<H85,E85,H85-F85) -> 0 | H85: =IF(E85<$M$4,E85+F85,$M$4) -> 0 | I85: =IF(I84<L84,0,I84-K84) -> 0 | J85: =ROUND(I85*$B85,2) -> 0 | K85: =IF(I85<L85,I85,L85-J85) -> 0 | L85: =IF(I85<$M$5,I85+J85,$M$5) -> 0 | M85: =IF(M84<P84,0,M84-O84) -> 0 | N85: =ROUND(M85*$B85,2) -> 0 | O85: =IF(M85<P85,M85,P85-N85) -> 0 | P85: =IF(M85<$M$10,M85+N85,$M$11) -> 0 | Q85: =IF(Q84<T84,0,Q84-S84) -> 0 | R85: =ROUND(Q85*$B85,2) -> 0 | S85: =IF(Q85<T85,Q85,T85-R85) -> 0 | T85: =IF(Q85<$M$17,Q85+R85,$M$17) -> 0
A86: =VLOOKUP(D86,$A$7:$B$11,2) -> 0.0715 | B86: =A86/12 -> 0.0059583333 | C86: =INT((D86+11)/12) -> 6 | D86: 64 | E86: =IF(E85<H85,0,E85-G85) -> 0 | F86: =ROUND(E86*$B86,2) -> 0 | G86: =IF(E86<H86,E86,H86-F86) -> 0 | H86: =IF(E86<$M$4,E86+F86,$M$4) -> 0 | I86: =IF(I85<L85,0,I85-K85) -> 0 | J86: =ROUND(I86*$B86,2) -> 0 | K86: =IF(I86<L86,I86,L86-J86) -> 0 | L86: =IF(I86<$M$5,I86+J86,$M$5) -> 0 | M86: =IF(M85<P85,0,M85-O85) -> 0 | N86: =ROUND(M86*$B86,2) -> 0 | O86: =IF(M86<P86,M86,P86-N86) -> 0 | P86: =IF(M86<$M$10,M86+N86,$M$11) -> 0 | Q86: =IF(Q85<T85,0,Q85-S85) -> 0 | R86: =ROUND(Q86*$B86,2) -> 0 | S86: =IF(Q86<T86,Q86,T86-R86) -> 0 | T86: =IF(Q86<$M$17,Q86+R86,$M$17) -> 0
A87: =VLOOKUP(D87,$A$7:$B$11,2) -> 0.0715 | B87: =A87/12 -> 0.0059583333 | C87: =INT((D87+11)/12) -> 6 | D87: 65 | E87: =IF(E86<H86,0,E86-G86) -> 0 | F87: =ROUND(E87*$B87,2) -> 0 | G87: =IF(E87<H87,E87,H87-F87) -> 0 | H87: =IF(E87<$M$4,E87+F87,$M$4) -> 0 | I87: =IF(I86<L86,0,I86-K86) -> 0 | J87: =ROUND(I87*$B87,2) -> 0 | K87: =IF(I87<L87,I87,L87-J87) -> 0 | L87: =IF(I87<$M$5,I87+J87,$M$5) -> 0 | M87: =IF(M86<P86,0,M86-O86) -> 0 | N87: =ROUND(M87*$B87,2) -> 0 | O87: =IF(M87<P87,M87,P87-N87) -> 0 | P87: =IF(M87<$M$10,M87+N87,$M$11) -> 0 | Q87: =IF(Q86<T86,0,Q86-S86) -> 0 | R87: =ROUND(Q87*$B87,2) -> 0 | S87: =IF(Q87<T87,Q87,T87-R87) -> 0 | T87: =IF(Q87<$M$17,Q87+R87,$M$17) -> 0
A88: =VLOOKUP(D88,$A$7:$B$11,2) -> 0.0715 | B88: =A88/12 -> 0.0059583333 | C88: =INT((D88+11)/12) -> 6 | D88: 66 | E88: =IF(E87<H87,0,E87-G87) -> 0 | F88: =ROUND(E88*$B88,2) -> 0 | G88: =IF(E88<H88,E88,H88-F88) -> 0 | H88: =IF(E88<$M$4,E88+F88,$M$4) -> 0 | I88: =IF(I87<L87,0,I87-K87) -> 0 | J88: =ROUND(I88*$B88,2) -> 0 | K88: =IF(I88<L88,I88,L88-J88) -> 0 | L88: =IF(I88<$M$5,I88+J88,$M$5) -> 0 | M88: =IF(M87<P87,0,M87-O87) -> 0 | N88: =ROUND(M88*$B88,2) -> 0 | O88: =IF(M88<P88,M88,P88-N88) -> 0 | P88: =IF(M88<$M$10,M88+N88,$M$11) -> 0 | Q88: =IF(Q87<T87,0,Q87-S87) -> 0 | R88: =ROUND(Q88*$B88,2) -> 0 | S88: =IF(Q88<T88,Q88,T88-R88) -> 0 | T88: =IF(Q88<$M$17,Q88+R88,$M$17) -> 0
A89: =VLOOKUP(D89,$A$7:$B$11,2) -> 0.0715 | B89: =A89/12 -> 0.0059583333 | C89: =INT((D89+11)/12) -> 6 | D89: 67 | E89: =IF(E88<H88,0,E88-G88) -> 0 | F89: =ROUND(E89*$B89,2) -> 0 | G89: =IF(E89<H89,E89,H89-F89) -> 0 | H89: =IF(E89<$M$4,E89+F89,$M$4) -> 0 | I89: =IF(I88<L88,0,I88-K88) -> 0 | J89: =ROUND(I89*$B89,2) -> 0 | K89: =IF(I89<L89,I89,L89-J89) -> 0 | L89: =IF(I89<$M$5,I89+J89,$M$5) -> 0 | M89: =IF(M88<P88,0,M88-O88) -> 0 | N89: =ROUND(M89*$B89,2) -> 0 | O89: =IF(M89<P89,M89,P89-N89) -> 0 | P89: =IF(M89<$M$10,M89+N89,$M$11) -> 0 | Q89: =IF(Q88<T88,0,Q88-S88) -> 0 | R89: =ROUND(Q89*$B89,2) -> 0 | S89: =IF(Q89<T89,Q89,T89-R89) -> 0 | T89: =IF(Q89<$M$17,Q89+R89,$M$17) -> 0
A90: =VLOOKUP(D90,$A$7:$B$11,2) -> 0.0715 | B90: =A90/12 -> 0.0059583333 | C90: =INT((D90+11)/12) -> 6 | D90: 68 | E90: =IF(E89<H89,0,E89-G89) -> 0 | F90: =ROUND(E90*$B90,2) -> 0 | G90: =IF(E90<H90,E90,H90-F90) -> 0 | H90: =IF(E90<$M$4,E90+F90,$M$4) -> 0 | I90: =IF(I89<L89,0,I89-K89) -> 0 | J90: =ROUND(I90*$B90,2) -> 0 | K90: =IF(I90<L90,I90,L90-J90) -> 0 | L90: =IF(I90<$M$5,I90+J90,$M$5) -> 0 | M90: =IF(M89<P89,0,M89-O89) -> 0 | N90: =ROUND(M90*$B90,2) -> 0 | O90: =IF(M90<P90,M90,P90-N90) -> 0 | P90: =IF(M90<$M$10,M90+N90,$M$11) -> 0 | Q90: =IF(Q89<T89,0,Q89-S89) -> 0 | R90: =ROUND(Q90*$B90,2) -> 0 | S90: =IF(Q90<T90,Q90,T90-R90) -> 0 | T90: =IF(Q90<$M$17,Q90+R90,$M$17) -> 0
A91: =VLOOKUP(D91,$A$7:$B$11,2) -> 0.0715 | B91: =A91/12 -> 0.0059583333 | C91: =INT((D91+11)/12) -> 6 | D91: 69 | E91: =IF(E90<H90,0,E90-G90) -> 0 | F91: =ROUND(E91*$B91,2) -> 0 | G91: =IF(E91<H91,E91,H91-F91) -> 0 | H91: =IF(E91<$M$4,E91+F91,$M$4) -> 0 | I91: =IF(I90<L90,0,I90-K90) -> 0 | J91: =ROUND(I91*$B91,2) -> 0 | K91: =IF(I91<L91,I91,L91-J91) -> 0 | L91: =IF(I91<$M$5,I91+J91,$M$5) -> 0 | M91: =IF(M90<P90,0,M90-O90) -> 0 | N91: =ROUND(M91*$B91,2) -> 0 | O91: =IF(M91<P91,M91,P91-N91) -> 0 | P91: =IF(M91<$M$10,M91+N91,$M$11) -> 0 | Q91: =IF(Q90<T90,0,Q90-S90) -> 0 | R91: =ROUND(Q91*$B91,2) -> 0 | S91: =IF(Q91<T91,Q91,T91-R91) -> 0 | T91: =IF(Q91<$M$17,Q91+R91,$M$17) -> 0
A92: =VLOOKUP(D92,$A$7:$B$11,2) -> 0.0715 | B92: =A92/12 -> 0.0059583333 | C92: =INT((D92+11)/12) -> 6 | D92: 70 | E92: =IF(E91<H91,0,E91-G91) -> 0 | F92: =ROUND(E92*$B92,2) -> 0 | G92: =IF(E92<H92,E92,H92-F92) -> 0 | H92: =IF(E92<$M$4,E92+F92,$M$4) -> 0 | I92: =IF(I91<L91,0,I91-K91) -> 0 | J92: =ROUND(I92*$B92,2) -> 0 | K92: =IF(I92<L92,I92,L92-J92) -> 0 | L92: =IF(I92<$M$5,I92+J92,$M$5) -> 0 | M92: =IF(M91<P91,0,M91-O91) -> 0 | N92: =ROUND(M92*$B92,2) -> 0 | O92: =IF(M92<P92,M92,P92-N92) -> 0 | P92: =IF(M92<$M$10,M92+N92,$M$11) -> 0 | Q92: =IF(Q91<T91,0,Q91-S91) -> 0 | R92: =ROUND(Q92*$B92,2) -> 0 | S92: =IF(Q92<T92,Q92,T92-R92) -> 0 | T92: =IF(Q92<$M$17,Q92+R92,$M$17) -> 0
A93: =VLOOKUP(D93,$A$7:$B$11,2) -> 0.0715 | B93: =A93/12 -> 0.0059583333 | C93: =INT((D93+11)/12) -> 6 | D93: 71 | E93: =IF(E92<H92,0,E92-G92) -> 0 | F93: =ROUND(E93*$B93,2) -> 0 | G93: =IF(E93<H93,E93,H93-F93) -> 0 | H93: =IF(E93<$M$4,E93+F93,$M$4) -> 0 | I93: =IF(I92<L92,0,I92-K92) -> 0 | J93: =ROUND(I93*$B93,2) -> 0 | K93: =IF(I93<L93,I93,L93-J93) -> 0 | L93: =IF(I93<$M$5,I93+J93,$M$5) -> 0 | M93: =IF(M92<P92,0,M92-O92) -> 0 | N93: =ROUND(M93*$B93,2) -> 0 | O93: =IF(M93<P93,M93,P93-N93) -> 0 | P93: =IF(M93<$M$10,M93+N93,$M$11) -> 0 | Q93: =IF(Q92<T92,0,Q92-S92) -> 0 | R93: =ROUND(Q93*$B93,2) -> 0 | S93: =IF(Q93<T93,Q93,T93-R93) -> 0 | T93: =IF(Q93<$M$17,Q93+R93,$M$17) -> 0
A94: =VLOOKUP(D94,$A$7:$B$11,2) -> 0.0715 | B94: =A94/12 -> 0.0059583333 | C94: =INT((D94+11)/12) -> 6 | D94: 72 | E94: =IF(E93<H93,0,E93-G93) -> 0 | F94: =ROUND(E94*$B94,2) -> 0 | G94: =IF(E94<H94,E94,H94-F94) -> 0 | H94: =IF(E94<$M$4,E94+F94,$M$4) -> 0 | I94: =IF(I93<L93,0,I93-K93) -> 0 | J94: =ROUND(I94*$B94,2) -> 0 | K94: =IF(I94<L94,I94,L94-J94) -> 0 | L94: =IF(I94<$M$5,I94+J94,$M$5) -> 0 | M94: =IF(M93<P93,0,M93-O93) -> 0 | N94: =ROUND(M94*$B94,2) -> 0 | O94: =IF(M94<P94,M94,P94-N94) -> 0 | P94: =IF(M94<$M$10,M94+N94,$M$11) -> 0 | Q94: =IF(Q93<T93,0,Q93-S93) -> 0 | R94: =ROUND(Q94*$B94,2) -> 0 | S94: =IF(Q94<T94,Q94,T94-R94) -> 0 | T94: =IF(Q94<$M$17,Q94+R94,$M$17) -> 0
... A392: =VLOOKUP(D392,$A$7:$B$11,2) -> 0.0715 | B392: =A392/12 -> 0.0059583333 | C392: =INT((D392+11)/12) -> 31 | D392: 370 | E392: =IF(E391<H391,0,E391-G391) -> 0 | F392: =ROUND(E392*$B392,2) -> 0 | G392: =IF(E392<H392,E392,H392-F392) -> 0 | H392: =IF(E392<$M$4,E392+F392,$M$4) -> 0 | I392: =IF(I391<L391,0,I391-K391) -> 0 | J392: =ROUND(I392*$B392,2) -> 0 | K392: =IF(I392<L392,I392,L392-J392) -> 0 | L392: =IF(I392<$M$5,I392+J392,$M$5) -> 0 | M392: =IF(M391<P391,0,M391-O391) -> 0 | N392: =ROUND(M392*$B392,2) -> 0 | O392: =IF(M392<P392,M392,P392-N392) -> 0 | P392: =IF(M392<$M$10,M392+N392,$M$11) -> 0 | Q392: =IF(Q391<T391,0,Q391-S391) -> 0 | R392: =ROUND(Q392*$B392,2) -> 0 | S392: =IF(Q392<T392,Q392,T392-R392) -> 0 | T392: =IF(Q392<$M$17,Q392+R392,$M$17) -> 0

Sheet Sheet6

Sheet คีย์ข้อมูล
A2: ผู้กู้หลัก | B2: อายุ | C2: =69-39 -> 30 | D2: ปี | E2: เพศ | F2: ชาย | G2: ผู้กู้ร่วม 1 | H2: อายุ | I2: =67-27 -> 40 | J2: ปี | K2: เพศ | L2: หญิง | M2: ผู้กู้ร่วม 2 | N2: อายุ | O2: 30 | P2: ปี | Q2: เพศ | R2: หญิง | T2: ราคาซื้อขาย | U2: ราคาประเมิน
A3: รายได้ | P3: สรุปวงเงิน | T3: 2540000 | U3: 2201680
A4: SL | B4: 30000 | C4: บาท | G4: ประจำ | I4: บาท | M4: ประจำ | N4: 0 | O4: บาท | P4: วงเงินที่ 1 | T4: LTV | U4: LTV
C5: บาท | G5: อื่นๆ | I5: บาท | M5: อื่นๆ | N5: 0 | O5: บาท | P5: HL | S5: =B15 -> 1000000 | T5: =S5/T3 -> 0.39370079 | U5: =S5/U3 -> 0.45419861
A6: รวม | B6: =B4+B5 -> 30000 | C6: บาท | G6: รวม | H6: =H4+H5 -> 0 | I6: บาท | M6: รวม | N6: =N4+N5 -> 0 | O6: บาท | P6: HL+ประกัน | S6: =B21 -> 1020980 | T6: =S6/T3 -> 0.40196063 | U6: =S6/U3 -> 0.4637277
A7: ภาระผ่อนสินเชื่อ (อย่าลืมใส่ภาระผ่อนสินเชื่อทั้งในและนอก NCB) | P7: วงเงินที่ 2
C8: บาท | I8: บาท | M8: ตาม NCB | N8: 0 | O8: บาท | P8: MP | S8: =B24 -> 0 | T8: =S8/T3 -> 0 | U8: =S8/U3 -> 0
C9: บาท | H9: 0 | I9: บาท | M9: นอกNCB | N9: 0 | O9: บาท | P9: MP+ประกัน | S9: =B30 -> 0 | T9: =S9/T3 -> 0 | U9: =S9/U3 -> 0
A10: รวม | B10: =B8+B9 -> 0 | C10: บาท | G10: รวม | H10: =H8+H9 -> 0 | I10: บาท | L10: Medium | M10: รวม | N10: =N8+N9 -> 0 | O10: บาท | P10: วงเงินรวม
A11: รายได้รวม | H11: =B6+H6+N6 -> 30000 | I11: บาท | J11: ควรมีรายได้ | L11: Limit DSR | M11: DSR | N11: =(H13+H12)/H11 -> 0.21766667 | P11: HL+MP | S11: =S5+S8 -> 1000000 | T11: =S11/T3 -> 0.39370079 | U11: =S11/U3 -> 0.45419861
A12: ภาระผ่อนสินเชื่อรวม | H12: =B10+H10+N10 -> 0 | I12: บาท | J12: =IF(N11>L12,((H12+H13)/L12),0) -> 0 | L12: 0.7 | M12: Net Income | N12: =H11-H12-H13 -> 23470 | O12: บาท | P12: HL+MP+ประกัน | S12: =B21+B30 -> 1020980 | T12: =S12/T3 -> 0.40196063 | U12: =S12/U3 -> 0.4637277
A13: ค่างวดผ่อน CIMB รวม | H13: =G30+G21 -> 6530 | I13: บาท | J13: =IF(N11>L12,((H12+H13)/L12-H11),0) -> 0 | L13: << เพิ่มอีก | M13: Net Income ต้อง > 7,500 บาท | Y13: MRTA | AB13: MRTA+
A14: วงเงินที่ 1 | L14: ระยะเวลา | M14: อัตราดอกเบี้ย | N14: % | X14: HL | Y14: ชาย | Z14: หญิง | AA14: เลือกเพศ | AB14: ชาย | AC14: หญิง | AD14: เลือกเพศ
A15: วงเงินที่ 1 | B15: 1000000 | C15: บาท | E15: ระยะเวลากู้ | G15: 35 | H15: ปี(ถ้าเลยวันเกิดกู้หลักระยะเวลากู้ -1) | L15: เดือนที่ 1-3 | N15: 0.0329 | X15: 1 | Y15: =VLOOKUP(G17,'อัตรา mrta'!$A$6:$AR$36,C2-18,0) -> 0.01642 | Z15: =VLOOKUP(G17,'อัตรา mrta'!$A$41:$AR$71,C2-18,0) -> 0.00568 | AA15: =IF(F2="หญิง",Z15,Y15) -> 0.01642 | AB15: =VLOOKUP(G17,'อัตรา mrta+'!$A$6:$AR$36,C2-18,0) -> 0.02098 | AC15: =VLOOKUP(G17,'อัตรา mrta+'!$A$41:$AR$71,C2-18,0) -> 0.01024 | AD15: =IF(F2="หญิง",AC15,AB15) -> 0.02098 | AE15: =IF(J17="NoMRTA",0,IF(J17="MRTA",AA15,AD15)) -> 0.02098
B16: เบี้ยประกัน | G16: ปี | H16: ทุนประกัน(บาท) | I16: อัตรา | J16: ประกัน | K16: % | L16: เดือนที่ 4-12 | N16: 0.0329 | X16: 2 | Y16: =VLOOKUP(G18,'อัตรา mrta'!$A$6:$AR$36,I2-18,0) -> 0.02132 | Z16: =VLOOKUP(G18,'อัตรา mrta'!$A$41:$AR$71,I2-18,0) -> 0.00828 | AA16: =IF(L2="หญิง",Z16,Y16) -> 0.00828 | AB16: =VLOOKUP(G18,'อัตรา mrta+'!$A$6:$AR$36,I2-18,0) -> 0.02507 | AC16: =VLOOKUP(G18,'อัตรา mrta+'!$A$41:$AR$71,I2-18,0) -> 0.01203 | AD16: =IF(L2="หญิง",AC16,AB16) -> 0.01203
A17: ผู้กู้หลัก | B17: =H17*I17 -> 20980 | C17: บาท | E17: ระยะเวลาคุ้มครอง | G17: 10 | H17: =$B$15*K17 -> 1000000 | I17: =IF(J17="NoMRTA",0,IF(J17="MRTA",AA15,AD15)) -> 0.02098 | J17: MRTA+ | K17: 1 | L17: ปีที่ 2 | N17: 0.0329 | X17: 3 | Y17: =VLOOKUP(G19,'อัตรา mrta'!$A$6:$AR$36,O2-18,0) -> 0.01263 | Z17: =VLOOKUP(G19,'อัตรา mrta'!$A$41:$AR$71,O2-18,0) -> 0.00434 | AA17: =IF(R2="หญิง",Z17,Y17) -> 0.00434 | AB17: =VLOOKUP(G19,'อัตรา mrta+'!$A$6:$AR$36,O2-18,0) -> 0.01638 | AC17: =VLOOKUP(G19,'อัตรา mrta+'!$A$41:$AR$71,O2-18,0) -> 0.00809 | AD17: =IF(R2="หญิง",AC17,AB17) -> 0.00809
A18: ผู้กู้ร่วม 1 | B18: =H18*I18 -> 0 | C18: บาท | E18: ระยะเวลาคุ้มครอง | G18: 8 | H18: =$B$15*K18 -> 1000000 | I18: =IF(J18="NoMRTA",0,IF(J18="MRTA",AA16,AD16)) -> 0 | J18: NoMRTA | K18: 1 | L18: ปีที่ 3 | N18: 0.0329 | S18: 8.525 | X18: 4 | Y18: =VLOOKUP(G26,'อัตรา mrta'!$A$6:$AR$36,C2-18,0) -> 0.01642 | Z18: =VLOOKUP(G26,'อัตรา mrta'!$A$41:$AR$71,C2-18,0) -> 0.00568 | AA18: =IF(F2="หญิง",Z18,Y18) -> 0.01642 | AB18: =VLOOKUP(G26,'อัตรา mrta+'!$A$6:$AR$36,C2-18,0) -> 0.02098 | AC18: =VLOOKUP(G26,'อัตรา mrta+'!$A$41:$AR$71,C2-18,0) -> 0.01024 | AD18: =IF(F2="หญิง",AC18,AB18) -> 0.02098
A19: ผู้กู้ร่วม 2 | B19: =H19*I19 -> 0 | C19: บาท | E19: ระยะเวลาคุ้มครอง | G19: 8 | H19: =$B$15*K19 -> 1000000 | I19: =IF(J19="NoMRTA",0,IF(J19="MRTA",AA17,AD17)) -> 0 | J19: NoMRTA | K19: 1 | L19: หลังจากนั้น | N19: 0.06525 | X19: 5 | Y19: =VLOOKUP(G27,'อัตรา mrta'!$A$6:$AR$36,I2-18,0) -> 0.02813 | Z19: =VLOOKUP(G27,'อัตรา mrta'!$A$41:$AR$71,I2-18,0) -> 0.01106 | AA19: =IF(L2="หญิง",Z19,Y19) -> 0.01106 | AB19: =VLOOKUP(G27,'อัตรา mrta+'!$A$6:$AR$36,I2-18,0) -> 0.03269 | AC19: =VLOOKUP(G27,'อัตรา mrta+'!$A$41:$AR$71,I2-18,0) -> 0.01562 | AD19: =IF(L2="หญิง",AC19,AB19) -> 0.01562
A20: อัคคีภัย | C20: บาท | E20: ระยะเวลาคุ้มครอง | G20: 9 | H20: 2312990 | L20: เฉลี่ย 3 ปี | M20: เฉลี่ย 5 ปี | N20: ตลอดอายุสัญญา | X20: 6 | Y20: =VLOOKUP(G28,'อัตรา mrta'!$A$6:$AR$36,O2-18,0) -> 0.01642 | Z20: =VLOOKUP(G28,'อัตรา mrta'!$A$41:$AR$71,O2-18,0) -> 0.00568 | AA20: =IF(R2="หญิง",Z20,Y20) -> 0.00568 | AB20: =VLOOKUP(G28,'อัตรา mrta+'!$A$6:$AR$36,O2-18,0) -> 0.02098 | AC20: =VLOOKUP(G28,'อัตรา mrta+'!$A$41:$AR$71,O2-18,0) -> 0.01024 | AD20: =IF(R2="หญิง",AC20,AB20) -> 0.01024
A21: วงเงินรวม | B21: =B15+B17+B18+B19+B20 -> 1020980 | C21: บาท | E21: ผ่อนชำระต่อเดือน | G21: ='ตารางผ่อนวงเงินที่ 1'!F24 -> 6530 | H21: บาท | L21: =(N15/12*3+N16/12*9+N17+N18)/3 -> 0.0329 | M21: =(N16/12*9+N17+N18+N19*2)/5 -> 0.044195 | N21: =((N15/12*3)+(N16/12*9)+N17+N18+N19*(G15-3))/G15 -> 0.062477143
A23: วงเงินที่ 2 | L23: ระยะเวลา | M23: อัตราดอกเบี้ย | N23: %
A24: วงเงินที่ 2 | B24: 0 | C24: บาท | E24: ระยะเวลากู้ | G24: 35 | H24: ปี(ถ้าเลยวันเกิดกู้หลักระยะเวลากู้ -1) | L24: เดือนที่ 1-3 | M24: MRR-6.26% | N24: 0.0539
B25: เบี้ยประกัน | G25: ปี | H25: ทุนประกัน(บาท) | I25: อัตรา | J25: ประกัน | K25: % | L25: เดือนที่ 4-12 | M25: MRR-6.26% | N25: 0.0539
A26: ผู้กู้หลัก | B26: =H26*I26 -> 0 | C26: บาท | E26: ระยะเวลาคุ้มครอง | G26: 10 | H26: =$B$24*K26 -> 0 | I26: =IF(J26="NoMRTA",0,IF(J26="MRTA",AA18,AD18)) -> 0.02098 | J26: MRTA+ | K26: 1 | L26: ปีที่ 2 | M26: MRR-5.36% | N26: 0.0539
A27: ผู้กู้ร่วม 1 | B27: =H27*I27 -> 0 | C27: บาท | E27: ระยะเวลาคุ้มครอง | G27: 10 | H27: =$B$24*K27 -> 0 | I27: =IF(J27="NoMRTA",0,IF(J27="MRTA",AA19,AD19)) -> 0 | J27: NoMRTA | K27: 1 | L27: ปีที่ 3 | M27: MRR-5.36% | N27: 0.0539
A28: ผู้กู้ร่วม 2 | B28: =H28*I28 -> 0 | C28: บาท | E28: ระยะเวลาคุ้มครอง | G28: 10 | H28: =$B$24*K28 -> 0 | I28: =IF(J28="NoMRTA",0,IF(J28="MRTA",AA20,AD20)) -> 0 | J28: NoMRTA | K28: 1 | L28: หลังจากนั้น | M28: MRR-1.65% | N28: 0.07025
A29: อัคคีภัย | B29: 0 | C29: บาท | E29: ระยะเวลาคุ้มครอง | G29: 9 | H29: 1411000 | L29: เฉลี่ย 3 ปี | M29: เฉลี่ย 5 ปี | N29: ตลอดอายุสัญญา
A30: วงเงินรวม | B30: =B24+B26+B27+B28+B29 -> 0 | C30: บาท | E30: ผ่อนชำระต่อเดือน | G30: =ตารางผ่อนวงเงินที่2!F24 -> 0 | H30: บาท | L30: =(N24/12*3+N25/12*9+N26+N27)/3 -> 0.0539 | M30: =(N25/12*9+N26+N27+N28*2)/5 -> 0.057745 | N30: =((N24/12*3)+(N25/12*9)+N26+N27+N28*(G24-3))/G24 -> 0.068848571
A35: ชาย | B35: MRTA
A36: หญิง | B36: MRTA+
B37: NoMRTA
U38: =T38+T34+T33 -> 0

Sheet สรุปทางเลือก
B1: อัตราดอกเบี้ยสำหรับลูกค้าพนักงานประจำ
B2: วงเงินกู้สูงสุด 95% ของราคาประเมินหรือราคาซื้อขาย
B3: 1.กรณีส่งเข้าไปพิจารณาแล้วประมวลผลได้ Low
B4: รายได้ประจำ(Fix Income) ตั้งแต่ 20,001 บาทขึ้นไป
B5: ทางเลือก | C5: การทำประกัน | D5: ปีที่ 1 | F5: ปีที่ 2 | G5: ปีที่ 3 | H5: ปีที่ 4 เป็นต้นไป | I5: เฉลี่ย 3 ปี | J5: หลัง 3 ปี
D6: เดือน 1-3 | E6: เดือน 4-12
B7: ฟรี ค่าดำเนินการสินเชื่อ, ค่าประเมิน, ค่าจดจำนอง 1%ของวงเงินกู้*** | C7: Insurance | D7: 0 | E7: MRR-3.936% | F7: MRR-3.936% | G7: MRR-3.936% | H7: MRR-2.000% | I7: 0.0313 | J7: 0.0535
C8: No Insurance | D8: 0 | E8: MRR-3.608% | F8: MRR-3.608% | G8: MRR-3.608% | H8: MRR-2.000% | I8: 0.0343 | J8: 0.0535
B9: ฟรี ค่าดำเนินการสินเชื่อ, ค่าประเมิน | C9: Insurance | D9: 0 | E9: MRR-4.045% | F9: MRR-4.045% | G9: MRR-4.045% | H9: MRR-2.000% | I9: 0.0303 | J9: 0.0535
C10: No Insurance | D10: 0 | E10: MRR-3.717% | F10: MRR-3.717% | G10: MRR-3.717% | H10: MRR-2.000% | I10: 0.0333 | J10: 0.0535
B11: ***ถ้าเลือกแบบฟรีค่าจดจำนอง หากปิดสินเชื่อภายใน5ปี ธนาคารจะเรียกค่าจดจำนองคืนในวันที่ไถ่ถอนกับธนาคาร
B12: 2.กรณีส่งเข้าไปพิจารณาแล้วประมวลผลได้ Medium
B13: รายได้ประจำ(Fix Income) ตั้งแต่ 20,001 บาทขึ้นไป
B14: ทางเลือก | C14: การทำประกัน | D14: ปีที่ 1 | F14: ปีที่ 2 | G14: ปีที่ 3 | H14: ปีที่ 4 เป็นต้นไป | I14: เฉลี่ย 3 ปี | J14: หลัง 3 ปี
B16: ฟรี เฉพาะค่าดำเนินการสินเชื่อ | C16: Insurance | D16: MRR-3.850% | F16: MRR-3.850% | G16: MRR-3.850% | H16: MRR-2.000% | I16: 0.035 | J16: 0.0535
C17: No Insurance | D17: MRR-3.550% | F17: MRR-3.550% | G17: MRR-3.550% | H17: MRR-2.000% | I17: 0.038 | J17: 0.0535
B18: 3.ลูกค้าที่รายได้ประจำน้อยกว่า20,000 บาท
B19: ***รายได้ประจำหมายถึงรายได้ที่ได้แน่นอน เช่น เงินเดือน, ค่าตำแหน่ง, ค่าเช่าบ้าน ฯลฯ***
B20: ทางเลือก | C20: การทำประกัน | D20: ปีที่ 1 | F20: ปีที่ 2 | G20: ปีที่ 3 | H20: ปีที่ 4 เป็นต้นไป | I20: เฉลี่ย 3 ปี | J20: หลัง 3 ปี
B22: ฟรี เฉพาะค่าดำเนินการสินเชื่อ | C22: Insurance | D22: MRR-3.100% | F22: MRR-3.100% | G22: MRR-3.100% | H22: MRR-2.000% | I22: 0.0425 | J22: 0.0535
C23: No Insurance | D23: MRR-2.800% | F23: MRR-2.800% | G23: MRR-2.800% | H23: MRR-2.000% | I23: 0.0455 | J23: 0.0535
B24: วงเงินกู้สูงสุด 90% ของราคาประเมินหรือราคาซื้อขาย
B25: รายได้ต่อเดือนตั้งแต่ 50,000 บาทขึ้นไป
B26: ทางเลือก | C26: การทำประกัน | D26: ปีที่ 1 | F26: ปีที่ 2 | G26: ปีที่ 3 | H26: ปีที่ 4 เป็นต้นไป | I26: เฉลี่ย 3 ปี | J26: หลัง 3 ปี
B28: ฟรี ค่าดำเนินการสินเชื่อ, ค่าประเมิน | C28: Insurance | D28: MRR-4.360% | F28: MRR-4.360% | G28: MRR-4.360% | H28: MRR-2.000% | I28: 0.0299 | J28: 0.0535
C29: No Insurance | D29: MRR-4.060% | F29: MRR-4.060% | G29: MRR-4.060% | H29: MRR-2.000% | I29: 0.0329 | J29: 0.0535
B30: วงเงินกู้สูงสุด 85% ของราคาประเมินหรือราคาซื้อขาย
B31: รายได้ต่อเดือนตั้งแต่ 50,000 บาทขึ้นไป
B32: ทางเลือก | C32: การทำประกัน | D32: ปีที่ 1 | F32: ปีที่ 2 | G32: ปีที่ 3 | H32: ปีที่ 4 เป็นต้นไป | I32: เฉลี่ย 3 ปี | J32: หลัง 3 ปี
B34: ฟรี ค่าดำเนินการสินเชื่อ, ค่าประเมิน | C34: Insurance | D34: MRR-4.460% | F34: MRR-4.460% | G34: MRR-4.460% | H34: MRR-2.000% | I34: 0.0289 | J34: 0.0535
C35: No Insurance | D35: MRR-4.160% | F35: MRR-4.160% | G35: MRR-4.160% | H35: MRR-2.000% | I35: 0.0319 | J35: 0.0535
B36: วงเงินกู้สูงสุด 80% ของราคาประเมินหรือราคาซื้อขาย
B37: รายได้ต่อเดือนตั้งแต่ 50,000 บาทขึ้นไป
B38: ทางเลือก | C38: การทำประกัน | D38: ปีที่ 1 | F38: ปีที่ 2 | G38: ปีที่ 3 | H38: ปีที่ 4 เป็นต้นไป | I38: เฉลี่ย 3 ปี | J38: หลัง 3 ปี
B40: ฟรี ค่าดำเนินการสินเชื่อ, ค่าประเมิน | C40: Insurance | D40: MRR-4.860% | F40: MRR-4.860% | G40: MRR-4.860% | H40: MRR-2.000% | I40: 0.0249 | J40: 0.0535
C41: No Insurance | D41: MRR-4.660% | F41: MRR-4.660% | G41: MRR-4.660% | H41: MRR-2.000% | I41: 0.0269 | J41: 0.0535
B42: ปัจจุบัน MRR ธนาคารเท่ากับ 7.350% ต่อปี
B44: ค่าใช้จ่าย
B45: 1.ค่าดำเนินการสินเชื่อ | C45: ฟรีทุกสินเชื่อ
B46: 2.ค่าประเมินหลักทรัพย์ | C46: ค่าประเมินสำหรับทาวน์เฮาส์ 3,250 บาท จะฟรีประเมินบางโปรฯ
B47: 3.ค่าอากรแสตมป์ติดสัญญาเงินกู้ | C47: 0.05% ของวงเงินกู้ หรือล้านละ 500 บาท ชำระให้กับธนาคาร ณ วันที่เซ็นสัญญาเงินกู้กับธนาคาร
B48: 4.ค่าจดจำนอง | C48: 1 % ของวงเงินกู้ ชำระให้กับกรมที่ดิน ณ วันที่จดจำนองกับธนาคาร
B49: 5.ค่าโอนกรรมสิทธิ์ | C49: ประมาณ 2% อยู่ที่ตกลงกับผู้ขายว่าฝ่ายไหนออก

Sheet สรุปทางเลือก (2)
B1: อัตราดอกเบี้ยสำหรับเจ้าของกิจการ
B2: วงเงินกู้สูงสุด 80% ของราคาประเมินหรือราคาซื้อขาย
B4: ทางเลือก | C4: การทำประกัน | D4: ปีที่ 1 | F4: ปีที่ 2 | G4: ปีที่ 3 | H4: ปีที่ 4 เป็นต้นไป | I4: เฉลี่ย 3 ปี | J4: หลัง 3 ปี
B6: ฟรี เฉพาะค่าดำเนินการสินเชื่อ | C6: Insurance | D6: MRR-3.100% | F6: MRR-3.100% | G6: MRR-3.100% | H6: MRR-2.000% | I6: 0.0425 | J6: 0.0535
C7: No Insurance | D7: MRR-2.800% | F7: MRR-2.800% | G7: MRR-2.800% | H7: MRR-2.000% | I7: 0.0455 | J7: 0.0535
B8: วงเงินกู้สูงสุด 80% ของราคาประเมินหรือราคาซื้อขาย
B9: รายได้ต่อเดือนตั้งแต่ 50,000 บาทขึ้นไป
B10: ทางเลือก | C10: การทำประกัน | D10: ปีที่ 1 | F10: ปีที่ 2 | G10: ปีที่ 3 | H10: ปีที่ 4 เป็นต้นไป | I10: เฉลี่ย 3 ปี | J10: หลัง 3 ปี
B12: ฟรี ค่าดำเนินการสินเชื่อ, ค่าประเมิน | C12: Insurance | D12: MRR-4.360% | F12: MRR-4.360% | G12: MRR-4.360% | H12: MRR-2.000% | I12: 0.0299 | J12: 0.0535
C13: No Insurance | D13: MRR-4.060% | F13: MRR-4.060% | G13: MRR-4.060% | H13: MRR-2.000% | I13: 0.0329 | J13: 0.0535
B14: วงเงินกู้สูงสุด 70% ของราคาประเมินหรือราคาซื้อขาย
B15: รายได้ต่อเดือนตั้งแต่ 50,000 บาทขึ้นไป
B16: ทางเลือก | C16: การทำประกัน | D16: ปีที่ 1 | F16: ปีที่ 2 | G16: ปีที่ 3 | H16: ปีที่ 4 เป็นต้นไป | I16: เฉลี่ย 3 ปี | J16: หลัง 3 ปี
B18: ฟรี ค่าดำเนินการสินเชื่อ, ค่าประเมิน | C18: Insurance | D18: MRR-4.460% | F18: MRR-4.460% | G18: MRR-4.460% | H18: MRR-2.000% | I18: 0.0289 | J18: 0.0535
C19: No Insurance | D19: MRR-4.160% | F19: MRR-4.160% | G19: MRR-4.160% | H19: MRR-2.000% | I19: 0.0319 | J19: 0.0535
B20: ปัจจุบัน MRR ธนาคารเท่ากับ 7.350% ต่อปี
B22: ค่าใช้จ่าย
B23: 1.ค่าดำเนินการสินเชื่อ | C23: ฟรีทุกสินเชื่อ
B24: 2.ค่าประเมินหลักทรัพย์ | C24: ค่าประเมินสำหรับทาวน์เฮาส์ 3,250 บาท จะฟรีประเมินบางโปรฯ
B25: 3.ค่าอากรแสตมป์ติดสัญญาเงินกู้ | C25: 0.05% ของวงเงินกู้ หรือล้านละ 500 บาท ชำระให้กับธนาคาร ณ วันที่เซ็นสัญญาเงินกู้กับธนาคาร
B26: 4.ค่าจดจำนอง | C26: 1 % ของวงเงินกู้ ชำระให้กับกรมที่ดิน ณ วันที่จดจำนองกับธนาคาร
B27: 5.ค่าโอนกรรมสิทธิ์ | C27: ประมาณ 2% อยู่ที่ตกลงกับผู้ขายว่าฝ่ายไหนออก

Sheet NCBX
E1: วงเงินกู้รวม | F1: ยอดหนี้รวม | G1: จ่ายต่อเดือนรวม | H1: Ratio | I1: ยอดหนี้/วงเงินรวม
E2: =SUBTOTAL(9,E4:E42) -> 194000 | F2: =SUBTOTAL(9,F4:F42) -> 55964 | G2: =SUBTOTAL(9,G4:G42) -> 4136.66 | H2: =G2/F2 -> 0.073916446 | I2: =F2/E2 -> 0.28847423
A3: Activate | B3: ลักษณะกู้ | C3: สินเชื่อ | D3: Bank | E3: Loan | F3: Balance | G3: จ่ายต่อเดือน | H3: Ratio | I3: หนี้/วงเงินอนุมัติ | J3: Over Limit | K3: ประวัติการผ่อน | L3: วันที่อนุมัติ | M3: หมายเหตุ
A4: 1 | B4: เดี่ยว | C4: บุคคล | D4: AEON | E4: 41000 | F4: 0 | G4: =F4*3/100 -> 0 | H4: 0 | I4: =F4/E4 -> 0 | J4: =IF(I4>=100%,"Y","N") -> N | K4: ไม่เคยมีค้าง | L4: 241187
A5: 2 | B5: เดี่ยว | C5: บุคคล | D5: AYCAP | E5: 58000 | F5: 20142 | G5: 3062 | H5: =G5/F5 -> 0.15202065 | I5: =F5/E5 -> 0.34727586 | J5: =IF(I5>=100%,"Y","N") -> N | K5: ไม่เคยมีค้าง | L5: 241191
A6: 3 | B6: เดี่ยว | C6: บุคคล | D6: KTC | E6: 65000 | F6: 35822 | G6: =F6*3/100 -> 1074.66 | H6: =G6/F6 -> 0.03 | I6: =F6/E6 -> 0.55110769 | J6: =IF(I6>=100%,"Y","N") -> N | K6: ไม่เคยมีค้าง | L6: 241187
A7: 4 | B7: เดี่ยว | C7: บัตรเครดิต | D7: BBL | E7: 15000 | F7: 0 | G7: 0 | H7: 0 | I7: =F7/E7 -> 0 | J7: =IF(I7>=100%,"Y","N") -> N | K7: เคย 2565 | L7: 241835 | M7: เคยค้าง 04/2565 ระดับ 1 จำนวน 3,000 บ. | N7: อาจจะเป็นเรื่องค่าธรรมเนียม
A8: 5 | B8: เดี่ยว | C8: บัตรเครดิต | D8: BBL | E8: 15000 | F8: 0 | G8: 0 | H8: 0 | I8: =F8/E8 -> 0 | J8: =IF(I8>=100%,"Y","N") -> N | K8: เคย 2565 | L8: 241835 | M8: เคยค้าง 04/2565 ระดับ 1 จำนวน 1,500 บ. | N8: อาจจะเป็นเรื่องค่าธรรมเนียม
C36: มีการดึงข้อมูลเครดิตจากการขอสินเชื่อ มิ.ย.- ส.ค. 66 จำนวน 9 ครั้ง
C37: มีการดึงข้อมูลเครดิตจากการขอสินเชื่อ ทั้งปี 2566 จำนวน 21 ครั้ง

Sheet อัตรา mrta
E1: คุ้มครอง | F1: 5 | H1: =VLOOKUP(F1,A6:AR36,F2-18,0) -> 0.05954
E2: อายุ | F2: 60
A3: M | AU3: Password: 123456
A5: ปี | B5: อายุผู้เอาประกันภัย (ปี)
B6: 20 | C6: 21 | D6: 22 | E6: 23 | F6: 24 | G6: 25 | H6: 26 | I6: 27 | J6: 28 | K6: 29 | L6: 30 | M6: 31 | N6: 32 | O6: 33 | P6: 34 | Q6: 35 | R6: 36 | S6: 37 | T6: 38 | U6: 39 | V6: 40 | W6: 41 | X6: 42 | Y6: 43 | Z6: 44 | AA6: 45 | AB6: 46 | AC6: 47 | AD6: 48 | AE6: 49 | AF6: 50 | AG6: 51 | AH6: 52 | AI6: 53 | AJ6: 54 | AK6: 55 | AL6: 56 | AM6: 57 | AN6: 58 | AO6: 59 | AP6: 60 | AQ6: 61 | AR6: 62
A7: 1 | B7: 0.00155 | C7: 0.00161 | D7: 0.00166 | E7: 0.00169 | F7: 0.00172 | G7: 0.00174 | H7: 0.00176 | I7: 0.00178 | J7: 0.0018 | K7: 0.00183 | L7: 0.00188 | M7: 0.00194 | N7: 0.00202 | O7: 0.0021 | P7: 0.0022 | Q7: 0.00232 | R7: 0.00244 | S7: 0.00257 | T7: 0.0027 | U7: 0.00286 | V7: 0.00302 | W7: 0.0032 | X7: 0.0034 | Y7: 0.00362 | Z7: 0.00386 | AA7: 0.00413 | AB7: 0.00442 | AC7: 0.00475 | AD7: 0.0051 | AE7: 0.00549 | AF7: 0.0059 | AG7: 0.00635 | AH7: 0.00683 | AI7: 0.00735 | AJ7: 0.00792 | AK7: 0.00854 | AL7: 0.00924 | AM7: 0.01002 | AN7: 0.01091 | AO7: 0.01191 | AP7: 0.01305 | AQ7: 0.01434 | AR7: 0.0158
A8: 2 | B8: 0.00305 | C8: 0.00316 | D8: 0.00325 | E8: 0.00331 | F8: 0.00336 | G8: 0.0034 | H8: 0.00343 | I8: 0.00347 | J8: 0.00352 | K8: 0.0036 | L8: 0.00369 | M8: 0.00382 | N8: 0.00397 | O8: 0.00415 | P8: 0.00435 | Q8: 0.00457 | R8: 0.00481 | S8: 0.00507 | T8: 0.00534 | U8: 0.00564 | V8: 0.00597 | W8: 0.00633 | X8: 0.00672 | Y8: 0.00716 | Z8: 0.00765 | AA8: 0.00818 | AB8: 0.00877 | AC8: 0.00942 | AD8: 0.01012 | AE8: 0.01089 | AF8: 0.01171 | AG8: 0.01259 | AH8: 0.01355 | AI8: 0.01458 | AJ8: 0.01571 | AK8: 0.01696 | AL8: 0.01836 | AM8: 0.01992 | AN8: 0.0217 | AO8: 0.02371 | AP8: 0.02598 | AQ8: 0.02856 | AR8: 0.03147
A9: 3 | B9: 0.0046 | C9: 0.00476 | D9: 0.00487 | E9: 0.00496 | F9: 0.00503 | G9: 0.00508 | H9: 0.00513 | I9: 0.0052 | J9: 0.00529 | K9: 0.00541 | L9: 0.00557 | M9: 0.00577 | N9: 0.00601 | O9: 0.00628 | P9: 0.00659 | Q9: 0.00692 | R9: 0.00729 | S9: 0.00768 | T9: 0.00811 | U9: 0.00857 | V9: 0.00907 | W9: 0.00962 | X9: 0.01023 | Y9: 0.0109 | Z9: 0.01165 | AA9: 0.01247 | AB9: 0.01337 | AC9: 0.01436 | AD9: 0.01544 | AE9: 0.0166 | AF9: 0.01785 | AG9: 0.0192 | AH9: 0.02065 | AI9: 0.02223 | AJ9: 0.02397 | AK9: 0.02589 | AL9: 0.02804 | AM9: 0.03046 | AN9: 0.0332 | AO9: 0.0363 | AP9: 0.0398 | AQ9: 0.04376 | AR9: 0.04823
A10: 4 | B10: 0.00524 | C10: 0.0054 | D10: 0.00552 | E10: 0.00561 | F10: 0.00569 | G10: 0.00575 | H10: 0.00581 | I10: 0.0059 | J10: 0.00601 | K10: 0.00616 | L10: 0.00636 | M10: 0.00659 | N10: 0.00688 | O10: 0.0072 | P10: 0.00755 | Q10: 0.00794 | R10: 0.00836 | S10: 0.00882 | T10: 0.00931 | U10: 0.00984 | V10: 0.01043 | W10: 0.01107 | X10: 0.01178 | Y10: 0.01256 | Z10: 0.01343 | AA10: 0.01439 | AB10: 0.01543 | AC10: 0.01658 | AD10: 0.01782 | AE10: 0.01916 | AF10: 0.0206 | AG10: 0.02215 | AH10: 0.02384 | AI10: 0.02567 | AJ10: 0.02769 | AK10: 0.02993 | AL10: 0.03244 | AM10: 0.03527 | AN10: 0.03847 | AO10: 0.04209 | AP10: 0.04618 | AQ10: 0.05079 | AR10: 0.05597
A11: 5 | B11: 0.00662 | C11: 0.0068 | D11: 0.00694 | E11: 0.00705 | F11: 0.00714 | G11: 0.00723 | H11: 0.00732 | I11: 0.00744 | J11: 0.00759 | K11: 0.0078 | L11: 0.00806 | M11: 0.00838 | N11: 0.00874 | O11: 0.00916 | P11: 0.00962 | Q11: 0.01012 | R11: 0.01066 | S11: 0.01124 | T11: 0.01188 | U11: 0.01257 | V11: 0.01332 | W11: 0.01415 | X11: 0.01507 | Y11: 0.01609 | Z11: 0.01721 | AA11: 0.01844 | AB11: 0.01979 | AC11: 0.02126 | AD11: 0.02284 | AE11: 0.02456 | AF11: 0.02641 | AG11: 0.0284 | AH11: 0.03057 | AI11: 0.03293 | AJ11: 0.03554 | AK11: 0.03845 | AL11: 0.04172 | AM11: 0.0454 | AN11: 0.04955 | AO11: 0.05425 | AP11: 0.05954 | AQ11: 0.06549 | AR11: 0.07218
A12: 6 | B12: 0.00802 | C12: 0.00823 | D12: 0.00839 | E12: 0.00852 | F12: 0.00863 | G12: 0.00873 | H12: 0.00886 | I12: 0.00902 | J12: 0.00923 | K12: 0.0095 | L12: 0.00984 | M12: 0.01023 | N12: 0.01069 | O12: 0.01121 | P12: 0.01178 | Q12: 0.0124 | R12: 0.01306 | S12: 0.01379 | T12: 0.01457 | U12: 0.01543 | V12: 0.01637 | W12: 0.01741 | X12: 0.01855 | Y12: 0.01981 | Z12: 0.0212 | AA12: 0.02273 | AB12: 0.02439 | AC12: 0.0262 | AD12: 0.02816 | AE12: 0.03027 | AF12: 0.03255 | AG12: 0.03501 | AH12: 0.03769 | AI12: 0.04064 | AJ12: 0.04389 | AK12: 0.04753 | AL12: 0.05161 | AM12: 0.0562 | AN12: 0.06139 | AO12: 0.06724 | AP12: 0.07382 | AQ12: 0.08121 | AR12: 0.0895
A13: 7 | B13: 0.00878 | C13: 0.00899 | D13: 0.00915 | E13: 0.00929 | F13: 0.00941 | G13: 0.00954 | H13: 0.00969 | I13: 0.00989 | J13: 0.01014 | K13: 0.01046 | L13: 0.01085 | M13: 0.0113 | N13: 0.01182 | O13: 0.0124 | P13: 0.01303 | Q13: 0.01372 | R13: 0.01447 | S13: 0.01528 | T13: 0.01616 | U13: 0.01712 | V13: 0.01818 | W13: 0.01935 | X13: 0.02063 | Y13: 0.02205 | Z13: 0.02361 | AA13: 0.02531 | AB13: 0.02717 | AC13: 0.02918 | AD13: 0.03136 | AE13: 0.03371 | AF13: 0.03625 | AG13: 0.039 | AH13: 0.04201 | AI13: 0.04533 | AJ13: 0.049 | AK13: 0.0531 | AL13: 0.05771 | AM13: 0.0629 | AN13: 0.06875 | AO13: 0.07533 | AP13: 0.08272 | AQ13: 0.09101 | AR13: 0.10029
A14: 8 | B14: 0.01012 | C14: 0.01036 | D14: 0.01054 | E14: 0.01069 | F14: 0.01085 | G14: 0.01101 | H14: 0.01121 | I14: 0.01146 | J14: 0.01177 | K14: 0.01216 | L14: 0.01263 | M14: 0.01317 | N14: 0.01379 | O14: 0.01447 | P14: 0.01522 | Q14: 0.01603 | R14: 0.01692 | S14: 0.01788 | T14: 0.01892 | U14: 0.02006 | V14: 0.02132 | W14: 0.02271 | X14: 0.02423 | Y14: 0.02591 | Z14: 0.02775 | AA14: 0.02976 | AB14: 0.03194 | AC14: 0.03431 | AD14: 0.03687 | AE14: 0.03963 | AF14: 0.04263 | AG14: 0.04589 | AH14: 0.04946 | AI14: 0.0534 | AJ14: 0.05777 | AK14: 0.06267 | AL14: 0.06816 | AM14: 0.07434 | AN14: 0.08129 | AO14: 0.0891 | AP14: 0.09785 | AQ14: 0.10766 | AR14: 0.11862
A15: 9 | B15: 0.01149 | C15: 0.01174 | D15: 0.01195 | E15: 0.01213 | F15: 0.01231 | G15: 0.01252 | H15: 0.01277 | I15: 0.01308 | J15: 0.01346 | K15: 0.01393 | L15: 0.01448 | M15: 0.01512 | N15: 0.01584 | O15: 0.01664 | P15: 0.01751 | Q15: 0.01846 | R15: 0.01948 | S15: 0.0206 | T15: 0.02182 | U15: 0.02316 | V15: 0.02463 | W15: 0.02625 | X15: 0.02803 | Y15: 0.02999 | Z15: 0.03212 | AA15: 0.03445 | AB15: 0.03698 | AC15: 0.03972 | AD15: 0.04268 | AE15: 0.04589 | AF15: 0.04938 | AG15: 0.05318 | AH15: 0.05736 | AI15: 0.06198 | AJ15: 0.06712 | AK15: 0.07287 | AL15: 0.07932 | AM15: 0.08656 | AN15: 0.09469 | AO15: 0.10381 | AP15: 0.11402 | AQ15: 0.12543 | AR15: 0
A16: 10 | B16: 0.01288 | C16: 0.01315 | D16: 0.01338 | E16: 0.0136 | F16: 0.01382 | G16: 0.01407 | H16: 0.01438 | I16: 0.01476 | J16: 0.01522 | K16: 0.01577 | L16: 0.01642 | M16: 0.01716 | N16: 0.01799 | O16: 0.0189 | P16: 0.0199 | Q16: 0.02099 | R16: 0.02218 | S16: 0.02347 | T16: 0.02488 | U16: 0.02643 | V16: 0.02813 | W16: 0.02999 | X16: 0.03204 | Y16: 0.03429 | Z16: 0.03674 | AA16: 0.0394 | AB16: 0.0423 | AC16: 0.04544 | AD16: 0.04883 | AE16: 0.05252 | AF16: 0.05653 | AG16: 0.06093 | AH16: 0.06577 | AI16: 0.07112 | AJ16: 0.07709 | AK16: 0.08376 | AL16: 0.09123 | AM16: 0.09961 | AN16: 0.109 | AO16: 0.11951 | AP16: 0.13126 | AQ16: 0 | AR16: 0
A17: 11 | B17: 0.01428 | C17: 0.01458 | D17: 0.01485 | E17: 0.0151 | F17: 0.01537 | G17: 0.01568 | H17: 0.01605 | I17: 0.0165 | J17: 0.01705 | K17: 0.01769 | L17: 0.01843 | M17: 0.01928 | N17: 0.02023 | O17: 0.02127 | P17: 0.02241 | Q17: 0.02365 | R17: 0.02501 | S17: 0.02649 | T17: 0.0281 | U17: 0.02987 | V17: 0.03181 | W17: 0.03394 | X17: 0.03628 | Y17: 0.03883 | Z17: 0.04161 | AA17: 0.04463 | AB17: 0.04792 | AC17: 0.05148 | AD17: 0.05534 | AE17: 0.05954 | AF17: 0.06413 | AG17: 0.06916 | AH17: 0.07471 | AI17: 0.08087 | AJ17: 0.08772 | AK17: 0.09538 | AL17: 0.10395 | AM17: 0.11354 | AN17: 0.12427 | AO17: 0.13627 | AP17: 0 | AQ17: 0 | AR17: 0
A18: 12 | B18: 0.01572 | C18: 0.01605 | D18: 0.01635 | E18: 0.01665 | F18: 0.01697 | G18: 0.01734 | H18: 0.01778 | I18: 0.01831 | J18: 0.01894 | K18: 0.01968 | L18: 0.02053 | M18: 0.0215 | N18: 0.02257 | O18: 0.02375 | P18: 0.02504 | Q18: 0.02645 | R18: 0.02798 | S18: 0.02966 | T18: 0.03149 | U18: 0.0335 | V18: 0.0357 | W18: 0.03811 | X18: 0.04074 | Y18: 0.04362 | Z18: 0.04675 | AA18: 0.05015 | AB18: 0.05385 | AC18: 0.05786 | AD18: 0.06223 | AE18: 0.06699 | AF18: 0.07219 | AG18: 0.07792 | AH18: 0.08424 | AI18: 0.09126 | AJ18: 0.09906 | AK18: 0.10778 | AL18: 0.11752 | AM18: 0.12841 | AN18: 0.14057 | AO18: 0 | AP18: 0 | AQ18: 0 | AR18: 0
... A36: 30 | B36: 0.05022 | C36: 0.05219 | D36: 0.05431 | E36: 0.05662 | F36: 0.05916 | G36: 0.06195 | H36: 0.06504 | I36: 0.06847 | J36: 0.07225 | K36: 0.07642 | L36: 0.081 | M36: 0.08603 | N36: 0.09153 | O36: 0.09754 | P36: 0.10411 | Q36: 0.11128 | R36: 0.11911 | S36: 0.12767 | T36: 0.13703 | U36: 0.14728 | V36: 0.1585 | W36: 0 | X36: 0 | Y36: 0 | Z36: 0 | AA36: 0 | AB36: 0 | AC36: 0 | AD36: 0 | AE36: 0 | AF36: 0 | AG36: 0 | AH36: 0 | AI36: 0 | AJ36: 0 | AK36: 0 | AL36: 0 | AM36: 0 | AN36: 0 | AO36: 0 | AP36: 0 | AQ36: 0 | AR36: 0
A37: 31
A38: F | B38: อัตราเบี้ยประกัน MRTA (มอร์เกจ โพรเทคชั่น)
B39: เพศหญิง ต่อทุนประกัน 1,000 บาท
A40: ปี | B40: อายุผู้เอาประกันภัย (ปี)
B41: 20 | C41: 21 | D41: 22 | E41: 23 | F41: 24 | G41: 25 | H41: 26 | I41: 27 | J41: 28 | K41: 29 | L41: 30 | M41: 31 | N41: 32 | O41: 33 | P41: 34 | Q41: 35 | R41: 36 | S41: 37 | T41: 38 | U41: 39 | V41: 40 | W41: 41 | X41: 42 | Y41: 43 | Z41: 44 | AA41: 45 | AB41: 46 | AC41: 47 | AD41: 48 | AE41: 49 | AF41: 50 | AG41: 51 | AH41: 52 | AI41: 53 | AJ41: 54 | AK41: 55 | AL41: 56 | AM41: 57 | AN41: 58 | AO41: 59 | AP41: 60 | AQ41: 61 | AR41: 62
A42: 1 | B42: 0.00055 | C42: 0.00057 | D42: 0.00059 | E42: 0.0006 | F42: 0.00062 | G42: 0.00063 | H42: 0.00065 | I42: 0.00066 | J42: 0.00068 | K42: 0.00069 | L42: 0.00071 | M42: 0.00073 | N42: 0.00076 | O42: 0.00079 | P42: 0.00083 | Q42: 0.00087 | R42: 0.00093 | S42: 0.00099 | T42: 0.00106 | U42: 0.00114 | V42: 0.00123 | W42: 0.00133 | X42: 0.00144 | Y42: 0.00155 | Z42: 0.00168 | AA42: 0.00182 | AB42: 0.00197 | AC42: 0.00213 | AD42: 0.00231 | AE42: 0.0025 | AF42: 0.00271 | AG42: 0.00295 | AH42: 0.00323 | AI42: 0.00354 | AJ42: 0.0039 | AK42: 0.0043 | AL42: 0.00476 | AM42: 0.00528 | AN42: 0.00586 | AO42: 0.00651 | AP42: 0.00725 | AQ42: 0.00808 | AR42: 0.00903
A43: 2 | B43: 0.00109 | C43: 0.00112 | D43: 0.00116 | E43: 0.00119 | F43: 0.00121 | G43: 0.00124 | H43: 0.00127 | I43: 0.0013 | J43: 0.00133 | K43: 0.00136 | L43: 0.0014 | M43: 0.00144 | N43: 0.00149 | O43: 0.00156 | P43: 0.00164 | Q43: 0.00173 | R43: 0.00183 | S43: 0.00196 | T43: 0.0021 | U43: 0.00226 | V43: 0.00244 | W43: 0.00264 | X43: 0.00286 | Y43: 0.00309 | Z43: 0.00335 | AA43: 0.00362 | AB43: 0.00392 | AC43: 0.00424 | AD43: 0.00459 | AE43: 0.00497 | AF43: 0.0054 | AG43: 0.00589 | AH43: 0.00644 | AI43: 0.00707 | AJ43: 0.00779 | AK43: 0.0086 | AL43: 0.00953 | AM43: 0.01056 | AN43: 0.01173 | AO43: 0.01304 | AP43: 0.01452 | AQ43: 0.0162 | AR43: 0.01812
A44: 3 | B44: 0.00164 | C44: 0.00169 | D44: 0.00174 | E44: 0.00178 | F44: 0.00182 | G44: 0.00187 | H44: 0.00191 | I44: 0.00195 | J44: 0.002 | K44: 0.00205 | L44: 0.00211 | M44: 0.00218 | N44: 0.00226 | O44: 0.00236 | P44: 0.00248 | Q44: 0.00263 | R44: 0.0028 | S44: 0.00299 | T44: 0.00321 | U44: 0.00346 | V44: 0.00374 | W44: 0.00404 | X44: 0.00437 | Y44: 0.00473 | Z44: 0.00512 | AA44: 0.00554 | AB44: 0.006 | AC44: 0.00649 | AD44: 0.00702 | AE44: 0.00762 | AF44: 0.00828 | AG44: 0.00904 | AH44: 0.0099 | AI44: 0.01088 | AJ44: 0.01199 | AK44: 0.01326 | AL44: 0.01468 | AM44: 0.01629 | AN44: 0.01809 | AO44: 0.02011 | AP44: 0.0224 | AQ44: 0.02501 | AR44: 0.028
A45: 4 | B45: 0.0017 | C45: 0.00175 | D45: 0.0018 | E45: 0.00184 | F45: 0.00188 | G45: 0.00193 | H45: 0.00197 | I45: 0.00201 | J45: 0.00206 | K45: 0.00212 | L45: 0.00218 | M45: 0.00226 | N45: 0.00235 | O45: 0.00246 | P45: 0.0026 | Q45: 0.00275 | R45: 0.00293 | S45: 0.00314 | T45: 0.00338 | U45: 0.00364 | V45: 0.00393 | W45: 0.00426 | X45: 0.00461 | Y45: 0.00499 | Z45: 0.0054 | AA45: 0.00584 | AB45: 0.00631 | AC45: 0.00683 | AD45: 0.0074 | AE45: 0.00804 | AF45: 0.00875 | AG45: 0.00956 | AH45: 0.01048 | AI45: 0.01153 | AJ45: 0.01272 | AK45: 0.01407 | AL45: 0.01559 | AM45: 0.01729 | AN45: 0.01921 | AO45: 0.02137 | AP45: 0.02382 | AQ45: 0.02662 | AR45: 0.02983
A46: 5 | B46: 0.00215 | C46: 0.00221 | D46: 0.00227 | E46: 0.00232 | F46: 0.00238 | G46: 0.00243 | H46: 0.00249 | I46: 0.00254 | J46: 0.00261 | K46: 0.00268 | L46: 0.00277 | M46: 0.00287 | N46: 0.003 | O46: 0.00314 | P46: 0.00332 | Q46: 0.00353 | R46: 0.00377 | S46: 0.00404 | T46: 0.00434 | U46: 0.00469 | V46: 0.00507 | W46: 0.00548 | X46: 0.00593 | Y46: 0.00642 | Z46: 0.00694 | AA46: 0.00751 | AB46: 0.00813 | AC46: 0.0088 | AD46: 0.00954 | AE46: 0.01037 | AF46: 0.0113 | AG46: 0.01236 | AH46: 0.01357 | AI46: 0.01494 | AJ46: 0.0165 | AK46: 0.01826 | AL46: 0.02023 | AM46: 0.02246 | AN46: 0.02496 | AO46: 0.02778 | AP46: 0.03099 | AQ46: 0.03466 | AR46: 0.03889
A47: 6 | B47: 0.00261 | C47: 0.00268 | D47: 0.00275 | E47: 0.00282 | F47: 0.00288 | G47: 0.00295 | H47: 0.00302 | I47: 0.00309 | J47: 0.00317 | K47: 0.00327 | L47: 0.00338 | M47: 0.00351 | N47: 0.00367 | O47: 0.00386 | P47: 0.00409 | Q47: 0.00435 | R47: 0.00465 | S47: 0.00499 | T47: 0.00537 | U47: 0.0058 | V47: 0.00627 | W47: 0.00678 | X47: 0.00734 | Y47: 0.00794 | Z47: 0.00859 | AA47: 0.00929 | AB47: 0.01006 | AC47: 0.0109 | AD47: 0.01183 | AE47: 0.01287 | AF47: 0.01405 | AG47: 0.01539 | AH47: 0.01691 | AI47: 0.01864 | AJ47: 0.02059 | AK47: 0.02279 | AL47: 0.02527 | AM47: 0.02805 | AN47: 0.03119 | AO47: 0.03475 | AP47: 0.03879 | AQ47: 0.04344 | AR47: 0.04881
A48: 7 | B48: 0.00286 | C48: 0.00294 | D48: 0.00301 | E48: 0.00308 | F48: 0.00316 | G48: 0.00323 | H48: 0.00331 | I48: 0.00339 | J48: 0.00349 | K48: 0.0036 | L48: 0.00373 | M48: 0.00388 | N48: 0.00407 | O48: 0.00429 | P48: 0.00455 | Q48: 0.00485 | R48: 0.00519 | S48: 0.00558 | T48: 0.00601 | U48: 0.00649 | V48: 0.00701 | W48: 0.00758 | X48: 0.00821 | Y48: 0.00888 | Z48: 0.00961 | AA48: 0.0104 | AB48: 0.01126 | AC48: 0.01221 | AD48: 0.01327 | AE48: 0.01446 | AF48: 0.0158 | AG48: 0.01733 | AH48: 0.01905 | AI48: 0.02101 | AJ48: 0.02323 | AK48: 0.02572 | AL48: 0.02853 | AM48: 0.03169 | AN48: 0.03526 | AO48: 0.03931 | AP48: 0.04394 | AQ48: 0.04926 | AR48: 0.05543
A49: 8 | B49: 0.00331 | C49: 0.0034 | D49: 0.00348 | E49: 0.00356 | F49: 0.00365 | G49: 0.00373 | H49: 0.00383 | I49: 0.00393 | J49: 0.00405 | K49: 0.00418 | L49: 0.00434 | M49: 0.00454 | N49: 0.00477 | O49: 0.00503 | P49: 0.00535 | Q49: 0.00571 | R49: 0.00612 | S49: 0.00658 | T49: 0.00709 | U49: 0.00766 | V49: 0.00828 | W49: 0.00896 | X49: 0.00969 | Y49: 0.01048 | Z49: 0.01134 | AA49: 0.01228 | AB49: 0.01331 | AC49: 0.01445 | AD49: 0.01572 | AE49: 0.01715 | AF49: 0.01877 | AG49: 0.0206 | AH49: 0.02268 | AI49: 0.02503 | AJ49: 0.02768 | AK49: 0.03067 | AL49: 0.03403 | AM49: 0.03782 | AN49: 0.04212 | AO49: 0.04701 | AP49: 0.0526 | AQ49: 0.05905 | AR49: 0.06652
A50: 9 | B50: 0.00377 | C50: 0.00387 | D50: 0.00396 | E50: 0.00406 | F50: 0.00415 | G50: 0.00425 | H50: 0.00436 | I50: 0.00449 | J50: 0.00463 | K50: 0.0048 | L50: 0.00499 | M50: 0.00523 | N50: 0.0055 | O50: 0.00582 | P50: 0.00619 | Q50: 0.00662 | R50: 0.0071 | S50: 0.00764 | T50: 0.00824 | U50: 0.0089 | V50: 0.00963 | W50: 0.01041 | X50: 0.01127 | Y50: 0.01219 | Z50: 0.0132 | AA50: 0.0143 | AB50: 0.01551 | AC50: 0.01686 | AD50: 0.01837 | AE50: 0.02006 | AF50: 0.02198 | AG50: 0.02415 | AH50: 0.0266 | AI50: 0.02938 | AJ50: 0.0325 | AK50: 0.03603 | AL50: 0.04001 | AM50: 0.0445 | AN50: 0.0496 | AO50: 0.05542 | AP50: 0.0621 | AQ50: 0.0698 | AR50: 0
A51: 10 | B51: 0.00423 | C51: 0.00434 | D51: 0.00445 | E51: 0.00456 | F51: 0.00467 | G51: 0.00479 | H51: 0.00492 | I51: 0.00507 | J51: 0.00524 | K51: 0.00544 | L51: 0.00568 | M51: 0.00595 | N51: 0.00628 | O51: 0.00666 | P51: 0.00709 | Q51: 0.00759 | R51: 0.00815 | S51: 0.00878 | T51: 0.00947 | U51: 0.01023 | V51: 0.01106 | W51: 0.01196 | X51: 0.01295 | Y51: 0.01401 | Z51: 0.01518 | AA51: 0.01646 | AB51: 0.01788 | AC51: 0.01945 | AD51: 0.02122 | AE51: 0.0232 | AF51: 0.02545 | AG51: 0.02798 | AH51: 0.03085 | AI51: 0.03409 | AJ51: 0.03774 | AK51: 0.04186 | AL51: 0.04652 | AM51: 0.05179 | AN51: 0.05779 | AO51: 0.06465 | AP51: 0.07253 | AQ51: 0 | AR51: 0
A52: 11 | B52: 0.00471 | C52: 0.00483 | D52: 0.00496 | E52: 0.00508 | F52: 0.00521 | G52: 0.00535 | H52: 0.0055 | I52: 0.00567 | J52: 0.00588 | K52: 0.00612 | L52: 0.00639 | M52: 0.00672 | N52: 0.0071 | O52: 0.00755 | P52: 0.00805 | Q52: 0.00863 | R52: 0.00927 | S52: 0.00999 | T52: 0.01078 | U52: 0.01164 | V52: 0.01259 | W52: 0.01362 | X52: 0.01474 | Y52: 0.01596 | Z52: 0.0173 | AA52: 0.01878 | AB52: 0.02042 | AC52: 0.02225 | AD52: 0.02429 | AE52: 0.0266 | AF52: 0.0292 | AG52: 0.03214 | AH52: 0.03545 | AI52: 0.0392 | AJ52: 0.04343 | AK52: 0.04821 | AL52: 0.05361 | AM52: 0.05976 | AN52: 0.06676 | AO52: 0.07478 | AP52: 0 | AQ52: 0 | AR52: 0
A53: 12 | B53: 0.0052 | C53: 0.00534 | D53: 0.00547 | E53: 0.00561 | F53: 0.00576 | G53: 0.00592 | H53: 0.0061 | I53: 0.00631 | J53: 0.00655 | K53: 0.00683 | L53: 0.00716 | M53: 0.00754 | N53: 0.00798 | O53: 0.00849 | P53: 0.00907 | Q53: 0.00973 | R53: 0.01046 | S53: 0.01127 | T53: 0.01216 | U53: 0.01314 | V53: 0.01421 | W53: 0.01538 | X53: 0.01665 | Y53: 0.01805 | Z53: 0.01958 | AA53: 0.02128 | AB53: 0.02316 | AC53: 0.02526 | AD53: 0.02762 | AE53: 0.03027 | AF53: 0.03326 | AG53: 0.03664 | AH53: 0.04045 | AI53: 0.04475 | AJ53: 0.04962 | AK53: 0.05513 | AL53: 0.06138 | AM53: 0.06849 | AN53: 0.07661 | AO53: 0 | AP53: 0 | AQ53: 0 | AR53: 0
... A71: 30 | B71: 0.01785 | C71: 0.01874 | D71: 0.01971 | E71: 0.02079 | F71: 0.02199 | G71: 0.02331 | H71: 0.02479 | I71: 0.02644 | J71: 0.02828 | K71: 0.03034 | L71: 0.03264 | M71: 0.03522 | N71: 0.03809 | O71: 0.04131 | P71: 0.0449 | Q71: 0.0489 | R71: 0.05338 | S71: 0.05838 | T71: 0.06397 | U71: 0.07024 | V71: 0.07727 | W71: 0 | X71: 0 | Y71: 0 | Z71: 0 | AA71: 0 | AB71: 0 | AC71: 0 | AD71: 0 | AE71: 0 | AF71: 0 | AG71: 0 | AH71: 0 | AI71: 0 | AJ71: 0 | AK71: 0 | AL71: 0 | AM71: 0 | AN71: 0 | AO71: 0 | AP71: 0 | AQ71: 0 | AR71: 0
A72: 31
A73: M | B73: อัตราเบี้ยประกันอุบัติเหตุแบบเงินสดและกู้เบี้ยแบบรายปี สำหรับ ML88 (มอร์เกจ โพรเทคชั่น)
B74: เพศชาย ต่อทุนประกัน 1,000 บาท
A75: ปี
B76: 20 | C76: 21 | D76: 22 | E76: 23 | F76: 24 | G76: 25 | H76: 26 | I76: 27 | J76: 28 | K76: 29 | L76: 30 | M76: 31 | N76: 32 | O76: 33 | P76: 34 | Q76: 35 | R76: 36 | S76: 37 | T76: 38 | U76: 39 | V76: 40 | W76: 41 | X76: 42 | Y76: 43 | Z76: 44 | AA76: 45 | AB76: 46 | AC76: 47 | AD76: 48 | AE76: 49 | AF76: 50 | AG76: 51 | AH76: 52 | AI76: 53 | AJ76: 54 | AK76: 55 | AL76: 56 | AM76: 57 | AN76: 58 | AO76: 59 | AP76: 60 | AQ76: 61 | AR76: 62
A77: 1
A78: 2
A79: 3
A80: 4
A81: 5
A82: 6
A83: 7
A84: 8
A85: 9
A86: 10
A87: 11
A88: 12
... A107: 31
A108: F | B108: อัตราเบี้ยประกันอุบัติเหตุแบบเงินสดและกู้เบี้ยแบบรายปี สำหรับ ML88 (มอร์เกจ โพรเทคชั่น)
B109: เพศหญิง ต่อทุนประกัน 1,000 บาท
A110: ปี
B111: 20 | C111: 21 | D111: 22 | E111: 23 | F111: 24 | G111: 25 | H111: 26 | I111: 27 | J111: 28 | K111: 29 | L111: 30 | M111: 31 | N111: 32 | O111: 33 | P111: 34 | Q111: 35 | R111: 36 | S111: 37 | T111: 38 | U111: 39 | V111: 40 | W111: 41 | X111: 42 | Y111: 43 | Z111: 44 | AA111: 45 | AB111: 46 | AC111: 47 | AD111: 48 | AE111: 49 | AF111: 50 | AG111: 51 | AH111: 52 | AI111: 53 | AJ111: 54 | AK111: 55 | AL111: 56 | AM111: 57 | AN111: 58 | AO111: 59 | AP111: 60 | AQ111: 61 | AR111: 62
A112: 1
A113: 2
A114: 3
A115: 4
A116: 5
A117: 6
A118: 7
A119: 8
A120: 9
A121: 10
A122: 11
A123: 12
... A142: 31
A143: M | B143: อัตราเบี้ยชีวิตแบบเงินสดและกู้เบี้ยแบบรายปี สำหรับ ML88 (มอร์เกจ โพรเทคชั่น)
B144: เพศชาย ต่อทุนประกัน 1,000 บาท
A145: ปี | B145: อายุผู้เอาประกันภัย (ปี)
B146: 20 | C146: 21 | D146: 22 | E146: 23 | F146: 24 | G146: 25 | H146: 26 | I146: 27 | J146: 28 | K146: 29 | L146: 30 | M146: 31 | N146: 32 | O146: 33 | P146: 34 | Q146: 35 | R146: 36 | S146: 37 | T146: 38 | U146: 39 | V146: 40 | W146: 41 | X146: 42 | Y146: 43 | Z146: 44 | AA146: 45 | AB146: 46 | AC146: 47 | AD146: 48 | AE146: 49 | AF146: 50 | AG146: 51 | AH146: 52 | AI146: 53 | AJ146: 54 | AK146: 55 | AL146: 56 | AM146: 57 | AN146: 58 | AO146: 59 | AP146: 60 | AQ146: 61 | AR146: 62
A147: 1 | B147: 1.35 | C147: 1.4 | D147: 1.44 | E147: 1.47 | F147: 1.5 | G147: 1.51 | H147: 1.53 | I147: 1.55 | J147: 1.57 | K147: 1.59 | L147: 1.63 | M147: 1.69 | N147: 1.76 | O147: 1.83 | P147: 1.91 | Q147: 2.03 | R147: 2.13 | S147: 2.24 | T147: 2.36 | U147: 2.5 | V147: 2.63 | W147: 2.79 | X147: 2.97 | Y147: 3.16 | Z147: 3.37 | AA147: 3.61 | AB147: 3.86 | AC147: 4.15 | AD147: 4.46 | AE147: 4.8 | AF147: 5.17 | AG147: 5.56 | AH147: 5.98 | AI147: 6.43 | AJ147: 6.94 | AK147: 7.49 | AL147: 8.11 | AM147: 8.8 | AN147: 9.59 | AO147: 10.48 | AP147: 11.5 | AQ147: 12.65 | AR147: 13.96
A148: 2 | B148: 2.67 | C148: 2.77 | D148: 2.84 | E148: 2.9 | F148: 2.94 | G148: 2.97 | H148: 3 | I148: 3.03 | J148: 3.09 | K148: 3.15 | L148: 3.23 | M148: 3.35 | N148: 3.49 | O148: 3.64 | P148: 3.82 | Q148: 4.01 | R148: 4.22 | S148: 4.45 | T148: 4.7 | U148: 4.96 | V148: 5.25 | W148: 5.57 | X148: 5.91 | Y148: 6.3 | Z148: 6.73 | AA148: 7.21 | AB148: 7.73 | AC148: 8.3 | AD148: 8.93 | AE148: 9.61 | AF148: 10.35 | AG148: 11.14 | AH148: 12 | AI148: 12.93 | AJ148: 13.94 | AK148: 15.08 | AL148: 16.34 | AM148: 17.76 | AN148: 19.37 | AO148: 21.21 | AP148: 23.3 | AQ148: 25.68 | AR148: 28.37
A149: 3 | B149: 4.05 | C149: 4.18 | D149: 4.29 | E149: 4.37 | F149: 4.43 | G149: 4.48 | H149: 4.52 | I149: 4.58 | J149: 4.66 | K149: 4.77 | L149: 4.9 | M149: 5.08 | N149: 5.3 | O149: 5.54 | P149: 5.81 | Q149: 6.11 | R149: 6.43 | S149: 6.78 | T149: 7.17 | U149: 7.57 | V149: 8.02 | W149: 8.5 | X149: 9.06 | Y149: 9.66 | Z149: 10.33 | AA149: 11.07 | AB149: 11.88 | AC149: 12.77 | AD149: 13.75 | AE149: 14.79 | AF149: 15.93 | AG149: 17.16 | AH149: 18.48 | AI149: 19.93 | AJ149: 21.53 | AK149: 23.3 | AL149: 25.29 | AM149: 27.54 | AN149: 30.1 | AO149: 33.02 | AP149: 36.35 | AQ149: 40.13 | AR149: 44.43
A150: 4 | B150: 4.63 | C150: 4.77 | D150: 4.88 | E150: 4.96 | F150: 5.03 | G150: 5.08 | H150: 5.14 | I150: 5.22 | J150: 5.32 | K150: 5.45 | L150: 5.62 | M150: 5.83 | N150: 6.09 | O150: 6.37 | P150: 6.7 | Q150: 7.04 | R150: 7.41 | S150: 7.82 | T150: 8.26 | U150: 8.74 | V150: 9.26 | W150: 9.84 | X150: 10.48 | Y150: 11.18 | Z150: 11.97 | AA150: 12.83 | AB150: 13.78 | AC150: 14.83 | AD150: 15.95 | AE150: 17.17 | AF150: 18.49 | AG150: 19.92 | AH150: 21.48 | AI150: 23.17 | AJ150: 25.04 | AK150: 27.13 | AL150: 29.49 | AM150: 32.16 | AN150: 35.19 | AO150: 38.65 | AP150: 42.59 | AQ150: 47.07 | AR150: 0
A151: 5 | B151: 5.88 | C151: 6.04 | D151: 6.17 | E151: 6.26 | F151: 6.34 | G151: 6.41 | H151: 6.5 | I151: 6.61 | J151: 6.75 | K151: 6.93 | L151: 7.17 | M151: 7.44 | N151: 7.78 | O151: 8.16 | P151: 8.57 | Q151: 9.02 | R151: 9.5 | S151: 10.03 | T151: 10.6 | U151: 11.22 | V151: 11.91 | W151: 12.66 | X151: 13.5 | Y151: 14.42 | Z151: 15.44 | AA151: 16.57 | AB151: 17.81 | AC151: 19.15 | AD151: 20.63 | AE151: 22.21 | AF151: 23.93 | AG151: 25.78 | AH151: 27.81 | AI151: 30.04 | AJ151: 32.51 | AK151: 35.29 | AL151: 38.42 | AM151: 41.97 | AN151: 46.02 | AO151: 50.63 | AP151: 55.88 | AQ151: 0 | AR151: 0
A152: 6 | B152: 7.15 | C152: 7.34 | D152: 7.48 | E152: 7.59 | F152: 7.69 | G152: 7.78 | H152: 7.9 | I152: 8.03 | J152: 8.23 | K152: 8.48 | L152: 8.78 | M152: 9.14 | N152: 9.56 | O152: 10.03 | P152: 10.54 | Q152: 11.1 | R152: 11.7 | S152: 12.37 | T152: 13.08 | U152: 13.86 | V152: 14.71 | W152: 15.67 | X152: 16.71 | Y152: 17.88 | Z152: 19.17 | AA152: 20.57 | AB152: 22.12 | AC152: 23.81 | AD152: 25.63 | AE152: 27.62 | AF152: 29.77 | AG152: 32.1 | AH152: 34.66 | AI152: 37.49 | AJ152: 40.63 | AK152: 44.17 | AL152: 48.17 | AM152: 52.73 | AN152: 57.92 | AO152: 63.83 | AP152: 0 | AQ152: 0 | AR152: 0
A153: 7 | B153: 7.84 | C153: 8.03 | D153: 8.18 | E153: 8.3 | F153: 8.42 | G153: 8.54 | H153: 8.67 | I153: 8.85 | J153: 9.08 | K153: 9.37 | L153: 9.71 | M153: 10.13 | N153: 10.61 | O153: 11.13 | P153: 11.7 | Q153: 12.34 | R153: 13.02 | S153: 13.77 | T153: 14.57 | U153: 15.45 | V153: 16.43 | W153: 17.5 | X153: 18.69 | Y153: 20.01 | Z153: 21.45 | AA153: 23.03 | AB153: 24.78 | AC153: 26.67 | AD153: 28.73 | AE153: 30.96 | AF153: 33.38 | AG153: 36.03 | AH153: 38.93 | AI153: 42.15 | AJ153: 45.75 | AK153: 49.8 | AL153: 54.39 | AM153: 59.63 | AN153: 65.58 | AO153: 0 | AP153: 0 | AQ153: 0 | AR153: 0
A154: 8 | B154: 9.09 | C154: 9.29 | D154: 9.46 | E154: 9.6 | F154: 9.73 | G154: 9.89 | H154: 10.06 | I154: 10.3 | J154: 10.58 | K154: 10.94 | L154: 11.37 | M154: 11.86 | N154: 12.43 | O154: 13.05 | P154: 13.75 | Q154: 14.49 | R154: 15.3 | S154: 16.18 | T154: 17.15 | U154: 18.21 | V154: 19.38 | W154: 20.67 | X154: 22.1 | Y154: 23.66 | Z154: 25.4 | AA154: 27.3 | AB154: 29.36 | AC154: 31.62 | AD154: 34.07 | AE154: 36.73 | AF154: 39.63 | AG154: 42.81 | AH154: 46.32 | AI154: 50.23 | AJ154: 54.61 | AK154: 59.56 | AL154: 65.18 | AM154: 71.57 | AN154: 0 | AO154: 0 | AP154: 0 | AQ154: 0 | AR154: 0
A155: 9 | B155: 10.35 | C155: 10.57 | D155: 10.76 | E155: 10.93 | F155: 11.1 | G155: 11.29 | H155: 11.51 | I155: 11.8 | J155: 12.16 | K155: 12.59 | L155: 13.1 | M155: 13.68 | N155: 14.35 | O155: 15.09 | P155: 15.89 | Q155: 16.76 | R155: 17.72 | S155: 18.76 | T155: 19.9 | U155: 21.15 | V155: 22.52 | W155: 24.04 | X155: 25.73 | Y155: 27.57 | Z155: 29.61 | AA155: 31.83 | AB155: 34.26 | AC155: 36.91 | AD155: 39.79 | AE155: 42.93 | AF155: 46.37 | AG155: 50.16 | AH155: 54.35 | AI155: 59.02 | AJ155: 64.29 | AK155: 70.24 | AL155: 77.02 | AM155: 0 | AN155: 0 | AO155: 0 | AP155: 0 | AQ155: 0 | AR155: 0
A156: 10 | B156: 11.64 | C156: 11.88 | D156: 12.1 | E156: 12.3 | F156: 12.5 | G156: 12.74 | H156: 13.02 | I156: 13.37 | J156: 13.8 | K156: 14.31 | L156: 14.91 | M156: 15.6 | N156: 16.37 | O156: 17.21 | P156: 18.15 | Q156: 19.17 | R156: 20.27 | S156: 21.49 | T156: 22.82 | U156: 24.28 | V156: 25.89 | W156: 27.66 | X156: 29.61 | Y156: 31.77 | Z156: 34.12 | AA156: 36.7 | AB156: 39.53 | AC156: 42.6 | AD156: 45.96 | AE156: 49.63 | AF156: 53.66 | AG156: 58.11 | AH156: 63.05 | AI156: 68.61 | AJ156: 74.86 | AK156: 81.97 | AL156: 0 | AM156: 0 | AN156: 0 | AO156: 0 | AP156: 0 | AQ156: 0 | AR156: 0
A157: 11 | B157: 12.96 | C157: 13.23 | D157: 13.47 | E157: 13.7 | F157: 13.96 | G157: 14.24 | H157: 14.6 | I157: 15.01 | J157: 15.52 | K157: 16.12 | L157: 16.82 | M157: 17.61 | N157: 18.49 | O157: 19.47 | P157: 20.53 | Q157: 21.71 | R157: 22.98 | S157: 24.39 | T157: 25.91 | U157: 27.61 | V157: 29.46 | W157: 31.51 | X157: 33.77 | Y157: 36.24 | Z157: 38.96 | AA157: 41.92 | AB157: 45.17 | AC157: 48.7 | AD157: 52.59 | AE157: 56.84 | AF157: 61.54 | AG157: 66.74 | AH157: 72.56 | AI157: 79.08 | AJ157: 86.46 | AK157: 0 | AL157: 0 | AM157: 0 | AN157: 0 | AO157: 0 | AP157: 0 | AQ157: 0 | AR157: 0
A158: 12 | B158: 14.3 | C158: 14.61 | D158: 14.89 | E158: 15.17 | F158: 15.47 | G158: 15.83 | H158: 16.23 | I158: 16.73 | J158: 17.32 | K158: 18.02 | L158: 18.82 | M158: 19.72 | N158: 20.72 | O158: 21.84 | P158: 23.07 | Q158: 24.41 | R158: 25.86 | S158: 27.47 | T158: 29.22 | U158: 31.16 | V158: 33.29 | W158: 35.63 | X158: 38.2 | Y158: 41.03 | Z158: 44.12 | AA158: 47.5 | AB158: 51.22 | AC158: 55.28 | AD158: 59.74 | AE158: 64.64 | AF158: 70.09 | AG158: 76.14 | AH158: 82.91 | AI158: 90.55 | AJ158: 0 | AK158: 0 | AL158: 0 | AM158: 0 | AN158: 0 | AO158: 0 | AP158: 0 | AQ158: 0 | AR158: 0
... A176: 30 | B176: 48.67 | C176: 50.73 | D176: 52.97 | E176: 55.4 | F176: 58.09 | G176: 61.08 | H176: 64.41 | I176: 68.1 | J176: 72.23 | K176: 76.81 | L176: 81.88 | M176: 87.51 | N176: 93.76 | O176: 100.67 | P176: 108.33 | Q176: 116.85 | R176: 0 | S176: 0 | T176: 0 | U176: 0 | V176: 0 | W176: 0 | X176: 0 | Y176: 0 | Z176: 0 | AA176: 0 | AB176: 0 | AC176: 0 | AD176: 0 | AE176: 0 | AF176: 0 | AG176: 0 | AH176: 0 | AI176: 0 | AJ176: 0 | AK176: 0 | AL176: 0 | AM176: 0 | AN176: 0 | AO176: 0 | AP176: 0 | AQ176: 0 | AR176: 0
A177: 31
A178: F | B178: อัตราเบี้ยชีวิตแบบเงินสดและกู้เบี้ยแบบรายปี สำหรับ ML88 (มอร์เกจ โพรเทคชั่น)
B179: เพศหญิง ต่อทุนประกัน 1,000 บาท
A180: ปี | B180: อายุผู้เอาประกันภัย (ปี)
B181: 20 | C181: 21 | D181: 22 | E181: 23 | F181: 24 | G181: 25 | H181: 26 | I181: 27 | J181: 28 | K181: 29 | L181: 30 | M181: 31 | N181: 32 | O181: 33 | P181: 34 | Q181: 35 | R181: 36 | S181: 37 | T181: 38 | U181: 39 | V181: 40 | W181: 41 | X181: 42 | Y181: 43 | Z181: 44 | AA181: 45 | AB181: 46 | AC181: 47 | AD181: 48 | AE181: 49 | AF181: 50 | AG181: 51 | AH181: 52 | AI181: 53 | AJ181: 54 | AK181: 55 | AL181: 56 | AM181: 57 | AN181: 58 | AO181: 59 | AP181: 60 | AQ181: 61 | AR181: 62
A182: 1 | B182: 0.48 | C182: 0.5 | D182: 0.51 | E182: 0.52 | F182: 0.54 | G182: 0.55 | H182: 0.57 | I182: 0.57 | J182: 0.59 | K182: 0.6 | L182: 0.62 | M182: 0.63 | N182: 0.66 | O182: 0.69 | P182: 0.72 | Q182: 0.76 | R182: 0.81 | S182: 0.86 | T182: 0.92 | U182: 0.99 | V182: 1.07 | W182: 1.16 | X182: 1.25 | Y182: 1.35 | Z182: 1.46 | AA182: 1.58 | AB182: 1.71 | AC182: 1.85 | AD182: 2.02 | AE182: 2.18 | AF182: 2.37 | AG182: 2.57 | AH182: 2.82 | AI182: 3.09 | AJ182: 3.41 | AK182: 3.76 | AL182: 4.16 | AM182: 4.62 | AN182: 5.12 | AO182: 5.7 | AP182: 6.35 | AQ182: 7.09 | AR182: 7.92
A183: 2 | B183: 0.95 | C183: 0.98 | D183: 1.01 | E183: 1.03 | F183: 1.06 | G183: 1.09 | H183: 1.11 | I183: 1.13 | J183: 1.16 | K183: 1.19 | L183: 1.22 | M183: 1.26 | N183: 1.3 | O183: 1.37 | P183: 1.43 | Q183: 1.5 | R183: 1.6 | S183: 1.71 | T183: 1.83 | U183: 1.98 | V183: 2.14 | W183: 2.31 | X183: 2.5 | Y183: 2.71 | Z183: 2.93 | AA183: 3.17 | AB183: 3.44 | AC183: 3.72 | AD183: 4.03 | AE183: 4.37 | AF183: 4.75 | AG183: 5.17 | AH183: 5.66 | AI183: 6.22 | AJ183: 6.85 | AK183: 7.58 | AL183: 8.4 | AM183: 9.32 | AN183: 10.37 | AO183: 11.54 | AP183: 12.87 | AQ183: 14.38 | AR183: 16.12
